Workbook

Sheet DCF Cover - Base
C2: CRWV | Power-driven DCF (IT-load GW x revenue per GW)
C3: US$ millions, except power (MW), revenue/GW, build cost/GW and D&A/GW (US$ billions per GW) and shares (millions). Horizon CY2023–2045; fiscal year = calendar year.
C4: Blue / yellow: assumptions (Assumptions & sources sheet; salmon = no source). Green: internal sources. CY23–25A: reported bases (10-K). 2026: company guide.
D5: CY23A | E5: CY24A | F5: CY25A | G5: CY26E | H5: CY27E | I5: CY28E | J5: CY29E | K5: CY30E | L5: CY31E | M5: CY32E | N5: CY33E | O5: CY34E | P5: CY35E | Q5: CY36E | R5: CY37E | S5: CY38E | T5: CY39E | U5: CY40E | V5: CY41E | W5: CY42E | X5: CY43E | Y5: CY44E | Z5: CY45E
C6: Grid inputs: D6 revenue/GW multiplier 2027+ (1.00 = base) | E6 EBITDA-margin adjustment 2027+ (pp) | F6 replacement life (years) | G6 replacement cost (% of build) | D6: 1 | E6: 0 | F6: 6 | G6: 0.8
C7: Capacity | active power (critical IT load, MW) and billable power
C8: Active power at year-end (MW) | D8: ='Assumptions & sources'!D18 -> 70 | E8: ='Assumptions & sources'!E18 -> 360 | F8: ='Assumptions & sources'!F18 -> 850 | G8: =F8+G9 -> 1900 | H8: =G8+H9 -> 3200 | I8: =H8+I9 -> 4700 | J8: =I8+J9 -> 6300 | K8: =J8+K9 -> 8000 | L8: =K8+L9 -> 9400 | M8: =L8+M9 -> 10600 | N8: =M8+N9 -> 11600 | ... Z8: =Y8+Z9 -> 17874.088
C9: Active power added in the year (MW) | D9: =D8 -> 70 | E9: =E8-D8 -> 290 | F9: =F8-E8 -> 490 | G9: ='Assumptions & sources'!G75 -> 1050 | H9: ='Assumptions & sources'!H75 -> 1300 | I9: ='Assumptions & sources'!I75 -> 1500 | J9: ='Assumptions & sources'!J75 -> 1600 | K9: ='Assumptions & sources'!K75 -> 1700 | L9: ='Assumptions & sources'!L75 -> 1400 | M9: ='Assumptions & sources'!M75 -> 1200 | N9: ='Assumptions & sources'!N75 -> 1000 | ... P9: ='Assumptions & sources'!P75 -> 800 | Q9: =P8*'Assumptions & sources'!$D$71 -> 399 | R9: =Q8*'Assumptions & sources'!$D$71 -> 410.97 | S9: =R8*'Assumptions & sources'!$D$71 -> 423.2991 | T9: =S8*'Assumptions & sources'!$D$71 -> 435.99807 | U9: =T8*'Assumptions & sources'!$D$71 -> 449.07802 | V9: =U8*'Assumptions & sources'!$D$71 -> 462.55036 | W9: =V8*'Assumptions & sources'!$D$71 -> 476.42687 | X9: =W8*'Assumptions & sources'!$D$71 -> 490.71967 | ... Z9: =Y8*'Assumptions & sources'!$D$71 -> 520.6045
C10: Average active power in the year (MW) — D&A basis | E10: =(D8+E8)/2 -> 215 | F10: =(E8+F8)/2 -> 605 | G10: =(F8+G8)/2 -> 1375 | H10: =(G8+H8)/2 -> 2550 | I10: =(H8+I8)/2 -> 3950 | J10: =(I8+J8)/2 -> 5500 | K10: =(J8+K8)/2 -> 7150 | L10: =(K8+L8)/2 -> 8700 | ... Z10: =(Y8+Z8)/2 -> 17613.786
C11: Average billable power (MW) = prior YE + (0.5 − lag) x adds | 2026: quarterly build | E11: =D8+(0.5-'Assumptions & sources'!$D$67)*E9 -> 142.5 | F11: =E8+(0.5-'Assumptions & sources'!$D$67)*F9 -> 482.5 | G11: ='Assumptions & sources'!$D$38 -> 1124 | H11: =G8+(0.5-'Assumptions & sources'!$D$67)*H9 -> 2225 | I11: =H8+(0.5-'Assumptions & sources'!$D$67)*I9 -> 3575 | J11: =I8+(0.5-'Assumptions & sources'!$D$67)*J9 -> 5100 | K11: =J8+(0.5-'Assumptions & sources'!$D$67)*K9 -> 6725 | L11: =K8+(0.5-'Assumptions & sources'!$D$67)*L9 -> 8350 | M11: =L8+(0.5-'Assumptions & sources'!$D$67)*M9 -> 9700 | N11: =M8+(0.5-'Assumptions & sources'!$D$67)*N9 -> 10850 | O11: =N8+(0.5-'Assumptions & sources'!$D$67)*O9 -> 11825 | ... Z11: =Y8+(0.5-'Assumptions & sources'!$D$67)*Z9 -> 17483.634
C12: Revenue per billable GW (US$ bn / GW-year) | CY24-26 implied | E12: =E15/E11 -> 13.438596 | F12: =F15/F11 -> 10.634197 | G12: =G15/G11 -> 11.3879 | H12: ='Assumptions & sources'!H76*$D$6 -> 12 | I12: ='Assumptions & sources'!I76*$D$6 -> 12.5 | J12: ='Assumptions & sources'!J76*$D$6 -> 12.8 | K12: ='Assumptions & sources'!K76*$D$6 -> 13 | L12: ='Assumptions & sources'!L76*$D$6 -> 13.3 | M12: ='Assumptions & sources'!M76*$D$6 -> 13.7 | N12: ='Assumptions & sources'!N76*$D$6 -> 14 | O12: ='Assumptions & sources'!O76*$D$6 -> 14 | ... Z12: ='Assumptions & sources'!Z76*$D$6 -> 14
C13: Memo: revenue per average ACTIVE GW (US$ bn / GW-year) — alternative, lower basis | E13: =E15/E10 -> 8.9069767 | F13: =F15/F10 -> 8.4809917 | G13: =G15/G10 -> 9.3090909 | H13: =H15/H10 -> 10.470588 | I13: =I15/I10 -> 11.313291 | J13: =J15/J10 -> 11.869091 | K13: =K15/K10 -> 12.227273 | L13: =L15/L10 -> 12.764943 | ... Z13: =Z15/Z10 -> 13.896552
C14: Revenue (US$ millions)
C15: Scenario revenue | D15: ='Assumptions & sources'!D9 -> 229 | E15: ='Assumptions & sources'!E9 -> 1915 | F15: ='Assumptions & sources'!F9 -> 5131 | G15: =('Assumptions & sources'!$D$28+'Assumptions & sources'!$D$29)/2 -> 12800 | H15: =H11*H12 -> 26700 | I15: =I11*I12 -> 44687.5 | J15: =J11*J12 -> 65280 | K15: =K11*K12 -> 87425 | L15: =L11*L12 -> 111055 | M15: =M11*M12 -> 132890 | N15: =N11*N12 -> 151900 | O15: =O11*O12 -> 165550 | ... Z15: =Z11*Z12 -> 244770.88
C16: Revenue growth | E16: =E15/D15-1 -> 7.3624454 | F16: =F15/E15-1 -> 1.6793734 | G16: =G15/F15-1 -> 1.4946404 | H16: =H15/G15-1 -> 1.0859375 | I16: =I15/H15-1 -> 0.67368914 | J16: =J15/I15-1 -> 0.46081119 | K16: =K15/J15-1 -> 0.339231 | L16: =L15/K15-1 -> 0.27028882 | ... Z16: =Z15/Y15-1 -> 0.03
C17: Revenue | BBG consensus CY26-28 (memo) | G17: ='Assumptions & sources'!G9 -> 12770.37 | H17: ='Assumptions & sources'!H9 -> 26439.52 | I17: ='Assumptions & sources'!I9 -> 42212.08
C18: Scenario ÷ consensus − 1 | G18: =G15/G17-1 -> 0.0023202147 | H18: =H15/H17-1 -> 0.0098519186 | I18: =I15/I17-1 -> 0.058642455
C19: Memo: 2030 revenue — UBS $84.8bn / Street ~$80bn (UBS 09-22) vs scenario | K19: =K15/84800-1 -> 0.030955189
C21: Operating result and cash (company adjusted basis; SBC deducted below)
C22: Adjusted EBITDA margin | E22: ='Assumptions & sources'!E10/E15 -> 0.64020888 | F22: ='Assumptions & sources'!F10/F15 -> 0.60378094 | G22: ='Assumptions & sources'!G77 -> 0.575 | H22: ='Assumptions & sources'!H77+$E$6 -> 0.62 | I22: ='Assumptions & sources'!I77+$E$6 -> 0.64 | J22: ='Assumptions & sources'!J77+$E$6 -> 0.64 | K22: ='Assumptions & sources'!K77+$E$6 -> 0.63 | L22: ='Assumptions & sources'!L77+$E$6 -> 0.62 | M22: ='Assumptions & sources'!M77+$E$6 -> 0.62 | N22: ='Assumptions & sources'!N77+$E$6 -> 0.62 | O22: ='Assumptions & sources'!O77+$E$6 -> 0.62 | ... Z22: ='Assumptions & sources'!Z77+$E$6 -> 0.62
C23: Adjusted EBITDA | E23: =E15*E22 -> 1226 | F23: =F15*F22 -> 3098 | G23: =G15*G22 -> 7360 | H23: =H15*H22 -> 16554 | I23: =I15*I22 -> 28600 | J23: =J15*J22 -> 41779.2 | K23: =K15*K22 -> 55077.75 | L23: =L15*L22 -> 68854.1 | ... Z23: =Z15*Z22 -> 151757.95
C24: EBITDA | BBG consensus (memo) | G24: ='Assumptions & sources'!G10 -> 7482.66 | H24: ='Assumptions & sources'!H10 -> 16630.37 | I24: ='Assumptions & sources'!I10 -> 27896.76
C25: D&A per average active GW (US$ bn / GW-year) | CY24-25 implied | E25: =E26/E10 -> 4.0139535 | F25: =F26/F10 -> 4.0561983 | G25: ='Assumptions & sources'!G78 -> 4.6 | H25: ='Assumptions & sources'!H78 -> 4.8 | I25: ='Assumptions & sources'!I78 -> 5 | J25: ='Assumptions & sources'!J78 -> 5 | K25: ='Assumptions & sources'!K78 -> 5 | L25: ='Assumptions & sources'!L78 -> 5 | M25: ='Assumptions & sources'!M78 -> 5 | N25: ='Assumptions & sources'!N78 -> 5 | ... Z25: ='Assumptions & sources'!Z78 -> 5
C26: Depreciation and amortization | D26: ='Assumptions & sources'!D14 -> 103 | E26: ='Assumptions & sources'!E14 -> 863 | F26: ='Assumptions & sources'!F14 -> 2454 | G26: =G10*G25 -> 6325 | H26: =H10*H25 -> 12240 | I26: =I10*I25 -> 19750 | J26: =J10*J25 -> 27500 | K26: =K10*K25 -> 35750 | L26: =L10*L25 -> 43500 | M26: =M10*M25 -> 50000 | N26: =N10*N25 -> 55500 | ... Z26: =Z10*Z25 -> 88068.928
C27: Adjusted operating income (AOI = EBITDA − D&A) | E27: =E23-E26 -> 363 | F27: =F23-F26 -> 644 | G27: =G23-G26 -> 1035 | H27: =H23-H26 -> 4314 | I27: =I23-I26 -> 8850 | J27: =J23-J26 -> 14279.2 | K27: =K23-K26 -> 19327.75 | L27: =L23-L26 -> 25354.1 | ... Z27: =Z23-Z26 -> 63689.019
C28: Adjusted operating margin | E28: =E27/E15 -> 0.18955614 | F28: =F27/F15 -> 0.1255116 | G28: =G27/G15 -> 0.080859375 | H28: =H27/H15 -> 0.16157303 | I28: =I27/I15 -> 0.19804196 | J28: =J27/J15 -> 0.21873775 | K28: =K27/K15 -> 0.22107807 | L28: =L27/L15 -> 0.22830219 | ... Z28: =Z27/Z15 -> 0.26019851
C29: AOI | BBG consensus EBIT (memo) / FY26 guide midpoint | G29: =('Assumptions & sources'!$D$30+'Assumptions & sources'!$D$31)/2 -> 1055 | H29: ='Assumptions & sources'!H11 -> 4113.1 | I29: ='Assumptions & sources'!I11 -> 7363.56
C30: Stock-based compensation | D30: =-'Assumptions & sources'!D15 -> -15 | E30: =-'Assumptions & sources'!E15 -> -31 | F30: =-'Assumptions & sources'!F15 -> -630 | G30: =-G15*'Assumptions & sources'!G79 -> -640 | H30: =-H15*'Assumptions & sources'!H79 -> -801 | I30: =-I15*'Assumptions & sources'!I79 -> -1117.1875 | J30: =-J15*'Assumptions & sources'!J79 -> -1305.6 | K30: =-K15*'Assumptions & sources'!K79 -> -1748.5 | L30: =-L15*'Assumptions & sources'!L79 -> -2221.1 | M30: =-M15*'Assumptions & sources'!M79 -> -2657.8 | N30: =-N15*'Assumptions & sources'!N79 -> -3038 | ... Z30: =-Z15*'Assumptions & sources'!Z79 -> -4895.4177
C31: EBIT after SBC | E31: =E27+E30 -> 332 | F31: =F27+F30 -> 14 | G31: =G27+G30 -> 395 | H31: =H27+H30 -> 3513 | I31: =I27+I30 -> 7732.8125 | J31: =J27+J30 -> 12973.6 | K31: =K27+K30 -> 17579.25 | L31: =L27+L30 -> 23133 | ... Z31: =Z27+Z30 -> 58793.602
C32: EBIT margin after SBC | E32: =E31/E15 -> 0.17336815 | F32: =F31/F15 -> 0.002728513 | G32: =G31/G15 -> 0.030859375 | H32: =H31/H15 -> 0.13157303 | I32: =I31/I15 -> 0.17304196 | J32: =J31/J15 -> 0.19873775 | K32: =K31/K15 -> 0.20107807 | L32: =L31/L15 -> 0.20830219 | ... Z32: =Z31/Z15 -> 0.24019851
C33: Cash tax rate | G33: ='Assumptions & sources'!G80 -> 0.05 | H33: ='Assumptions & sources'!H80 -> 0.05 | I33: ='Assumptions & sources'!I80 -> 0.05 | J33: ='Assumptions & sources'!J80 -> 0.1 | K33: ='Assumptions & sources'!K80 -> 0.15 | L33: ='Assumptions & sources'!L80 -> 0.21 | M33: ='Assumptions & sources'!M80 -> 0.21 | N33: ='Assumptions & sources'!N80 -> 0.21 | ... Z33: ='Assumptions & sources'!Z80 -> 0.21
C34: NOPAT | G34: =G31*(1-G33) -> 375.25 | H34: =H31*(1-H33) -> 3337.35 | I34: =I31*(1-I33) -> 7346.1719 | J34: =J31*(1-J33) -> 11676.24 | K34: =K31*(1-K33) -> 14942.362 | L34: =L31*(1-L33) -> 18275.07 | M34: =M31*(1-M33) -> 23489.86 | N34: =N31*(1-N33) -> 28155.6 | ... Z34: =Z31*(1-Z33) -> 46446.945
C35: Build cost per GW added (US$ bn / GW) | G35: ='Assumptions & sources'!G81 -> 33 | H35: ='Assumptions & sources'!H81 -> 38 | I35: ='Assumptions & sources'!I81 -> 40 | J35: ='Assumptions & sources'!J81 -> 40 | K35: ='Assumptions & sources'!K81 -> 40 | L35: ='Assumptions & sources'!L81 -> 40 | M35: ='Assumptions & sources'!M81 -> 40 | N35: ='Assumptions & sources'!N81 -> 40 | ... Z35: ='Assumptions & sources'!Z81 -> 40
C36: Growth capex = build x ((1 − pre-build) x adds t + pre-build x adds t+1) | G36: =-G35*((1-'Assumptions & sources'!$D$68)*G9+'Assumptions & sources'!$D$68*H9) -> -36300 | H36: =-H35*((1-'Assumptions & sources'!$D$68)*H9+'Assumptions & sources'!$D$68*I9) -> -50920 | I36: =-I35*((1-'Assumptions & sources'!$D$68)*I9+'Assumptions & sources'!$D$68*J9) -> -60800 | J36: =-J35*((1-'Assumptions & sources'!$D$68)*J9+'Assumptions & sources'!$D$68*K9) -> -64800 | K36: =-K35*((1-'Assumptions & sources'!$D$68)*K9+'Assumptions & sources'!$D$68*L9) -> -65600 | L36: =-L35*((1-'Assumptions & sources'!$D$68)*L9+'Assumptions & sources'!$D$68*M9) -> -54400 | M36: =-M35*((1-'Assumptions & sources'!$D$68)*M9+'Assumptions & sources'!$D$68*N9) -> -46400 | N36: =-N35*((1-'Assumptions & sources'!$D$68)*N9+'Assumptions & sources'!$D$68*O9) -> -39200 | ... Y36: =-Y35*((1-'Assumptions & sources'!$D$68)*Y9+'Assumptions & sources'!$D$68*Z9) -> -20338.956 | Z36: =-Z35*((1-'Assumptions & sources'!$D$68)*Z9+'Assumptions & sources'!$D$68*Z9) -> -20824.18
C37: Power replaced in the year (MW) = power installed in (t − life), adds and replacements included | D37: =IF(COLUMN(D9)-COLUMN($D$9)+1-$F$6>=1,INDEX($D$38:$Z$38,1,COLUMN(D9)-COLUMN($D$9)+1-$F$6),0) -> 0 | E37: =IF(COLUMN(E9)-COLUMN($D$9)+1-$F$6>=1,INDEX($D$38:$Z$38,1,COLUMN(E9)-COLUMN($D$9)+1-$F$6),0) -> 0 | F37: =IF(COLUMN(F9)-COLUMN($D$9)+1-$F$6>=1,INDEX($D$38:$Z$38,1,COLUMN(F9)-COLUMN($D$9)+1-$F$6),0) -> 0 | G37: =IF(COLUMN(G9)-COLUMN($D$9)+1-$F$6>=1,INDEX($D$38:$Z$38,1,COLUMN(G9)-COLUMN($D$9)+1-$F$6),0) -> 0 | H37: =IF(COLUMN(H9)-COLUMN($D$9)+1-$F$6>=1,INDEX($D$38:$Z$38,1,COLUMN(H9)-COLUMN($D$9)+1-$F$6),0) -> 0 | I37: =IF(COLUMN(I9)-COLUMN($D$9)+1-$F$6>=1,INDEX($D$38:$Z$38,1,COLUMN(I9)-COLUMN($D$9)+1-$F$6),0) -> 0 | J37: =IF(COLUMN(J9)-COLUMN($D$9)+1-$F$6>=1,INDEX($D$38:$Z$38,1,COLUMN(J9)-COLUMN($D$9)+1-$F$6),0) -> 70 | K37: =IF(COLUMN(K9)-COLUMN($D$9)+1-$F$6>=1,INDEX($D$38:$Z$38,1,COLUMN(K9)-COLUMN($D$9)+1-$F$6),0) -> 290 | ... Z37: =IF(COLUMN(Z9)-COLUMN($D$9)+1-$F$6>=1,INDEX($D$38:$Z$38,1,COLUMN(Z9)-COLUMN($D$9)+1-$F$6),0) -> 2735.9981
C38: Power installed in the year (MW) = adds + replacements | D38: =D9+D37 -> 70 | E38: =E9+E37 -> 290 | F38: =F9+F37 -> 490 | G38: =G9+G37 -> 1050 | H38: =H9+H37 -> 1300 | I38: =I9+I37 -> 1500 | J38: =J9+J37 -> 1670 | K38: =K9+K37 -> 1990 | ... Z38: =Z9+Z37 -> 3256.6026
C39: Replacement capex = power replaced x build x replacement % | G39: =-G37*G35*$G$6 -> 0 | H39: =-H37*H35*$G$6 -> 0 | I39: =-I37*I35*$G$6 -> 0 | J39: =-J37*J35*$G$6 -> -2240 | K39: =-K37*K35*$G$6 -> -9280 | L39: =-L37*L35*$G$6 -> -15680 | M39: =-M37*M35*$G$6 -> -33600 | N39: =-N37*N35*$G$6 -> -41600 | ... Z39: =-Z37*Z35*$G$6 -> -87551.938
C40: Total capex | CY23-25 reported cash; 2026 guide (midpoint) | D40: =-'Assumptions & sources'!D16 -> -2943 | E40: =-'Assumptions & sources'!E16 -> -8702 | F40: =-'Assumptions & sources'!F16 -> -10309 | G40: =-('Assumptions & sources'!$D$32+'Assumptions & sources'!$D$33)/2 -> -37000 | H40: =H36+H39 -> -50920 | I40: =I36+I39 -> -60800 | J40: =J36+J39 -> -67040 | K40: =K36+K39 -> -74880 | L40: =L36+L39 -> -70080 | M40: =M36+M39 -> -80000 | N40: =N36+N39 -> -80800 | O40: =O36+O39 -> -83200 | ... Z40: =Z36+Z39 -> -108376.12
C41: Capex | BBG consensus (memo) | G41: =-'Assumptions & sources'!G16 -> -35670.67 | H41: =-'Assumptions & sources'!H16 -> -47897.41 | I41: =-'Assumptions & sources'!I16 -> -50387.97
C42: Memo: 2026 capex by the formula (calibration check) | G42: =G36+G39 -> -36300
C43: Memo: total capex per GW INSTALLED in the year (adds + replacements; US$ bn / GW) — flow basis, includes pre-build | E43: =-E40/E38 -> 30.006897 | F43: =-F40/F38 -> 21.038776 | G43: =-G40/G38 -> 35.238095 | H43: =-H40/H38 -> 39.169231 | I43: =-I40/I38 -> 40.533333 | J43: =-J40/J38 -> 40.143713 | K43: =-K40/K38 -> 37.628141 | L43: =-L40/L38 -> 37.079365 | ... Z43: =-Z40/Z38 -> 33.27889
C44: Operating NWC (receivables − deferred revenue) | E44: ='Assumptions & sources'!E22-'Assumptions & sources'!E21 -> -3647 | F44: ='Assumptions & sources'!F22-'Assumptions & sources'!F21 -> -5016 | G44: =G15*'Assumptions & sources'!G82 -> -8960 | H44: =H15*'Assumptions & sources'!H82 -> -14685 | I44: =I15*'Assumptions & sources'!I82 -> -20109.375 | J44: =J15*'Assumptions & sources'!J82 -> -26112 | K44: =K15*'Assumptions & sources'!K82 -> -30598.75 | L44: =L15*'Assumptions & sources'!L82 -> -38869.25 | M44: =M15*'Assumptions & sources'!M82 -> -46511.5 | N44: =N15*'Assumptions & sources'!N82 -> -53165 | ... Z44: =Z15*'Assumptions & sources'!Z82 -> -85669.809
C45: Change in NWC | cash effect (customer prepayments) | F45: =-(F44-E44) -> 1369 | G45: =-(G44-F44) -> 3944 | H45: =-(H44-G44) -> 5725 | I45: =-(I44-H44) -> 5424.375 | J45: =-(J44-I44) -> 6002.625 | K45: =-(K44-J44) -> 4486.75 | L45: =-(L44-K44) -> 8270.5 | M45: =-(M44-L44) -> 7642.25 | ... Z45: =-(Z44-Y44) -> 2495.2372
C46: Free cash flow to the firm (FCFF) | G46: =G34+G26+G40+G45 -> -26355.75 | H46: =H34+H26+H40+H45 -> -29617.65 | I46: =I34+I26+I40+I45 -> -28279.453 | J46: =J34+J26+J40+J45 -> -21861.135 | K46: =K34+K26+K40+K45 -> -19700.888 | L46: =L34+L26+L40+L45 -> -34.43 | M46: =M34+M26+M40+M45 -> 1132.11 | N46: =N34+N26+N40+N45 -> 9509.1 | ... Z46: =Z34+Z26+Z40+Z45 -> 28634.992
C47: FCFF / revenue | G47: =G46/G15 -> -2.059043 | H47: =H46/H15 -> -1.1092753 | I47: =I46/I15 -> -0.63282692 | J47: =J46/J15 -> -0.33488258 | K47: =K46/K15 -> -0.22534615 | L47: =L46/L15 -> -0.00031002656 | M47: =M46/M15 -> 0.0085191512 | N47: =N46/N15 -> 0.062601053 | ... Z47: =Z46/Z15 -> 0.11698692
C48: Memo: implied incremental ROIC = ΔNOPAT ÷ prior year's (capex − D&A) | I48: =IFERROR((I34-H34)/(-H40-H26),NA()) -> 0.10364069 | J48: =IFERROR((J34-I34)/(-I40-I26),NA()) -> 0.10548278 | K48: =IFERROR((K34-J34)/(-J40-J26),NA()) -> 0.082602997 | L48: =IFERROR((L34-K34)/(-K40-K26),NA()) -> 0.085170138 | M48: =IFERROR((M34-L34)/(-L40-L26),NA()) -> 0.19619225 | N48: =IFERROR((N34-M34)/(-M40-M26),NA()) -> 0.15552467 | O48: =IFERROR((O34-N34)/(-N40-N26),NA()) -> 0.10741502 | P48: =IFERROR((P34-O34)/(-O40-O26),NA()) -> 0.10671024 | ... Z48: =IFERROR((Z34-Y34)/(-Y40-Y26),NA()) -> 0.066377637
C50: Cash-flow date | D50: =DATE(2023,12,31) -> 45291 | E50: =DATE(2024,12,31) -> 45657 | F50: =DATE(2025,12,31) -> 46022 | G50: =DATE(2026,12,31) -> 46387 | H50: =DATE(2027,12,31) -> 46752 | I50: =DATE(2028,12,31) -> 47118 | J50: =DATE(2029,12,31) -> 47483 | K50: =DATE(2030,12,31) -> 47848 | L50: =DATE(2031,12,31) -> 48213 | M50: =DATE(2032,12,31) -> 48579 | N50: =DATE(2033,12,31) -> 48944 | O50: =DATE(2034,12,31) -> 49309 | P50: =DATE(2035,12,31) -> 49674 | Q50: =DATE(2036,12,31) -> 50040 | R50: =DATE(2037,12,31) -> 50405 | S50: =DATE(2038,12,31) -> 50770 | T50: =DATE(2039,12,31) -> 51135 | U50: =DATE(2040,12,31) -> 51501 | V50: =DATE(2041,12,31) -> 51866 | W50: =DATE(2042,12,31) -> 52231 | X50: =DATE(2043,12,31) -> 52596 | Y50: =DATE(2044,12,31) -> 52962 | Z50: =DATE(2045,12,31) -> 53327
C51: Discount period (years) | D51: =MAX(0,(D50-$D$57)/365) -> 0 | E51: =MAX(0,(E50-$D$57)/365) -> 0 | F51: =MAX(0,(F50-$D$57)/365) -> 0 | G51: =MAX(0,(G50-$D$57)/365) -> 0.50410959 | H51: =MAX(0,(H50-$D$57)/365) -> 1.5041096 | I51: =MAX(0,(I50-$D$57)/365) -> 2.5068493 | J51: =MAX(0,(J50-$D$57)/365) -> 3.5068493 | K51: =MAX(0,(K50-$D$57)/365) -> 4.5068493 | ... Z51: =MAX(0,(Z50-$D$57)/365) -> 19.517808
C52: Post-valuation fraction of the year | D52: =MAX(0,MIN(1,(D50-$D$57)/(D50-DATE(2023,1,1)+1))) -> 0 | E52: =MAX(0,MIN(1,(E50-$D$57)/(E50-DATE(2024,1,1)+1))) -> 0 | F52: =MAX(0,MIN(1,(F50-$D$57)/(F50-DATE(2025,1,1)+1))) -> 0 | G52: =MAX(0,MIN(1,(G50-$D$57)/(G50-DATE(2026,1,1)+1))) -> 0.50410959 | H52: =MAX(0,MIN(1,(H50-$D$57)/(H50-DATE(2027,1,1)+1))) -> 1 | I52: =MAX(0,MIN(1,(I50-$D$57)/(I50-DATE(2028,1,1)+1))) -> 1 | J52: =MAX(0,MIN(1,(J50-$D$57)/(J50-DATE(2029,1,1)+1))) -> 1 | K52: =MAX(0,MIN(1,(K50-$D$57)/(K50-DATE(2030,1,1)+1))) -> 1 | L52: =MAX(0,MIN(1,(L50-$D$57)/(L50-DATE(2031,1,1)+1))) -> 1 | M52: =MAX(0,MIN(1,(M50-$D$57)/(M50-DATE(2032,1,1)+1))) -> 1 | N52: =MAX(0,MIN(1,(N50-$D$57)/(N50-DATE(2033,1,1)+1))) -> 1 | O52: =MAX(0,MIN(1,(O50-$D$57)/(O50-DATE(2034,1,1)+1))) -> 1 | P52: =MAX(0,MIN(1,(P50-$D$57)/(P50-DATE(2035,1,1)+1))) -> 1 | Q52: =MAX(0,MIN(1,(Q50-$D$57)/(Q50-DATE(2036,1,1)+1))) -> 1 | R52: =MAX(0,MIN(1,(R50-$D$57)/(R50-DATE(2037,1,1)+1))) -> 1 | S52: =MAX(0,MIN(1,(S50-$D$57)/(S50-DATE(2038,1,1)+1))) -> 1 | T52: =MAX(0,MIN(1,(T50-$D$57)/(T50-DATE(2039,1,1)+1))) -> 1 | U52: =MAX(0,MIN(1,(U50-$D$57)/(U50-DATE(2040,1,1)+1))) -> 1 | V52: =MAX(0,MIN(1,(V50-$D$57)/(V50-DATE(2041,1,1)+1))) -> 1 | W52: =MAX(0,MIN(1,(W50-$D$57)/(W50-DATE(2042,1,1)+1))) -> 1 | X52: =MAX(0,MIN(1,(X50-$D$57)/(X50-DATE(2043,1,1)+1))) -> 1 | Y52: =MAX(0,MIN(1,(Y50-$D$57)/(Y50-DATE(2044,1,1)+1))) -> 1 | Z52: =MAX(0,MIN(1,(Z50-$D$57)/(Z50-DATE(2045,1,1)+1))) -> 1
C53: FCFF included in the valuation | D53: =0 -> 0 | E53: =0 -> 0 | F53: =0 -> 0 | G53: =G46*G52 -> -13286.186 | H53: =H46*H52 -> -29617.65 | I53: =I46*I52 -> -28279.453 | J53: =J46*J52 -> -21861.135 | K53: =K46*K52 -> -19700.888 | L53: =L46*L52 -> -34.43 | M53: =M46*M52 -> 1132.11 | N53: =N46*N52 -> 9509.1 | ... Z53: =Z46*Z52 -> 28634.992
C54: Present value of FCFF | D54: =D53/(1+$D$58)^D51 -> 0 | E54: =E53/(1+$D$58)^E51 -> 0 | F54: =F53/(1+$D$58)^F51 -> 0 | G54: =G53/(1+$D$58)^G51 -> -12662.921 | H54: =H53/(1+$D$58)^H51 -> -25662.057 | I54: =I53/(1+$D$58)^I51 -> -22269.26 | J54: =J53/(1+$D$58)^J51 -> -15650.016 | K54: =K53/(1+$D$58)^K51 -> -12821.393 | ... Z54: =Z53/(1+$D$58)^Z51 -> 4456.5889
C56: Valuation | FCFF and bridge to equity
C57: Valuation date | D57: ='Assumptions & sources'!D54 -> 46203 | F57: Sensitivity | WACC x g (US$ / share)
C58: WACC | D58: ='Assumptions & sources'!D55 -> 0.1
C59: Terminal growth (g) | D59: ='Assumptions & sources'!D56 -> 0.02 | F59: =D74 -> 59.010557 | G59: =$D$59+-0.01 -> 0.01 | H59: =$D$59+-0.005 -> 0.015 | I59: =$D$59+0 -> 0.02 | J59: =$D$59+0.005 -> 0.025 | K59: =$D$59+0.01 -> 0.03
C60: Terminal incremental ROIC | D60: ='Assumptions & sources'!D57 -> 0.08 | F60: =$D$58+-0.02 -> 0.08 | G60: =(SUMPRODUCT($G$53:$Z$53,1/(1+$F60)^$G$51:$Z$51)+$Z$34*(1+G$59)*(1-G$59/$D$60)/($F60-G$59)/(1+$F60)^$Z$51-$D$64)/$D$61 -> 193.09545 | H60: =(SUMPRODUCT($G$53:$Z$53,1/(1+$F60)^$G$51:$Z$51)+$Z$34*(1+H$59)*(1-H$59/$D$60)/($F60-H$59)/(1+$F60)^$Z$51-$D$64)/$D$61 -> 194.16666 | I60: =(SUMPRODUCT($G$53:$Z$53,1/(1+$F60)^$G$51:$Z$51)+$Z$34*(1+I$59)*(1-I$59/$D$60)/($F60-I$59)/(1+$F60)^$Z$51-$D$64)/$D$61 -> 195.23786 | J60: =(SUMPRODUCT($G$53:$Z$53,1/(1+$F60)^$G$51:$Z$51)+$Z$34*(1+J$59)*(1-J$59/$D$60)/($F60-J$59)/(1+$F60)^$Z$51-$D$64)/$D$61 -> 196.30907 | K60: =(SUMPRODUCT($G$53:$Z$53,1/(1+$F60)^$G$51:$Z$51)+$Z$34*(1+K$59)*(1-K$59/$D$60)/($F60-K$59)/(1+$F60)^$Z$51-$D$64)/$D$61 -> 197.38028
C61: Diluted shares (millions) | D61: ='Assumptions & sources'!D58 -> 603.4 | F61: =$D$58+-0.01 -> 0.09 | G61: =(SUMPRODUCT($G$53:$Z$53,1/(1+$F61)^$G$51:$Z$51)+$Z$34*(1+G$59)*(1-G$59/$D$60)/($F61-G$59)/(1+$F61)^$Z$51-$D$64)/$D$61 -> 117.4588 | H61: =(SUMPRODUCT($G$53:$Z$53,1/(1+$F61)^$G$51:$Z$51)+$Z$34*(1+H$59)*(1-H$59/$D$60)/($F61-H$59)/(1+$F61)^$Z$51-$D$64)/$D$61 -> 116.72801 | I61: =(SUMPRODUCT($G$53:$Z$53,1/(1+$F61)^$G$51:$Z$51)+$Z$34*(1+I$59)*(1-I$59/$D$60)/($F61-I$59)/(1+$F61)^$Z$51-$D$64)/$D$61 -> 115.76498 | J61: =(SUMPRODUCT($G$53:$Z$53,1/(1+$F61)^$G$51:$Z$51)+$Z$34*(1+J$59)*(1-J$59/$D$60)/($F61-J$59)/(1+$F61)^$Z$51-$D$64)/$D$61 -> 114.51613 | K61: =(SUMPRODUCT($G$53:$Z$53,1/(1+$F61)^$G$51:$Z$51)+$Z$34*(1+K$59)*(1-K$59/$D$60)/($F61-K$59)/(1+$F61)^$Z$51-$D$64)/$D$61 -> 112.91
C62: Cash + securities (unrestricted) | D62: ='Assumptions & sources'!D59 -> 5539 | F62: =$D$58+0 -> 0.1 | G62: =(SUMPRODUCT($G$53:$Z$53,1/(1+$F62)^$G$51:$Z$51)+$Z$34*(1+G$59)*(1-G$59/$D$60)/($F62-G$59)/(1+$F62)^$Z$51-$D$64)/$D$61 -> 62.088755 | H62: =(SUMPRODUCT($G$53:$Z$53,1/(1+$F62)^$G$51:$Z$51)+$Z$34*(1+H$59)*(1-H$59/$D$60)/($F62-H$59)/(1+$F62)^$Z$51-$D$64)/$D$61 -> 60.684235 | I62: =(SUMPRODUCT($G$53:$Z$53,1/(1+$F62)^$G$51:$Z$51)+$Z$34*(1+I$59)*(1-I$59/$D$60)/($F62-I$59)/(1+$F62)^$Z$51-$D$64)/$D$61 -> 59.010557 | J62: =(SUMPRODUCT($G$53:$Z$53,1/(1+$F62)^$G$51:$Z$51)+$Z$34*(1+J$59)*(1-J$59/$D$60)/($F62-J$59)/(1+$F62)^$Z$51-$D$64)/$D$61 -> 57.013887 | K62: =(SUMPRODUCT($G$53:$Z$53,1/(1+$F62)^$G$51:$Z$51)+$Z$34*(1+K$59)*(1-K$59/$D$60)/($F62-K$59)/(1+$F62)^$Z$51-$D$64)/$D$61 -> 54.625015
C63: Gross financial debt (principal + finance leases) | D63: ='Assumptions & sources'!D60 -> 35772 | F63: =$D$58+0.01 -> 0.11 | G63: =(SUMPRODUCT($G$53:$Z$53,1/(1+$F63)^$G$51:$Z$51)+$Z$34*(1+G$59)*(1-G$59/$D$60)/($F63-G$59)/(1+$F63)^$Z$51-$D$64)/$D$61 -> 20.534155 | H63: =(SUMPRODUCT($G$53:$Z$53,1/(1+$F63)^$G$51:$Z$51)+$Z$34*(1+H$59)*(1-H$59/$D$60)/($F63-H$59)/(1+$F63)^$Z$51-$D$64)/$D$61 -> 18.962056 | I63: =(SUMPRODUCT($G$53:$Z$53,1/(1+$F63)^$G$51:$Z$51)+$Z$34*(1+I$59)*(1-I$59/$D$60)/($F63-I$59)/(1+$F63)^$Z$51-$D$64)/$D$61 -> 17.145554 | J63: =(SUMPRODUCT($G$53:$Z$53,1/(1+$F63)^$G$51:$Z$51)+$Z$34*(1+J$59)*(1-J$59/$D$60)/($F63-J$59)/(1+$F63)^$Z$51-$D$64)/$D$61 -> 15.041521 | K63: =(SUMPRODUCT($G$53:$Z$53,1/(1+$F63)^$G$51:$Z$51)+$Z$34*(1+K$59)*(1-K$59/$D$60)/($F63-K$59)/(1+$F63)^$Z$51-$D$64)/$D$61 -> 12.596044
C64: Net debt | D64: =D63-D62 -> 30233 | F64: =$D$58+0.02 -> 0.12 | G64: =(SUMPRODUCT($G$53:$Z$53,1/(1+$F64)^$G$51:$Z$51)+$Z$34*(1+G$59)*(1-G$59/$D$60)/($F64-G$59)/(1+$F64)^$Z$51-$D$64)/$D$61 -> -11.260389 | H64: =(SUMPRODUCT($G$53:$Z$53,1/(1+$F64)^$G$51:$Z$51)+$Z$34*(1+H$59)*(1-H$59/$D$60)/($F64-H$59)/(1+$F64)^$Z$51-$D$64)/$D$61 -> -12.776789 | I64: =(SUMPRODUCT($G$53:$Z$53,1/(1+$F64)^$G$51:$Z$51)+$Z$34*(1+I$59)*(1-I$59/$D$60)/($F64-I$59)/(1+$F64)^$Z$51-$D$64)/$D$61 -> -14.497503 | J64: =(SUMPRODUCT($G$53:$Z$53,1/(1+$F64)^$G$51:$Z$51)+$Z$34*(1+J$59)*(1-J$59/$D$60)/($F64-J$59)/(1+$F64)^$Z$51-$D$64)/$D$61 -> -16.454793 | K64: =(SUMPRODUCT($G$53:$Z$53,1/(1+$F64)^$G$51:$Z$51)+$Z$34*(1+K$59)*(1-K$59/$D$60)/($F64-K$59)/(1+$F64)^$Z$51-$D$64)/$D$61 -> -18.688086
C66: PV of explicit cash flows | D66: =SUM(G54:Z54) -> -3284.8662 | F66: Sensitivity | revenue per GW in 2030 (US$ bn/GW, columns) x LT EBITDA margin (rows) — US$ / share (data table, filled by Excel)
C67: Terminal NOPAT | D67: =Z34*(1+D59) -> 47375.884 | F67: =D74 -> 59.010557 | G67: 0.846154 | H67: 0.923077 | I67: 1 | J67: 1.076923 | K67: 1.153846 | L67: 1.230769
C68: Terminal net reinvestment | D68: =D67*D59/D60 -> 11843.971 | E68: ='Assumptions & sources'!$Z$77+F68 -> 0.57 | F68: -0.05 | G68: -204.70714 | H68: -119.56101 | I68: -34.414891 | J68: 50.731232 | K68: 135.87736 | L68: 221.02348
C69: Terminal FCFF | D69: =IF(AND(D58>D59,D60>D59),D67-D68,NA()) -> 35531.913 | E69: ='Assumptions & sources'!$Z$77+F69 -> 0.62 | F69: 0 | G69: -125.65482 | H69: -33.322132 | I69: 59.010557 | J69: 151.34325 | K69: 243.67593 | L69: 336.00862
C70: Undiscounted terminal value | D70: =D69/(D58-D59) -> 444148.91 | E70: ='Assumptions & sources'!$Z$77+F70 -> 0.67 | F70: 0.05 | G70: -46.602505 | H70: 52.91675 | I70: 152.436 | J70: 251.95526 | K70: 351.47451 | L70: 450.99377
C71: PV of terminal value | D71: =D70/(1+D58)^Z51 -> 69124.836 | E71: ='Assumptions & sources'!$Z$77+F71 -> 0.72 | F71: 0.1 | G71: 32.449811 | H71: 139.15563 | I71: 245.86145 | J71: 352.56727 | K71: 459.27309 | L71: 565.97891
C72: Enterprise value | D72: =SUM(D66,D71) -> 65839.97
C73: Equity value | D73: =D72-D64 -> 35606.97 | F73: Rows: EBITDA-margin adjustment (pp) over the WHOLE 2027+ path (column E = resulting LT margin). Columns: revenue/GW multiplier over the WHOLE 2027+ path (top row) — the bottom row shows the equivalent 2030 level (LT = 14.0 x mult). Base 2030 = 13.0 sits BELOW management's floor for new contracts (15-16): 1.9 GW legacy at 11 + 6.1 GW new at 15.5 would blend to ~14.4.
C74: Value per share (US$) | D74: =D73/D61 -> 59.010557 | G74: 11 | H74: 12 | I74: 13 | J74: 14 | K74: 15 | L74: 16
C75: Terminal value / enterprise value | D75: =D71/D72 -> 1.0498917
C76: Value per share | explicit cash flows only (no terminal) | D76: =(D66-D64)/D61 -> -55.548336 | F76: Sensitivity | replacement life (years, columns) x replacement cost (% of build, rows) — US$ / share (data table)
C77: Memo: EV at the reference price (market cap + net debt) | D77: ='Assumptions & sources'!$D$64+D64 -> 73718.6 | F77: =D74 -> 59.010557 | G77: 5 | H77: 6 | I77: 7 | J77: 8 | K77: 10
C78: Memo: EV/EBITDA CY27E and CY28E at the reference price | D78: =D77/H23 -> 4.4532198 | E78: =D77/I23 -> 2.5775734 | F78: 1 | G78: -229.40076 | H78: -56.673157 | I78: 63.961 | J78: 151.46103 | K78: 277.99014
C79: Memo: EV/revenue CY28E at the price (UBS PT $120 = 3.8x CY28E; peers ~4.5x) | D79: =D77/I15 -> 1.649647 | F79: 0.8 | G79: -79.171529 | H79: 59.010557 | I79: 155.51788 | J79: 225.51791 | K79: 326.74119
F80: 0.6 | G80: 71.057706 | H80: 174.69427 | I80: 247.07476 | J80: 299.57478 | K80: 375.49225
F81: 0.4 | G81: 221.28694 | H81: 290.37798 | I81: 338.63165 | J81: 373.63166 | K81: 424.2433
F82: Replacement is what the Street rarely charges explicitly: at 6 years / 80% a mature fleet consumes ~$5.3bn per GW-year (≈ D&A). Longer life = re-contracting old GPUs (A100/H100 still rented in year 9) without replacing them — but the 7-10-year columns keep full pricing on old GPUs (DB 2025-06-16: 50-75% of ASP in years 5-6), so they are the UPPER BOUND, not a case.
C84: Steady-state unit economics per GW (column CY35E) — the arithmetic behind the DCF
C85: Revenue per billable GW (US$ bn / GW-year) | D85: =P12 -> 14
C86: EBITDA per GW (US$ bn) | D86: =D85*P22 -> 8.68
C87: D&A per GW (US$ bn) | D87: =P25 -> 5
C88: SBC per GW (US$ bn) | D88: =D85*'Assumptions & sources'!P79 -> 0.28
C89: Tax per GW = (EBITDA − D&A − SBC) x tax rate (US$ bn) | D89: =(D86-D87-D88)*P33 -> 0.714
C90: Operating cash per GW before capex = EBITDA − SBC − tax (US$ bn) | D90: =D86-D88-D89 -> 7.686
C91: Build cost per GW (US$ bn) | D91: =P35 -> 40
C92: Replacement per GW-year, mature fleet = build x replacement % ÷ life (US$ bn) — memo, what the DCF charges at steady state | D92: =D91*$G$6/$F$6 -> 5.3333333
C93: Replacement of 1 NEW GW, annual equivalent (sinking fund: first swap in year 'life') = build x % x WACC ÷ ((1+WACC)^life − 1) | D93: =D91*$G$6*D58/((1+D58)^$F$6-1) -> 4.1474362
C94: FCF per GW-year of 1 new GW, no growth = operating cash − equivalent replacement (US$ bn) | D94: =D90-D93 -> 3.5385638
C95: Cash yield on build cost (FCF ÷ build) | D95: =D94/D91 -> 0.088464096
C96: Gross payback of the build = build ÷ operating cash (years) | D96: =D91/D90 -> 5.2042675
C97: Value of 1 GW in perpetuity at WACC = FCF ÷ WACC (US$ bn) | D97: =D94/D58 -> 35.385638
C98: NPV of 1 new GW = value − build (US$ bn) — negative = each GW destroys value at WACC | D98: =D97-D91 -> -4.6143617
C99: Break-even revenue/GW (NPV = 0) at the same margin, life and replacement (US$ bn / GW-year) | D99: =(D91*D58+D93-D87*P33)/((P22-'Assumptions & sources'!P79)*(1-P33)) -> 14.973494
C100: Break-even: (EBITDA − SBC) x (1 − t) + D&A x t − equivalent replacement = build x WACC. Compare with the marks: installed book ~11, management's floor for new contracts 15-16 (= the break-even), short-dated ~40. A MATURE fleet replaces ~fleet ÷ life per year (memo row) — that is what the DCF charges from 2032.
C103: Memo outside the DCF | implied net debt, interest, net income and EPS (no equity raised after 2026)
C104: Net debt at year-end (US$ m) | F104: ='Assumptions & sources'!$D$65 -> 18488 | G104: =F104-G46+G105-'Assumptions & sources'!$D$66 -> 45362.008 | H104: =G104-H46+H105 -> 80395.033 | I104: =H104-I46+I105 -> 117182.61 | J104: =I104-J46+J105 -> 150573.94 | K104: =J104-K46+K105 -> 184713.02 | L104: =K104-L46+L105 -> 201373.17 | M104: =L104-M46+M105 -> 218313.7 | N104: =M104-N46+N105 -> 228024.92 | O104: =N104-O46+O105 -> 235274.93 | ... Z104: =Y104-Z46+Z105 -> 129669.27
C105: Net interest = (prior net debt − 0.5 x FCFF of the year) x cost of debt | G105: =(F104-0.5*G46)*'Assumptions & sources'!G83 -> 3008.2581 | H105: =(G104-0.5*H46)*'Assumptions & sources'!H83 -> 5415.375 | I105: =(H104-0.5*I46)*'Assumptions & sources'!I83 -> 8508.1284 | J105: =(I104-0.5*J46)*'Assumptions & sources'!J83 -> 11530.186 | K105: =(J104-0.5*K46)*'Assumptions & sources'!K83 -> 14438.194 | L105: =(K104-0.5*L46)*'Assumptions & sources'!L83 -> 16625.721 | M105: =(L104-0.5*M46)*'Assumptions & sources'!M83 -> 18072.64 | N105: =(M104-0.5*N46)*'Assumptions & sources'!N83 -> 19220.323 | ... Z105: =(Y104-0.5*Z46)*'Assumptions & sources'!Z83 -> 11888.816
C106: Interest | reported FY23-25 (memo) | D106: ='Assumptions & sources'!D17 -> 28 | E106: ='Assumptions & sources'!E17 -> 361 | F106: ='Assumptions & sources'!F17 -> 1229
C107: Net debt / EBITDA | F107: =F104/F23 -> 5.9677211 | G107: =G104/G23 -> 6.1633163 | H107: =H104/H23 -> 4.8565321 | I107: =I104/I23 -> 4.0972942 | J107: =J104/J23 -> 3.6040407 | K107: =K104/K23 -> 3.3536776 | L107: =L104/L23 -> 2.9246358 | M107: =M104/M23 -> 2.6497018 | ... Z107: =Z104/Z23 -> 0.85444797
C108: Adjusted net income (company basis, EX-SBC) = (AOI − interest) x (1 − tax if positive) | G108: =IF(G27-G105>0,(G27-G105)*(1-G33),G27-G105) -> -1973.2581 | H108: =IF(H27-H105>0,(H27-H105)*(1-H33),H27-H105) -> -1101.375 | I108: =IF(I27-I105>0,(I27-I105)*(1-I33),I27-I105) -> 324.77805 | J108: =IF(J27-J105>0,(J27-J105)*(1-J33),J27-J105) -> 2474.1122 | K108: =IF(K27-K105>0,(K27-K105)*(1-K33),K27-K105) -> 4156.1224 | L108: =IF(L27-L105>0,(L27-L105)*(1-L33),L27-L105) -> 6895.4195 | M108: =IF(M27-M105>0,(M27-M105)*(1-M33),M27-M105) -> 11312.136 | N108: =IF(N27-N105>0,(N27-N105)*(1-N33),N27-N105) -> 15371.565 | ... Z108: =IF(Z27-Z105>0,(Z27-Z105)*(1-Z33),Z27-Z105) -> 40922.161
...

Sheet Assumptions & sources
C2: CRWV | Assumptions & sources
C3: Data taken from the sources named. US$ millions unless stated; power in MW (critical IT load, the company's basis); revenue per GW and build cost per GW in US$ billions per GW. Fiscal year = calendar year.
C4: Blue = HARD input (filing / consensus); yellow = PARTIAL assumption (sourced range, point is ours); salmon = ESTIMATE (no source). Source in column L (tables) or AB (series).
D5: 2023 | E5: 2024 | F5: 2025 | G5: 2026 | H5: 2027 | I5: 2028
L6: File, sheet and source cells. CY = calendar year (= CoreWeave's fiscal year).
C8: Reported history (10-K FY25, 10-Q 2Q26) and BBG consensus (2026-10-13)
C9: Revenue (US$ m) | 10-K FY23-25 / BBG consensus CY26-28 | D9: 229 | E9: 1915 | F9: 5131 | G9: 12770.37 | H9: 26439.52 | I9: 42212.08 | L9: 10-K FY25 (CRWV/CRWV_10-K_2026-03-02): 229 / 1,915 / 5,131. CY26-28: _wiki/_data/estimates.json CRWV CY2026 / CY2027 / 3FY (BEst 2026-10-13; 47 analysts, 33 buy / 10 hold / 4 sell).
C10: Adjusted EBITDA (US$ m) | company / consensus | E10: 1226 | F10: 3098 | G10: 7482.66 | H10: 16630.37 | I10: 27896.76 | L10: FY24: 64% margin (DB CRWV unit economics 2025-06-16) x 1,915 = 1,226 (PARTIAL). FY25 = sum of quarters: 1Q25 ~609 (1Q26 ~1,164 = 56% x 2,078, '+91% y/y', call 2026-05-07 — PARTIAL) + 2Q 753 + 3Q 838 + 4Q 898 (calls). CY26-28 BEst EBITDA.
C11: Adjusted operating income (AOI, US$ m) | consensus EBIT CY26-28 | G11: 1004.25 | H11: 4113.1 | I11: 7363.56 | L11: BEst EBIT (estimates.json). FY26 guide (call 2026-08-11): AOI $960-1,150m; 3Q26 $200-260m.
C12: GAAP net income (US$ m) | 10-K / consensus | D12: -594 | E12: -863 | F12: -1167 | G12: -2197.83 | H12: -1132.69 | I12: 974.96 | L12: 10-K FY25 (net loss); BEst NI CY26-28.
C13: GAAP diluted EPS (US$) | 10-K / consensus | D13: -3.09 | E13: -4.3 | F13: -2.81 | G13: -3.92 | H13: -2.09 | I13: 1.431 | L13: 10-K FY25 p.1508: net loss per share attributable to common stockholders, diluted: (3.09) / (4.30) / (2.81) (two-class method; post 20:1 split of Mar-25). CY26-28 BEst EPS (ex-SBC).
C14: Depreciation and amortization (US$ m) | D14: 103 | E14: 863 | F14: 2454 | G14: 2540 | L14: 10-K cash flow FY23-25; 1H26 = 2,540 (10-Q 2Q26). 2026 column = 1H26 (memo).
C15: Stock-based compensation (US$ m) | D15: 15 | E15: 31 | F15: 630 | G15: 318 | L15: 10-K cash flow (FY25 includes $177m of RSUs vested at the IPO); 1H26 = 318 (memo).
C16: Cash capex (US$ m) | 10-K / BBG consensus CY26-28 | D16: 2943 | E16: 8702 | F16: 10309 | G16: 35670.67 | H16: 47897.41 | I16: 50387.97 | L16: 10-K 'Purchase of property and equipment' 2,943 / 8,702 / 10,309 (FY25 company basis ~$14bn incl. OEM financing: 3Q25 guide $12-14bn). CY26-28 BEst capex. FY26 guide (company basis): $35-39bn.
C17: Net interest expense (US$ m) | D17: 28 | E17: 361 | F17: 1229 | G17: 1176 | L17: 10-K FY23-25; 1H26 = 1,176 (10-Q 2Q26). 3Q26 guide: $860-940m.
C18: Active power at year-end (MW, IT load) | D18: 70 | E18: 360 | F18: 850 | G18: 1500 | L18: 10-K FY25 p.194: ~70 MW (Dec-23), ~360 MW (Dec-24), >850 MW (Dec-25). 2026 column = Jun-26: 1.5 GW (call 2026-08-11). YE26 guide: >1.85 GW.
C19: Contracted power (MW) | F19: 3100 | G19: 4200 | L19: 10-K FY25: ~3.1 GW (Dec-25). Call 2026-08-11: 3.7 GW at 2Q-end, 4.2 GW as of 11-Aug-26 (2026 column). Target: >=8 GW active by 2030.
C20: Unsatisfied RPO (US$ m) | F20: 60700 | G20: 103700 | L20: 10-K FY25: $60.7bn (43% within 24 months). 10-Q 2Q26: $103.7bn, 41% in the 24 months to Jun-28, 39% months 25-48, balance months 49-78. Backlog (company metric): $66.8bn Dec-25 / $104bn Jun-26.
C21: Total deferred revenue (US$ m) | Dec-24 / Dec-25 / Jun-26 | E21: 4064 | F21: 8185 | G21: 9692 | L21: 10-K FY25 balance sheet (769+3,295; 1,709+6,476); 10-Q 2Q26 (2,686+7,006). Customer prepayments = 15-25% of TCV (UBS 2026-09-22).
C22: Accounts receivable (US$ m) | Dec-24 / Dec-25 / Jun-26 | E22: 417 | F22: 3169 | G22: 2541 | L22: 10-K FY25; 10-Q 2Q26.
C23: Cash and equivalents (US$ m) | Dec-24 / Dec-25 / Jun-26 | E23: 1361 | F23: 3127 | G23: 5524 | L23: 10-K FY25; 10-Q 2Q26. Additional restricted cash: 1,003 (Dec-25: 819 + 184) / 1,380 (Jun-26: 873 + 507) — debt-service coverage, excluded from net cash.
C24: Gross debt, principal (US$ m) | Dec-24 / Dec-25 / Jun-26 | E24: 7926 | F24: 21615 | G24: 35551 | L24: 10-K FY25 note 10 (Dec-24 carrying value 7,926; Dec-25 carrying 21,373 + discount 242 = 21,615). 10-Q 2Q26 note 10: total principal 35,551 (recourse + non-recourse). See Debt sheet.
C25: Operating lease liabilities (US$ m) | Dec-24 / Dec-25 / Jun-26 | E25: 2602 | F25: 8195 | G25: 16319 | L25: 10-K FY25; 10-Q 2Q26 (10% rate, 12-year term). Plus $35.5bn of leases not yet commenced (Jun-26). Rent sits in EBITDA — NOT added to net debt.
C27: FY26 guidance (2Q26 call, 2026-08-11) — company basis
C28: FY26 revenue — low end (US$ m) | D28: 12400 | F28: Call 2026-08-11: $12.4-13.2bn (raised from $12.0-13.0bn in Feb-26).
C29: FY26 revenue — high end (US$ m) | D29: 13200 | F29: Same.
C30: FY26 AOI — low end (US$ m) | D30: 960 | F30: Call 2026-08-11: $960-1,150m (from $900-1,100m).
C31: FY26 AOI — high end (US$ m) | D31: 1150 | F31: Same.
C32: FY26 capex — low end (US$ m, company basis) | D32: 35000 | F32: Call 2026-08-11: $35-39bn (from $31-35bn). 1H26 reported: 6.8 + 9.4 = $16.2bn (cash: 14.1).
C33: FY26 capex — high end (US$ m) | D33: 39000 | F33: Same.
C34: Active power YE26 — guide (MW) | D34: 1850 | F34: Call 2026-08-11: '>1.85 GW' (from >1.7 GW). UBS 09-22: 1,900 MW FY26E, 3,200 FY27E, 4,720 FY28E, 6,320 FY29E, 8,000 FY30E.
C35: 3Q26 revenue — midpoint (US$ m) | D35: 3525 | F35: Call 2026-08-11: $3.45-3.60bn; 3Q AOI $200-260m; 3Q interest $860-940m; 3Q capex $11.5-13.5bn.
C36: 1H26 reported revenue (US$ m) | D36: 4653 | F36: 10-Q 2Q26: 2,078 + 2,575.
C37: 1H26 reported AOI (US$ m) | D37: 149 | F37: Calls: 1Q26 $21m + 2Q26 $128m.
C38: Average billable power 2026 (MW) — quarterly build | D38: 1124 | F38: Average over four quarters of the PRIOR quarter's average active power (UBS 09-22: 'it takes about a quarter for active power to generate revs'): 1Q (590+850)/2=720; 2Q (850+1,000)/2=925; 3Q (1,000+1,500)/2=1,250; 4Q (1,500+1,700)/2=1,600 (3Q26 YE estimated 1,700). Average 1,124. Overrides the annual formula in 2026 (adds were front-loaded in 1H).
C40: Revenue-per-GW marks (US$ bn per IT-load GW per YEAR) — wiki ledger; NEVER net different bases
C41: Realised on the installed book (UBS, 09-22) | D41: 11 | F41: UBS Keirstead 2026-09-22: 2Q26 $2.575bn x4 / 925 MW average active power in 1Q26 = ~$11bn/GW; 'closer to $15bn by end of 2027'. This model: 2026 implied by the guide = ~11.4.
C42: Floor for new long-dated contracts (4-6 years) — management | D42: 15.5 | F42: Nick Robbins (VP Corp Dev) @ BTG Pactual, 2026-09-21: mid-teens $/W/year is 'the absolute floor'; long-dated Vera Rubin 'clearing higher'. Seller of the capacity, not audited.
C43: Nscale's filed book (S-1 2026-09-18) — blended / VR tranche | D43: 13.2 | F43: Nscale S-1: $103.4bn TCV / 5.7 years / 1.37 GW IT = ~$13.2bn/GW-year; Anthropic Vera Rubin tranche ~$16.2bn. Read by the wiki as the CEILING of a contracted book (open conflict with management).
C44: Short-dated contracts (3-6 months) — annualised | D44: 40 | F44: Robbins 09-21: 'about $40 million a megawatt' on short-dated contracts for PRIOR generations (Blackwell / Grace Blackwell), term and time basis not stated; JPM 09-24 repeats the print without a basis; only UBS 09-22 gives the term (3-6 months) and the annualised basis ($40bn/GW). Small slice of the book. Arete 08-21: $20-25m/MW on 2-3-year contracts.
C45: Revenue / capex on a 5-year contract (management) | D45: 2 | F45: Robbins 09-21: 'historically… two to one ratio for a five-year deal between revenue and capex', 'expanded' since early 2026. 2:1 over 5 years on $40bn/GW = $16bn/GW-year.
C46: Bear memo: monetisation per connected MW did not improve in 2025 (Hedgeye, Dec-25) | D46: 0 | F46: HE Global Technology BB, Dec-2025 (short since Apr-25). This model's quarterly calibration: 2Q25 ~12.4 → 2Q26 ~11.1 US$bn/GW (History sheet) — revenue per installed GW FELL as the fleet scaled.
C48: Build cost per GW (CoreWeave's capex; it leases the shell) — US$ bn per IT-load GW
C49: Blackwell — UBS | D49: 35 | F49: UBS 09-22: 'capex to CoreWeave might be closer to $35bn per Blackwell-based GW and $40bn per Vera Rubin-based GW' (Crusoe all-in $57bn/GW, $30bn of it GPUs).
C50: Vera Rubin — UBS | D50: 40 | F50: Same. Arete 08-21: VR NVL72 racks 70-80% more expensive than Blackwell, ~+20% GPU capex per MW.
C51: Backward check: 2024-26 capex / 1.85 GW | D51: 34 | F51: UBS: $62bn of 2024-26 capex to stand up 1.85 GW by YE26 = $34bn/GW ('flattered' — part of 2026 capex buys 2027 capacity). Calibration basis for the pre-build share.
C53: Valuation and balance sheet
C54: Valuation date | D54: 46203 | F54: Same as the balance-sheet date (30-Jun-26). DEVIATION from the family convention (27-Aug-26): with ~$26bn/year of cash burn, valuing in August against June net debt would leave ~$5.6bn of July-August burn out of the bridge (~−$9/share; double-check 2026-10-14). Update both together at the 10-Q 3Q26.
C55: WACC | D55: 0.1 | F55: Family convention (10%), kept for comparability — but for CRWV it is a SUBSIDY: with no tax shield (NOLs; 5% cash tax to 2028) Kd 10% x 65% + Ke 14% x 35% = 11.4%; at market weights (net debt 30bn vs market cap 43bn) 12-13%. Arete 11%; Redburn Ke 20%. See the WACC x g grid: 11% and 12% are the honest reading.
C56: Terminal growth | D56: 0.02 | F56: Template DCF NVDA.xlsx | Capa DCF - Base!D91.
C57: Terminal incremental ROIC | D57: 0.08 | F57: ESTIMATE. The template uses 20%; here 8% because a new GW costs ~$40bn and generates NOPAT of ~$2-3bn (5-7% gross). See the 'implied incremental ROIC' row on the cover. Sensitivity in the grid.
C58: Diluted shares (m) | 551 outstanding + 29 RSUs + 23.4 options (treasury) | D58: 603.4 | F58: 10-Q 2Q26: 457m class A + 94m class B (30-Jun-26); 29m unvested RSUs/RSAs; 24m options at $1.84 (intrinsic value $2,341m) → treasury method at $77.81 = 23.4m. Out-of-the-money converts (2031: $107.80 / cap $215.60; 2032: $119.60 / cap $230) stay in debt. No ATM (management 09-21: 'not at these prices').
C59: Cash + securities, unrestricted (US$ m, 30-Jun-26) | D59: 5539 | F59: 10-Q 2Q26: cash 5,524 + securities 15. Restricted cash 1,380 excluded (mandatory interest/principal coverage under the DDTLs).
C60: Gross financial debt, principal (US$ m, 30-Jun-26) | D60: 35772 | F60: 10-Q 2Q26 note 10: principal 35,551 (DDTLs, senior notes, converts, OEM financing, Magnetar) + finance leases 221. Operating leases (16,319) NOT added: rent already sits in EBITDA.
C61: Balance-sheet date used in the model | D61: 46203 | F61: Update at the 10-Q 3Q26.
C62: Reference price (US$, informational) | D62: 77.81 | F62: BBG PX_LAST CRWV US, 2026-10-13 (estimates.json). Not used in the valuation.
C63: Consensus average PT (US$, informational) | D63: 139.77 | F63: BBG BEST_TARGET_PRICE, 47 analysts (hi 278 / lo 39), 2026-10-13. UBS Buy $120; JPM OW $125; Bernstein UP $74; Redburn Sell $54; Arete Buy $317.
C64: Market cap (US$ m, informational) | D64: 43485.6 | F64: BBG 2026-10-13.
C65: Net debt Dec-25 (US$ m) — anchor of the debt roll | D65: 18488 | F65: Principal 21,615 − cash 3,127 (10-K FY25). Used only in the debt/EPS memo block, not in the DCF.
... C68: Share of the year's capex that buys NEXT year's capacity | D68: 0.2 | F68: Calibrated: FY26 guide $37bn (mid) vs formula 33 x (0.8 x 1.05 GW + 0.2 x 1.3 GW) = 36.3 (−1.9%; the current-year build cost also prices the pre-built share). UBS: backward check 'flattered' by 2026 capex buying 2027.
C69: Useful life for replacement (years) — INPUT ON THE COVER, F6 (memo) | D69: ='DCF Cover - Base'!F6 -> 6 | F69: CoreWeave GPU depreciation: 6 years (10-K; MS AI Factories). Replacement in t = everything installed in t−6 (adds and replacements). Re-contracting in years 5-6 at 50-75% of ASP (DB 2025-06-16) is the optimistic side — sensitise 8 years.
C70: Replacement cost (% of the year's build cost) — INPUT ON THE COVER, G6 (memo) | D70: ='DCF Cover - Base'!G6 -> 0.8 | F70: ESTIMATE: the shell is leased; GPUs/servers/network (~80% of capex) are replaced, part of the MEP/fit-out is kept.
C71: Fleet growth after 2035 (% of prior YE) | D71: 0.03 | F71: ESTIMATE: adds = 3% of the prior year's active power from 2036.
C73: Assumptions by year (CY)
D74: CY23A | E74: CY24A | F74: CY25A | G74: CY26E | H74: CY27E | I74: CY28E | J74: CY29E | K74: CY30E | L74: CY31E | M74: CY32E | N74: CY33E | O74: CY34E | P74: CY35E | Q74: CY36E | R74: CY37E | S74: CY38E | T74: CY39E | U74: CY40E | V74: CY41E | W74: CY42E | X74: CY43E | Y74: CY44E | Z74: CY45E
C75: Active power additions (MW, IT load) | G75: 1050 | H75: 1300 | I75: 1500 | J75: 1600 | K75: 1700 | L75: 1400 | M75: 1200 | N75: 1000 | O75: 900 | P75: 800 | AB75: 2026: +1,050 → YE 1,900 (guide >1,850; UBS 1,900; 1.5 GW already in Jun-26). 2027-30: 1,300 / 1,500 / 1,600 / 1,700 → 3.2 / 4.7 / 6.3 / 8.0 GW = UBS 09-22 path to management's ≥8 GW-by-2030 target. Contracted 4.2 GW + 1.5 GW powered land = ~6 GW visible (call 08-11). 2031-35 ESTIMATE: decelerates to 800 MW/year; 2036+ formula (g_fleet).
C76: Revenue per billable GW (US$ bn / GW-year), base | H76: 12 | I76: 12.5 | J76: 12.8 | K76: 13 | L76: 13.3 | M76: 13.7 | N76: 14 | O76: 14 | P76: 14 | Q76: 14 | R76: 14 | S76: 14 | T76: 14 | U76: 14 | V76: 14 | W76: 14 | X76: 14 | Y76: 14 | Z76: 14 | AB76: 2026 implied by the guide = 12,800 / 1,124 MW = ~11.4 (cover). 2027 12.0 → 2030 13.0: blend of the legacy book (~11) with new long-dated contracts at mid-teens (management 09-21; Nscale 13.2-16.2) and a short-dated slice at ~40. UBS: ~15 at the 2027 EXIT; UBS 2030 target $85bn / ~6.7 GW billable = 12.7. 2031-33 rises to 14.0 and stays flat nominal: the legacy book (2025-26, ~2 GW at ~11) is re-contracted and the fleet becomes mostly 2027+ vintages contracted at >=15; 14.0 is BELOW every forward mark (management floor 15-16, Nscale VR 16.2, UBS 15 exit-27). PARTIAL.
C77: Adjusted EBITDA margin | G77: 0.575 | H77: 0.62 | I77: 0.64 | J77: 0.64 | K77: 0.63 | L77: 0.62 | M77: 0.62 | N77: 0.62 | O77: 0.62 | P77: 0.62 | Q77: 0.62 | R77: 0.62 | S77: 0.62 | T77: 0.62 | U77: 0.62 | V77: 0.62 | W77: 0.62 | X77: 0.62 | Y77: 0.62 | Z77: 0.62 | AB77: 2026 57.5%: 1H 57.6% (2.71bn / 4.65) + implied 2H (AOI guide 1,055 − 149 + D&A ~3.6bn) ≈ 56%; consensus 58.6%. 2027-28 62/64% (consensus 62.9/66.1%). LT 62%: between the contract-level mid-70s (management) and the long-term 25-30% operating-margin target after D&A (4Q25 call). DC rent (leases) and overhead sit here.
C78: D&A per average active GW (US$ bn / GW-year) | G78: 4.6 | H78: 4.8 | I78: 5 | J78: 5 | K78: 5 | L78: 5 | M78: 5 | N78: 5 | O78: 5 | P78: 5 | Q78: 5 | R78: 5 | S78: 5 | T78: 5 | U78: 5 | V78: 5 | W78: 5 | X78: 5 | Y78: 5 | Z78: 5 | AB78: Calibrated: FY25 2,454 / 605 MW average = 4.1; 1H26 annualised 5,080 / ~1,090 MW = 4.7. VR at $40bn/GW with mixed 6-15-year lives → ~5.0-5.5. 5.0 flat (PARTIAL). Drives EBIT/EPS, not FCFF (only through tax).
C79: SBC / revenue (deducted in EBIT after SBC) | G79: 0.05 | H79: 0.03 | I79: 0.025 | J79: 0.02 | K79: 0.02 | L79: 0.02 | M79: 0.02 | N79: 0.02 | O79: 0.02 | P79: 0.02 | Q79: 0.02 | R79: 0.02 | S79: 0.02 | T79: 0.02 | U79: 0.02 | V79: 0.02 | W79: 0.02 | X79: 0.02 | Y79: 0.02 | Z79: 0.02 | AB79: FY25 12.3% (includes $177m from the IPO); 1H26 6.8%. 5% → 2% LT. The company's AOI EXCLUDES SBC; the FCFF here deducts it.
C80: Cash tax rate on EBIT | G80: 0.05 | H80: 0.05 | I80: 0.05 | J80: 0.1 | K80: 0.15 | L80: 0.21 | M80: 0.21 | N80: 0.21 | O80: 0.21 | P80: 0.21 | Q80: 0.21 | R80: 0.21 | S80: 0.21 | T80: 0.21 | U80: 0.21 | V80: 0.21 | W80: 0.21 | X80: 0.21 | Y80: 0.21 | Z80: 0.21 | AB80: NOLs >$3bn (DB 2025-06-16); GAAP provision positive despite losses (146m in 1H26 — state/foreign). 5% to 2028, 21% from 2031.
C81: Build cost per GW added (US$ bn / GW) | G81: 33 | H81: 38 | I81: 40 | J81: 40 | K81: 40 | L81: 40 | M81: 40 | N81: 40 | O81: 40 | P81: 40 | Q81: 40 | R81: 40 | S81: 40 | T81: 40 | U81: 40 | V81: 40 | W81: 40 | X81: 40 | Y81: 40 | Z81: 40 | AB81: 2026 33 (Blackwell; UBS 35 / backward check 34), 2027 38, 2028+ 40 (Vera Rubin, UBS). Flat nominal after 2028: memory/rack inflation vs density gains. PARTIAL.
C82: Operating NWC / revenue = (receivables − deferred revenue) / revenue | G82: -0.7 | H82: -0.55 | I82: -0.45 | J82: -0.4 | K82: -0.35 | L82: -0.35 | M82: -0.35 | N82: -0.35 | O82: -0.35 | P82: -0.35 | Q82: -0.35 | R82: -0.35 | S82: -0.35 | T82: -0.35 | U82: -0.35 | V82: -0.35 | W82: -0.35 | X82: -0.35 | Y82: -0.35 | Z82: -0.35 | AB82: Dec-25: (3,169 − 8,185) / 5,131 = −98%; Jun-26: (2,541 − 9,692) / LTM 7,590 = −94%. Prepayments (15-25% of TCV) scale with bookings, not revenue: the ratio compresses to −35% by 2030 (ESTIMATE — the only anchor is the prepayment %). Cash inflow = 35-70% of the revenue increment; UBS implies much larger inflows (12/27E net debt $56.5bn vs ~$80bn here).
C83: Average cost of debt (memo, debt/EPS block) | G83: 0.095 | H83: 0.09 | I83: 0.09 | J83: 0.09 | K83: 0.09 | L83: 0.09 | M83: 0.09 | N83: 0.09 | O83: 0.09 | P83: 0.09 | Q83: 0.09 | R83: 0.09 | S83: 0.09 | T83: 0.09 | U83: 0.09 | V83: 0.09 | W83: 0.09 | X83: 0.09 | Y83: 0.09 | Z83: 0.09 | AB83: 10-Q 2Q26: effective rates 9-11% (DDTLs 9-15%, notes 9-10%, DDTL 4.0 7%, converts 2%). 1H26 interest 1,176 / average debt ~29bn = 8.1% + capitalised. UBS: every 100bp = ~$30m/quarter.
C84: Diluted shares for EPS (m, year average) | G84: 603.4 | H84: 603.4 | I84: 603.4 | J84: 603.4 | K84: 603.4 | L84: 603.4 | M84: 603.4 | N84: 603.4 | O84: 603.4 | P84: 603.4 | Q84: 603.4 | R84: 603.4 | S84: 603.4 | T84: 603.4 | U84: 603.4 | V84: 603.4 | W84: 603.4 | X84: 603.4 | Y84: 603.4 | Z84: 603.4 | AB84: 603.4 flat: no ATM, net SBC dilution ~1%/year ignored. The 2032 convert only dilutes above ~$200 (capped call).
C86: Method: revenue = average billable power (prior YE + (0.5 − lag) x adds; 2026 from the quarterly build) x revenue per GW. EBITDA = revenue x margin. D&A = average active power x D&A/GW. FCFF = (EBITDA − D&A − SBC) x (1 − tax) + D&A − capex − change in NWC.
C87: Capex = growth [build cost x ((1 − pre-build) x adds of the year + pre-build x adds of the next year)] + replacement [power installed in t−life (adds AND prior replacements) x build cost x replacement % — at steady state replacement ≈ fleet ÷ life]. 2023-25 = reported cash capex; 2026 = guide (midpoint).
C88: Terminal: NOPAT x (1 + g) x (1 − g / ROIC). End-of-year discounting; CY26 pro rata for the days after the valuation date. Net debt = principal + finance leases − unrestricted cash (30-Jun-26).
C89: GW bases: ALL CoreWeave power is critical IT load (UBS 09-22) — never compare with facility GW (10-25% larger; Galaxy Helios 526 MW IT = 800 MW gross). Revenue/GW, build cost/GW and D&A/GW are three different bases — never net them.
C90: Primary sources: 10-K FY25 (2026-03-02), 10-Qs 1Q25-2Q26, calls 2Q25-2Q26 (CRWV/transcripts), BTG Pactual websession with Nick Robbins 2026-09-21 (Capstone notes). Sell-side: UBS 09-22, JPM 09-24, Arete 08-21, Bernstein 07-01/09-24, DB 2025-06-16, Redburn 09-21. BBG consensus 2026-10-13.

Sheet History
C2: CRWV | Reported history (annual and quarterly)
C3: US$ millions unless stated. Source: 10-K FY25, 10-Qs 1Q25-2Q26 (CRWV/), earnings calls (CRWV/transcripts). Blue = reported; derived/PARTIAL noted in the source column.
D5: FY23 | E5: FY24 | F5: FY25 | G5: 1Q25 | H5: 2Q25 | I5: 3Q25 | J5: 4Q25 | K5: 1Q26 | L5: 2Q26 | N5: Source
C7: Income statement and cash flow
C8: Revenue | D8: 229 | E8: 1915 | F8: 5131 | G8: 981.6 | H8: 1212.8 | I8: 1364.7 | J8: 1571.9 | K8: 2078 | L8: 2575 | N8: 10-K FY25; 10-Qs (1Q25-3Q25 in US$ thousands, converted); 4Q25 = FY − 9M.
C9: Cost of revenue | D9: 69 | E9: 493 | F9: 1453 | G9: 262.4 | H9: 312.7 | I9: 368.8 | J9: 509.1 | K9: 716 | L9: 879 | N9: Same.
C10: Technology and infrastructure | D10: 131 | E10: 961 | F10: 2929 | G10: 561.4 | H10: 669.9 | I10: 747.5 | J10: 950.2 | K10: 1273 | L10: 1507 | N10: Same (includes DC rent, power, D&A).
C11: Sales and marketing | D11: 13 | E11: 18 | F11: 144 | G11: 10.5 | H11: 36.8 | I11: 44.6 | J11: 52 | K11: 69 | L11: 60 | N11: Same.
C12: General and administrative | D12: 30 | E12: 119 | F12: 651 | G12: 174.8 | H12: 174.2 | I12: 151.9 | J12: 150.2 | K12: 164 | L12: 178 | N12: Same.
C13: GAAP operating income | D13: -14 | E13: 324 | F13: -46 | G13: -27.5 | H13: 19.2 | I13: 51.9 | J13: -89.6 | K13: -144 | L13: -49 | N13: Same.
C14: Net interest expense | D14: -28 | E14: -361 | F14: -1229 | G14: -263.8 | H14: -267.2 | I14: -311 | J14: -387 | K14: -536 | L14: -640 | N14: Same; 3Q25 call ($311m).
C15: GAAP net income | D15: -594 | E15: -863 | F15: -1167 | G15: -314.6 | H15: -290.5 | I15: -110.1 | J15: -451.8 | K15: -740 | L15: -626 | N15: Same.
C16: Depreciation and amortization | D16: 103 | E16: 863 | F16: 2454 | G16: 443.5 | H16: 559.5 | I16: 630.5 | J16: 820.5 | K16: 1147 | L16: 1393 | N16: Cash-flow YTD figures differenced by quarter.
C17: Stock-based compensation | D17: 15 | E17: 31 | F17: 630 | G17: 184 | H17: 145 | I17: 144.4 | J17: 156.6 | K17: 153 | L17: 165 | N17: Cash-flow YTD differenced (9M25 473.4): 3Q 144.4 / 4Q 156.6 (the statement of equity shows 156.9 in 3Q — different basis).
C18: Cash capex (purchase of PP&E) | D18: 2943 | E18: 8702 | F18: 10309 | G18: 1407 | H18: 2453 | I18: 2389 | J18: 4060 | K18: 7695 | L18: 6422 | N18: Cash-flow YTD differenced.
C19: Capex, company basis (calls) | K19: 6800 | L19: 9400 | N19: Calls 1Q26 (05-07) and 2Q26 (08-11). FY26 guide $35-39bn. Includes OEM financing; differs from cash.
C20: Adjusted EBITDA (company) | E20: 1226 | F20: 3098 | G20: 609 | H20: 753 | I20: 838 | J20: 898 | K20: 1164 | L20: 1510 | N20: Calls; FY24 = 64% (DB 2025-06-16) PARTIAL; 1Q26 = '$1.2bn, ~56%' x 2,078 = 1,164 PARTIAL; 1Q25 = 1,164/1.91 ('+91% y/y') PARTIAL.
C21: Adjusted EBITDA margin | E21: =E20/E8 -> 0.64020888 | F21: =F20/F8 -> 0.60378094 | G21: =G20/G8 -> 0.62041565 | H21: =H20/H8 -> 0.62087731 | I21: =I20/I8 -> 0.61405437 | J21: =J20/J8 -> 0.57128316 | K21: =K20/K8 -> 0.56015399 | L21: =L20/L8 -> 0.58640777 | N21: Calculated.
C22: AOI (adjusted operating income, company) | H22: 200 | I22: 217 | K22: 21 | L22: 128 | N22: Calls: 2Q25 $200m (cited on the 2Q26 call, 08-11), 3Q25 $217m, 1Q26 $21m, 2Q26 $128m. FY25 guide $690-720m (3Q25 call).
C23: Operating and balance sheet
C24: Active power at period-end (MW) | D24: 70 | E24: 360 | F24: 850 | G24: 420 | H24: 470 | I24: 590 | J24: 850 | K24: 1000 | L24: 1500 | N24: 10-K FY25 (70 / 360 / >850); calls (3Q25 590 = +120 q/q → 2Q25 470; 1Q25 ~420 ESTIMATE; 1Q26 '>1 GW'; 2Q26 1.5 GW).
C25: Contracted power at period-end (MW) | F25: 3100 | I25: 2900 | J25: 3100 | K25: 3500 | L25: 3700 | N25: Calls; 4.2 GW as of 11-Aug-26.
C26: Revenue backlog (company, US$ bn) | E26: 15.1 | F26: 66.8 | H26: 30.1 | I26: 55.6 | J26: 66.8 | K26: 99.4 | L26: 104 | N26: Calls (2Q25 'doubled YTD' → Dec-24 ~15.1 PARTIAL). RPO 10-K/10-Q: 60.7 (Dec-25) / 103.7 (Jun-26).
C27: Total deferred revenue (US$ m) | E27: 4064 | F27: 8185 | J27: 8185 | L27: 9692 | N27: Balance sheets.
C28: Unrestricted cash (US$ m) | D28: 217 | E28: 1361 | F28: 3127 | J28: 3127 | L28: 5524 | N28: Balance sheets.
C29: Gross debt, principal (US$ m) | E29: 7926 | F29: 21615 | J29: 21615 | L29: 35551 | N29: Debt notes (Dec-24 carrying value).
C30: Weighted diluted shares (m) | D30: 192 | E30: 218 | F30: 436 | H30: 487 | L30: 551 | N30: 10-K / 10-Q (post 20:1 split).
C32: Calibration | annualised quarterly revenue ÷ average active power of the PRIOR quarter (US$ bn / GW-year)
C33: Average active power of the prior quarter (MW) | H33: =(E24+G24)/2 -> 390 | I33: =(G24+H24)/2 -> 445 | J33: =(H24+I24)/2 -> 530 | K33: =(I24+J24)/2 -> 720 | L33: =(J24+K24)/2 -> 925 | N33: Prior quarter = average of the end of the quarter before last and the end of the prior quarter (2Q25 uses Dec-24 360 and 1Q25 ~420 ESTIMATE). 1Q25 omitted (3Q24 not reported). Basis UBS 09-22 ('about a quarter for active power to generate revs'); 2Q26 = 2,575 x 4 / 925 = 11.1 = UBS.
C34: Revenue per billable GW (US$ bn / GW-year) | H34: =H8*4/H33 -> 12.438974 | I34: =I8*4/I33 -> 12.266966 | J34: =J8*4/J33 -> 11.863396 | K34: =K8*4/K33 -> 11.544444 | L34: =L8*4/L33 -> 11.135135 | N34: Falls from ~12.4 (2Q25) to ~11.1 (2Q26): the fleet scaled faster than the average price (legacy MSFT/OpenAI book). UBS: ~11 → ~15 at the 2027 exit. Anchor of the model (cover row 12).
C35: Annualised D&A ÷ average active power of the quarter (US$ bn / GW-year) | H35: =H16*4/((G24+H24)/2) -> 5.0292135 | I35: =I16*4/((H24+I24)/2) -> 4.7584906 | J35: =J16*4/((I24+J24)/2) -> 4.5583333 | K35: =K16*4/((J24+K24)/2) -> 4.96 | L35: =L16*4/((K24+L24)/2) -> 4.4576 | N35: Anchor of D&A per GW (cover): ~4.5-5.0.
C36: Annualised interest ÷ period-end gross debt (memo) | J36: =-J14*4/J29 -> 0.071616933 | L36: =-L14*4/L29 -> 0.072009226 | N36: 4Q25 ~7.2% and 2Q26 ~7.2% on END-of-period principal (debt grew during the period; capitalised interest excluded) — contractual effective rates 9-11%.

Sheet Debt
C2: CRWV | Debt (10-Q 2Q26, note 10 — principal, US$ millions)
C3: Source: CRWV/CRWV_10-Q_2026-08-12 note 10 (total debt obligations; future principal payments). Rates = 'effective interest rates' from the table.
C5: Type | D5: Instrument | E5: Maturity | F5: Effective rate | G5: 30-Jun-2026 | H5: 31-Dec-2025
C6: Recourse | D6: DDTL 1.0 Facility | E6: Mar-2028 | F6: 0.15 | G6: 1300 | H6: 1553
C7: Recourse | D7: DDTL 2.0 Facility | E7: Aug-2030 | F7: 0.11 | G7: 3190 | H7: 5037
C8: Recourse | D8: DDTL 2.1 Facility | E8: Mar-2031 | F8: 0.09 | G8: 3000 | H8: 2741
C9: Recourse | D9: DDTL 3.0 Facility | E9: Aug-2030 | F9: 0.09 | G9: 2215 | H9: 340
C10: Recourse | D10: DDTL 5.0 Facility (SOFR + 4.50%, May-26) | E10: Nov-2031 | F10: 0.09 | G10: 1101 | H10: 0
C11: Recourse | D11: 2030 Senior Notes (9.25%) | E11: Jun-2030 | F11: 0.1 | G11: 2000 | H11: 2000
C12: Recourse | D12: 2031 9.00% Senior Notes | E12: Feb-2031 | F12: 0.1 | G12: 1750 | H12: 1750
C13: Recourse | D13: 2031 9.75% Senior Notes (Apr-26) | E13: Oct-2031 | F13: 0.1 | G13: 2750 | H13: 0
C14: Recourse | D14: 2032 9.625% Senior Notes (Jun-26) | E14: Jul-2032 | F14: 0.1 | G14: 1250 | H14: 0
C15: Recourse | D15: 2032 EUR Senior Notes (8.50%, EUR 2.0bn, swapped to US$) | E15: Jul-2032 | F15: 0.09 | G15: 2279 | H15: 0
C16: Recourse | D16: 2031 Convertible Senior Notes (1.75%) | E16: Dec-2031 | F16: 0.02 | G16: 2588 | H16: 2588
C17: Recourse | D17: 2032 Convertible Senior Notes (1.75%; conv. $119.60; cap call $230) | E17: Oct-2032 | F17: 0.02 | G17: 4000 | H17: 0
... C23: Non-recourse | D23: OEM and Software License Financing Arrangements | E23: Aug-26 to Aug-28 | F23: 0.09 | G23: 882 | H23: 647
D24: Total principal (recourse + non-recourse) | G24: =SUM(G6:G23) -> 35551 | H24: =SUM(H6:H23) -> 21615
D25: Weighted-average effective rate (Jun-26) | G25: =SUMPRODUCT(F6:F23,G6:G23)/G24 -> 0.084134342
D26: Check: note total = 35,551 (Jun-26) / 21,615 (Dec-25) | G26: =G24-35551 -> 0 | H26: =H24-21615 -> 0
D27: Less: unamortized discount and issuance costs (Jun-26: 427 + 56) | G27: -483
D28: Carrying value (recourse 31,405 + non-recourse 3,663 = 35,068) | G28: =G24+G27 -> 35068
D30: Principal amortization (Jun-26) | G30: US$ m
D31: Remainder of 2026 | G31: 4413
D32: 2027 | G32: 6184
D33: 2028 | G33: 4416
D34: 2029 | G34: 2421
D35: 2030 | G35: 3221
D36: Thereafter | G36: 14896
D37: Total | G37: =SUM(G31:G36) -> 35551
D39: 2Q26 interest: contractual 592 + discount amortization 45 − capitalised 79 = 558 (note 10); 'interest expense, net' on the P&L = 640. 3Q26 guide: $860-940m. 1H26 cash paid 806.
D40: Operating leases (Jun-26): PV 16,319 (10% rate, 12 years); future payments 29,135; not yet commenced 35,500 (a single site = 14,700, 393 MW to be delivered). Rent sits in EBITDA — do not add to debt.
D41: DDTL spreads (Redburn 09-21, Fig 70): S+962 (Jul-23), +425 (Sep-24), +400 (OpenAI, Jul-25), +225 (Meta, Mar-26), +450 (non-IG, May-26), +550 (Aug-26, $2.6bn DDTL 5.5, Sep-31). Term loan S+550 yields 9.15% (MS Credit 08-20).
D42: Capital raised: >$32bn of debt + equity through 2Q26 (call 08-11); WACD −300bp in 12 months (~$1.1bn/year of interest). S&P B+ positive (Apr-26). ATM registered, 'not at these prices' (Robbins 09-21).
D43: 2031 convert: 9.2764 shares per $1,000 (conv. $107.80; capped call strike 107.80 / cap 215.60 — 10-K FY25). 2032 convert: 8.3612 shares per $1,000 (conv. $119.60); capped calls cost 492m, strike 119.60 / cap 230. Management: effective strike ~$200. Both treated as debt in the model (out of the money at $77.81).
D44: Subsequent events (10-Q 2Q26 note 16): Aug-26 $2.6bn DDTL 5.5 (JPMorgan agent; SOFR+550, matures Sep-31) and a $1.2bn draw on the Revolving Credit Facility — NOT in the model's 30-Jun-26 net debt (the draw funds 2H26 capex already discounted in the FCFF).
