Workbook

Sheet Assumptions
A1: AAOI — Bottoms-up revenue model · Assumptions
A2: Units $000s. Tag colors: GREEN=HARD (filing/guide) · BLUE=PARTIAL/ANCHOR (directional mgmt color) · AMBER=ESTIMATE (calibrated to observed growth). BBG asof 2026-07-01, px $139.
A4: Segment / Qtr | B4: Value ($000s) | C4: Tag | D4: Basis / Source (+date)
A5: Q1-26 Data Center | B5: 81404 | C5: HARD | D5: 10-Q Q1'26 Note3 "major product categories" (2026-05-07)
A6: Q1-26 CATV | B6: 66841 | C6: HARD | D6: 10-Q Q1'26 Note3 (2026-05-07)
A7: Q1-26 Telecom | B7: 2559 | C7: HARD | D7: 10-Q Q1'26 Note3 (2026-05-07)
A8: Q1-26 Other/FTTH | B8: 340 | C8: HARD | D8: 10-Q Q1'26 Note3 (2026-05-07)
A9: Q4-25 Data Center | B9: 74876 | C9: HARD | D9: Derived: FY25 10-K market table (195,651) - 9M'25 10-Q (120,775); (2026-02-26 / 2025-11-06)
A10: Q4-25 CATV | B10: 54002 | C10: HARD | D10: Derived: FY25 10-K (245,124) - 9M'25 (191,123)
A11: Q4-25 Telecom | B11: 5110 | C11: HARD | D11: Derived: FY25 10-K (13,729) - 9M'25 (8,618)
A12: Q4-25 Other/FTTH | B12: 286 | C12: HARD | D12: Derived: FY25 10-K (1,211) - 9M'25 (925)
A13: Q2-26 Total (guide mid) | B13: 189000 | C13: HARD | D13: Q1'26 call: Q2 rev $180-198M, midpoint (2026-05-07)
A14: Q2-26 CATV (guide mid) | B14: 77500 | C14: HARD | D14: Q1'26 call: Q2 CATV $75-80M, midpoint (2026-05-07)
A15: Q2-26 Telecom | B15: 3000 | C15: EST | D15: Lumpy; ~trailing avg, mgmt "fluctuates q/q" (Q1'26)
A16: Q2-26 Other/FTTH | B16: 300 | C16: EST | D16: ~trailing avg
... A27: FY27 Telecom / Other | B27: 13500 | C27: EST | D27: FY combined, lumpy

Sheet Model
A1: AAOI — Quarterly revenue build ($000s) · last 4 actual + 4 forecast
A2: Actuals (green) tie to reported total. Forecast cols use live formulas off Assumptions growth rates. A=Actual, F=Forecast.
A4: Segment | B4: Q2-25 (A) | C4: Q3-25 (A) | D4: Q4-25 (A) | E4: Q1-26 (A) | F4: Q2-26 (F) | G4: Q3-26 (F) | H4: Q4-26 (F) | I4: FY26 | J4: FY27 (F)
A5: Data Center | B5: 44791 | C5: 43935 | D5: 74876 | E5: 81404 | F5: =189000-F6-F7-F8 -> 108200 | G5: =F5*(1+0.6) -> 173120 | H5: =G5*(1+0.5) -> 259680 | I5: =E5+F5+G5+H5 -> 622404 | J5: =H5*(1.3)+H5*1.3*1.25+H5*1.3*1.25*1.2+H5*1.3*1.25*1.2*1.15 -> 1848272.4
A6: CATV | B6: 56019 | C6: 70602 | D6: 54002 | E6: 66841 | F6: 77500 | G6: 88000 | H6: 90000 | I6: =E6+F6+G6+H6 -> 322341 | J6: 380000
A7: Telecom | B7: 1940 | C7: 3742 | D7: 5110 | E7: 2559 | F7: 3000 | G7: 3000 | H7: 3000 | I7: =E7+F7+G7+H7 -> 11559 | J7: 10000
A8: Other/FTTH | B8: 202 | C8: 351 | D8: 286 | E8: 340 | F8: 300 | G8: 300 | H8: 300 | I8: =E8+F8+G8+H8 -> 1240 | J8: 3500
A9: TOTAL | B9: =SUM(B5:B8) -> 102952 | C9: =SUM(C5:C8) -> 118630 | D9: =SUM(D5:D8) -> 134274 | E9: =SUM(E5:E8) -> 151144 | F9: =SUM(F5:F8) -> 189000 | G9: =SUM(G5:G8) -> 264420 | H9: =SUM(H5:H8) -> 352980 | I9: =SUM(I5:I8) -> 957544 | J9: =SUM(J5:J8) -> 2241772.4
A11: Reported total (guardrail) | B11: 102952 | C11: 118630 | D11: 134274 | E11: 151144
A12: Tie-out (model - reported) | B12: =B9-B11 -> 0 | C12: =C9-C11 -> 0 | D12: =D9-D11 -> 0 | E12: =E9-E11 -> 0
A14: DC q/q growth % | F14: =F5/E5-1 -> 0.32917301 | G14: =G5/F5-1 -> 0.6 | H14: =H5/G5-1 -> 0.5

Sheet vs Consensus
A1: AAOI — Bottoms-up vs BBG consensus (BEST_SALES)
A2: BBG estimates.json asof 2026-07-01. $000s. Positive delta = above Street.
A4: Period | B4: My bottoms-up | C4: BBG consensus | D4: $ delta | E4: % delta | F4: Note
A5: Q2-26 | B5: =Model!F9 -> 189000 | C5: 189333 | D5: =B5-C5 -> -333 | E5: =B5/C5-1 -> -0.0017588059 | F5: In line — I anchor mgmt guide midpoint; Street ~= same
A6: Q3-26 | B6: =Model!G9 -> 264420 | C6: 273000 | D6: =B6-C6 -> -8580 | E6: =B6/C6-1 -> -0.031428571 | F6: -3% — Street models near TOP of mgmt +60-80% q/q band; I use +60% low end
A7: Q4-26 | B7: =Model!H9 -> 352980 | C7: n/a | F7: No discrete Q4 BBG in snapshot; implied by CY26
A8: CY2026 | B8: =Model!I9 -> 957544 | C8: 1022500 | D8: =B8-C8 -> -64956 | E8: =B8/C8-1 -> -0.06352665 | F8: -6% vs Street; -13% vs mgmt >1.1B guide. Gap is TWO stacked haircuts: (1) applying mgmt literal 60-80%/qtr language - stated for TOTAL company revenue - to the Data Center segment ONLY, and (2) using the low end (60%). Segment re-basing (not just low-end-of-range) is the dominant driver (~70% of gap); re-basing mgmt rate to total revenue would land ~1,126M, at guide. Both deliberate: CATV is capacity-constrained and will not grow 60%.
A9: CY2027 | B9: =Model!J9 -> 2241772.4 | C9: 2484000 | D9: =B9-C9 -> -242227.6 | E9: =B9/C9-1 -> -0.097515137 | F9: -10% vs Street. I do NOT underwrite $471M/mo mid-27 DC marquee ($5.65B annualized)
A12: SENSITIVITY — DC ramp is the load-bearing input
A13: Scenario | B13: FY26 total | C13: FY27 total | D13: Comment
A14: DC ramp -25% | B14: 897000 | C14: 2007000 | D14: Slippage / lumpy qual: H2-26 q/q +45%/+38%; FY27 ramp -25%
A15: Base | B15: 958000 | C15: 2242000 | D15: H2-26 DC +60%/+50%; FY27 DC +30/25/20/15%
A16: DC ramp +25% | B16: 1022000 | C16: 2501000 | D16: ~ Street. H2-26 +75%/+62%. Consensus effectively prices the high end
A18: FY26 swing on +/-25% DC ramp: ~+/-$63M (6.5% of FY26). FY27 swing: ~+/-$250M (11% of FY27).
A20: BBG context | B20: Consensus MEAN (1,022.5M) is itself already BELOW the >1.1B guide, and even the Street HIGH (1,122.5M) only just clears it - so our below-guide stance is directionally consistent with where the Street already sits, not an outlier view.

Sheet Sources
A1: AAOI — Sources (every number tied to a filing/transcript/consensus snapshot)
A3: Source | B3: Date | C3: What was pulled
A4: 10-Q Q1'26 (Note 3 "major product categories") | B4: 2026-05-07 | C4: Q1-26 seg actuals: DC 81,404 / CATV 66,841 / Tel 2,559 / Other 340 = 151,144; DC sub-mix 100G41%/200-400G46.7%/800G5.6%; 800G=$4.6M
A5: 10-Q Q3'25 | B5: 2025-11-06 | C5: 9M'25 seg: CATV 191,123 / DC 120,775 / Tel 8,618 / Other 925 = 321,441 (used to derive Q4-25)
A6: 10-Q Q2'25 | B6: 2025-08-07 | C6: Q2-25 seg actuals; CATV FY26 target $300-350M; 800G "late Q3/Q4 2025"
A7: 10-Q Q1'25 | B7: 2025-05-08 | C7: Q1-25 seg actuals: CATV 64,501 / DC 32,049 / Tel 2,937 / Other 372
A8: 10-K FY25 (market revenue table) | B8: 2026-02-26 | C8: FY25 seg: CATV 245,124 / DC 195,651 / Tel 13,729 / FTTH+Oth 1,211 = 455,715; top-10 = 96.6% of rev
A9: Transcript Q1'26 earnings call | B9: 2026-05-07 | C9: Q2 guide $180-198M, GM 29-30%; Q2 CATV $75-80M; FY26 >$1.1B / >$140M op inc; Q3&Q4 +60-80% q/q step-function; 800G ~4x Q1 units in Q2; mid-27 $471M/mo DC ($90/$217/$164 by speed); FY CATV >$325M
A10: Transcript Q4'25 earnings call | B10: 2026-02-26 | C10: FY26 ~$1.0B (then), 800G <$4M slipped to Q1 (firmware); Q2'26 800G ">$25-30M"; DC ~$700M implied / CATV ~$300M; 3 >10% hyperscalers; $378M/mo mid-27 (later raised to $471M)
A11: Transcript Q2'25 earnings call | B11: 2025-08-07 | C11: Q2-25 $103M; GM 30.4%; CapEx FY $120-150M; CATV FY26 $300-350M
A12: Transcript Q2'24 earnings call | B12: 2024-08-06 | C12: Q2-24 $43.3M; DC 79% mix; Q3 guide $60-66M; 40% GM long-term goal
A13: BBG estimates.json (companies.AAOI) | B13: 2026-07-01 | C13: Consensus BEST_SALES: Q2-26 189.3M, Q3-26 273M, CY26 1,022.5M, CY27 2,484M; px $139; mktcap $11.15bn; GM CY26 31.3%/CY27 34.9%
A14: Wiki page AAOI.md | B14: 2026-06-18 | C14: Thesis/debate context; flagged as FinTwit-driven volatile small-cap — used for framing, not as a number source
