Workbook

Sheet Assumptions
A1: CSCO — Bottoms-up Revenue Model — Assumptions
A2: Capstone buy-side · built 2026-07-01 · USD millions · fiscal year ends late July
A4: Tag legend: | B4: HARD (filing/guidance/mgmt) | C4: PARTIAL/ANCHOR | D4: ESTIMATE
A6: INPUT | B6: VALUE | C6: TAG | D6: SOURCE / NOTE
A7: — Reported guidance (HARD) —
A8: Q4 FY26 revenue guide low | B8: 16700 | C8: HARD | D8: Q3 FY26 call, Patterson, 2026-05-13
A9: Q4 FY26 revenue guide high | B9: 16900 | C9: HARD | D9: Q3 FY26 call, 2026-05-13
A10: Q4 FY26 revenue guide midpoint | B10: 16800 | C10: HARD | D10: midpoint of guide
A11: FY26 revenue guide low | B11: 62800 | C11: HARD | D11: Q3 FY26 call, 2026-05-13
A12: FY26 revenue guide high | B12: 63000 | C12: HARD | D12: Q3 FY26 call, 2026-05-13
A13: FY26 revenue guide midpoint | B13: 62900 | C13: HARD | D13: midpoint of guide
A14: FY26 9-month actual revenue | B14: 46073 | C14: HARD | D14: 10-Q 2026-05-19 (Q1+Q2+Q3 FY26)
A15: Q4 FY26 implied by FY26 guide mid | B15: =B13-B14 -> 16827 | C15: HARD | D15: FY26 mid 62,900 - 9mo 46,073 = 16,827
A16: — AI-hyperscaler revenue (HARD FY anchors; quarterly split = ANCHOR) —
A17: FY26 hyperscaler AI revenue (total) | B17: 4000 | C17: HARD | D17: $4B FY26 - Robbins (CEO), prepared remarks, Q3 FY26 call 2026-05-13
A18: FY27 hyperscaler AI revenue (floor) | B18: 6000 | C18: HARD | D18: >=$6B FY27 - Patterson, Q&A, same call (stated FLOOR: at least $6B)
A19: AI rev Q1 FY26 | B19: 600 | C19: ANCHOR | D19: ramp split; FY sum tied to HARD 4,000
A20: AI rev Q2 FY26 | B20: 900 | C20: ANCHOR | D20: nonlinear ramp; Q2 orders $2.1B
A21: AI rev Q3 FY26 | B21: 1100 | C21: ANCHOR | D21: nonlinear ramp; Q3 orders $1.9B
A22: AI rev Q4 FY26 (plug to 4,000) | B22: 1400 | C22: ANCHOR
A23: AI rev Q1 FY27E | B23: 1350 | C23: EST | D23: FY27 ramp; sums to 6,000 floor
A24: AI rev Q2 FY27E | B24: 1500 | C24: EST | D24: FY27 ramp
A25: AI rev Q3 FY27E | B25: 1550 | C25: EST | D25: FY27 ramp
A26: AI rev Q4 FY27E (out of horizon) | B26: 1600 | C26: EST | D26: FY27 ramp; completes 6,000
A27: — Core-segment YoY growth (FY27E) —
A28: Core Networking (ex-AI-hyper) YoY | B28: 0.055 | C28: EST | D28: campus refresh + DC switching; vs 2-5% LT frame (Inv Day 2024)
A29: Security YoY | B29: 0.03 | C29: EST | D29: Splunk cloud drag easing; exit-FY26 near dbl-digit organic (Q3 FY26)
A30: Collaboration YoY | B30: -0.01 | C30: EST | D30: Webex decline vs device growth (Q3 FY26 call)
A31: Observability YoY | B31: 0.05 | C31: EST | D31: Splunk-adjacent; FY25 +26% decelerating (10-K 2025-09-03)
A32: Services YoY | B32: 0.02 | C32: EST | D32: 2-4% LT frame; contract-start timing (Q3 FY26 call)

Sheet Model
A1: CSCO — Quarterly Revenue Build ($M) — Model
A2: Actuals HARD (tie to reported). Forecast = core-segment YoY + AI-hyperscaler ramp (HARD FY anchors). Yellow = forecast.
A4: Line ($M) | B4: Q3 FY25 | C4: Q4 FY25 | D4: Q1 FY26 | E4: Q2 FY26 | F4: Q3 FY26 | G4: Q4 FY26E | H4: Q1 FY27E | I4: Q2 FY27E | J4: Q3 FY27E
A5: Period end | B5: 2025-04-26 | C5: 2025-07-26 | D5: 2025-10-25 | E5: 2026-01-24 | F5: 2026-04-25 | G5: 2026-07-25 | H5: 2026-10-24 | I5: 2027-01-23 | J5: 2027-04-24
A6: AI-hyperscaler revenue (within Networking) | B6: 0 | C6: 0 | D6: =Assumptions!B19 -> 600 | E6: =Assumptions!B20 -> 900 | F6: =Assumptions!B21 -> 1100 | G6: =Assumptions!B22 -> 1400 | H6: =Assumptions!B23 -> 1350 | I6: =Assumptions!B24 -> 1500 | J6: =Assumptions!B25 -> 1550
A7: Networking — core (ex-AI-hyper) | B7: =B8-B6 -> 7068 | C7: =C8-C6 -> 7633 | D7: =D8-D6 -> 7168 | E7: =E8-E6 -> 7394 | F7: =F8-F6 -> 7715 | G7: =Assumptions!B15-G6-G9-G10-G11-G13 -> 8250.17 | H7: =D7*(1+Assumptions!B28) -> 7562.24 | I7: =E7*(1+Assumptions!B28) -> 7800.67 | J7: =F7*(1+Assumptions!B28) -> 8139.325
A8: Networking — TOTAL | B8: 7068 | C8: 7633 | D8: 7768 | E8: 8294 | F8: 8815 | G8: =G6+G7 -> 9650.17 | H8: =H6+H7 -> 8912.24 | I8: =I6+I7 -> 9300.67 | J8: =J6+J7 -> 9689.325
A9: Security | B9: 2013 | C9: 1952 | D9: 1980 | E9: 2018 | F9: 2008 | G9: =C9*(1+Assumptions!B29) -> 2010.56 | H9: =D9*(1+Assumptions!B29) -> 2039.4 | I9: =E9*(1+Assumptions!B29) -> 2078.54 | J9: =F9*(1+Assumptions!B29) -> 2068.24
A10: Collaboration | B10: 1031 | C10: 1042 | D10: 1055 | E10: 1054 | F10: 1024 | G10: =C10*(1+Assumptions!B30) -> 1031.58 | H10: =D10*(1+Assumptions!B30) -> 1044.45 | I10: =E10*(1+Assumptions!B30) -> 1043.46 | J10: =F10*(1+Assumptions!B30) -> 1013.76
A11: Observability | B11: 261 | C11: 259 | D11: 274 | E11: 277 | F11: 269 | G11: =C11*(1+Assumptions!B31) -> 271.95 | H11: =D11*(1+Assumptions!B31) -> 287.7 | I11: =E11*(1+Assumptions!B31) -> 290.85 | J11: =F11*(1+Assumptions!B31) -> 282.45
A12: Total Product | B12: =B8+B9+B10+B11 -> 10373 | C12: =C8+C9+C10+C11 -> 10886 | D12: =D8+D9+D10+D11 -> 11077 | E12: =E8+E9+E10+E11 -> 11643 | F12: =F8+F9+F10+F11 -> 12116 | G12: =G8+G9+G10+G11 -> 12964.26 | H12: =H8+H9+H10+H11 -> 12283.79 | I12: =I8+I9+I10+I11 -> 12713.52 | J12: =J8+J9+J10+J11 -> 13053.775
A13: Services | B13: 3775 | C13: 3787 | D13: 3806 | E13: 3707 | F13: 3724 | G13: =C13*(1+Assumptions!B32) -> 3862.74 | H13: =D13*(1+Assumptions!B32) -> 3882.12 | I13: =E13*(1+Assumptions!B32) -> 3781.14 | J13: =F13*(1+Assumptions!B32) -> 3798.48
A14: TOTAL REVENUE (bottoms-up) | B14: =B12+B13 -> 14148 | C14: =C12+C13 -> 14673 | D14: =D12+D13 -> 14883 | E14: =E12+E13 -> 15350 | F14: =F12+F13 -> 15840 | G14: =G12+G13 -> 16827 | H14: =H12+H13 -> 16165.91 | I14: =I12+I13 -> 16494.66 | J14: =J12+J13 -> 16852.255
A15: Reported / Guide-implied total (check) | B15: 14149 | C15: 14673 | D15: 14883 | E15: 15349 | F15: 15841 | G15: =Assumptions!B15 -> 16827
A16: Tie-out variance ($M) | B16: =B14-B15 -> -1 | C16: =C14-C15 -> 0 | D16: =D14-D15 -> 0 | E16: =E14-E15 -> 1 | F16: =F14-F15 -> -1 | G16: =G14-G15 -> 0
A19: FISCAL-YEAR TOTALS ($M)
A20: FY26 total (Q1+Q2+Q3 act + Q4E) | B20: =D14+E14+F14+G14 -> 62900
A21: o/w Networking FY26 | B21: =D8+E8+F8+G8 -> 34527.17
A22: o/w AI-hyperscaler rev FY26 (HARD ~4,000) | B22: =D6+E6+F6+G6 -> 4000

Sheet vs Consensus
A1: CSCO — Bottoms-up vs BBG Consensus (BEST_SALES)
A2: BBG consensus asof 2026-07-01 (estimates.json companies.CSCO). Bottoms-up linked to Model tab. $M.
A4: Period | B4: Bottoms-up ($M) | C4: BBG consensus ($M) | D4: Variance $ | E4: Variance % | F4: Note
A5: Q4 FY26E (next FQ) | B5: =Model!G14 -> 16827 | C5: 16838.6 | D5: =B5-C5 -> -11.6 | E5: =(B5-C5)/C5 -> -0.00068889338 | F5: BBG 1FQ; BU ties to FY26 guide-implied $16.83B
A6: Q1 FY27E | B6: =Model!H14 -> 16165.91 | C6: 16802.1 | D6: =B6-C6 -> -636.19 | E6: =(B6-C6)/C6 -> -0.037863719 | F6: BBG 2FQ
A7: CY2026 (Jan+Apr+Jul+Oct qtrs) | B7: =Model!E14+Model!F14+Model!G14+Model!H14 -> 64182.91 | C7: 66156.35 | D7: =B7-C7 -> -1973.44 | E7: =(B7-C7)/C7 -> -0.029829941 | F7: CY sum, fiscal snapped to nearest CY qtr
A8: CY2027 (beyond horizon) | B8: n/a — horizon ends Q3 FY27E (Apr'27) | C8: 70806.7 | F8: Model horizon = next 4 FQ; CY27 not fully covered
A9: FY26 (fiscal Aug'25-Jul'26) | B9: =Model!D14+Model!E14+Model!F14+Model!G14 -> 62900 | C9: 62900 | D9: =B9-C9 -> 0 | E9: =(B9-C9)/C9 -> 0 | F9: vs FY26 guide mid $62.9B (HARD)

Sheet Sensitivity
A1: CSCO — Sensitivity on load-bearing ESTIMATE inputs
A2: Two most sensitive inputs: (1) FY27 AI-hyperscaler revenue; (2) Core-Networking YoY. ±25% each. FY27 base ~$71B.
A4: Input | B4: Base | C4: -25% | D4: +25% | E4: FY27 rev basis
A5: FY27 AI-hyperscaler revenue (HARD floor) | B5: $6.0B | C5: $4.5B | D5: $7.5B | E5: direct $ to Networking/total
A6: -> FY27 total-rev impact vs base | B6: — | C6: -$1.5B (-2.1%) | D6: +$1.5B (+2.1%) | E6: on ~$71B FY27 base
A7: Core-Networking YoY growth (FY27E) | B7: 5.5% | C7: 4.1% | D7: 6.9% | E7: ~$27B core-Net base
A8: -> FY27 total-rev impact vs base | B8: — | C8: -$0.37B (-0.5%) | D8: +$0.37B (+0.5%) | E8: 0.25*5.5%*27B
A9: COMBINED both -25% (downside) | B9: — | C9: -$1.87B (-2.6%)
A10: COMBINED both +25% (upside) | B10: — | D10: +$1.87B (+2.6%)
A12: Conclusion: AI-hyperscaler ramp is the dominant swing (~4x the core-Networking sensitivity).
A13: FLOOR-AS-BASE-CASE NOTE: | B13: Base case = management stated FY27 AI-revenue FLOOR (Patterson: at least $6 billion), chosen as a conservative anchor - NOT a probability-weighted midpoint. This explains most of the model -3% variance vs Street. Given FY26 AI orders are already tracking toward ~$9B (YTD $5.3B Q3 + prior quarters, per Q3 FY26 call), the +25% sensitivity case (~$7.5B FY27) may be the more probable outcome, not just an upside tail.

Sheet Sources
A1: CSCO — Sources
A3: Type | B3: Document | C3: Date | D3: Used for
A4: 10-Q | B4: CSCO_10-Q_2026-05-19 (Q3 FY26, PE 2026-04-25) | C4: 2026-05-19 | D4: Q3 FY26 segment rev, geo, 9mo FY26, Q3FY25 comparative
A5: 10-Q | B5: CSCO_10-Q_2026-02-17 (Q2 FY26, PE 2026-01-24) | C5: 2026-02-17 | D5: Q2 FY26 segment rev + 6mo
A6: 10-Q | B6: CSCO_10-Q_2025-11-18 (Q1 FY26, PE 2025-10-25) | C6: 2025-11-18 | D6: Q1 FY26 segment rev; Q1FY25 comparative
A7: 10-K | B7: CSCO_10-K_2025-09-03 (FY25, YE 2025-07-26) | C7: 2025-09-03 | D7: FY25 FY seg rev -> Q4 FY25 by subtraction; seg definitions
A8: Transcript | B8: CSCO Q3 FY26 earnings call | C8: 2026-05-13 | D8: Q4 $16.7-16.9B / FY26 $62.8-63.0B guide; AI rev ~$4B FY26 (Robbins, prepared remarks, line 25) vs >=$6B FY27 (Patterson, Q&A, line 99); pull-forward Q&A; nonlinear orders
A9: Transcript | B9: CSCO Q2 FY26 earnings call | C9: 2026-02-11 | D9: AI orders $2.1B; AI rev raise >$3B FY26; Networking +21%; G300
A10: Consensus | B10: BBG estimates.json companies.CSCO | C10: 2026-07-01 | D10: BEST_SALES next FQ 16,838.6 / +1FQ 16,802.1 / CY26 66,156.4 / CY27 70,806.7; px 117.01
A11: Wiki | B11: _wiki/CSCO.md | C11: 2026-06-18 | D11: Thesis, bull/bear, AI order cadence, campus EOL, pull-forward bear point
