Workbook

Sheet Assumptions
A1: TXN — Bottoms-Up Quarterly Revenue Model — Assumptions
A2: Build date 2026-07-01 · consensus asof 2026-07-01 (BBG) · segment build is HARD quarterly disclosure; end-market is annual-only (ANCHOR)
A4: Legend: | B4: HARD (filed/guided + cite) | C4: PARTIAL / ANCHOR | D4: ESTIMATE
A6: Input | B6: Value | C6: Tag | D6: Source / basis
A7: SEGMENT ACTUALS ($m) — from filings
A8: Q1FY26 Analog revenue | B8: 3924 | C8: HARD | D8: 10-Q filed 2026-04-24, segment note
A9: Q1FY26 Embedded revenue | B9: 723 | C9: HARD | D9: 10-Q 2026-04-24
A10: Q1FY26 Other revenue | B10: 178 | C10: HARD | D10: 10-Q 2026-04-24
A11: Q1FY26 Total (tie-out target) | B11: 4825 | C11: HARD | D11: 10-Q 2026-04-24; +19% YoY, +9% QoQ
A12: Q4FY25 Total (Dec-25) | B12: 4423 | C12: HARD | D12: FY25 10-K 2026-02-06 less 9-mo 10-Q (Q1+Q2+Q3)
A13: Q3FY25 Total (Sep-25) | B13: 4742 | C13: HARD | D13: 10-Q filed 2025-10-23
A14: Q2FY25 Total (Jun-25) | B14: 4448 | C14: HARD | D14: 10-Q filed 2025-07-29 (3-mo table)
A15: Q1FY25 Total (Mar-25) | B15: 4069 | C15: HARD | D15: 10-Q filed 2025-04-24
A16: NEXT-QUARTER GUIDE — HARD
A17: Q2FY26 revenue guide LOW | B17: 5000 | C17: HARD | D17: Q1FY26 call 2026-04-22 (Lizardi)
A18: Q2FY26 revenue guide HIGH | B18: 5400 | C18: HARD | D18: Q1FY26 call 2026-04-22
A19: Q2FY26 guide MIDPOINT | B19: 5200 | C19: HARD | D19: midpoint (5000+5400)/2 ; ~+7.8% QoQ
A20: CALIBRATED GROWTH SLOPES (from observed QoQ)
A21: Analog up-quarter QoQ (Q2/Q3) | B21: 0.075 | C21: ESTIMATE | D21: Observed up-qtr avg +8.0% (Q2F25 +7.5, Q3F25 +8.0, Q1F26 +8.5); use 7.5% as base
A22: Analog Q3 QoQ (moderating) | B22: 0.06 | C22: ESTIMATE | D22: Q3F25 tot was +6.6% QoQ; cycle maturing
A23: Analog Q4 seasonal QoQ | B23: -0.02 | C23: ESTIMATE | D23: Q4F25 was -3.1%; milder now on 2H pricing + DC (Ilan, Jefferies July hike)
A24: Analog Q1 up-quarter QoQ | B24: 0.08 | C24: ESTIMATE | D24: Q1F26 was +8.5% QoQ
A25: Embedded up-quarter QoQ | B25: 0.035 | C25: ESTIMATE | D25: ~+4.5% (up-quarter average, excluding seasonal Q4 dip); +3.5% forecast conservative vs trailing; lags Analog in recovery
A26: Embedded Q4 seasonal QoQ | B26: -0.03 | C26: ESTIMATE | D26: Q4F25 Emb -6.6%; softened for pricing
A27: END-MARKET ANCHOR (annual %, 10-K MD&A)
A28: Industrial % of revenue | B28: 0.33 | C28: ANCHOR | D28: FY25 10-K 2026-02-06 (annual, rounded, not quarterly)
A29: Automotive % of revenue | B29: 0.33 | C29: ANCHOR | D29: FY25 10-K 2026-02-06
A30: Personal electronics % | B30: 0.21 | C30: ANCHOR | D30: FY25 10-K 2026-02-06
A31: Data center % | B31: 0.09 | C31: ANCHOR | D31: FY25 10-K; DC +~90% YoY Q1F26 (call)
A32: Comms equipment % | B32: 0.03 | C32: ANCHOR | D32: FY25 10-K 2026-02-06
A33: Calculators % | B33: 0.01 | C33: ANCHOR | D33: FY25 10-K 2026-02-06

Sheet Model
A1: TXN — Quarterly Revenue Build ($m) — Analog / Embedded / Other
A2: Cols B-F = ACTUAL (tie to filed total). Cols G-J = FORECAST. Q2FY26 anchored to guide midpoint; forward slopes calibrated to observed QoQ.
A4: Line ($m) | B4: Q1FY25 | C4: Q2FY25 | D4: Q3FY25 | E4: Q4FY25 | F4: Q1FY26 | G4: Q2FY26E | H4: Q3FY26E | I4: Q4FY26E | J4: Q1FY27E
A5: Analog | B5: 3210 | C5: 3452 | D5: 3729 | E5: 3615 | F5: 3924 | G5: =ROUND(F5*(1+$B$21),0) -> 4218 | H5: =ROUND(G5*(1+$B$22),0) -> 4471 | I5: =ROUND(H5*(1+$B$23),0) -> 4382 | J5: =ROUND(I5*(1+$B$24),0) -> 4733
A6: Embedded Processing | B6: 647 | C6: 679 | D6: 709 | E6: 662 | F6: 723 | G6: =ROUND(F6*(1+$B$25),0) -> 748 | H6: =ROUND(G6*(1+$B$26),0) -> 770 | I6: =ROUND(H6*(1+$B$27),0) -> 747 | J6: =ROUND(I6*(1+$B$28),0) -> 792
A7: Other | B7: 212 | C7: 317 | D7: 304 | E7: 146 | F7: 178 | G7: 234 | H7: 250 | I7: 150 | J7: 185
A8: TOTAL REVENUE | B8: =SUM(B5:B7) -> 4069 | C8: =SUM(C5:C7) -> 4448 | D8: =SUM(D5:D7) -> 4742 | E8: =SUM(E5:E7) -> 4423 | F8: =SUM(F5:F7) -> 4825 | G8: =SUM(G5:G7) -> 5200 | H8: =SUM(H5:H7) -> 5491 | I8: =SUM(I5:I7) -> 5279 | J8: =SUM(J5:J7) -> 5710
A10: Total QoQ % | C10: =C8/B8-1 -> 0.093143278 | D10: =D8/C8-1 -> 0.066097122 | E10: =E8/D8-1 -> -0.067271194 | F10: =F8/E8-1 -> 0.090888537 | G10: =G8/F8-1 -> 0.077720207 | H10: =H8/G8-1 -> 0.055961538 | I10: =I8/H8-1 -> -0.038608632 | J10: =J8/I8-1 -> 0.081644251
A11: Total YoY % | F11: =F8/B8-1 -> 0.18579504 | G11: =G8/C8-1 -> 0.16906475 | H11: =H8/D8-1 -> 0.15795023 | I11: =I8/E8-1 -> 0.1935338 | J11: =J8/F8-1 -> 0.18341969
A13: TIE-OUT CHECK (Q1FY26) | B13: =F8 -> 4825 | C13: 4825 | D13: =IF(F8=4825,"PASS","FAIL") -> PASS
A15: CY2026E (Q1F26 act + Q2-Q4F26E) | B15: =F8+G8+H8+I8 -> 20795
A16: CY2026E QoQ note | B16: =SUM(F5:I5) -> 16995
A20: Forecast parameters (calibrated slopes)
A21: Analog Q2 QoQ | B21: 0.075
A22: Analog Q3 QoQ | B22: 0.06
A23: Analog Q4 QoQ | B23: -0.02
A24: Analog Q1F27 QoQ | B24: 0.08
A25: Emb Q2 QoQ | B25: 0.035
A26: Emb Q3 QoQ | B26: 0.03
A27: Emb Q4 QoQ | B27: -0.03
A28: Emb Q1F27 QoQ | B28: 0.06

Sheet vs Consensus
A1: TXN — Bottoms-Up vs BBG Consensus & vs Guidance
A2: BBG BEST_SALES asof 2026-07-01. Nearest-quarter also checked vs TXN's own guided range (sharper than consensus).
A4: Period | B4: Bottoms-up ($m) | C4: BBG cons ($m) | D4: $ var | E4: % var | F4: TXN guide range | G4: Inside guide?
A5: Q2FY26E | B5: =Model!G8 -> 5200 | C5: 5211 | D5: =B5-C5 -> -11 | E5: =B5/C5-1 -> -0.0021109192 | F5: $5,000–5,400 | G5: Q2 guide (call 2026-04-22)
A6: Q3FY26E | B6: =Model!H8 -> 5491 | C6: 5570 | D6: =B6-C6 -> -79 | E6: =B6/C6-1 -> -0.014183124 | F6: n/a (not guided) | G6: beyond guided qtr
A7: Q4FY26E | B7: =Model!I8 -> 5279 | C7: n/a | D7: n/a | E7: n/a | F7: n/a | G7: no discrete cons qtr
A8: CY2026E | B8: =Model!F8+Model!G8+Model!H8+Model!I8 -> 20795 | C8: 20689 | D8: =B8-C8 -> 106 | E8: =B8/C8-1 -> 0.0051234956 | F8: n/a | G8: vs cons FY
A9: CY2027E | B9: 24606 | C9: 23421 | D9: =B9-C9 -> 1185 | E9: =B9/C9-1 -> 0.050595619 | F9: [!] 7 of 8 quarters extrapolated (0 explicitly guided) — treat CY27 as directional, not precise
A12: Q2FY26 inside guide 5,000–5,400? | B12: =IF(AND(Model!G8>=5000,Model!G8<=5400),"YES","NO") -> YES
A14: [!] CY2027E CONFIDENCE FLAG: only Q2FY26 is hard-guided ($5.0-5.4B). 7 of the 8 quarters in the CY27 comparison are EXTRAPOLATED off the observed up-quarter recovery slope (Analog ~+7.5-8%/qtr). The +5.1% above-Street headline holds only if that slope persists for all 7 unguided quarters. Treat CY27 as directional, not precise. See Sensitivity tab flat-sequential row for the downside stress case.

Sheet Sensitivity
A1: TXN — Sensitivity: load-bearing ESTIMATE inputs at +/-25%
A2: Two most sensitive: (1) Analog recovery slope (industrial), (2) Analog Q4 seasonal dip (auto/China + 2H pricing offset).
A4: Scenario | B4: Analog Q2/Q3/Q1F27 slope | C4: CY26E rev ($m) | D4: CY27E rev ($m) | E4: vs base CY26 | F4: vs base CY27
A5: Slope +25% | B5: 0.094/0.075/0.100 | C5: 21154 | D5: 25651 | E5: 357 | F5: 1045
A6: Base | B6: 0.075/0.060/0.080 | C6: 20797 | D6: 24606 | E6: 0 | F6: 0
A7: Slope -25% | B7: 0.056/0.045/0.060 | C7: 20448 | D7: 23598 | E7: -349 | F7: -1008
A10: Q4 seasonal-dip sensitivity (Analog Q4 QoQ)
A11: Scenario | B11: Analog Q4 QoQ | C11: CY26E rev ($m) | D11: CY27E rev ($m) | E11: vs base CY26 | F11: vs base CY27
A12: Mild dip -1.5% | B12: -0.015 | C12: 20819 | D12: 24708 | E12: 22 | F12: 102
A13: Base -2.0% | B13: -0.02 | C13: 20797 | D13: 24606 | E13: 0 | F13: 0
A14: Deep dip -6.7% (=Q4F25) | B14: -0.067 | C14: 20586 | D14: 23620 | E14: -211 | F14: -986
A16: NORMALIZATION SCENARIO (skeptic downside stress)
A17: Scenario | B17: Analog/Emb QoQ from Q3FY26E | C17: CY26E rev ($m) | D17: CY27E rev ($m) | E17: vs base CY27 | F17: % vs BBG cons CY27
A18: Flat-sequential from Q3FY26E onward (no further recovery, cycle normalizes) | B18: 0.0% / 0.0% (held flat) | C18: 20357 | D18: 20694 | E18: -3912 | F18: -0.11643397
A20: Base case = +5.1% ABOVE Street on CY27. Flat-sequential collapses CY27 to $20,694 (-11.6% vs BBG cons $23,421) — i.e. ~10-12% BELOW consensus. This is the swing from the recovery-slope assumption: base case assumes Analog ~+7.5-8%/qtr persists through 7 unguided quarters; flat case assumes the cycle stops recovering after the one guided quarter (Q2FY26). Directional only.

Sheet Sources
A1: TXN Model — Sources
A3: Type | B3: Document | C3: Date | D3: Used for
A4: Filing | B4: TXN 10-K FY2025 (acc 0000097476-26-000059) | C4: 2026-02-06 | D4: FY25/24/23 annual segment rev; end-market % (annual)
A5: Filing | B5: TXN 10-Q Q1FY26 (acc ...-26-000101) | C5: 2026-04-24 | D5: Q1FY26 segment rev (tie-out); Q1FY25 comp
A6: Filing | B6: TXN 10-Q Q3FY25 (acc ...-25-000060) | C6: 2025-10-23 | D6: Q3FY25 quarter + 9-mo (Q4 back-out)
A7: Filing | B7: TXN 10-Q Q2FY25 (acc ...-25-000036) | C7: 2025-07-29 | D7: Q2FY25 quarter (3-mo table)
A8: Filing | B8: TXN 10-Q Q1FY25 (acc ...-25-000027) | C8: 2025-04-24 | D8: Q1FY25 quarter
A9: Transcript | B9: TXN Q1FY26 earnings call | C9: 2026-04-22 | D9: Q2FY26 guide $5.0-5.4bn; end-market color; capex/FCF
A10: Transcript | B10: TXN Q4FY25 earnings call | C10: 2026-01-27 | D10: Q1FY26 guide; DC +70% YoY; loadings/GM
A11: Transcript | B11: TXN Q3FY25 earnings call | C11: 2025-10-22 | D11: Industrial recovery pace; DC $1.2bn run-rate
A12: Equity call | B12: UBS/Arcuri TXN callback | C12: 2026-04-23 | D12: Pricing scrapes (TXN sandbagging 2H); industrial pull-in debate
A13: Equity call | B13: BofA/Arya TXN analog | C13: 2026-04-23 | D13: AI/DC exposure framing; own-analog H1 call
A14: Consensus | B14: BBG estimates.json companies.TXN (asof) | C14: 2026-07-01 | D14: BEST_SALES Q2/Q3/CY26/CY27; px 298.41
A15: Wiki | B15: _wiki/TXN.md (thesis/debate) | C15: 2026-06-19 | D15: Broker PTs/stances; end-market mix; DC bull/bear
