Workbook

Sheet Monitor
A1: AI data center credit: live monitor
A2: Layout follows the Barclays IG/HY Data Center Comp Sheets (16-Sep-2026). Blue cells are live Bloomberg formulas. Principal vs par = (live price - 100) / 100 x amount outstanding; negative = below par.
A4: Company / description | B4: Ticker | C4: Tenant | D4: Data center location | E4: Critical IT (MW) | F4: Rating (Moody's / S&P / Fitch) | G4: Amt o/s ($mn) | H4: LIVE price | I4: Chg % 1D | J4: LIVE yield % | K4: Last trade size (TRACE) | L4: Price time | M4: Principal vs par ($mn) | N4: Principal vs par (%) | O4: Today's change in value ($mn) | P4: Since 15-Sep ($mn) | Q4: Δ yield since 15-Sep (bp) | R4: Barclays rec | S4: First issued | T4: LIVE spread (bp, OAS) | U4: Tenant comparable bond | V4: Comp LIVE spread (bp, OAS) | W4: LIVE pickup vs comp (bp) | X4: Pickup 15-Sep (bp, Barclays) | Y4: Δ pickup since 15-Sep (bp) | Z4: Bloomberg ticker (terminal)
A5: Investment Grade HPC Data Center Builders
A6: Hut 8 (Beacon Point DC LLC) 6.129% Sec Notes due 11/30/2042 | B6: HUTBPA | C6: NVIDIA | D6: Nueces County, TX | E6: 352 | F6: Baa2/NR/NR | G6: 4250 | H6: =_xll.BDP($Z6,"LAST_PRICE") -> 92.424 | I6: =_xll.BDP($Z6,"CHG_PCT_1D") -> -0.034323654 | J6: =_xll.BDP($Z6,"YLD_YTM_MID") -> 6.9070348 | K6: =IFERROR(_xll.BDP($Z6,"TRACE_LAST_TRADE_SIZE"),"n/a") -> 11 | L6: =IFERROR(_xll.BDP($Z6,"PRICE_LAST_TIME"),"") -> 16:44:24 | M6: =IF(AND(ISNUMBER(H6),ISNUMBER(G6)),(H6-100)/100*G6,"") -> -321.98 | N6: =IF(ISNUMBER(H6),(H6-100)/100,"") -> -0.07576 | O6: =IFERROR((H6-_xll.BDP($Z6,"PX_CLOSE_1D"))/100*G6,"") -> -4.5475 | P6: =IF(ISNUMBER(H6),(H6-93.65)/100*G6,"") -> -52.105 | Q6: =IF(ISNUMBER(J6),(J6-6.99)*100,"") -> -8.2965174 | S6: 46182 | T6: =_xll.BDP($Z6,"OAS_SPREAD_MID") -> 195.27657 | U6: NVDA 4.95% 2036 | V6: =_xll.BDP("NVDA 4.95 06/15/36 Corp","OAS_SPREAD_MID") -> 80.51352 | W6: =IF(AND(ISNUMBER(T6),ISNUMBER(V6)),T6-V6,"") -> 114.76306 | X6: 125 | Y6: =IF(ISNUMBER(W6),W6-X6,"") -> -10.236945 | Z6: HUTBPA 6.129 11/30/42 144A Corp
A7: Hut 8 (Hut 8 DC LLC) 6.192% Sec Notes due 11/15/2042 | B7: HUTRBA | C7: Fluidstack (Google backstop) | D7: St. Francisville, LA | E7: 245 | F7: NR/BBB-/BBB- | G7: 3250 | H7: =_xll.BDP($Z7,"LAST_PRICE") -> 93.919 | I7: =_xll.BDP($Z7,"CHG_PCT_1D") -> -0.43961784 | J7: =_xll.BDP($Z7,"YLD_YTM_MID") -> 6.8227402 | K7: =IFERROR(_xll.BDP($Z7,"TRACE_LAST_TRADE_SIZE"),"n/a") -> 5MM+ | L7: =IFERROR(_xll.BDP($Z7,"PRICE_LAST_TIME"),"") -> 16:44:24 | M7: =IF(AND(ISNUMBER(H7),ISNUMBER(G7)),(H7-100)/100*G7,"") -> -197.6325 | N7: =IF(ISNUMBER(H7),(H7-100)/100,"") -> -0.06081 | O7: =IFERROR((H7-_xll.BDP($Z7,"PX_CLOSE_1D"))/100*G7,"") -> -12.61 | P7: =IF(ISNUMBER(H7),(H7-96.15)/100*G7,"") -> -72.5075 | Q7: =IF(ISNUMBER(J7),(J7-6.74)*100,"") -> 8.2740175 | S7: 46142 | T7: =_xll.BDP($Z7,"OAS_SPREAD_MID") -> 188.37732 | U7: GOOGL 4.8% 2036 | V7: =_xll.BDP("US02079KBM80 Corp","OAS_SPREAD_MID") -> 68.481578 | W7: =IF(AND(ISNUMBER(T7),ISNUMBER(V7)),T7-V7,"") -> 119.89574 | X7: 110 | Y7: =IF(ISNUMBER(W7),W7-X7,"") -> 9.8957419 | Z7: HUTRBA 6.192 11/15/42 144A Corp
A8: BlueOwl/Meta JV (Beignet Investor LLC) 6.581% Sec Notes due 5/30/2049 | B8: RPLDCI | C8: Meta | D8: Richland Parish, LA | E8: 2064 | F8: NR/A+/NR | G8: 27293.8 | H8: =_xll.BDP($Z8,"LAST_PRICE") -> 91.908 | I8: =_xll.BDP($Z8,"CHG_PCT_1D") -> -0.50901119 | J8: =_xll.BDP($Z8,"YLD_YTM_MID") -> 7.4801614 | K8: =IFERROR(_xll.BDP($Z8,"TRACE_LAST_TRADE_SIZE"),"n/a") -> 5MM+ | L8: =IFERROR(_xll.BDP($Z8,"PRICE_LAST_TIME"),"") -> 16:44:24 | M8: =IF(AND(ISNUMBER(H8),ISNUMBER(G8)),(H8-100)/100*G8,"") -> -2208.6143 | N8: =IF(ISNUMBER(H8),(H8-100)/100,"") -> -0.08092 | O8: =IFERROR((H8-_xll.BDP($Z8,"PX_CLOSE_1D"))/100*G8,"") -> -139.19838 | P8: =IF(ISNUMBER(H8),(H8-94.73)/100*G8,"") -> -770.23104 | Q8: =IF(ISNUMBER(J8),(J8-7.15)*100,"") -> 33.016135 | R8: OW | S8: 45951 | T8: =_xll.BDP($Z8,"OAS_SPREAD_MID") -> 222.60592 | U8: META 5.25% 2036 | V8: =_xll.BDP("US30303MAH51 Corp","OAS_SPREAD_MID") -> 107.58046 | W8: =IF(AND(ISNUMBER(T8),ISNUMBER(V8)),T8-V8,"") -> 115.02546 | X8: 111 | Y8: =IF(ISNUMBER(W8),W8-X8,"") -> 4.0254617 | Z8: RPLDCI 6.581 05/30/49 144A Corp
A9: Blackrock/Meta JV (Sopapilla Investor LLC) 7.534% Sec Notes due 11/30/2048 | B9: TXEDCI | C9: Meta | D9: El Paso, TX | E9: 960 | F9: NR/A+/AA- | G9: 12639.5 | H9: =_xll.BDP($Z9,"LAST_PRICE") -> 98.999 | I9: =_xll.BDP($Z9,"CHG_PCT_1D") -> -0.33711873 | J9: =_xll.BDP($Z9,"YLD_YTM_MID") -> 7.6225604 | K9: =IFERROR(_xll.BDP($Z9,"TRACE_LAST_TRADE_SIZE"),"n/a") -> 175 | L9: =IFERROR(_xll.BDP($Z9,"PRICE_LAST_TIME"),"") -> 16:44:24 | M9: =IF(AND(ISNUMBER(H9),ISNUMBER(G9)),(H9-100)/100*G9,"") -> -126.5214 | N9: =IF(ISNUMBER(H9),(H9-100)/100,"") -> -0.01001 | O9: =IFERROR((H9-_xll.BDP($Z9,"PX_CLOSE_1D"))/100*G9,"") -> -70.27562 | P9: =IF(ISNUMBER(H9),(H9-103.65)/100*G9,"") -> -587.86315 | Q9: =IF(ISNUMBER(J9),(J9-7.22)*100,"") -> 40.256044 | R9: OW | S9: 46233 | T9: =_xll.BDP($Z9,"OAS_SPREAD_MID") -> 238.0114 | U9: META 5.25% 2036 | V9: =_xll.BDP("US30303MAH51 Corp","OAS_SPREAD_MID") -> 107.58046 | W9: =IF(AND(ISNUMBER(T9),ISNUMBER(V9)),T9-V9,"") -> 130.43094 | X9: 128 | Y9: =IF(ISNUMBER(W9),W9-X9,"") -> 2.4309429 | Z9: TXEDCI 7.534 11/30/48 144A Corp
A10: Related Digital (RD Michigan Pro Owner I) 7.50% Sec Notes due 3/30/2045 | B10: RDMICH | C10: Oracle | D10: Saline, MI | E10: 974 | F10: Baa3/NR/BBB | G10: 14000 | H10: =_xll.BDP($Z10,"LAST_PRICE") -> 87.247 | I10: =_xll.BDP($Z10,"CHG_PCT_1D") -> -1.3388337 | J10: =_xll.BDP($Z10,"YLD_YTM_MID") -> 8.9678816 | K10: =IFERROR(_xll.BDP($Z10,"TRACE_LAST_TRADE_SIZE"),"n/a") -> 5000 | L10: =IFERROR(_xll.BDP($Z10,"PRICE_LAST_TIME"),"") -> 16:44:24 | M10: =IF(AND(ISNUMBER(H10),ISNUMBER(G10)),(H10-100)/100*G10,"") -> -1785.42 | N10: =IF(ISNUMBER(H10),(H10-100)/100,"") -> -0.12753 | O10: =IFERROR((H10-_xll.BDP($Z10,"PX_CLOSE_1D"))/100*G10,"") -> -104.58 | P10: =IF(ISNUMBER(H10),(H10-94.25)/100*G10,"") -> -980.42 | Q10: =IF(ISNUMBER(J10),(J10-8.21)*100,"") -> 75.788156 | S10: 46142 | T10: =_xll.BDP($Z10,"OAS_SPREAD_MID") -> 400.12212 | U10: ORCL 3.6% 2040 | V10: =_xll.BDP("US68389XBW48 Corp","OAS_SPREAD_MID") -> 275.0577 | W10: =IF(AND(ISNUMBER(T10),ISNUMBER(V10)),T10-V10,"") -> 125.06442 | X10: 71 | Y10: =IF(ISNUMBER(W10),W10-X10,"") -> 54.064421 | Z10: RDMICH 7.5 03/30/45 144A Corp
A11: QTS (QTS Central Issuer LLC) 6.625% Sec Notes due 9/1/2031 (5NC2) | B11: QTSODY | C11: Microsoft | D11: Atlanta, GA | E11: 204 | F11: Baa3/NR/NR | G11: 3900 | H11: =_xll.BDP($Z11,"LAST_PRICE") -> 97.166 | I11: =_xll.BDP($Z11,"CHG_PCT_1D") -> 0.15399598 | J11: =_xll.BDP($Z11,"YLD_YTM_MID") -> 7.3295727 | K11: =IFERROR(_xll.BDP($Z11,"TRACE_LAST_TRADE_SIZE"),"n/a") -> 400 | L11: =IFERROR(_xll.BDP($Z11,"PRICE_LAST_TIME"),"") -> 16:44:24 | M11: =IF(AND(ISNUMBER(H11),ISNUMBER(G11)),(H11-100)/100*G11,"") -> -110.526 | N11: =IF(ISNUMBER(H11),(H11-100)/100,"") -> -0.02834 | O11: =IFERROR((H11-_xll.BDP($Z11,"PX_CLOSE_1D"))/100*G11,"") -> 6.63 | P11: =IF(ISNUMBER(H11),(H11-98.88)/100*G11,"") -> -66.846 | Q11: =IF(ISNUMBER(J11),(J11-6.9)*100,"") -> 42.957271 | S11: 46261 | T11: =_xll.BDP($Z11,"OAS_SPREAD_MID") -> 222.09584 | U11: MSFT 3.45% 2036 | V11: =_xll.BDP("US594918BS26 Corp","OAS_SPREAD_MID") -> 29.725185 | W11: =IF(AND(ISNUMBER(T11),ISNUMBER(V11)),T11-V11,"") -> 192.37065 | X11: 145 | Y11: =IF(ISNUMBER(W11),W11-X11,"") -> 47.370653 | Z11: QTSODY 6.625 09/01/31 144A Corp
A12: QTS (QTS Fayetteville Dc1-2 LLC) 5.70% Sec Notes due 4/15/2036 | B12: QTSQST | C12: Microsoft | D12: Atlanta, GA | E12: 340 | F12: Baa2/NR/NR | G12: 4600 | H12: =_xll.BDP($Z12,"LAST_PRICE") -> 87.991 | I12: =_xll.BDP($Z12,"CHG_PCT_1D") -> -0.034385601 | J12: =_xll.BDP($Z12,"YLD_YTM_MID") -> 7.5219323 | K12: =IFERROR(_xll.BDP($Z12,"TRACE_LAST_TRADE_SIZE"),"n/a") -> 96 | L12: =IFERROR(_xll.BDP($Z12,"PRICE_LAST_TIME"),"") -> 16:44:24 | M12: =IF(AND(ISNUMBER(H12),ISNUMBER(G12)),(H12-100)/100*G12,"") -> -552.414 | N12: =IF(ISNUMBER(H12),(H12-100)/100,"") -> -0.12009 | O12: =IFERROR((H12-_xll.BDP($Z12,"PX_CLOSE_1D"))/100*G12,"") -> 7.544 | P12: =IF(ISNUMBER(H12),(H12-89.96)/100*G12,"") -> -90.574 | Q12: =IF(ISNUMBER(J12),(J12-7.17)*100,"") -> 35.193235 | S12: 46127 | T12: =_xll.BDP($Z12,"OAS_SPREAD_MID") -> 244.8938 | U12: MSFT 3.45% 2036 | V12: =_xll.BDP("US594918BS26 Corp","OAS_SPREAD_MID") -> 29.725185 | W12: =IF(AND(ISNUMBER(T12),ISNUMBER(V12)),T12-V12,"") -> 215.16862 | X12: 189 | Y12: =IF(ISNUMBER(W12),W12-X12,"") -> 26.168619 | Z12: QTSQST 5.7 04/15/36 144A Corp
A13: IG total | G13: =SUM(G6:G12) -> 69933.3 | H13: =IFERROR(SUMPRODUCT(H6:H12,G6:G12)/SUM(G6:G12),"") -> 92.416906 | M13: =IFERROR(SUM(M6:M12),"") -> -5303.1082 | N13: =IFERROR(M13/G13,"") -> -0.075830944 | O13: =IFERROR(SUM(O6:O12),"") -> -317.0375 | P13: =IFERROR(SUM(P6:P12),"") -> -2620.5467
A14: High Yield HPC Data Center Builders
A15: Applied Digital (APLD ComputeCo LLC) 9 1/4% Sec Notes due 12/15/2030 | B15: APLD | C15: CoreWeave | D15: Ellendale, ND | E15: 250 | F15: NR/BB-/BB- | G15: 2350 | H15: =_xll.BDP($Z15,"LAST_PRICE") -> 102.776 | I15: =_xll.BDP($Z15,"CHG_PCT_1D") -> -0.69392549 | J15: =_xll.BDP($Z15,"YLD_YTM_MID") -> 8.4534708 | K15: =IFERROR(_xll.BDP($Z15,"TRACE_LAST_TRADE_SIZE"),"n/a") -> 1MM+ | L15: =IFERROR(_xll.BDP($Z15,"PRICE_LAST_TIME"),"") -> 16:44:24 | M15: =IF(AND(ISNUMBER(H15),ISNUMBER(G15)),(H15-100)/100*G15,"") -> 65.236 | N15: =IF(ISNUMBER(H15),(H15-100)/100,"") -> 0.02776 | O15: =IFERROR((H15-_xll.BDP($Z15,"PX_CLOSE_1D"))/100*G15,"") -> -15.6275 | P15: =IF(ISNUMBER(H15),(H15-105.29)/100*G15,"") -> -59.079 | Q15: =IF(ISNUMBER(J15),(J15-7.6)*100,"") -> 85.347083 | R15: MW | S15: 45981 | T15: =_xll.BDP($Z15,"OAS_SPREAD_MID") -> 324.69677 | U15: CRWV 9% 2031 | V15: =_xll.BDP("CRWV 9 02/01/2031 144A Corp","OAS_SPREAD_MID") -> 1050.1994 | W15: =IF(AND(ISNUMBER(T15),ISNUMBER(V15)),T15-V15,"") -> -725.50259 | X15: -434 | Y15: =IF(ISNUMBER(W15),W15-X15,"") -> -291.50259 | Z15: APLD 9.25 12/15/30 144A Corp
A16: Applied Digital (APLD ComputeCo 2 LLC) 6 3/4% Sec Notes due 3/15/2031 | B16: PFORGE | C16: Oracle | D16: Harwood, ND | E16: 200 | F16: Ba3/NR/BB- | G16: 2150 | H16: =_xll.BDP($Z16,"LAST_PRICE") -> 95.153 | I16: =_xll.BDP($Z16,"CHG_PCT_1D") -> -0.52129588 | J16: =_xll.BDP($Z16,"YLD_YTM_MID") -> 8.1104983 | K16: =IFERROR(_xll.BDP($Z16,"TRACE_LAST_TRADE_SIZE"),"n/a") -> 50 | L16: =IFERROR(_xll.BDP($Z16,"PRICE_LAST_TIME"),"") -> 16:44:24 | M16: =IF(AND(ISNUMBER(H16),ISNUMBER(G16)),(H16-100)/100*G16,"") -> -104.2105 | N16: =IF(ISNUMBER(H16),(H16-100)/100,"") -> -0.04847 | O16: =IFERROR((H16-_xll.BDP($Z16,"PX_CLOSE_1D"))/100*G16,"") -> -8.127 | P16: =IF(ISNUMBER(H16),(H16-96)/100*G16,"") -> -18.2105 | Q16: =IF(ISNUMBER(J16),(J16-7.93)*100,"") -> 18.049834 | R16: MW | S16: 46091 | T16: =_xll.BDP($Z16,"OAS_SPREAD_MID") -> 339.02994 | U16: ORCL 4.95% 2031 | V16: =_xll.BDP("US68389XDX03 Corp","OAS_SPREAD_MID") -> 225.91147 | W16: =IF(AND(ISNUMBER(T16),ISNUMBER(V16)),T16-V16,"") -> 113.11846 | X16: 167 | Y16: =IF(ISNUMBER(W16),W16-X16,"") -> -53.881536 | Z16: PFORGE 6.75 03/15/31 144A Corp
A17: Applied Digital (APLD ComputeCo 3 LLC) 7% Sec Notes due 6/15/2031 | B17: ELNFOR | C17: CoreWeave | D17: Ellendale, ND | E17: 150 | F17: NR/BB-/BB- | G17: 1590 | H17: =_xll.BDP($Z17,"LAST_PRICE") -> 92.836 | I17: =_xll.BDP($Z17,"CHG_PCT_1D") -> -0.64598564 | J17: =_xll.BDP($Z17,"YLD_YTM_MID") -> 8.831383 | K17: =IFERROR(_xll.BDP($Z17,"TRACE_LAST_TRADE_SIZE"),"n/a") -> 254 | L17: =IFERROR(_xll.BDP($Z17,"PRICE_LAST_TIME"),"") -> 16:44:24 | M17: =IF(AND(ISNUMBER(H17),ISNUMBER(G17)),(H17-100)/100*G17,"") -> -113.9076 | N17: =IF(ISNUMBER(H17),(H17-100)/100,"") -> -0.07164 | O17: =IFERROR((H17-_xll.BDP($Z17,"PX_CLOSE_1D"))/100*G17,"") -> -14.0556 | P17: =IF(ISNUMBER(H17),(H17-95.75)/100*G17,"") -> -46.3326 | Q17: =IF(ISNUMBER(J17),(J17-8.19)*100,"") -> 64.138297 | R17: OW | S17: 46189 | T17: =_xll.BDP($Z17,"OAS_SPREAD_MID") -> 408.84269 | U17: CRWV 9% 2031 | V17: =_xll.BDP("CRWV 9 02/01/2031 144A Corp","OAS_SPREAD_MID") -> 1050.1994 | W17: =IF(AND(ISNUMBER(T17),ISNUMBER(V17)),T17-V17,"") -> -641.35667 | X17: -332 | Y17: =IF(ISNUMBER(W17),W17-X17,"") -> -309.35667 | Z17: ELNFOR 7 06/15/31 144A Corp
A18: Cipher Digital (Cipher Compute LLC) 7 1/8% Sec Notes due 11/15/2030 | B18: CIFR | C18: Fluidstack (Google backstop) | D18: Colorado City, TX | E18: 207 | F18: Ba3/NR/BB- | G18: 1733 | H18: =_xll.BDP($Z18,"LAST_PRICE") -> 99.088 | I18: =_xll.BDP($Z18,"CHG_PCT_1D") -> -0.28045974 | J18: =_xll.BDP($Z18,"YLD_YTM_MID") -> 7.3958154 | K18: =IFERROR(_xll.BDP($Z18,"TRACE_LAST_TRADE_SIZE"),"n/a") -> 535 | L18: =IFERROR(_xll.BDP($Z18,"PRICE_LAST_TIME"),"") -> 16:44:24 | M18: =IF(AND(ISNUMBER(H18),ISNUMBER(G18)),(H18-100)/100*G18,"") -> -15.80496 | N18: =IF(ISNUMBER(H18),(H18-100)/100,"") -> -0.00912 | O18: =IFERROR((H18-_xll.BDP($Z18,"PX_CLOSE_1D"))/100*G18,"") -> -4.24585 | P18: =IF(ISNUMBER(H18),(H18-101.5)/100*G18,"") -> -41.79996 | Q18: =IF(ISNUMBER(J18),(J18-6.72)*100,"") -> 67.581538 | R18: MW | S18: 45974 | T18: =_xll.BDP($Z18,"OAS_SPREAD_MID") -> 238.72623 | U18: GOOGL 4.1% 2031 | V18: =_xll.BDP("US02079KBK25 Corp","OAS_SPREAD_MID") -> 41.152337 | W18: =IF(AND(ISNUMBER(T18),ISNUMBER(V18)),T18-V18,"") -> 197.57389 | X18: 127 | Y18: =IF(ISNUMBER(W18),W18-X18,"") -> 70.57389 | Z18: CIFR 7.125 11/15/30 144A Corp
A19: Cipher Digital (Black Pearl Compute LLC) 6 1/8% Sec Notes due 2/15/2031 | B19: BLKPRL | C19: Amazon | D19: Wink, TX | E19: 216 | F19: Ba2/NR/BB- | G19: 2000 | H19: =_xll.BDP($Z19,"LAST_PRICE") -> 98.352 | I19: =_xll.BDP($Z19,"CHG_PCT_1D") -> -0.29605155 | J19: =_xll.BDP($Z19,"YLD_YTM_MID") -> 6.5859493 | K19: =IFERROR(_xll.BDP($Z19,"TRACE_LAST_TRADE_SIZE"),"n/a") -> 8 | L19: =IFERROR(_xll.BDP($Z19,"PRICE_LAST_TIME"),"") -> 16:44:24 | M19: =IF(AND(ISNUMBER(H19),ISNUMBER(G19)),(H19-100)/100*G19,"") -> -32.96 | N19: =IF(ISNUMBER(H19),(H19-100)/100,"") -> -0.01648 | O19: =IFERROR((H19-_xll.BDP($Z19,"PX_CLOSE_1D"))/100*G19,"") -> -4.38 | P19: =IF(ISNUMBER(H19),(H19-99.75)/100*G19,"") -> -27.96 | Q19: =IF(ISNUMBER(J19),(J19-6.22)*100,"") -> 36.594926 | R19: MW | S19: 46064 | T19: =_xll.BDP($Z19,"OAS_SPREAD_MID") -> 158.72643 | U19: AMZN 4.25% 2031 | V19: =_xll.BDP("US023135DD51 Corp","OAS_SPREAD_MID") -> 52.588859 | W19: =IF(AND(ISNUMBER(T19),ISNUMBER(V19)),T19-V19,"") -> 106.13757 | X19: 77 | Y19: =IF(ISNUMBER(W19),W19-X19,"") -> 29.137574 | Z19: BLKPRL 6.125 02/15/31 144A Corp
A20: Cipher Digital (Stingray Compute LLC) 6% Sec Notes due 6/15/2031 | B20: STNGRY | C20: Amazon | D20: Andrews, TX | E20: 70 | F20: Ba2/NR/BB- | G20: 810 | H20: =_xll.BDP($Z20,"LAST_PRICE") -> 95.265 | I20: =_xll.BDP($Z20,"CHG_PCT_1D") -> -0.26301011 | J20: =_xll.BDP($Z20,"YLD_YTM_MID") -> 7.2172472 | K20: =IFERROR(_xll.BDP($Z20,"TRACE_LAST_TRADE_SIZE"),"n/a") -> 150 | L20: =IFERROR(_xll.BDP($Z20,"PRICE_LAST_TIME"),"") -> 16:44:24 | M20: =IF(AND(ISNUMBER(H20),ISNUMBER(G20)),(H20-100)/100*G20,"") -> -38.3535 | N20: =IF(ISNUMBER(H20),(H20-100)/100,"") -> -0.04735 | O20: =IFERROR((H20-_xll.BDP($Z20,"PX_CLOSE_1D"))/100*G20,"") -> -1.8873 | P20: =IF(ISNUMBER(H20),(H20-97.13)/100*G20,"") -> -15.1065 | Q20: =IF(ISNUMBER(J20),(J20-6.72)*100,"") -> 49.724717 | R20: OW | S20: 46188 | T20: =_xll.BDP($Z20,"OAS_SPREAD_MID") -> 229.4324 | U20: AMZN 4.25% 2031 | V20: =_xll.BDP("US023135DD51 Corp","OAS_SPREAD_MID") -> 52.588859 | W20: =IF(AND(ISNUMBER(T20),ISNUMBER(V20)),T20-V20,"") -> 176.84354 | X20: 136 | Y20: =IF(ISNUMBER(W20),W20-X20,"") -> 40.843543 | Z20: STNGRY 6 06/15/31 144A Corp
A21: Core Scientific (Core Scientific Finance I LLC) 7 3/4% Sec Notes due 5/15/2031 | B21: CORZ | C21: CoreWeave | D21: Various (5 sites: TX, GA, OK, NC) | E21: 590 | F21: NR/BB/BB- | G21: 3300 | H21: =_xll.BDP($Z21,"LAST_PRICE") -> 93.155 | I21: =_xll.BDP($Z21,"CHG_PCT_1D") -> -0.75096229 | J21: =_xll.BDP($Z21,"YLD_YTM_MID") -> 9.6475756 | K21: =IFERROR(_xll.BDP($Z21,"TRACE_LAST_TRADE_SIZE"),"n/a") -> 1MM+ | L21: =IFERROR(_xll.BDP($Z21,"PRICE_LAST_TIME"),"") -> 16:44:24 | M21: =IF(AND(ISNUMBER(H21),ISNUMBER(G21)),(H21-100)/100*G21,"") -> -225.885 | N21: =IF(ISNUMBER(H21),(H21-100)/100,"") -> -0.06845 | O21: =IFERROR((H21-_xll.BDP($Z21,"PX_CLOSE_1D"))/100*G21,"") -> -21.549 | P21: =IF(ISNUMBER(H21),(H21-97.67)/100*G21,"") -> -148.995 | Q21: =IF(ISNUMBER(J21),(J21-8.41)*100,"") -> 123.75756 | R21: OW | S21: 46148 | T21: =_xll.BDP($Z21,"OAS_SPREAD_MID") -> 489.68715 | U21: CRWV 9% 2031 | V21: =_xll.BDP("CRWV 9 02/01/2031 144A Corp","OAS_SPREAD_MID") -> 1050.1994 | W21: =IF(AND(ISNUMBER(T21),ISNUMBER(V21)),T21-V21,"") -> -560.51221 | X21: -313 | Y21: =IF(ISNUMBER(W21),W21-X21,"") -> -247.51221 | Z21: CORZ 7.75 05/15/31 144A Corp
A22: Edged (Edged Compute LLC) 7 1/2% Sec Notes due 4/30/2031 | B22: EDGCOM | C22: CoreWeave (Chicago) / Alibaba (Atlanta) | D22: Chicago, IL (72MW) / Atlanta, GA (42MW) | E22: 114 | F22: NR/BB+/BB- | G22: 1300 | H22: =_xll.BDP($Z22,"LAST_PRICE") -> 87.946 | I22: =_xll.BDP($Z22,"CHG_PCT_1D") -> -1.0217074 | J22: =_xll.BDP($Z22,"YLD_YTM_MID") -> 10.899613 | K22: =IFERROR(_xll.BDP($Z22,"TRACE_LAST_TRADE_SIZE"),"n/a") -> 1MM+ | L22: =IFERROR(_xll.BDP($Z22,"PRICE_LAST_TIME"),"") -> 16:44:24 | M22: =IF(AND(ISNUMBER(H22),ISNUMBER(G22)),(H22-100)/100*G22,"") -> -156.702 | N22: =IF(ISNUMBER(H22),(H22-100)/100,"") -> -0.12054 | O22: =IFERROR((H22-_xll.BDP($Z22,"PX_CLOSE_1D"))/100*G22,"") -> -13.663 | P22: =IF(ISNUMBER(H22),(H22-94.25)/100*G22,"") -> -81.952 | Q22: =IF(ISNUMBER(J22),(J22-9.3)*100,"") -> 159.96128 | R22: UW | S22: 46141 | T22: =_xll.BDP($Z22,"OAS_SPREAD_MID") -> 654.06518 | U22: CRWV 9% 2031 | V22: =_xll.BDP("CRWV 9 02/01/2031 144A Corp","OAS_SPREAD_MID") -> 1050.1994 | W22: =IF(AND(ISNUMBER(T22),ISNUMBER(V22)),T22-V22,"") -> -396.13418 | X22: -217 | Y22: =IF(ISNUMBER(W22),W22-X22,"") -> -179.13418 | Z22: EDGCOM 7.5 04/30/31 144A Corp
A23: Fleet Data Centers/Tract (SV RNO Property Owner 1) 5 7/8% Sec Notes due 3/1/2031 | B23: TRACTC | C23: NVIDIA | D23: Storey County, NV | E23: 200 | F23: Ba1/(P)BB+/BB | G23: 3800 | H23: =_xll.BDP($Z23,"LAST_PRICE") -> 89.109 | I23: =_xll.BDP($Z23,"CHG_PCT_1D") -> -0.57204535 | J23: =_xll.BDP($Z23,"YLD_YTM_MID") -> 8.8175717 | K23: =IFERROR(_xll.BDP($Z23,"TRACE_LAST_TRADE_SIZE"),"n/a") -> 8 | L23: =IFERROR(_xll.BDP($Z23,"PRICE_LAST_TIME"),"") -> 16:44:24 | M23: =IF(AND(ISNUMBER(H23),ISNUMBER(G23)),(H23-100)/100*G23,"") -> -413.858 | N23: =IF(ISNUMBER(H23),(H23-100)/100,"") -> -0.10891 | O23: =IFERROR((H23-_xll.BDP($Z23,"PX_CLOSE_1D"))/100*G23,"") -> -34.846 | P23: =IF(ISNUMBER(H23),(H23-92.63)/100*G23,"") -> -133.798 | Q23: =IF(ISNUMBER(J23),(J23-7.93)*100,"") -> 88.75717 | R23: OW | S23: 46077 | T23: =_xll.BDP($Z23,"OAS_SPREAD_MID") -> 405.1552 | U23: NVDA 2% 2031 | V23: =_xll.BDP("US67066GAN43 Corp","OAS_SPREAD_MID") -> 44.411947 | W23: =IF(AND(ISNUMBER(T23),ISNUMBER(V23)),T23-V23,"") -> 360.74326 | X23: 276 | Y23: =IF(ISNUMBER(W23),W23-X23,"") -> 84.743255 | Z23: TRACTC 5.875 03/01/31 144A Corp
A24: Fleet Data Centers/Tract (PR RNO Property Owner 1) 6 1/2% Sec Notes due 5/1/2031 | B24: TRACTD | C24: NVIDIA | D24: Storey County, NV | E24: 200 | F24: Ba1/(P)BB/BB | G24: 4585 | H24: =_xll.BDP($Z24,"LAST_PRICE") -> 90.215 | I24: =_xll.BDP($Z24,"CHG_PCT_1D") -> -1.054426 | J24: =_xll.BDP($Z24,"YLD_YTM_MID") -> 9.2035095 | K24: =IFERROR(_xll.BDP($Z24,"TRACE_LAST_TRADE_SIZE"),"n/a") -> 500 | L24: =IFERROR(_xll.BDP($Z24,"PRICE_LAST_TIME"),"") -> 16:44:24 | M24: =IF(AND(ISNUMBER(H24),ISNUMBER(G24)),(H24-100)/100*G24,"") -> -448.64225 | N24: =IF(ISNUMBER(H24),(H24-100)/100,"") -> -0.09785 | O24: =IFERROR((H24-_xll.BDP($Z24,"PX_CLOSE_1D"))/100*G24,"") -> -41.3567 | P24: =IF(ISNUMBER(H24),(H24-93.75)/100*G24,"") -> -162.07975 | Q24: =IF(ISNUMBER(J24),(J24-8.2)*100,"") -> 100.35095 | R24: OW | S24: 46143 | T24: =_xll.BDP($Z24,"OAS_SPREAD_MID") -> 439.52395 | U24: NVDA 2% 2031 | V24: =_xll.BDP("US67066GAN43 Corp","OAS_SPREAD_MID") -> 44.411947 | W24: =IF(AND(ISNUMBER(T24),ISNUMBER(V24)),T24-V24,"") -> 395.11201 | X24: 302 | Y24: =IF(ISNUMBER(W24),W24-X24,"") -> 93.112006 | Z24: TRACTD 6.5 05/01/31 144A Corp
A25: Fluidstack-led JV (Flash Compute LLC) 7 1/4% Sec Notes due 12/31/2030 | B25: FLASHC | C25: Fluidstack (Google backstop) | D25: Abernathy, TX | E25: 168 | F25: Ba3/NR/NR | G25: 1300 | H25: =_xll.BDP($Z25,"LAST_PRICE") -> 99.374 | I25: =_xll.BDP($Z25,"CHG_PCT_1D") -> -0.32772999 | J25: =_xll.BDP($Z25,"YLD_YTM_MID") -> 7.4587606 | K25: =IFERROR(_xll.BDP($Z25,"TRACE_LAST_TRADE_SIZE"),"n/a") -> 1MM+ | L25: =IFERROR(_xll.BDP($Z25,"PRICE_LAST_TIME"),"") -> 16:44:24 | M25: =IF(AND(ISNUMBER(H25),ISNUMBER(G25)),(H25-100)/100*G25,"") -> -8.138 | N25: =IF(ISNUMBER(H25),(H25-100)/100,"") -> -0.00626 | O25: =IFERROR((H25-_xll.BDP($Z25,"PX_CLOSE_1D"))/100*G25,"") -> -2.548 | P25: =IF(ISNUMBER(H25),(H25-100.25)/100*G25,"") -> -11.388 | Q25: =IF(ISNUMBER(J25),(J25-7.19)*100,"") -> 26.87606 | R25: MW | S25: 46020 | T25: =_xll.BDP($Z25,"OAS_SPREAD_MID") -> 260.34913 | U25: GOOGL 4.1% 2031 | V25: =_xll.BDP("US02079KBK25 Corp","OAS_SPREAD_MID") -> 41.152337 | W25: =IF(AND(ISNUMBER(T25),ISNUMBER(V25)),T25-V25,"") -> 219.19679 | X25: 192 | Y25: =IF(ISNUMBER(W25),W25-X25,"") -> 27.19679 | Z25: FLASHC 7.25 12/31/30 144A Corp
A26: Fluidstack/Next Frontier JV (Meridian Arc Holdco LLC) 6 1/4% Sec Notes due 4/30/2031 | B26: MERIDI | C26: Fluidstack (Google backstop) | D26: New Lebanon, IN | E26: 430 | F26: Ba2/BB-/BB | G26: 5700 | H26: =_xll.BDP($Z26,"LAST_PRICE") -> 91.868 | I26: =_xll.BDP($Z26,"CHG_PCT_1D") -> -0.31145585 | J26: =_xll.BDP($Z26,"YLD_YTM_MID") -> 8.4501543 | K26: =IFERROR(_xll.BDP($Z26,"TRACE_LAST_TRADE_SIZE"),"n/a") -> 100 | L26: =IFERROR(_xll.BDP($Z26,"PRICE_LAST_TIME"),"") -> 16:44:24 | M26: =IF(AND(ISNUMBER(H26),ISNUMBER(G26)),(H26-100)/100*G26,"") -> -463.524 | N26: =IF(ISNUMBER(H26),(H26-100)/100,"") -> -0.08132 | O26: =IFERROR((H26-_xll.BDP($Z26,"PX_CLOSE_1D"))/100*G26,"") -> -15.561 | P26: =IF(ISNUMBER(H26),(H26-94.63)/100*G26,"") -> -157.434 | Q26: =IF(ISNUMBER(J26),(J26-7.67)*100,"") -> 78.015426 | R26: MW | S26: 46136 | T26: =_xll.BDP($Z26,"OAS_SPREAD_MID") -> 357.71613 | U26: GOOGL 4.1% 2031 | V26: =_xll.BDP("US02079KBK25 Corp","OAS_SPREAD_MID") -> 41.152337 | W26: =IF(AND(ISNUMBER(T26),ISNUMBER(V26)),T26-V26,"") -> 316.56379 | X26: 245 | Y26: =IF(ISNUMBER(W26),W26-X26,"") -> 71.563792 | Z26: MERIDI 6.25 04/30/31 144A Corp
A27: Fluidstack/Next Frontier JV (Zenith Arc LLC) 8 7/8% Sec Notes due 8/31/2031 | B27: ZENARC | C27: Jane Street | D27: Okmulgee, OK | E27: 149 | F27: Ba2/BB/NR | G27: 2250 | H27: =_xll.BDP($Z27,"LAST_PRICE") -> 85.008 | I27: =_xll.BDP($Z27,"CHG_PCT_1D") -> 2.1858097 | J27: =_xll.BDP($Z27,"YLD_YTM_MID") -> 13.095812 | K27: =IFERROR(_xll.BDP($Z27,"TRACE_LAST_TRADE_SIZE"),"n/a") -> 1000 | L27: =IFERROR(_xll.BDP($Z27,"PRICE_LAST_TIME"),"") -> 16:44:24 | M27: =IF(AND(ISNUMBER(H27),ISNUMBER(G27)),(H27-100)/100*G27,"") -> -337.32 | N27: =IF(ISNUMBER(H27),(H27-100)/100,"") -> -0.14992 | O27: =IFERROR((H27-_xll.BDP($Z27,"PX_CLOSE_1D"))/100*G27,"") -> 39.5325 | P27: =IF(ISNUMBER(H27),(H27-92.5)/100*G27,"") -> -168.57 | Q27: =IF(ISNUMBER(J27),(J27-10.86)*100,"") -> 223.58125 | S27: 46252 | T27: =_xll.BDP($Z27,"OAS_SPREAD_MID") -> 822.75219 | U27: Jane Street 7.294% 2031 | V27: =_xll.BDP("USU47015AH24 Corp","OAS_SPREAD_MID") -> 226.43298 | W27: =IF(AND(ISNUMBER(T27),ISNUMBER(V27)),T27-V27,"") -> 596.3192 | X27: 410 | Y27: =IF(ISNUMBER(W27),W27-X27,"") -> 186.3192 | Z27: ZENARC 8.875 08/31/31 144A Corp
A28: Galaxy Digital (Galaxy Helios Data Centers II LLC) 9 7/8% Sec Notes due 8/1/2031 | B28: GALAXY | C28: CoreWeave | D28: Dickens County, TX | E28: 260 | F28: NR/BB-/BB- | G28: 3507 | H28: =_xll.BDP($Z28,"LAST_PRICE") -> 91.064 | I28: =_xll.BDP($Z28,"CHG_PCT_1D") -> -1.0446242 | J28: =_xll.BDP($Z28,"YLD_YTM_MID") -> 12.517412 | K28: =IFERROR(_xll.BDP($Z28,"TRACE_LAST_TRADE_SIZE"),"n/a") -> 1000 | L28: =IFERROR(_xll.BDP($Z28,"PRICE_LAST_TIME"),"") -> 16:44:24 | M28: =IF(AND(ISNUMBER(H28),ISNUMBER(G28)),(H28-100)/100*G28,"") -> -313.38552 | N28: =IF(ISNUMBER(H28),(H28-100)/100,"") -> -0.08936 | O28: =IFERROR((H28-_xll.BDP($Z28,"PX_CLOSE_1D"))/100*G28,"") -> -19.42878 | P28: =IF(ISNUMBER(H28),(H28-99.25)/100*G28,"") -> -287.08302 | Q28: =IF(ISNUMBER(J28),(J28-10.1)*100,"") -> 241.74116 | R28: OW | S28: 46231 | T28: =_xll.BDP($Z28,"OAS_SPREAD_MID") -> 764.7852 | U28: CRWV 9% 2031 | V28: =_xll.BDP("CRWV 9 02/01/2031 144A Corp","OAS_SPREAD_MID") -> 1050.1994 | W28: =IF(AND(ISNUMBER(T28),ISNUMBER(V28)),T28-V28,"") -> -285.41417 | X28: -150 | Y28: =IF(ISNUMBER(W28),W28-X28,"") -> -135.41417 | Z28: GALAXY 9.875 08/01/31 144A Corp
A29: Prime Data Centers (Elk Grove Village Property LLC) 7 1/2% Sec Notes due 6/15/2031 | B29: ELKGVP | C29: CoreWeave | D29: Chicago, IL | E29: 72 | F29: Ba3/BB-/BB- | G29: 900 | H29: =_xll.BDP($Z29,"LAST_PRICE") -> 93.622 | I29: =_xll.BDP($Z29,"CHG_PCT_1D") -> -0.32418555 | J29: =_xll.BDP($Z29,"YLD_YTM_MID") -> 9.2615243 | K29: =IFERROR(_xll.BDP($Z29,"TRACE_LAST_TRADE_SIZE"),"n/a") -> 1MM+ | L29: =IFERROR(_xll.BDP($Z29,"PRICE_LAST_TIME"),"") -> 16:44:24 | M29: =IF(AND(ISNUMBER(H29),ISNUMBER(G29)),(H29-100)/100*G29,"") -> -57.402 | N29: =IF(ISNUMBER(H29),(H29-100)/100,"") -> -0.06378 | O29: =IFERROR((H29-_xll.BDP($Z29,"PX_CLOSE_1D"))/100*G29,"") -> -1.089 | P29: =IF(ISNUMBER(H29),(H29-95.63)/100*G29,"") -> -18.072 | Q29: =IF(ISNUMBER(J29),(J29-8.79)*100,"") -> 47.15243 | R29: OW | S29: 46182 | T29: =_xll.BDP($Z29,"OAS_SPREAD_MID") -> 460.50215 | U29: CRWV 9% 2031 | V29: =_xll.BDP("CRWV 9 02/01/2031 144A Corp","OAS_SPREAD_MID") -> 1050.1994 | W29: =IF(AND(ISNUMBER(T29),ISNUMBER(V29)),T29-V29,"") -> -589.69722 | X29: -271 | Y29: =IF(ISNUMBER(W29),W29-X29,"") -> -318.69722 | Z29: ELKGVP 7.5 06/15/31 144A Corp
A30: SB Energy (SE Cosmos, LLC) 8 7/8% Sec Notes due 5/1/2031 | B30: SECMOS | C30: SoftBank | D30: Austin, TX | E30: 50 | F30: NR/(P)BB/BB- | G30: 999 | H30: =_xll.BDP($Z30,"LAST_PRICE") -> 95.294 | I30: =_xll.BDP($Z30,"CHG_PCT_1D") -> -1.2367635 | J30: =_xll.BDP($Z30,"YLD_YTM_MID") -> 10.262203 | K30: =IFERROR(_xll.BDP($Z30,"TRACE_LAST_TRADE_SIZE"),"n/a") -> 1MM+ | L30: =IFERROR(_xll.BDP($Z30,"PRICE_LAST_TIME"),"") -> 16:44:24 | M30: =IF(AND(ISNUMBER(H30),ISNUMBER(G30)),(H30-100)/100*G30,"") -> -47.01294 | N30: =IF(ISNUMBER(H30),(H30-100)/100,"") -> -0.04706 | O30: =IFERROR((H30-_xll.BDP($Z30,"PX_CLOSE_1D"))/100*G30,"") -> -9.5904 | P30: =IF(ISNUMBER(H30),(H30-97.13)/100*G30,"") -> -18.34164 | Q30: =IF(ISNUMBER(J30),(J30-9.66)*100,"") -> 60.220277 | R30: MW | S30: 46149 | T30: =_xll.BDP($Z30,"OAS_SPREAD_MID") -> 536.33904 | U30: SoftBank 8.25% 2031 | V30: =_xll.BDP("XS3344488864 Corp","OAS_SPREAD_MID") -> 392.92231 | W30: =IF(AND(ISNUMBER(T30),ISNUMBER(V30)),T30-V30,"") -> 143.41673 | X30: 106 | Y30: =IF(ISNUMBER(W30),W30-X30,"") -> 37.41673 | Z30: SECMOS 8.875 05/01/31 144A Corp
A31: TeraWulf (WULF Compute LLC) 7 3/4% Sec Notes due 10/15/2030 | B31: WULF | C31: Fluidstack (Google backstop) 366MW / Core42 60MW | D31: Barker, NY | E31: 366 | F31: Ba2/BB/BB | G31: 3200 | H31: =_xll.BDP($Z31,"LAST_PRICE") -> 102.417 | I31: =_xll.BDP($Z31,"CHG_PCT_1D") -> -0.078565559 | J31: =_xll.BDP($Z31,"YLD_YTM_MID") -> 7.0540663 | K31: =IFERROR(_xll.BDP($Z31,"TRACE_LAST_TRADE_SIZE"),"n/a") -> 1MM+ | L31: =IFERROR(_xll.BDP($Z31,"PRICE_LAST_TIME"),"") -> 16:44:24 | M31: =IF(AND(ISNUMBER(H31),ISNUMBER(G31)),(H31-100)/100*G31,"") -> 77.344 | N31: =IF(ISNUMBER(H31),(H31-100)/100,"") -> 0.02417 | O31: =IFERROR((H31-_xll.BDP($Z31,"PX_CLOSE_1D"))/100*G31,"") -> -1.44 | P31: =IF(ISNUMBER(H31),(H31-103.9)/100*G31,"") -> -47.456 | Q31: =IF(ISNUMBER(J31),(J31-6.34)*100,"") -> 71.406627 | R31: MW | S31: 45953 | T31: =_xll.BDP($Z31,"OAS_SPREAD_MID") -> 183.86387 | U31: GOOGL 4.1% 2031 | V31: =_xll.BDP("US02079KBK25 Corp","OAS_SPREAD_MID") -> 41.152337 | W31: =IF(AND(ISNUMBER(T31),ISNUMBER(V31)),T31-V31,"") -> 142.71153 | X31: 90 | Y31: =IF(ISNUMBER(W31),W31-X31,"") -> 52.711534 | Z31: WULF 7.75 10/15/30 144A Corp
A32: Yondr Group/JK Land Holdings JV (Yondr JK 1, LLC) 6 7/8% Sec Notes due 6/30/2031 | B32: YNDRDC | C32: Oracle | D32: Loudoun County, VA | E32: 48 | F32: Ba3/NR/BB | G32: 715 | H32: =_xll.BDP($Z32,"LAST_PRICE") -> 89.657 | I32: =_xll.BDP($Z32,"CHG_PCT_1D") -> -2.0872717 | J32: =_xll.BDP($Z32,"YLD_YTM_MID") -> 9.6972191 | K32: =IFERROR(_xll.BDP($Z32,"TRACE_LAST_TRADE_SIZE"),"n/a") -> 1000 | L32: =IFERROR(_xll.BDP($Z32,"PRICE_LAST_TIME"),"") -> 16:44:24 | M32: =IF(AND(ISNUMBER(H32),ISNUMBER(G32)),(H32-100)/100*G32,"") -> -73.95245 | N32: =IF(ISNUMBER(H32),(H32-100)/100,"") -> -0.10343 | O32: =IFERROR((H32-_xll.BDP($Z32,"PX_CLOSE_1D"))/100*G32,"") -> -12.7413 | P32: =IF(ISNUMBER(H32),(H32-92.75)/100*G32,"") -> -22.11495 | Q32: =IF(ISNUMBER(J32),(J32-8.92)*100,"") -> 77.721914 | R32: OW | S32: 46203 | T32: =_xll.BDP($Z32,"OAS_SPREAD_MID") -> 508.10483 | U32: ORCL 4.95% 2031 | V32: =_xll.BDP("US68389XDX03 Corp","OAS_SPREAD_MID") -> 225.91147 | W32: =IF(AND(ISNUMBER(T32),ISNUMBER(V32)),T32-V32,"") -> 282.19336 | X32: 267 | Y32: =IF(ISNUMBER(W32),W32-X32,"") -> 15.193357 | Z32: YNDRDC 6.875 06/30/31 144A Corp
A33: HY total | G33: =SUM(G15:G32) -> 42189 | H33: =IFERROR(SUMPRODUCT(H15:H32,G15:G32)/SUM(G15:G32),"") -> 93.580131 | M33: =IFERROR(SUM(M15:M32),"") -> -2708.4787 | N33: =IFERROR(M33/G33,"") -> -0.064198694 | O33: =IFERROR(SUM(O15:O32),"") -> -182.60393 | P33: =IFERROR(SUM(P15:P32),"") -> -1465.7729
A34: Tenant / parent comparables
A35: CoreWeave 9 3/4% Sr Notes due 10/1/2031 | B35: CRWV | C35: CoreWeave | D35: HPC cloud provider | G35: 2750 | H35: =_xll.BDP($Z35,"LAST_PRICE") -> 81.122 | I35: =_xll.BDP($Z35,"CHG_PCT_1D") -> -2.6888331 | J35: =_xll.BDP($Z35,"YLD_YTM_MID") -> 15.566073 | K35: =IFERROR(_xll.BDP($Z35,"TRACE_LAST_TRADE_SIZE"),"n/a") -> 1000 | L35: =IFERROR(_xll.BDP($Z35,"PRICE_LAST_TIME"),"") -> 16:44:24 | M35: =IF(AND(ISNUMBER(H35),ISNUMBER(G35)),(H35-100)/100*G35,"") -> -519.145 | N35: =IF(ISNUMBER(H35),(H35-100)/100,"") -> -0.18878 | O35: =IFERROR((H35-_xll.BDP($Z35,"PX_CLOSE_1D"))/100*G35,"") -> -41.5525 | P35: =IF(ISNUMBER(H35),(H35-90.25)/100*G35,"") -> -251.02 | Q35: =IF(ISNUMBER(J35),(J35-12.46)*100,"") -> 310.60726 | S35: 46126 | T35: =_xll.BDP($Z35,"OAS_SPREAD_MID") -> 1070.0762 | Z35: CRWV 9.75 10/01/2031 144A Corp
A36: Oracle 4.95% Sr Notes due 2/4/2031 | B36: ORCL | C36: Oracle | D36: Tenant parent | G36: 3500 | H36: =_xll.BDP($Z36,"LAST_PRICE") -> 91.99 | I36: =_xll.BDP($Z36,"CHG_PCT_1D") -> 0.066211329 | J36: =_xll.BDP($Z36,"YLD_YTM_MID") -> 7.128663 | K36: =IFERROR(_xll.BDP($Z36,"TRACE_LAST_TRADE_SIZE"),"n/a") -> 48 | L36: =IFERROR(_xll.BDP($Z36,"PRICE_LAST_TIME"),"") -> 16:44:24 | M36: =IF(AND(ISNUMBER(H36),ISNUMBER(G36)),(H36-100)/100*G36,"") -> -280.35 | N36: =IF(ISNUMBER(H36),(H36-100)/100,"") -> -0.0801 | O36: =IFERROR((H36-_xll.BDP($Z36,"PX_CLOSE_1D"))/100*G36,"") -> -0.105 | P36: =IF(ISNUMBER(H36),(H36-94.96)/100*G36,"") -> -103.95 | Q36: =IF(ISNUMBER(J36),(J36-6.28)*100,"") -> 84.866299 | S36: 46057 | T36: =_xll.BDP($Z36,"OAS_SPREAD_MID") -> 225.91147 | Z36: ORCL 4.95 02/04/31 Corp
A38: Notes: composite quotes refresh about every 15 seconds and are not individual trades. 'Last trade size' is the latest TRACE print (e.g. 5MM+ = $5mm or more); cumulative daily bond volume is not available from Bloomberg fields. Principal vs par excludes accrued interest. Amber yield = 10% or more (MS: HY datacenter deals get pulled near ~10%). Pink = yield up 25bp or more since 15-Sep (Barclays YTW vs live YTM, approximate). Pickup = bond OAS minus the tenant comparable bond's OAS (both live, Bloomberg OAS_SPREAD_MID); Barclays used G-spread on IG non-callables, so IG pickups differ slightly in basis. A negative pickup means the project bond trades tighter than the tenant's own unsecured bond (the CoreWeave comparable is now at about 1,050bp OAS). EDGCOM is measured against CoreWeave 9% 2031 (Chicago, about 60% of the credit); the Alibaba leg (BABA 2.125% 2031) is not blended. First issued = Bloomberg ISSUE_DT (issue / settlement date of the original issue; later taps are not separated).

Sheet Deal Index
A1: Deal dossiers: one tab per bond on the Monitor sheet
A2: Built from official documents where available (SEC filings, indentures, company releases, rating agency releases). Each dossier lists its sources and what could not be verified. Click a ticker to open its tab.
A4: Ticker | B4: Bond | C4: Section | D4: Sources | E4: of which official-type | F4: Open gaps | G4: Headline
A5: HUTBPA | B5: Beacon Point DC LLC 6.129% Senior Secured Notes due 30-Nov-2042 | C5: IG | D5: 15 | E5: 11 | F5: 11 | G5: $4.25bn fully amortizing, non-recourse 144A notes issued 9 Jun 2026 by a Hut 8 SPV to build the 352 MW first phase of the Beacon Point campus in Nueces County, Texas, secured by the project and a 15-year triple-net take-or-pay lease to an unnamed tenant rated AA- or better (reported by the FT to be NVIDIA). Moody's rates the notes Baa2 and they priced at T+165bp. Credit rests on one tenant and on energization and delivery in Q1-Q3 2027; Phase 2 (a second 352 MW lease), NVIDIA's disclosure that it expects to reassign leases to third parties, and the reported Lambda/Anthropic usage raise assignment and end-user questions, with indenture limits on assignment to Qualifying Tenants or Creditworthy Transferees the main protection.
A6: HUTRBA | B6: Hut 8 DC LLC 6.192% Senior Secured Notes due 15-Nov-2042 | C6: IG | D6: 16 | E6: 11 | F6: 9 | G6: $3.25bn fully amortizing, non-recourse 144A notes issued 30 Apr 2026 by a Hut 8 SPV to build the 245 MW River Bend campus in West Feliciana Parish, Louisiana, secured by the project and a 15-year triple-net lease to Fluidstack (unrated) whose rent and certain other obligations are backstopped by Google LLC. Rated BBB- by S&P and Fitch (per press). The credit is effectively Google's for rent, but the backstop's cap and conditions are not public; no warrants to Google are disclosed (the company said none were issued). Execution risk remains until the first hall energizes in Q2 2027 at about 95% loan-to-cost.
A7: RPLDCI | B7: Beignet Investor LLC 6.581% Senior Secured Notes due 30-May-2049 | C7: IG | D7: 12 | E7: 7 | F7: 9 | G7: A single-tranche, fully amortising 144A project bond (about $27.3bn) issued in Oct 2025 to fund the Hyperion data centre campus in Richland Parish, Louisiana, owned by a joint venture in which Blue Owl funds hold 80% and Meta 20%. Debt service is meant to come from Meta's lease rent plus a Meta residual value guarantee (RVG), so the credit is essentially Meta's; S&P rates it A+ (one notch below Meta), per press reports. Meta consolidates nothing: it treats the JV as an unconsolidated VIE, but discloses $46.0bn of maximum exposure to loss as of 30-Jun-2026. Main watch items are construction and power delivery (the campus was announced in Jul 2026 to scale to 5 GW) and what happens at the end of each four-year lease block.
A8: TXEDCI | B8: Sopaipilla Investor LLC 7.534% Senior Secured Notes due 30-Nov-2048 | C8: IG | D8: 8 | E8: 2 | F8: 8 | G8: A roughly $12.3-12.6bn 144A senior secured bond issued in late Jul 2026 to fund Meta's El Paso, Texas data centre campus (about 1 GW, about $14bn total cost), owned by a JV in which BlackRock-managed funds (GIP and HPS) hold 80% and Meta 20%. Meta is sole tenant, developer and operator, pays rent from Dec 2028 whether or not the campus is complete, and provides a residual value guarantee (up to about $13bn per its 10-Q). Ratings reported at A+ (S&P, preliminary) and AA- (Fitch, expected); the one-notch gap reflects the absence of an asset mortgage. Seed 7.534% coupon, ISIN and maturity are confirmed by a fund holdings filing, but almost everything else rests on press and newsletter coverage because the offering memorandum is private and Meta has not yet filed its post-closing 10-Q.
A9: RDMICH | B9: RD Michigan Property Owner I LLC 7.50% Senior Secured Notes due 2045 (Related Digital / Blackstone, Oracle campus, Saline Township, MI) | C9: IG | D9: 18 | E9: 9 | F9: 9 | G9: $14bn 7.500% senior secured notes due 2045 issued in spring 2026 by a Related Digital/Blackstone SPV to fund a 974MW Oracle data center campus in Saline Township, Michigan, anchored by PIMCO. Cash flows come from four triple-net leases to Oracle America Cloud Services guaranteed by Oracle Corporation, so the credit is essentially Oracle (S&P BBB-, Moody's Baa2 negative per Feb-2026 data) plus construction risk; KBRA rates it BBB Stable. The spread over Oracle's own bonds reflects project, construction, power-approval litigation and 144A illiquidity.
A10: QTSODY | B10: QTS Central Issuer LLC 6.625% Senior Secured Notes due 1-Sep-2031 (5NC2) | C10: IG | D10: 18 | E10: 5 | F10: 9 | G10: QTSODY is a $3.9bn five-year non-call-2 non-recourse project bond sold by Blackstone's QTS in Aug 2026 (closed 27-Aug) to finance part of the Microsoft-leased Fayetteville, Georgia campus (Project Odyssey). It was reshaped from a larger bond-and-loan package into an investment-grade deal reportedly rated Baa3/BBB-, yet priced at a 7.228% yield. Support is the Microsoft lease and the project; there is little official disclosure because it is a 144A deal with no SEC filings.
A11: QTSQST | B11: QTS Fayetteville I DC1-2 LLC 5.70% Senior Secured Notes due 15-Apr-2036 | C11: IG | D11: 18 | E11: 5 | F11: 7 | G11: QTSQST is a $4.6bn 10-year non-amortising, non-recourse single-asset project bond issued in April 2026 by QualityTech (Blackstone) subsidiaries, refinancing construction credit facilities for two Microsoft-leased data centers on the Fayetteville, Georgia campus. Moody's reportedly assigned Baa2. Support is the Microsoft lease and the project; it moved from a 5.70% issue yield to about 7.2% by Aug-Sep 2026 as AI-infrastructure credit repriced.
A12: APLD | B12: APLD ComputeCo LLC 9 1/4% Senior Secured Notes due 15-Dec-2030 | C12: HY | D12: 17 | E12: 15 | F12: 11 | G12: APLD ComputeCo LLC's $2.35bn 9.25% senior secured notes due December 2030 are a ring-fenced, project-style financing of two CoreWeave-leased buildings (100 MW and 150 MW, now both live) at the Polaris Forge 1 campus in Ellendale, North Dakota. Applied Digital provides only a completion guarantee, not a payment guarantee; credit rests on CoreWeave rent (now partly owed by a CoreWeave SPV with springing parent guaranty), a DSRA, and a sculpted amortization that leaves roughly 70-75% to refinance at maturity. The sponsor's own model shows coverage near 1.0x in 2028-2029, which together with CoreWeave credit concerns and a heavy parent funding pipeline explains why the notes carry a high-yield spread despite full delivery of the assets.
A13: PFORGE | B13: APLD ComputeCo 2 LLC 6 3/4% Senior Secured Notes due 15-Mar-2031 | C13: HY | D13: 14 | E13: 12 | F13: 9 | G13: APLD ComputeCo 2 LLC's $2.15bn 6.75% senior secured notes due March 2031 finance the 200 MW Oracle-leased Polaris Forge 2 campus in Harwood, North Dakota, through a ring-fenced chain of lessor SPVs with an Applied Digital completion guarantee. The 15-year take-or-pay lease and sculpted amortization (about 81% balloon, about 1.0x modelled coverage, $148mm DSRA) put the bond between investment-grade-tenant and high-yield sponsor risk; the campus is still under construction, with first ready-for-service now guided to 2H CY2026 after a model date of 1-Oct-2026, and the notes marked in the mid-90s at 31-Aug-2026 after a sell-side downgrade on supply overhang.
A14: ELNFOR | B14: APLD ComputeCo 3 LLC 7% Senior Secured Notes due 15-Jun-2031 | C14: HY | D14: 17 | E14: 14 | F14: 9 | G14: APLD ComputeCo 3 LLC's $1.59bn 7.00% senior secured notes due June 2031 fund the third 150 MW building (ELN-04) at Applied Digital's Polaris Forge 1 campus in Ellendale, North Dakota, leased to CoreWeave. The building is still under construction, so the credit combines construction and delivery risk (backstopped by a parent completion guarantee), single-tenant CoreWeave exposure with a possible upgrade path through an unconsummated June-2026 MoU to an investment-grade CoreWeave subsidiary, and an amortization profile that leaves about 85% to refinance in 2031. Sponsor model coverage is 1.2x from 2028, and the bond traded down to about 94 by Oct 2026 amid supply-overhang concerns.
A15: CIFR | B15: Cipher Compute LLC 7.125% Senior Secured Notes due 15-Nov-2030 | C15: HY | D15: 19 | E15: 16 | F15: 9 | G15: Project-finance notes of Cipher Compute LLC ($1.733bn outstanding) that fund the 207 MW critical IT Barber Lake data center in Colorado City, Texas, leased to Fluidstack with a Google backstop equal to the debt and a Cipher completion guarantee. Credit hinges on on-time delivery (now Q4 2026-Q1 2027 after change orders), Google's backstop, and the parent's ability to fund a cost increase of roughly $0.5bn while its equity has been hit by a heavy 2032 convertible and 2030 exchange. The notes amortize but leave a large balloon at Nov-2030.
A16: BLKPRL | B16: Black Pearl Compute LLC 6.125% Senior Secured Notes due 15-Feb-2031 | C16: HY | D16: 13 | E16: 11 | F16: 9 | G16: $2.0bn project notes of Black Pearl Compute LLC funding the retrofit and build-out of a 300 MW gross / 216 MW critical IT campus in Wink, Texas, leased to Amazon Data Services under a 15-year triple-net sublease with an Amazon.com parent guaranty and a $9.5mm per MW tenant cost cap. First capacity was delivered two months early (Aug-2026) and rent has started, but later halls are being re-phased, the notes amortize only 7% a year leaving roughly a 70% balloon at Feb-2031, and loss of the lease or guaranty is an immediate default. Tight pricing reflects Amazon credit and tenant protections against overruns.
... A31: ORCL | B31: Oracle Corporation 4.950% Senior Notes due 4-Feb-2031 | C31: Parent | D31: 12 | E31: 9 | F31: 7 | G31: $3.5bn of Oracle's 4.950% unsecured senior notes due 4-Feb-2031, one of eight series in a $25bn offering priced on 2-Feb-2026 (alongside a $5bn mandatory convertible and a $20bn ATM that Oracle has since fully used). It is the parent/tenant comparable for Oracle-leased project bonds: priced at T+115bp, now rated BBB- at S&P (cut 9-Jul-2026), Baa2 negative at Moody's and BBB at Fitch as last confirmed. Credit story is heavy AI capex (Q1 FY27 capex $28.5bn, FCF -$5.4bn), $125bn of debt and $288bn of not-yet-commenced data center leases against a $664bn backlog.

Sheet Terms & Lease
A1: Terms, call schedule and lease structure
A2: From Barclays Figures 7 and 8 (15-Sep). Live price links to the Monitor sheet.
A4: Company / description | B4: Ticker | C4: Tenant | D4: LIVE price | E4: Next call | F4: Call price | G4: Live price to call (pts) | H4: Amort. start | I4: Est. amortization before maturity (% of original) | J4: Tenant comp bond | K4: Tenant comp spread (bp) | L4: Lease type | M4: Lease tenor | N4: Construction start | O4: Lease commencement | P4: Barclays spread 15-Sep (bp)
A5: Investment Grade HPC Data Center Builders
A6: Hut 8 (Beacon Point DC LLC) 6.129% Sec Notes due 11/30/2042 | B6: HUTBPA | C6: NVIDIA | D6: =Monitor!H6 -> 92.424 | E6: 5/30/42 | F6: 100 | G6: =IF(ISNUMBER(D6),F6-D6,"") -> 7.576 | H6: Mid 2030 | I6: 1 | J6: NVDA 4.95% 2036 | K6: 75 | L6: Triple Net | M6: 15yrs, three 5-yr ext. | N6: Early 2026 | O6: Aug 2027 - Apr 2028 | P6: 200
A7: Hut 8 (Hut 8 DC LLC) 6.192% Sec Notes due 11/15/2042 | B7: HUTRBA | C7: Fluidstack (Google backstop) | D7: =Monitor!H7 -> 93.919 | E7: 5/15/42 | F7: 100 | G7: =IF(ISNUMBER(D7),F7-D7,"") -> 6.081 | H7: Mid 2028 | I7: 1 | J7: GOOGL 4.8% 2036 | K7: 68 | L7: Triple Net | M7: 15yrs, three 5-yr ext. | N7: Dec 2025 | O7: Apr 2027 - Oct 2027 | P7: 178
A8: BlueOwl/Meta JV (Beignet Investor LLC) 6.581% Sec Notes due 5/30/2049 | B8: RPLDCI | C8: Meta | D8: =Monitor!H8 -> 91.908 | E8: 11/30/48 | F8: 100 | G8: =IF(ISNUMBER(D8),F8-D8,"") -> 8.092 | H8: Mid 2029 | I8: 1 | J8: META 5.25% 2036 | K8: 94 | L8: Triple Net | M8: 20yrs (4yr initial + 4 x 4yr ext.) | N8: Late 2024 | O8: June 2029 | P8: 205
A9: Blackrock/Meta JV (Sopapilla Investor LLC) 7.534% Sec Notes due 11/30/2048 | B9: TXEDCI | C9: Meta | D9: =Monitor!H9 -> 98.999 | E9: 5/30/48 | F9: 100 | G9: =IF(ISNUMBER(D9),F9-D9,"") -> 1.001 | H9: Late 2028 | I9: 1 | J9: META 5.25% 2036 | K9: 94 | L9: Triple Net | M9: 20yrs (4yr initial + 4 x 4yr ext.) | N9: Oct 2025 | O9: Dec 2028 | P9: 222
A10: Related Digital (RD Michigan Pro Owner I) 7.50% Sec Notes due 3/30/2045 | B10: RDMICH | C10: Oracle | D10: =Monitor!H10 -> 87.247 | E10: 4/30/29 | F10: 100 | G10: =IF(ISNUMBER(D10),F10-D10,"") -> 12.753 | H10: Mid 2032 | I10: 1 | J10: ORCL 3.6% 2040 | K10: 208 | L10: Triple Net | M10: 17.5yrs, two 10-yr renewals | N10: Early 2026 | O10: Feb 2027 - Mar 2028 | P10: 279
A11: QTS (QTS Central Issuer LLC) 6.625% Sec Notes due 9/1/2031 (5NC2) | B11: QTSODY | C11: Microsoft | D11: =Monitor!H11 -> 97.166 | E11: 9/1/28 | F11: 100 | G11: =IF(ISNUMBER(D11),F11-D11,"") -> 2.834 | H11: Mid 2029 | I11: 0.055 | J11: MSFT 3.45% 2036 | K11: 31 | L11: Triple Net | M11: 15yrs, 15-yr renewal | N11: Early 2026 | O11: Nov 2027 - Feb 2028 | P11: 176
A12: QTS (QTS Fayetteville Dc1-2 LLC) 5.70% Sec Notes due 4/15/2036 | B12: QTSQST | C12: Microsoft | D12: =Monitor!H12 -> 87.991 | E12: 10/15/35 | F12: 100 | G12: =IF(ISNUMBER(D12),F12-D12,"") -> 12.009 | H12: N/A | I12: 0 | J12: MSFT 3.45% 2036 | K12: 33 | L12: Triple Net | M12: 20yrs, 15-yr renewal | N12: 2023 | O12: Apr 2025 - Apr 2026 | P12: 222
A14: High Yield HPC Data Center Builders
A15: Applied Digital (APLD ComputeCo LLC) 9 1/4% Sec Notes due 12/15/2030 | B15: APLD | C15: CoreWeave | D15: =Monitor!H15 -> 102.776 | E15: 12/15/27 | F15: 104.63 | G15: =IF(ISNUMBER(D15),F15-D15,"") -> 1.854 | H15: Late 2027 | I15: 0.304 | J15: CRWV 9% 2031 | K15: 670 | L15: Modified Gross | M15: 15yrs, three 5-yr ext. | N15: Early 2024 | O15: 4Q25 - 2Q26 | P15: 236
A16: Applied Digital (APLD ComputeCo 2 LLC) 6 3/4% Sec Notes due 3/15/2031 | B16: PFORGE | C16: Oracle | D16: =Monitor!H16 -> 95.153 | E16: 3/15/28 | F16: 103.38 | G16: =IF(ISNUMBER(D16),F16-D16,"") -> 8.227 | H16: Mid 2027 | I16: 0.191 | J16: ORCL 4.95% 2031 | K16: 147 | L16: Modified Gross | M16: 15yrs, two 5-yr ext. | N16: Sept 2025 | O16: Nov 2026 - June 2027 | P16: 314
A17: Applied Digital (APLD ComputeCo 3 LLC) 7% Sec Notes due 6/15/2031 | B17: ELNFOR | C17: CoreWeave | D17: =Monitor!H17 -> 92.836 | E17: 6/15/28 | F17: 103.5 | G17: =IF(ISNUMBER(D17),F17-D17,"") -> 10.664 | H17: Mid 2027 | I17: 0.147 | J17: CRWV 9% 2031 | K17: 670 | L17: Modified Gross | M17: 15yrs, three 5-yr ext. | N17: Aug 2025 | O17: Jan 2027 - June 2027 | P17: 338
A18: Cipher Digital (Cipher Compute LLC) 7 1/8% Sec Notes due 11/15/2030 | B18: CIFR | C18: Fluidstack (Google backstop) | D18: =Monitor!H18 -> 99.088 | E18: 11/15/27 | F18: 103.56 | G18: =IF(ISNUMBER(D18),F18-D18,"") -> 4.472 | H18: Late 2026 | I18: 0.441 | J18: GOOGL 4.1% 2031 | K18: 42 | L18: Modified Gross | M18: 10yrs, two 5-yr ext. | N18: Mid 2025 | O18: Sept 2026 - Jan 2027 | P18: 169
A19: Cipher Digital (Black Pearl Compute LLC) 6 1/8% Sec Notes due 2/15/2031 | B19: BLKPRL | C19: Amazon | D19: =Monitor!H19 -> 98.352 | E19: 2/15/28 | F19: 103.06 | G19: =IF(ISNUMBER(D19),F19-D19,"") -> 4.708 | H19: Early 2027 | I19: 0.277 | J19: AMZN 4.25% 2031 | K19: 50 | L19: Triple Net | M19: 15yrs, three 5-yr ext. | N19: Feb 2026 | O19: Oct 2026 - Mar 2027 | P19: 127
A20: Cipher Digital (Stingray Compute LLC) 6% Sec Notes due 6/15/2031 | B20: STNGRY | C20: Amazon | D20: =Monitor!H20 -> 95.265 | E20: 6/15/28 | F20: 103 | G20: =IF(ISNUMBER(D20),F20-D20,"") -> 7.735 | H20: Mid 2027 | I20: 0.258 | J20: AMZN 4.25% 2031 | K20: 50 | L20: Triple Net | M20: 15yrs, three 5-yr ext. | N20: May 2026 | O20: Apr 2027 | P20: 186
A21: Core Scientific (Core Scientific Finance I LLC) 7 3/4% Sec Notes due 5/15/2031 | B21: CORZ | C21: CoreWeave | D21: =Monitor!H21 -> 93.155 | E21: 5/15/28 | F21: 103.88 | G21: =IF(ISNUMBER(D21),F21-D21,"") -> 10.725 | H21: Early 2029 | I21: 0.236 | J21: CRWV 9% 2031 | K21: 670 | L21: Modified Gross | M21: 12yrs, two 5-yr ext. | N21: Mid 2024 | O21: Late 2024 - Early 2027 | P21: 357
A22: Edged (Edged Compute LLC) 7 1/2% Sec Notes due 4/30/2031 | B22: EDGCOM | C22: CoreWeave (Chicago) / Alibaba (Atlanta) | D22: =Monitor!H22 -> 87.946 | E22: 4/30/28 | F22: 103.75 | G22: =IF(ISNUMBER(D22),F22-D22,"") -> 15.804 | H22: Late 2029 | I22: 0.066 | J22: CRWV 9% 2031 / BABA 2.125% 2031 | L22: Triple Net (Chi) / Mod. Gross (Atl) | M22: 16yrs Chicago / 15yrs Atlanta, two 5-yr ext. | N22: 3Q25 | O22: Chicago May-Dec 2027; Atlanta Jan-Jun 2027 | P22: 453
A23: Fleet Data Centers/Tract (SV RNO Property Owner 1) 5 7/8% Sec Notes due 3/1/2031 | B23: TRACTC | C23: NVIDIA | D23: =Monitor!H23 -> 89.109 | E23: 3/1/28 | F23: 102.94 | G23: =IF(ISNUMBER(D23),F23-D23,"") -> 13.831 | H23: Mid 2028 | I23: 0.082 | J23: NVDA 2% 2031 | K23: 39 | L23: Triple Net | M23: 16.4yrs, two 10-yr ext. | N23: June 2026 | O23: Oct 2027 - June 2028 | P23: 315
A24: Fleet Data Centers/Tract (PR RNO Property Owner 1) 6 1/2% Sec Notes due 5/1/2031 | B24: TRACTD | C24: NVIDIA | D24: =Monitor!H24 -> 90.215 | E24: 5/1/28 | F24: 103.25 | G24: =IF(ISNUMBER(D24),F24-D24,"") -> 13.035 | H24: Mid 2028 | I24: 0.075 | J24: NVDA 2% 2031 | K24: 39 | L24: Triple Net | M24: 16.4yrs, two 10-yr ext. | N24: Summer 2026 | O24: Oct 2027 - Apr 2028 | P24: 341
A25: Fluidstack-led JV (Flash Compute LLC) 7 1/4% Sec Notes due 12/31/2030 | B25: FLASHC | C25: Fluidstack (Google backstop) | D25: =Monitor!H25 -> 99.374 | E25: 12/31/27 | F25: 103.63 | G25: =IF(ISNUMBER(D25),F25-D25,"") -> 4.256 | H25: Late 2026 | I25: 0.325 | J25: GOOGL 4.1% 2031 | K25: 42 | L25: Modified Gross | M25: 25yrs, two 5-yr shortening options | N25: Sept 2025 | O25: Late 4Q26 | P25: 234
A26: Fluidstack/Next Frontier JV (Meridian Arc Holdco LLC) 6 1/4% Sec Notes due 4/30/2031 | B26: MERIDI | C26: Fluidstack (Google backstop) | D26: =Monitor!H26 -> 91.868 | E26: 4/30/28 | F26: 103.13 | G26: =IF(ISNUMBER(D26),F26-D26,"") -> 11.262 | H26: Mid 2027 | I26: 0.13 | J26: GOOGL 4.1% 2031 | K26: 42 | L26: Triple Net | M26: 15yrs, three 5-yr ext. | N26: May 2026 | O26: Aug 2027 - Feb 2028 | P26: 287
A27: Fluidstack/Next Frontier JV (Zenith Arc LLC) 8 7/8% Sec Notes due 8/31/2031 | B27: ZENARC | C27: Jane Street | D27: =Monitor!H27 -> 85.008 | E27: 8/31/28 | F27: 104.44 | G27: =IF(ISNUMBER(D27),F27-D27,"") -> 19.432 | H27: Late 2027 | I27: 0.089 | J27: JANEST 7.294% 2031 | K27: 196 | L27: Triple Net | M27: 15yrs, two 5-yr ext. | N27: July 2026 | O27: Oct 2027 - Nov 2028 | P27: 606
A28: Galaxy Digital (Galaxy Helios Data Centers II LLC) 9 7/8% Sec Notes due 8/1/2031 | B28: GALAXY | C28: CoreWeave | D28: =Monitor!H28 -> 91.064 | E28: 8/1/28 | F28: 104.94 | G28: =IF(ISNUMBER(D28),F28-D28,"") -> 13.876 | H28: Late 2028 | I28: 0.099 | J28: CRWV 9% 2031 | K28: 670 | L28: Modified Gross | M28: 15yrs, two 5-yr ext. | N28: 4Q25 | O28: 2Q27 - 1Q28 | P28: 520
A29: Prime Data Centers (Elk Grove Village Property LLC) 7 1/2% Sec Notes due 6/15/2031 | B29: ELKGVP | C29: CoreWeave | D29: =Monitor!H29 -> 93.622 | E29: 6/15/28 | F29: 103.75 | G29: =IF(ISNUMBER(D29),F29-D29,"") -> 10.128 | H29: Mid 2027 | I29: 0.195 | J29: CRWV 9% 2031 | K29: 670 | L29: Triple Net | M29: 15yrs, two 7-yr ext. | N29: Mid 2024 | O29: Oct 2025 - Early 2027 | P29: 399
A30: SB Energy (SE Cosmos, LLC) 8 7/8% Sec Notes due 5/1/2031 | B30: SECMOS | C30: SoftBank | D30: =Monitor!H30 -> 95.294 | E30: 5/1/28 | F30: 104.44 | G30: =IF(ISNUMBER(D30),F30-D30,"") -> 9.146 | H30: N/A | I30: 0 | J30: SOFTBK 8.25% 2031 | K30: 376 | L30: Triple Net | M30: 15yrs, one 10-yr ext. | N30: Feb 2026 | O30: Dec 2026 - June 2027 | P30: 482
A31: TeraWulf (WULF Compute LLC) 7 3/4% Sec Notes due 10/15/2030 | B31: WULF | C31: Fluidstack (Google backstop) 366MW / Core42 60MW | D31: =Monitor!H31 -> 102.417 | E31: 10/15/27 | F31: 103.88 | G31: =IF(ISNUMBER(D31),F31-D31,"") -> 1.463 | H31: Late 2026 | I31: 0.45 | J31: GOOGL 4.1% 2031 | K31: 42 | L31: Modified Gross | M31: 10yrs, two 5-yr ext. | N31: Apr 2025 (Core42: late 2024) | O31: May - Dec 2026 (Core42: 3Q25-4Q25) | P31: 132
A32: Yondr Group/JK Land Holdings JV (Yondr JK 1, LLC) 6 7/8% Sec Notes due 6/30/2031 | B32: YNDRDC | C32: Oracle | D32: =Monitor!H32 -> 89.657 | E32: 6/30/28 | F32: 103.44 | G32: =IF(ISNUMBER(D32),F32-D32,"") -> 13.783 | H32: Late 2028 | I32: 0.088 | J32: ORCL 4.95% 2031 | K32: 147 | L32: Modified Gross | M32: 15yrs, two 5-yr ext. | N32: Feb 2026 | O32: Jan 2028 - Oct 2028 | P32: 414
A34: Tenant / parent comparables
A35: CoreWeave 9 3/4% Sr Notes due 10/1/2031 | B35: CRWV | C35: CoreWeave | D35: =Monitor!H35 -> 81.122 | P35: 768
A36: Oracle 4.95% Sr Notes due 2/4/2031 | B36: ORCL | C36: Oracle | D36: =Monitor!H36 -> 91.99 | P36: 149

Sheet Financials
A1: Project financial metrics
A2: From Barclays Figure 9 (15-Sep). Rent yield on cost and debt per MW are calculated here. Estimates are Barclays': base rent is estimated where not disclosed; leverage at issuance = pre-amortization debt / run-rate NOI.
A4: Company / description | B4: Ticker | C4: Tenant | D4: LIVE price | E4: LIVE yield % | F4: Amt o/s ($mn) | G4: Facility cost ($mn) | H4: Cost per MW ($mn) | I4: Est. base rent per MW ($mn) | J4: Annual rent escalator | K4: % of funding debt financed | L4: Gross leverage at issuance (x) | M4: Gross leverage at maturity (x) | N4: Rent yield on cost | O4: Debt per MW ($mn) | P4: Critical IT (MW)
A5: Investment Grade HPC Data Center Builders
A6: Hut 8 (Beacon Point DC LLC) 6.129% Sec Notes due 11/30/2042 | B6: HUTBPA | C6: NVIDIA | D6: =Monitor!H6 -> 92.424 | E6: =Monitor!J6 -> 6.9070348 | F6: =Monitor!G6 -> 4250 | G6: 3871 | H6: 11 | I6: 1.57 | J6: 3.0% | K6: 0.97 | L6: 7.7 | M6: 0 | N6: =IF(AND(ISNUMBER(I6),ISNUMBER(H6)),I6/H6,"") -> 0.14272727 | O6: =IF(AND(ISNUMBER(F6),ISNUMBER(P6),P6>0),F6/P6,"") -> 12.073864 | P6: 352
A7: Hut 8 (Hut 8 DC LLC) 6.192% Sec Notes due 11/15/2042 | B7: HUTRBA | C7: Fluidstack (Google backstop) | D7: =Monitor!H7 -> 93.919 | E7: =Monitor!J7 -> 6.8227402 | F7: =Monitor!G7 -> 3250 | G7: 3057 | H7: 12.5 | I7: 1.5 | J7: 3.0% | K7: 0.97 | L7: 8.8 | M7: 0 | N7: =IF(AND(ISNUMBER(I7),ISNUMBER(H7)),I7/H7,"") -> 0.12 | O7: =IF(AND(ISNUMBER(F7),ISNUMBER(P7),P7>0),F7/P7,"") -> 13.265306 | P7: 245
A8: BlueOwl/Meta JV (Beignet Investor LLC) 6.581% Sec Notes due 5/30/2049 | B8: RPLDCI | C8: Meta | D8: =Monitor!H8 -> 91.908 | E8: =Monitor!J8 -> 7.4801614 | F8: =Monitor!G8 -> 27293.8 | G8: 28800 | H8: 14 | I8: 1.23 | J8: 2.0% | K8: 0.9 | L8: 9.1 | M8: 0 | N8: =IF(AND(ISNUMBER(I8),ISNUMBER(H8)),I8/H8,"") -> 0.087857143 | O8: =IF(AND(ISNUMBER(F8),ISNUMBER(P8),P8>0),F8/P8,"") -> 13.22374 | P8: 2064
A9: Blackrock/Meta JV (Sopapilla Investor LLC) 7.534% Sec Notes due 11/30/2048 | B9: TXEDCI | C9: Meta | D9: =Monitor!H9 -> 98.999 | E9: =Monitor!J9 -> 7.6225604 | F9: =Monitor!G9 -> 12639.5 | G9: 13700 | H9: 14.3 | I9: 1.38 | J9: 2.0% | K9: 0.9 | L9: 9.3 | M9: 0 | N9: =IF(AND(ISNUMBER(I9),ISNUMBER(H9)),I9/H9,"") -> 0.096503497 | O9: =IF(AND(ISNUMBER(F9),ISNUMBER(P9),P9>0),F9/P9,"") -> 13.166146 | P9: 960
A10: Related Digital (RD Michigan Pro Owner I) 7.50% Sec Notes due 3/30/2045 | B10: RDMICH | C10: Oracle | D10: =Monitor!H10 -> 87.247 | E10: =Monitor!J10 -> 8.9678816 | F10: =Monitor!G10 -> 14000 | G10: 15543 | H10: 16 | I10: 1.43 | J10: 3.0% | K10: 0.9 | L10: 10.1 | M10: 0 | N10: =IF(AND(ISNUMBER(I10),ISNUMBER(H10)),I10/H10,"") -> 0.089375 | O10: =IF(AND(ISNUMBER(F10),ISNUMBER(P10),P10>0),F10/P10,"") -> 14.373717 | P10: 974
A11: QTS (QTS Central Issuer LLC) 6.625% Sec Notes due 9/1/2031 (5NC2) | B11: QTSODY | C11: Microsoft | D11: =Monitor!H11 -> 97.166 | E11: =Monitor!J11 -> 7.3295727 | F11: =Monitor!G11 -> 3900 | I11: 1.74 | J11: 3.0% | L11: 11 | M11: 9.8 | N11: =IF(AND(ISNUMBER(I11),ISNUMBER(H11)),I11/H11,"") | O11: =IF(AND(ISNUMBER(F11),ISNUMBER(P11),P11>0),F11/P11,"") -> 19.117647 | P11: 204
A12: QTS (QTS Fayetteville Dc1-2 LLC) 5.70% Sec Notes due 4/15/2036 | B12: QTSQST | C12: Microsoft | D12: =Monitor!H12 -> 87.991 | E12: =Monitor!J12 -> 7.5219323 | F12: =Monitor!G12 -> 4600 | I12: 0.9 | J12: 3.0% | L12: 15 | M12: 11.3 | N12: =IF(AND(ISNUMBER(I12),ISNUMBER(H12)),I12/H12,"") | O12: =IF(AND(ISNUMBER(F12),ISNUMBER(P12),P12>0),F12/P12,"") -> 13.529412 | P12: 340
A14: High Yield HPC Data Center Builders
A15: Applied Digital (APLD ComputeCo LLC) 9 1/4% Sec Notes due 12/15/2030 | B15: APLD | C15: CoreWeave | D15: =Monitor!H15 -> 102.776 | E15: =Monitor!J15 -> 8.4534708 | F15: =Monitor!G15 -> 2350 | G15: 3100 | H15: 12.4 | I15: 1.39 | J15: 3.0% | K15: 0.66 | L15: 7.2 | M15: 4.5 | N15: =IF(AND(ISNUMBER(I15),ISNUMBER(H15)),I15/H15,"") -> 0.11209677 | O15: =IF(AND(ISNUMBER(F15),ISNUMBER(P15),P15>0),F15/P15,"") -> 9.4 | P15: 250
A16: Applied Digital (APLD ComputeCo 2 LLC) 6 3/4% Sec Notes due 3/15/2031 | B16: PFORGE | C16: Oracle | D16: =Monitor!H16 -> 95.153 | E16: =Monitor!J16 -> 8.1104983 | F16: =Monitor!G16 -> 2150 | G16: 2391 | H16: 12 | I16: 1.34 | J16: 2.5% | K16: 0.8 | L16: 9.1 | M16: 6.6 | N16: =IF(AND(ISNUMBER(I16),ISNUMBER(H16)),I16/H16,"") -> 0.11166667 | O16: =IF(AND(ISNUMBER(F16),ISNUMBER(P16),P16>0),F16/P16,"") -> 10.75 | P16: 200
A17: Applied Digital (APLD ComputeCo 3 LLC) 7% Sec Notes due 6/15/2031 | B17: ELNFOR | C17: CoreWeave | D17: =Monitor!H17 -> 92.836 | E17: =Monitor!J17 -> 8.831383 | F17: =Monitor!G17 -> 1590 | G17: 1923 | H17: 12.8 | I17: 1.43 | J17: 3.0% | K17: 0.74 | L17: 8.2 | M17: 6.3 | N17: =IF(AND(ISNUMBER(I17),ISNUMBER(H17)),I17/H17,"") -> 0.11171875 | O17: =IF(AND(ISNUMBER(F17),ISNUMBER(P17),P17>0),F17/P17,"") -> 10.6 | P17: 150
A18: Cipher Digital (Cipher Compute LLC) 7 1/8% Sec Notes due 11/15/2030 | B18: CIFR | C18: Fluidstack (Google backstop) | D18: =Monitor!H18 -> 99.088 | E18: =Monitor!J18 -> 7.3958154 | F18: =Monitor!G18 -> 1733 | G18: 2443 | H18: 11.8 | I18: 1.59 | J18: 3.0% | K18: 0.7 | L18: 6.1 | M18: 3 | N18: =IF(AND(ISNUMBER(I18),ISNUMBER(H18)),I18/H18,"") -> 0.13474576 | O18: =IF(AND(ISNUMBER(F18),ISNUMBER(P18),P18>0),F18/P18,"") -> 8.3719807 | P18: 207
A19: Cipher Digital (Black Pearl Compute LLC) 6 1/8% Sec Notes due 2/15/2031 | B19: BLKPRL | C19: Amazon | D19: =Monitor!H19 -> 98.352 | E19: =Monitor!J19 -> 6.5859493 | F19: =Monitor!G19 -> 2000 | G19: 2100 | H19: 9.7 | I19: 1.38 | J19: 3.0% | K19: 0.85 | L19: 6.7 | M19: 4.3 | N19: =IF(AND(ISNUMBER(I19),ISNUMBER(H19)),I19/H19,"") -> 0.14226804 | O19: =IF(AND(ISNUMBER(F19),ISNUMBER(P19),P19>0),F19/P19,"") -> 9.2592593 | P19: 216
A20: Cipher Digital (Stingray Compute LLC) 6% Sec Notes due 6/15/2031 | B20: STNGRY | C20: Amazon | D20: =Monitor!H20 -> 95.265 | E20: =Monitor!J20 -> 7.2172472 | F20: =Monitor!G20 -> 810 | G20: 735 | H20: 10.5 | I20: 1.58 | J20: 3.0% | K20: 0.98 | L20: 7.3 | M20: 4.9 | N20: =IF(AND(ISNUMBER(I20),ISNUMBER(H20)),I20/H20,"") -> 0.15047619 | O20: =IF(AND(ISNUMBER(F20),ISNUMBER(P20),P20>0),F20/P20,"") -> 11.571429 | P20: 70
A21: Core Scientific (Core Scientific Finance I LLC) 7 3/4% Sec Notes due 5/15/2031 | B21: CORZ | C21: CoreWeave | D21: =Monitor!H21 -> 93.155 | E21: =Monitor!J21 -> 9.6475756 | F21: =Monitor!G21 -> 3300 | G21: 5500 | H21: 9.3 | I21: 1.2 | J21: 3.0% | K21: 0.56 | L21: 5.7 | M21: 3.8 | N21: =IF(AND(ISNUMBER(I21),ISNUMBER(H21)),I21/H21,"") -> 0.12903226 | O21: =IF(AND(ISNUMBER(F21),ISNUMBER(P21),P21>0),F21/P21,"") -> 5.5932203 | P21: 590
A22: Edged (Edged Compute LLC) 7 1/2% Sec Notes due 4/30/2031 | B22: EDGCOM | C22: CoreWeave (Chicago) / Alibaba (Atlanta) | D22: =Monitor!H22 -> 87.946 | E22: =Monitor!J22 -> 10.899613 | F22: =Monitor!G22 -> 1300 | G22: 1633 | H22: 14.3 | I22: 1.71 | J22: 3.0% | K22: 0.71 | L22: 7.4 | M22: 6 | N22: =IF(AND(ISNUMBER(I22),ISNUMBER(H22)),I22/H22,"") -> 0.11958042 | O22: =IF(AND(ISNUMBER(F22),ISNUMBER(P22),P22>0),F22/P22,"") -> 11.403509 | P22: 114
A23: Fleet Data Centers/Tract (SV RNO Property Owner 1) 5 7/8% Sec Notes due 3/1/2031 | B23: TRACTC | C23: NVIDIA | D23: =Monitor!H23 -> 89.109 | E23: =Monitor!J23 -> 8.8175717 | F23: =Monitor!G23 -> 3800 | G23: 4400 | H23: 22 | I23: 2 | J23: 3.25% | K23: 0.83 | L23: 9.1 | M23: 8 | N23: =IF(AND(ISNUMBER(I23),ISNUMBER(H23)),I23/H23,"") -> 0.090909091 | O23: =IF(AND(ISNUMBER(F23),ISNUMBER(P23),P23>0),F23/P23,"") -> 19 | P23: 200
A24: Fleet Data Centers/Tract (PR RNO Property Owner 1) 6 1/2% Sec Notes due 5/1/2031 | B24: TRACTD | C24: NVIDIA | D24: =Monitor!H24 -> 90.215 | E24: =Monitor!J24 -> 9.2035095 | F24: =Monitor!G24 -> 4585 | G24: 4435 | H24: 22.2 | I24: 2.27 | J24: 3.25% | K24: 0.91 | L24: 10 | M24: 8.7 | N24: =IF(AND(ISNUMBER(I24),ISNUMBER(H24)),I24/H24,"") -> 0.10225225 | O24: =IF(AND(ISNUMBER(F24),ISNUMBER(P24),P24>0),F24/P24,"") -> 22.925 | P24: 200
A25: Fluidstack-led JV (Flash Compute LLC) 7 1/4% Sec Notes due 12/31/2030 | B25: FLASHC | C25: Fluidstack (Google backstop) | D25: =Monitor!H25 -> 99.374 | E25: =Monitor!J25 -> 7.4587606 | F25: =Monitor!G25 -> 1300 | G25: 1354 | H25: 8.1 | I25: 1.55 | J25: 3.0% | K25: 0.79 | L25: 5.9 | M25: 3.5 | N25: =IF(AND(ISNUMBER(I25),ISNUMBER(H25)),I25/H25,"") -> 0.19135802 | O25: =IF(AND(ISNUMBER(F25),ISNUMBER(P25),P25>0),F25/P25,"") -> 7.7380952 | P25: 168
A26: Fluidstack/Next Frontier JV (Meridian Arc Holdco LLC) 6 1/4% Sec Notes due 4/30/2031 | B26: MERIDI | C26: Fluidstack (Google backstop) | D26: =Monitor!H26 -> 91.868 | E26: =Monitor!J26 -> 8.4501543 | F26: =Monitor!G26 -> 5700 | G26: 5250 | H26: 12.2 | I26: 1.49 | J26: 3.0% | K26: 0.91 | L26: 8.9 | M26: 7.1 | N26: =IF(AND(ISNUMBER(I26),ISNUMBER(H26)),I26/H26,"") -> 0.12213115 | O26: =IF(AND(ISNUMBER(F26),ISNUMBER(P26),P26>0),F26/P26,"") -> 13.255814 | P26: 430
... A32: Yondr Group/JK Land Holdings JV (Yondr JK 1, LLC) 6 7/8% Sec Notes due 6/30/2031 | B32: YNDRDC | C32: Oracle | D32: =Monitor!H32 -> 89.657 | E32: =Monitor!J32 -> 9.6972191 | F32: =Monitor!G32 -> 715 | G32: 738 | H32: 15.4 | I32: 1.95 | J32: 3.0% | K32: 0.82 | L32: 8.9 | M32: 7.3 | N32: =IF(AND(ISNUMBER(I32),ISNUMBER(H32)),I32/H32,"") -> 0.12662338 | O32: =IF(AND(ISNUMBER(F32),ISNUMBER(P32),P32>0),F32/P32,"") -> 14.895833 | P32: 48
A34: Tenant / parent comparables
A35: CoreWeave 9 3/4% Sr Notes due 10/1/2031 | B35: CRWV | C35: CoreWeave | D35: =Monitor!H35 -> 81.122 | E35: =Monitor!J35 -> 15.566073 | F35: =Monitor!G35 -> 2750
A36: Oracle 4.95% Sr Notes due 2/4/2031 | B36: ORCL | C36: Oracle | D36: =Monitor!H36 -> 91.99 | E36: =Monitor!J36 -> 7.128663 | F36: =Monitor!G36 -> 3500

Sheet Since Barclays
A1: Change in levels: Barclays 3-Aug and 15-Sep vs live
A2: Barclays Figure 5 levels (YTW; callable bonds on OAS). Live yield is yield to maturity at the live composite price, so yield changes are approximate.
A4: Company / description | B4: Ticker | C4: Tenant | D4: 3-Aug price | E4: 3-Aug YTW % | F4: 3-Aug spread (bp) | G4: 15-Sep price | H4: 15-Sep YTW % | I4: 15-Sep spread (bp) | J4: LIVE price | K4: LIVE yield % | L4: Δ price vs 15-Sep (pts) | M4: Δ yield vs 15-Sep (bp) | N4: Δ yield vs 3-Aug (bp) | O4: Δ price vs 3-Aug (pts)
A5: Investment Grade HPC Data Center Builders
A6: Hut 8 (Beacon Point DC LLC) 6.129% Sec Notes due 11/30/2042 | B6: HUTBPA | C6: NVIDIA | D6: 96.42 | E6: 6.59 | F6: 185 | G6: 93.65 | H6: 6.99 | I6: 200 | J6: =Monitor!H6 -> 92.424 | K6: =Monitor!J6 -> 6.9070348 | L6: =IF(ISNUMBER(J6),J6-G6,"") -> -1.226 | M6: =IF(ISNUMBER(K6),(K6-H6)*100,"") -> -8.2965174 | N6: =IF(ISNUMBER(K6),(K6-E6)*100,"") -> 31.703483 | O6: =IF(ISNUMBER(J6),J6-D6,"") -> -3.996
A7: Hut 8 (Hut 8 DC LLC) 6.192% Sec Notes due 11/15/2042 | B7: HUTRBA | C7: Fluidstack (Google backstop) | D7: 97.46 | E7: 6.54 | F7: 184 | G7: 96.15 | H7: 6.74 | I7: 178 | J7: =Monitor!H7 -> 93.919 | K7: =Monitor!J7 -> 6.8227402 | L7: =IF(ISNUMBER(J7),J7-G7,"") -> -2.231 | M7: =IF(ISNUMBER(K7),(K7-H7)*100,"") -> 8.2740175 | N7: =IF(ISNUMBER(K7),(K7-E7)*100,"") -> 28.274018 | O7: =IF(ISNUMBER(J7),J7-D7,"") -> -3.541
A8: BlueOwl/Meta JV (Beignet Investor LLC) 6.581% Sec Notes due 5/30/2049 | B8: RPLDCI | C8: Meta | D8: 97.07 | E8: 6.89 | F8: 197 | G8: 94.73 | H8: 7.15 | I8: 205 | J8: =Monitor!H8 -> 91.908 | K8: =Monitor!J8 -> 7.4801614 | L8: =IF(ISNUMBER(J8),J8-G8,"") -> -2.822 | M8: =IF(ISNUMBER(K8),(K8-H8)*100,"") -> 33.016135 | N8: =IF(ISNUMBER(K8),(K8-E8)*100,"") -> 59.016135 | O8: =IF(ISNUMBER(J8),J8-D8,"") -> -5.162
A9: Blackrock/Meta JV (Sopapilla Investor LLC) 7.534% Sec Notes due 11/30/2048 | B9: TXEDCI | C9: Meta | D9: 104.11 | E9: 7.09 | F9: 217 | G9: 103.65 | H9: 7.22 | I9: 222 | J9: =Monitor!H9 -> 98.999 | K9: =Monitor!J9 -> 7.6225604 | L9: =IF(ISNUMBER(J9),J9-G9,"") -> -4.651 | M9: =IF(ISNUMBER(K9),(K9-H9)*100,"") -> 40.256044 | N9: =IF(ISNUMBER(K9),(K9-E9)*100,"") -> 53.256044 | O9: =IF(ISNUMBER(J9),J9-D9,"") -> -5.111
A10: Related Digital (RD Michigan Pro Owner I) 7.50% Sec Notes due 3/30/2045 | B10: RDMICH | C10: Oracle | D10: 96.97 | E10: 7.87 | F10: 271 | G10: 94.25 | H10: 8.21 | I10: 279 | J10: =Monitor!H10 -> 87.247 | K10: =Monitor!J10 -> 8.9678816 | L10: =IF(ISNUMBER(J10),J10-G10,"") -> -7.003 | M10: =IF(ISNUMBER(K10),(K10-H10)*100,"") -> 75.788156 | N10: =IF(ISNUMBER(K10),(K10-E10)*100,"") -> 109.78816 | O10: =IF(ISNUMBER(J10),J10-D10,"") -> -9.723
A11: QTS (QTS Central Issuer LLC) 6.625% Sec Notes due 9/1/2031 (5NC2) | B11: QTSODY | C11: Microsoft | G11: 98.88 | H11: 6.9 | I11: 176 | J11: =Monitor!H11 -> 97.166 | K11: =Monitor!J11 -> 7.3295727 | L11: =IF(ISNUMBER(J11),J11-G11,"") -> -1.714 | M11: =IF(ISNUMBER(K11),(K11-H11)*100,"") -> 42.957271
A12: QTS (QTS Fayetteville Dc1-2 LLC) 5.70% Sec Notes due 4/15/2036 | B12: QTSQST | C12: Microsoft | D12: 91.83 | E12: 6.87 | F12: 219 | G12: 89.96 | H12: 7.17 | I12: 222 | J12: =Monitor!H12 -> 87.991 | K12: =Monitor!J12 -> 7.5219323 | L12: =IF(ISNUMBER(J12),J12-G12,"") -> -1.969 | M12: =IF(ISNUMBER(K12),(K12-H12)*100,"") -> 35.193235 | N12: =IF(ISNUMBER(K12),(K12-E12)*100,"") -> 65.193235 | O12: =IF(ISNUMBER(J12),J12-D12,"") -> -3.839
A14: High Yield HPC Data Center Builders
A15: Applied Digital (APLD ComputeCo LLC) 9 1/4% Sec Notes due 12/15/2030 | B15: APLD | C15: CoreWeave | D15: 106.57 | E15: 7.29 | F15: 240 | G15: 105.29 | H15: 7.6 | I15: 236 | J15: =Monitor!H15 -> 102.776 | K15: =Monitor!J15 -> 8.4534708 | L15: =IF(ISNUMBER(J15),J15-G15,"") -> -2.514 | M15: =IF(ISNUMBER(K15),(K15-H15)*100,"") -> 85.347083 | N15: =IF(ISNUMBER(K15),(K15-E15)*100,"") -> 116.34708 | O15: =IF(ISNUMBER(J15),J15-D15,"") -> -3.794
A16: Applied Digital (APLD ComputeCo 2 LLC) 6 3/4% Sec Notes due 3/15/2031 | B16: PFORGE | C16: Oracle | D16: 98.15 | E16: 7.28 | F16: 289 | G16: 96 | H16: 7.93 | I16: 314 | J16: =Monitor!H16 -> 95.153 | K16: =Monitor!J16 -> 8.1104983 | L16: =IF(ISNUMBER(J16),J16-G16,"") -> -0.847 | M16: =IF(ISNUMBER(K16),(K16-H16)*100,"") -> 18.049834 | N16: =IF(ISNUMBER(K16),(K16-E16)*100,"") -> 83.049834 | O16: =IF(ISNUMBER(J16),J16-D16,"") -> -2.997
A17: Applied Digital (APLD ComputeCo 3 LLC) 7% Sec Notes due 6/15/2031 | B17: ELNFOR | C17: CoreWeave | D17: 98.33 | E17: 7.44 | F17: 325 | G17: 95.75 | H17: 8.19 | I17: 338 | J17: =Monitor!H17 -> 92.836 | K17: =Monitor!J17 -> 8.831383 | L17: =IF(ISNUMBER(J17),J17-G17,"") -> -2.914 | M17: =IF(ISNUMBER(K17),(K17-H17)*100,"") -> 64.138297 | N17: =IF(ISNUMBER(K17),(K17-E17)*100,"") -> 139.1383 | O17: =IF(ISNUMBER(J17),J17-D17,"") -> -5.494
A18: Cipher Digital (Cipher Compute LLC) 7 1/8% Sec Notes due 11/15/2030 | B18: CIFR | C18: Fluidstack (Google backstop) | D18: 102.45 | E18: 6.46 | F18: 181 | G18: 101.5 | H18: 6.72 | I18: 169 | J18: =Monitor!H18 -> 99.088 | K18: =Monitor!J18 -> 7.3958154 | L18: =IF(ISNUMBER(J18),J18-G18,"") -> -2.412 | M18: =IF(ISNUMBER(K18),(K18-H18)*100,"") -> 67.581538 | N18: =IF(ISNUMBER(K18),(K18-E18)*100,"") -> 93.581538 | O18: =IF(ISNUMBER(J18),J18-D18,"") -> -3.362
A19: Cipher Digital (Black Pearl Compute LLC) 6 1/8% Sec Notes due 2/15/2031 | B19: BLKPRL | C19: Amazon | D19: 100.06 | E19: 6.1 | F19: 164 | G19: 99.75 | H19: 6.22 | I19: 127 | J19: =Monitor!H19 -> 98.352 | K19: =Monitor!J19 -> 6.5859493 | L19: =IF(ISNUMBER(J19),J19-G19,"") -> -1.398 | M19: =IF(ISNUMBER(K19),(K19-H19)*100,"") -> 36.594926 | N19: =IF(ISNUMBER(K19),(K19-E19)*100,"") -> 48.594926 | O19: =IF(ISNUMBER(J19),J19-D19,"") -> -1.708
A20: Cipher Digital (Stingray Compute LLC) 6% Sec Notes due 6/15/2031 | B20: STNGRY | C20: Amazon | D20: 98.17 | E20: 6.44 | F20: 199 | G20: 97.13 | H20: 6.72 | I20: 186 | J20: =Monitor!H20 -> 95.265 | K20: =Monitor!J20 -> 7.2172472 | L20: =IF(ISNUMBER(J20),J20-G20,"") -> -1.865 | M20: =IF(ISNUMBER(K20),(K20-H20)*100,"") -> 49.724717 | N20: =IF(ISNUMBER(K20),(K20-E20)*100,"") -> 77.724717 | O20: =IF(ISNUMBER(J20),J20-D20,"") -> -2.905
A21: Core Scientific (Core Scientific Finance I LLC) 7 3/4% Sec Notes due 5/15/2031 | B21: CORZ | C21: CoreWeave | D21: 98.51 | E21: 8.15 | F21: 386 | G21: 97.67 | H21: 8.41 | I21: 357 | J21: =Monitor!H21 -> 93.155 | K21: =Monitor!J21 -> 9.6475756 | L21: =IF(ISNUMBER(J21),J21-G21,"") -> -4.515 | M21: =IF(ISNUMBER(K21),(K21-H21)*100,"") -> 123.75756 | N21: =IF(ISNUMBER(K21),(K21-E21)*100,"") -> 149.75756 | O21: =IF(ISNUMBER(J21),J21-D21,"") -> -5.355
A22: Edged (Edged Compute LLC) 7 1/2% Sec Notes due 4/30/2031 | B22: EDGCOM | C22: CoreWeave (Chicago) / Alibaba (Atlanta) | D22: 94.94 | E22: 9 | F22: 462 | G22: 94.25 | H22: 9.3 | I22: 453 | J22: =Monitor!H22 -> 87.946 | K22: =Monitor!J22 -> 10.899613 | L22: =IF(ISNUMBER(J22),J22-G22,"") -> -6.304 | M22: =IF(ISNUMBER(K22),(K22-H22)*100,"") -> 159.96128 | N22: =IF(ISNUMBER(K22),(K22-E22)*100,"") -> 189.96128 | O22: =IF(ISNUMBER(J22),J22-D22,"") -> -6.994
A23: Fleet Data Centers/Tract (SV RNO Property Owner 1) 5 7/8% Sec Notes due 3/1/2031 | B23: TRACTC | C23: NVIDIA | D23: 93.53 | E23: 7.62 | F23: 330 | G23: 92.63 | H23: 7.93 | I23: 315 | J23: =Monitor!H23 -> 89.109 | K23: =Monitor!J23 -> 8.8175717 | L23: =IF(ISNUMBER(J23),J23-G23,"") -> -3.521 | M23: =IF(ISNUMBER(K23),(K23-H23)*100,"") -> 88.75717 | N23: =IF(ISNUMBER(K23),(K23-E23)*100,"") -> 119.75717 | O23: =IF(ISNUMBER(J23),J23-D23,"") -> -4.421
A24: Fleet Data Centers/Tract (PR RNO Property Owner 1) 6 1/2% Sec Notes due 5/1/2031 | B24: TRACTD | C24: NVIDIA | D24: 94.48 | E24: 7.94 | F24: 357 | G24: 93.75 | H24: 8.2 | I24: 341 | J24: =Monitor!H24 -> 90.215 | K24: =Monitor!J24 -> 9.2035095 | L24: =IF(ISNUMBER(J24),J24-G24,"") -> -3.535 | M24: =IF(ISNUMBER(K24),(K24-H24)*100,"") -> 100.35095 | N24: =IF(ISNUMBER(K24),(K24-E24)*100,"") -> 126.35095 | O24: =IF(ISNUMBER(J24),J24-D24,"") -> -4.265
A25: Fluidstack-led JV (Flash Compute LLC) 7 1/4% Sec Notes due 12/31/2030 | B25: FLASHC | C25: Fluidstack (Google backstop) | D25: 101.33 | E25: 6.8 | F25: 232 | G25: 100.25 | H25: 7.19 | I25: 234 | J25: =Monitor!H25 -> 99.374 | K25: =Monitor!J25 -> 7.4587606 | L25: =IF(ISNUMBER(J25),J25-G25,"") -> -0.876 | M25: =IF(ISNUMBER(K25),(K25-H25)*100,"") -> 26.87606 | N25: =IF(ISNUMBER(K25),(K25-E25)*100,"") -> 65.87606 | O25: =IF(ISNUMBER(J25),J25-D25,"") -> -1.956
A26: Fluidstack/Next Frontier JV (Meridian Arc Holdco LLC) 6 1/4% Sec Notes due 4/30/2031 | B26: MERIDI | C26: Fluidstack (Google backstop) | D26: 96.41 | E26: 7.15 | F26: 274 | G26: 94.63 | H26: 7.67 | I26: 287 | J26: =Monitor!H26 -> 91.868 | K26: =Monitor!J26 -> 8.4501543 | L26: =IF(ISNUMBER(J26),J26-G26,"") -> -2.762 | M26: =IF(ISNUMBER(K26),(K26-H26)*100,"") -> 78.015426 | N26: =IF(ISNUMBER(K26),(K26-E26)*100,"") -> 130.01543 | O26: =IF(ISNUMBER(J26),J26-D26,"") -> -4.542
A27: Fluidstack/Next Frontier JV (Zenith Arc LLC) 8 7/8% Sec Notes due 8/31/2031 | B27: ZENARC | C27: Jane Street | G27: 92.5 | H27: 10.86 | I27: 606 | J27: =Monitor!H27 -> 85.008 | K27: =Monitor!J27 -> 13.095812 | L27: =IF(ISNUMBER(J27),J27-G27,"") -> -7.492 | M27: =IF(ISNUMBER(K27),(K27-H27)*100,"") -> 223.58125
A28: Galaxy Digital (Galaxy Helios Data Centers II LLC) 9 7/8% Sec Notes due 8/1/2031 | B28: GALAXY | C28: CoreWeave | D28: 101.2 | E28: 9.51 | F28: 505 | G28: 99.25 | H28: 10.1 | I28: 520 | J28: =Monitor!H28 -> 91.064 | K28: =Monitor!J28 -> 12.517412 | L28: =IF(ISNUMBER(J28),J28-G28,"") -> -8.186 | M28: =IF(ISNUMBER(K28),(K28-H28)*100,"") -> 241.74116 | N28: =IF(ISNUMBER(K28),(K28-E28)*100,"") -> 300.74116 | O28: =IF(ISNUMBER(J28),J28-D28,"") -> -10.136
A29: Prime Data Centers (Elk Grove Village Property LLC) 7 1/2% Sec Notes due 6/15/2031 | B29: ELKGVP | C29: CoreWeave | D29: 97.66 | E29: 8.15 | F29: 379 | G29: 95.63 | H29: 8.79 | I29: 399 | J29: =Monitor!H29 -> 93.622 | K29: =Monitor!J29 -> 9.2615243 | L29: =IF(ISNUMBER(J29),J29-G29,"") -> -2.008 | M29: =IF(ISNUMBER(K29),(K29-H29)*100,"") -> 47.15243 | N29: =IF(ISNUMBER(K29),(K29-E29)*100,"") -> 111.15243 | O29: =IF(ISNUMBER(J29),J29-D29,"") -> -4.038
A30: SB Energy (SE Cosmos, LLC) 8 7/8% Sec Notes due 5/1/2031 | B30: SECMOS | C30: SoftBank | D30: 98.94 | E30: 9.15 | F30: 467 | G30: 97.13 | H30: 9.66 | I30: 482 | J30: =Monitor!H30 -> 95.294 | K30: =Monitor!J30 -> 10.262203 | L30: =IF(ISNUMBER(J30),J30-G30,"") -> -1.836 | M30: =IF(ISNUMBER(K30),(K30-H30)*100,"") -> 60.220277 | N30: =IF(ISNUMBER(K30),(K30-E30)*100,"") -> 111.22028 | O30: =IF(ISNUMBER(J30),J30-D30,"") -> -3.646
A31: TeraWulf (WULF Compute LLC) 7 3/4% Sec Notes due 10/15/2030 | B31: WULF | C31: Fluidstack (Google backstop) 366MW / Core42 60MW | D31: 104.26 | E31: 6.26 | F31: 175 | G31: 103.9 | H31: 6.34 | I31: 132 | J31: =Monitor!H31 -> 102.417 | K31: =Monitor!J31 -> 7.0540663 | L31: =IF(ISNUMBER(J31),J31-G31,"") -> -1.483 | M31: =IF(ISNUMBER(K31),(K31-H31)*100,"") -> 71.406627 | N31: =IF(ISNUMBER(K31),(K31-E31)*100,"") -> 79.406627 | O31: =IF(ISNUMBER(J31),J31-D31,"") -> -1.843
A32: Yondr Group/JK Land Holdings JV (Yondr JK 1, LLC) 6 7/8% Sec Notes due 6/30/2031 | B32: YNDRDC | C32: Oracle | D32: 95.81 | E32: 8 | F32: 361 | G32: 92.75 | H32: 8.92 | I32: 414 | J32: =Monitor!H32 -> 89.657 | K32: =Monitor!J32 -> 9.6972191 | L32: =IF(ISNUMBER(J32),J32-G32,"") -> -3.093 | M32: =IF(ISNUMBER(K32),(K32-H32)*100,"") -> 77.721914 | N32: =IF(ISNUMBER(K32),(K32-E32)*100,"") -> 169.72191 | O32: =IF(ISNUMBER(J32),J32-D32,"") -> -6.153
A34: Tenant / parent comparables
A35: CoreWeave 9 3/4% Sr Notes due 10/1/2031 | B35: CRWV | C35: CoreWeave | D35: 91.58 | E35: 11.98 | F35: 752 | G35: 90.25 | H35: 12.46 | I35: 768 | J35: =Monitor!H35 -> 81.122 | K35: =Monitor!J35 -> 15.566073 | L35: =IF(ISNUMBER(J35),J35-G35,"") -> -9.128 | M35: =IF(ISNUMBER(K35),(K35-H35)*100,"") -> 310.60726 | N35: =IF(ISNUMBER(K35),(K35-E35)*100,"") -> 358.60726 | O35: =IF(ISNUMBER(J35),J35-D35,"") -> -10.458
A36: Oracle 4.95% Sr Notes due 2/4/2031 | B36: ORCL | C36: Oracle | D36: 95.95 | E36: 5.99 | F36: 164 | G36: 94.96 | H36: 6.28 | I36: 149 | J36: =Monitor!H36 -> 91.99 | K36: =Monitor!J36 -> 7.128663 | L36: =IF(ISNUMBER(J36),J36-G36,"") -> -2.97 | M36: =IF(ISNUMBER(K36),(K36-H36)*100,"") -> 84.866299 | N36: =IF(ISNUMBER(K36),(K36-E36)*100,"") -> 113.8663 | O36: =IF(ISNUMBER(J36),J36-D36,"") -> -3.96

Sheet Other Instruments
A1: Vendor and hyperscaler bonds, neocloud converts and HY, loans
A2: Live formulas as on the Monitor sheet. Snapshot reference: 2026-10-16_1248. Converts and loans are measured against par for comparability; their economic value depends on the equity / loan terms.
A4: Instrument | B4: Group | C4: Amt o/s ($mn) | D4: LIVE price | E4: Chg % 1D | F4: LIVE yield % | G4: Last trade size (TRACE) | H4: Price time | I4: Principal vs par ($mn) | J4: Principal vs par (%) | K4: Today's change in value ($mn) | L4: Yield at snapshot % | M4: Δ yield vs snapshot (bp) | N4: Rating S&P | O4: ISIN | P4: Bloomberg ticker (terminal)
A5: NVIDIA senior notes (June-2026 issue and 2036/2046)
A6: NVDA 4.25 '28 | B6: NVIDIA senior notes (June-2026 issue and 2036/2046) | C6: 3500 | D6: =_xll.BDP($P6,"LAST_PRICE") -> 98.887 | E6: =_xll.BDP($P6,"CHG_PCT_1D") -> 0.05224237 | F6: =_xll.BDP($P6,"YLD_YTM_MID") -> 4.9477722 | G6: =IFERROR(_xll.BDP($P6,"TRACE_LAST_TRADE_SIZE"),"n/a") -> 1000 | H6: =IFERROR(_xll.BDP($P6,"PRICE_LAST_TIME"),"") -> 16:44:24 | I6: =IF(AND(ISNUMBER(D6),ISNUMBER(C6)),(D6-100)/100*C6,"") -> -38.955 | J6: =IF(ISNUMBER(D6),(D6-100)/100,"") -> -0.01113 | K6: =IFERROR((D6-_xll.BDP($P6,"PX_CLOSE_1D"))/100*C6,"") -> 1.4 | L6: 4.9333572 | M6: =IF(AND(ISNUMBER(F6),ISNUMBER(L6)),(F6-L6)*100,"") -> 1.4415063 | N6: AA | O6: US67066GAP90 | P6: NVDA 4.25 06/15/28 Corp
A7: NVDA 4.35 '29 | B7: NVIDIA senior notes (June-2026 issue and 2036/2046) | C7: 3500 | D7: =_xll.BDP($P7,"LAST_PRICE") -> 97.973 | E7: =_xll.BDP($P7,"CHG_PCT_1D") -> -0.0070328491 | F7: =_xll.BDP($P7,"YLD_YTM_MID") -> 5.1789924 | G7: =IFERROR(_xll.BDP($P7,"TRACE_LAST_TRADE_SIZE"),"n/a") -> 20 | H7: =IFERROR(_xll.BDP($P7,"PRICE_LAST_TIME"),"") -> 16:44:24 | I7: =IF(AND(ISNUMBER(D7),ISNUMBER(C7)),(D7-100)/100*C7,"") -> -70.945 | J7: =IF(ISNUMBER(D7),(D7-100)/100,"") -> -0.02027 | K7: =IFERROR((D7-_xll.BDP($P7,"PX_CLOSE_1D"))/100*C7,"") -> 0.14 | L7: 5.174451 | M7: =IF(AND(ISNUMBER(F7),ISNUMBER(L7)),(F7-L7)*100,"") -> 0.45414712 | N7: AA | O7: US67066GAQ73 | P7: NVDA 4.35 06/15/29 Corp
A8: NVDA 4.5 '31 | B8: NVIDIA senior notes (June-2026 issue and 2036/2046) | C8: 4000 | D8: =_xll.BDP($P8,"LAST_PRICE") -> 95.952 | E8: =_xll.BDP($P8,"CHG_PCT_1D") -> 0.0072089296 | F8: =_xll.BDP($P8,"YLD_YTM_MID") -> 5.4839067 | G8: =IFERROR(_xll.BDP($P8,"TRACE_LAST_TRADE_SIZE"),"n/a") -> 12 | H8: =IFERROR(_xll.BDP($P8,"PRICE_LAST_TIME"),"") -> 16:44:24 | I8: =IF(AND(ISNUMBER(D8),ISNUMBER(C8)),(D8-100)/100*C8,"") -> -161.92 | J8: =IF(ISNUMBER(D8),(D8-100)/100,"") -> -0.04048 | K8: =IFERROR((D8-_xll.BDP($P8,"PX_CLOSE_1D"))/100*C8,"") -> -1.6 | L8: 5.4709213 | M8: =IF(AND(ISNUMBER(F8),ISNUMBER(L8)),(F8-L8)*100,"") -> 1.2985319 | N8: AA | O8: US67066GAR56 | P8: NVDA 4.5 06/15/31 Corp
A9: NVDA 4.75 '33 | B9: NVIDIA senior notes (June-2026 issue and 2036/2046) | C9: 3500 | D9: =_xll.BDP($P9,"LAST_PRICE") -> 95.049 | E9: =_xll.BDP($P9,"CHG_PCT_1D") -> -0.25740125 | F9: =_xll.BDP($P9,"YLD_YTM_MID") -> 5.6836283 | G9: =IFERROR(_xll.BDP($P9,"TRACE_LAST_TRADE_SIZE"),"n/a") -> 50 | H9: =IFERROR(_xll.BDP($P9,"PRICE_LAST_TIME"),"") -> 16:44:24 | I9: =IF(AND(ISNUMBER(D9),ISNUMBER(C9)),(D9-100)/100*C9,"") -> -173.285 | J9: =IF(ISNUMBER(D9),(D9-100)/100,"") -> -0.04951 | K9: =IFERROR((D9-_xll.BDP($P9,"PX_CLOSE_1D"))/100*C9,"") -> -2.625 | L9: 5.652406 | M9: =IF(AND(ISNUMBER(F9),ISNUMBER(L9)),(F9-L9)*100,"") -> 3.1222229 | N9: AA | O9: US67066GAS30 | P9: NVDA 4.75 06/15/33 Corp
A10: NVDA 4.95 '36 | B10: NVIDIA senior notes (June-2026 issue and 2036/2046) | C10: 4000 | D10: =_xll.BDP($P10,"LAST_PRICE") -> 93.078 | E10: =_xll.BDP($P10,"CHG_PCT_1D") -> -0.22418592 | F10: =_xll.BDP($P10,"YLD_YTM_MID") -> 5.8910648 | G10: =IFERROR(_xll.BDP($P10,"TRACE_LAST_TRADE_SIZE"),"n/a") -> 50 | H10: =IFERROR(_xll.BDP($P10,"PRICE_LAST_TIME"),"") -> 16:44:24 | I10: =IF(AND(ISNUMBER(D10),ISNUMBER(C10)),(D10-100)/100*C10,"") -> -276.88 | J10: =IF(ISNUMBER(D10),(D10-100)/100,"") -> -0.06922 | K10: =IFERROR((D10-_xll.BDP($P10,"PX_CLOSE_1D"))/100*C10,"") -> -10.76 | L10: 5.8594365 | M10: =IF(AND(ISNUMBER(F10),ISNUMBER(L10)),(F10-L10)*100,"") -> 3.1628256 | N10: AA | O10: US67066GAT13 | P10: NVDA 4.95 06/15/36 Corp
A11: NVDA 5.55 '46 | B11: NVIDIA senior notes (June-2026 issue and 2036/2046) | C11: 3000 | D11: =_xll.BDP($P11,"LAST_PRICE") -> 89.835 | E11: =_xll.BDP($P11,"CHG_PCT_1D") -> -0.22849531 | F11: =_xll.BDP($P11,"YLD_YTM_MID") -> 6.4707832 | G11: =IFERROR(_xll.BDP($P11,"TRACE_LAST_TRADE_SIZE"),"n/a") -> 2 | H11: =IFERROR(_xll.BDP($P11,"PRICE_LAST_TIME"),"") -> 16:44:24 | I11: =IF(AND(ISNUMBER(D11),ISNUMBER(C11)),(D11-100)/100*C11,"") -> -304.95 | J11: =IF(ISNUMBER(D11),(D11-100)/100,"") -> -0.10165 | K11: =IFERROR((D11-_xll.BDP($P11,"PX_CLOSE_1D"))/100*C11,"") -> -6.06 | L11: 6.4509419 | M11: =IF(AND(ISNUMBER(F11),ISNUMBER(L11)),(F11-L11)*100,"") -> 1.9841262 | N11: AA | O11: US67066GAU85 | P11: NVDA 5.55 06/15/46 Corp
A12: NVDA 5.625 '56 | B12: NVIDIA senior notes (June-2026 issue and 2036/2046) | C12: 3500 | D12: =_xll.BDP($P12,"LAST_PRICE") -> 87.466 | E12: =_xll.BDP($P12,"CHG_PCT_1D") -> -0.51128102 | F12: =_xll.BDP($P12,"YLD_YTM_MID") -> 6.6036484 | G12: =IFERROR(_xll.BDP($P12,"TRACE_LAST_TRADE_SIZE"),"n/a") -> 5MM+ | H12: =IFERROR(_xll.BDP($P12,"PRICE_LAST_TIME"),"") -> 16:44:24 | I12: =IF(AND(ISNUMBER(D12),ISNUMBER(C12)),(D12-100)/100*C12,"") -> -438.69 | J12: =IF(ISNUMBER(D12),(D12-100)/100,"") -> -0.12534 | K12: =IFERROR((D12-_xll.BDP($P12,"PX_CLOSE_1D"))/100*C12,"") -> -10.92 | L12: 6.58513 | M12: =IF(AND(ISNUMBER(F12),ISNUMBER(L12)),(F12-L12)*100,"") -> 1.8518343 | N12: AA | O12: US67066GAV68 | P12: NVDA 5.625 06/15/56 Corp
A13: Broadcom senior notes
A14: AVGO 4.6 2033 | B14: Broadcom senior notes | C14: 1250 | D14: =_xll.BDP($P14,"LAST_PRICE") -> 92.8 | E14: =_xll.BDP($P14,"CHG_PCT_1D") -> -0.17004354 | F14: =_xll.BDP($P14,"YLD_YTM_MID") -> 6.0070574 | G14: =IFERROR(_xll.BDP($P14,"TRACE_LAST_TRADE_SIZE"),"n/a") -> 2 | H14: =IFERROR(_xll.BDP($P14,"PRICE_LAST_TIME"),"") -> 16:44:24 | I14: =IF(AND(ISNUMBER(D14),ISNUMBER(C14)),(D14-100)/100*C14,"") -> -90 | J14: =IF(ISNUMBER(D14),(D14-100)/100,"") -> -0.072 | K14: =IFERROR((D14-_xll.BDP($P14,"PX_CLOSE_1D"))/100*C14,"") -> -1.4625 | L14: 5.9776009 | M14: =IF(AND(ISNUMBER(F14),ISNUMBER(L14)),(F14-L14)*100,"") -> 2.9456466 | N14: A- | O14: US11135FDA66 | P14: AVGO 4.6 01/15/2033 Corp
A15: AVGO 4.8 2034 | B15: Broadcom senior notes | C15: 1750 | D15: =_xll.BDP($P15,"LAST_PRICE") -> 90.962 | E15: =_xll.BDP($P15,"CHG_PCT_1D") -> -0.43272842 | F15: =_xll.BDP($P15,"YLD_YTM_MID") -> 6.2717355 | G15: =IFERROR(_xll.BDP($P15,"TRACE_LAST_TRADE_SIZE"),"n/a") -> 10 | H15: =IFERROR(_xll.BDP($P15,"PRICE_LAST_TIME"),"") -> 16:44:24 | I15: =IF(AND(ISNUMBER(D15),ISNUMBER(C15)),(D15-100)/100*C15,"") -> -158.165 | J15: =IF(ISNUMBER(D15),(D15-100)/100,"") -> -0.09038 | K15: =IFERROR((D15-_xll.BDP($P15,"PX_CLOSE_1D"))/100*C15,"") -> -5.145 | L15: 6.2306887 | M15: =IF(AND(ISNUMBER(F15),ISNUMBER(L15)),(F15-L15)*100,"") -> 4.1046776 | N15: A- | O15: US11135FCD15 | P15: AVGO 4.8 10/15/2034 Corp
A16: AVGO 5.2 2035 | B16: Broadcom senior notes | C16: 2500 | D16: =_xll.BDP($P16,"LAST_PRICE") -> 92.538 | E16: =_xll.BDP($P16,"CHG_PCT_1D") -> -0.41688305 | F16: =_xll.BDP($P16,"YLD_YTM_MID") -> 6.3376816 | G16: =IFERROR(_xll.BDP($P16,"TRACE_LAST_TRADE_SIZE"),"n/a") -> 20 | H16: =IFERROR(_xll.BDP($P16,"PRICE_LAST_TIME"),"") -> 16:44:24 | I16: =IF(AND(ISNUMBER(D16),ISNUMBER(C16)),(D16-100)/100*C16,"") -> -186.55 | J16: =IF(ISNUMBER(D16),(D16-100)/100,"") -> -0.07462 | K16: =IFERROR((D16-_xll.BDP($P16,"PX_CLOSE_1D"))/100*C16,"") -> -7.35 | L16: 6.2989258 | M16: =IF(AND(ISNUMBER(F16),ISNUMBER(L16)),(F16-L16)*100,"") -> 3.8755849 | N16: A- | O16: US11135FCM14 | P16: AVGO 5.2 07/15/2035 Corp
A17: AVGO 4.95 2036 | B17: Broadcom senior notes | C17: 1250 | D17: =_xll.BDP($P17,"LAST_PRICE") -> 90.311 | E17: =_xll.BDP($P17,"CHG_PCT_1D") -> -0.38034004 | F17: =_xll.BDP($P17,"YLD_YTM_MID") -> 6.3663488 | G17: =IFERROR(_xll.BDP($P17,"TRACE_LAST_TRADE_SIZE"),"n/a") -> 110 | H17: =IFERROR(_xll.BDP($P17,"PRICE_LAST_TIME"),"") -> 16:44:24 | I17: =IF(AND(ISNUMBER(D17),ISNUMBER(C17)),(D17-100)/100*C17,"") -> -121.1125 | J17: =IF(ISNUMBER(D17),(D17-100)/100,"") -> -0.09689 | K17: =IFERROR((D17-_xll.BDP($P17,"PX_CLOSE_1D"))/100*C17,"") -> -3.0625 | L17: 6.3314813 | M17: =IF(AND(ISNUMBER(F17),ISNUMBER(L17)),(F17-L17)*100,"") -> 3.4867454 | N17: A- | O17: US11135FDB40 | P17: AVGO 4.95 01/15/2036 Corp
A18: AVGO 4.8 2036 | B18: Broadcom senior notes | C18: 2250 | D18: =_xll.BDP($P18,"LAST_PRICE") -> 89.008 | E18: =_xll.BDP($P18,"CHG_PCT_1D") -> -0.40946952 | F18: =_xll.BDP($P18,"YLD_YTM_MID") -> 6.3975005 | G18: =IFERROR(_xll.BDP($P18,"TRACE_LAST_TRADE_SIZE"),"n/a") -> 8 | H18: =IFERROR(_xll.BDP($P18,"PRICE_LAST_TIME"),"") -> 16:44:24 | I18: =IF(AND(ISNUMBER(D18),ISNUMBER(C18)),(D18-100)/100*C18,"") -> -247.32 | J18: =IF(ISNUMBER(D18),(D18-100)/100,"") -> -0.10992 | K18: =IFERROR((D18-_xll.BDP($P18,"PX_CLOSE_1D"))/100*C18,"") -> -5.8725 | L18: 6.3551843 | M18: =IF(AND(ISNUMBER(F18),ISNUMBER(L18)),(F18-L18)*100,"") -> 4.2316181 | N18: A- | O18: US11135FCY51 | P18: AVGO 4.8 02/15/2036 Corp
A19: AVGO 5.7 2056 | B19: Broadcom senior notes | C19: 1250 | D19: =_xll.BDP($P19,"LAST_PRICE") -> 86.782 | E19: =_xll.BDP($P19,"CHG_PCT_1D") -> -0.46331278 | F19: =_xll.BDP($P19,"YLD_YTM_MID") -> 6.7627229 | G19: =IFERROR(_xll.BDP($P19,"TRACE_LAST_TRADE_SIZE"),"n/a") -> 5MM+ | H19: =IFERROR(_xll.BDP($P19,"PRICE_LAST_TIME"),"") -> 16:44:24 | I19: =IF(AND(ISNUMBER(D19),ISNUMBER(C19)),(D19-100)/100*C19,"") -> -165.225 | J19: =IF(ISNUMBER(D19),(D19-100)/100,"") -> -0.13218 | K19: =IFERROR((D19-_xll.BDP($P19,"PX_CLOSE_1D"))/100*C19,"") -> -1.775 | L19: 6.7303168 | M19: =IF(AND(ISNUMBER(F19),ISNUMBER(L19)),(F19-L19)*100,"") -> 3.2406079 | N19: A- | O19: US11135FDD06 | P19: AVGO 5.7 01/15/2056 Corp
A20: AMD senior notes
A21: AMD 5 2031 | B21: AMD senior notes | C21: 1500 | D21: =_xll.BDP($P21,"LAST_PRICE") -> 97.886 | E21: =_xll.BDP($P21,"CHG_PCT_1D") -> -0.028611908 | F21: =_xll.BDP($P21,"YLD_YTM_MID") -> 5.5239091 | G21: =IFERROR(_xll.BDP($P21,"TRACE_LAST_TRADE_SIZE"),"n/a") -> 50 | H21: =IFERROR(_xll.BDP($P21,"PRICE_LAST_TIME"),"") -> 16:44:24 | I21: =IF(AND(ISNUMBER(D21),ISNUMBER(C21)),(D21-100)/100*C21,"") -> -31.71 | J21: =IF(ISNUMBER(D21),(D21-100)/100,"") -> -0.02114 | K21: =IFERROR((D21-_xll.BDP($P21,"PX_CLOSE_1D"))/100*C21,"") -> 0.9 | L21: 5.4996141 | M21: =IF(AND(ISNUMBER(F21),ISNUMBER(L21)),(F21-L21)*100,"") -> 2.4295023 | N21: A | O21: US007903BL07 | P21: AMD 5 08/17/2031 Corp
A22: AMD 5.5 2036 | B22: AMD senior notes | C22: 1000 | D22: =_xll.BDP($P22,"LAST_PRICE") -> 96.535 | E22: =_xll.BDP($P22,"CHG_PCT_1D") -> -0.10311723 | F22: =_xll.BDP($P22,"YLD_YTM_MID") -> 5.9896524 | G22: =IFERROR(_xll.BDP($P22,"TRACE_LAST_TRADE_SIZE"),"n/a") -> 9 | H22: =IFERROR(_xll.BDP($P22,"PRICE_LAST_TIME"),"") -> 16:44:24 | I22: =IF(AND(ISNUMBER(D22),ISNUMBER(C22)),(D22-100)/100*C22,"") -> -34.65 | J22: =IF(ISNUMBER(D22),(D22-100)/100,"") -> -0.03465 | K22: =IFERROR((D22-_xll.BDP($P22,"PX_CLOSE_1D"))/100*C22,"") -> 0.43 | L22: 5.9702552 | M22: =IF(AND(ISNUMBER(F22),ISNUMBER(L22)),(F22-L22)*100,"") -> 1.939727 | N22: A | O22: US007903BN62 | P22: AMD 5.5 08/17/2036 Corp
A23: SpaceX
A24: SPCX 6.65 2056 144A | B24: SpaceX | C24: 3500 | D24: =_xll.BDP($P24,"LAST_PRICE") -> 84.937 | E24: =_xll.BDP($P24,"CHG_PCT_1D") -> -1.1296513 | F24: =_xll.BDP($P24,"YLD_YTM_MID") -> 8.0264084 | G24: =IFERROR(_xll.BDP($P24,"TRACE_LAST_TRADE_SIZE"),"n/a") -> 5000 | H24: =IFERROR(_xll.BDP($P24,"PRICE_LAST_TIME"),"") -> 16:44:24 | I24: =IF(AND(ISNUMBER(D24),ISNUMBER(C24)),(D24-100)/100*C24,"") -> -527.205 | J24: =IF(ISNUMBER(D24),(D24-100)/100,"") -> -0.15063 | K24: =IFERROR((D24-_xll.BDP($P24,"PX_CLOSE_1D"))/100*C24,"") -> -17.78 | L24: 7.9249448 | M24: =IF(AND(ISNUMBER(F24),ISNUMBER(L24)),(F24-L24)*100,"") -> 10.146359 | N24: BBB | O24: US84615QAJ22 | P24: SPCX 6.65 07/15/2056 144A Corp
A25: SPCX bridge TL (guaranteed) | B25: SpaceX | C25: 20000 | D25: =_xll.BDP($P25,"LAST_PRICE") -> 99 | E25: =_xll.BDP($P25,"CHG_PCT_1D") -> 0 | F25: =_xll.BDP($P25,"YLD_YTM_MID") -> 6.1656172 | G25: =IFERROR(_xll.BDP($P25,"TRACE_LAST_TRADE_SIZE"),"n/a") -> #N/A Field Not Applicable | H25: =IFERROR(_xll.BDP($P25,"PRICE_LAST_TIME"),"") -> 16:00:00 | I25: =IF(AND(ISNUMBER(D25),ISNUMBER(C25)),(D25-100)/100*C25,"") -> -200 | J25: =IF(ISNUMBER(D25),(D25-100)/100,"") -> -0.01 | K25: =IFERROR((D25-_xll.BDP($P25,"PX_CLOSE_1D"))/100*C25,"") -> 0 | L25: 6.1656172 | M25: =IF(AND(ISNUMBER(F25),ISNUMBER(L25)),(F25-L25)*100,"") -> 0 | P25: BL570250 Corp
A26: SPCX revolver 2031 | B26: SpaceX | C26: 0 | D26: =_xll.BDP($P26,"LAST_PRICE") -> #N/A Real Time | E26: =_xll.BDP($P26,"CHG_PCT_1D") -> #N/A N/A | F26: =_xll.BDP($P26,"YLD_YTM_MID") -> #N/A N/A | G26: =IFERROR(_xll.BDP($P26,"TRACE_LAST_TRADE_SIZE"),"n/a") -> #N/A Field Not Applicable | H26: =IFERROR(_xll.BDP($P26,"PRICE_LAST_TIME"),"") -> #N/A Field Not Applicable | I26: =IF(AND(ISNUMBER(D26),ISNUMBER(C26)),(D26-100)/100*C26,"") | J26: =IF(ISNUMBER(D26),(D26-100)/100,"") | K26: =IFERROR((D26-_xll.BDP($P26,"PX_CLOSE_1D"))/100*C26,"") | M26: =IF(AND(ISNUMBER(F26),ISNUMBER(L26)),(F26-L26)*100,"") | O26: US84615MAK80 | P26: BL097034 Corp
A27: Neocloud / miner converts and HY
A28: CRWV 1.75 12/2031 (cv) | B28: Neocloud / miner converts and HY | C28: 2587.5 | D28: =_xll.BDP($P28,"LAST_PRICE") -> 77.839 | E28: =_xll.BDP($P28,"CHG_PCT_1D") -> -3.0317498 | F28: =_xll.BDP($P28,"YLD_YTM_MID") -> 6.7118905 | G28: =IFERROR(_xll.BDP($P28,"TRACE_LAST_TRADE_SIZE"),"n/a") -> 1MM+ | H28: =IFERROR(_xll.BDP($P28,"PRICE_LAST_TIME"),"") -> 12:32:46 | I28: =IF(AND(ISNUMBER(D28),ISNUMBER(C28)),(D28-100)/100*C28,"") -> -573.41588 | J28: =IF(ISNUMBER(D28),(D28-100)/100,"") -> -0.22161 | K28: =IFERROR((D28-_xll.BDP($P28,"PX_CLOSE_1D"))/100*C28,"") -> -88.777125 | L28: 6.0617975 | M28: =IF(AND(ISNUMBER(F28),ISNUMBER(L28)),(F28-L28)*100,"") -> 65.009306 | N28: B | O28: US21873SAD09 | P28: CRWV 1.75 12/01/2031 144A Corp
A29: CRWV 1.75 10/2032 (cv) | B29: Neocloud / miner converts and HY | C29: 4000 | D29: =_xll.BDP($P29,"LAST_PRICE") -> 70.859 | E29: =_xll.BDP($P29,"CHG_PCT_1D") -> -7.0582524 | F29: =_xll.BDP($P29,"YLD_YTM_MID") -> 7.807774 | G29: =IFERROR(_xll.BDP($P29,"TRACE_LAST_TRADE_SIZE"),"n/a") -> 1MM+ | H29: =IFERROR(_xll.BDP($P29,"PRICE_LAST_TIME"),"") -> 12:32:31 | I29: =IF(AND(ISNUMBER(D29),ISNUMBER(C29)),(D29-100)/100*C29,"") -> -1165.64 | J29: =IF(ISNUMBER(D29),(D29-100)/100,"") -> -0.29141 | K29: =IFERROR((D29-_xll.BDP($P29,"PX_CLOSE_1D"))/100*C29,"") -> -247.2 | L29: 6.4588591 | M29: =IF(AND(ISNUMBER(F29),ISNUMBER(L29)),(F29-L29)*100,"") -> 134.89149 | O29: US21873SAH13 | P29: CRWV 1.75 10/01/2032 144A Corp
A30: CRWV 2.875 04/2033 (cv, Sep-26) | B30: Neocloud / miner converts and HY | C30: 4200 | D30: =_xll.BDP($P30,"LAST_PRICE") -> 78.738 | E30: =_xll.BDP($P30,"CHG_PCT_1D") -> -7.3694818 | F30: =_xll.BDP($P30,"YLD_YTM_MID") -> 5.8690661 | G30: =IFERROR(_xll.BDP($P30,"TRACE_LAST_TRADE_SIZE"),"n/a") -> 1MM+ | H30: =IFERROR(_xll.BDP($P30,"PRICE_LAST_TIME"),"") -> 12:32:10 | I30: =IF(AND(ISNUMBER(D30),ISNUMBER(C30)),(D30-100)/100*C30,"") -> -893.004 | J30: =IF(ISNUMBER(D30),(D30-100)/100,"") -> -0.21262 | K30: =IFERROR((D30-_xll.BDP($P30,"PX_CLOSE_1D"))/100*C30,"") -> -506.688 | L30: 4.5354428 | M30: =IF(AND(ISNUMBER(F30),ISNUMBER(L30)),(F30-L30)*100,"") -> 133.36233 | O30: US21873SAL25 | P30: CRWV 2.875 04/01/2033 144A Corp
A31: CRWV 9.25 06/2030 | B31: Neocloud / miner converts and HY | C31: 2000 | D31: =_xll.BDP($P31,"LAST_PRICE") -> 84.688 | E31: =_xll.BDP($P31,"CHG_PCT_1D") -> -1.7004658 | F31: =_xll.BDP($P31,"YLD_YTM_MID") -> 14.730329 | G31: =IFERROR(_xll.BDP($P31,"TRACE_LAST_TRADE_SIZE"),"n/a") -> 1MM+ | H31: =IFERROR(_xll.BDP($P31,"PRICE_LAST_TIME"),"") -> 16:44:24 | I31: =IF(AND(ISNUMBER(D31),ISNUMBER(C31)),(D31-100)/100*C31,"") -> -306.24 | J31: =IF(ISNUMBER(D31),(D31-100)/100,"") -> -0.15312 | K31: =IFERROR((D31-_xll.BDP($P31,"PX_CLOSE_1D"))/100*C31,"") -> -35.98 | L31: 14.345195 | M31: =IF(AND(ISNUMBER(F31),ISNUMBER(L31)),(F31-L31)*100,"") -> 38.513344 | N31: B | O31: US21873SAB43 | P31: CRWV 9.25 06/01/2030 144A Corp
A32: CRWV 9 02/2031 | B32: Neocloud / miner converts and HY | C32: 1750 | D32: =_xll.BDP($P32,"LAST_PRICE") -> 81.065 | E32: =_xll.BDP($P32,"CHG_PCT_1D") -> -2.9102486 | F32: =_xll.BDP($P32,"YLD_YTM_MID") -> 15.36832 | G32: =IFERROR(_xll.BDP($P32,"TRACE_LAST_TRADE_SIZE"),"n/a") -> 1MM+ | H32: =IFERROR(_xll.BDP($P32,"PRICE_LAST_TIME"),"") -> 16:44:24 | I32: =IF(AND(ISNUMBER(D32),ISNUMBER(C32)),(D32-100)/100*C32,"") -> -331.3625 | J32: =IF(ISNUMBER(D32),(D32-100)/100,"") -> -0.18935 | K32: =IFERROR((D32-_xll.BDP($P32,"PX_CLOSE_1D"))/100*C32,"") -> -32.305 | L32: 14.776175 | M32: =IF(AND(ISNUMBER(F32),ISNUMBER(L32)),(F32-L32)*100,"") -> 59.214559 | N32: B | O32: US21873SAC26 | P32: CRWV 9 02/01/2031 144A Corp
A33: CRWV 9.625 07/2032 | B33: Neocloud / miner converts and HY | C33: 1250 | D33: =_xll.BDP($P33,"LAST_PRICE") -> 79.702 | E33: =_xll.BDP($P33,"CHG_PCT_1D") -> -2.6568141 | F33: =_xll.BDP($P33,"YLD_YTM_MID") -> 15.051917 | G33: =IFERROR(_xll.BDP($P33,"TRACE_LAST_TRADE_SIZE"),"n/a") -> 1MM+ | H33: =IFERROR(_xll.BDP($P33,"PRICE_LAST_TIME"),"") -> 16:44:24 | I33: =IF(AND(ISNUMBER(D33),ISNUMBER(C33)),(D33-100)/100*C33,"") -> -253.725 | J33: =IF(ISNUMBER(D33),(D33-100)/100,"") -> -0.20298 | K33: =IFERROR((D33-_xll.BDP($P33,"PX_CLOSE_1D"))/100*C33,"") -> -25.2875 | L33: 14.782869 | M33: =IF(AND(ISNUMBER(F33),ISNUMBER(L33)),(F33-L33)*100,"") -> 26.904788 | N33: B | O33: US21873SAK42 | P33: CRWV 9.625 07/15/2032 144A Corp
A34: CRWV GPU DDTL 11/2031 | B34: Neocloud / miner converts and HY | C34: 1101 | D34: =_xll.BDP($P34,"LAST_PRICE") -> 99.47 | E34: =_xll.BDP($P34,"CHG_PCT_1D") -> -0.054119211 | F34: =_xll.BDP($P34,"YLD_YTM_MID") -> 8.5464185 | G34: =IFERROR(_xll.BDP($P34,"TRACE_LAST_TRADE_SIZE"),"n/a") -> #N/A Field Not Applicable | H34: =IFERROR(_xll.BDP($P34,"PRICE_LAST_TIME"),"") -> 16:00:00 | I34: =IF(AND(ISNUMBER(D34),ISNUMBER(C34)),(D34-100)/100*C34,"") -> -5.8353 | J34: =IF(ISNUMBER(D34),(D34-100)/100,"") -> -0.0053 | K34: =IFERROR((D34-_xll.BDP($P34,"PX_CLOSE_1D"))/100*C34,"") -> -3.0031977 | L34: 8.529616 | M34: =IF(AND(ISNUMBER(F34),ISNUMBER(L34)),(F34-L34)*100,"") -> 1.6802475 | O34: US21882DAB64 | P34: BL567281 Corp
A35: CRWV DDTL 09/2031 | B35: Neocloud / miner converts and HY | C35: 1200 | D35: =_xll.BDP($P35,"LAST_PRICE") -> 98.563 | E35: =_xll.BDP($P35,"CHG_PCT_1D") -> -0.062383032 | F35: =_xll.BDP($P35,"YLD_YTM_MID") -> 8.1203522 | G35: =IFERROR(_xll.BDP($P35,"TRACE_LAST_TRADE_SIZE"),"n/a") -> #N/A Field Not Applicable | H35: =IFERROR(_xll.BDP($P35,"PRICE_LAST_TIME"),"") -> 16:00:00 | I35: =IF(AND(ISNUMBER(D35),ISNUMBER(C35)),(D35-100)/100*C35,"") -> -17.244 | J35: =IF(ISNUMBER(D35),(D35-100)/100,"") -> -0.01437 | K35: =IFERROR((D35-_xll.BDP($P35,"PX_CLOSE_1D"))/100*C35,"") -> -19.494 | L35: 8.1203522 | M35: =IF(AND(ISNUMBER(F35),ISNUMBER(L35)),(F35-L35)*100,"") -> 0 | O35: US21882EAB48 | P35: BL577043 Corp
A36: NBIS 1.25 03/2031 (cv) | B36: Neocloud / miner converts and HY | C36: 2587.5 | D36: =_xll.BDP($P36,"LAST_PRICE") -> 113.562 | E36: =_xll.BDP($P36,"CHG_PCT_1D") -> 0 | F36: =_xll.BDP($P36,"YLD_YTM_MID") -> 1.1892055 | G36: =IFERROR(_xll.BDP($P36,"TRACE_LAST_TRADE_SIZE"),"n/a") -> 1MM+ | H36: =IFERROR(_xll.BDP($P36,"PRICE_LAST_TIME"),"") -> 15:31:45 | I36: =IF(AND(ISNUMBER(D36),ISNUMBER(C36)),(D36-100)/100*C36,"") -> 350.91675 | J36: =IF(ISNUMBER(D36),(D36-100)/100,"") -> 0.13562 | K36: =IFERROR((D36-_xll.BDP($P36,"PX_CLOSE_1D"))/100*C36,"") -> -146.97 | L36: 1.1892055 | M36: =IF(AND(ISNUMBER(F36),ISNUMBER(L36)),(F36-L36)*100,"") -> -2.220446e-14 | O36: US63954QAJ58 | P36: NBIS 1.25 03/15/2031 144A Corp
A37: NBIS 2.625 03/2033 (cv) | B37: Neocloud / miner converts and HY | C37: 1750 | D37: =_xll.BDP($P37,"LAST_PRICE") -> 115.244 | E37: =_xll.BDP($P37,"CHG_PCT_1D") -> -1.0297716 | F37: =_xll.BDP($P37,"YLD_YTM_MID") -> 2.8690391 | G37: =IFERROR(_xll.BDP($P37,"TRACE_LAST_TRADE_SIZE"),"n/a") -> 1MM+ | H37: =IFERROR(_xll.BDP($P37,"PRICE_LAST_TIME"),"") -> 12:22:34 | I37: =IF(AND(ISNUMBER(D37),ISNUMBER(C37)),(D37-100)/100*C37,"") -> 266.77 | J37: =IF(ISNUMBER(D37),(D37-100)/100,"") -> 0.15244 | K37: =IFERROR((D37-_xll.BDP($P37,"PX_CLOSE_1D"))/100*C37,"") -> -20.9825 | L37: 2.694239 | M37: =IF(AND(ISNUMBER(F37),ISNUMBER(L37)),(F37-L37)*100,"") -> 17.480005 | O37: US63954QAL05 | P37: NBIS 2.625 03/15/2033 144A Corp
A38: NBIS 4.5 02/2034 (cv, Aug-26) | B38: Neocloud / miner converts and HY | C38: 2300 | D38: =_xll.BDP($P38,"LAST_PRICE") -> 84.353 | E38: =_xll.BDP($P38,"CHG_PCT_1D") -> -5.5064757 | F38: =_xll.BDP($P38,"YLD_YTM_MID") -> 9.9552673 | G38: =IFERROR(_xll.BDP($P38,"TRACE_LAST_TRADE_SIZE"),"n/a") -> 1MM+ | H38: =IFERROR(_xll.BDP($P38,"PRICE_LAST_TIME"),"") -> 12:39:40 | I38: =IF(AND(ISNUMBER(D38),ISNUMBER(C38)),(D38-100)/100*C38,"") -> -359.881 | J38: =IF(ISNUMBER(D38),(D38-100)/100,"") -> -0.15647 | K38: =IFERROR((D38-_xll.BDP($P38,"PX_CLOSE_1D"))/100*C38,"") -> -113.505 | L38: 9.0128136 | M38: =IF(AND(ISNUMBER(F38),ISNUMBER(L38)),(F38-L38)*100,"") -> 94.245368 | O38: US63954QAQ91 | P38: NBIS 4.5 02/15/2034 144A Corp
A39: CIFR 1.75 05/2030 (cv) | B39: Neocloud / miner converts and HY | C39: 172.5 | D39: =_xll.BDP($P39,"LAST_PRICE") -> 223.502 | E39: =_xll.BDP($P39,"CHG_PCT_1D") -> -9.5358456 | F39: =_xll.BDP($P39,"YLD_YTM_MID") -> -20.000854 | G39: =IFERROR(_xll.BDP($P39,"TRACE_LAST_TRADE_SIZE"),"n/a") -> 1MM+ | H39: =IFERROR(_xll.BDP($P39,"PRICE_LAST_TIME"),"") -> 16:00:00 | I39: =IF(AND(ISNUMBER(D39),ISNUMBER(C39)),(D39-100)/100*C39,"") -> 213.04095 | J39: =IF(ISNUMBER(D39),(D39-100)/100,"") -> 1.23502 | K39: =IFERROR((D39-_xll.BDP($P39,"PX_CLOSE_1D"))/100*C39,"") -> -38.003475 | L39: -20.911975 | M39: =IF(AND(ISNUMBER(F39),ISNUMBER(L39)),(F39-L39)*100,"") -> 91.112166 | O39: US17253JAA43 | P39: CIFR 1.75 05/15/2030 Corp
A40: CIFR 0 10/2031 (cv) | B40: Neocloud / miner converts and HY | C40: 1300 | D40: =_xll.BDP($P40,"LAST_PRICE") -> 89.531 | E40: =_xll.BDP($P40,"CHG_PCT_1D") -> 0 | F40: =_xll.BDP($P40,"YLD_YTM_MID") -> 1.4377929 | G40: =IFERROR(_xll.BDP($P40,"TRACE_LAST_TRADE_SIZE"),"n/a") -> 1MM+ | H40: =IFERROR(_xll.BDP($P40,"PRICE_LAST_TIME"),"") -> 17:08:59 | I40: =IF(AND(ISNUMBER(D40),ISNUMBER(C40)),(D40-100)/100*C40,"") -> -136.097 | J40: =IF(ISNUMBER(D40),(D40-100)/100,"") -> -0.10469 | K40: =IFERROR((D40-_xll.BDP($P40,"PX_CLOSE_1D"))/100*C40,"") -> -47.099 | L40: 1.4377929 | M40: =IF(AND(ISNUMBER(F40),ISNUMBER(L40)),(F40-L40)*100,"") -> 0 | O40: US17253JAB26 | P40: CIFR 0 10/01/2031 144A Corp
A41: CIFR 0 11/2032 (cv, NEW 16-Oct) | B41: Neocloud / miner converts and HY | C41: 850 | D41: =_xll.BDP($P41,"LAST_PRICE") -> 87.749 | E41: =_xll.BDP($P41,"CHG_PCT_1D") -> -1.7182945 | F41: =_xll.BDP($P41,"YLD_YTM_MID") -> 1.8327374 | G41: =IFERROR(_xll.BDP($P41,"TRACE_LAST_TRADE_SIZE"),"n/a") -> 1MM+ | H41: =IFERROR(_xll.BDP($P41,"PRICE_LAST_TIME"),"") -> 12:11:21 | I41: =IF(AND(ISNUMBER(D41),ISNUMBER(C41)),(D41-100)/100*C41,"") -> -104.1335 | J41: =IF(ISNUMBER(D41),(D41-100)/100,"") -> -0.12251 | K41: =IFERROR((D41-_xll.BDP($P41,"PX_CLOSE_1D"))/100*C41,"") -> -28.849 | L41: 1.5430572 | M41: =IF(AND(ISNUMBER(F41),ISNUMBER(L41)),(F41-L41)*100,"") -> 28.968023 | O41: US17252AAA43 | P41: CIFR 0 11/01/2032 144A Corp
A42: SOFTBK 9.75 04/2034 (Sep-26) | B42: Neocloud / miner converts and HY | C42: 4500 | D42: =_xll.BDP($P42,"LAST_PRICE") -> 98.903 | E42: =_xll.BDP($P42,"CHG_PCT_1D") -> -2.4784683 | F42: =_xll.BDP($P42,"YLD_YTM_MID") -> 10.104966 | G42: =IFERROR(_xll.BDP($P42,"TRACE_LAST_TRADE_SIZE"),"n/a") -> 1MM+ | H42: =IFERROR(_xll.BDP($P42,"PRICE_LAST_TIME"),"") -> 16:44:24 | I42: =IF(AND(ISNUMBER(D42),ISNUMBER(C42)),(D42-100)/100*C42,"") -> -49.365 | J42: =IF(ISNUMBER(D42),(D42-100)/100,"") -> -0.01097 | K42: =IFERROR((D42-_xll.BDP($P42,"PX_CLOSE_1D"))/100*C42,"") -> -78.795 | L42: 9.7278248 | M42: =IF(AND(ISNUMBER(F42),ISNUMBER(L42)),(F42-L42)*100,"") -> 37.714115 | N42: BB+ | O42: US83408KAC36 | P42: SOFTBK 9.75 04/01/2034 144A Corp
A43: Tenant / parent comparator bond
A44: NVDA 2 06/2031 (comp) | B44: Tenant / parent comparator bond | C44: 1250 | D44: =_xll.BDP($P44,"LAST_PRICE") -> 86.515 | E44: =_xll.BDP($P44,"CHG_PCT_1D") -> -0.11621104 | F44: =_xll.BDP($P44,"YLD_YTM_MID") -> 5.3217499 | G44: =IFERROR(_xll.BDP($P44,"TRACE_LAST_TRADE_SIZE"),"n/a") -> 35 | H44: =IFERROR(_xll.BDP($P44,"PRICE_LAST_TIME"),"") -> 16:44:24 | I44: =IF(AND(ISNUMBER(D44),ISNUMBER(C44)),(D44-100)/100*C44,"") -> -168.5625 | J44: =IF(ISNUMBER(D44),(D44-100)/100,"") -> -0.13485 | K44: =IFERROR((D44-_xll.BDP($P44,"PX_CLOSE_1D"))/100*C44,"") -> -0.5375 | L44: 5.3192161 | M44: =IF(AND(ISNUMBER(F44),ISNUMBER(L44)),(F44-L44)*100,"") -> 0.25338702 | N44: AA | O44: US67066GAN43 | P44: US67066GAN43 Corp
A45: GOOGL 4.8 02/2036 (comp) | B45: Tenant / parent comparator bond | C45: 4250 | D45: =_xll.BDP($P45,"LAST_PRICE") -> 93.151 | E45: =_xll.BDP($P45,"CHG_PCT_1D") -> -0.081072896 | F45: =_xll.BDP($P45,"YLD_YTM_MID") -> 5.7643551 | G45: =IFERROR(_xll.BDP($P45,"TRACE_LAST_TRADE_SIZE"),"n/a") -> 15 | H45: =IFERROR(_xll.BDP($P45,"PRICE_LAST_TIME"),"") -> 16:44:24 | I45: =IF(AND(ISNUMBER(D45),ISNUMBER(C45)),(D45-100)/100*C45,"") -> -291.0825 | J45: =IF(ISNUMBER(D45),(D45-100)/100,"") -> -0.06849 | K45: =IFERROR((D45-_xll.BDP($P45,"PX_CLOSE_1D"))/100*C45,"") -> -1.5725 | L45: 5.7500257 | M45: =IF(AND(ISNUMBER(F45),ISNUMBER(L45)),(F45-L45)*100,"") -> 1.4329445 | N45: AA+ | O45: US02079KBM80 | P45: US02079KBM80 Corp
A46: GOOGL 4.1 02/2031 (comp) | B46: Tenant / parent comparator bond | C46: 3000 | D46: =_xll.BDP($P46,"LAST_PRICE") -> 95.519 | E46: =_xll.BDP($P46,"CHG_PCT_1D") -> -0.038553315 | F46: =_xll.BDP($P46,"YLD_YTM_MID") -> 5.2852494 | G46: =IFERROR(_xll.BDP($P46,"TRACE_LAST_TRADE_SIZE"),"n/a") -> 65 | H46: =IFERROR(_xll.BDP($P46,"PRICE_LAST_TIME"),"") -> 16:44:24 | I46: =IF(AND(ISNUMBER(D46),ISNUMBER(C46)),(D46-100)/100*C46,"") -> -134.43 | J46: =IF(ISNUMBER(D46),(D46-100)/100,"") -> -0.04481 | K46: =IFERROR((D46-_xll.BDP($P46,"PX_CLOSE_1D"))/100*C46,"") -> 0.45 | L46: 5.2802737 | M46: =IF(AND(ISNUMBER(F46),ISNUMBER(L46)),(F46-L46)*100,"") -> 0.49756509 | N46: AA+ | O46: US02079KBK25 | P46: US02079KBK25 Corp
A47: META 5.25 05/2036 (comp) | B47: Tenant / parent comparator bond | C47: 6000 | D47: =_xll.BDP($P47,"LAST_PRICE") -> 93.414 | E47: =_xll.BDP($P47,"CHG_PCT_1D") -> -0.23901027 | F47: =_xll.BDP($P47,"YLD_YTM_MID") -> 6.1574729 | G47: =IFERROR(_xll.BDP($P47,"TRACE_LAST_TRADE_SIZE"),"n/a") -> 2 | H47: =IFERROR(_xll.BDP($P47,"PRICE_LAST_TIME"),"") -> 16:44:24 | I47: =IF(AND(ISNUMBER(D47),ISNUMBER(C47)),(D47-100)/100*C47,"") -> -395.16 | J47: =IF(ISNUMBER(D47),(D47-100)/100,"") -> -0.06586 | K47: =IFERROR((D47-_xll.BDP($P47,"PX_CLOSE_1D"))/100*C47,"") -> -18.84 | L47: 6.1477173 | M47: =IF(AND(ISNUMBER(F47),ISNUMBER(L47)),(F47-L47)*100,"") -> 0.9755591 | N47: AA- | O47: US30303MAH51 | P47: US30303MAH51 Corp
A48: ORCL 3.6 04/2040 (comp) | B48: Tenant / parent comparator bond | C48: 3000 | D48: =_xll.BDP($P48,"LAST_PRICE") -> 63.829 | E48: =_xll.BDP($P48,"CHG_PCT_1D") -> -1.104558 | F48: =_xll.BDP($P48,"YLD_YTM_MID") -> 8.0571207 | G48: =IFERROR(_xll.BDP($P48,"TRACE_LAST_TRADE_SIZE"),"n/a") -> 700 | H48: =IFERROR(_xll.BDP($P48,"PRICE_LAST_TIME"),"") -> 16:44:24 | I48: =IF(AND(ISNUMBER(D48),ISNUMBER(C48)),(D48-100)/100*C48,"") -> -1085.13 | J48: =IF(ISNUMBER(D48),(D48-100)/100,"") -> -0.36171 | K48: =IFERROR((D48-_xll.BDP($P48,"PX_CLOSE_1D"))/100*C48,"") -> -20.4 | L48: 8.0349418 | M48: =IF(AND(ISNUMBER(F48),ISNUMBER(L48)),(F48-L48)*100,"") -> 2.2178905 | N48: BBB- | O48: US68389XBW48 | P48: US68389XBW48 Corp
A49: ORCL 4.95 02/2031 (comp) | B49: Tenant / parent comparator bond | C49: 3500 | D49: =_xll.BDP($P49,"LAST_PRICE") -> 91.99 | E49: =_xll.BDP($P49,"CHG_PCT_1D") -> 0.066211329 | F49: =_xll.BDP($P49,"YLD_YTM_MID") -> 7.128663 | G49: =IFERROR(_xll.BDP($P49,"TRACE_LAST_TRADE_SIZE"),"n/a") -> 48 | H49: =IFERROR(_xll.BDP($P49,"PRICE_LAST_TIME"),"") -> 16:44:24 | I49: =IF(AND(ISNUMBER(D49),ISNUMBER(C49)),(D49-100)/100*C49,"") -> -280.35 | J49: =IF(ISNUMBER(D49),(D49-100)/100,"") -> -0.0801 | K49: =IFERROR((D49-_xll.BDP($P49,"PX_CLOSE_1D"))/100*C49,"") -> -0.105 | L49: 7.1314024 | M49: =IF(AND(ISNUMBER(F49),ISNUMBER(L49)),(F49-L49)*100,"") -> -0.27393982 | N49: BBB- | O49: US68389XDX03 | P49: US68389XDX03 Corp
A50: MSFT 3.45 08/2036 (comp) | B50: Tenant / parent comparator bond | C50: 1749.3 | D50: =_xll.BDP($P50,"LAST_PRICE") -> 85.391 | E50: =_xll.BDP($P50,"CHG_PCT_1D") -> -0.22969062 | F50: =_xll.BDP($P50,"YLD_YTM_MID") -> 5.3957353 | G50: =IFERROR(_xll.BDP($P50,"TRACE_LAST_TRADE_SIZE"),"n/a") -> 6 | H50: =IFERROR(_xll.BDP($P50,"PRICE_LAST_TIME"),"") -> 16:44:24 | I50: =IF(AND(ISNUMBER(D50),ISNUMBER(C50)),(D50-100)/100*C50,"") -> -255.55524 | J50: =IF(ISNUMBER(D50),(D50-100)/100,"") -> -0.14609 | K50: =IFERROR((D50-_xll.BDP($P50,"PX_CLOSE_1D"))/100*C50,"") -> -2.396541 | L50: 5.3699722 | M50: =IF(AND(ISNUMBER(F50),ISNUMBER(L50)),(F50-L50)*100,"") -> 2.5763151 | N50: AAA | O50: US594918BS26 | P50: US594918BS26 Corp
A51: AMZN 4.25 03/2031 (comp) | B51: Tenant / parent comparator bond | C51: 5000 | D51: =_xll.BDP($P51,"LAST_PRICE") -> 95.614 | E51: =_xll.BDP($P51,"CHG_PCT_1D") -> -0.099199639 | F51: =_xll.BDP($P51,"YLD_YTM_MID") -> 5.3958071 | G51: =IFERROR(_xll.BDP($P51,"TRACE_LAST_TRADE_SIZE"),"n/a") -> 18 | H51: =IFERROR(_xll.BDP($P51,"PRICE_LAST_TIME"),"") -> 16:44:24 | I51: =IF(AND(ISNUMBER(D51),ISNUMBER(C51)),(D51-100)/100*C51,"") -> -219.3 | J51: =IF(ISNUMBER(D51),(D51-100)/100,"") -> -0.04386 | K51: =IFERROR((D51-_xll.BDP($P51,"PX_CLOSE_1D"))/100*C51,"") -> -2.1 | L51: 5.3877169 | M51: =IF(AND(ISNUMBER(F51),ISNUMBER(L51)),(F51-L51)*100,"") -> 0.80901682 | N51: AA | O51: US023135DD51 | P51: US023135DD51 Corp
A52: JANEST 7.294 08/2031 (comp) | B52: Tenant / parent comparator bond | C52: 5860 | D52: =_xll.BDP($P52,"LAST_PRICE") -> 99.932 | E52: =_xll.BDP($P52,"CHG_PCT_1D") -> -0.61884805 | F52: =_xll.BDP($P52,"YLD_YTM_MID") -> 7.3160842 | G52: =IFERROR(_xll.BDP($P52,"TRACE_LAST_TRADE_SIZE"),"n/a") -> 100 | H52: =IFERROR(_xll.BDP($P52,"PRICE_LAST_TIME"),"") -> 16:44:24 | I52: =IF(AND(ISNUMBER(D52),ISNUMBER(C52)),(D52-100)/100*C52,"") -> -3.9848 | J52: =IF(ISNUMBER(D52),(D52-100)/100,"") -> -0.00068 | K52: =IFERROR((D52-_xll.BDP($P52,"PX_CLOSE_1D"))/100*C52,"") -> -34.867 | L52: 7.2826007 | M52: =IF(AND(ISNUMBER(F52),ISNUMBER(L52)),(F52-L52)*100,"") -> 3.3483483 | N52: BB | O52: USU47015AH24 | P52: USU47015AH24 Corp
A53: SOFTBK 8.25 10/2031 (comp) | B53: Tenant / parent comparator bond | C53: 600 | D53: =_xll.BDP($P53,"LAST_PRICE") -> 97.75 | E53: =_xll.BDP($P53,"CHG_PCT_1D") -> -0.083210268 | F53: =_xll.BDP($P53,"YLD_YTM_MID") -> 8.8231535 | G53: =IFERROR(_xll.BDP($P53,"TRACE_LAST_TRADE_SIZE"),"n/a") -> 200 | H53: =IFERROR(_xll.BDP($P53,"PRICE_LAST_TIME"),"") -> 16:44:24 | I53: =IF(AND(ISNUMBER(D53),ISNUMBER(C53)),(D53-100)/100*C53,"") -> -13.5 | J53: =IF(ISNUMBER(D53),(D53-100)/100,"") -> -0.0225 | K53: =IFERROR((D53-_xll.BDP($P53,"PX_CLOSE_1D"))/100*C53,"") -> -0.3 | L53: 8.8018693 | M53: =IF(AND(ISNUMBER(F53),ISNUMBER(L53)),(F53-L53)*100,"") -> 2.1284147 | N53: BB+ | O53: XS3344488864 | P53: XS3344488864 Corp
A54: BABA 2.125 02/2031 (comp) | B54: Tenant / parent comparator bond | C54: 1500 | D54: =_xll.BDP($P54,"LAST_PRICE") -> 87.706 | E54: =_xll.BDP($P54,"CHG_PCT_1D") -> -0.03798348 | F54: =_xll.BDP($P54,"YLD_YTM_MID") -> 5.3718895 | G54: =IFERROR(_xll.BDP($P54,"TRACE_LAST_TRADE_SIZE"),"n/a") -> 200 | H54: =IFERROR(_xll.BDP($P54,"PRICE_LAST_TIME"),"") -> 16:44:24 | I54: =IF(AND(ISNUMBER(D54),ISNUMBER(C54)),(D54-100)/100*C54,"") -> -184.41 | J54: =IF(ISNUMBER(D54),(D54-100)/100,"") -> -0.12294 | K54: =IFERROR((D54-_xll.BDP($P54,"PX_CLOSE_1D"))/100*C54,"") -> 0.15 | L54: 5.3819758 | M54: =IF(AND(ISNUMBER(F54),ISNUMBER(L54)),(F54-L54)*100,"") -> -1.0086258 | N54: A+ | O54: US01609WAX02 | P54: BABA 2.125 02/09/2031 Corp
A55: Neocloud / miner converts and HY
A56: CRWV 8.5 07/2032 EUR | B56: Neocloud / miner converts and HY | C56: 2000 | D56: =_xll.BDP($P56,"LAST_PRICE") -> 78.251 | E56: =_xll.BDP($P56,"CHG_PCT_1D") -> -0.3137291 | F56: =_xll.BDP($P56,"YLD_YTM_MID") -> 14.14672 | G56: =IFERROR(_xll.BDP($P56,"TRACE_LAST_TRADE_SIZE"),"n/a") -> #N/A Field Not Applicable | H56: =IFERROR(_xll.BDP($P56,"PRICE_LAST_TIME"),"") -> 12:59:55 | I56: =IF(AND(ISNUMBER(D56),ISNUMBER(C56)),(D56-100)/100*C56,"") -> -434.98 | J56: =IF(ISNUMBER(D56),(D56-100)/100,"") -> -0.21749 | K56: =IFERROR((D56-_xll.BDP($P56,"PX_CLOSE_1D"))/100*C56,"") -> -4.94 | L56: 14.146568 | M56: =IF(AND(ISNUMBER(F56),ISNUMBER(L56)),(F56-L56)*100,"") -> 0.01520554 | N56: B | O56: XS3333139288 | P56: XS3333139288 Corp
A57: NBIS 2 06/2029 (cv) | B57: Neocloud / miner converts and HY | C57: 87.5 | D57: =_xll.BDP($P57,"LAST_PRICE") -> 323.302 | E57: =_xll.BDP($P57,"CHG_PCT_1D") -> -12.625642 | F57: =_xll.BDP($P57,"YLD_YTM_MID") -> -33.200486 | G57: =IFERROR(_xll.BDP($P57,"TRACE_LAST_TRADE_SIZE"),"n/a") -> 5 | H57: =IFERROR(_xll.BDP($P57,"PRICE_LAST_TIME"),"") -> 16:00:00 | I57: =IF(AND(ISNUMBER(D57),ISNUMBER(C57)),(D57-100)/100*C57,"") -> 195.38925 | J57: =IF(ISNUMBER(D57),(D57-100)/100,"") -> 2.23302 | K57: =IFERROR((D57-_xll.BDP($P57,"PX_CLOSE_1D"))/100*C57,"") -> -38.737125 | L57: -34.692671 | M57: =IF(AND(ISNUMBER(F57),ISNUMBER(L57)),(F57-L57)*100,"") -> 149.21857 | O57: US63954QAB23 | P57: NBIS 2 06/05/2029 Corp
A58: NBIS 3 06/2031 (cv) | B58: Neocloud / miner converts and HY | C58: 87.5 | D58: =_xll.BDP($P58,"LAST_PRICE") -> 347 | E58: =_xll.BDP($P58,"CHG_PCT_1D") -> 0 | F58: =_xll.BDP($P58,"YLD_YTM_MID") -> -19.474582 | G58: =IFERROR(_xll.BDP($P58,"TRACE_LAST_TRADE_SIZE"),"n/a") -> 250 | H58: =IFERROR(_xll.BDP($P58,"PRICE_LAST_TIME"),"") -> 12:47:46 | I58: =IF(AND(ISNUMBER(D58),ISNUMBER(C58)),(D58-100)/100*C58,"") -> 216.125 | J58: =IF(ISNUMBER(D58),(D58-100)/100,"") -> 2.47 | K58: =IFERROR((D58-_xll.BDP($P58,"PX_CLOSE_1D"))/100*C58,"") -> 0 | L58: -19.474582 | M58: =IF(AND(ISNUMBER(F58),ISNUMBER(L58)),(F58-L58)*100,"") -> 3.5527137e-13 | O58: US63954QAD88 | P58: NBIS 3 06/05/2031 Corp
A59: NBIS 2.75 09/2032 (cv) | B59: Neocloud / miner converts and HY | C59: 1581.2 | D59: =_xll.BDP($P59,"LAST_PRICE") -> 137.682 | E59: =_xll.BDP($P59,"CHG_PCT_1D") -> #N/A N/A | F59: =_xll.BDP($P59,"YLD_YTM_MID") -> -1.1408687 | G59: =IFERROR(_xll.BDP($P59,"TRACE_LAST_TRADE_SIZE"),"n/a") -> 1MM+ | H59: =IFERROR(_xll.BDP($P59,"PRICE_LAST_TIME"),"") -> 12:43:46 | I59: =IF(AND(ISNUMBER(D59),ISNUMBER(C59)),(D59-100)/100*C59,"") -> 595.82778 | J59: =IF(ISNUMBER(D59),(D59-100)/100,"") -> 0.37682 | K59: =IFERROR((D59-_xll.BDP($P59,"PX_CLOSE_1D"))/100*C59,"") | L59: -1.2728158 | M59: =IF(AND(ISNUMBER(F59),ISNUMBER(L59)),(F59-L59)*100,"") -> 13.194704 | O59: US63954QAH92 | P59: NBIS 2.75 09/15/2032 Corp
A60: IREN 3.25 06/2030 (cv) | B60: Neocloud / miner converts and HY | C60: 212.3 | D60: =_xll.BDP($P60,"LAST_PRICE") -> 184.033 | E60: =_xll.BDP($P60,"CHG_PCT_1D") -> -9.1116712 | F60: =_xll.BDP($P60,"YLD_YTM_MID") -> -13.573531 | G60: =IFERROR(_xll.BDP($P60,"TRACE_LAST_TRADE_SIZE"),"n/a") -> 22 | H60: =IFERROR(_xll.BDP($P60,"PRICE_LAST_TIME"),"") -> 16:00:00 | I60: =IF(AND(ISNUMBER(D60),ISNUMBER(C60)),(D60-100)/100*C60,"") -> 178.40206 | J60: =IF(ISNUMBER(D60),(D60-100)/100,"") -> 0.84033 | K60: =IFERROR((D60-_xll.BDP($P60,"PX_CLOSE_1D"))/100*C60,"") -> -37.369046 | L60: -14.365478 | M60: =IF(AND(ISNUMBER(F60),ISNUMBER(L60)),(F60-L60)*100,"") -> 79.194776 | O60: US46270CAB54 | P60: IREN 3.25 06/15/2030 Corp
A61: IREN 3.5 12/2029 (cv) | B61: Neocloud / miner converts and HY | C61: 233.4 | D61: =_xll.BDP($P61,"LAST_PRICE") -> 218.307 | E61: =_xll.BDP($P61,"CHG_PCT_1D") -> -10.233906 | F61: =_xll.BDP($P61,"YLD_YTM_MID") -> -20.825854 | G61: =IFERROR(_xll.BDP($P61,"TRACE_LAST_TRADE_SIZE"),"n/a") -> 1MM+ | H61: =IFERROR(_xll.BDP($P61,"PRICE_LAST_TIME"),"") -> 16:00:00 | I61: =IF(AND(ISNUMBER(D61),ISNUMBER(C61)),(D61-100)/100*C61,"") -> 276.12854 | J61: =IF(ISNUMBER(D61),(D61-100)/100,"") -> 1.18307 | K61: =IFERROR((D61-_xll.BDP($P61,"PX_CLOSE_1D"))/100*C61,"") -> -54.736968 | L61: -21.841514 | M61: =IF(AND(ISNUMBER(F61),ISNUMBER(L61)),(F61-L61)*100,"") -> 101.56602 | O61: US46270CAD11 | P61: IREN 3.5 12/15/2029 Corp

Sheet CDS
A1: CDS: live flat spreads
A2: CDS_FLAT_SPREAD in bp. MS desk marks are Morgan Stanley Credit Trading, 24-Aug-2026.
A4: Name | B4: Bloomberg ticker | C4: LIVE flat spread (bp) | D4: Spread at snapshot (bp) | E4: Δ vs snapshot (bp) | F4: MS desk 24-Aug (bp) | G4: Δ vs MS (bp)
A5: AVGO B CDS 5Y | B5: AVGO B CDS USD SR 5Y D14 Corp | C5: =_xll.BDP($B5,"CDS_FLAT_SPREAD") -> 146.93 | D5: 146.93 | E5: =IF(AND(ISNUMBER(C5),ISNUMBER(D5)),C5-D5,"") -> 0 | F5: 124 | G5: =IF(AND(ISNUMBER(C5),ISNUMBER(F5)),C5-F5,"") -> 22.93
A6: AVAGO CDS 5Y | B6: AVAGO CDS USD SR 5Y D14 Corp | C6: =_xll.BDP($B6,"CDS_FLAT_SPREAD") -> 100 | D6: 100 | E6: =IF(AND(ISNUMBER(C6),ISNUMBER(D6)),C6-D6,"") -> 0 | G6: =IF(AND(ISNUMBER(C6),ISNUMBER(F6)),C6-F6,"")
A7: AMD CDS 5Y | B7: AMD CDS USD SR 5Y D14 Corp | C7: =_xll.BDP($B7,"CDS_FLAT_SPREAD") -> 101.3124 | D7: 101.3124 | E7: =IF(AND(ISNUMBER(C7),ISNUMBER(D7)),C7-D7,"") -> 0 | F7: 94 | G7: =IF(AND(ISNUMBER(C7),ISNUMBER(F7)),C7-F7,"") -> 7.3124
A8: SPCX CDS 5Y | B8: SPCX CDS USD SR 5Y D14 Corp | C8: =_xll.BDP($B8,"CDS_FLAT_SPREAD") -> 220.87 | D8: 220.87 | E8: =IF(AND(ISNUMBER(C8),ISNUMBER(D8)),C8-D8,"") -> -2.8421709e-14 | F8: 171 | G8: =IF(AND(ISNUMBER(C8),ISNUMBER(F8)),C8-F8,"") -> 49.87
A9: NVDA CDS 5Y | B9: NVDA CDS USD SR 5Y D14 Corp | C9: =_xll.BDP($B9,"CDS_FLAT_SPREAD") -> 96.83 | D9: 96.83 | E9: =IF(AND(ISNUMBER(C9),ISNUMBER(D9)),C9-D9,"") -> 0 | F9: 84 | G9: =IF(AND(ISNUMBER(C9),ISNUMBER(F9)),C9-F9,"") -> 12.83
A10: ORCL CDS 5Y | B10: ORCLCP CDS USD SR 5Y D14 Corp | C10: =_xll.BDP($B10,"CDS_FLAT_SPREAD") -> 287.15 | D10: 287.15 | E10: =IF(AND(ISNUMBER(C10),ISNUMBER(D10)),C10-D10,"") -> 0 | F10: 217 | G10: =IF(AND(ISNUMBER(C10),ISNUMBER(F10)),C10-F10,"") -> 70.15
A11: CRWV CDS 1Y | B11: CRWV CDS USD SR 1Y D14 Corp | C11: =_xll.BDP($B11,"CDS_FLAT_SPREAD") -> 790.30152 | D11: 790.30152 | E11: =IF(AND(ISNUMBER(C11),ISNUMBER(D11)),C11-D11,"") -> 0 | G11: =IF(AND(ISNUMBER(C11),ISNUMBER(F11)),C11-F11,"")
A12: CRWV CDS 3Y | B12: CRWV CDS USD SR 3Y D14 Corp | C12: =_xll.BDP($B12,"CDS_FLAT_SPREAD") -> 1033.1828 | D12: 1033.1828 | E12: =IF(AND(ISNUMBER(C12),ISNUMBER(D12)),C12-D12,"") -> -4.5474735e-13 | G12: =IF(AND(ISNUMBER(C12),ISNUMBER(F12)),C12-F12,"")
A13: CRWV CDS 5Y | B13: CRWV CDS USD SR 5Y D14 Corp | C13: =_xll.BDP($B13,"CDS_FLAT_SPREAD") -> 1119.6389 | D13: 1119.6389 | E13: =IF(AND(ISNUMBER(C13),ISNUMBER(D13)),C13-D13,"") -> -2.2737368e-13 | G13: =IF(AND(ISNUMBER(C13),ISNUMBER(F13)),C13-F13,"")
A14: CRWV CDS 7Y | B14: CRWV CDS USD SR 7Y D14 Corp | C14: =_xll.BDP($B14,"CDS_FLAT_SPREAD") -> 1180.4991 | D14: 1180.4991 | E14: =IF(AND(ISNUMBER(C14),ISNUMBER(D14)),C14-D14,"") -> 2.2737368e-13 | G14: =IF(AND(ISNUMBER(C14),ISNUMBER(F14)),C14-F14,"")
A15: CRWV CDS 10Y | B15: CRWV CDS USD SR 10Y D14 Corp | C15: =_xll.BDP($B15,"CDS_FLAT_SPREAD") -> 1204.8019 | D15: 1204.8019 | E15: =IF(AND(ISNUMBER(C15),ISNUMBER(D15)),C15-D15,"") -> -2.2737368e-13 | G15: =IF(AND(ISNUMBER(C15),ISNUMBER(F15)),C15-F15,"")
A16: META CDS 5Y | B16: META CDS USD SR 5Y D14 Corp | C16: =_xll.BDP($B16,"CDS_FLAT_SPREAD") -> 108.56 | D16: 108.56 | E16: =IF(AND(ISNUMBER(C16),ISNUMBER(D16)),C16-D16,"") -> 1.4210855e-14 | F16: 95 | G16: =IF(AND(ISNUMBER(C16),ISNUMBER(F16)),C16-F16,"") -> 13.56
A17: GOOGL CDS 5Y | B17: GOOGL CDS USD SR 5Y D14 Corp | C17: =_xll.BDP($B17,"CDS_FLAT_SPREAD") -> 77.27 | D17: 77.27 | E17: =IF(AND(ISNUMBER(C17),ISNUMBER(D17)),C17-D17,"") -> 0 | F17: 56 | G17: =IF(AND(ISNUMBER(C17),ISNUMBER(F17)),C17-F17,"") -> 21.27
A18: MSFT CDS 5Y | B18: MSFT CDS USD SR 5Y D14 Corp | C18: =_xll.BDP($B18,"CDS_FLAT_SPREAD") -> 55.3865 | D18: 54.44 | E18: =IF(AND(ISNUMBER(C18),ISNUMBER(D18)),C18-D18,"") -> 0.9465 | F18: 46 | G18: =IF(AND(ISNUMBER(C18),ISNUMBER(F18)),C18-F18,"") -> 9.3865
A19: AMZN CDS 5Y | B19: AMZN CDS USD SR 5Y D14 Corp | C19: =_xll.BDP($B19,"CDS_FLAT_SPREAD") -> 78.9986 | D19: 78.0262 | E19: =IF(AND(ISNUMBER(C19),ISNUMBER(D19)),C19-D19,"") -> 0.9724 | F19: 63 | G19: =IF(AND(ISNUMBER(C19),ISNUMBER(F19)),C19-F19,"") -> 15.9986

Sheet Equities
A1: Issuer and tenant equities: live daily volume
A2: Equity volume is real and a good proxy for activity in the credit. Relative volume = today's volume / 30-day average (amber at 1.5x or more).
A4: Equity | B4: Why it matters | C4: Bloomberg ticker | D4: LIVE price | E4: Chg % 1D | F4: Volume today | G4: 30d avg volume | H4: Relative volume (x) | I4: Volume time
A5: CoreWeave | B5: Tenant behind APLD/ELNFOR/CORZ/GALAXY/ELKGVP; own HY bonds and converts | C5: CRWV US Equity | D5: =_xll.BDP($C5,"LAST_PRICE") -> 61.39 | E5: =_xll.BDP($C5,"CHG_PCT_1D") -> -13.45961 | F5: =_xll.BDP($C5,"VOLUME") -> 94831682 | G5: =_xll.BDP($C5,"VOLUME_AVG_30D") -> 35350154 | H5: =IFERROR(F5/G5,"") -> 2.6826384 | I5: =IFERROR(_xll.BDP($C5,"LAST_TRADE_TIME"),"") -> 16:44:52
A6: Nebius | B6: Neocloud converts | C6: NBIS US Equity | D6: =_xll.BDP($C6,"LAST_PRICE") -> 165.47 | E6: =_xll.BDP($C6,"CHG_PCT_1D") -> -12.90271 | F6: =_xll.BDP($C6,"VOLUME") -> 34945608 | G6: =_xll.BDP($C6,"VOLUME_AVG_30D") -> 17411746 | H6: =IFERROR(F6/G6,"") -> 2.0070134 | I6: =IFERROR(_xll.BDP($C6,"LAST_TRADE_TIME"),"") -> 16:44:52
A7: IREN | B7: Neocloud converts | C7: IREN US Equity | D7: =_xll.BDP($C7,"LAST_PRICE") -> 26.99 | E7: =_xll.BDP($C7,"CHG_PCT_1D") -> -12.35604 | F7: =_xll.BDP($C7,"VOLUME") -> 68109967 | G7: =_xll.BDP($C7,"VOLUME_AVG_30D") -> 42105308 | H7: =IFERROR(F7/G7,"") -> 1.61761 | I7: =IFERROR(_xll.BDP($C7,"LAST_TRADE_TIME"),"") -> 16:44:52
A8: Applied Digital | B8: APLD, PFORGE, ELNFOR project bonds | C8: APLD US Equity | D8: =_xll.BDP($C8,"LAST_PRICE") -> 18.05 | E8: =_xll.BDP($C8,"CHG_PCT_1D") -> -13.16822 | F8: =_xll.BDP($C8,"VOLUME") -> 34783641 | G8: =_xll.BDP($C8,"VOLUME_AVG_30D") -> 20851899 | H8: =IFERROR(F8/G8,"") -> 1.6681282 | I8: =IFERROR(_xll.BDP($C8,"LAST_TRADE_TIME"),"") -> 16:44:52
A9: Core Scientific | B9: CORZ bond (CoreWeave tenant) | C9: CORZ US Equity | D9: =_xll.BDP($C9,"LAST_PRICE") -> 13.48 | E9: =_xll.BDP($C9,"CHG_PCT_1D") -> -6.848841 | F9: =_xll.BDP($C9,"VOLUME") -> 22283335 | G9: =_xll.BDP($C9,"VOLUME_AVG_30D") -> 12635102 | H9: =IFERROR(F9/G9,"") -> 1.7636055 | I9: =IFERROR(_xll.BDP($C9,"LAST_TRADE_TIME"),"") -> 16:44:51
A10: Cipher Digital | B10: CIFR/BLKPRL/STNGRY bonds, new 0% 2032 convert | C10: CIFR US Equity | D10: =_xll.BDP($C10,"LAST_PRICE") -> 8.98 | E10: =_xll.BDP($C10,"CHG_PCT_1D") -> -11.95219 | F10: =_xll.BDP($C10,"VOLUME") -> 49235290 | G10: =_xll.BDP($C10,"VOLUME_AVG_30D") -> 40807709 | H10: =IFERROR(F10/G10,"") -> 1.2065193 | I10: =IFERROR(_xll.BDP($C10,"LAST_TRADE_TIME"),"") -> 16:44:52
A11: TeraWulf | B11: WULF bond (Google-backstopped) | C11: WULF US Equity | D11: =_xll.BDP($C11,"LAST_PRICE") -> 11.68 | E11: =_xll.BDP($C11,"CHG_PCT_1D") -> -7.913629 | F11: =_xll.BDP($C11,"VOLUME") -> 55576764 | G11: =_xll.BDP($C11,"VOLUME_AVG_30D") -> 31964217 | H11: =IFERROR(F11/G11,"") -> 1.7387182 | I11: =IFERROR(_xll.BDP($C11,"LAST_TRADE_TIME"),"") -> 16:44:51
A12: Galaxy Digital | B12: GALAXY bond (CoreWeave tenant) | C12: GLXY US Equity | D12: =_xll.BDP($C12,"LAST_PRICE") -> 16.14 | E12: =_xll.BDP($C12,"CHG_PCT_1D") -> -12.60274 | F12: =_xll.BDP($C12,"VOLUME") -> 8796959 | G12: =_xll.BDP($C12,"VOLUME_AVG_30D") -> 5400968.8 | H12: =IFERROR(F12/G12,"") -> 1.6287743 | I12: =IFERROR(_xll.BDP($C12,"LAST_TRADE_TIME"),"") -> 16:44:52
A13: Hut 8 | B13: HUTBPA (NVIDIA) and HUTRBA (Google backstop) | C13: HUT US Equity | D13: =_xll.BDP($C13,"LAST_PRICE") -> 67.75 | E13: =_xll.BDP($C13,"CHG_PCT_1D") -> -11.37469 | F13: =_xll.BDP($C13,"VOLUME") -> 6182193 | G13: =_xll.BDP($C13,"VOLUME_AVG_30D") -> 5676837.1 | H13: =IFERROR(F13/G13,"") -> 1.0890207 | I13: =IFERROR(_xll.BDP($C13,"LAST_TRADE_TIME"),"") -> 16:44:46
A14: Oracle | B14: RDMICH, PFORGE, YNDRDC tenant; own bonds and CDS | C14: ORCL US Equity | D14: =_xll.BDP($C14,"LAST_PRICE") -> 128.23 | E14: =_xll.BDP($C14,"CHG_PCT_1D") -> -4.759426 | F14: =_xll.BDP($C14,"VOLUME") -> 35960721 | G14: =_xll.BDP($C14,"VOLUME_AVG_30D") -> 33477277 | H14: =IFERROR(F14/G14,"") -> 1.074183 | I14: =IFERROR(_xll.BDP($C14,"LAST_TRADE_TIME"),"") -> 16:44:49
A15: Broadcom | B15: Backstop provider; AVGO bonds | C15: AVGO US Equity | D15: =_xll.BDP($C15,"LAST_PRICE") -> 328.75 | E15: =_xll.BDP($C15,"CHG_PCT_1D") -> -4.354834 | F15: =_xll.BDP($C15,"VOLUME") -> 29714467 | G15: =_xll.BDP($C15,"VOLUME_AVG_30D") -> 25351404 | H15: =IFERROR(F15/G15,"") -> 1.1721034 | I15: =IFERROR(_xll.BDP($C15,"LAST_TRADE_TIME"),"") -> 16:44:52
A16: NVIDIA | B16: Tenant TRACTC/TRACTD/HUTBPA; backstop provider | C16: NVDA US Equity | D16: =_xll.BDP($C16,"LAST_PRICE") -> 214.13 | E16: =_xll.BDP($C16,"CHG_PCT_1D") -> -1.420154 | F16: =_xll.BDP($C16,"VOLUME") -> 120806855 | G16: =_xll.BDP($C16,"VOLUME_AVG_30D") -> 1.0828449e+08 | H16: =IFERROR(F16/G16,"") -> 1.1156432 | I16: =IFERROR(_xll.BDP($C16,"LAST_TRADE_TIME"),"") -> 16:44:52
... A23: SoftBank | B23: SECMOS tenant; $11.1bn HY offering | C23: 9984 JT Equity | D23: =_xll.BDP($C23,"LAST_PRICE") -> 4944 | E23: =_xll.BDP($C23,"CHG_PCT_1D") -> 1.896125 | F23: =_xll.BDP($C23,"VOLUME") -> 43833700 | G23: =_xll.BDP($C23,"VOLUME_AVG_30D") -> 63391133 | H23: =IFERROR(F23/G23,"") -> 0.69147999 | I23: =IFERROR(_xll.BDP($C23,"LAST_TRADE_TIME"),"") -> 03:30:00

Sheet README
A1: AI credit live workbook. Blue cells are Bloomberg formulas (=BDP) that update while this file is open in Excel with the Bloomberg add-in loaded (same login as the terminal).
A2: If cells show #NAME?: Excel > Bloomberg tab > Log In, then Refresh (F9). 'Requesting Data...' clears after a minute or two on first open.
A3: Principal gained / lost = (live price - 100) / 100 x amount outstanding, in $mn on the whole issue. Negative = trading below par. Also shown: today's change in value (live vs previous close) and, for the Barclays universe, the change since 15-Sep.
A4: Totals per section (IG, HY) give face outstanding, weighted-average price and aggregate principal vs par.
A5: Bond prices and bid/ask are Bloomberg composite quotes that refresh about every 15 seconds; they are not individual trades. Cumulative daily bond volume is not available in Bloomberg fields; 'Last trade size (TRACE)' is the latest print. For the tape use TRAC <GO>. Equity volume (Equities sheet) is real.
A6: Reference data: Barclays IG/HY Data Center Credit Digest, 16-Sep-2026 (Figures 5, 7, 8, 9); Morgan Stanley desk CDS 24-Aug-2026; instrument master and latest snapshot (2026-10-16_1248).
A7: Rebuild: python C:\Users\daniel.grozdea\scripts\build_ai_credit_live.py (after running ai_credit_refresh.py to reset the snapshot reference).
A8: Monitor columns S to Y: First issued (Bloomberg ISSUE_DT), live OAS, tenant comparable bond and its live OAS, live pickup (bond OAS minus comparable OAS), Barclays 15-Sep pickup and the change since. The bond ticker for terminal lookups moved to column Z.
A9: Deal dossiers: the Deal Index sheet links to one tab per bond on the Monitor (built from SEC filings, indentures, company and rating agency releases; each tab lists its sources and what could not be verified). Dossiers live in the dossiers folder and are read at build time.
A10: Caveats: yield changes vs Barclays mix YTW (Barclays) with yield-to-maturity (live), so they are approximate. Converts and loans are measured against par for comparability only.

Sheet HUTBPA
A1: Beacon Point DC LLC 6.129% Senior Secured Notes due 30-Nov-2042 | D1: << Monitor
A2: Dossier as of 2026-10-16 | ISIN US07367AAA79 (seed, unverified) | IG section | Bloomberg: HUTBPA 6.129 11/30/42 144A Corp
A4: LIVE price | B4: =Monitor!H6 -> 92.424
A5: LIVE yield % | B5: =Monitor!J6 -> 6.9070348
A6: Amt o/s ($mn) | B6: =Monitor!G6 -> 4250
A7: Principal vs par ($mn) | B7: =Monitor!M6 -> -321.98
A8: Principal vs par (%) | B8: =Monitor!N6 -> -0.07576
A9: Today's change ($mn) | B9: =Monitor!O6 -> -4.5475
A10: First issued | B10: =Monitor!S6 -> 46182
A11: LIVE pickup vs tenant comp (bp) | B11: =Monitor!W6 -> 114.76306
A12: Rating | B12: =Monitor!F6 -> Baa2/NR/NR
A13: Tenant | B13: =Monitor!C6 -> NVIDIA
A15: Summary
A16: Headline | B16: $4.25bn fully amortizing, non-recourse 144A notes issued 9 Jun 2026 by a Hut 8 SPV to build the 352 MW first phase of the Beacon Point campus in Nueces County, Texas, secured by the project and a 15-year triple-net take-or-pay lease to an unnamed tenant rated AA- or better (reported by the FT to be NVIDIA). Moody's rates the notes Baa2 and they priced at T+165bp. Credit rests on one tenant and on energization and delivery in Q1-Q3 2027; Phase 2 (a second 352 MW lease), NVIDIA's disclosure that it expects to reassign leases to third parties, and the reported Lambda/Anthropic usage raise assignment and end-user questions, with indenture limits on assignment to Qualifying Tenants or Creditworthy Transferees the main protection.
A18: Security terms | C18: Source | D18: Status
A19: Issuer | B19: Beacon Point DC LLC, a Delaware LLC; indirect wholly-owned subsidiary of Hut 8 Corp. | C19: S1 | D19: verified (official doc)
A20: Notes | B20: 6.129% Senior Secured Notes due 2042; senior secured obligations of the Issuer. | C20: S1 | D20: verified (official doc)
A21: Principal | B21: $4,250mm aggregate, issued at 100% of par. Original and current principal are the same: no amortization before 30 May 2030. The indenture permits Additional Notes (conditions not retrieved). | C21: S2 | D21: verified (official doc)
A22: Coupon / day count | B22: 6.129% fixed, 30/360 (twelve 30-day months); interest accrues from 9 Jun 2026; payable semi-annually 30 May and 30 Nov, first payment 30 Nov 2026; record dates 15 May and 15 Nov. | C22: S1 | D22: verified (official doc)
A23: Pricing / issue date | B23: Priced 4 Jun 2026 (purchase agreement dated 4 Jun); issued and indenture dated 9 Jun 2026. Priced at T+165bp, 20bp inside the River Bend notes' issuance spread; substantially oversubscribed. | C23: S5 | D23: company statement
A24: Maturity | B24: 30 Nov 2042 (about 16.5 years from issue). | C24: S1 | D24: verified (official doc)
A25: Offering format | B25: Rule 144A / Regulation S. J.P. Morgan Securities LLC represented the initial purchasers (lead bookrunner); Goldman Sachs & Co. LLC bookrunner. The 144A offering memorandum is dated 4 Jun 2026 and is not public. | C25: S2 | D25: verified (official doc)
A26: ISIN / CUSIP | B26: ISIN US07367AAA79 and CUSIP 07367AAA7 are seed leads; the form of note filed with the indenture leaves the identifier fields blank, so they could not be verified. Reg S identifiers not found. | C26: S15 | D26: seed, unverified
A27: Denominations | B27: Minimum $2,000 with integral multiples of $1,000 above that. | C27: S1 | D27: verified (official doc)
A28: Trustee / agents | B28: Wilmington Trust, National Association: trustee, collateral agent, paying agent and registrar. | C28: S1 | D28: verified (official doc)
A29: Governing law / jurisdiction | B29: New York law (Sec. 13.06(a)); exclusive jurisdiction of New York Supreme Court (New York County) and SDNY. | C29: S1 | D29: verified (official doc)
A30: Optional redemption | B30: Before the Par Call Date (30 May 2042): make-whole at the greater of 100% and discounted value at Treasury Rate + 25bp (Sec. 3.08(a)). On or after 30 May 2042: 100% plus accrued. A 90% tender clean-up call exists (Sec. 3.08(e)). Seed call date and price (5/30/42 at 100) are consistent. | C30: S1 | D30: verified (official doc)
... A35: Trading levels (seed) | B35: Seed: yield 6.99%, spread +200bp on 15 Sep 2026; comp NVDA 4.95% 2036. Not verified. | C35: S15 | D35: seed, unverified
A37: Issuer and structure | C37: Source | D37: Status
A38: Borrower chain | B38: Hut 8 Corp. (Nasdaq: HUT) -> indirect subsidiaries -> Beacon Point Holding LLC (HoldCo, party to the indenture, pledges Issuer equity) -> Beacon Point DC LLC (Issuer, landlord under the Data Center Lease and owner of the project). | C38: S1 | D38: verified (official doc)
A39: Obligor / guarantees | B39: Issuer is the sole obligor. Notes are non-recourse to Hut 8 Corp. (company statement; Hut 8 says the parent keeps zero recourse debt). No parent guarantee identified. | C39: S5 | D39: company statement
A40: Ring-fencing | B40: Special-purpose covenants (Sec. 4.19): no material assets beyond the project, no subsidiaries, no employees, no commingling, independent director consent to a bankruptcy filing; restrictions can be lifted only with a Rating Agency Confirmation. HoldCo has a negative-pledge covenant (Sec. 4.20). | C40: S1 | D40: verified (official doc)
A41: Campus sharing | B41: The indenture contemplates Shared Facilities and Commercial Property Association arrangements and carves Adjacent Property out of the collateral, which fits a campus where later phases are developed alongside. How Phase 2 sits relative to this SPV is not disclosed. | C41: S1 | D41: verified (official doc)
A42: Equity contribution | B42: Not quantified in documents retrieved. Hut 8 says it does not expect to issue equity to fund the project. The campus was originally underwritten to serve affiliate American Bitcoin Corp. before the third-party lease. | C42: S5 | D42: company statement
A44: Sponsor and parent | C44: Source | D44: Status
A45: Sponsor | B45: Hut 8 Corp., Miami-based developer/operator (formerly bitcoin miner) now building AI data centers. Contracted AI portfolio 949 MW (704 MW Beacon Point, 245 MW River Bend), about $26.6bn base-term contract value (company figures). | C45: S7 | D45: company statement
A46: Other financings | B46: $3.25bn River Bend notes (Hut 8 DC LLC, Apr 2026); $1.07bn parent revolver closed 24 Sep 2026 (JPMorgan agent, undrawn at closing, Term SOFR + 1.50-2.00%, minimum liquidity 40% of commitments from 31 Mar 2027 falling to 25% after the Stabilization Date); FalconX $200mm bitcoin-backed facility refinanced to 7.0%; Coatue $150mm convertible converted. | C46: S13 | D46: verified (official doc)
A47: Parent liquidity | B47: About $8.1bn total liquidity at 30 Jun 2026 including $7.6bn attributable to Hut 8 (largely project cash) and $497mm at American Bitcoin. Consolidated restricted cash was $6.79bn at 30 Jun 2026. | C47: S8 | D47: company statement
A48: Revolver relevance | B48: The revolver is parent-level with first lien on substantially all assets of Hut 8 and guarantors; bondholders are structurally separate (non-recourse), but the revolver's covenants bear on sponsor capacity to support the project. | C48: S13 | D48: verified (official doc)
A50: Tenant and lease | C50: Source | D50: Status
A51: Lease document | B51: Data Center Lease dated 12 Mar 2026 between the Issuer (landlord) and the Tenant, amended 29 Apr 2026. The lease itself is not filed. | C51: S1 | D51: verified (official doc)
A52: Tenant identity (official) | B52: Hut 8 filings do not name the tenant. The 8-K says the lease is to a tenant rated AA- or higher as of 9 Jun 2026; Hut 8 calls it a 'high-investment-grade' tenant. | C52: S2 | D52: verified (official doc)
A53: Tenant identity (reported) | B53: The Financial Times, citing five people, reported NVIDIA as the tenant behind both Beacon Point leases, and Bloomberg reportedly concurred. NVIDIA and Hut 8 have not confirmed. The indenture's Qualifying Tenant list names NVIDIA, Apple, Microsoft, Amazon, Alphabet (Google) and Meta, consistent with but not proof of NVIDIA. | C53: S11 | D53: third party / news
A54: Lease structure | B54: 15-year base term, triple net, take-or-pay; 352 MW IT; $9.8bn base-term contract value for Phase 1; fixed rent with 3.0% annual escalator (stated for Phase 2 as substantially the same terms); three 5-year renewal options (campus value $50.2bn with all options, per company). The CEO reportedly said there is no termination for convenience. | C54: S7 | D54: company statement
A55: Rent economics | B55: Company illustration: Phase 1 cumulative NOI about $9,788mm over the base term; revenue about $63mm in 2027 rising to about $776mm in 2041; implied stabilised average NOI about $655mm/yr, roughly $1.86mm per MW-year (derived). Seed base rent of $1.57mm/MW is not confirmed. | C55: S3 | D55: company statement
A56: Commencement | B56: Initial data hall delivery targeted Q3 2027; seed shows rent commencement Aug 2027 to Apr 2028 (unverified). The lease 'Commencement Date' is defined per Critical Power Phase; the Initial Commencement Date is the first phase. | C56: S8 | D56: company statement
A57: Assignment and termination protections in the indenture | B57: The Issuer may not consent to a tenant assignment unless the transferee is a Qualifying Tenant or Creditworthy Transferee (AA-/Aa2 stable with at least $25.0bn tangible net worth) (Sec. 4.21(b)). Lease termination alone is not an Event of Default: it needs the lease ceasing, no Qualifying Data Center Lease within 6 months (12 with conditions), and failure to run a Termination Fee Offer (Sec. 6.01(9)). | C57: S1 | D57: verified (official doc)
A58: Termination fee | B58: A Data Center Lease Termination Fee payable by the Tenant exists (amount not disclosed); it is paid into a Designated Account and used to repurchase notes at 100%. | C58: S1 | D58: verified (official doc)
A59: SLA credits, delay rights, extension mechanics | B59: Not found: lease not public. | C59: S1 | D59: verified (official doc)
A61: Project and site | C61: Source | D61: Status
A62: Location / size | B62: About 521 acres in Nueces County, Texas; six data halls; 352 MW critical IT; on-site substation. Press describes about 525 acres. | C62: S2 | D62: verified (official doc)
A63: Campus | B63: Beacon Point is a 1 GW campus (1,000 MW AEP Texas interconnection agreement). Phase 2 (500 MW of utility capacity, a further 352 MW) is a separate lease; total contracted 704 MW. | C63: S7 | D63: company statement
A64: NVIDIA DSX redesign | B64: The Phase 1 data hall was redesigned to NVIDIA's DSX reference architecture, giving about 57% more IT capacity within the same land and utility footprint (company statement). | C64: S7 | D64: company statement
A65: Cost per MW / facility cost | B65: Seed: facility cost $3,871mm, $11.0mm/MW, 97% debt-funded. Not verified, and hard to square with $4.25bn of notes (which also fund reserves and capitalised interest). Capex budget not found. | C65: S15 | D65: seed, unverified
A66: Cooling / density | B66: Not found in documents retrieved. | C66: S2 | D66: verified (official doc)
A68: Power and utilities | C68: Source | D68: Status
A69: Grid connection | B69: Grid-connected via AEP Texas; 1,000 MW interconnection agreement for the campus. Advancing through the ERCOT process; Contribution in Aid of Construction funded and substation construction started as of May 2026. | C69: S6 | D69: company statement
A70: Energization | B70: Initial energization targeted Q1 2027 (company). Phase 2 is supported by 500 MW of the 1,000 MW; no incremental capacity needed. | C70: S8 | D70: company statement
A71: Permits / ERCOT large-load approvals | B71: Not found in documents retrieved; no county or PUCT records reviewed. | C71: S6 | D71: company statement
A73: Construction and delivery | C73: Source | D73: Status
A74: Status at 16 Oct 2026 | B74: As of 4 Aug 2026: Phase 1 construction and campus substation underway; initial data hall delivery Q3 2027. Phase 2 initial hall Q2 2028, site preparation underway, long-lead equipment procured. No later milestone disclosure found. | C74: S8 | D74: company statement
A75: Contractor / contract type | B75: Not disclosed for Beacon Point in documents retrieved. The indenture refers to Full Budgeted Cost of Construction, Unused Contingency and Underbudget Amount mechanics, implying a budget with contingency; no GMP mention found for this deal (unlike River Bend). | C75: S1 | D75: verified (official doc)
A76: Construction-period liquidity | B76: Debt Service Reserve Required Amount during construction: $481.9mm (estimated accrued interest during construction) less interest paid, plus 50% of next interest payment and 50% of the first amortization installment. | C76: S1 | D76: verified (official doc)
A77: Completion guarantee / yield-on-cost | B77: None found. Overrun risk sits with the Issuer / Hut 8; unused contingency at commencement may be distributed once (Sec. 4.05(b)(6)). | C77: S1 | D77: verified (official doc)
A78: Seed schedule | B78: Seed: construction start early 2026; commencement Aug 2027 to Apr 2028. | C78: S15 | D78: seed, unverified
A80: Financing and capital structure | C80: Source | D80: Status
A81: Debt | B81: The $4,250mm notes are the only project debt disclosed; fully amortizing, non-recourse. A construction-debt basket allows up to Full Budgeted Cost of Construction less the notes (Sec. 4.04(a)(21)); post-commencement pari passu debt needs a Rating Agency Confirmation. | C81: S1 | D81: verified (official doc)
A82: Company illustrative metrics | B82: DSCR 1.34x in sculpted years, initial ICR 2.01x, peak leverage 7.95x (debt/NOI); cumulative NOI $9,788mm, interest $2,569mm, levered FCF $2,860mm; amortization sculpted to repay by end of initial lease term. Seed leverage 7.7x not confirmed. | C82: S3 | D82: company statement
A83: Sources and uses | B83: Not disclosed in detail. Uses: construction, substation, debt service reserves, fees. Unlike River Bend, no reimbursement of sponsor equity is listed. | C83: S2 | D83: verified (official doc)
A84: Reserves | B84: DSRA funded at issue (see Construction); after construction, 50% of next interest plus 50% of next installment. May be satisfied with cash, securities, letters of credit or equity. | C84: S1 | D84: verified (official doc)
A85: Refinancing risk | B85: Fully amortizing to maturity from lease cash flows. The 15-year base lease from commencement (roughly 2027-2028 to 2042-2043) is about co-terminous with the Nov 2042 maturity, leaving little tail beyond the base term; final installment is $98mm. | C85: S1 | D85: estimate
A87: Credit enhancement and support | C87: Source | D87: Status
A88: Parent recourse | B88: None: non-recourse to Hut 8 Corp. | C88: S5 | D88: company statement
A89: Third-party credit support | B89: No tenant-parent guarantee or Google-style backstop is disclosed. Credit rests on the tenant's own obligation (AA- or better per the 8-K). If the tenant is an NVIDIA subsidiary, whether NVIDIA parent guarantees the lease is not disclosed; the indenture treats controlled affiliates as Qualifying Tenants only where the parent guarantees. | C89: S1 | D89: verified (official doc)
A90: Replacement-tenant provisions | B90: A Qualifying Data Center Lease with a Qualifying Tenant plus Rating Agency Confirmation cures; 6-month window, up to 12 months with an LOI and funded DSRA. | C90: S1 | D90: verified (official doc)
A91: Lease termination fee | B91: Fee paid by tenant into a Designated Account and applied to par repurchase of notes. | C91: S1 | D91: verified (official doc)
A93: Covenants, waterfall and reserves | C93: Source | D93: Status
A94: Waterfall | B94: Revenue Account applied in order: operating expenses; Notes debt service (with DSRA); DSRA replenishment; then any purpose not prohibited (Sec. 4.23(f)). The Notes Proceeds Account funds construction and debt service pre-commencement. Lease termination fees go to a Designated Account. | C94: S1 | D94: verified (official doc)
A95: Distribution test | B95: Restricted Payments from Available Retained Excess Cash Flow only if DSCR exceeds 1.10x; other payments allowed only if pro forma DSCR stays at or above 1.10x. Tax distributions require a fully funded DSRA. No separate cash-sweep percentage found. | C95: S1 | D95: verified (official doc)
A96: Debt and lien limits | B96: General debt basket $50.0mm, secured asset debt $50.0mm, finance leases $50.0mm, letters of credit $100.0mm; non-pari passu secured credit facilities need DSCR of at least 1.10x. | C96: S1 | D96: verified (official doc)
A97: Events of default | B97: Interest 30 days; principal/premium 3 Business Days; covenant breach 90 days (150 for reporting); cross-default and judgment threshold $50.0mm (judgment unstayed 90 days); lease-termination default per Sec. 6.01(9). | C97: S1 | D97: verified (official doc)
A98: Reporting | B98: Quarterly reports within 60 days (75 for specified quarters); annual within 120 days (150 for FY2026, may be unaudited); annual compliance certificate within 120 days. | C98: S1 | D98: verified (official doc)
A99: Lease protection covenant | B99: No termination or materially adverse amendment of the lease without majority holder consent, Rating Agency Confirmation, or other listed exceptions (Sec. 4.21). | C99: S1 | D99: verified (official doc)
A101: Ratings | C101: Source | D101: Status
A102: Moody's | B102: Baa2 per the company press release; outlook not found. Moody's own release not retrieved. | C102: S5 | D102: company statement
A103: S&P / Fitch | B103: Seed shows NR. No S&P or Fitch rating found for Beacon Point (both rated River Bend). The change-of-control test uses the first rating assigned within 60 days of issue. | C103: S15 | D103: seed, unverified
A104: Rating drivers and triggers | B104: Not found because the agency report was not accessed. | C104: S5 | D104: company statement
A106: Use of proceeds | C106: Source | D106: Status
A107: Uses | B107: (1) Development and construction of the turnkey 352 MW, six-hall data center on about 521 acres in Nueces County and the on-site substation; (2) debt service reserves; (3) offering fees and expenses. | C107: S2 | D107: verified (official doc)
A109: Key risks and open issues | C109: Source | D109: Status
A110: Tenant identity and credit | B110: Tenant is unnamed in filings; AA- or higher at issuance per the 8-K. If NVIDIA (reported), standalone credit is strong, but several protections hinge on tenant rating and Qualifying Tenant status. | C110: S2 | D110: verified (official doc)
A111: NVIDIA reassignment disclosure | B111: NVIDIA's 10-Q for the quarter ended 26 Jul 2026 reports $20bn of data center leases not yet commenced 'for third parties' (about 15-year terms, commencing fiscal 2028-2029) and says it expects to reassign these leases to third parties; it separately lists $25bn of its own not-commenced data center leases. The filing does not name Hut 8 or Beacon Point; the $20bn figure and 15-year tenor are consistent with, but do not prove, the two Beacon Point leases ($19.6bn base value). If assigned, the indenture lets the Issuer consent only to an assignee that is a Qualifying Tenant or Creditworthy Transferee (Sec. 4.21(b)); a sublease with NVIDIA remaining liable is not addressed in public documents. | C111: S10 | D111: verified (official doc)
A112: Lambda / Anthropic | B112: WSJ, with Reuters single-source confirmation, reported a $35bn, six-year Anthropic cloud deal with NVIDIA-backed Lambda using about 350 MW at Beacon Point; NVIDIA reportedly holds the lease, Lambda runs the GPUs and Anthropic buys the compute. Hut 8 has not confirmed how much of the 704 MW is involved. Credit read: the end-user is a fast-growing AI lab, not an investment-grade entity, so repayment depends on NVIDIA staying the obligor (or an AA-/Aa2 transferee). NVIDIA's 10-Q notes AI clouds can stop supplying NVIDIA and sell to others, which shows circularity risk. | C112: S12 | D112: third party / news
A113: Construction and schedule | B113: Energization Q1 2027 and first hall Q3 2027 are company targets; interconnection and substation progress are on the critical path. Delay defers revenue (about $63mm in 2027 in the company illustration) while interest accrues; the DSRA is sized for construction interest of $482mm. | C113: S1 | D113: estimate
A114: Cost overrun | B114: No completion guarantee identified; overruns are covered only by contingency or sponsor equity, and a construction-debt basket exists. | C114: S1 | D114: estimate
A115: Back-loaded amortization / tail | B115: Amortization is light until the late 2030s; $4.25bn of debt against a 15-year base lease leaves limited residual tail and reliance on renewal or re-leasing for any shortfall. | C115: S1 | D115: estimate
A116: Technology obsolescence | B116: The Phase 1 hall was redesigned for NVIDIA DSX architecture (higher density); the value of a purpose-built shell to a replacement tenant is uncertain. | C116: S7 | D116: company statement
A117: Phase 2 spill-over | B117: Phase 2 (same tenant) concentrates exposure on one counterparty at the campus; its financing is under evaluation. Shared power capacity and Shared Facilities arrangements could create cross-dependencies with Phase 2. | C117: S8 | D117: company statement
A119: Recent developments (since issuance) | C119: Source | D119: Status
A120: 20 Jul 2026 | B120: Second 15-year, 352 MW lease signed with the same tenant ($9.8bn base value; campus $19.6bn; about $655mm/yr NOI per phase); Phase 2 hall delivery Q2 2028; financing not specified. | C120: S7 | D120: company statement
...

Sheet HUTRBA
A1: Hut 8 DC LLC 6.192% Senior Secured Notes due 15-Nov-2042 | D1: << Monitor
A2: Dossier as of 2026-10-16 | ISIN US44813DAA46 (seed, unverified) | IG section | Bloomberg: HUTRBA 6.192 11/15/42 144A Corp
A4: LIVE price | B4: =Monitor!H7 -> 93.919
A5: LIVE yield % | B5: =Monitor!J7 -> 6.8227402
A6: Amt o/s ($mn) | B6: =Monitor!G7 -> 3250
A7: Principal vs par ($mn) | B7: =Monitor!M7 -> -197.6325
A8: Principal vs par (%) | B8: =Monitor!N7 -> -0.06081
A9: Today's change ($mn) | B9: =Monitor!O7 -> -12.61
A10: First issued | B10: =Monitor!S7 -> 46142
A11: LIVE pickup vs tenant comp (bp) | B11: =Monitor!W7 -> 119.89574
A12: Rating | B12: =Monitor!F7 -> NR/BBB-/BBB-
A13: Tenant | B13: =Monitor!C7 -> Fluidstack (Google backstop)
A15: Summary
A16: Headline | B16: $3.25bn fully amortizing, non-recourse 144A notes issued 30 Apr 2026 by a Hut 8 SPV to build the 245 MW River Bend campus in West Feliciana Parish, Louisiana, secured by the project and a 15-year triple-net lease to Fluidstack (unrated) whose rent and certain other obligations are backstopped by Google LLC. Rated BBB- by S&P and Fitch (per press). The credit is effectively Google's for rent, but the backstop's cap and conditions are not public; no warrants to Google are disclosed (the company said none were issued). Execution risk remains until the first hall energizes in Q2 2027 at about 95% loan-to-cost.
A18: Security terms | C18: Source | D18: Status
A19: Issuer | B19: Hut 8 DC LLC, indirect wholly-owned subsidiary of Hut 8 Corp.; direct parent Hut 8 DC Member LLC ('HoldCo') is also a party to the indenture. | C19: S2 | D19: verified (official doc)
A20: Notes | B20: 6.192% Senior Secured Notes due 2042; senior secured obligations of the Issuer. | C20: S2 | D20: verified (official doc)
A21: Principal | B21: $3,250mm issued at 100% of par; original equals current (amortization starts 15 May 2028). The launch 8-K referred to $3,248mm and the company's illustrative schedule funds $3,248mm; the indenture defines Initial Notes as $3,250,000,000. Treat $3,250mm as the face amount. | C21: S1 | D21: verified (official doc)
A22: Coupon / payment dates | B22: 6.192% per annum, paid semi-annually in arrears on 15 May and 15 Nov, first payment 15 Nov 2026. Day count and record dates not captured (form of note not retrieved); 30/360 is typical but not verified. | C22: S2 | D22: verified (official doc)
A23: Pricing / issue date | B23: Priced 27 Apr 2026; indenture dated and closing 30 Apr 2026 (seed shows 30 Apr issue date, consistent). Initial price talk was about 213bp over the benchmark; final spread not stated in filings (Beacon Point priced 20bp inside River Bend at T+165, implying about T+185). | C23: S4 | D23: verified (official doc)
A24: Maturity | B24: 15 Nov 2042 (about 16.5 years). | C24: S2 | D24: verified (official doc)
A25: Offering format | B25: Rule 144A / Regulation S; J.P. Morgan Securities LLC as representative of initial purchasers; Goldman Sachs and Morgan Stanley also named as underwriters in press. | C25: S2 | D25: verified (official doc)
A26: ISIN / CUSIP | B26: Seed: ISIN US44813DAA46, CUSIP 44813DAA4. Not verified (form of note not retrieved). | C26: S16 | D26: seed, unverified
A27: Trustee | B27: Wilmington Trust, National Association, trustee and collateral agent. | C27: S1 | D27: verified (official doc)
A28: Optional redemption | B28: Make-whole (Treasury-based; spread in basis points not captured) before the Par Call Date of 15 May 2042; 100% plus accrued on or after it. 100% after a Data Center Lease Termination Event; partial 100% redemption if DSCR is below 1.10x after the Initial Commencement Date, sized to restore about 1.10x. | C28: S2 | D28: verified (official doc)
A29: Mandatory offers | B29: Change of control: put at 101%. Asset sales (excess proceeds over $15.0mm), Data Center Lease Termination Default (Termination Fee Offer within 15 Business Days) and Underbudget Amount (GMP reduction) offers at 100% plus accrued; the underbudget offer is at the Issuer's option. | C29: S1 | D29: verified (official doc)
A30: Mandatory amortization | B30: Semi-annual installments from 15 May 2028 (Amortization Commencement Date). The indenture's installment schedule (Art. 14) could not be retrieved. Company illustration (sculpted to 1.31x DSCR, $mm): 2028 63, 2029 96, 2030 112, 2031 128, 2032 146, 2033 165, 2034 185, 2035 208, 2036 232, 2037 258, 2038 286, 2039 316, 2040 348, 2041 383, 2042 323; total 3,248; fully repaid by maturity. Seed 'mid-2028 start' is consistent. | C30: S3 | D30: company statement
... A32: Trading levels (seed) | B32: Seed: yield 6.74%, spread +178bp on 15 Sep 2026; comp GOOGL 4.8% 2036. Not verified. | C32: S16 | D32: seed, unverified
A34: Issuer and structure | C34: Source | D34: Status
A35: Borrower chain | B35: Hut 8 Corp. -> indirect subsidiaries -> Hut 8 DC Member LLC (HoldCo) -> Hut 8 DC LLC (Issuer, landlord under the Fluidstack lease at River Bend). | C35: S2 | D35: verified (official doc)
A36: Recourse | B36: Non-recourse to Hut 8 Corp. (company). The Issuer is the only obligor; Google backstops the tenant, not the Issuer. | C36: S10 | D36: company statement
A37: Ring-fencing | B37: Standard SPE covenants: no unrelated business, no subsidiaries, no general partner interests, affiliate-transaction limits, restrictions on modifying the lease, the Google Guarantee or organizational documents. | C37: S2 | D37: verified (official doc)
A38: Equity | B38: Project funded at about 95% loan-to-cost per company; $184mm of prior Hut 8 equity returned at closing from note proceeds; Hut 8 expects no incremental equity. Notes plus $184mm is $3.43bn, implying a total cost near $3.4bn (derived, about $14mm per MW), above the $9-11mm per MW build cost targeted in Dec 2025. | C38: S9 | D38: company statement
A40: Sponsor and parent | C40: Source | D40: Status
A41: Sponsor | B41: Hut 8 Corp. (Nasdaq: HUT), Miami. Contracted AI portfolio 949 MW including 245 MW at River Bend, supported by 1,330 MW utility capacity (company). | C41: S10 | D41: company statement
A42: Related financings | B42: $4.25bn Beacon Point notes (Jun 2026, Baa2); $1.07bn parent revolver closed 24 Sep 2026, undrawn, first-lien on substantially all parent and guarantor assets, minimum liquidity covenant of 40% of commitments from 31 Mar 2027; FalconX bitcoin-backed loan refinanced to 7.0%. | C42: S14 | D42: verified (official doc)
A43: Anthropic partnership | B43: December 2025 partnership with Anthropic and Fluidstack: Hut 8 and Anthropic may jointly develop up to 1,050 MW of additional optional capacity, up to 2,295 MW in total, with River Bend as the anchor. This is not a commitment of the River Bend notes' credit. | C43: S8 | D43: company statement
A45: Tenant and lease | C45: Source | D45: Status
A46: Tenant | B46: Fluidstack USA IV Inc., a Delaware corporation (subsidiary of Fluidstack Ltd., a private AI infrastructure provider); not rated. Anthropic is reported as the workload provider. | C46: S1 | D46: verified (official doc)
A47: Lease document | B47: Data Center Lease dated 15 Dec 2025 between the Issuer (landlord) and Fluidstack USA IV Inc.; not filed in full. | C47: S1 | D47: verified (official doc)
A48: Lease terms | B48: 15-year base term, triple net, build-to-suit, 245 MW critical IT supported by 330 MW utility capacity (PUE 1.35); fixed rent with 3.0% annual escalator; three 5-year renewal options (up to 30 years); base-term contract value $7.0bn; $17.5-17.7bn with all renewals (the company's two slides differ). | C48: S7 | D48: company statement
A49: Rent / NOI | B49: Company: expected cumulative NOI $6.9bn over base term, about $454mm per year or about $1.85mm per MW. Illustrative revenue $171mm in 2027, $373mm in 2028 rising to $547mm in 2041. Absolute base rent per MW not disclosed; seed $1.50mm/MW is below the company's $1.85mm average and unverified. | C49: S3 | D49: company statement
A50: Expansion right | B50: Fluidstack holds a right of first offer on up to 1,000 MW of additional IT capacity, subject to expanded power; excluded from pipeline figures. | C50: S10 | D50: company statement
A51: Commencement | B51: Initial data hall Q2 2027 (company), more halls through the rest of 2027; seed commencement Apr-Oct 2027. Lease Commencement Date is defined per Critical Power Phase. | C51: S6 | D51: company statement
A52: Assignment / replacement | B52: Novation or assignment under the project documents, including by Google or its affiliates, is permitted without breaching covenants. Qualifying Tenant: NVIDIA, Apple, Microsoft, Amazon, Alphabet (incl. Google), Meta or controlled affiliates; any NASDAQ/NYSE-listed hyperscaler or technology company with market cap or EV of at least $50.0bn; or a party approved by a majority of holders. Replacement needs a Rating Agency Confirmation. | C52: S1 | D52: verified (official doc)
A53: Operations Services Agreement | B53: A separate OSA between Hut 8 and Fluidstack is expected to be backed by an additional Google backstop; it is not part of the notes' collateral as described. | C53: S6 | D53: company statement
A54: Delay, termination, SLA terms | B54: Not found: lease not public. The 10-K lists construction delay penalties or liquidated damages to customers as a risk factor in general. | C54: S8 | D54: company statement
A56: Project and site | C56: Source | D56: Status
A57: Location | B57: River Bend campus, St. Francisville, West Feliciana Parish, Louisiana (MISO); 627 owned acres with potential expansion to 2,988 acres (company, Dec 2025). | C57: S7 | D57: company statement
A58: Capacity | B58: 245 MW critical IT of turnkey data center plus substation; first of four data halls reported (local source). 330 MW utility capacity under construction. | C58: S10 | D58: company statement
A59: Cost | B59: Dec 2025 target build cost $9-11mm per MW; derived all-in near $3.4bn (see Equity). Seed facility cost $3,057mm and $12.5mm/MW not verified. | C59: S16 | D59: seed, unverified
A60: Water | B60: Hut 8 reportedly committed about $16mm to a new well and about eight miles of water main to be transferred to the parish. | C60: S13 | D60: third party / news
A62: Power and utilities | C62: Source | D62: Status
A63: Utility | B63: Entergy Louisiana: initial 330 MW with potential for up to 1,000 MW more; 330 MW available from 1 Jul 2026 (company); a 16-year electric service agreement is reported by secondary press. | C63: S7 | D63: company statement
A64: Site works | B64: Grading, Entergy access roads, switchyard construction and transmission line preparation underway as of Dec 2025; campus substation under construction at Aug 2026. | C64: S10 | D64: company statement
A65: Permits | B65: Not found in documents retrieved; no parish or Louisiana PSC records reviewed. | C65: S10 | D65: company statement
A67: Construction and delivery | C67: Source | D67: Status
A68: Contractor | B68: Jacobs is EPCM / design-build partner working with Vertiv for critical power and cooling; indenture refers to a Guaranteed Maximum Price contract in effect on the Issue Date and an Underbudget Amount mechanism if a revised GMP is signed. | C68: S1 | D68: verified (official doc)
A69: Schedule | B69: Initial data hall energization and commissioning targeted Q2 2027; remaining halls in phases through 2027. | C69: S10 | D69: company statement
A70: Status at 16 Oct 2026 | B70: As of 4 Aug 2026: vertical construction started, campus substation continuing, initial long-lead equipment received. A local report in Oct 2026 cites over 1,200 workers and first hall operating early 2027. | C70: S10 | D70: company statement
A71: Overrun protection | B71: GMP contract with Jacobs per indenture/press; GMP terms (cap, liquidated damages, completion security) not disclosed. No sponsor completion guarantee found. | C71: S1 | D71: verified (official doc)
A72: Construction DSRA | B72: $293.475mm (interest on next three payment dates) less interest paid, plus 50% of next interest and 50% of the first installment due 15 May 2028. | C72: S1 | D72: verified (official doc)
A74: Financing and capital structure | C74: Source | D74: Status
A75: Debt | B75: Single tranche $3,250mm fully amortizing notes; about 95% LTC; non-recourse. Post-commencement pari passu debt needs a Rating Agency Confirmation; general basket $10.0mm, secured/finance leases $20.0mm combined, letters of credit $50.0mm, construction debt up to the budgeted cost less the notes. | C75: S1 | D75: verified (official doc)
A76: Company illustrative metrics | B76: DSCR 1.31x for 2028-2041 (1.74x in 2027), initial leverage 9.20x falling to 4.61x in 2035 and 0.58x in 2041, initial ICR 1.74x; cumulative interest $1,982mm; levered FCF $1,670mm. Seed leverage 8.8x differs. | C76: S3 | D76: company statement
A77: Fitch forecast | B77: Fitch forecasts minimum DSCR 1.31x and average 1.32x (secondary report of the agency view). | C77: S11 | D77: third party / news
A78: Refinancing risk | B78: None by design (fully amortizing to zero by Nov 2042); the 2042 company year shows final-year DSCR 1.82x. Tail is thin: maturity roughly coincides with end of the 15-year base lease. | C78: S3 | D78: estimate
A80: Credit enhancement and support | C80: Source | D80: Status
A81: Google backstop (scope) | B81: Google LLC provides a financial backstop (the 'Google Guarantee', governed by a guarantee of the 15 Dec 2025 lease) covering all rent and certain other financial obligations under the lease, described by the company as lease payments and related pass-through obligations for the 15-year base term. Google is an Alphabet subsidiary (S&P AA+, Moody's Aa2 at the Dec 2025 announcement). | C81: S5 | D81: verified (official doc)
A82: Google backstop (cap, conditions, effectiveness) | B82: No cap, dollar limit, term beyond the base term, conditions precedent, notice or demand mechanics, or default definition were found in public documents; the guarantee instrument is not filed. Indenture treats the Google Guarantee as a Project Document that the Issuer cannot terminate or materially adversely amend without holder consent or Rating Agency Confirmation, and permits novation or assignment by Google or its affiliates (Sec. 4.21(a)(iv)). A Google Guarantee ceasing is not listed as a standalone event of default in the portion read. | C82: S1 | D82: verified (official doc)
A83: Reported structural features | B83: Secondary press reports (single source) describe novation rights during the first six years and a springing Alphabet guarantee if Google's revenue falls below 50% of Alphabet consolidated revenue. Not verified in primary documents. | C83: S11 | D83: third party / news
A84: Warrants to Google | B84: None found. The company's Dec 2025 presentation states that no equity or warrants were issued to secure the transaction. No later disclosure of warrants to Google found in Hut 8 filings reviewed. | C84: S7 | D84: company statement
A85: Termination fee / replacement | B85: Lease termination fee (amount undisclosed) goes to a Designated Account; the Issuer must use commercially reasonable efforts to cause the Tenant, Google or a Qualifying Tenant to pay it; funds repurchase notes at 100%. Lease EoD requires lease termination, no Qualifying Data Center Lease within 6 months (12 with LOI with Google or a Qualifying Tenant and funded DSRA), and failure to run a Termination Fee Offer. | C85: S1 | D85: verified (official doc)
A86: Parent recourse | B86: None. | C86: S10 | D86: company statement
A88: Covenants, waterfall and reserves | C88: Source | D88: Status
A89: Waterfall | B89: Notes Proceeds Account funds project costs and debt service before commencement. Revenue Account excludes termination fees and excluded property; applied under Sec. 4.23(f) in priority (operating costs, debt service, DSRA, then other uses). Project Accounts have springing control agreements. | C89: S1 | D89: verified (official doc)
A90: Distribution test | B90: Restricted Payments from Available Retained Excess Cash Flow only if DSCR exceeds 1.10x; other payments only if DSCR stays at or above 1.10x; tax distributions need a funded DSRA; a one-time distribution of unused contingency at commencement. | C90: S1 | D90: verified (official doc)
A91: DSRA after construction | B91: 50% of next interest plus 50% of next installment; may use letters of credit (basket $50.0mm plus DSRA-specific LC capacity). | C91: S1 | D91: verified (official doc)
A92: Events of default | B92: Cross-default and judgment threshold $25.0mm (judgment 90 days unstayed); lease termination default per Sec. 6.01(9); other EoD details not fully captured. | C92: S1 | D92: verified (official doc)
A93: Change of control | B93: 101% put on a Change of Control Trigger Event (Change of Control plus Ratings Decline); control tests tied to Hut 8 voting power before the Initial Commencement Date and operational control (Qualified Operator needs 200MW+ US data center control). | C93: S1 | D93: verified (official doc)
A95: Ratings | C95: Source | D95: Status
A96: S&P | B96: BBB- (preliminary Positive outlook at pricing; later press cites final BBB-). S&P reportedly flagged single-tenant concentration as mitigated by the Google backstop. S&P release not retrieved. | C96: S12 | D96: third party / news
A97: Fitch | B97: BBB- (expected at pricing; Stable outlook). Fitch reportedly forecasts minimum DSCR 1.31x. Fitch release not retrieved. | C97: S11 | D97: third party / news
A98: Moody's | B98: Not rated (seed shows NR). Hut 8 PR for Beacon Point compared its Baa2 to the BBB- on River Bend from S&P and Fitch. | C98: S16 | D98: seed, unverified
A99: Triggers | B99: Rating-agency upgrade/downgrade triggers not found; indenture Applicable Rating is the lower of the first rating within 60 days and the rating at announcement of a change of control. | C99: S1 | D99: verified (official doc)
A101: Use of proceeds | C101: Source | D101: Status
A102: Uses | B102: (1) Finance part of the development and construction of the turnkey 245 MW data center and substation at River Bend; (2) reimburse Hut 8 for part of prior equity contributions (about $184mm per press); (3) fund debt service reserves; (4) fees and expenses. | C102: S2 | D102: verified (official doc)
A104: Key risks and open issues | C104: Source | D104: Status
A105: Tenant credit | B105: Fluidstack is an unrated private company; the lease is investment grade only through the Google Guarantee. The cap and conditions of that guarantee are the key unknown. | C105: S5 | D105: verified (official doc)
A106: Backstop effectiveness | B106: Public documents do not show whether Google pays on first demand, whether it covers termination payments, damages or only rent, whether it survives lease amendment or assignment, or the cap. The reported Alphabet springing guarantee and six-year novation right are unverified. | C106: S11 | D106: third party / news
A107: Anthropic dependence | B107: Anthropic is reported as the workload provider; Anthropic is not a lease party or guarantor. If Fluidstack loses the end-customer, the lease continues but Google exposure grows. | C107: S8 | D107: company statement
A108: Construction | B108: Q2 2027 first hall with phased halls through 2027; ~95% LTC leaves little equity cushion; cost overrun beyond GMP is on Hut 8 DC LLC. Revenue starts 2027 at $171mm illustration; DSRA sized to three interest payments during construction. | C108: S9 | D108: estimate
A109: Thin tail | B109: Debt amortizes fully by Nov 2042 and base lease runs about 15 years from 2027; no residual beyond the base term. | C109: S3 | D109: estimate
A110: Power | B110: Entergy Louisiana 330 MW; energization on the critical path for the Q2 2027 date; local water/infrastructure scrutiny reported. | C110: S7 | D110: company statement
A111: Technology obsolescence / replacement | B111: Replacement tenant must be a Qualifying Tenant plus Rating Agency Confirmation, a high bar for a purpose-built AI shell. | C111: S1 | D111: verified (official doc)
A113: Recent developments (since issuance) | C113: Source | D113: Status
A114: Q2 2027 delivery on track | B114: 4 Aug 2026: vertical construction started, substation under way, initial long-lead equipment received; Fluidstack ROFO on 1,000 MW remains. | C114: S10 | D114: company statement
A115: Parent revolver | B115: 24-28 Sep 2026: $1.07bn revolver closed (undrawn). | C115: S14 | D115: verified (official doc)
A116: Local status | B116: Oct 2026 local report: over 1,200 workers on site; first hall expected early 2027. | C116: S13 | D116: third party / news
A117: Trading | B117: Seed: +178bp / 6.74% on 15 Sep 2026; unverified. | C117: S16 | D117: seed, unverified
...

Sheet RPLDCI
A1: Beignet Investor LLC 6.581% Senior Secured Notes due 30-May-2049 | D1: << Monitor
A2: Dossier as of 2026-10-16 | ISIN US076912AA21 (144A; CUSIP 076912AA2) | IG section | Bloomberg: RPLDCI 6.581 05/30/49 144A Corp
A4: LIVE price | B4: =Monitor!H8 -> 91.908
A5: LIVE yield % | B5: =Monitor!J8 -> 7.4801614
A6: Amt o/s ($mn) | B6: =Monitor!G8 -> 27293.8
A7: Principal vs par ($mn) | B7: =Monitor!M8 -> -2208.6143
A8: Principal vs par (%) | B8: =Monitor!N8 -> -0.08092
A9: Today's change ($mn) | B9: =Monitor!O8 -> -139.19838
A10: First issued | B10: =Monitor!S8 -> 45951
A11: LIVE pickup vs tenant comp (bp) | B11: =Monitor!W8 -> 115.02546
A12: Rating | B12: =Monitor!F8 -> NR/A+/NR
A13: Tenant | B13: =Monitor!C8 -> Meta
A15: Summary
A16: Headline | B16: A single-tranche, fully amortising 144A project bond (about $27.3bn) issued in Oct 2025 to fund the Hyperion data centre campus in Richland Parish, Louisiana, owned by a joint venture in which Blue Owl funds hold 80% and Meta 20%. Debt service is meant to come from Meta's lease rent plus a Meta residual value guarantee (RVG), so the credit is essentially Meta's; S&P rates it A+ (one notch below Meta), per press reports. Meta consolidates nothing: it treats the JV as an unconsolidated VIE, but discloses $46.0bn of maximum exposure to loss as of 30-Jun-2026. Main watch items are construction and power delivery (the campus was announced in Jul 2026 to scale to 5 GW) and what happens at the end of each four-year lease block.
A18: Security terms | C18: Source | D18: Status
A19: Issuer / notes title | B19: Beignet Investor LLC, 6.581% Senior Secured Notes due 30 May 2049 (fixed rate). | C19: S5 | D19: verified (official doc)
A20: ISIN / CUSIP | B20: ISIN US076912AA21, CUSIP 076912AA2 as held in a US mutual fund N-PORT filing (fund holdings report, not the indenture). Reg S identifiers not found. | C20: S5 | D20: verified (official doc)
A21: Coupon and maturity | B21: 6.581% fixed; maturity 30-May-2049. N-PORT reports the same coupon and maturity date. IFR describes a 23.6-year tenor. | C21: S5 | D21: verified (official doc)
A22: Size | B22: About $27.3bn, single tranche, senior secured, amortising, 144A/Reg S format (IFR). Seed outstanding $27,293.8mm. No official document found that states the exact original principal. | C22: S7 | D22: third party / news
A23: Pricing and issue date | B23: Priced 16-Oct-2025 at a reported spread of about T+225bp (IFR / Global Data Center Hub). JV signing announced 21-Oct-2025; seed issue date 2025-10-21 is consistent with closing. | C23: S7 | D23: third party / news
A24: Ranking and amortisation | B24: IFR describes a single-asset, long-dated, fully amortising bond; proceeds held in Treasuries and drawn down during construction; investors accepted no make-whole. The amortisation schedule itself was not found. Seed: amortisation starts mid-2029 at about 1% p.a. (seed, unverified). | C24: S8 | D24: third party / news
A25: Call / redemption | B25: Seed shows next call 30-Nov-2048 at par (6 months before maturity). Not verified against an indenture. | C25: S0 | D25: seed, unverified
A26: Trustee, governing law, denominations, clearing | B26: Not found: indenture and offering memorandum are private (data-room access under NDA per IFR). | C26: S7 | D26: third party / news
A28: Issuer and structure | C28: Source | D28: Status
A29: Joint venture ownership | B29: In Oct 2025 Meta and an affiliate of Blue Owl-managed funds formed a JV to co-develop the Louisiana campus. After closing, Meta holds a 20% membership interest and the Blue Owl investor 80%. Meta contributed about $4.3bn of held-for-sale assets (mostly construction in progress and land), net of liabilities; the investor contributed $7.0bn cash; Meta received a one-time $2.6bn distribution. | C29: S1 | D29: verified (official doc)
A30: Press release figures differ slightly | B30: The joint press release (as relayed by Hubbis) says Meta received a one-time distribution of about $3bn and cash from Blue Owl was about $7bn; Meta's 10-Q says $2.6bn. The 10-Q is used as the authoritative figure. | C30: S6 | D30: company statement
A31: Funding commitment | B31: The parties committed to fund their pro rata shares of approximately $27bn of total estimated development costs (buildings plus long-lived power, cooling and connectivity infrastructure). | C31: S4 | D31: verified (official doc)
A32: Structure in words | B32: Per IFR and Global Data Center Hub, Beignet Investor is a Blue Owl fund-sponsored issuer sitting above the JV (JV Co) that owns the campus; Meta leases the campus from the JV. Bondholders have no direct recourse to the underlying data centre assets (reported). The exact security package (pledge of JV equity vs mortgage) was not confirmed from an offering document. | C32: S9 | D32: third party / news
A33: Services by Meta | B33: Meta provides construction management, administrative and property management services to the JV. | C33: S1 | D33: verified (official doc)
A34: Equity quantum | B34: Global Data Center Hub reports about $2.5bn of equity alongside $27.3bn of debt (plus accrued interest income during construction) and a total capital base of about $28.8bn; the numbers do not fully reconcile in the source. Seed facility cost $28,800mm is consistent with this. | C34: S9 | D34: third party / news
A36: Sponsor and parent | C36: Source | D36: Status
A37: Sponsor | B37: Funds managed by Blue Owl Capital (rated BBB by S&P per IFR) hold the 80% equity and formal governance. The JV was arranged by Morgan Stanley, which was exclusive financial adviser to Meta and sole bookrunner on the private offering. | C37: S6 | D37: company statement
A38: Meta role | B38: Meta is 20% JV partner, developer/construction manager, property manager, sole tenant and RVG provider. Meta guided that Hyperion is part of a larger AI buildout and announced a scale-up to 5 GW in Jul 2026. | C38: S9 | D38: third party / news
A39: Other Blue Owl financings | B39: Not researched in detail: no document found linking Blue Owl's own capital position to this deal beyond the equity commitment. | C39: S6 | D39: company statement
A41: Tenant and lease | C41: Source | D41: Status
A42: Tenant | B42: Meta Platforms (and subsidiaries) enters multiple operating leases with the JV for properties on the campus. Meta corporate rating AA-/Aa3 per IFR. | C42: S4 | D42: verified (official doc)
A43: Lease term | B43: Each leased property has an initial four-year term, with renewal options for a total lease period of up to 20 years. Leases commence in 2029. | C43: S4 | D43: verified (official doc)
A44: Aggregate initial lease commitment | B44: About $12.31bn for the initial four-year terms (company disclosure, contractual). Simple arithmetic implies roughly $3.1bn a year, or about $1.5mm per MW-year on the seed 2,064 MW (estimate; the 12.31bn may reflect staggered commencement dates, so this is not the contractual rent per MW). Seed base rent $1.23mm/MW and 2% escalator are not verified. | C44: S4 | D44: estimate
A45: Lease type | B45: Reported as triple-net with rent payable in full during construction delays; abatement only for force majeure or landlord default (Global Data Center Hub). Seed also says triple net. Lease documents not seen. | C45: S9 | D45: third party / news
A46: Rent start | B46: Seed/third parties cite rent commencement June 2029 (IFR: completion slated June 2029). | C46: S7 | D46: third party / news
A47: Payment guaranty | B47: Global Data Center Hub reports Meta provides a payment guaranty plus the RVG; S&P-related commentary elsewhere disputes whether a guarantee of rent exists. Not confirmed in any Meta filing. | C47: S9 | D47: third party / news
A49: Project and site | C49: Source | D49: Status
A50: Location and scale | B50: Richland Parish, Louisiana. Seed critical IT 2,064 MW (about 2.1 GW; IFR also 2.1 GW). Meta confirmed on 13-Jul-2026 a scale-up to 5 GW across 3,200 acres with total investment above $50bn (secondary report of Meta announcement). It is not clear whether the expansion sits inside the notes' collateral perimeter. | C50: S9 | D50: third party / news
A51: Cost | B51: About $27bn estimated development cost per Meta's filings; capital base about $28.8bn per Global Data Center Hub. Implied capex per MW about $13-14mm (seed $14.0mm). | C51: S4 | D51: verified (official doc)
A52: Buildings and phases | B52: Earlier plans reported nine buildings delivered in phases through 2030; first 2 GW online by about 2030 and full 5 GW about 2032 (news). Groundbreaking Dec 2024 with an initial $10bn budget (news). | C52: S9 | D52: third party / news
A53: What the notes finance | B53: The campus the JV owns and Meta leases: buildings and long-lived power, cooling and connectivity infrastructure (Meta's description of the $27bn cost base). | C53: S4 | D53: verified (official doc)
A55: Power and utilities | C55: Source | D55: Status
A56: Utility and first approval | B56: Entergy Louisiana serves the campus. The Louisiana Public Service Commission approved, on 20-Aug-2025 by 4-1, three new gas plants totalling about 2.26 GW: two in Richland Parish (expected late 2028) and one at Waterford in St. Charles Parish (expected end 2029). Meta subsidises costs for the first 15 years per press reports. | C56: S11 | D56: third party / news
A57: Electric service agreement | B57: Entergy states an electric service agreement with a subsidiary of Meta was previously executed for the first north-Louisiana data centre. In March 2026 Entergy Louisiana signed a second ESA with Evest LLC, a Meta subsidiary, for a second north-Louisiana data centre, secured partly by a Meta guaranty and conditional on LPSC approval. That second ESA and the related application are separate from the Hyperion notes unless the site is the expansion; Entergy does not use the name Hyperion. | C57: S10 | D57: verified (official doc)
A58: Pending large generation application | B58: March 2026 application to the LPSC for seven combined-cycle units totalling 5,278 MW (about $12.9bn), four near the customer site in Richland Parish and three at Pointe Coupee, with in-service dates in 2030-2031, plus a 500 kV line (about $1.4bn). Decision targeted at the LPSC December 2026 meeting; intervenors obtained a ruling in Jul 2026 on a subpoena to Meta for project information. | C58: S10 | D58: verified (official doc)
A59: Grid dependence | B59: Reports say the 5 GW scale-up depends on plants still under regulatory review; Meta funds the Smalling substation (groundbreaking Jun 2026) and a reported 2.5 GW of renewables. | C59: S9 | D59: third party / news
A61: Construction and delivery | C61: Source | D61: Status
A62: Start and status | B62: Construction began late 2024 (groundbreaking Dec 2024 reported); construction described as well underway with thousands of workers in Oct 2025. Meta is construction manager. Entergy said construction started in earnest early 2026 (secondary). | C62: S6 | D62: company statement
A63: Schedule | B63: Leases commence in 2029 per Meta; rent start June 2029 per IFR / seed. No official phase-by-phase delivery schedule was found. | C63: S4 | D63: verified (official doc)
A64: Overrun protection | B64: Meta's 10-K says its exposure includes its estimated future funding commitments to the JV. Detailed completion guarantee or cost-overrun terms were not found. IFR says Meta bears construction and demand risk. | C64: S2 | D64: company statement
A65: Advisers | B65: Arup (independent engineer), Arthur D. Little (commercial diligence), Marsh (risk and insurance), Latham & Watkins (Meta counsel), Kirkland & Ellis (Blue Owl counsel), Milbank (Morgan Stanley counsel). | C65: S6 | D65: company statement
A67: Financing and capital structure | C67: Source | D67: Status
A68: Sources | B68: Debt about $27.3bn (notes) plus Blue Owl equity; Meta contributed assets of $4.3bn and Blue Owl $7.0bn cash at closing; remaining pro rata commitments funded over construction. Seed debt-funded share 90%, leverage at issuance 9.1x (seed, unverified). | C68: S1 | D68: verified (official doc)
A69: Anchor investor and demand | B69: PIMCO was the main anchor per IFR; a low double-digit number of investors; BlackRock ETFs reportedly took more than $3bn. Bonds traded up about 10 points early. | C69: S7 | D69: third party / news
A70: Reserves / interest | B70: Proceeds held in Treasuries and drawn during construction; Global Data Center Hub notes about $1.2bn accrued interest income. No DSRA or reserve details found. | C70: S8 | D70: third party / news
A71: Refinancing | B71: Bond is fully amortising to 2049 and is meant to be repaid from rent and, at the end of lease blocks, RVG or remarketing proceeds, so there is no stated balloon (IFR). | C71: S8 | D71: third party / news
A73: Credit enhancement and support | C73: Source | D73: Status
A74: Residual value guarantee | B74: Meta provided an RVG for the first 16 years of operations. If Meta terminates or does not renew a lease and certain conditions are met, and the then-current value falls below an agreed threshold, Meta makes a capped cash payment equal to the shortfall (difference between fair value and threshold). Aggregate threshold about $28bn at inception and decreasing over time; Meta's maximum payment is capped at this shortfall per property. | C74: S2 | D74: verified (official doc)
A75: Years 17-20 | B75: IFR reports the final four years are covered by a termination fee equal to the outstanding balance instead of the RVG. Not confirmed in Meta filings. | C75: S8 | D75: third party / news
A76: Meta payment guaranty | B76: Reported by Global Data Center Hub; not seen in Meta's SEC filings. | C76: S9 | D76: third party / news
A77: Meta maximum exposure | B77: Meta reports maximum exposure to loss from the JV of $46.03bn at 30-Jun-2026 ($45.95bn at 31-Dec-2025), made up of the equity carrying value ($2.92bn at Jun 2026), the lease commitments, estimated future funding commitments and the maximum RVG threshold. | C77: S4 | D77: verified (official doc)
A79: Covenants, waterfall and reserves | C79: Source | D79: Status
A80: Documentation | B80: Indenture, waterfall, DSCR tests, lock-up triggers, events of default and additional-debt limits are in a private offering memorandum that was not accessible. S&P is reported to use a 1.12x debt service coverage ratio for the operating phase (IFR). No covenant detail verified. | C80: S8 | D80: third party / news
A81: No make-whole | B81: IFR reports investors accepted no make-whole on early repayment. | C81: S8 | D81: third party / news
A83: Ratings | C83: Source | D83: Status
A84: S&P | B84: A+ (per IFR and The Asset; S&P is reportedly the only agency). Rated one notch below Meta (AA-) because bondholders rely on Meta's rent and RVG; S&P's primary release was not accessed, so outlook and exact triggers are unknown. Reported base case includes eight years of lease payments. | C84: S7 | D84: third party / news
A85: Moody's / Fitch | B85: Seed shows NR/A+/NR. No Moody's or Fitch rating found. | C85: S7 | D85: seed, unverified
A86: Triggers | B86: Not found. A downgrade of Meta would presumably pass through given the one-notch linkage (analyst inference). | C86: S7 | D86: estimate
A88: Use of proceeds | C88: Source | D88: Status
A89: Use | B89: Fund the JV's development of the Hyperion campus (buildings and long-lived power, cooling and connectivity infrastructure) pro rata with equity; proceeds are parked in Treasuries and drawn during construction. | C89: S4 | D89: verified (official doc)
A91: Key risks and open issues | C91: Source | D91: Status
A92: Tenant concentration | B92: All rent and the RVG come from Meta; the notes are rated one notch below Meta. | C92: S7 | D92: third party / news
A93: Lease-block roll-off | B93: Each lease has only a four-year firm term; if Meta does not renew, the bond is repaid from RVG (capped, decreasing threshold), sale or re-leasing. Meta judged remarketing decisions to be the activity that most affects the JV's performance, which is why it does not consolidate. | C93: S3 | D93: verified (official doc)
A94: Power delivery and cost | B94: Gas plants approved for about 2.26 GW arrive late 2028 to end 2029; the larger expansion needs 5.3 GW of further plants not yet approved (decision targeted Dec 2026), and ratepayer-cost opposition at the LPSC (4-1 vote in 2025). | C94: S10 | D94: verified (official doc)
A95: Scope creep | B95: Expansion to 5 GW and over $50bn may move cash and construction priority between the financed perimeter and new phases; the notes cover the original roughly 2 GW project. | C95: S9 | D95: third party / news
A96: Accounting optics | B96: Meta does not consolidate the JV (unconsolidated VIE) but discloses $46bn maximum exposure; critics argue the debt is economically Meta's (IFR). | C96: S4 | D96: verified (official doc)
A97: Technology obsolescence | B97: Asset value must support RVG threshold decreasing over time; AI hardware cycles are shorter than the 20-year horizon (analyst view). | C97: S8 | D97: estimate
A99: Recent developments (since issuance) | C99: Source | D99: Status
A100: Meta filings | B100: 10-K (29-Jan-2026) and 10-Qs of 30-Apr-2026 and 30-Jul-2026 repeat the same terms; RVG payments judged not probable and no liability recorded. Equity carrying value rose from $1.83bn (Dec 2025) to $2.92bn (Jun 2026). | C100: S4 | D100: verified (official doc)
A101: 5 GW expansion | B101: 13-Jul-2026: Meta confirms campus to 5 GW and over $50bn (secondary report). | C101: S9 | D101: third party / news
A102: Entergy filings | B102: Mar 2026 ESA with Evest LLC and the 5,278 MW application, pending; LPSC schedule aims for a December 2026 vote. | C102: S10 | D102: verified (official doc)
A103: Pricing | B103: Seed: yield 7.15% and spread 205bp at 15-Sep-2026 versus about T+225bp at issue (seed, unverified). | C103: S0 | D103: seed, unverified
A105: Timeline | C105: Source
A106: 2024-12 | B106: Groundbreaking at Hyperion with an initial $10bn budget (reported). | C106: S9
A107: 2025-08-20 | B107: Louisiana PSC approves, 4-1, Entergy Louisiana's three gas plants (about 2.26 GW) to serve the Meta data centre. | C107: S11
A108: 2025-10-16 | B108: Beignet Investor prices roughly $27.3bn single-tranche 144A notes at about T+225bp; S&P A+. | C108: S7
A109: 2025-10-21 | B109: Meta and Blue Owl funds sign JV agreement; Meta contributes about $4.3bn of assets and receives $2.6bn distribution, Blue Owl funds contribute $7.0bn. | C109: S1
A110: 2025-10-27 | B110: Joint announcement of the roughly $27bn JV (80/20) and Meta RVG for first 16 years. | C110: S6
A111: 2025-10-30 | B111: Meta Q3 10-Q discloses the JV, leases ($12.3bn initial commitment), RVG and unconsolidated VIE treatment. | C111: S1
A112: 2026-01-29 | B112: Meta 10-K: maximum exposure to loss $45.95bn; RVG payments not probable. | C112: S2
A113: 2026-03 | B113: Entergy Louisiana signs second Meta ESA (Evest LLC) and files for seven new CCGTs totalling 5,278 MW. | C113: S10
A114: 2026-04-30 | B114: Meta Q1 10-Q: same lease and RVG terms; judgment on consolidation explained. | C114: S3
A115: 2026-06 | B115: Entergy breaks ground on Smalling Substation, funded by Meta (reported). | C115: S9
A116: 2026-07-13 | B116: Meta announces Hyperion scale-up to 5 GW and over $50bn (reported). | C116: S9
A117: 2026-07-30 | B117: Meta Q2 10-Q: JV equity carrying value $2.92bn; maximum exposure $46.03bn. | C117: S4
...

Sheet TXEDCI
A1: Sopaipilla Investor LLC 7.534% Senior Secured Notes due 30-Nov-2048 | D1: << Monitor
A2: Dossier as of 2026-10-16 | ISIN US83577VAA89 (144A; CUSIP 83577VAA8) | IG section | Bloomberg: TXEDCI 7.534 11/30/48 144A Corp
A4: LIVE price | B4: =Monitor!H9 -> 98.999
A5: LIVE yield % | B5: =Monitor!J9 -> 7.6225604
A6: Amt o/s ($mn) | B6: =Monitor!G9 -> 12639.5
A7: Principal vs par ($mn) | B7: =Monitor!M9 -> -126.5214
A8: Principal vs par (%) | B8: =Monitor!N9 -> -0.01001
A9: Today's change ($mn) | B9: =Monitor!O9 -> -70.27562
A10: First issued | B10: =Monitor!S9 -> 46233
A11: LIVE pickup vs tenant comp (bp) | B11: =Monitor!W9 -> 130.43094
A12: Rating | B12: =Monitor!F9 -> NR/A+/AA-
A13: Tenant | B13: =Monitor!C9 -> Meta
A15: Summary
A16: Headline | B16: A roughly $12.3-12.6bn 144A senior secured bond issued in late Jul 2026 to fund Meta's El Paso, Texas data centre campus (about 1 GW, about $14bn total cost), owned by a JV in which BlackRock-managed funds (GIP and HPS) hold 80% and Meta 20%. Meta is sole tenant, developer and operator, pays rent from Dec 2028 whether or not the campus is complete, and provides a residual value guarantee (up to about $13bn per its 10-Q). Ratings reported at A+ (S&P, preliminary) and AA- (Fitch, expected); the one-notch gap reflects the absence of an asset mortgage. Seed 7.534% coupon, ISIN and maturity are confirmed by a fund holdings filing, but almost everything else rests on press and newsletter coverage because the offering memorandum is private and Meta has not yet filed its post-closing 10-Q.
A18: Security terms | C18: Source | D18: Status
A19: Issuer / notes title | B19: Sopaipilla Investor, LLC, 7.534% Senior Secured Notes due 30 Nov 2048 (the N-PORT shows the coupon rounded to 7.53%). | C19: S2 | D19: verified (official doc)
A20: ISIN / CUSIP | B20: ISIN US83577VAA89, CUSIP 83577VAA8 as reported in a US mutual fund N-PORT (Hartford Mutual Funds II, period 31-Jul-2026). Reg S identifiers not found. | C20: S2 | D20: verified (official doc)
A21: Maturity and coupon | B21: Fixed rate; maturity 30-Nov-2048 per N-PORT. Seed coupon 7.534% matches the issue title; N-PORT shows 7.53. | C21: S2 | D21: verified (official doc)
A22: Size | B22: Launched at $12.3bn on 23-24 Jul 2026 (bookrunners JPMorgan and Morgan Stanley); other press reports about $12.5bn sold after a nearly week-long process with weaker-than-expected demand. Seed shows $12,639.5mm outstanding; no official document confirms the final amount. | C22: S3 | D22: third party / news
A23: Issue date | B23: Seed issue date 30-Jul-2026; priced in the week of 27-Jul-2026 per press. Not confirmed from an indenture. | C23: S0 | D23: seed, unverified
A24: Ranking, call, amortisation, trustee, law | B24: Described as senior secured; call (seed: 30-May-2048 at par), amortisation schedule (seed: starts late 2028, about 1% p.a.), make-whole, denominations, trustee and governing law are not found in any accessible document. | C24: S0 | D24: seed, unverified
A26: Issuer and structure | C26: Source | D26: Status
A27: JV ownership | B27: Funds managed by BlackRock (through GIP and HPS) hold 80% of the JV that owns the El Paso campus; Meta holds 20%. Meta is construction manager, property manager and sole tenant. Announced 28-Jul-2026. | C27: S5 | D27: company statement
A28: Meta disclosure | B28: Meta's Q2 10-Q (30-Jul-2026) says that in July 2026 it entered an exclusivity agreement to co-develop an El Paso campus through a venture in which it would hold a 20% interest; subject to definitive agreements and closing, expected Q3 2026. Meta expects to contribute about $2.3bn of held-for-sale assets (net) and receive a one-time distribution of about $1bn. | C28: S1 | D28: verified (official doc)
A29: Contributions | B29: Press release (via TNW): BlackRock contributes about $4.9bn cash at financial close; Meta contributes land and construction in progress worth about $2.3bn and receives about $1bn to align ownership; about $12.5bn of debt is raised at the venture level. | C29: S5 | D29: third party / news
A30: Obligor and security package | B30: Issuer is a holding vehicle tied to Project Sopaipilla Holdings, LLC, the JV owning the campus; Meta is not the issuer. Notes are secured by the issuer's accounts, revenues and equity interests in the JV, with no direct mortgage on land and buildings (per Global Data Center Hub). Reg-level pledge documents not seen. | C30: S4 | D30: third party / news
A31: Closing status | B31: As of the Q2 10-Q, closing was still expected in Q3 2026. Press reports say the deal was due to close within days of 28-Jul-2026; no Meta filing yet confirms closing (Meta Q3 10-Q due late Oct 2026). | C31: S1 | D31: verified (official doc)
A33: Sponsor and parent | C33: Source | D33: Status
A34: Sponsor | B34: BlackRock, via GIP and HPS funds, is the 80% equity owner. Press cites BlackRock's Aligned Data Centers acquisition ($40bn) as context. Equity returns and sponsor liquidity were not researched beyond this. | C34: S5 | D34: third party / news
A35: Template | B35: Same 80/20 structure as Meta's Hyperion/Beignet financing with Blue Owl (see RPLDCI), arranged by Morgan Stanley there and JPMorgan/Morgan Stanley here. | C35: S3 | D35: third party / news
A37: Tenant and lease | C37: Source | D37: Status
A38: Tenant | B38: Meta (a Meta subsidiary on the lease). Meta rated AA- by S&P per Global Data Center Hub. | C38: S4 | D38: third party / news
A39: Term | B39: Four-year initial term with four extension options, up to about 20 years in total (press release as reported; seed agrees). Meta will enter leases for properties to be developed. | C39: S5 | D39: third party / news
A40: Rent commencement | B40: Base rent starts December 2028 whether or not the campus is complete; deferral only for force majeure, landlord funding default or landlord-directed stoppage; abatement for landlord-directed delay capped at $218mm and offset by delayed start-up insurance (Global Data Center Hub reading of offering materials). | C40: S4 | D40: third party / news
A41: Lease type and SLAs | B41: Triple-net: Meta pays property taxes, utilities, insurance, routine maintenance, capital repairs and structural replacement. No uptime or performance SLAs reported. | C41: S4 | D41: third party / news
A42: Rent per MW / escalator | B42: Seed: $1.38mm per MW-year, 2% escalator. Not verified; Meta's 10-Q gives no aggregate lease commitment for El Paso. | C42: S0 | D42: seed, unverified
A44: Project and site | C44: Source | D44: Status
A45: Location and size | B45: About 1,000 acres in northeast El Paso, Texas. Campus is about 1 GW (seed critical IT 960 MW) with total development cost about $14bn (seed facility cost $13.7bn). Meta filed in Jul 2026 to add 12 buildings of nearly 26 million sq ft, completion pushed to Feb 2029 (news). | C45: S3 | D45: third party / news
A46: Phasing and jobs | B46: Five phases reported; groundbreaking Oct 2025 with an initial $1.5bn commitment, raised to over $10bn in Mar 2026 as the target grew to about 1 GW by 2028; over 4,000 construction workers at peak and about 300 permanent jobs. | C46: S3 | D46: third party / news
A47: Local incentives | B47: Dec 2023 city incentive deal with Wurldwide LLC (Meta affiliate): up to 80% city property-tax abatement for 15 years if at least $800mm invested (worth up to about $110mm per El Paso Times). | C47: S7 | D47: third party / news
A48: Cooling | B48: Closed-loop liquid cooling reported; Meta says it will match facility consumption with 100% clean/renewable energy (not detailed). | C48: S3 | D48: company statement
A50: Power and utilities | C50: Source | D50: Status
A51: Utility and bridge plant | B51: El Paso Electric (EPE) plans to supply through McCloud Generation, a 366 MW plant of 813 modular gas generators next to the site, filed with the Public Utility Commission of Texas. It would serve the data centre exclusively for an initial five-year bridge period starting 2027, separate from EPE's transmission system, with all costs recovered from Meta under a commission-approved rate. | C51: S6 | D51: third party / news
A52: Load | B52: Original request 220 MW (Wurldwide LLC); projected over 440 MW by 2027 and potentially 1 GW by 2029 per the amended filing. After the bridge period EPE would seek to connect McCloud to the grid and fold costs into retail rates. | C52: S6 | D52: third party / news
A53: Discrepancy with brief | B53: The request describes 1.0 GW grid with 225 MW on-site generation. Sources found show 366 MW on-site (813 modular units, a $473mm line item online by 2027) and 1 GW total; the 225 MW figure was not found in any source. | C53: S3 | D53: third party / news
A54: Approvals | B54: McCloud requires approval from the PUCT (certificate of convenience and necessity amendment) and the TCEQ. The city of El Paso intervened; opposition groups have pushed for contract termination and cite ozone and water concerns. Outcome of the PUCT docket was not found. | C54: S7 | D54: third party / news
A56: Construction and delivery | C56: Source | D56: Status
A57: Start and status | B57: Groundbreaking Oct 2025; construction under way, about 2,300 on site in Jul 2026 per press release coverage. Meta is the construction manager. | C57: S5 | D57: third party / news
A58: Schedule | B58: Servers expected online 2028, rent from Dec 2028 (seed lease commencement Dec 2028 consistent); expanded buildings to Feb 2029 (news, not reconciled with the 2028 target). | C58: S3 | D58: third party / news
A59: Overrun protection | B59: Meta funds cost overruns above 105% of the fixed construction budget (budget amount not stated), per Global Data Center Hub. | C59: S4 | D59: third party / news
A60: Contractor / contract type | B60: Not found. | C60: S4 | D60: third party / news
A62: Financing and capital structure | C62: Source | D62: Status
A63: Sources and uses (reported) | B63: About $14bn total development cost funded by about $12.5bn of venture-level debt plus equity (BlackRock about $4.9bn cash, Meta about $2.3bn of assets; Meta receives about $1bn). The sums do not reconcile exactly in the source. | C63: S5 | D63: third party / news
A64: Leverage | B64: Seed: 90% debt funded, 9.3x leverage at issuance; seed amortisation start late 2028. Not verified. | C64: S0 | D64: seed, unverified
A65: Reserves and refinancing | B65: Not found: reserve accounts, DSRA, capex reserve and amortisation profile are in the private offering memorandum. | C65: S4 | D65: third party / news
A67: Credit enhancement and support | C67: Source | D67: Status
A68: Residual value guarantee | B68: Meta will provide RVGs with a maximum aggregate exposure of about $13bn (company disclosure). Reported as sized to outstanding principal and triggered if Meta declines to renew at lease expiry. | C68: S1 | D68: verified (official doc)
A69: Overruns | B69: Meta funds cost overruns above 105% of budget; rent does not abate for construction delay except narrow cases. | C69: S4 | D69: third party / news
A70: Accounting | B70: Meta's Q2 10-Q only describes the venture as a subsequent event with leases and RVG; consolidation treatment (expected unconsolidated VIE like Hyperion) is not yet disclosed because closing is pending. | C70: S1 | D70: verified (official doc)
A72: Covenants, waterfall and reserves | C72: Source | D72: Status
A73: Documentation | B73: No covenant, waterfall, DSCR, lock-up or events-of-default detail found. Offering memorandum is private. | C73: S4 | D73: third party / news
A75: Ratings | C75: Source | D75: Status
A76: S&P | B76: Preliminary A+, stable outlook; one notch below Meta's AA-, attributed to the absence of an asset pledge (Global Data Center Hub). S&P report not accessed. | C76: S4 | D76: third party / news
A77: Fitch | B77: Expected AA-(EXP), level with Meta, reasoning that transfer of construction, operating and power-supply risk to Meta makes physical security largely academic (secondary). Fitch release not accessed. | C77: S4 | D77: third party / news
A78: Moody's | B78: No Moody's rating found; seed NR. | C78: S0 | D78: seed, unverified
A79: Triggers | B79: Not found; ratings are in effect linked to Meta's own rating (analyst inference). | C79: S4 | D79: estimate
A81: Use of proceeds | C81: Source | D81: Status
A82: Use | B82: Fund the JV's development of the El Paso campus (about $14bn total development cost). Exact allocation of notes proceeds not found. | C82: S5 | D82: third party / news
A84: Key risks and open issues | C84: Source | D84: Status
A85: Power | B85: Bridge plant (366 MW) still needs PUCT and TCEQ approval for 2027 operation; long-term grid supply for 1 GW depends on EPE expansion; local opposition and intervenors. | C85: S6 | D85: third party / news
A86: Tenant and renewal | B86: Four-year lease blocks; at non-renewal the notes rely on the Meta RVG (about $13bn maximum exposure). | C86: S1 | D86: verified (official doc)
A87: Scope changes | B87: Expanded footprint (12 more buildings, completion Feb 2029) versus the 2028 target. | C87: S3 | D87: third party / news
A88: Weak demand at issue | B88: Press reports weaker-than-expected demand and a long marketing process. | C88: S3 | D88: third party / news
A89: No asset mortgage | B89: Security is equity and revenues, not land and buildings; hence S&P/Fitch split. | C89: S4 | D89: third party / news
A91: Recent developments (since issuance) | C91: Source | D91: Status
A92: Closing | B92: Meta expects closing in Q3 2026; no closing filing found as of 16-Oct-2026. | C92: S1 | D92: verified (official doc)
A93: Fund holdings | B93: Mutual funds already hold the notes (Hartford fund N-PORT at 31-Jul-2026 shows $1.56mm face). | C93: S2 | D93: verified (official doc)
A94: Market | B94: Seed: yield 7.22%, spread 222bp at 15-Sep-2026. | C94: S0 | D94: seed, unverified
A96: Timeline | C96: Source
A97: 2023-12 | B97: El Paso city incentive agreement with Wurldwide LLC (Meta affiliate) for 1,000-acre site. | C97: S7
A98: 2025-10 | B98: Groundbreaking in El Paso with initial $1.5bn commitment. | C98: S3
A99: 2026-01 | B99: Reports that El Paso Electric seeks PUC approval for 366 MW gas plant; local opposition. | C99: S7
A100: 2026-03 | B100: Meta raises El Paso commitment to over $10bn as target grows to about 1 GW by 2028. | C100: S3
A101: 2026-04 | B101: PUCT filing amended: McCloud 366 MW bridge plant; load up to 1 GW by 2029 (Argus). | C101: S6
A102: 2026-07-22 | B102: JPMorgan and Morgan Stanley begin investor calls for Sopaipilla Investor notes. | C102: S3
A103: 2026-07-23 | B103: Notes launched at $12.3bn; S&P preliminary A+, Fitch expected AA-. | C103: S3
A104: 2026-07-28 | B104: Meta and BlackRock announce the 80/20 El Paso JV, about $14bn project. | C104: S5
A105: 2026-07-30 | B105: Meta Q2 10-Q discloses exclusivity agreement, $13bn maximum RVG and expected Q3 closing. | C105: S1
A106: 2026-07-31 | B106: Notes held by funds (N-PORT) with ISIN US83577VAA89. | C106: S2
A108: Sources (official documents first)
A109: S0 | News | 2026-09-16 | B109: Seed data: Barclays IG/HY Data Center Credit Digest 16-Sep-2026 and Bloomberg (Seed file (secondary)). Used for: Unverified seed values only
A110: S1 | SEC filing | 2026-07-30 | B110: Meta Platforms Form 10-Q for quarter ended 30-Jun-2026 (Note 13 Subsequent Event; held-for-sale assets) (SEC EDGAR / Meta Platforms). Used for: 20% interest, $2.3bn contribution, $1bn distribution, $13bn RVG, expected Q3 closing | C110: link
A111: S2 | SEC filing | 2026-09-29 | B111: Form N-PORT holdings report of Hartford Mutual Funds II (period 31-Jul-2026) (SEC EDGAR). Used for: ISIN, CUSIP, coupon, maturity | C111: link
A112: S3 | News | 2026-07-24 | B112: BlackRock Launches $12.3 Billion Bond For Meta's El Paso Campus (Global Data Center Hub). Used for: Launch, bookrunners, site, power, construction timeline (newsletter; secondary) | C112: link
A113: S4 | News | 2026-08 | B113: Bondholders are not underwriting (Global Data Center Hub). Used for: Ratings, collateral, rent start, overrun protection, RVG (newsletter; secondary) | C113: link
