Workbook

Sheet README
A1: Anthropic ARR, FUNDA ANT dashboard and compute-spend reconciliation — transcription
A3: SOURCE: FundaAI — FUNDA ANT dashboard, 2026-10-26 (all three exhibits; the ARR tab legend reads "v7 (2026-10-26)"). Attribution confirmed by Felipe Monteiro on 2026-10-27; screenshots pasted in Claude Code the same day. Cite as "FundaAI, FUNDA ANT dashboard, 2026-10-26".
A5: Tabs
A6: ARR Monthly — screenshot 1: monthly T28 / exit run-rate ARR Dec-25 to Dec-26 plus the quarterly summary ($Bn).
A7: ANT Dashboard — screenshot 2: quarterly 3Q25-2Q27E and annual 2025-2030E P&L, drivers, cost structure, compute commitments, Broadcom TPU leases, AMD Helios and cash flow (US$ M).
A8: Compute Reconciliation — screenshot 3: P&L-basis to commitment-basis compute spend 2026E-2030E vs the ~$750B press figure, and S-1 contract values vs amounts expensed through 2030E (US$ M).
A9: Checks — live formulas tying each subtotal to its components across and within tabs.
A11: Conventions
A12: Every number is typed exactly as displayed in the screenshots (hard-coded, display-rounded). The source model's formulas are not visible, so none are reproduced; the only formulas are in Checks.
A13: A "-" in the source is stored as 0 (renders as a dash); an empty cell in the source is left empty; "–" in the ARR tab is kept as text.
A14: Percentages are stored as fractions; multiples (1.50x) as numbers. Blue font in ARR Monthly mirrors the source's blue (input) cells.
A15: Cell comments in the source (red corner markers; text not visible): ARR Monthly T28 ARR for Feb-26, Apr-26, May-26, Jun-26, Aug-26; Distillation ARR for Aug-26 and Sep-26; Reported Revenue for Q1-26, Q2-26, Q3-26.
... A24: Built 2026-10-27 by Claude Code from the pasted images; builder script kept in the session scratchpad.

Sheet ARR Monthly
A1: Anthropic ARR
A2: Units: $Bn. T28 ARR is on a reported basis (incl. distillation). Blue = inputs; black = formulas; yellow = levers. Oct-26 onward = forecast. v7 (2026-10-26): Q1/Q2 ti... [legend truncated in the screenshot]
A4: Month | B4: Days | C4: T28 ARR ($Bn) | D4: Distillation ARR | E4: Ex-Distillation ARR | F4: Net Add ARR | G4: Ex-Distillation Net Add ARR | H4: Exit Run-Rate ARR ($Bn) | I4: MoM Growth (T28) | J4: MoM Growth (Exit RR) | K4: Monthly Revenue ($Bn)
A5: 45992 | B5: 31 | C5: 8.9 | D5: 0.7 | E5: 8.2 | H5: 10.3 | I5: – | J5: – | K5: –
A6: 46023 | B6: 31 | C6: 13.8 | D6: 1.2 | E6: 12.6 | F6: 4.9 | G6: 4.4 | H6: 15.9 | I6: 0.551 | J6: 0.551 | K6: 1.17
A7: 46054 | B7: 28 | C7: 19 | D7: 1.6 | E7: 17.5 | F7: 5.2 | G7: 4.9 | H7: 21.4 | I7: 0.38 | J7: 0.345 | K7: 1.46
A8: 46082 | B8: 31 | C8: 24.7 | D8: 2.1 | E8: 22.6 | F8: 5.7 | G8: 5.1 | H8: 26.9 | I8: 0.297 | J8: 0.257 | K8: 2.1
A9: 46113 | B9: 30 | C9: 39 | D9: 2.8 | E9: 36.2 | F9: 14.3 | G9: 13.6 | H9: 45.4 | I9: 0.579 | J9: 0.688 | K9: 3.21
A10: 46143 | B10: 31 | C10: 45 | D10: 4 | E10: 41 | F10: 6 | G10: 4.8 | H10: 47.2 | I10: 0.154 | J10: 0.039 | K10: 3.82
A11: 46174 | B11: 30 | C11: 55.1 | D11: 4.7 | E11: 50.4 | F11: 10.1 | G11: 9.4 | H11: 59 | I11: 0.224 | J11: 0.251 | K11: 4.53
A12: 46204 | B12: 31 | C12: 65 | D12: 5.2 | E12: 59.8 | F12: 9.9 | G12: 9.4 | H12: 68.7 | I12: 0.18 | J12: 0.163 | K12: 5.52
A13: 46235 | B13: 31 | C13: 66.2 | D13: 2 | E13: 64.2 | F13: 1.2 | G13: 4.4 | H13: 66.6 | I13: 0.019 | J13: -0.03 | K13: 5.62
A14: 46266 | B14: 30 | C14: 68.8 | D14: 0.2 | E14: 68.6 | F14: 2.6 | G14: 4.4 | H14: 69.7 | I14: 0.039 | J14: 0.046 | K14: 5.65
A15: 46296 | B15: 31 | C15: 73.3 | D15: 0.2 | E15: 73.1 | F15: 4.5 | G15: 4.5 | H15: 74.9 | I15: 0.065 | J15: 0.074 | K15: 6.23
A16: 46327 | B16: 30 | C16: 78.1 | D16: 0.2 | E16: 77.9 | F16: 4.8 | G16: 4.8 | H16: 79.8 | I16: 0.065 | J16: 0.066 | K16: 6.42
A17: 46357 | B17: 31 | C17: 83.2 | D17: 0.2 | E17: 83 | F17: 5.1 | G17: 5.1 | H17: 85 | I17: 0.065 | J17: 0.065 | K17: 7.07
A19: Quarterly Summary
A20: Period | B20: Revenue ($Bn) | C20: Period-End T28 ARR ($Bn) | D20: Period-End Exit RR ARR ($Bn) | E20: QoQ Revenue Growth | F20: Reported Revenue ($Bn) | G20: Diff vs Reported
A21: Q1-26 | B21: 4.73 | C21: 24.7 | D21: 26.9 | E21: – | F21: 4.73 | G21: 0
A22: Q2-26 | B22: 11.56 | C22: 55.1 | D22: 59 | E22: 1.442 | F22: 11.56 | G22: 0
A23: Q3-26 | B23: 16.8 | C23: 68.8 | D23: 69.7 | E23: 0.454 | F23: 16.8 | G23: 0
A24: Q4-26E | B24: 19.71 | C24: 83.2 | D24: 85 | E24: 0.173
A25: FY26E | B25: 52.8

Sheet ANT Dashboard
A1: Period end date | B1: 45930 | C1: 46022 | D1: 46112 | E1: 46203 | F1: 46295 | G1: 46387 | H1: 46477 | I1: 46568 | K1: 46022 | L1: 46387 | M1: 46752 | N1: 47118 | O1: 47483 | P1: 47848
A2: Days in period | B2: 92 | C2: 92 | D2: 90 | E2: 91 | F2: 92 | G2: 92 | H2: 90 | I2: 91 | K2: 365 | L2: 365 | M2: 365 | N2: 366 | O2: 365 | P2: 365
A3: FUNDA ANT Dashboard | B3: 3Q25 | C3: 4Q25 | D3: 1Q26 | E3: 2Q26 | F3: 3Q26E | G3: 4Q26E | H3: 1Q27E | I3: 2Q27E | K3: 2025 | L3: 2026E | M3: 2027E | N3: 2028E | O3: 2029E | P3: 2030E
A5: P&L summary (US$ M)
A6: Run-rate revenue (T28 ARR), end of period | C6: 8900 | D6: 24700 | E6: 55086 | F6: 68800 | G6: 83201 | H6: 98494 | I6: 114954 | K6: 8900 | L6: 83201 | M6: 150007 | N6: 240011 | O6: 360016 | P6: 504023
A7: % growth q/q (annual: y/y) | D7: 1.775 | E7: 1.23 | F7: 0.249 | G7: 0.209 | H7: 0.184 | I7: 0.167 | K7: 0 | L7: 8.348 | M7: 0.803 | N7: 0.6 | O7: 0.5 | P7: 0.4
A8: Revenue | B8: 1382 | C8: 2040 | D8: 4731 | E8: 11555 | F8: 16800 | G8: 19710 | H8: 22983 | I8: 27245 | K8: 4585 | L8: 52796 | M8: 118326 | N8: 197890 | O8: 304446 | P8: 438402
A9: % growth y/y | D9: 11.582 | E9: 13.682 | F9: 11.156 | G9: 8.662 | H9: 3.858 | I9: 1.358 | K9: 10.878 | L9: 10.515 | M9: 1.241 | N9: 0.672 | O9: 0.538 | P9: 0.44
A10: Consumption-based revenue | D10: 3795 | E10: 9269 | F10: 13440 | G10: 15768 | H10: 18386 | I10: 21796 | K10: 3796 | L10: 42272 | M10: 94661 | N10: 158312 | O10: 243557 | P10: 350722
A11: Subscription-based revenue | D11: 936 | E11: 2286 | F11: 3360 | G11: 3942 | H11: 4597 | I11: 5449 | K11: 789 | L11: 10524 | M11: 23665 | N11: 39578 | O11: 60889 | P11: 87680
A12: Compute and infrastructure | B12: 2047 | C12: 2945 | D12: 3387 | E12: 5558 | F12: 9497 | G12: 15365 | H12: 21180 | I12: 23168 | K12: 7326 | L12: 33807 | M12: 98619 | N12: 152285 | O12: 181989 | P12: 212011
A13: % of revenue | B13: 1.481 | C13: 1.444 | D13: 0.716 | E13: 0.481 | F13: 0.565 | G13: 0.78 | H13: 0.922 | I13: 0.85 | K13: 1.598 | L13: 0.64 | M13: 0.833 | N13: 0.77 | O13: 0.598 | P13: 0.484
A14: Adjusted operating income (non-GAAP) | B14: -1284 | C14: -1721 | D14: -617 | E14: 2235 | F14: 2023 | G14: -1820 | H14: -5084 | I14: -4010 | K14: -4854 | L14: 1821 | M14: -15263 | N14: -7126 | O14: 43073 | P14: 113670
A15: Adjusted operating margin | B15: -0.929 | C15: -0.844 | D15: -0.13 | E15: 0.193 | F15: 0.12 | G15: -0.092 | H15: -0.221 | I15: -0.147 | K15: -1.059 | L15: 0.034 | M15: -0.129 | N15: -0.036 | O15: 0.141 | P15: 0.259
A16: Operating income (loss), GAAP | B16: -3089 | C16: -2836 | D16: -1667 | E16: 974 | F16: 427 | G16: -3594 | H16: -6922 | I16: -6190 | K16: -8060 | L16: -3860 | M16: -24729 | N16: -20978 | O16: 24806 | P16: 91749
A17: Operating margin | B17: -2.235 | C17: -1.39 | D17: -0.352 | E17: 0.084 | F17: 0.025 | G17: -0.182 | H17: -0.301 | I17: -0.227 | K17: -1.758 | L17: -0.073 | M17: -0.209 | N17: -0.106 | O17: 0.081 | P17: 0.209
A18: Interest expense on finance leases | B18: 0 | C18: 0 | D18: 0 | E18: 0 | F18: 0 | G18: -52 | H18: -151 | I18: -316 | K18: 0 | L18: -52 | M18: -2128 | N18: -6386 | O18: -8924 | P18: -6641
A19: Net income (loss), GAAP | B19: -12138 | C19: -16858 | D19: -14439 | E19: -66309 | F19: 1667 | G19: -2303 | H19: -5178 | I19: -4630 | K19: -41965 | L19: -81384 | M19: -19455 | N19: -20568 | O19: 20791 | P19: 87888
A20: Adjusted net income (non-GAAP) | B20: -1168 | C20: -1539 | D20: -310 | E20: 2981 | F20: 3263 | G20: -529 | H20: -3339 | I20: -2451 | K20: -4448 | L20: 5405 | M20: -9989 | N20: -6715 | O20: 39058 | P20: 109808
A22: Revenue drivers
A23: Run-rate revenue (T28 ARR), end of period | C23: 8900 | D23: 24700 | E23: 55086 | F23: 68800 | G23: 83201 | H23: 98494 | I23: 114954 | K23: 8900 | L23: 83201 | M23: 150007 | N23: 240011 | O23: 360016 | P23: 504023
A24: % growth q/q (annual: y/y) | D24: 1.775 | E24: 1.23 | F24: 0.249 | G24: 0.209 | H24: 0.184 | I24: 0.167 | K24: 0 | L24: 8.348 | M24: 0.803 | N24: 0.6 | O24: 0.5 | P24: 0.4
A25: Exit run-rate (last 7 days), end of period | C25: 0 | D25: 27183 | E25: 59407 | F25: 69736 | G25: 85044 | H25: 100425 | I25: 117080 | K25: 0 | L25: 85044 | M25: 152184 | N25: 0 | O25: 0 | P25: 0
A26: Distillation ARR in T28, end of period | C26: 695 | D26: 2085 | E26: 4690 | F26: 200 | G26: 200 | H26: 200 | I26: 200 | K26: 695 | L26: 200 | M26: 200 | N26: 0 | O26: 0 | P26: 0
A27: T28 ARR excluding distillation | C27: 8205 | D27: 22615 | E27: 50395 | F27: 68600 | G27: 83001 | H27: 98294 | I27: 114754 | K27: 8205 | L27: 83001 | M27: 149807 | N27: 0 | O27: 0 | P27: 0
A28: Revenue | B28: 1382 | C28: 2040 | D28: 4731 | E28: 11555 | F28: 16800 | G28: 19710 | H28: 22983 | I28: 27245 | K28: 4585 | L28: 52796 | M28: 118326 | N28: 197890 | O28: 304446 | P28: 438402
A29: Revenue as % of average run-rate revenue | B29: 0 | C29: 0 | D29: 0 | E29: 0 | F29: 0 | G29: 0 | H29: 0 | I29: 0 | K29: 0 | L29: 0 | M29: 1.015 | N29: 1.015 | O29: 1.015 | P29: 1.015
A30: Subscription share of revenue | D30: 0.198 | E30: 0.198 | F30: 0.2 | G30: 0.2 | H30: 0.2 | I30: 0.2 | K30: 0.172 | L30: 0.199 | M30: 0.2 | N30: 0.2 | O30: 0.2 | P30: 0.2
A31: Share of revenue through CSP marketplaces (memo) | B31: 0 | C31: 0 | D31: 0 | E31: 0.48 | F31: 0.48 | G31: 0.48 | H31: 0.48 | I31: 0.48 | K31: 0.47 | L31: 0 | M31: 0 | N31: 0.48 | O31: 0.48 | P31: 0.48
A33: Cost structure and assumptions (US$ M)
A34: Compute and infrastructure | B34: 2047 | C34: 2945 | D34: 3387 | E34: 5558 | F34: 9497 | G34: 15365 | H34: 21180 | I34: 23168 | K34: 7326 | L34: 33807 | M34: 98619 | N34: 152285 | O34: 181989 | P34: 212011
A35: % of revenue | B35: 1.481 | C35: 1.444 | D35: 0.716 | E35: 0.481 | F35: 0.565 | G35: 0.78 | H35: 0.922 | I35: 0.85 | K35: 1.598 | L35: 0.64 | M35: 0.833 | N35: 0.77 | O35: 0.598 | P35: 0.484
A36: Customer-serving compute (cost of revenue) | B36: 782 | C36: 972 | D36: 1119 | E36: 1261 | F36: 2016 | G36: 2464 | H36: 2988 | I36: 3542 | K36: 2773 | L36: 6860 | M36: 15723 | N36: 27705 | O36: 44145 | P36: 65760
A37: Serving cost, % of revenue (assumption) | B37: 0.566 | C37: 0.476 | D37: 0.236 | E37: 0.109 | F37: 0.12 | G37: 0.125 | H37: 0.13 | I37: 0.13 | K37: 0.605 | L37: 0.13 | M37: 0.133 | N37: 0.14 | O37: 0.145 | P37: 0.15
A38: Training, research and internal use (remaining capacity) | B38: 1265 | C38: 1973 | D38: 2268 | E38: 4297 | F38: 7481 | G38: 12901 | H38: 18192 | I38: 19626 | K38: 4553 | L38: 26947 | M38: 82896 | N38: 124581 | O38: 137844 | P38: 146251
A39: % of revenue | B39: 0.915 | C39: 0.967 | D39: 0.479 | E39: 0.372 | F39: 0.445 | G39: 0.655 | H39: 0.792 | I39: 0.72 | K39: 0.993 | L39: 0.51 | M39: 0.701 | N39: 0.63 | O39: 0.453 | P39: 0.334
A40: Minimum training and research need, % of revenue (assumption) | F40: 0.442 | G40: 0.465 | H40: 0.46 | I40: 0.46
A41: Compute beyond disclosed contracts | B41: 0 | C41: 0 | D41: 0 | E41: 0 | F41: 950 | G41: 0 | H41: 0 | I41: 0 | K41: 0 | L41: 950 | M41: 0 | N41: 0 | O41: 0 | P41: 30023
A42: New long-term contracts | B42: 0 | C42: 0 | D42: 0 | E42: 0 | F42: 717 | G42: 0 | H42: 0 | I42: 0 | K42: 0 | L42: 717 | M42: 0 | N42: 0 | O42: 0 | P42: 30023
A43: Short-term compute (incl. premium) | B43: 0 | C43: 0 | D43: 0 | E43: 0 | F43: 233 | G43: 0 | H43: 0 | I43: 0 | K43: 0 | L43: 233 | M43: 0 | N43: 0 | O43: 0 | P43: 0
A44: Share covered by new long-term contracts | F44: 0.8 | G44: 0.8 | H44: 0.8 | I44: 0.8
A45: Short-term premium | F45: 0.3 | G45: 0.3 | H45: 0.3 | I45: 0.3
A46: Personnel | B46: 489 | C46: 812 | D46: 1295 | E46: 1857 | F46: 2340 | G46: 2618 | H46: 2750 | I46: 3183 | K46: 1839 | L46: 8109 | M46: 13671 | N46: 19089 | O46: 24584 | P46: 29425
A47: % of revenue | B47: 0.354 | C47: 0.398 | D47: 0.274 | E47: 0.161 | F47: 0.139 | G47: 0.133 | H47: 0.12 | I47: 0.117 | K47: 0.401 | L47: 0.154 | M47: 0.116 | N47: 0.096 | O47: 0.081 | P47: 0.067
A48: Personnel excluding SBC | B48: 184 | C48: 238 | D48: 371 | E48: 596 | F48: 744 | G48: 844 | H48: 911 | I48: 1004 | K48: 674 | L48: 2554 | M48: 4205 | N48: 5237 | O48: 6317 | P48: 7505
A49: Average employees | B49: 1795 | C49: 2330 | D49: 3150 | E49: 4050 | F49: 4900 | G49: 5450 | H49: 5900 | I49: 6300 | K49: 1685 | L49: 4388 | M49: 6500 | N49: 7475 | O49: 8372 | P49: 9209
A50: Cash cost per employee ($K, annualized) | B50: 407 | C50: 405 | D50: 478 | E50: 590 | F50: 602 | G50: 614 | H50: 626 | I50: 639 | K50: 400 | L50: 582 | M50: 647 | N50: 699 | O50: 755 | P50: 815
A51: % growth (q/q; annual: y/y) | B51: 0.069 | C51: -0.004 | D51: 0.179 | E51: 0.236 | F51: 0.02 | G51: 0.02 | H51: 0.02 | I51: 0.02 | K51: 0 | L51: 0.455 | M51: 0.111 | N51: 0.08 | O51: 0.08 | P51: 0.08
A52: Stock-based compensation | B52: 305 | C52: 574 | D52: 924 | E52: 1261 | F52: 1596 | G52: 1774 | H52: 1839 | I52: 2180 | K52: 1165 | L52: 5555 | M52: 9466 | N52: 13852 | O52: 18267 | P52: 21920
A53: % of revenue | B53: 0.221 | C53: 0.281 | D53: 0.195 | E53: 0.109 | F53: 0.095 | G53: 0.09 | H53: 0.08 | I53: 0.08 | K53: 0.254 | L53: 0.105 | M53: 0.08 | N53: 0.07 | O53: 0.06 | P53: 0.05
A54: Sales, marketing, and partnerships | B54: 202 | C54: 246 | D54: 1033 | E54: 2135 | F54: 3108 | G54: 3646 | H54: 4137 | I54: 4904 | K54: 568 | L54: 9922 | M54: 21299 | N54: 33641 | O54: 51756 | P54: 74528
A55: % of revenue (includes CSP fees) | B55: 0.146 | C55: 0.121 | D55: 0.218 | E55: 0.185 | F55: 0.185 | G55: 0.185 | H55: 0.18 | I55: 0.18 | K55: 0.124 | L55: 0.188 | M55: 0.18 | N55: 0.17 | O55: 0.17 | P55: 0.17
A56: Other operating and administrative | B56: 233 | C56: 873 | D56: 683 | E56: 1031 | F56: 1428 | G56: 1675 | H56: 1839 | I56: 2180 | K56: 1412 | L56: 4817 | M56: 9466 | N56: 13852 | O56: 21311 | P56: 30688
A57: Excluding one-off charges, % of revenue | B57: 0.169 | C57: 0.163 | D57: 0.118 | E57: 0.089 | F57: 0.085 | G57: 0.085 | H57: 0.08 | I57: 0.08 | K57: 0.19 | L57: 0.089 | M57: 0.08 | N57: 0.07 | O57: 0.07 | P57: 0.07
... A62: Adjusted operating margin | B62: -0.929 | C62: -0.844 | D62: -0.13 | E62: 0.193 | F62: 0.12 | G62: -0.092 | H62: -0.221 | I62: -0.147 | K62: -1.059 | L62: 0.034 | M62: -0.129 | N62: -0.036 | O62: 0.141 | P62: 0.259
A64: Compute commitments: contracted capacity cost (US$ M)
A65: Contracted compute capacity cost | B65: 0 | C65: 0 | D65: 0 | E65: 0 | F65: 8547 | G65: 15365 | H65: 21180 | I65: 23168 | K65: 0 | L65: 23912 | M65: 98619 | N65: 152285 | O65: 181989 | P65: 181989
A66: Cloud service agreements signed in 2026 (expensed as delivered) | B66: 0 | C66: 0 | D66: 0 | E66: 5741 | F66: 6654 | G66: 13132 | H66: 17415 | I66: 18309 | K66: 0 | L66: 25527 | M66: 75028 | N66: 101018 | O66: 114768 | P66: 87243
A67: Google | B67: 0 | C67: 0 | D67: 0 | E67: 3904 | F67: 3904 | G67: 3904 | H67: 3904 | I67: 3904 | K67: 0 | L67: 11712 | M67: 15616 | N67: 15614 | O67: 15614 | P67: 15614
A68: Amazon | B68: 0 | C68: 0 | D68: 0 | E68: 1837 | F68: 2750 | G68: 2750 | H68: 2750 | I68: 2750 | K68: 0 | L68: 7337 | M68: 11000 | N68: 11000 | O68: 11000 | P68: 11000
A69: Microsoft (2026 increase) | B69: 0 | C69: 0 | D69: 0 | E69: 0 | F69: 0 | G69: 378 | H69: 566 | I69: 566 | K69: 0 | L69: 378 | M69: 2264 | N69: 2263 | O69: 2263 | P69: 2263
A70: SpaceXAI | B70: 0 | C70: 0 | D70: 0 | E70: 0 | F70: 0 | G70: 6100 | H70: 9300 | I70: 9300 | K70: 0 | L70: 6100 | M70: 37200 | N70: 37200 | O70: 37200 | P70: 2800
A71: Nscale | B71: 0 | C71: 0 | D71: 0 | E71: 0 | F71: 0 | G71: 0 | H71: 465 | I71: 929 | K71: 0 | L71: 0 | M71: 4646 | N71: 7433 | O71: 7433 | P71: 7433
A72: Lambda | B72: 0 | C72: 0 | D72: 0 | E72: 0 | F72: 0 | G72: 0 | H72: 430 | I72: 860 | K72: 0 | L72: 0 | M72: 4302 | N72: 6883 | O72: 6883 | P72: 6883
A73: Google / TPU providers 2028-31 | B73: 0 | C73: 0 | D73: 0 | E73: 0 | F73: 0 | G73: 0 | H73: 0 | I73: 0 | K73: 0 | L73: 0 | M73: 0 | N73: 20625 | O73: 34375 | P73: 41250
A74: Commitments existing at Dec 31, 2025 (S-1 Note 13) | B74: 0 | C74: 0 | D74: 0 | E74: 0 | F74: 1779 | G74: 1779 | H74: 2744 | I74: 2774 | K74: 0 | L74: 3559 | M74: 11128 | N74: 10832 | O74: 8304 | P74: 5428
A75: Broadcom TPU leases: right-of-use amortization | B75: 0 | C75: 0 | D75: 0 | E75: 0 | F75: 76 | G75: 302 | H75: 688 | I75: 1436 | K75: 0 | L75: 378 | M75: 8697 | N75: 26029 | O75: 32160 | P75: 32160
A76: Data center, colocation and power for Broadcom capacity | B76: 0 | C76: 0 | D76: 0 | E76: 0 | F76: 38 | G76: 151 | H76: 333 | I76: 598 | K76: 0 | L76: 189 | M76: 3162 | N76: 7399 | O76: 8757 | P76: 8757
... A82: % of revenue | B82: 1.481 | C82: 1.444 | D82: 0.716 | E82: 0.481 | F82: 0.565 | G82: 0.78 | H82: 0.922 | I82: 0.85 | K82: 1.598 | L82: 0.64 | M82: 0.833 | N82: 0.77 | O82: 0.598 | P82: 0.484
A84: Broadcom TPU leases, data centers and AMD hardware
A86: 1. Commencement and amortization
A87: Google TPU systems sold to third parties (thousand) | B87: 0 | C87: 0 | D87: 0 | E87: 100 | F87: 200 | G87: 300 | H87: 400 | I87: 450 | K87: 0 | L87: 0 | M87: 0 | N87: 0 | O87: 0 | P87: 0
A88: Net ASP per TPU (US$ thousand) | B88: 0 | C88: 0 | D88: 0 | E88: 20 | F88: 20 | G88: 22 | H88: 33 | I88: 34
A89: Google TPU sales value (US$ M) | B89: 0 | C89: 0 | D89: 0 | E89: 2000 | F89: 4000 | G89: 6600 | H89: 13200 | I89: 15300 | K89: 0 | L89: 12600 | M89: 80250 | N89: 0 | O89: 0 | P89: 0
A90: Share leased to Anthropic via Broadcom | F90: 1 | G90: 1 | H90: 1 | I90: 1
A91: Leased system value / TPU sale value | F91: 1.5 | G91: 1.5 | H91: 1.5 | I91: 1.5
A92: New right-of-use assets (ready for service, next quarter) | B92: 0 | C92: 0 | D92: 0 | E92: 0 | F92: 3000 | G92: 6000 | H92: 9900 | I92: 19800 | K92: 0 | L92: 9000 | M92: 89775 | N92: 62025 | O92: 0 | P92: 0
A93: Cumulative right-of-use additions | B93: 0 | C93: 0 | D93: 0 | E93: 0 | F93: 3000 | G93: 9000 | H93: 18900 | I93: 38700 | K93: 0 | L93: 9000 | M93: 98775 | N93: 160800 | O93: 160800 | P93: 160800
A94: Amortization rate (annual) | F94: 0.2 | G94: 0.2 | H94: 0.2 | I94: 0.2
A95: Right-of-use amortization (in compute) | B95: 0 | C95: 0 | D95: 0 | E95: 0 | F95: 76 | G95: 302 | H95: 688 | I95: 1436 | K95: 0 | L95: 378 | M95: 8697 | N95: 26029 | O95: 32160 | P95: 32160
A97: 2. Interest, liability and principal
A98: Lease interest rate (S-1: 7.1%) | F98: 0.071 | G98: 0.071 | H98: 0.071 | I98: 0.071
A99: Interest expense (below operating income) | B99: 0 | C99: 0 | D99: 0 | E99: 0 | F99: 0 | G99: 52 | H99: 151 | I99: 316 | K99: 0 | L99: 52 | M99: 2128 | N99: 6386 | O99: 8924 | P99: 6641
A100: Principal payments (financing cash flow) | B100: 0 | C100: 0 | D100: 0 | E100: 0 | F100: 76 | G100: 302 | H100: 688 | I100: 1436 | K100: 0 | L100: 378 | M100: 8697 | N100: 26029 | O100: 32160 | P100: 32160
A101: Finance lease liability, end of period | B101: 0 | C101: 0 | D101: 0 | E101: 0 | F101: 2924 | G101: 8622 | H101: 17834 | I101: 36198 | K101: 0 | L101: 8622 | M101: 89700 | N101: 125696 | O101: 93536 | P101: 61376
A103: 3. Data center, colocation and power
A104: TPUs ready for service (thousand) | B104: 0 | C104: 0 | D104: 0 | E104: 0 | F104: 100 | G104: 200 | H104: 300 | I104: 400 | K104: 0 | L104: 300 | M104: 1700 | N104: 919 | O104: 0 | P104: 0
A105: TPUs in service, end of period (thousand) | B105: 0 | C105: 0 | D105: 0 | E105: 0 | F105: 100 | G105: 300 | H105: 600 | I105: 1000 | K105: 0 | L105: 300 | M105: 2000 | N105: 2919 | O105: 2919 | P105: 2919
A106: IT power per TPU (kW) | F106: 1.2 | G106: 1.2 | H106: 1.2 | I106: 1.2
A107: IT power in service (MW) | B107: 0 | C107: 0 | D107: 0 | E107: 0 | F107: 120 | G107: 360 | H107: 720 | I107: 1200 | K107: 0 | L107: 360 | M107: 2400 | N107: 3503 | O107: 3503 | P107: 3503
A108: Cost per MW per year (US$ M) | F108: 2.5 | G108: 2.5 | H108: 2.5 | I108: 2.5
A109: Data center, colocation and power cost (in compute) | B109: 0 | C109: 0 | D109: 0 | E109: 0 | F109: 38 | G109: 151 | H109: 333 | I109: 598 | K109: 0 | L109: 189 | M109: 3162 | N109: 7399 | O109: 8757 | P109: 8757
A111: AMD Helios hardware (capex and depreciation)
A112: AMD Helios purchases (capex) | B112: 0 | C112: 0 | D112: 0 | E112: 0 | F112: 0 | G112: 0 | H112: 0 | I112: 2000 | K112: 0 | L112: 0 | M112: 10000 | N112: 10000 | O112: 0 | P112: 0
A113: Depreciation rate (annual) | F113: 0.2 | G113: 0.2 | H113: 0.2 | I113: 0.2
A114: AMD depreciation (in compute) | B114: 0 | C114: 0 | D114: 0 | E114: 0 | F114: 0 | G114: 0 | H114: 0 | I114: 50 | K114: 0 | L114: 0 | M114: 604 | N114: 3008 | O114: 4000 | P114: 4000
A116: Cash flow and balance sheet (US$ M)
A117: Net cash provided by (used in) operating activities | F117: 2173 | G117: -167 | H117: -2774 | I117: -888 | K117: -2637 | L117: 5936 | M117: -486 | N117: 22602 | O117: 76342 | P117: 148442
A118: Purchases of property and equipment | F118: -504 | G118: -591 | H118: -689 | I118: -817 | K118: -131 | L118: -1577 | M118: -3550 | N118: -5937 | O118: -9133 | P118: -13152
A119: Purchases of compute hardware (AMD) | F119: 0 | G119: 0 | H119: 0 | I119: -2000 | K119: 0 | L119: 0 | M119: -10000 | N119: -10000 | O119: 0 | P119: 0
...

Sheet Compute Reconciliation
A1: Compute spend reconciliation 2026E-2030E: P&L basis -> spend basis, vs press report (~$750B through 2030)
A2: US$ M | B2: 2026E | C2: 2027E | D2: 2028E | E2: 2029E | F2: 2030E | G2: 2026-30E
A3: Compute and infrastructure (P&L basis) | B3: 33807 | C3: 98619 | D3: 152285 | E3: 181989 | F3: 212011 | G3: 678712
A4: Plus: Broadcom right-of-use commenced less amortization | B4: 8622 | C4: 81078 | D4: 35996 | E4: -32160 | F4: -32160 | G4: 61376
A5: Plus: AMD Helios capex less depreciation | B5: 0 | C5: 9396 | D5: 6992 | E5: -4000 | F5: -4000 | G5: 8387
A6: Compute spend, commitment basis (excl. lease interest) | B6: 42429 | C6: 189093 | D6: 195274 | E6: 145829 | F6: 175851 | G6: 748475
A7: Memo: Broadcom lease interest (below operating income) | B7: 52 | C7: 2128 | D7: 6386 | E7: 8924 | F7: 6641 | G7: 24132
A8: Compute spend including lease interest | B8: 42481 | C8: 191221 | D8: 201660 | E8: 154753 | F8: 182492 | G8: 772607
A9: Of which assumptions beyond S-1 contracts (renewals, ahead of demand, beyond disclosed contracts) | B9: 950 | C9: 0 | D9: 4000 | E9: 14000 | F9: 74424 | G9: 93374
A10: Press report: company compute plan through 2030 | G10: 750000
A11: Difference: model spend (excl. interest) less press report | G11: -1525
A13: Compute commitments: S-1 contract values vs payments expensed in the model through 2030E
A14: US$ M | B14: S-1 value | C14: Expensed to 2030E | D14: Tail after 2030E | E14: % within 2030E
A15: Google | B15: 114500 | C15: 74170 | D15: 40330 | E15: 0.648
A16: Amazon | B16: 110000 | C16: 51337 | D16: 58663 | E16: 0.467
A17: Microsoft (2026 increase) | B17: 14900 | C17: 9431 | D17: 5469 | E17: 0.633
A18: SpaceXAI | B18: 120500 | C18: 120500 | D18: 0 | E18: 1
A19: Nscale | B19: 44600 | C19: 26945 | D19: 17655 | E19: 0.604
A20: Lambda | B20: 41300 | C20: 24951 | D20: 16349 | E20: 0.604
A21: Google / TPU providers 2028-31 (midpoint of $125-150B) | B21: 137500 | C21: 96250 | D21: 41250 | E21: 0.7
A22: Cloud service agreements signed in 2026 | B22: 583300 | C22: 403584 | D22: 179716 | E22: 0.692
A23: Commitments at Dec 31, 2025 (Note 13; from Jan-26) | B23: 54559 | C23: 42751 | D23: 11808 | E23: 0.784
A24: Broadcom TPU leases (rent excl. interest; amortization) | B24: 161200 | C24: 99824 | D24: 61376 | E24: 0.619
A25: AMD Helios hardware (lower bound; depreciation) | B25: 20000 | C25: 11613 | D25: 8387 | E25: 0.581
A26: Total S-1 compute commitments | B26: 819059 | C26: 557771 | D26: 261288 | E26: 0.681

Sheet Checks
A1: Transcription tie-outs (live formulas)
A2: Each cell = components minus total, as transcribed. Status OK when every |diff| <= tolerance (display rounding). A GAP that is also explained in column R sits in the source exhibit itself, not the transcription.
A5: ANT Dashboard (US$ M) | B5: 3Q25 | C5: 4Q25 | D5: 1Q26 | E5: 2Q26 | F5: 3Q26E | G5: 4Q26E | H5: 1Q27E | I5: 2Q27E | J5: 2025 | K5: 2026E | L5: 2027E | M5: 2028E | N5: 2029E | O5: 2030E | Q5: Status | R5: Note (source-level gap)
A6: Consumption + subscription - revenue | D6: =+'ANT Dashboard'!D10+'ANT Dashboard'!D11-'ANT Dashboard'!D8 -> 0 | E6: =+'ANT Dashboard'!E10+'ANT Dashboard'!E11-'ANT Dashboard'!E8 -> 0 | F6: =+'ANT Dashboard'!F10+'ANT Dashboard'!F11-'ANT Dashboard'!F8 -> 0 | G6: =+'ANT Dashboard'!G10+'ANT Dashboard'!G11-'ANT Dashboard'!G8 -> 0 | H6: =+'ANT Dashboard'!H10+'ANT Dashboard'!H11-'ANT Dashboard'!H8 -> 0 | I6: =+'ANT Dashboard'!I10+'ANT Dashboard'!I11-'ANT Dashboard'!I8 -> 0 | J6: =+'ANT Dashboard'!K10+'ANT Dashboard'!K11-'ANT Dashboard'!K8 -> 0 | K6: =+'ANT Dashboard'!L10+'ANT Dashboard'!L11-'ANT Dashboard'!L8 -> 0 | L6: =+'ANT Dashboard'!M10+'ANT Dashboard'!M11-'ANT Dashboard'!M8 -> 0 | M6: =+'ANT Dashboard'!N10+'ANT Dashboard'!N11-'ANT Dashboard'!N8 -> 0 | N6: =+'ANT Dashboard'!O10+'ANT Dashboard'!O11-'ANT Dashboard'!O8 -> 0 | O6: =+'ANT Dashboard'!P10+'ANT Dashboard'!P11-'ANT Dashboard'!P8 -> 0 | Q6: =IF(MAX(MAX(D6:O6),-MIN(D6:O6))<=2,"OK","GAP") -> OK
A7: Distillation + ex-distillation - T28 ARR | C7: =+'ANT Dashboard'!C26+'ANT Dashboard'!C27-'ANT Dashboard'!C6 -> 0 | D7: =+'ANT Dashboard'!D26+'ANT Dashboard'!D27-'ANT Dashboard'!D6 -> 0 | E7: =+'ANT Dashboard'!E26+'ANT Dashboard'!E27-'ANT Dashboard'!E6 -> -1 | F7: =+'ANT Dashboard'!F26+'ANT Dashboard'!F27-'ANT Dashboard'!F6 -> 0 | G7: =+'ANT Dashboard'!G26+'ANT Dashboard'!G27-'ANT Dashboard'!G6 -> 0 | H7: =+'ANT Dashboard'!H26+'ANT Dashboard'!H27-'ANT Dashboard'!H6 -> 0 | I7: =+'ANT Dashboard'!I26+'ANT Dashboard'!I27-'ANT Dashboard'!I6 -> 0 | J7: =+'ANT Dashboard'!K26+'ANT Dashboard'!K27-'ANT Dashboard'!K6 -> 0 | K7: =+'ANT Dashboard'!L26+'ANT Dashboard'!L27-'ANT Dashboard'!L6 -> 0 | L7: =+'ANT Dashboard'!M26+'ANT Dashboard'!M27-'ANT Dashboard'!M6 -> 0 | Q7: =IF(MAX(MAX(C7:L7),-MIN(C7:L7))<=2,"OK","GAP") -> OK | R7: 2028E-2030E excluded: the source leaves distillation and ex-distillation as "-" in those years
A8: Customer-serving + training - compute and infrastructure | B8: =+'ANT Dashboard'!B36+'ANT Dashboard'!B38-'ANT Dashboard'!B34 -> 0 | C8: =+'ANT Dashboard'!C36+'ANT Dashboard'!C38-'ANT Dashboard'!C34 -> 0 | D8: =+'ANT Dashboard'!D36+'ANT Dashboard'!D38-'ANT Dashboard'!D34 -> 0 | E8: =+'ANT Dashboard'!E36+'ANT Dashboard'!E38-'ANT Dashboard'!E34 -> 0 | F8: =+'ANT Dashboard'!F36+'ANT Dashboard'!F38-'ANT Dashboard'!F34 -> 0 | G8: =+'ANT Dashboard'!G36+'ANT Dashboard'!G38-'ANT Dashboard'!G34 -> 0 | H8: =+'ANT Dashboard'!H36+'ANT Dashboard'!H38-'ANT Dashboard'!H34 -> 0 | I8: =+'ANT Dashboard'!I36+'ANT Dashboard'!I38-'ANT Dashboard'!I34 -> 0 | J8: =+'ANT Dashboard'!K36+'ANT Dashboard'!K38-'ANT Dashboard'!K34 -> 0 | K8: =+'ANT Dashboard'!L36+'ANT Dashboard'!L38-'ANT Dashboard'!L34 -> 0 | L8: =+'ANT Dashboard'!M36+'ANT Dashboard'!M38-'ANT Dashboard'!M34 -> 0 | M8: =+'ANT Dashboard'!N36+'ANT Dashboard'!N38-'ANT Dashboard'!N34 -> 1 | N8: =+'ANT Dashboard'!O36+'ANT Dashboard'!O38-'ANT Dashboard'!O34 -> 0 | O8: =+'ANT Dashboard'!P36+'ANT Dashboard'!P38-'ANT Dashboard'!P34 -> 0 | Q8: =IF(MAX(MAX(B8:O8),-MIN(B8:O8))<=2,"OK","GAP") -> OK
A9: New long-term + short-term - compute beyond contracts | B9: =+'ANT Dashboard'!B42+'ANT Dashboard'!B43-'ANT Dashboard'!B41 -> 0 | C9: =+'ANT Dashboard'!C42+'ANT Dashboard'!C43-'ANT Dashboard'!C41 -> 0 | D9: =+'ANT Dashboard'!D42+'ANT Dashboard'!D43-'ANT Dashboard'!D41 -> 0 | E9: =+'ANT Dashboard'!E42+'ANT Dashboard'!E43-'ANT Dashboard'!E41 -> 0 | F9: =+'ANT Dashboard'!F42+'ANT Dashboard'!F43-'ANT Dashboard'!F41 -> 0 | G9: =+'ANT Dashboard'!G42+'ANT Dashboard'!G43-'ANT Dashboard'!G41 -> 0 | H9: =+'ANT Dashboard'!H42+'ANT Dashboard'!H43-'ANT Dashboard'!H41 -> 0 | I9: =+'ANT Dashboard'!I42+'ANT Dashboard'!I43-'ANT Dashboard'!I41 -> 0 | J9: =+'ANT Dashboard'!K42+'ANT Dashboard'!K43-'ANT Dashboard'!K41 -> 0 | K9: =+'ANT Dashboard'!L42+'ANT Dashboard'!L43-'ANT Dashboard'!L41 -> 0 | L9: =+'ANT Dashboard'!M42+'ANT Dashboard'!M43-'ANT Dashboard'!M41 -> 0 | M9: =+'ANT Dashboard'!N42+'ANT Dashboard'!N43-'ANT Dashboard'!N41 -> 0 | N9: =+'ANT Dashboard'!O42+'ANT Dashboard'!O43-'ANT Dashboard'!O41 -> 0 | O9: =+'ANT Dashboard'!P42+'ANT Dashboard'!P43-'ANT Dashboard'!P41 -> 0 | Q9: =IF(MAX(MAX(B9:O9),-MIN(B9:O9))<=2,"OK","GAP") -> OK
A10: Personnel ex-SBC + SBC - personnel | B10: =+'ANT Dashboard'!B48+'ANT Dashboard'!B52-'ANT Dashboard'!B46 -> 0 | C10: =+'ANT Dashboard'!C48+'ANT Dashboard'!C52-'ANT Dashboard'!C46 -> 0 | D10: =+'ANT Dashboard'!D48+'ANT Dashboard'!D52-'ANT Dashboard'!D46 -> 0 | E10: =+'ANT Dashboard'!E48+'ANT Dashboard'!E52-'ANT Dashboard'!E46 -> 0 | F10: =+'ANT Dashboard'!F48+'ANT Dashboard'!F52-'ANT Dashboard'!F46 -> 0 | G10: =+'ANT Dashboard'!G48+'ANT Dashboard'!G52-'ANT Dashboard'!G46 -> 0 | H10: =+'ANT Dashboard'!H48+'ANT Dashboard'!H52-'ANT Dashboard'!H46 -> 0 | I10: =+'ANT Dashboard'!I48+'ANT Dashboard'!I52-'ANT Dashboard'!I46 -> 1 | J10: =+'ANT Dashboard'!K48+'ANT Dashboard'!K52-'ANT Dashboard'!K46 -> 0 | K10: =+'ANT Dashboard'!L48+'ANT Dashboard'!L52-'ANT Dashboard'!L46 -> 0 | L10: =+'ANT Dashboard'!M48+'ANT Dashboard'!M52-'ANT Dashboard'!M46 -> 0 | M10: =+'ANT Dashboard'!N48+'ANT Dashboard'!N52-'ANT Dashboard'!N46 -> 0 | N10: =+'ANT Dashboard'!O48+'ANT Dashboard'!O52-'ANT Dashboard'!O46 -> 0 | O10: =+'ANT Dashboard'!P48+'ANT Dashboard'!P52-'ANT Dashboard'!P46 -> 0 | Q10: =IF(MAX(MAX(B10:O10),-MIN(B10:O10))<=2,"OK","GAP") -> OK
A11: Compute + personnel + S&M + other - total opex | B11: =+'ANT Dashboard'!B34+'ANT Dashboard'!B46+'ANT Dashboard'!B54+'ANT Dashboard'!B56-'ANT Dashboard'!B59 -> -1500 | C11: =+'ANT Dashboard'!C34+'ANT Dashboard'!C46+'ANT Dashboard'!C54+'ANT Dashboard'!C56-'ANT Dashboard'!C59 -> 0 | D11: =+'ANT Dashboard'!D34+'ANT Dashboard'!D46+'ANT Dashboard'!D54+'ANT Dashboard'!D56-'ANT Dashboard'!D59 -> 0 | E11: =+'ANT Dashboard'!E34+'ANT Dashboard'!E46+'ANT Dashboard'!E54+'ANT Dashboard'!E56-'ANT Dashboard'!E59 -> 0 | F11: =+'ANT Dashboard'!F34+'ANT Dashboard'!F46+'ANT Dashboard'!F54+'ANT Dashboard'!F56-'ANT Dashboard'!F59 -> 0 | G11: =+'ANT Dashboard'!G34+'ANT Dashboard'!G46+'ANT Dashboard'!G54+'ANT Dashboard'!G56-'ANT Dashboard'!G59 -> 0 | H11: =+'ANT Dashboard'!H34+'ANT Dashboard'!H46+'ANT Dashboard'!H54+'ANT Dashboard'!H56-'ANT Dashboard'!H59 -> 1 | I11: =+'ANT Dashboard'!I34+'ANT Dashboard'!I46+'ANT Dashboard'!I54+'ANT Dashboard'!I56-'ANT Dashboard'!I59 -> 1 | J11: =+'ANT Dashboard'!K34+'ANT Dashboard'!K46+'ANT Dashboard'!K54+'ANT Dashboard'!K56-'ANT Dashboard'!K59 -> -1500 | K11: =+'ANT Dashboard'!L34+'ANT Dashboard'!L46+'ANT Dashboard'!L54+'ANT Dashboard'!L56-'ANT Dashboard'!L59 -> -1 | L11: =+'ANT Dashboard'!M34+'ANT Dashboard'!M46+'ANT Dashboard'!M54+'ANT Dashboard'!M56-'ANT Dashboard'!M59 -> 0 | M11: =+'ANT Dashboard'!N34+'ANT Dashboard'!N46+'ANT Dashboard'!N54+'ANT Dashboard'!N56-'ANT Dashboard'!N59 -> -1 | N11: =+'ANT Dashboard'!O34+'ANT Dashboard'!O46+'ANT Dashboard'!O54+'ANT Dashboard'!O56-'ANT Dashboard'!O59 -> 0 | O11: =+'ANT Dashboard'!P34+'ANT Dashboard'!P46+'ANT Dashboard'!P54+'ANT Dashboard'!P56-'ANT Dashboard'!P59 -> -1 | Q11: =IF(MAX(MAX(B11:O11),-MIN(B11:O11))<=2,"OK","GAP") -> GAP | R11: 3Q25 and 2025: 1,500 in total opex is not itemised in any line of the exhibit
A12: Revenue - total opex - GAAP operating income | B12: ='ANT Dashboard'!B8-'ANT Dashboard'!B59-'ANT Dashboard'!B16 -> 0 | C12: ='ANT Dashboard'!C8-'ANT Dashboard'!C59-'ANT Dashboard'!C16 -> 0 | D12: ='ANT Dashboard'!D8-'ANT Dashboard'!D59-'ANT Dashboard'!D16 -> 0 | E12: ='ANT Dashboard'!E8-'ANT Dashboard'!E59-'ANT Dashboard'!E16 -> 0 | F12: ='ANT Dashboard'!F8-'ANT Dashboard'!F59-'ANT Dashboard'!F16 -> 0 | G12: ='ANT Dashboard'!G8-'ANT Dashboard'!G59-'ANT Dashboard'!G16 -> 0 | H12: ='ANT Dashboard'!H8-'ANT Dashboard'!H59-'ANT Dashboard'!H16 -> 0 | I12: ='ANT Dashboard'!I8-'ANT Dashboard'!I59-'ANT Dashboard'!I16 -> 1 | J12: ='ANT Dashboard'!K8-'ANT Dashboard'!K59-'ANT Dashboard'!K16 -> 0 | K12: ='ANT Dashboard'!L8-'ANT Dashboard'!L59-'ANT Dashboard'!L16 -> 0 | L12: ='ANT Dashboard'!M8-'ANT Dashboard'!M59-'ANT Dashboard'!M16 -> 0 | M12: ='ANT Dashboard'!N8-'ANT Dashboard'!N59-'ANT Dashboard'!N16 -> 0 | N12: ='ANT Dashboard'!O8-'ANT Dashboard'!O59-'ANT Dashboard'!O16 -> 0 | O12: ='ANT Dashboard'!P8-'ANT Dashboard'!P59-'ANT Dashboard'!P16 -> 0 | Q12: =IF(MAX(MAX(B12:O12),-MIN(B12:O12))<=2,"OK","GAP") -> OK
A13: GAAP OI + SBC + one-offs - adjusted OI | B13: =+'ANT Dashboard'!B16+'ANT Dashboard'!B52+'ANT Dashboard'!B58-'ANT Dashboard'!B14 -> -1500 | C13: =+'ANT Dashboard'!C16+'ANT Dashboard'!C52+'ANT Dashboard'!C58-'ANT Dashboard'!C14 -> 0 | D13: =+'ANT Dashboard'!D16+'ANT Dashboard'!D52+'ANT Dashboard'!D58-'ANT Dashboard'!D14 -> 0 | E13: =+'ANT Dashboard'!E16+'ANT Dashboard'!E52+'ANT Dashboard'!E58-'ANT Dashboard'!E14 -> 0 | F13: =+'ANT Dashboard'!F16+'ANT Dashboard'!F52+'ANT Dashboard'!F58-'ANT Dashboard'!F14 -> 0 | G13: =+'ANT Dashboard'!G16+'ANT Dashboard'!G52+'ANT Dashboard'!G58-'ANT Dashboard'!G14 -> 0 | H13: =+'ANT Dashboard'!H16+'ANT Dashboard'!H52+'ANT Dashboard'!H58-'ANT Dashboard'!H14 -> 1 | I13: =+'ANT Dashboard'!I16+'ANT Dashboard'!I52+'ANT Dashboard'!I58-'ANT Dashboard'!I14 -> 0 | J13: =+'ANT Dashboard'!K16+'ANT Dashboard'!K52+'ANT Dashboard'!K58-'ANT Dashboard'!K14 -> -1500 | K13: =+'ANT Dashboard'!L16+'ANT Dashboard'!L52+'ANT Dashboard'!L58-'ANT Dashboard'!L14 -> 0 | L13: =+'ANT Dashboard'!M16+'ANT Dashboard'!M52+'ANT Dashboard'!M58-'ANT Dashboard'!M14 -> 0 | M13: =+'ANT Dashboard'!N16+'ANT Dashboard'!N52+'ANT Dashboard'!N58-'ANT Dashboard'!N14 -> 0 | N13: =+'ANT Dashboard'!O16+'ANT Dashboard'!O52+'ANT Dashboard'!O58-'ANT Dashboard'!O14 -> 0 | O13: =+'ANT Dashboard'!P16+'ANT Dashboard'!P52+'ANT Dashboard'!P58-'ANT Dashboard'!P14 -> -1 | Q13: =IF(MAX(MAX(B13:O13),-MIN(B13:O13))<=2,"OK","GAP") -> GAP | R13: 3Q25 and 2025: the same un-itemised 1,500 is added back
A14: Counterparties - cloud service agreements signed in 2026 | B14: =+'ANT Dashboard'!B67+'ANT Dashboard'!B68+'ANT Dashboard'!B69+'ANT Dashboard'!B70+'ANT Dashboard'!B71+'ANT Dashboard'!B72+'ANT Dashboard'!B73-'ANT Dashboard'!B66 -> 0 | C14: =+'ANT Dashboard'!C67+'ANT Dashboard'!C68+'ANT Dashboard'!C69+'ANT Dashboard'!C70+'ANT Dashboard'!C71+'ANT Dashboard'!C72+'ANT Dashboard'!C73-'ANT Dashboard'!C66 -> 0 | D14: =+'ANT Dashboard'!D67+'ANT Dashboard'!D68+'ANT Dashboard'!D69+'ANT Dashboard'!D70+'ANT Dashboard'!D71+'ANT Dashboard'!D72+'ANT Dashboard'!D73-'ANT Dashboard'!D66 -> 0 | E14: =+'ANT Dashboard'!E67+'ANT Dashboard'!E68+'ANT Dashboard'!E69+'ANT Dashboard'!E70+'ANT Dashboard'!E71+'ANT Dashboard'!E72+'ANT Dashboard'!E73-'ANT Dashboard'!E66 -> 0 | F14: =+'ANT Dashboard'!F67+'ANT Dashboard'!F68+'ANT Dashboard'!F69+'ANT Dashboard'!F70+'ANT Dashboard'!F71+'ANT Dashboard'!F72+'ANT Dashboard'!F73-'ANT Dashboard'!F66 -> 0 | G14: =+'ANT Dashboard'!G67+'ANT Dashboard'!G68+'ANT Dashboard'!G69+'ANT Dashboard'!G70+'ANT Dashboard'!G71+'ANT Dashboard'!G72+'ANT Dashboard'!G73-'ANT Dashboard'!G66 -> 0 | H14: =+'ANT Dashboard'!H67+'ANT Dashboard'!H68+'ANT Dashboard'!H69+'ANT Dashboard'!H70+'ANT Dashboard'!H71+'ANT Dashboard'!H72+'ANT Dashboard'!H73-'ANT Dashboard'!H66 -> 0 | I14: =+'ANT Dashboard'!I67+'ANT Dashboard'!I68+'ANT Dashboard'!I69+'ANT Dashboard'!I70+'ANT Dashboard'!I71+'ANT Dashboard'!I72+'ANT Dashboard'!I73-'ANT Dashboard'!I66 -> 0 | J14: =+'ANT Dashboard'!K67+'ANT Dashboard'!K68+'ANT Dashboard'!K69+'ANT Dashboard'!K70+'ANT Dashboard'!K71+'ANT Dashboard'!K72+'ANT Dashboard'!K73-'ANT Dashboard'!K66 -> 0 | K14: =+'ANT Dashboard'!L67+'ANT Dashboard'!L68+'ANT Dashboard'!L69+'ANT Dashboard'!L70+'ANT Dashboard'!L71+'ANT Dashboard'!L72+'ANT Dashboard'!L73-'ANT Dashboard'!L66 -> 0 | L14: =+'ANT Dashboard'!M67+'ANT Dashboard'!M68+'ANT Dashboard'!M69+'ANT Dashboard'!M70+'ANT Dashboard'!M71+'ANT Dashboard'!M72+'ANT Dashboard'!M73-'ANT Dashboard'!M66 -> 0 | M14: =+'ANT Dashboard'!N67+'ANT Dashboard'!N68+'ANT Dashboard'!N69+'ANT Dashboard'!N70+'ANT Dashboard'!N71+'ANT Dashboard'!N72+'ANT Dashboard'!N73-'ANT Dashboard'!N66 -> 0 | N14: =+'ANT Dashboard'!O67+'ANT Dashboard'!O68+'ANT Dashboard'!O69+'ANT Dashboard'!O70+'ANT Dashboard'!O71+'ANT Dashboard'!O72+'ANT Dashboard'!O73-'ANT Dashboard'!O66 -> 0 | O14: =+'ANT Dashboard'!P67+'ANT Dashboard'!P68+'ANT Dashboard'!P69+'ANT Dashboard'!P70+'ANT Dashboard'!P71+'ANT Dashboard'!P72+'ANT Dashboard'!P73-'ANT Dashboard'!P66 -> 0 | Q14: =IF(MAX(MAX(B14:O14),-MIN(B14:O14))<=2,"OK","GAP") -> OK
A15: Cloud + Note 13 + Broadcom ROU + DC + AMD dep + renewals + ahead-of-demand - contracted cost | F15: =+'ANT Dashboard'!F66+'ANT Dashboard'!F74+'ANT Dashboard'!F75+'ANT Dashboard'!F76+'ANT Dashboard'!F77+'ANT Dashboard'!F78+'ANT Dashboard'!F79-'ANT Dashboard'!F65 -> 0 | G15: =+'ANT Dashboard'!G66+'ANT Dashboard'!G74+'ANT Dashboard'!G75+'ANT Dashboard'!G76+'ANT Dashboard'!G77+'ANT Dashboard'!G78+'ANT Dashboard'!G79-'ANT Dashboard'!G65 -> -1 | H15: =+'ANT Dashboard'!H66+'ANT Dashboard'!H74+'ANT Dashboard'!H75+'ANT Dashboard'!H76+'ANT Dashboard'!H77+'ANT Dashboard'!H78+'ANT Dashboard'!H79-'ANT Dashboard'!H65 -> 0 | I15: =+'ANT Dashboard'!I66+'ANT Dashboard'!I74+'ANT Dashboard'!I75+'ANT Dashboard'!I76+'ANT Dashboard'!I77+'ANT Dashboard'!I78+'ANT Dashboard'!I79-'ANT Dashboard'!I65 -> -1 | L15: =+'ANT Dashboard'!M66+'ANT Dashboard'!M74+'ANT Dashboard'!M75+'ANT Dashboard'!M76+'ANT Dashboard'!M77+'ANT Dashboard'!M78+'ANT Dashboard'!M79-'ANT Dashboard'!M65 -> 0 | M15: =+'ANT Dashboard'!N66+'ANT Dashboard'!N74+'ANT Dashboard'!N75+'ANT Dashboard'!N76+'ANT Dashboard'!N77+'ANT Dashboard'!N78+'ANT Dashboard'!N79-'ANT Dashboard'!N65 -> 1 | N15: =+'ANT Dashboard'!O66+'ANT Dashboard'!O74+'ANT Dashboard'!O75+'ANT Dashboard'!O76+'ANT Dashboard'!O77+'ANT Dashboard'!O78+'ANT Dashboard'!O79-'ANT Dashboard'!O65 -> 0 | O15: =+'ANT Dashboard'!P66+'ANT Dashboard'!P74+'ANT Dashboard'!P75+'ANT Dashboard'!P76+'ANT Dashboard'!P77+'ANT Dashboard'!P78+'ANT Dashboard'!P79-'ANT Dashboard'!P65 -> 0 | Q15: =IF(MAX(MAX(F15:O15),-MIN(F15:O15))<=2,"OK","GAP") -> OK | R15: 2026E excluded: contracted cost (23,912) covers 3Q26E+4Q26E only, while the 2026E cloud-agreement line (25,527) includes 2Q26 (5,741)
A16: Contracted + beyond contracts - compute and infrastructure | F16: =+'ANT Dashboard'!F65+'ANT Dashboard'!F80-'ANT Dashboard'!F81 -> 0 | G16: =+'ANT Dashboard'!G65+'ANT Dashboard'!G80-'ANT Dashboard'!G81 -> 0 | H16: =+'ANT Dashboard'!H65+'ANT Dashboard'!H80-'ANT Dashboard'!H81 -> 0 | I16: =+'ANT Dashboard'!I65+'ANT Dashboard'!I80-'ANT Dashboard'!I81 -> 0 | L16: =+'ANT Dashboard'!M65+'ANT Dashboard'!M80-'ANT Dashboard'!M81 -> 0 | M16: =+'ANT Dashboard'!N65+'ANT Dashboard'!N80-'ANT Dashboard'!N81 -> 0 | N16: =+'ANT Dashboard'!O65+'ANT Dashboard'!O80-'ANT Dashboard'!O81 -> 0 | O16: =+'ANT Dashboard'!P65+'ANT Dashboard'!P80-'ANT Dashboard'!P81 -> 1 | Q16: =IF(MAX(MAX(F16:O16),-MIN(F16:O16))<=2,"OK","GAP") -> OK | R16: 2026E excluded: compute (33,807) includes 1H26 actuals; contracted cost is H2-only
A17: ROU amortization (lease block) - ROU line in compute | B17: =+'ANT Dashboard'!B95-'ANT Dashboard'!B75 -> 0 | C17: =+'ANT Dashboard'!C95-'ANT Dashboard'!C75 -> 0 | D17: =+'ANT Dashboard'!D95-'ANT Dashboard'!D75 -> 0 | E17: =+'ANT Dashboard'!E95-'ANT Dashboard'!E75 -> 0 | F17: =+'ANT Dashboard'!F95-'ANT Dashboard'!F75 -> 0 | G17: =+'ANT Dashboard'!G95-'ANT Dashboard'!G75 -> 0 | H17: =+'ANT Dashboard'!H95-'ANT Dashboard'!H75 -> 0 | I17: =+'ANT Dashboard'!I95-'ANT Dashboard'!I75 -> 0 | J17: =+'ANT Dashboard'!K95-'ANT Dashboard'!K75 -> 0 | K17: =+'ANT Dashboard'!L95-'ANT Dashboard'!L75 -> 0 | L17: =+'ANT Dashboard'!M95-'ANT Dashboard'!M75 -> 0 | M17: =+'ANT Dashboard'!N95-'ANT Dashboard'!N75 -> 0 | N17: =+'ANT Dashboard'!O95-'ANT Dashboard'!O75 -> 0 | O17: =+'ANT Dashboard'!P95-'ANT Dashboard'!P75 -> 0 | Q17: =IF(MAX(MAX(B17:O17),-MIN(B17:O17))<=2,"OK","GAP") -> OK
A18: DC/colo/power (lease block) - DC line in compute | B18: =+'ANT Dashboard'!B109-'ANT Dashboard'!B76 -> 0 | C18: =+'ANT Dashboard'!C109-'ANT Dashboard'!C76 -> 0 | D18: =+'ANT Dashboard'!D109-'ANT Dashboard'!D76 -> 0 | E18: =+'ANT Dashboard'!E109-'ANT Dashboard'!E76 -> 0 | F18: =+'ANT Dashboard'!F109-'ANT Dashboard'!F76 -> 0 | G18: =+'ANT Dashboard'!G109-'ANT Dashboard'!G76 -> 0 | H18: =+'ANT Dashboard'!H109-'ANT Dashboard'!H76 -> 0 | I18: =+'ANT Dashboard'!I109-'ANT Dashboard'!I76 -> 0 | J18: =+'ANT Dashboard'!K109-'ANT Dashboard'!K76 -> 0 | K18: =+'ANT Dashboard'!L109-'ANT Dashboard'!L76 -> 0 | L18: =+'ANT Dashboard'!M109-'ANT Dashboard'!M76 -> 0 | M18: =+'ANT Dashboard'!N109-'ANT Dashboard'!N76 -> 0 | N18: =+'ANT Dashboard'!O109-'ANT Dashboard'!O76 -> 0 | O18: =+'ANT Dashboard'!P109-'ANT Dashboard'!P76 -> 0 | Q18: =IF(MAX(MAX(B18:O18),-MIN(B18:O18))<=2,"OK","GAP") -> OK
A19: OCF + PP&E + AMD purchases - FCF | F19: =+'ANT Dashboard'!F117+'ANT Dashboard'!F118+'ANT Dashboard'!F119-'ANT Dashboard'!F120 -> 0 | G19: =+'ANT Dashboard'!G117+'ANT Dashboard'!G118+'ANT Dashboard'!G119-'ANT Dashboard'!G120 -> 0 | H19: =+'ANT Dashboard'!H117+'ANT Dashboard'!H118+'ANT Dashboard'!H119-'ANT Dashboard'!H120 -> 0 | I19: =+'ANT Dashboard'!I117+'ANT Dashboard'!I118+'ANT Dashboard'!I119-'ANT Dashboard'!I120 -> 0 | J19: =+'ANT Dashboard'!K117+'ANT Dashboard'!K118+'ANT Dashboard'!K119-'ANT Dashboard'!K120 -> 0 | K19: =+'ANT Dashboard'!L117+'ANT Dashboard'!L118+'ANT Dashboard'!L119-'ANT Dashboard'!L120 -> 1 | L19: =+'ANT Dashboard'!M117+'ANT Dashboard'!M118+'ANT Dashboard'!M119-'ANT Dashboard'!M120 -> 0 | M19: =+'ANT Dashboard'!N117+'ANT Dashboard'!N118+'ANT Dashboard'!N119-'ANT Dashboard'!N120 -> 0 | N19: =+'ANT Dashboard'!O117+'ANT Dashboard'!O118+'ANT Dashboard'!O119-'ANT Dashboard'!O120 -> 1 | O19: =+'ANT Dashboard'!P117+'ANT Dashboard'!P118+'ANT Dashboard'!P119-'ANT Dashboard'!P120 -> 0 | Q19: =IF(MAX(MAX(F19:O19),-MIN(F19:O19))<=2,"OK","GAP") -> OK
A20: FCF + lease principal - FCF after principal | F20: =+'ANT Dashboard'!F120+'ANT Dashboard'!F122-'ANT Dashboard'!F123 -> 0 | G20: =+'ANT Dashboard'!G120+'ANT Dashboard'!G122-'ANT Dashboard'!G123 -> 0 | H20: =+'ANT Dashboard'!H120+'ANT Dashboard'!H122-'ANT Dashboard'!H123 -> 0 | I20: =+'ANT Dashboard'!I120+'ANT Dashboard'!I122-'ANT Dashboard'!I123 -> 0 | J20: =+'ANT Dashboard'!K120+'ANT Dashboard'!K122-'ANT Dashboard'!K123 -> 0 | K20: =+'ANT Dashboard'!L120+'ANT Dashboard'!L122-'ANT Dashboard'!L123 -> 0 | L20: =+'ANT Dashboard'!M120+'ANT Dashboard'!M122-'ANT Dashboard'!M123 -> 0 | M20: =+'ANT Dashboard'!N120+'ANT Dashboard'!N122-'ANT Dashboard'!N123 -> 0 | N20: =+'ANT Dashboard'!O120+'ANT Dashboard'!O122-'ANT Dashboard'!O123 -> 0 | O20: =+'ANT Dashboard'!P120+'ANT Dashboard'!P122-'ANT Dashboard'!P123 -> 0 | Q20: =IF(MAX(MAX(F20:O20),-MIN(F20:O20))<=2,"OK","GAP") -> OK
A22: ARR Monthly ($Bn) | B22: Dec-25 | C22: Jan-26 | D22: Feb-26 | E22: Mar-26 | F22: Apr-26 | G22: May-26 | H22: Jun-26 | I22: Jul-26 | J22: Aug-26 | K22: Sep-26 | L22: Oct-26 | M22: Nov-26 | N22: Dec-26 | Q22: Status | R22: Note (source-level gap)
A23: Distillation + ex-distillation - T28 ARR | B23: ='ARR Monthly'!D5+'ARR Monthly'!E5-'ARR Monthly'!C5 -> 0 | C23: ='ARR Monthly'!D6+'ARR Monthly'!E6-'ARR Monthly'!C6 -> 0 | D23: ='ARR Monthly'!D7+'ARR Monthly'!E7-'ARR Monthly'!C7 -> 0.1 | E23: ='ARR Monthly'!D8+'ARR Monthly'!E8-'ARR Monthly'!C8 -> 0 | F23: ='ARR Monthly'!D9+'ARR Monthly'!E9-'ARR Monthly'!C9 -> 0 | G23: ='ARR Monthly'!D10+'ARR Monthly'!E10-'ARR Monthly'!C10 -> 0 | H23: ='ARR Monthly'!D11+'ARR Monthly'!E11-'ARR Monthly'!C11 -> 0 | I23: ='ARR Monthly'!D12+'ARR Monthly'!E12-'ARR Monthly'!C12 -> 0 | J23: ='ARR Monthly'!D13+'ARR Monthly'!E13-'ARR Monthly'!C13 -> 0 | K23: ='ARR Monthly'!D14+'ARR Monthly'!E14-'ARR Monthly'!C14 -> 0 | L23: ='ARR Monthly'!D15+'ARR Monthly'!E15-'ARR Monthly'!C15 -> 0 | M23: ='ARR Monthly'!D16+'ARR Monthly'!E16-'ARR Monthly'!C16 -> 0 | N23: ='ARR Monthly'!D17+'ARR Monthly'!E17-'ARR Monthly'!C17 -> 0 | Q23: =IF(MAX(MAX(B23:N23),-MIN(B23:N23))<=0.11,"OK","GAP") -> OK
A24: T28 change - net add | C24: ='ARR Monthly'!C6-'ARR Monthly'!C5-'ARR Monthly'!F6 -> 0 | D24: ='ARR Monthly'!C7-'ARR Monthly'!C6-'ARR Monthly'!F7 -> 0 | E24: ='ARR Monthly'!C8-'ARR Monthly'!C7-'ARR Monthly'!F8 -> 0 | F24: ='ARR Monthly'!C9-'ARR Monthly'!C8-'ARR Monthly'!F9 -> 0 | G24: ='ARR Monthly'!C10-'ARR Monthly'!C9-'ARR Monthly'!F10 -> 0 | H24: ='ARR Monthly'!C11-'ARR Monthly'!C10-'ARR Monthly'!F11 -> 0 | I24: ='ARR Monthly'!C12-'ARR Monthly'!C11-'ARR Monthly'!F12 -> 0 | J24: ='ARR Monthly'!C13-'ARR Monthly'!C12-'ARR Monthly'!F13 -> 2.8865799e-15 | K24: ='ARR Monthly'!C14-'ARR Monthly'!C13-'ARR Monthly'!F14 -> -5.7731597e-15 | L24: ='ARR Monthly'!C15-'ARR Monthly'!C14-'ARR Monthly'!F15 -> 0 | M24: ='ARR Monthly'!C16-'ARR Monthly'!C15-'ARR Monthly'!F16 -> 0 | N24: ='ARR Monthly'!C17-'ARR Monthly'!C16-'ARR Monthly'!F17 -> 8.8817842e-15 | Q24: =IF(MAX(MAX(C24:N24),-MIN(C24:N24))<=0.11,"OK","GAP") -> OK
A25: Ex-distillation change - ex-distillation net add | C25: ='ARR Monthly'!E6-'ARR Monthly'!E5-'ARR Monthly'!G6 -> 0 | D25: ='ARR Monthly'!E7-'ARR Monthly'!E6-'ARR Monthly'!G7 -> 0 | E25: ='ARR Monthly'!E8-'ARR Monthly'!E7-'ARR Monthly'!G8 -> 0 | F25: ='ARR Monthly'!E9-'ARR Monthly'!E8-'ARR Monthly'!G9 -> 0 | G25: ='ARR Monthly'!E10-'ARR Monthly'!E9-'ARR Monthly'!G10 -> 0 | H25: ='ARR Monthly'!E11-'ARR Monthly'!E10-'ARR Monthly'!G11 -> 0 | I25: ='ARR Monthly'!E12-'ARR Monthly'!E11-'ARR Monthly'!G12 -> 0 | J25: ='ARR Monthly'!E13-'ARR Monthly'!E12-'ARR Monthly'!G13 -> 0 | K25: ='ARR Monthly'!E14-'ARR Monthly'!E13-'ARR Monthly'!G14 -> -8.8817842e-15 | L25: ='ARR Monthly'!E15-'ARR Monthly'!E14-'ARR Monthly'!G15 -> 0 | M25: ='ARR Monthly'!E16-'ARR Monthly'!E15-'ARR Monthly'!G16 -> 1.1546319e-14 | N25: ='ARR Monthly'!E17-'ARR Monthly'!E16-'ARR Monthly'!G17 -> 0 | Q25: =IF(MAX(MAX(C25:N25),-MIN(C25:N25))<=0.11,"OK","GAP") -> OK
A26: T28 ARR x days/365 - monthly revenue | C26: ='ARR Monthly'!C6*'ARR Monthly'!B6/365-'ARR Monthly'!K6 -> 0.0020547945 | D26: ='ARR Monthly'!C7*'ARR Monthly'!B7/365-'ARR Monthly'!K7 -> -0.0024657534 | E26: ='ARR Monthly'!C8*'ARR Monthly'!B8/365-'ARR Monthly'!K8 -> -0.0021917808 | F26: ='ARR Monthly'!C9*'ARR Monthly'!B9/365-'ARR Monthly'!K9 -> -0.0045205479 | G26: ='ARR Monthly'!C10*'ARR Monthly'!B10/365-'ARR Monthly'!K10 -> 0.0019178082 | H26: ='ARR Monthly'!C11*'ARR Monthly'!B11/365-'ARR Monthly'!K11 -> -0.0012328767 | I26: ='ARR Monthly'!C12*'ARR Monthly'!B12/365-'ARR Monthly'!K12 -> 0.00054794521 | J26: ='ARR Monthly'!C13*'ARR Monthly'!B13/365-'ARR Monthly'!K13 -> 0.0024657534 | K26: ='ARR Monthly'!C14*'ARR Monthly'!B14/365-'ARR Monthly'!K14 -> 0.0047945205 | L26: ='ARR Monthly'!C15*'ARR Monthly'!B15/365-'ARR Monthly'!K15 -> -0.0045205479 | M26: ='ARR Monthly'!C16*'ARR Monthly'!B16/365-'ARR Monthly'!K16 -> -0.00082191781 | N26: ='ARR Monthly'!C17*'ARR Monthly'!B17/365-'ARR Monthly'!K17 -> -0.0036986301 | Q26: =IF(MAX(MAX(C26:N26),-MIN(C26:N26))<=0.02,"OK","GAP") -> OK
A28: ARR Quarterly ($Bn) | B28: Q1-26 | C28: Q2-26 | D28: Q3-26 | E28: Q4-26E | F28: FY26E | Q28: Status | R28: Note (source-level gap)
A29: Sum of monthly revenue - quarterly revenue | B29: =SUM('ARR Monthly'!K6:'ARR Monthly'!K8)-'ARR Monthly'!B21 -> 0 | C29: =SUM('ARR Monthly'!K9:'ARR Monthly'!K11)-'ARR Monthly'!B22 -> 0 | D29: =SUM('ARR Monthly'!K12:'ARR Monthly'!K14)-'ARR Monthly'!B23 -> -0.01 | E29: =SUM('ARR Monthly'!K15:'ARR Monthly'!K17)-'ARR Monthly'!B24 -> 0.01 | F29: =SUM('ARR Monthly'!B21:'ARR Monthly'!B24)-'ARR Monthly'!B25 -> 0 | Q29: =IF(MAX(MAX(B29:F29),-MIN(B29:F29))<=0.02,"OK","GAP") -> OK
A30: ARR tab revenue x 1,000 - dashboard revenue (US$ M) | B30: ='ARR Monthly'!B21*1000-'ANT Dashboard'!D8 -> -1 | C30: ='ARR Monthly'!B22*1000-'ANT Dashboard'!E8 -> 5 | D30: ='ARR Monthly'!B23*1000-'ANT Dashboard'!F8 -> 0 | E30: ='ARR Monthly'!B24*1000-'ANT Dashboard'!G8 -> 0 | F30: ='ARR Monthly'!B25*1000-'ANT Dashboard'!L8 -> 4 | Q30: =IF(MAX(MAX(B30:F30),-MIN(B30:F30))<=10,"OK","GAP") -> OK | R30: Q2-26 and FY26E: $Bn shown to 2 decimals, so up to ~5-10 US$ M rounding
A32: Compute Reconciliation (US$ M) | B32: 2026E | C32: 2027E | D32: 2028E | E32: 2029E | F32: 2030E | G32: 2026-30E | Q32: Status | R32: Note (source-level gap)
A33: P&L + ROU + AMD - commitment-basis spend | B33: ='Compute Reconciliation'!B3+'Compute Reconciliation'!B4+'Compute Reconciliation'!B5-'Compute Reconciliation'!B6 -> 0 | C33: ='Compute Reconciliation'!C3+'Compute Reconciliation'!C4+'Compute Reconciliation'!C5-'Compute Reconciliation'!C6 -> 0 | D33: ='Compute Reconciliation'!D3+'Compute Reconciliation'!D4+'Compute Reconciliation'!D5-'Compute Reconciliation'!D6 -> -1 | E33: ='Compute Reconciliation'!E3+'Compute Reconciliation'!E4+'Compute Reconciliation'!E5-'Compute Reconciliation'!E6 -> 0 | F33: ='Compute Reconciliation'!F3+'Compute Reconciliation'!F4+'Compute Reconciliation'!F5-'Compute Reconciliation'!F6 -> 0 | G33: ='Compute Reconciliation'!G3+'Compute Reconciliation'!G4+'Compute Reconciliation'!G5-'Compute Reconciliation'!G6 -> 0 | Q33: =IF(MAX(MAX(B33:G33),-MIN(B33:G33))<=2,"OK","GAP") -> OK
A34: Commitment-basis spend + lease interest - spend incl. interest | B34: ='Compute Reconciliation'!B6+'Compute Reconciliation'!B7-'Compute Reconciliation'!B8 -> 0 | C34: ='Compute Reconciliation'!C6+'Compute Reconciliation'!C7-'Compute Reconciliation'!C8 -> 0 | D34: ='Compute Reconciliation'!D6+'Compute Reconciliation'!D7-'Compute Reconciliation'!D8 -> 0 | E34: ='Compute Reconciliation'!E6+'Compute Reconciliation'!E7-'Compute Reconciliation'!E8 -> 0 | F34: ='Compute Reconciliation'!F6+'Compute Reconciliation'!F7-'Compute Reconciliation'!F8 -> 0 | G34: ='Compute Reconciliation'!G6+'Compute Reconciliation'!G7-'Compute Reconciliation'!G8 -> 0 | Q34: =IF(MAX(MAX(B34:G34),-MIN(B34:G34))<=2,"OK","GAP") -> OK
A35: Sum of 2026E-2030E - 2026-30E column | G35: =SUM('Compute Reconciliation'!B6:'Compute Reconciliation'!F6)-'Compute Reconciliation'!G6 -> 1 | Q35: =IF(MAX(MAX(G35:G35),-MIN(G35:G35))<=3,"OK","GAP") -> OK
A36: Row sum 2026E-2030E - 2026-30E (P&L basis) | G36: =SUM('Compute Reconciliation'!B3:'Compute Reconciliation'!F3)-'Compute Reconciliation'!G3 -> -1 | Q36: =IF(MAX(MAX(G36:G36),-MIN(G36:G36))<=3,"OK","GAP") -> OK
A37: Row sum 2026E-2030E - 2026-30E (Broadcom ROU) | G37: =SUM('Compute Reconciliation'!B4:'Compute Reconciliation'!F4)-'Compute Reconciliation'!G4 -> 0 | Q37: =IF(MAX(MAX(G37:G37),-MIN(G37:G37))<=3,"OK","GAP") -> OK
A38: Row sum 2026E-2030E - 2026-30E (AMD) | G38: =SUM('Compute Reconciliation'!B5:'Compute Reconciliation'!F5)-'Compute Reconciliation'!G5 -> 1 | Q38: =IF(MAX(MAX(G38:G38),-MIN(G38:G38))<=3,"OK","GAP") -> OK
A39: Row sum 2026E-2030E - 2026-30E (lease interest) | G39: =SUM('Compute Reconciliation'!B7:'Compute Reconciliation'!F7)-'Compute Reconciliation'!G7 -> -1 | Q39: =IF(MAX(MAX(G39:G39),-MIN(G39:G39))<=3,"OK","GAP") -> OK
A40: Row sum 2026E-2030E - 2026-30E (spend incl. interest) | G40: =SUM('Compute Reconciliation'!B8:'Compute Reconciliation'!F8)-'Compute Reconciliation'!G8 -> 0 | Q40: =IF(MAX(MAX(G40:G40),-MIN(G40:G40))<=3,"OK","GAP") -> OK
A41: Row sum 2026E-2030E - 2026-30E (beyond-S-1 assumptions) | G41: =SUM('Compute Reconciliation'!B9:'Compute Reconciliation'!F9)-'Compute Reconciliation'!G9 -> 0 | Q41: =IF(MAX(MAX(G41:G41),-MIN(G41:G41))<=3,"OK","GAP") -> OK
A42: Commitment-basis total - press report - difference | G42: ='Compute Reconciliation'!G6-'Compute Reconciliation'!G10-'Compute Reconciliation'!G11 -> 0 | Q42: =IF(MAX(MAX(G42:G42),-MIN(G42:G42))<=0,"OK","GAP") -> OK
A43: Cross-sheet: P&L-basis compute - dashboard compute (annual) | B43: ='Compute Reconciliation'!B3-'ANT Dashboard'!L34 -> 0 | C43: ='Compute Reconciliation'!C3-'ANT Dashboard'!M34 -> 0 | D43: ='Compute Reconciliation'!D3-'ANT Dashboard'!N34 -> 0 | E43: ='Compute Reconciliation'!E3-'ANT Dashboard'!O34 -> 0 | F43: ='Compute Reconciliation'!F3-'ANT Dashboard'!P34 -> 0 | Q43: =IF(MAX(MAX(B43:F43),-MIN(B43:F43))<=0,"OK","GAP") -> OK
A44: Cross-sheet: lease interest - dashboard interest expense (sign flipped) | B44: ='Compute Reconciliation'!B7+'ANT Dashboard'!L18 -> 0 | C44: ='Compute Reconciliation'!C7+'ANT Dashboard'!M18 -> 0 | D44: ='Compute Reconciliation'!D7+'ANT Dashboard'!N18 -> 0 | E44: ='Compute Reconciliation'!E7+'ANT Dashboard'!O18 -> 0 | F44: ='Compute Reconciliation'!F7+'ANT Dashboard'!P18 -> 0 | Q44: =IF(MAX(MAX(B44:F44),-MIN(B44:F44))<=0,"OK","GAP") -> OK
A45: Cross-sheet: beyond-S-1 row - (beyond contracts + renewals + ahead of demand) | B45: ='Compute Reconciliation'!B9-('ANT Dashboard'!L80+'ANT Dashboard'!L78+'ANT Dashboard'!L79) -> 0 | C45: ='Compute Reconciliation'!C9-('ANT Dashboard'!M80+'ANT Dashboard'!M78+'ANT Dashboard'!M79) -> 0 | D45: ='Compute Reconciliation'!D9-('ANT Dashboard'!N80+'ANT Dashboard'!N78+'ANT Dashboard'!N79) -> 0 | E45: ='Compute Reconciliation'!E9-('ANT Dashboard'!O80+'ANT Dashboard'!O78+'ANT Dashboard'!O79) -> 0 | F45: ='Compute Reconciliation'!F9-('ANT Dashboard'!P80+'ANT Dashboard'!P78+'ANT Dashboard'!P79) -> 0 | Q45: =IF(MAX(MAX(B45:F45),-MIN(B45:F45))<=2,"OK","GAP") -> OK
A47: S-1 commitments table (US$ M) | B47: S-1 - expensed - tail | C47: Expensed / S-1 - % | D47: Expensed - model sum 2026E-30E | Q47: Status | R47: Note (source-level gap)
A48: Google | B48: ='Compute Reconciliation'!B15-'Compute Reconciliation'!C15-'Compute Reconciliation'!D15 -> 0 | C48: =('Compute Reconciliation'!C15/'Compute Reconciliation'!B15-'Compute Reconciliation'!E15)*1000 -> -0.22707424 | D48: ='Compute Reconciliation'!C15-(SUM('ANT Dashboard'!L67:'ANT Dashboard'!P67)) -> 0 | Q48: =IF(MAX(MAX(B48:D48),-MIN(B48:D48))<=2,"OK","GAP") -> OK
A49: Amazon | B49: ='Compute Reconciliation'!B16-'Compute Reconciliation'!C16-'Compute Reconciliation'!D16 -> 0 | C49: =('Compute Reconciliation'!C16/'Compute Reconciliation'!B16-'Compute Reconciliation'!E16)*1000 -> -0.3 | D49: ='Compute Reconciliation'!C16-(SUM('ANT Dashboard'!L68:'ANT Dashboard'!P68)) -> 0 | Q49: =IF(MAX(MAX(B49:D49),-MIN(B49:D49))<=2,"OK","GAP") -> OK
A50: Microsoft (2026 increase) | B50: ='Compute Reconciliation'!B17-'Compute Reconciliation'!C17-'Compute Reconciliation'!D17 -> 0 | C50: =('Compute Reconciliation'!C17/'Compute Reconciliation'!B17-'Compute Reconciliation'!E17)*1000 -> -0.046979866 | D50: ='Compute Reconciliation'!C17-(SUM('ANT Dashboard'!L69:'ANT Dashboard'!P69)) -> 0 | Q50: =IF(MAX(MAX(B50:D50),-MIN(B50:D50))<=2,"OK","GAP") -> OK
A51: SpaceXAI | B51: ='Compute Reconciliation'!B18-'Compute Reconciliation'!C18-'Compute Reconciliation'!D18 -> 0 | C51: =('Compute Reconciliation'!C18/'Compute Reconciliation'!B18-'Compute Reconciliation'!E18)*1000 -> 0 | D51: ='Compute Reconciliation'!C18-(SUM('ANT Dashboard'!L70:'ANT Dashboard'!P70)) -> 0 | Q51: =IF(MAX(MAX(B51:D51),-MIN(B51:D51))<=2,"OK","GAP") -> OK
A52: Nscale | B52: ='Compute Reconciliation'!B19-'Compute Reconciliation'!C19-'Compute Reconciliation'!D19 -> 0 | C52: =('Compute Reconciliation'!C19/'Compute Reconciliation'!B19-'Compute Reconciliation'!E19)*1000 -> 0.14798206 | D52: ='Compute Reconciliation'!C19-(SUM('ANT Dashboard'!L71:'ANT Dashboard'!P71)) -> 0 | Q52: =IF(MAX(MAX(B52:D52),-MIN(B52:D52))<=2,"OK","GAP") -> OK
A53: Lambda | B53: ='Compute Reconciliation'!B20-'Compute Reconciliation'!C20-'Compute Reconciliation'!D20 -> 0 | C53: =('Compute Reconciliation'!C20/'Compute Reconciliation'!B20-'Compute Reconciliation'!E20)*1000 -> 0.14043584 | D53: ='Compute Reconciliation'!C20-(SUM('ANT Dashboard'!L72:'ANT Dashboard'!P72)) -> 0 | Q53: =IF(MAX(MAX(B53:D53),-MIN(B53:D53))<=2,"OK","GAP") -> OK
A54: Google / TPU providers 2028-31 (midpoint of $125-150B) | B54: ='Compute Reconciliation'!B21-'Compute Reconciliation'!C21-'Compute Reconciliation'!D21 -> 0 | C54: =('Compute Reconciliation'!C21/'Compute Reconciliation'!B21-'Compute Reconciliation'!E21)*1000 -> 0 | D54: ='Compute Reconciliation'!C21-(SUM('ANT Dashboard'!L73:'ANT Dashboard'!P73)) -> 0 | Q54: =IF(MAX(MAX(B54:D54),-MIN(B54:D54))<=2,"OK","GAP") -> OK
A55: Cloud service agreements signed in 2026 | B55: ='Compute Reconciliation'!B22-'Compute Reconciliation'!C22-'Compute Reconciliation'!D22 -> 0 | C55: =('Compute Reconciliation'!C22/'Compute Reconciliation'!B22-'Compute Reconciliation'!E22)*1000 -> -0.10217727 | D55: ='Compute Reconciliation'!C22-(SUM('ANT Dashboard'!L66:'ANT Dashboard'!P66)) -> 0 | Q55: =IF(MAX(MAX(B55:D55),-MIN(B55:D55))<=2,"OK","GAP") -> OK
A56: Commitments at Dec 31, 2025 (Note 13; from Jan-26) | B56: ='Compute Reconciliation'!B23-'Compute Reconciliation'!C23-'Compute Reconciliation'!D23 -> 0 | C56: =('Compute Reconciliation'!C23/'Compute Reconciliation'!B23-'Compute Reconciliation'!E23)*1000 -> -0.42625415 | D56: ='Compute Reconciliation'!C23-(SUM('ANT Dashboard'!L74:'ANT Dashboard'!P74)) -> 3500 | Q56: =IF(MAX(MAX(B56:D56),-MIN(B56:D56))<=2,"OK","GAP") -> GAP | R56: expensed counts from Jan-26; dashboard Note 13 line starts in 3Q26E (1H26 sits in actuals)
A57: Broadcom TPU leases (rent excl. interest; amortization) | B57: ='Compute Reconciliation'!B24-'Compute Reconciliation'!C24-'Compute Reconciliation'!D24 -> 0 | C57: =('Compute Reconciliation'!C24/'Compute Reconciliation'!B24-'Compute Reconciliation'!E24)*1000 -> 0.25558313 | D57: ='Compute Reconciliation'!C24-(SUM('ANT Dashboard'!L75:'ANT Dashboard'!P75)) -> 400 | Q57: =IF(MAX(MAX(B57:D57),-MIN(B57:D57))<=2,"OK","GAP") -> GAP | R57: expensed = S-1 less 2030E lease liability (61,376); amortization rows sum to 99,424
A58: AMD Helios hardware (lower bound; depreciation) | B58: ='Compute Reconciliation'!B25-'Compute Reconciliation'!C25-'Compute Reconciliation'!D25 -> 0 | C58: =('Compute Reconciliation'!C25/'Compute Reconciliation'!B25-'Compute Reconciliation'!E25)*1000 -> -0.35 | D58: ='Compute Reconciliation'!C25-(SUM('ANT Dashboard'!L77:'ANT Dashboard'!P77)) -> 1 | Q58: =IF(MAX(MAX(B58:D58),-MIN(B58:D58))<=2,"OK","GAP") -> OK
A59: Total S-1 compute commitments | B59: ='Compute Reconciliation'!B26-'Compute Reconciliation'!C26-'Compute Reconciliation'!D26 -> 0 | C59: =('Compute Reconciliation'!C26/'Compute Reconciliation'!B26-'Compute Reconciliation'!E26)*1000 -> -0.0099858496 | Q59: =IF(MAX(MAX(B59:C59),-MIN(B59:C59))<=2,"OK","GAP") -> OK
A60: Counterparties - cloud service agreements (S-1 / expensed / tail) | B60: =SUM('Compute Reconciliation'!B15:'Compute Reconciliation'!B21)-'Compute Reconciliation'!B22 -> 0 | C60: =SUM('Compute Reconciliation'!C15:'Compute Reconciliation'!C21)-'Compute Reconciliation'!C22 -> 0 | D60: =SUM('Compute Reconciliation'!D15:'Compute Reconciliation'!D21)-'Compute Reconciliation'!D22 -> 0 | Q60: =IF(MAX(MAX(B60:D60),-MIN(B60:D60))<=2,"OK","GAP") -> OK
A61: Four categories - total S-1 commitments (S-1 / expensed / tail) | B61: ='Compute Reconciliation'!B22+'Compute Reconciliation'!B23+'Compute Reconciliation'!B24+'Compute Reconciliation'!B25-'Compute Reconciliation'!B26 -> 0 | C61: ='Compute Reconciliation'!C22+'Compute Reconciliation'!C23+'Compute Reconciliation'!C24+'Compute Reconciliation'!C25-'Compute Reconciliation'!C26 -> 1 | D61: ='Compute Reconciliation'!D22+'Compute Reconciliation'!D23+'Compute Reconciliation'!D24+'Compute Reconciliation'!D25-'Compute Reconciliation'!D26 -> -1 | Q61: =IF(MAX(MAX(B61:D61),-MIN(B61:D61))<=2,"OK","GAP") -> OK
A63: Column "Expensed / S-1 - %" is shown x1,000 (tolerance 2 = 0.2pp).
