Workbook

Sheet Summary
A1: New Street Research “$4tn AI capex in 2030” (18-Sep-2026) vs Capstone — summary
A2: NSR (Pierre Ferragu, Antoine Chkaiban, Benjamin Harwood, Peter Vogel) raised its 2030 AI capex forecast from ~$3.1tn to $4.15tn. This workbook transcribes the note with live formulas (NSR_* sheets), lays the Capstone series beside it (House) and compares them line by line (Comparison). This page links to those cells.
A4: WHAT NSR SAYS
A5: • $4.15tn of AI infrastructure capex in 2030 (from $584bn in 2025, 48% CAGR): XPUs $1.70tn (41%), other equipment & buildings $1.02tn (24%), networking $465bn, DRAM & NAND $423bn, other server content $373bn, CPUs $168bn. Increase is volume-driven; ~275 GW of installed AI capacity in 2030 (from ~225 GW).
A6: • Memory share of AI infrastructure keeps rising even as prices normalise: HBM $560bn in 2030 (33% of XPU spend, GM ~76%), DRAM $241bn, NAND $182bn.
A7: • Hyperscalers: group capex $8.7tn cumulative 2026-30, FCF negative through 2029 (trough −$486bn in 2028), positive again in 2030; OCF $8.0tn vs consensus $6tn on a 24% revenue CAGR and 77% incremental OCF margin.
A8: • Funding: $16.5tn of datacenter capex 2026-30, >75% covered by hyperscaler / tier-2 / neocloud OCF and enterprise self-funding; ~$3.7tn (23%) needs external financing, mostly neoclouds with hyperscaler guarantees; industry leverage ~2.2x 2027 EBITDA.
A10: KEY READS — NSR vs Capstone
A11: 1. Level: NSR is above the house on total AI capex in every year — $584bn vs $396bn in 2025 (+47%), $1,132 vs $902 (2026), $2,190 vs $1,885 (2027), $3,330 vs $2,913 (2028, +14%). The gap narrows because the house grows faster in 2026-27 (+128% / +109% vs NSR +94% / +93%).
A12: 2. 2030: NSR $4.15tn vs the house's July-vintage extension $3.48tn (−16%). Re-based on the current CY28 ($2,913bn) the same growth path gives ~$3.9tn — within ~6% of NSR. The house has no modeled CY29-30 on the current base.
A13: 3. Mix: the house puts more into accelerators (48% → 40% of capex) than NSR (35% → 41%); NSR puts more into shell/buildings early (44% in 2025 vs 36%) and less later (27% vs 36% in 2028). Capex per GW converges on ~$42bn by 2028 (NSR $40-45bn; house $30.5 → $41.9bn).
A14: 4. Memory is the biggest dollar disagreement: HBM 2030 NSR $560bn vs house repriced $283bn (BofA $168bn) — the two agree in 2027 (~$190bn) and diverge after, as NSR keeps HBM compounding at 22-38% into 2029-30 where the house fades price. Ex-HBM DRAM+NAND agree within 6% (2027) and 4% (2030).
... A21: HEADLINE TABLE — 2028 and 2030 (linked to the Comparison sheet; blue Δ = Capstone above NSR, red = below)
A22: Metric | B22: Unit | C22: NSR 2028 | D22: Capstone 2028 | E22: Δ 2028 | F22: NSR 2030 | G22: Capstone 2030 | H22: Δ 2030 | I22: Read
A23: Total AI capex | B23: $bn | C23: =IF(Comparison!F6="","",Comparison!F6) -> 3330 | D23: =IF(Comparison!F7="","",Comparison!F7) -> 2913.1 | E23: =IF(Comparison!F8="","",Comparison!F8) -> -0.1251952 | F23: =IF(Comparison!H6="","",Comparison!H6) -> 4150 | G23: =IF(Comparison!H7="","",Comparison!H7) -> 3481.9 | H23: =IF(Comparison!H8="","",Comparison!H8) -> -0.16098795 | I23: Capstone 2030 is a July-vintage extension; re-based ~$3.9tn.
A24: XPUs / accelerators | B24: $bn | C24: =IF(Comparison!F32="","",Comparison!F32) -> 1252 | D24: =IF(Comparison!F33="","",Comparison!F33) -> 1157.4 | E24: =IF(Comparison!F34="","",Comparison!F34) -> -0.075559105 | F24: =IF(Comparison!H32="","",Comparison!H32) -> 1702 | G24: =IF(Comparison!H33="","",Comparison!H33) -> 1414.2 | H24: =IF(Comparison!H34="","",Comparison!H34) -> -0.16909518 | I24: House chips = designers' revenue incl. HBM.
A25: HBM (Semis MAP repriced) | B25: $bn | C25: =IF(Comparison!F73="","",Comparison!F73) -> 332 | D25: =IF(Comparison!F74="","",Comparison!F74) -> 224 | E25: =IF(Comparison!F75="","",Comparison!F75) -> -0.3253012 | F25: =IF(Comparison!H73="","",Comparison!H73) -> 560 | G25: =IF(Comparison!H74="","",Comparison!H74) -> 283.4 | H25: =IF(Comparison!H75="","",Comparison!H75) -> -0.49392857 | I25: The largest dollar gap; agree in 2027, diverge after.
A26: DRAM ex-HBM + NAND | B26: $bn | C26: =IF(Comparison!F81="","",Comparison!F81) -> 459 | D26: =IF(Comparison!F82="","",Comparison!F82) -> 345.8 | E26: =IF(Comparison!F83="","",Comparison!F83) -> -0.24662309 | F26: =IF(Comparison!H81="","",Comparison!H81) -> 423 | G26: =IF(Comparison!H82="","",Comparison!H82) -> 404.9 | H26: =IF(Comparison!H83="","",Comparison!H83) -> -0.042789598 | I26: Close in 2027 and 2030; house lower in 2028.
A27: Total memory (HBM + DRAM + NAND) | B27: $bn | C27: =IF(Comparison!F89="","",Comparison!F89) -> 791 | D27: =IF(Comparison!F90="","",Comparison!F90) -> 596.5 | E27: =IF(Comparison!F91="","",Comparison!F91) -> -0.24589128 | F27: =IF(Comparison!H89="","",Comparison!H89) -> 983 | G27: =IF(Comparison!H90="","",Comparison!H90) -> 737 | H27: =IF(Comparison!H91="","",Comparison!H91) -> -0.25025432 | I27: House TOTAL CSP memory bill vs NSR sum.
A28: Networking | B28: $bn | C28: =IF(Comparison!F52="","",Comparison!F52) -> 336 | D28: =IF(Comparison!F53="","",Comparison!F53) -> 450.7 | E28: =IF(Comparison!F54="","",Comparison!F54) -> 0.34136905 | F28: =IF(Comparison!H52="","",Comparison!H52) -> 465 | G28: =IF(Comparison!H53="","",Comparison!H53) -> 606.3 | H28: =IF(Comparison!H54="","",Comparison!H54) -> 0.30387097 | I28: Semis MAP line; Bottom_Up build is ~0.65x NSR.
A29: Hyperscaler capex (total) | B29: $bn | C29: =IF(Comparison!F123="","",Comparison!F123) -> 1975 | D29: =IF(Comparison!F124="","",Comparison!F124) -> 1463.3 | E29: =IF(Comparison!F125="","",Comparison!F125) -> -0.25908861 | I29: NSR basket not enumerated; house = big-4 calendar.
A30: Hyperscaler FCF | B30: $bn | C30: =IF(Comparison!F127="","",Comparison!F127) -> -486 | D30: =IF(Comparison!F128="","",Comparison!F128) -> -261.4 | E30: =IF(Comparison!F129="","",Comparison!F129) -> -0.46213992 | I30: House trough earlier and shallower.
A31: AI cloud revenue | B31: $bn | C31: =IF(Comparison!F136="","",Comparison!F136) -> 651 | D31: =IF(Comparison!F137="","",Comparison!F137) -> 627.1 | E31: =IF(Comparison!F138="","",Comparison!F138) -> -0.03671275 | F31: =IF(Comparison!H136="","",Comparison!H136) -> 1511 | G31: =IF(Comparison!H137="","",Comparison!H137) -> 1492 | H31: =IF(Comparison!H138="","",Comparison!H138) -> -0.012574454 | I31: Strongest convergence in the note.
A32: Installed AI GW (chip-content basis) | B32: GW | F32: =IF(Comparison!H98="","",Comparison!H98) -> 275 | G32: =IF(Comparison!H99="","",Comparison!H99) -> 298.7 | H32: =IF(Comparison!H100="","",Comparison!H100) -> 0.086181818 | I32: NSR basis unstated; house chip GW, gross of retirements.
A33: Installed AI GW (facility basis) | B33: GW | F33: =IF(Comparison!H102="","",Comparison!H102) -> 275 | G33: =IF(Comparison!H103="","",Comparison!H103) -> 241.7 | H33: =IF(Comparison!H104="","",Comparison!H104) -> -0.12109091 | I33: Bottom_Up physical facility GW.
A34: Capex per GW | B34: $bn/GW | C34: =IF(Comparison!F110="","",Comparison!F110) -> 42.5 | D34: =IF(Comparison!F111="","",Comparison!F111) -> 41.9 | E34: =IF(Comparison!F112="","",Comparison!F112) -> -0.014117647 | I34: Converging on ~$42bn by 2028.
A36: VENDOR MARKET SHARES ON THE NSR POOLS — 2028 and 2030 (linked to Share_XPU / Share_CPU / Share_Memory; implied $bn = NSR pool × share)
A37: Not additive across blocks: HBM dollars sit inside the XPU figures AND appear as vendor HBM revenue below (NSR p.5 puts HBM inside XPU spending) — summing NVIDIA/Broadcom with SK Hynix/Samsung/Micron double-counts $332bn in 2028 and $560bn in 2030. Capstone-mix shares are house forecasts (EST), not market prints; CY29-30 sit on the July base.
A38: Pool — vendor | C38: Share 2028 | D38: $bn 2028 | F38: Share 2030 | G38: $bn 2030 | I38: Share lens / basis
A39: XPU — NVIDIA | C39: =IF(Share_XPU!F20="","",Share_XPU!F20) -> 0.67732181 | D39: =IF(Share_XPU!F36="","",Share_XPU!F36) -> 848.00691 | F39: =IF(Share_XPU!H20="","",Share_XPU!H20) -> 0.63635721 | G39: =IF(Share_XPU!H36="","",Share_XPU!H36) -> 1083.08 | I39: Capstone designer mix (AI Model CY28; Semis MAP CY30 — the CY28→29 share step is a vintage splice). NSR itself has ~60% in 2030, BofA 68%.
A40: XPU — Broadcom (custom ASIC) | C40: =IF(Share_XPU!F21="","",Share_XPU!F21) -> 0.24587473 | D40: =IF(Share_XPU!F37="","",Share_XPU!F37) -> 307.83516 | F40: =IF(Share_XPU!H21="","",Share_XPU!H21) -> 0.27872446 | G40: =IF(Share_XPU!H37="","",Share_XPU!H37) -> 474.38903 | I40: Capstone mix; BofA 16% in 2030. On NSR's pool this implies more Broadcom revenue than NSR's own $230bn FY28 Broadcom datapoint — see Share_XPU guardrail.
A41: XPU — AMD | C41: =IF(Share_XPU!F22="","",Share_XPU!F22) -> 0.04475162 | D41: =IF(Share_XPU!F38="","",Share_XPU!F38) -> 56.029028 | F41: =IF(Share_XPU!H22="","",Share_XPU!H22) -> 0.048575267 | G41: =IF(Share_XPU!H38="","",Share_XPU!H38) -> 82.675104 | I41: Capstone mix; BofA ~7% in 2030.
A42: XPU — NVIDIA at NSR’s own 60% (2030 only) | C42: =IF(Share_XPU!F29="","",Share_XPU!F29) | D42: =IF(Share_XPU!F42="","",Share_XPU!F42) | F42: =IF(Share_XPU!H29="","",Share_XPU!H29) -> 0.6 | G42: =IF(Share_XPU!H42="","",Share_XPU!H42) -> 1021.2 | I42: NSR p.3: ~$1.0tn of NVIDIA XPU revenue in 2030.
A43: Server CPU — Intel | C43: =IF(Share_CPU!F47="","",Share_CPU!F47) -> 0.32902468 | D43: =IF(Share_CPU!F53="","",Share_CPU!F53) -> 38.495887 | F43: =IF(Share_CPU!H47="","",Share_CPU!H47) -> 0.3093679 | G43: =IF(Share_CPU!H53="","",Share_CPU!H53) -> 62.492316 | I43: Silicon anchor build applied to NSR's total CPU pool: Intel on BofA's printed path ($14.1bn CY25 → $46.3bn CY30E).
A44: Server CPU — AMD | C44: =IF(Share_CPU!F48="","",Share_CPU!F48) -> 0.28397963 | D44: =IF(Share_CPU!F54="","",Share_CPU!F54) -> 33.225617 | F44: =IF(Share_CPU!H48="","",Share_CPU!H48) -> 0.33409061 | G44: =IF(Share_CPU!H54="","",Share_CPU!H54) -> 67.486302 | I44: Segment prints to 2026, UBS 05-21 on its own TAM in 2030 (29% × $173bn ≈ $50bn); AMD's own target is >50% of $220bn.
A45: Server CPU — NVIDIA (Grace/Vera) | C45: =IF(Share_CPU!F49="","",Share_CPU!F49) -> 0.23893459 | D45: =IF(Share_CPU!F55="","",Share_CPU!F55) -> 27.955347 | F45: =IF(Share_CPU!H49="","",Share_CPU!H49) -> 0.15769077 | G45: =IF(Share_CPU!H55="","",Share_CPU!H55) -> 31.853535 | I45: CHIP basis: Bernstein units × $4k ASP (≈ Grace TTM >$5bn in 2025). Management's ‘$20bn demand / more than double in FY28’ is a systems-basis reading, kept as a scenario.
A46: Server CPU — captive Arm + Hygon + others | C46: =IF(Share_CPU!F50="","",Share_CPU!F50) -> 0.1480611 | D46: =IF(Share_CPU!F56="","",Share_CPU!F56) -> 17.323149 | F46: =IF(Share_CPU!H50="","",Share_CPU!H50) -> 0.19885073 | G46: =IF(Share_CPU!H56="","",Share_CPU!H56) -> 40.167847 | I46: Bernstein units × ~$1.2k EST (±$0.5k moves the line ±42%).
A47: HBM — SK Hynix | C47: =IF(Share_Memory!F18="","",Share_Memory!F18) -> 0.42 | D47: =IF(Share_Memory!F50="","",Share_Memory!F50) -> 139.44 | F47: =IF(Share_Memory!H18="","",Share_Memory!H18) -> 0.42 | G47: =IF(Share_Memory!H50="","",Share_Memory!H50) -> 235.2 | I47: JPM SALES-share path (60% → 42% by 2028) held at 2028; if JPM's −6pp/yr slope continues, 30% / $168bn in 2030 (Share_Memory scenario). Capstone Semis MAP has 47% in 2028.
A48: HBM — Samsung | C48: =IF(Share_Memory!F19="","",Share_Memory!F19) -> 0.38 | D48: =IF(Share_Memory!F51="","",Share_Memory!F51) -> 126.16 | F48: =IF(Share_Memory!H19="","",Share_Memory!H19) -> 0.38 | G48: =IF(Share_Memory!H51="","",Share_Memory!H51) -> 212.8 | I48: JPM 20% → 38% held; slope-continued 50% / $280bn in 2030. UBS's ‘41% in 2027’ is a BIT share. Capstone 28%.
A49: HBM — Micron | C49: =IF(Share_Memory!F20="","",Share_Memory!F20) -> 0.2 | D49: =IF(Share_Memory!F52="","",Share_Memory!F52) -> 66.4 | F49: =IF(Share_Memory!H20="","",Share_Memory!H20) -> 0.2 | G49: =IF(Share_Memory!H52="","",Share_Memory!H52) -> 112 | I49: JPM ~20% flat; Capstone 25%; UBS 20-21% (bits).
A50: Server DRAM — Samsung | C50: =IF(Share_Memory!F34="","",Share_Memory!F34) -> 0.35939343 | D50: =IF(Share_Memory!F58="","",Share_Memory!F58) -> 98.114406 | F50: =IF(Share_Memory!H34="","",Share_Memory!H34) -> 0.35939343 | G50: =IF(Share_Memory!H58="","",Share_Memory!H58) -> 86.613816 | I50: DRAM bit-supply share (memory bible), held from 2028 — proxy for server-DRAM value share.
A51: Server DRAM — SK Hynix | C51: =IF(Share_Memory!F35="","",Share_Memory!F35) -> 0.28828981 | D51: =IF(Share_Memory!F59="","",Share_Memory!F59) -> 78.703117 | F51: =IF(Share_Memory!H35="","",Share_Memory!H35) -> 0.28828981 | G51: =IF(Share_Memory!H59="","",Share_Memory!H59) -> 69.477843 | I51: Bit share.
A52: Server DRAM — Micron | C52: =IF(Share_Memory!F36="","",Share_Memory!F36) -> 0.22847515 | D52: =IF(Share_Memory!F60="","",Share_Memory!F60) -> 62.373715 | F52: =IF(Share_Memory!H36="","",Share_Memory!H36) -> 0.22847515 | G52: =IF(Share_Memory!H60="","",Share_Memory!H60) -> 55.062511 | I52: Bit share.
A53: Server DRAM — CXMT | C53: =IF(Share_Memory!F37="","",Share_Memory!F37) -> 0.10783488 | D53: =IF(Share_Memory!F61="","",Share_Memory!F61) -> 29.438922 | F53: =IF(Share_Memory!H37="","",Share_Memory!H37) -> 0.10783488 | G53: =IF(Share_Memory!H61="","",Share_Memory!H61) -> 25.988206 | I53: Bit share overstates CXMT in servers (Wells: ~8% revenue share, DDR4/LPDDR4-heavy); at a ~3% server share the 2028 figure would be ~$8bn (Share_Memory alternative row).
A54: Server NAND — Samsung | C54: =IF(Share_Memory!F42="","",Share_Memory!F42) -> 0.351 | D54: =IF(Share_Memory!F64="","",Share_Memory!F64) -> 65.286 | F54: =IF(Share_Memory!H42="","",Share_Memory!H42) -> 0.351 | G54: =IF(Share_Memory!H64="","",Share_Memory!H64) -> 63.882 | I54: TrendForce 2Q26 enterprise-SSD revenue share (35%), held flat.
A55: Server NAND — SK Hynix + Solidigm | C55: =IF(Share_Memory!F43="","",Share_Memory!F43) -> 0.211 | D55: =IF(Share_Memory!F65="","",Share_Memory!F65) -> 39.246 | F55: =IF(Share_Memory!H43="","",Share_Memory!H43) -> 0.211 | G55: =IF(Share_Memory!H65="","",Share_Memory!H65) -> 38.402 | I55: eSSD share 21% (2Q26).
A56: Server NAND — Micron | C56: =IF(Share_Memory!F44="","",Share_Memory!F44) -> 0.171 | D56: =IF(Share_Memory!F66="","",Share_Memory!F66) -> 31.806 | F56: =IF(Share_Memory!H44="","",Share_Memory!H44) -> 0.171 | G56: =IF(Share_Memory!H66="","",Share_Memory!H66) -> 31.122 | I56: eSSD share 17% (2Q26).
A57: Server NAND — Kioxia | C57: =IF(Share_Memory!F45="","",Share_Memory!F45) -> 0.11 | D57: =IF(Share_Memory!F67="","",Share_Memory!F67) -> 20.46 | F57: =IF(Share_Memory!H45="","",Share_Memory!H45) -> 0.11 | G57: =IF(Share_Memory!H67="","",Share_Memory!H67) -> 20.02 | I57: eSSD share 11% (2Q26; TrendForce via Jefferies).
A59: Colour code: blue numbers = inputs as printed / pasted; black = formulas; green = links. Sheet order: Summary → Comparison → Share_XPU → Share_CPU → Share_Memory → NSR_Capex → NSR_Memory → NSR_HyperPL → NSR_Funding → NSR_Datapoints → House → README (sources, basis warnings).

Sheet Comparison
A1: NSR (18-Sep-2026) vs Capstone — side by side, 2025-2030
A2: Each metric has three rows: NSR (linked from the NSR sheets) / Capstone (linked from House) / Δ = Capstone ÷ NSR − 1 (blue = Capstone above NSR, red = below). Capstone CY29-30 come from July-vintage extensions (stale base) or are blank. Read the basis note before quoting a delta.
A4: Metric | B4: Series | C4: 2025 | D4: 2026 | E4: 2027 | F4: 2028 | G4: 2029 | H4: 2030 | I4: Basis / how to read
A5: 1. THE HEADLINE — total AI capex, all buyers
A6: Total AI capex ($bn) | B6: NSR | C6: =IF(NSR_Capex!C12="","",NSR_Capex!C12) -> 584 | D6: =IF(NSR_Capex!D12="","",NSR_Capex!D12) -> 1132 | E6: =IF(NSR_Capex!E12="","",NSR_Capex!E12) -> 2190 | F6: =IF(NSR_Capex!F12="","",NSR_Capex!F12) -> 3330 | G6: =IF(NSR_Capex!G12="","",NSR_Capex!G12) -> 3810 | H6: =IF(NSR_Capex!H12="","",NSR_Capex!H12) -> 4150 | I6: NSR p.4 total (all buyers). Capstone CY25-28 = AI Model Capex Total (31-Aug, all players); CY29-30 = Semis MAP v11 scenario extension on the JULY base (CY28 2,588 vs current 2,913) — re-based on the current CY28 the CY29-30 house path would be ~$3.4tn / ~$3.9tn. Read: NSR is ABOVE the house in every year — +47% in 2025 ($584bn vs $396bn), narrowing to +14% in 2028 ($3,330bn vs $2,913bn) because the house grows faster in 2026-27. In 2030 NSR $4.15tn vs the stale house extension $3.48tn (−16%); on the re-based ~$3.9tn the gap is ~6%.
B7: Capstone | C7: =IF(House!E6="","",House!E6) -> 396.3 | D7: =IF(House!F6="","",House!F6) -> 901.6 | E7: =IF(House!G6="","",House!G6) -> 1885.4 | F7: =IF(House!H6="","",House!H6) -> 2913.1 | G7: =IF(House!I28="","",House!I28) -> 3054.3 | H7: =IF(House!J28="","",House!J28) -> 3481.9
B8: Δ Capstone vs NSR | C8: =IF(OR(C6="",C7=""),"",IFERROR(C7/C6-1,"")) -> -0.32140411 | D8: =IF(OR(D6="",D7=""),"",IFERROR(D7/D6-1,"")) -> -0.20353357 | E8: =IF(OR(E6="",E7=""),"",IFERROR(E7/E6-1,"")) -> -0.13908676 | F8: =IF(OR(F6="",F7=""),"",IFERROR(F7/F6-1,"")) -> -0.1251952 | G8: =IF(OR(G6="",G7=""),"",IFERROR(G7/G6-1,"")) -> -0.19834646 | H8: =IF(OR(H6="",H7=""),"",IFERROR(H7/H6-1,"")) -> -0.16098795
A10: Total AI capex — y/y growth | B10: NSR | C10: =IF(NSR_Capex!C22="","",NSR_Capex!C22) | D10: =IF(NSR_Capex!D22="","",NSR_Capex!D22) -> 0.93996569 | E10: =IF(NSR_Capex!E22="","",NSR_Capex!E22) -> 0.93899204 | F10: =IF(NSR_Capex!F22="","",NSR_Capex!F22) -> 0.51801186 | G10: =IF(NSR_Capex!G22="","",NSR_Capex!G22) -> 0.14328627 | H10: =IF(NSR_Capex!H22="","",NSR_Capex!H22) -> 0.089595376 | I10: House 2026 +128% / 2027 +109% / 2028 +54% vs NSR +94% / +93% / +52% / +14% / +9%. Same 2028 deceleration; house 2027 is the steeper year.
B11: Capstone | C11: =IF(House!E11="","",House!E11) -> 0.69431381 | D11: =IF(House!F11="","",House!F11) -> 1.2750442 | E11: =IF(House!G11="","",House!G11) -> 1.0911713 | F11: =IF(House!H11="","",House!H11) -> 0.54508327
B12: Δ Capstone vs NSR | C12: =IF(OR(C10="",C11=""),"",IFERROR(C11/C10-1,"")) | D12: =IF(OR(D10="",D11=""),"",IFERROR(D11/D10-1,"")) -> 0.35647946 | E12: =IF(OR(E10="",E11=""),"",IFERROR(E11/E10-1,"")) -> 0.16206656 | F12: =IF(OR(F10="",F11=""),"",IFERROR(F11/F10-1,"")) -> 0.052260224 | G12: =IF(OR(G10="",G11=""),"",IFERROR(G11/G10-1,"")) | H12: =IF(OR(H10="",H11=""),"",IFERROR(H11/H10-1,""))
A14: Cumulative AI capex ($bn) — NSR 2026-30 in the 2030 column; Capstone 2026-28 in the 2028 column | B14: NSR | H14: =IF(NSR_Capex!H36="","",NSR_Capex!H36) -> 14606 | I14: NSR 2026-30 cumulative $14.6tn AI (inside a $16.5tn total DC figure). House 2026-28 alone = $5.7tn on the current model (NSR 2026-28 = $6.65tn). No house cumulative to 2030 on the current base.
B15: Capstone | F15: =IF(House!H23="","",House!H23) -> 5700.1
B16: Δ Capstone vs NSR | C16: =IF(OR(C14="",C15=""),"",IFERROR(C15/C14-1,"")) | D16: =IF(OR(D14="",D15=""),"",IFERROR(D15/D14-1,"")) | E16: =IF(OR(E14="",E15=""),"",IFERROR(E15/E14-1,"")) | F16: =IF(OR(F14="",F15=""),"",IFERROR(F15/F14-1,"")) | G16: =IF(OR(G14="",G15=""),"",IFERROR(G15/G14-1,"")) | H16: =IF(OR(H14="",H15=""),"",IFERROR(H15/H14-1,""))
A18: 2. WHO SPENDS — hyperscalers vs the rest
A19: Hyperscaler capex, total incl. non-AI ($bn) | B19: NSR | C19: =IF(NSR_HyperPL!C33="","",NSR_HyperPL!C33) -> 415 | D19: =IF(NSR_HyperPL!D33="","",NSR_HyperPL!D33) -> 795 | E19: =IF(NSR_HyperPL!E33="","",NSR_HyperPL!E33) -> 1384 | F19: =IF(NSR_HyperPL!F33="","",NSR_HyperPL!F33) -> 1975 | G19: =IF(NSR_HyperPL!G33="","",NSR_HyperPL!G33) -> 2181 | H19: =IF(NSR_HyperPL!H33="","",NSR_HyperPL!H33) -> 2387 | I19: NSR p.7 group capex, basket not enumerated. Capstone = MSFT+AMZN+GOOG+META official models (calendar). NSR 2027 $1,384bn vs house big-4 $1,098bn: NSR is ~26% above on a basket that probably includes ORCL and possibly others.
B20: Capstone | C20: =IF(House!E20="","",House!E20) -> 410.1 | D20: =IF(House!F20="","",House!F20) -> 738.9 | E20: =IF(House!G20="","",House!G20) -> 1097.8 | F20: =IF(House!H20="","",House!H20) -> 1425.1
B21: Δ Capstone vs NSR | C21: =IF(OR(C19="",C20=""),"",IFERROR(C20/C19-1,"")) -> -0.011807229 | D21: =IF(OR(D19="",D20=""),"",IFERROR(D20/D19-1,"")) -> -0.070566038 | E21: =IF(OR(E19="",E20=""),"",IFERROR(E20/E19-1,"")) -> -0.20679191 | F21: =IF(OR(F19="",F20=""),"",IFERROR(F20/F19-1,"")) -> -0.27843038 | G21: =IF(OR(G19="",G20=""),"",IFERROR(G20/G19-1,"")) | H21: =IF(OR(H19="",H20=""),"",IFERROR(H20/H19-1,""))
A23: Hyperscaler AI capex ($bn) | B23: NSR | C23: =IF(NSR_HyperPL!C42="","",NSR_HyperPL!C42) -> 290 | D23: =IF(NSR_HyperPL!D42="","",NSR_HyperPL!D42) -> 653.75 | E23: =IF(NSR_HyperPL!E42="","",NSR_HyperPL!E42) -> 1224.3875 | F23: =IF(NSR_HyperPL!F42="","",NSR_HyperPL!F42) -> 1794.6379 | G23: =IF(NSR_HyperPL!G42="","",NSR_HyperPL!G42) -> 1977.1908 | H23: =IF(NSR_HyperPL!H42="","",NSR_HyperPL!H42) -> 2156.6956 | I23: NSR implied = group capex − non-AI ($125bn +13% p.a., NSR's own comment). Capstone = AI Model hyperscaler AI bottom-up (big-4). House is above NSR in 2025-26 (+16% / +4%) and below from 2027 (−8%) and 2028 (−21%); by 2028 both put ~all of the growth in AI.
B24: Capstone | C24: =IF(House!E15="","",House!E15) -> 336.4 | D24: =IF(House!F15="","",House!F15) -> 681.9 | E24: =IF(House!G15="","",House!G15) -> 1125.5 | F24: =IF(House!H15="","",House!H15) -> 1425.1
B25: Δ Capstone vs NSR | C25: =IF(OR(C23="",C24=""),"",IFERROR(C24/C23-1,"")) -> 0.16 | D25: =IF(OR(D23="",D24=""),"",IFERROR(D24/D23-1,"")) -> 0.043059273 | E25: =IF(OR(E23="",E24=""),"",IFERROR(E24/E23-1,"")) -> -0.080764872 | F25: =IF(OR(F23="",F24=""),"",IFERROR(F24/F23-1,"")) -> -0.20591222 | G25: =IF(OR(G23="",G24=""),"",IFERROR(G24/G23-1,"")) | H25: =IF(OR(H23="",H24=""),"",IFERROR(H24/H23-1,""))
A27: Non-hyperscaler share of AI capex | B27: NSR | H27: =IFERROR((NSR_Funding!B7+NSR_Funding!B8)/NSR_Funding!B10,"") -> 0.47878788 | I27: NSR: cumulative 2026-30, neocloud $6.5tn + enterprise/gov $1.4tn = 48% of $16.5tn (neocloud alone 39%). Capstone: other players (ORCL, CRWV, SpaceX, labs, sovereign) = 24% of 2026 → 40% of 2027 → 51% of 2028 AI capex. Both houses agree the non-hyperscaler half is where the funding question lives.
B28: Capstone | C28: =IF(House!E22="","",House!E22) -> 0.15089579 | D28: =IF(House!F22="","",House!F22) -> 0.24367791 | E28: =IF(House!G22="","",House!G22) -> 0.40304445 | F28: =IF(House!H22="","",House!H22) -> 0.51079606
B29: Δ Capstone vs NSR | C29: =IF(OR(C27="",C28=""),"",IFERROR(C28/C27-1,"")) | D29: =IF(OR(D27="",D28=""),"",IFERROR(D28/D27-1,"")) | E29: =IF(OR(E27="",E28=""),"",IFERROR(E28/E27-1,"")) | F29: =IF(OR(F27="",F28=""),"",IFERROR(F28/F27-1,"")) | G29: =IF(OR(G27="",G28=""),"",IFERROR(G28/G27-1,"")) | H29: =IF(OR(H27="",H28=""),"",IFERROR(H28/H27-1,""))
A31: 3. WHERE IT GOES — component mix
A32: XPUs / accelerators ($bn) | B32: NSR | C32: =IF(NSR_Capex!C5="","",NSR_Capex!C5) -> 205 | D32: =IF(NSR_Capex!D5="","",NSR_Capex!D5) -> 408 | E32: =IF(NSR_Capex!E5="","",NSR_Capex!E5) -> 782 | F32: =IF(NSR_Capex!F5="","",NSR_Capex!F5) -> 1252 | G32: =IF(NSR_Capex!G5="","",NSR_Capex!G5) -> 1517 | H32: =IF(NSR_Capex!H5="","",NSR_Capex!H5) -> 1702 | I32: NSR XPUs (incl. HBM) vs Capstone chips = designers' revenue incl. HBM (AI Model CY25-28; Semis MAP extension CY29-30). Capstone is only 2-8% below NSR on XPUs while it is 12-32% below on total capex — i.e. the house puts a LARGER share of each capex dollar into the accelerator than NSR does.
B33: Capstone | C33: =IF(House!E7="","",House!E7) -> 190.2 | D33: =IF(House!F7="","",House!F7) -> 399.9 | E33: =IF(House!G7="","",House!G7) -> 767 | F33: =IF(House!H7="","",House!H7) -> 1157.4 | G33: =IF(House!I31="","",House!I31) -> 1240.6 | H33: =IF(House!J31="","",House!J31) -> 1414.2
B34: Δ Capstone vs NSR | C34: =IF(OR(C32="",C33=""),"",IFERROR(C33/C32-1,"")) -> -0.072195122 | D34: =IF(OR(D32="",D33=""),"",IFERROR(D33/D32-1,"")) -> -0.019852941 | E34: =IF(OR(E32="",E33=""),"",IFERROR(E33/E32-1,"")) -> -0.019181586 | F34: =IF(OR(F32="",F33=""),"",IFERROR(F33/F32-1,"")) -> -0.075559105 | G34: =IF(OR(G32="",G33=""),"",IFERROR(G33/G32-1,"")) -> -0.18220171 | H34: =IF(OR(H32="",H33=""),"",IFERROR(H33/H32-1,"")) -> -0.16909518
A36: XPUs as % of total AI capex | B36: NSR | C36: =IF(NSR_Capex!C25="","",NSR_Capex!C25) -> 0.3516295 | D36: =IF(NSR_Capex!D25="","",NSR_Capex!D25) -> 0.36074271 | E36: =IF(NSR_Capex!E25="","",NSR_Capex!E25) -> 0.35658915 | F36: =IF(NSR_Capex!F25="","",NSR_Capex!F25) -> 0.37608892 | G36: =IF(NSR_Capex!G25="","",NSR_Capex!G25) -> 0.39858119 | H36: =IF(NSR_Capex!H25="","",NSR_Capex!H25) -> 0.41041717 | I36: NSR 35% → 38% (2028) → 41% (2030), rising. Capstone 48% → 40% (CY28), falling as the networking/CPU/memory bucket grows 16% → 25%. House share is higher every year but the trajectories cross — the sharpest structural disagreement in this comparison.
B37: Capstone | C37: =IF(House!E12="","",House!E12) -> 0.47993944 | D37: =IF(House!F12="","",House!F12) -> 0.44354481 | E37: =IF(House!G12="","",House!G12) -> 0.40681023 | F37: =IF(House!H12="","",House!H12) -> 0.39730871
B38: Δ Capstone vs NSR | C38: =IF(OR(C36="",C37=""),"",IFERROR(C37/C36-1,"")) -> 0.36490094 | D38: =IF(OR(D36="",D37=""),"",IFERROR(D37/D36-1,"")) -> 0.2295323 | E38: =IF(OR(E36="",E37=""),"",IFERROR(E37/E36-1,"")) -> 0.14083737 | F38: =IF(OR(F36="",F37=""),"",IFERROR(F37/F36-1,"")) -> 0.056422278 | G38: =IF(OR(G36="",G37=""),"",IFERROR(G37/G36-1,"")) | H38: =IF(OR(H36="",H37=""),"",IFERROR(H37/H36-1,""))
A40: NVDA share of accelerator value | B40: NSR | H40: =NSR_Datapoints!B21 -> 0.6 | I40: NSR: ~60% in 2030 (~$1.0tn NVDA of $1.7tn). Capstone: 68% CY28 (AI Model), 64% CY30 (Semis MAP). House is 4-8pp more NVDA-heavy at the end of the decade; BofA has 68% CY30.
B41: Capstone | C41: =IF(House!E70="","",House!E70) -> 0.83491062 | D41: =IF(House!F70="","",House!F70) -> 0.77969492 | E41: =IF(House!G70="","",House!G70) -> 0.75436767 | F41: =IF(House!H70="","",House!H70) -> 0.67738034 | G41: =IF(House!I35="","",House!I35) -> 0.64106078 | H41: =IF(House!J35="","",House!J35) -> 0.63640221
B42: Δ Capstone vs NSR | C42: =IF(OR(C40="",C41=""),"",IFERROR(C41/C40-1,"")) | D42: =IF(OR(D40="",D41=""),"",IFERROR(D41/D40-1,"")) | E42: =IF(OR(E40="",E41=""),"",IFERROR(E41/E40-1,"")) | F42: =IF(OR(F40="",F41=""),"",IFERROR(F41/F40-1,"")) | G42: =IF(OR(G40="",G41=""),"",IFERROR(G41/G40-1,"")) | H42: =IF(OR(H40="",H41=""),"",IFERROR(H41/H40-1,"")) -> 0.060670344
A44: CPUs — AI slice ($bn) | B44: NSR | C44: =IF(NSR_Capex!C6="","",NSR_Capex!C6) -> 6 | D44: =IF(NSR_Capex!D6="","",NSR_Capex!D6) -> 27 | E44: =IF(NSR_Capex!E6="","",NSR_Capex!E6) -> 56 | F44: =IF(NSR_Capex!F6="","",NSR_Capex!F6) -> 90 | G44: =IF(NSR_Capex!G6="","",NSR_Capex!G6) -> 129 | H44: =IF(NSR_Capex!H6="","",NSR_Capex!H6) -> 168 | I44: NSR p.4 CPUs (AI) 6 → 168. Capstone Semis MAP AI CPUs (head-node, BofA-mix on house capex) 15 → 171. Nearly identical 2030 level, but the house is 1.5-2.5x NSR in 2025-26 (NSR's $6bn 2025 looks too low against any head-node count).
B45: Capstone | C45: =IF(House!E38="","",House!E38) -> 15.2 | D45: =IF(House!F38="","",House!F38) -> 40.2 | E45: =IF(House!G38="","",House!G38) -> 79.2 | F45: =IF(House!H38="","",House!H38) -> 127.2 | G45: =IF(House!I38="","",House!I38) -> 150.1 | H45: =IF(House!J38="","",House!J38) -> 171.1
B46: Δ Capstone vs NSR | C46: =IF(OR(C44="",C45=""),"",IFERROR(C45/C44-1,"")) -> 1.5333333 | D46: =IF(OR(D44="",D45=""),"",IFERROR(D45/D44-1,"")) -> 0.48888889 | E46: =IF(OR(E44="",E45=""),"",IFERROR(E45/E44-1,"")) -> 0.41428571 | F46: =IF(OR(F44="",F45=""),"",IFERROR(F45/F44-1,"")) -> 0.41333333 | G46: =IF(OR(G44="",G45=""),"",IFERROR(G45/G44-1,"")) -> 0.16356589 | H46: =IF(OR(H44="",H45=""),"",IFERROR(H45/H44-1,"")) -> 0.018452381
A48: CPUs — total server-CPU market ($bn) | B48: NSR | C48: =IF(NSR_Memory!C25="","",NSR_Memory!C25) -> 25 | D48: =IF(NSR_Memory!D25="","",NSR_Memory!D25) -> 49 | E48: =IF(NSR_Memory!E25="","",NSR_Memory!E25) -> 80 | F48: =IF(NSR_Memory!F25="","",NSR_Memory!F25) -> 117 | G48: =IF(NSR_Memory!G25="","",NSR_Memory!G25) -> 159 | H48: =IF(NSR_Memory!H25="","",NSR_Memory!H25) -> 202 | I48: NSR p.5 CPUs spending 25 → 202. Capstone ledger: house build ~$55bn CY26 / $96bn CY27 / $137bn CY28, ~$180-200bn 2030 (CPU-silicon total incl. Vera + enterprise). House is above NSR in 2026-28 (front-loaded agentic 1:1), converges by 2030; AMD's $220bn 2030 is above both.
B49: Capstone | D49: =IF(House!F116="","",House!F116) -> 55 | E49: =IF(House!G116="","",House!G116) -> 96 | F49: =IF(House!H116="","",House!H116) -> 137 | H49: =IF(House!J116="","",House!J116) -> 190
B50: Δ Capstone vs NSR | C50: =IF(OR(C48="",C49=""),"",IFERROR(C49/C48-1,"")) | D50: =IF(OR(D48="",D49=""),"",IFERROR(D49/D48-1,"")) -> 0.12244898 | E50: =IF(OR(E48="",E49=""),"",IFERROR(E49/E48-1,"")) -> 0.2 | F50: =IF(OR(F48="",F49=""),"",IFERROR(F49/F48-1,"")) -> 0.17094017 | G50: =IF(OR(G48="",G49=""),"",IFERROR(G49/G48-1,"")) | H50: =IF(OR(H48="",H49=""),"",IFERROR(H49/H48-1,"")) -> -0.059405941
A52: Networking ($bn) | B52: NSR | C52: =IF(NSR_Capex!C9="","",NSR_Capex!C9) -> 40 | D52: =IF(NSR_Capex!D9="","",NSR_Capex!D9) -> 103 | E52: =IF(NSR_Capex!E9="","",NSR_Capex!E9) -> 211 | F52: =IF(NSR_Capex!F9="","",NSR_Capex!F9) -> 336 | G52: =IF(NSR_Capex!G9="","",NSR_Capex!G9) -> 405 | H52: =IF(NSR_Capex!H9="","",NSR_Capex!H9) -> 465 | I52: NSR networking 40 → 465. Capstone Semis MAP AI networking (BofA ratio × house accelerators) 57 → 606; Bottom_Up physical build is lower (56 → 306). NSR sits between the two house constructions; all three agree networking outgrows compute.
B53: Capstone | C53: =IF(House!E47="","",House!E47) -> 56.6 | D53: =IF(House!F47="","",House!F47) -> 156.5 | E53: =IF(House!G47="","",House!G47) -> 292.6 | F53: =IF(House!H47="","",House!H47) -> 450.7 | G53: =IF(House!I47="","",House!I47) -> 531.9 | H53: =IF(House!J47="","",House!J47) -> 606.3
B54: Δ Capstone vs NSR | C54: =IF(OR(C52="",C53=""),"",IFERROR(C53/C52-1,"")) -> 0.415 | D54: =IF(OR(D52="",D53=""),"",IFERROR(D53/D52-1,"")) -> 0.51941748 | E54: =IF(OR(E52="",E53=""),"",IFERROR(E53/E52-1,"")) -> 0.38672986 | F54: =IF(OR(F52="",F53=""),"",IFERROR(F53/F52-1,"")) -> 0.34136905 | G54: =IF(OR(G52="",G53=""),"",IFERROR(G53/G52-1,"")) -> 0.31333333 | H54: =IF(OR(H52="",H53=""),"",IFERROR(H53/H52-1,"")) -> 0.30387097
A56: Networking — vs Capstone Bottom_Up physical build ($bn) | B56: NSR | C56: =IF(NSR_Capex!C9="","",NSR_Capex!C9) -> 40 | D56: =IF(NSR_Capex!D9="","",NSR_Capex!D9) -> 103 | E56: =IF(NSR_Capex!E9="","",NSR_Capex!E9) -> 211 | F56: =IF(NSR_Capex!F9="","",NSR_Capex!F9) -> 336 | G56: =IF(NSR_Capex!G9="","",NSR_Capex!G9) -> 405 | H56: =IF(NSR_Capex!H9="","",NSR_Capex!H9) -> 465 | I56: Same NSR line vs the physical units×ASP build (Bottom_Up_Capex_v3). Shows the house's own range on networking: 0.65x (2028-30) to 1.4x (2025) of NSR.
B57: Capstone | C57: =IF(House!E58="","",House!E58) -> 55.8 | D57: =IF(House!F58="","",House!F58) -> 101.4 | E57: =IF(House!G58="","",House!G58) -> 158 | F57: =IF(House!H58="","",House!H58) -> 217.1 | G57: =IF(House!I58="","",House!I58) -> 266.5 | H57: =IF(House!J58="","",House!J58) -> 305.8
B58: Δ Capstone vs NSR | C58: =IF(OR(C56="",C57=""),"",IFERROR(C57/C56-1,"")) -> 0.395 | D58: =IF(OR(D56="",D57=""),"",IFERROR(D57/D56-1,"")) -> -0.015533981 | E58: =IF(OR(E56="",E57=""),"",IFERROR(E57/E56-1,"")) -> -0.25118483 | F58: =IF(OR(F56="",F57=""),"",IFERROR(F57/F56-1,"")) -> -0.35386905 | G58: =IF(OR(G56="",G57=""),"",IFERROR(G57/G56-1,"")) -> -0.34197531 | H58: =IF(OR(H56="",H57=""),"",IFERROR(H57/H56-1,"")) -> -0.34236559
A60: Other equipment & buildings / shell, power, site ($bn) | B60: NSR | C60: =IF(NSR_Capex!C10="","",NSR_Capex!C10) -> 258 | D60: =IF(NSR_Capex!D10="","",NSR_Capex!D10) -> 328 | E60: =IF(NSR_Capex!E10="","",NSR_Capex!E10) -> 614 | F60: =IF(NSR_Capex!F10="","",NSR_Capex!F10) -> 899 | G60: =IF(NSR_Capex!G10="","",NSR_Capex!G10) -> 986 | H60: =IF(NSR_Capex!H10="","",NSR_Capex!H10) -> 1016 | I60: NSR 258 → 1,016 (44% → 24% of capex, 'frontloaded'). Capstone AI Model 'Other' 141 → 1,041 CY25-28 (held ~36% of capex). NSR has ~$120bn MORE shell in 2025 and ~$140bn LESS by 2028 — NSR front-loads the physical build, the house scales it with chips.
B61: Capstone | C61: =IF(House!E9="","",House!E9) -> 140.8 | D61: =IF(House!F9="","",House!F9) -> 323.1 | E61: =IF(House!G9="","",House!G9) -> 683.3 | F61: =IF(House!H9="","",House!H9) -> 1040.6
B62: Δ Capstone vs NSR | C62: =IF(OR(C60="",C61=""),"",IFERROR(C61/C60-1,"")) -> -0.45426357 | D62: =IF(OR(D60="",D61=""),"",IFERROR(D61/D60-1,"")) -> -0.014939024 | E62: =IF(OR(E60="",E61=""),"",IFERROR(E61/E60-1,"")) -> 0.11286645 | F62: =IF(OR(F60="",F61=""),"",IFERROR(F61/F60-1,"")) -> 0.15750834 | G62: =IF(OR(G60="",G61=""),"",IFERROR(G61/G60-1,"")) | H62: =IF(OR(H60="",H61=""),"",IFERROR(H61/H60-1,""))
A64: Shell / other equipment as % of total AI capex | B64: NSR | C64: =IF(NSR_Capex!C30="","",NSR_Capex!C30) -> 0.44253859 | D64: =IF(NSR_Capex!D30="","",NSR_Capex!D30) -> 0.29000884 | E64: =IF(NSR_Capex!E30="","",NSR_Capex!E30) -> 0.27998176 | F64: =IF(NSR_Capex!F30="","",NSR_Capex!F30) -> 0.27005107 | G64: =IF(NSR_Capex!G30="","",NSR_Capex!G30) -> 0.25906463 | H64: =IF(NSR_Capex!H30="","",NSR_Capex!H30) -> 0.24499638 | I64: See above. NSR's falling share is the mechanism behind its 'financing is easy' conclusion (less long-lived asset per capex dollar over time).
B65: Capstone | C65: =IF(House!E14="","",House!E14) -> 0.3552864 | D65: =IF(House!F14="","",House!F14) -> 0.35836291 | E65: =IF(House!G14="","",House!G14) -> 0.36241646 | F65: =IF(House!H14="","",House!H14) -> 0.35721396
B66: Δ Capstone vs NSR | C66: =IF(OR(C64="",C65=""),"",IFERROR(C65/C64-1,"")) -> -0.1971629 | D66: =IF(OR(D64="",D65=""),"",IFERROR(D65/D64-1,"")) -> 0.2356965 | E66: =IF(OR(E64="",E65=""),"",IFERROR(E65/E64-1,"")) -> 0.29442883 | F66: =IF(OR(F64="",F65=""),"",IFERROR(F65/F64-1,"")) -> 0.3227645 | G66: =IF(OR(G64="",G65=""),"",IFERROR(G65/G64-1,"")) | H66: =IF(OR(H64="",H65=""),"",IFERROR(H65/H64-1,""))
A68: 4. MEMORY — the biggest dollar disagreement
A69: HBM ($bn) — vs Capstone AI Model bottom-up | B69: NSR | C69: =IF(NSR_Memory!C13="","",NSR_Memory!C13) -> 34 | D69: =IF(NSR_Memory!D13="","",NSR_Memory!D13) -> 82 | E69: =IF(NSR_Memory!E13="","",NSR_Memory!E13) -> 189 | F69: =IF(NSR_Memory!F13="","",NSR_Memory!F13) -> 332 | G69: =IF(NSR_Memory!G13="","",NSR_Memory!G13) -> 457 | H69: =IF(NSR_Memory!H13="","",NSR_Memory!H13) -> 560 | I69: NSR HBM 34 → 560 (33% of XPU by 2030, GM normalizing to 76%). Capstone AI Model HBM Model (units × GB × spec-sheet $/GB) 27 → 282 CY25-28. House CY28 is 15% below NSR; the house has NO 2027 repricing in this line.
B70: Capstone | C70: =IF(House!E85="","",House!E85) -> 27 | D70: =IF(House!F85="","",House!F85) -> 63.7 | E70: =IF(House!G85="","",House!G85) -> 127.8 | F70: =IF(House!H85="","",House!H85) -> 281.5
B71: Δ Capstone vs NSR | C71: =IF(OR(C69="",C70=""),"",IFERROR(C70/C69-1,"")) -> -0.20588235 | D71: =IF(OR(D69="",D70=""),"",IFERROR(D70/D69-1,"")) -> -0.22317073 | E71: =IF(OR(E69="",E70=""),"",IFERROR(E70/E69-1,"")) -> -0.32380952 | F71: =IF(OR(F69="",F70=""),"",IFERROR(F70/F69-1,"")) -> -0.15210843 | G71: =IF(OR(G69="",G70=""),"",IFERROR(G70/G69-1,"")) | H71: =IF(OR(H69="",H70=""),"",IFERROR(H70/H69-1,""))
A73: HBM ($bn) — vs Capstone Semis MAP repriced (bits × $/GB) | B73: NSR | C73: =IF(NSR_Memory!C13="","",NSR_Memory!C13) -> 34 | D73: =IF(NSR_Memory!D13="","",NSR_Memory!D13) -> 82 | E73: =IF(NSR_Memory!E13="","",NSR_Memory!E13) -> 189 | F73: =IF(NSR_Memory!F13="","",NSR_Memory!F13) -> 332 | G73: =IF(NSR_Memory!G13="","",NSR_Memory!G13) -> 457 | H73: =IF(NSR_Memory!H13="","",NSR_Memory!H13) -> 560 | I73: Same NSR line vs Semis MAP repriced HBM (2/4.3/6.25/8/9.6/11.2 EB × $17.5/18/31/28/26.6/25.3 per GB). House 2027 ($194bn) matches NSR ($189bn); by 2030 NSR is 2.0x the house ($560bn vs $283bn) — NSR keeps HBM $ compounding at +22-38% into 2029-30 where the house fades price. BofA CY30 is $168bn.
B74: Capstone | C74: =IF(House!E41="","",House!E41) -> 35 | D74: =IF(House!F41="","",House!F41) -> 77.4 | E74: =IF(House!G41="","",House!G41) -> 193.8 | F74: =IF(House!H41="","",House!H41) -> 224 | G74: =IF(House!I41="","",House!I41) -> 255.4 | H74: =IF(House!J41="","",House!J41) -> 283.4
B75: Δ Capstone vs NSR | C75: =IF(OR(C73="",C74=""),"",IFERROR(C74/C73-1,"")) -> 0.029411765 | D75: =IF(OR(D73="",D74=""),"",IFERROR(D74/D73-1,"")) -> -0.056097561 | E75: =IF(OR(E73="",E74=""),"",IFERROR(E74/E73-1,"")) -> 0.025396825 | F75: =IF(OR(F73="",F74=""),"",IFERROR(F74/F73-1,"")) -> -0.3253012 | G75: =IF(OR(G73="",G74=""),"",IFERROR(G74/G73-1,"")) -> -0.44113786 | H75: =IF(OR(H73="",H74=""),"",IFERROR(H74/H73-1,"")) -> -0.49392857
A77: HBM as % of XPU spending | B77: NSR | C77: =IF(NSR_Memory!C15="","",NSR_Memory!C15) -> 0.16585366 | D77: =IF(NSR_Memory!D15="","",NSR_Memory!D15) -> 0.20098039 | E77: =IF(NSR_Memory!E15="","",NSR_Memory!E15) -> 0.24168798 | F77: =IF(NSR_Memory!F15="","",NSR_Memory!F15) -> 0.26517572 | G77: =IF(NSR_Memory!G15="","",NSR_Memory!G15) -> 0.30125247 | H77: =IF(NSR_Memory!H15="","",NSR_Memory!H15) -> 0.32902468 | I77: NSR 16% → 33%. Capstone AI Model 14% → 24% (CY28). The HBM-content-per-dollar story is the same direction; NSR is more extreme.
B78: Capstone | C78: =IF(House!E87="","",House!E87) -> 0.14195584 | D78: =IF(House!F87="","",House!F87) -> 0.15928982 | E78: =IF(House!G87="","",House!G87) -> 0.16662321 | F78: =IF(House!H87="","",House!H87) -> 0.24321756
B79: Δ Capstone vs NSR | C79: =IF(OR(C77="",C78=""),"",IFERROR(C78/C77-1,"")) -> -0.14408981 | D79: =IF(OR(D77="",D78=""),"",IFERROR(D78/D77-1,"")) -> -0.20743601 | E79: =IF(OR(E77="",E78=""),"",IFERROR(E78/E77-1,"")) -> -0.31058546 | F79: =IF(OR(F77="",F78=""),"",IFERROR(F78/F77-1,"")) -> -0.082806082 | G79: =IF(OR(G77="",G78=""),"",IFERROR(G78/G77-1,"")) | H79: =IF(OR(H77="",H78=""),"",IFERROR(H78/H77-1,""))
A81: DRAM (ex-HBM) + NAND ($bn) | B81: NSR | C81: =IF(NSR_Capex!C7="","",NSR_Capex!C7) -> 26 | D81: =IF(NSR_Capex!D7="","",NSR_Capex!D7) -> 160 | E81: =IF(NSR_Capex!E7="","",NSR_Capex!E7) -> 338 | F81: =IF(NSR_Capex!F7="","",NSR_Capex!F7) -> 459 | G81: =IF(NSR_Capex!G7="","",NSR_Capex!G7) -> 431 | H81: =IF(NSR_Capex!H7="","",NSR_Capex!H7) -> 423 | I81: NSR DRAM & NAND 26 → 338 (2027 peak) → 423. Capstone Semis MAP fleet DDR5 + DC NAND 42 → 317 (2027) → 405. Close in 2027 (−6%) and 2030 (−4%); the house is ~25% lower in 2028 (house DDR5 price fades from 2028 while NSR peaks there) and ~$16bn higher in 2025 (fleet DRAM already counted). Both fade price after 2027-28.
B82: Capstone | C82: =IF(House!E45="","",House!E45) -> 42.3 | D82: =IF(House!F45="","",House!F45) -> 211 | E82: =IF(House!G45="","",House!G45) -> 316.8 | F82: =IF(House!H45="","",House!H45) -> 345.8 | G82: =IF(House!I45="","",House!I45) -> 370.2 | H82: =IF(House!J45="","",House!J45) -> 404.9
B83: Δ Capstone vs NSR | C83: =IF(OR(C81="",C82=""),"",IFERROR(C82/C81-1,"")) -> 0.62692308 | D83: =IF(OR(D81="",D82=""),"",IFERROR(D82/D81-1,"")) -> 0.31875 | E83: =IF(OR(E81="",E82=""),"",IFERROR(E82/E81-1,"")) -> -0.062721893 | F83: =IF(OR(F81="",F82=""),"",IFERROR(F82/F81-1,"")) -> -0.24662309 | G83: =IF(OR(G81="",G82=""),"",IFERROR(G82/G81-1,"")) -> -0.14106729 | H83: =IF(OR(H81="",H82=""),"",IFERROR(H82/H81-1,"")) -> -0.042789598
A85: DRAM + NAND ($bn) — vs Capstone Bottom_Up 'memory bought direct' | B85: NSR | C85: =IF(NSR_Capex!C7="","",NSR_Capex!C7) -> 26 | D85: =IF(NSR_Capex!D7="","",NSR_Capex!D7) -> 160 | E85: =IF(NSR_Capex!E7="","",NSR_Capex!E7) -> 338 | F85: =IF(NSR_Capex!F7="","",NSR_Capex!F7) -> 459 | G85: =IF(NSR_Capex!G7="","",NSR_Capex!G7) -> 431 | H85: =IF(NSR_Capex!H7="","",NSR_Capex!H7) -> 423 | I85: Same NSR line vs the physical Bottom_Up build (DDR5 + DC NAND + …; broader perimeter incl. LPDDR/HDD legs). Bottom_Up runs 1.4-2.9x NSR — the sheet's own note flags stacked bull assumptions; treat as the house's upper bound.
B86: Capstone | C86: =IF(House!E57="","",House!E57) -> 75.7 | D86: =IF(House!F57="","",House!F57) -> 301.3 | E86: =IF(House!G57="","",House!G57) -> 495.7 | F86: =IF(House!H57="","",House!H57) -> 628.1 | G86: =IF(House!I57="","",House!I57) -> 751.8 | H86: =IF(House!J57="","",House!J57) -> 892.2
B87: Δ Capstone vs NSR | C87: =IF(OR(C85="",C86=""),"",IFERROR(C86/C85-1,"")) -> 1.9115385 | D87: =IF(OR(D85="",D86=""),"",IFERROR(D86/D85-1,"")) -> 0.883125 | E87: =IF(OR(E85="",E86=""),"",IFERROR(E86/E85-1,"")) -> 0.46656805 | F87: =IF(OR(F85="",F86=""),"",IFERROR(F86/F85-1,"")) -> 0.36840959 | G87: =IF(OR(G85="",G86=""),"",IFERROR(G86/G85-1,"")) -> 0.74431555 | H87: =IF(OR(H85="",H86=""),"",IFERROR(H86/H85-1,"")) -> 1.1092199
A89: Total memory = HBM + DRAM + NAND ($bn) | B89: NSR | C89: =IF(NSR_Memory!C52="","",NSR_Memory!C52) -> 60 | D89: =IF(NSR_Memory!D52="","",NSR_Memory!D52) -> 242 | E89: =IF(NSR_Memory!E52="","",NSR_Memory!E52) -> 527 | F89: =IF(NSR_Memory!F52="","",NSR_Memory!F52) -> 791 | G89: =IF(NSR_Memory!G52="","",NSR_Memory!G52) -> 888 | H89: =IF(NSR_Memory!H52="","",NSR_Memory!H52) -> 983 | I89: NSR 60 → 983. Capstone Semis MAP TOTAL CSP memory bill (mapped + repricing + fleet DDR5/NAND/HDD) 90 → 737. House above NSR in 2025-26, below from 2027 as NSR keeps HBM compounding. Memory-as-%-of-capex: NSR 10% → 24% (2030); house 21% → 21%.
B90: Capstone | C90: =IF(House!E46="","",House!E46) -> 90.4 | D90: =IF(House!F46="","",House!F46) -> 272.4 | E90: =IF(House!G46="","",House!G46) -> 496 | F90: =IF(House!H46="","",House!H46) -> 596.5 | G90: =IF(House!I46="","",House!I46) -> 667 | H90: =IF(House!J46="","",House!J46) -> 737
B91: Δ Capstone vs NSR | C91: =IF(OR(C89="",C90=""),"",IFERROR(C90/C89-1,"")) -> 0.50666667 | D91: =IF(OR(D89="",D90=""),"",IFERROR(D90/D89-1,"")) -> 0.12561983 | E91: =IF(OR(E89="",E90=""),"",IFERROR(E90/E89-1,"")) -> -0.058823529 | F91: =IF(OR(F89="",F90=""),"",IFERROR(F90/F89-1,"")) -> -0.24589128 | G91: =IF(OR(G89="",G90=""),"",IFERROR(G90/G89-1,"")) -> -0.24887387 | H91: =IF(OR(H89="",H90=""),"",IFERROR(H90/H89-1,"")) -> -0.25025432
A93: Total memory as % of total AI capex | B93: NSR | C93: =IF(NSR_Memory!C54="","",NSR_Memory!C54) -> 0.10291595 | D93: =IF(NSR_Memory!D54="","",NSR_Memory!D54) -> 0.21396994 | E93: =IF(NSR_Memory!E54="","",NSR_Memory!E54) -> 0.24031008 | F93: =IF(NSR_Memory!F54="","",NSR_Memory!F54) -> 0.23760889 | G93: =IF(NSR_Memory!G54="","",NSR_Memory!G54) -> 0.23331582 | H93: =IF(NSR_Memory!H54="","",NSR_Memory!H54) -> 0.23703882 | I93: House share uses the Semis MAP capex path as denominator (same vintage as its numerator). JPM Kwon (08-09) has memory at 31%/49%/60% of CSP HARDWARE capex 2026-28 — a different denominator (ex-shell); not comparable to either row.
B94: Capstone | C94: =IFERROR(House!E46/House!E28,"") -> 0.20940468 | D94: =IFERROR(House!F46/House!F28,"") -> 0.30280124 | E94: =IFERROR(House!G46/House!G28,"") -> 0.29527325 | F94: =IFERROR(House!H46/House!H28,"") -> 0.23045124 | G94: =IFERROR(House!I46/House!I28,"") -> 0.21838064 | H94: =IFERROR(House!J46/House!J28,"") -> 0.21166604
B95: Δ Capstone vs NSR | C95: =IF(OR(C93="",C94=""),"",IFERROR(C94/C93-1,"")) -> 1.0347155 | D95: =IF(OR(D93="",D94=""),"",IFERROR(D94/D93-1,"")) -> 0.41515788 | E95: =IF(OR(E93="",E94=""),"",IFERROR(E94/E93-1,"")) -> 0.2287177 | F95: =IF(OR(F93="",F94=""),"",IFERROR(F94/F93-1,"")) -> -0.030123652 | G95: =IF(OR(G93="",G94=""),"",IFERROR(G94/G93-1,"")) -> -0.064012692 | H95: =IF(OR(H93="",H94=""),"",IFERROR(H94/H93-1,"")) -> -0.1070406
A97: 5. GIGAWATTS — three bases, none of them NSR's
A98: Installed AI capacity (GW) — vs Capstone cumulative CHIP-content GW | B98: NSR | H98: =NSR_Datapoints!B26 -> 275 | I98: NSR ~275 GW 2030 (basis not stated; prior ~225). Capstone purchase-basis chip stock 24/51/102/171 GW CY25-28 (AI Model, all players) and Semis MAP cumulative chip-content GW 217/299 CY29-30 (gross, no retirements, July base). On this basis the house is AT NSR's 2030 mark (+9%). Chip GW ≠ facility GW.
B99: Capstone | C99: =IF(House!E73="","",House!E73) -> 24.1 | D99: =IF(House!F73="","",House!F73) -> 51.2 | E99: =IF(House!G73="","",House!G73) -> 101.9 | F99: =IF(House!H73="","",House!H73) -> 171.4 | G99: =IF(House!I51="","",House!I51) -> 217.4 | H99: =IF(House!J51="","",House!J51) -> 298.7
B100: Δ Capstone vs NSR | C100: =IF(OR(C98="",C99=""),"",IFERROR(C99/C98-1,"")) | D100: =IF(OR(D98="",D99=""),"",IFERROR(D99/D98-1,"")) | E100: =IF(OR(E98="",E99=""),"",IFERROR(E99/E98-1,"")) | F100: =IF(OR(F98="",F99=""),"",IFERROR(F99/F98-1,"")) | G100: =IF(OR(G98="",G99=""),"",IFERROR(G99/G98-1,"")) | H100: =IF(OR(H98="",H99=""),"",IFERROR(H99/H98-1,"")) -> 0.086181818
A102: Installed AI capacity (GW) — vs Capstone cumulative FACILITY GW | B102: NSR | H102: =NSR_Datapoints!B26 -> 275 | I102: Bottom_Up_Capex_v3 physical facility GW (units × kW × PUE): 24/44/80/125/179/242 GW CY25-30. 12% below NSR's 275 in 2030; matches BofA's 233 GW. The Tokenomics bridge's BofA-derived 224 GW IT (~314 GW facility) brackets NSR from the other side.
B103: Capstone | C103: =IF(House!E63="","",House!E63) -> 23.6 | D103: =IF(House!F63="","",House!F63) -> 44.4 | E103: =IF(House!G63="","",House!G63) -> 79.9 | F103: =IF(House!H63="","",House!H63) -> 125.3 | G103: =IF(House!I63="","",House!I63) -> 179.1 | H103: =IF(House!J63="","",House!J63) -> 241.7
B104: Δ Capstone vs NSR | C104: =IF(OR(C102="",C103=""),"",IFERROR(C103/C102-1,"")) | D104: =IF(OR(D102="",D103=""),"",IFERROR(D103/D102-1,"")) | E104: =IF(OR(E102="",E103=""),"",IFERROR(E103/E102-1,"")) | F104: =IF(OR(F102="",F103=""),"",IFERROR(F103/F102-1,"")) | G104: =IF(OR(G102="",G103=""),"",IFERROR(G103/G102-1,"")) | H104: =IF(OR(H102="",H103=""),"",IFERROR(H103/H102-1,"")) -> -0.12109091
A106: Installed AI capacity (GW) — vs Capstone ONLINE-capacity stock | B106: NSR | H106: =NSR_Datapoints!B26 -> 275 | I106: AI Model online-capacity stock 14/31/64/119 GW CY25-28 — what is actually energised and billable, ~1 year behind purchases. NSR's hyperscaler-only '>100 GW deployed by end of decade' sits closest to this basis.
B107: Capstone | C107: =IF(House!E74="","",House!E74) -> 14.3 | D107: =IF(House!F74="","",House!F74) -> 30.7 | E107: =IF(House!G74="","",House!G74) -> 63.7 | F107: =IF(House!H74="","",House!H74) -> 119.1
B108: Δ Capstone vs NSR | C108: =IF(OR(C106="",C107=""),"",IFERROR(C107/C106-1,"")) | D108: =IF(OR(D106="",D107=""),"",IFERROR(D107/D106-1,"")) | E108: =IF(OR(E106="",E107=""),"",IFERROR(E107/E106-1,"")) | F108: =IF(OR(F106="",F107=""),"",IFERROR(F107/F106-1,"")) | G108: =IF(OR(G106="",G107=""),"",IFERROR(G107/G106-1,"")) | H108: =IF(OR(H106="",H107=""),"",IFERROR(H107/H106-1,""))
A110: Capex per GW ($bn/GW) | B110: NSR | D110: =NSR_Datapoints!B30 -> 42.5 | E110: =NSR_Datapoints!B30 -> 42.5 | F110: =NSR_Datapoints!B30 -> 42.5 | I110: NSR '~$40-45bn/GW' (midpoint 42.5, hyperscaler AI capex). Capstone blended build cost per GW added 30.5/34/38/41.9 CY25-28 (NVDA-only basis runs 37 → 51; CY28E NVDA 50.8 = chip 25.5 + networking 10.3 + other 15.0). MS GB300 all-in $39bn/GW. Converging on ~$42bn by 2028.
B111: Capstone | C111: =IF(House!E79="","",House!E79) -> 30.5 | D111: =IF(House!F79="","",House!F79) -> 34 | E111: =IF(House!G79="","",House!G79) -> 38 | F111: =IF(House!H79="","",House!H79) -> 41.9
B112: Δ Capstone vs NSR | C112: =IF(OR(C110="",C111=""),"",IFERROR(C111/C110-1,"")) | D112: =IF(OR(D110="",D111=""),"",IFERROR(D111/D110-1,"")) -> -0.2 | E112: =IF(OR(E110="",E111=""),"",IFERROR(E111/E110-1,"")) -> -0.10588235 | F112: =IF(OR(F110="",F111=""),"",IFERROR(F111/F110-1,"")) -> -0.014117647 | G112: =IF(OR(G110="",G111=""),"",IFERROR(G111/G110-1,"")) | H112: =IF(OR(H110="",H111=""),"",IFERROR(H111/H110-1,""))
A114: AI revenue per GW ($bn/GW/yr) | B114: NSR | F114: =NSR_Datapoints!B29 -> 13 | H114: =NSR_Datapoints!B29 -> 13 | I114: NSR ~$13bn/GW (AI cloud revenue / deployed GW) — but its tier-2/neocloud block implies ~$25bn/GW ($2.3tn on 91 GW). Capstone implied blend (implied AI revenue / avg online GW) ~13-14 $bn/GW; by designer NVDA $20bn, Google $14bn, Trainium $7bn. Ledger rental marks $12-13bn merchant GPU. NSR's hyperscaler figure = the house blend; its neocloud figure = the house NVDA-premium figure.
B115: Capstone | D115: =IF(House!F81="","",House!F81) -> 13.586667 | E115: =IF(House!G81="","",House!G81) -> 14.506356 | F115: =IF(House!H81="","",House!H81) -> 12.943107
B116: Δ Capstone vs NSR | C116: =IF(OR(C114="",C115=""),"",IFERROR(C115/C114-1,"")) | D116: =IF(OR(D114="",D115=""),"",IFERROR(D115/D114-1,"")) | E116: =IF(OR(E114="",E115=""),"",IFERROR(E115/E114-1,"")) | F116: =IF(OR(F114="",F115=""),"",IFERROR(F115/F114-1,"")) -> -0.0043763676 | G116: =IF(OR(G114="",G115=""),"",IFERROR(G115/G114-1,"")) | H116: =IF(OR(H114="",H115=""),"",IFERROR(H115/H114-1,""))
A118: 6. HYPERSCALER CASH — OCF, capex, FCF (NSR basket vs Capstone big-4, calendar)
A119: Hyperscaler OCF ($bn) | B119: NSR | C119: =IF(NSR_HyperPL!C31="","",NSR_HyperPL!C31) -> 580 | D119: =IF(NSR_HyperPL!D31="","",NSR_HyperPL!D31) -> 774 | E119: =IF(NSR_HyperPL!E31="","",NSR_HyperPL!E31) -> 1074 | F119: =IF(NSR_HyperPL!F31="","",NSR_HyperPL!F31) -> 1489 | G119: =IF(NSR_HyperPL!G31="","",NSR_HyperPL!G31) -> 2019 | H119: =IF(NSR_HyperPL!H31="","",NSR_HyperPL!H31) -> 2650 | I119: NSR OCF 580 → 2,650 (its basket). Capstone big-4 OCF 515/688/923/1,202 CY25-28 (GOOG/META on the conservative LL+D&A definition). House is 11-19% below NSR each year — consistent with NSR's stated +$2tn OCF uplift vs consensus (24% revenue CAGR, 77% incremental OCF margin).
B120: Capstone | C120: =IF(House!E90="","",House!E90) -> 514.8 | D120: =IF(House!F90="","",House!F90) -> 687.6 | E120: =IF(House!G90="","",House!G90) -> 923.3 | F120: =IF(House!H90="","",House!H90) -> 1201.9
B121: Δ Capstone vs NSR | C121: =IF(OR(C119="",C120=""),"",IFERROR(C120/C119-1,"")) -> -0.11241379 | D121: =IF(OR(D119="",D120=""),"",IFERROR(D120/D119-1,"")) -> -0.11162791 | E121: =IF(OR(E119="",E120=""),"",IFERROR(E120/E119-1,"")) -> -0.14031657 | F121: =IF(OR(F119="",F120=""),"",IFERROR(F120/F119-1,"")) -> -0.19281397 | G121: =IF(OR(G119="",G120=""),"",IFERROR(G120/G119-1,"")) | H121: =IF(OR(H119="",H120=""),"",IFERROR(H120/H119-1,""))
A123: Hyperscaler capex ($bn) | B123: NSR | C123: =IF(NSR_HyperPL!C33="","",NSR_HyperPL!C33) -> 415 | D123: =IF(NSR_HyperPL!D33="","",NSR_HyperPL!D33) -> 795 | E123: =IF(NSR_HyperPL!E33="","",NSR_HyperPL!E33) -> 1384 | F123: =IF(NSR_HyperPL!F33="","",NSR_HyperPL!F33) -> 1975 | G123: =IF(NSR_HyperPL!G33="","",NSR_HyperPL!G33) -> 2181 | H123: =IF(NSR_HyperPL!H33="","",NSR_HyperPL!H33) -> 2387 | I123: NSR group capex 415 → 2,387. Capstone big-4 total capex 410/750/1,163/1,463. Level agrees in 2025; NSR is 19% above the house in 2027 and 35% above in 2028 (basket + NSR's higher AI intensity).
B124: Capstone | C124: =IF(House!E91="","",House!E91) -> 409.7 | D124: =IF(House!F91="","",House!F91) -> 749.9 | E124: =IF(House!G91="","",House!G91) -> 1163 | F124: =IF(House!H91="","",House!H91) -> 1463.3
B125: Δ Capstone vs NSR | C125: =IF(OR(C123="",C124=""),"",IFERROR(C124/C123-1,"")) -> -0.012771084 | D125: =IF(OR(D123="",D124=""),"",IFERROR(D124/D123-1,"")) -> -0.05672956 | E125: =IF(OR(E123="",E124=""),"",IFERROR(E124/E123-1,"")) -> -0.15968208 | F125: =IF(OR(F123="",F124=""),"",IFERROR(F124/F123-1,"")) -> -0.25908861 | G125: =IF(OR(G123="",G124=""),"",IFERROR(G124/G123-1,"")) | H125: =IF(OR(H123="",H124=""),"",IFERROR(H124/H123-1,""))
A127: Hyperscaler FCF = OCF − capex ($bn) | B127: NSR | C127: =IF(NSR_HyperPL!C36="","",NSR_HyperPL!C36) -> 165 | D127: =IF(NSR_HyperPL!D36="","",NSR_HyperPL!D36) -> -21 | E127: =IF(NSR_HyperPL!E36="","",NSR_HyperPL!E36) -> -310 | F127: =IF(NSR_HyperPL!F36="","",NSR_HyperPL!F36) -> -486 | G127: =IF(NSR_HyperPL!G36="","",NSR_HyperPL!G36) -> -162 | H127: =IF(NSR_HyperPL!H36="","",NSR_HyperPL!H36) -> 263 | I127: NSR 164 / (22) / (310) / (486) / (162) / +263 — trough 2028, positive 2030, ~$700bn cumulative burn. Capstone big-4 105 / (62) / (240) / (261) CY25-28 — the house goes negative a year EARLIER and less deep (no 2029-30). BBG consensus basket (07-28): (3.5) / (18.8) / +132 — both NSR and the house are far below consensus on 2027-28 FCF.
B128: Capstone | C128: =IF(House!E92="","",House!E92) -> 105.1 | D128: =IF(House!F92="","",House!F92) -> -62.3 | E128: =IF(House!G92="","",House!G92) -> -239.7 | F128: =IF(House!H92="","",House!H92) -> -261.4
B129: Δ Capstone vs NSR | C129: =IF(OR(C127="",C128=""),"",IFERROR(C128/C127-1,"")) -> -0.3630303 | D129: =IF(OR(D127="",D128=""),"",IFERROR(D128/D127-1,"")) -> 1.9666667 | E129: =IF(OR(E127="",E128=""),"",IFERROR(E128/E127-1,"")) -> -0.22677419 | F129: =IF(OR(F127="",F128=""),"",IFERROR(F128/F127-1,"")) -> -0.46213992 | G129: =IF(OR(G127="",G128=""),"",IFERROR(G128/G127-1,"")) | H129: =IF(OR(H127="",H128=""),"",IFERROR(H128/H127-1,""))
A131: Capex / OCF (x) | B131: NSR | C131: =IFERROR(NSR_HyperPL!C33/NSR_HyperPL!C31,"") -> 0.71551724 | D131: =IFERROR(NSR_HyperPL!D33/NSR_HyperPL!D31,"") -> 1.0271318 | E131: =IFERROR(NSR_HyperPL!E33/NSR_HyperPL!E31,"") -> 1.2886406 | F131: =IFERROR(NSR_HyperPL!F33/NSR_HyperPL!F31,"") -> 1.3263936 | G131: =IFERROR(NSR_HyperPL!G33/NSR_HyperPL!G31,"") -> 1.0802377 | H131: =IFERROR(NSR_HyperPL!H33/NSR_HyperPL!H31,"") -> 0.90075472 | I131: NSR 0.72x → 1.33x (2028 peak) → 0.90x. Capstone 0.80x → 1.26x (2027) → 1.22x. Same peak intensity, house peaks a year earlier.
...

Sheet Share_XPU
A1: XPU / accelerators — vendor market share and implied revenue, 2025-2030 ($bn)
A2: Pool = NSR XPUs (p.4, HBM inside the package) and the Capstone chip pool. Shares = Capstone designer revenue ÷ Capstone pool (our model's mix, tagged EST because it is a house forecast), with NSR's and BofA's 2030 marks as the external alternatives. Implied revenue = NSR pool × share. NOT ADDITIVE with Share_Memory: the HBM dollars inside these XPU figures are the same dollars shown as vendor HBM revenue there. Tags: HARD = sourced figure; PARTIAL = sourced range, point is ours; EST = our assumption; SCENARIO = alternative reading; FORMULA = derived.
A4: Line | B4: Unit | C4: 2025 | D4: 2026 | E4: 2027 | F4: 2028 | G4: 2029 | H4: 2030 | I4: Tag | J4: Source
A5: A. Pools ($bn)
A6: NSR XPU spending (incl. HBM inside the package) | B6: $bn | C6: =IF(NSR_Capex!C5="","",NSR_Capex!C5) -> 205 | D6: =IF(NSR_Capex!D5="","",NSR_Capex!D5) -> 408 | E6: =IF(NSR_Capex!E5="","",NSR_Capex!E5) -> 782 | F6: =IF(NSR_Capex!F5="","",NSR_Capex!F5) -> 1252 | G6: =IF(NSR_Capex!G5="","",NSR_Capex!G5) -> 1517 | H6: =IF(NSR_Capex!H5="","",NSR_Capex!H5) -> 1702 | I6: LINK | J6: NSR p.4 (NSR_Capex)
A7: Capstone chip pool = designers' AI chip revenue (incl. HBM inside) | B7: $bn | C7: =IF(House!E7="","",House!E7) -> 190.2 | D7: =IF(House!F7="","",House!F7) -> 399.9 | E7: =IF(House!G7="","",House!G7) -> 767 | F7: =IF(House!H7="","",House!H7) -> 1157.4 | G7: =IF(House!I31="","",House!I31) -> 1240.6 | H7: =IF(House!J31="","",House!J31) -> 1414.2 | I7: LINK | J7: House!cx_chips CY25-28 (AI Model 31-Aug); House!sm_des CY29-30 (Semis MAP v11, July base). VINTAGE SPLICE: NVDA CY28 → CY29 grows only +1.4% across the join (Semis MAP's own CY28→29 is +17%), so the CY29-30 NVDA share step-down is an artifact, not a view
A9: B. Capstone vendor chip revenue ($bn) — the house mix (EST: house model output)
A10: NVIDIA (merchant GPU) | B10: $bn | C10: 158.8 | D10: 311.8 | E10: 578.6 | F10: 784 | G10: 795.3 | H10: 900 | I10: EST | J10: AI Model.xlsx (31-Aug-2026) → Resumo | Designers ‘Receita de Chip das Designers’ rows 34-45 (CY25-28); Semis MAP v11 → Designers TAM (CY29-30, July base). HOUSE MODEL OUTPUT — a forecast split, not a market print (hence EST)
A11: Broadcom (Google TPU + Meta MTIA + OpenAI Titan, custom ASIC) | B11: $bn | C11: 20.1 | D11: 60.4 | E11: 125.5 | F11: 284.6 | G11: 340.3 | H11: 394.2 | I11: EST | J11: same source. NOTE the house fork: the official AVGO model (Modelo Avgo pós 2Q26) has AI semis $251bn FY28 INCLUDING networking, below this XPU-only $284.6bn
A12: AMD (MI series) | B12: $bn | C12: 8 | D12: 20.7 | E12: 38.4 | F12: 51.8 | G12: 60.7 | H12: 68.7 | I12: EST | J12: same source
A13: Marvell (Trainium + other custom) | B13: $bn | C13: 2.9 | D13: 6.9 | E13: 9.3 | F13: 13.3 | G13: 15.9 | H13: 18.4 | I13: EST | J13: same source
A14: MediaTek (TPU co-design) | B14: $bn | C14: 0 | D14: 0.2 | E14: 12.3 | F14: 20.3 | G14: 24.2 | H14: 28.1 | I14: EST | J14: same source
A15: Alchip (incl. Microsoft Maia co-design) | B15: $bn | C15: 0.4 | D15: 0 | E15: 3 | F15: 3.5 | G15: 4.2 | H15: 4.9 | I15: EST | J15: same source — Semis MAP labels the row ‘Microsoft (Alchip)’; Maia is INSIDE Alchip, not additive (skeptic fix)
A16: Sum of vendor rows | B16: $bn | C16: =SUM(C10:C15) -> 190.2 | D16: =SUM(D10:D15) -> 400 | E16: =SUM(E10:E15) -> 767.1 | F16: =SUM(F10:F15) -> 1157.5 | G16: =SUM(G10:G15) -> 1240.6 | H16: =SUM(H10:H15) -> 1414.3 | I16: FORMULA
A17: Check: vendor rows − Capstone pool (should be ~0) | B17: $bn | C17: =IF(C7="","",C16-C7) -> 2.8421709e-14 | D17: =IF(D7="","",D16-D7) -> 0.1 | E17: =IF(E7="","",E16-E7) -> 0.1 | F17: =IF(F7="","",F16-F7) -> 0.1 | G17: =IF(G7="","",G16-G7) -> 2.2737368e-13 | H17: =IF(H7="","",H16-H7) -> 0.1 | I17: FORMULA | J17: AI Model total = NVDA + AVGO + AMD + MRVL + MTK + Alchip exactly
A19: C. Market share — Capstone mix (share of the Capstone pool)
A20: NVIDIA — share of accelerator value | B20: % | C20: =IF(OR(C10="",C16=""),"",IFERROR(C10/C16,"")) -> 0.83491062 | D20: =IF(OR(D10="",D16=""),"",IFERROR(D10/D16,"")) -> 0.7795 | E20: =IF(OR(E10="",E16=""),"",IFERROR(E10/E16,"")) -> 0.75426933 | F20: =IF(OR(F10="",F16=""),"",IFERROR(F10/F16,"")) -> 0.67732181 | G20: =IF(OR(G10="",G16=""),"",IFERROR(G10/G16,"")) -> 0.64106078 | H20: =IF(OR(H10="",H16=""),"",IFERROR(H10/H16,"")) -> 0.63635721 | I20: EST | J20: → vendor row / sum of vendor rows (house forecast split)
A21: Broadcom — share of accelerator value | B21: % | C21: =IF(OR(C11="",C16=""),"",IFERROR(C11/C16,"")) -> 0.10567823 | D21: =IF(OR(D11="",D16=""),"",IFERROR(D11/D16,"")) -> 0.151 | E21: =IF(OR(E11="",E16=""),"",IFERROR(E11/E16,"")) -> 0.16360318 | F21: =IF(OR(F11="",F16=""),"",IFERROR(F11/F16,"")) -> 0.24587473 | G21: =IF(OR(G11="",G16=""),"",IFERROR(G11/G16,"")) -> 0.27430276 | H21: =IF(OR(H11="",H16=""),"",IFERROR(H11/H16,"")) -> 0.27872446 | I21: EST | J21: → vendor row / sum of vendor rows (house forecast split)
A22: AMD — share of accelerator value | B22: % | C22: =IF(OR(C12="",C16=""),"",IFERROR(C12/C16,"")) -> 0.042060988 | D22: =IF(OR(D12="",D16=""),"",IFERROR(D12/D16,"")) -> 0.05175 | E22: =IF(OR(E12="",E16=""),"",IFERROR(E12/E16,"")) -> 0.050058662 | F22: =IF(OR(F12="",F16=""),"",IFERROR(F12/F16,"")) -> 0.04475162 | G22: =IF(OR(G12="",G16=""),"",IFERROR(G12/G16,"")) -> 0.048927938 | H22: =IF(OR(H12="",H16=""),"",IFERROR(H12/H16,"")) -> 0.048575267 | I22: EST | J22: → vendor row / sum of vendor rows (house forecast split)
A23: Marvell — share of accelerator value | B23: % | C23: =IF(OR(C13="",C16=""),"",IFERROR(C13/C16,"")) -> 0.015247108 | D23: =IF(OR(D13="",D16=""),"",IFERROR(D13/D16,"")) -> 0.01725 | E23: =IF(OR(E13="",E16=""),"",IFERROR(E13/E16,"")) -> 0.012123582 | F23: =IF(OR(F13="",F16=""),"",IFERROR(F13/F16,"")) -> 0.011490281 | G23: =IF(OR(G13="",G16=""),"",IFERROR(G13/G16,"")) -> 0.012816379 | H23: =IF(OR(H13="",H16=""),"",IFERROR(H13/H16,"")) -> 0.01300997 | I23: EST | J23: → vendor row / sum of vendor rows (house forecast split)
A24: MediaTek — share of accelerator value | B24: % | C24: =IF(OR(C14="",C16=""),"",IFERROR(C14/C16,"")) -> 0 | D24: =IF(OR(D14="",D16=""),"",IFERROR(D14/D16,"")) -> 0.0005 | E24: =IF(OR(E14="",E16=""),"",IFERROR(E14/E16,"")) -> 0.016034415 | F24: =IF(OR(F14="",F16=""),"",IFERROR(F14/F16,"")) -> 0.017537797 | G24: =IF(OR(G14="",G16=""),"",IFERROR(G14/G16,"")) -> 0.01950669 | H24: =IF(OR(H14="",H16=""),"",IFERROR(H14/H16,"")) -> 0.019868486 | I24: EST | J24: → vendor row / sum of vendor rows (house forecast split)
A25: Alchip (incl. Maia) — share of accelerator value | B25: % | C25: =IF(OR(C15="",C16=""),"",IFERROR(C15/C16,"")) -> 0.0021030494 | D25: =IF(OR(D15="",D16=""),"",IFERROR(D15/D16,"")) -> 0 | E25: =IF(OR(E15="",E16=""),"",IFERROR(E15/E16,"")) -> 0.003910833 | F25: =IF(OR(F15="",F16=""),"",IFERROR(F15/F16,"")) -> 0.0030237581 | G25: =IF(OR(G15="",G16=""),"",IFERROR(G15/G16,"")) -> 0.0033854586 | H25: =IF(OR(H15="",H16=""),"",IFERROR(H15/H16,"")) -> 0.0034646115 | I25: EST | J25: → vendor row / sum of vendor rows (house forecast split)
A26: Custom ASIC total (Broadcom + Marvell + MediaTek + Alchip) — share | B26: % | C26: =IF(C20="","",1-C20-C22) -> 0.12302839 | D26: =IF(D20="","",1-D20-D22) -> 0.16875 | E26: =IF(E20="","",1-E20-E22) -> 0.19567201 | F26: =IF(F20="","",1-F20-F22) -> 0.27792657 | G26: =IF(G20="","",1-G20-G22) -> 0.31001128 | H26: =IF(H20="","",1-H20-H22) -> 0.31506752 | I26: FORMULA | J26: → 1 − NVIDIA − AMD
A28: D. Third-party marks (share of accelerator value unless stated)
A29: NVIDIA — NSR (2030) | B29: % | H29: 0.6 | I29: HARD | J29: NSR p.3: “Nvidia at close to 60% of XPU value in 2030, implying ~$1.7tn of total XPU spending”
A30: NVIDIA — BofA AI 2030 (CY30) | B30: % | H30: 0.68 | I30: HARD | J30: BofA Arya “AI 2030” 2026-05-13 (themes/ai-tam-bofa.md §5): NVDA ~$800bn of $1.17tn accelerators CY30 (83% → 68%)
A31: Broadcom — BofA AI 2030 (CY30) | B31: % | H31: 0.16 | I31: HARD | J31: BofA: AVGO custom ASIC ~$182bn CY30 = 16% (8% → 16%)
A32: AMD — BofA AI 2030 (CY30) | B32: % | H32: 0.07 | I32: HARD | J32: BofA: AMD ~$80bn CY30 = ~5-7%
A33: Custom ASIC — JPM UNIT share (units, NOT value) | B33: % | D33: 0.42 | E33: 0.53 | I33: HARD | J33: JPM Sur ‘AI Capex 2.0’ 2026-06-16 (assumptions.md asic-vs-gpu-share): ASIC 42% of units 2026E → 53% 2027E. Unit share ≠ value share (ASIC ASP ~$9-19k vs NVDA $41-137k in our model)
A35: E. Implied vendor revenue on the NSR pool ($bn) = NSR XPU pool × Capstone share
A36: NVIDIA — implied on NSR pool | B36: $bn | C36: =IF(OR(C6="",C20=""),"",C6*C20) -> 171.15668 | D36: =IF(OR(D6="",D20=""),"",D6*D20) -> 318.036 | E36: =IF(OR(E6="",E20=""),"",E6*E20) -> 589.83861 | F36: =IF(OR(F6="",F20=""),"",F6*F20) -> 848.00691 | G36: =IF(OR(G6="",G20=""),"",G6*G20) -> 972.4892 | H36: =IF(OR(H6="",H20=""),"",H6*H20) -> 1083.08 | I36: FORMULA | J36: NSR pool × Capstone share
A37: Broadcom — implied on NSR pool | B37: $bn | C37: =IF(OR(C6="",C21=""),"",C6*C21) -> 21.664038 | D37: =IF(OR(D6="",D21=""),"",D6*D21) -> 61.608 | E37: =IF(OR(E6="",E21=""),"",E6*E21) -> 127.93769 | F37: =IF(OR(F6="",F21=""),"",F6*F21) -> 307.83516 | G37: =IF(OR(G6="",G21=""),"",G6*G21) -> 416.11728 | H37: =IF(OR(H6="",H21=""),"",H6*H21) -> 474.38903 | I37: FORMULA | J37: NSR pool × Capstone share
A38: AMD — implied on NSR pool | B38: $bn | C38: =IF(OR(C6="",C22=""),"",C6*C22) -> 8.6225026 | D38: =IF(OR(D6="",D22=""),"",D6*D22) -> 21.114 | E38: =IF(OR(E6="",E22=""),"",E6*E22) -> 39.145874 | F38: =IF(OR(F6="",F22=""),"",F6*F22) -> 56.029028 | G38: =IF(OR(G6="",G22=""),"",G6*G22) -> 74.223682 | H38: =IF(OR(H6="",H22=""),"",H6*H22) -> 82.675104 | I38: FORMULA | J38: NSR pool × Capstone share
A39: Marvell — implied on NSR pool | B39: $bn | C39: =IF(OR(C6="",C23=""),"",C6*C23) -> 3.1256572 | D39: =IF(OR(D6="",D23=""),"",D6*D23) -> 7.038 | E39: =IF(OR(E6="",E23=""),"",E6*E23) -> 9.4806414 | F39: =IF(OR(F6="",F23=""),"",F6*F23) -> 14.385832 | G39: =IF(OR(G6="",G23=""),"",G6*G23) -> 19.442447 | H39: =IF(OR(H6="",H23=""),"",H6*H23) -> 22.142968 | I39: FORMULA | J39: NSR pool × Capstone share
A40: MediaTek — implied on NSR pool | B40: $bn | C40: =IF(OR(C6="",C24=""),"",C6*C24) -> 0 | D40: =IF(OR(D6="",D24=""),"",D6*D24) -> 0.204 | E40: =IF(OR(E6="",E24=""),"",E6*E24) -> 12.538913 | F40: =IF(OR(F6="",F24=""),"",F6*F24) -> 21.957322 | G40: =IF(OR(G6="",G24=""),"",G6*G24) -> 29.591649 | H40: =IF(OR(H6="",H24=""),"",H6*H24) -> 33.816163 | I40: FORMULA | J40: NSR pool × Capstone share
A41: Alchip (incl. Maia) — implied on NSR pool | B41: $bn | C41: =IF(OR(C6="",C25=""),"",C6*C25) -> 0.43112513 | D41: =IF(OR(D6="",D25=""),"",D6*D25) -> 0 | E41: =IF(OR(E6="",E25=""),"",E6*E25) -> 3.0582714 | F41: =IF(OR(F6="",F25=""),"",F6*F25) -> 3.7857451 | G41: =IF(OR(G6="",G25=""),"",G6*G25) -> 5.1357408 | H41: =IF(OR(H6="",H25=""),"",H6*H25) -> 5.8967687 | I41: FORMULA | J41: NSR pool × Capstone share
A42: NVIDIA — implied on NSR pool at NSR's own 60% (2030) | B42: $bn | C42: =IF(OR(C6="",C29=""),"",C6*C29) | D42: =IF(OR(D6="",D29=""),"",D6*D29) | E42: =IF(OR(E6="",E29=""),"",E6*E29) | F42: =IF(OR(F6="",F29=""),"",F6*F29) | G42: =IF(OR(G6="",G29=""),"",G6*G29) | H42: =IF(OR(H6="",H29=""),"",H6*H29) -> 1021.2 | I42: FORMULA | J42: → $1,702bn × 60% ≈ $1.02tn, NSR's implied NVIDIA 2030 XPU revenue
A43: NVIDIA — implied on NSR pool at BofA's 68% (2030) | B43: $bn | C43: =IF(OR(C6="",C30=""),"",C6*C30) | D43: =IF(OR(D6="",D30=""),"",D6*D30) | E43: =IF(OR(E6="",E30=""),"",E6*E30) | F43: =IF(OR(F6="",F30=""),"",F6*F30) | G43: =IF(OR(G6="",G30=""),"",G6*G30) | H43: =IF(OR(H6="",H30=""),"",H6*H30) -> 1157.36 | I43: FORMULA
A44: Broadcom — implied on NSR pool at BofA's 16% (2030) | B44: $bn | C44: =IF(OR(C6="",C31=""),"",C6*C31) | D44: =IF(OR(D6="",D31=""),"",D6*D31) | E44: =IF(OR(E6="",E31=""),"",E6*E31) | F44: =IF(OR(F6="",F31=""),"",F6*F31) | G44: =IF(OR(G6="",G31=""),"",G6*G31) | H44: =IF(OR(H6="",H31=""),"",H6*H31) -> 272.32 | I44: FORMULA
A46: F. Guardrails — implied revenue vs what the companies / consensus actually print
A47: NVIDIA total revenue — BBG consensus | B47: $bn | D47: 402.4 | E47: 701.2 | I47: HARD | J47: estimates.json asof 2026-09-18 (CY2026 / CY2027)
A48: NVIDIA data-center COMPUTE revenue — Capstone official model | B48: $bn | C48: 162 | D48: 313 | E48: 518 | I48: EST | J48: house.json NVDA ‘Compute / Networking’ 162/31, 313/67, 518/111 (Modelo Felipe NVDA, CY25-27). Compute INCLUDES Grace/Vera CPUs (ledger server-cpu-tam scope note), so this denominator is ~$5-20bn wider than the XPU-only numerator
A49: Implied NVDA XPU (NSR pool) ÷ Capstone DC compute | B49: x | C49: =IF(OR(C36="",C48=""),"",IFERROR(C36/C48,"")) -> 1.0565227 | D49: =IF(OR(D36="",D48=""),"",IFERROR(D36/D48,"")) -> 1.0160895 | E49: =IF(OR(E36="",E48=""),"",IFERROR(E36/E48,"")) -> 1.1386846 | F49: =IF(OR(F36="",F48=""),"",IFERROR(F36/F48,"")) | G49: =IF(OR(G36="",G48=""),"",IFERROR(G36/G48,"")) | H49: =IF(OR(H36="",H48=""),"",IFERROR(H36/H48,"")) | I49: FORMULA | J49: ≈ NSR pool ÷ Capstone pool, slightly flattered by the CPU inside the denominator
A50: Flag (±25%) | C50: =IF(OR(C36="",C48=""),"",IF(ABS(C36/C48-1)>0.25,"OFF >25%","OK")) -> OK | D50: =IF(OR(D36="",D48=""),"",IF(ABS(D36/D48-1)>0.25,"OFF >25%","OK")) -> OK | E50: =IF(OR(E36="",E48=""),"",IF(ABS(E36/E48-1)>0.25,"OFF >25%","OK")) -> OK | F50: =IF(OR(F36="",F48=""),"",IF(ABS(F36/F48-1)>0.25,"OFF >25%","OK")) | G50: =IF(OR(G36="",G48=""),"",IF(ABS(G36/G48-1)>0.25,"OFF >25%","OK")) | H50: =IF(OR(H36="",H48=""),"",IF(ABS(H36/H48-1)>0.25,"OFF >25%","OK"))
A51: Implied NVDA XPU (NSR pool) ÷ BBG NVDA total revenue | B51: x | C51: =IF(OR(C36="",C47=""),"",IFERROR(C36/C47,"")) | D51: =IF(OR(D36="",D47=""),"",IFERROR(D36/D47,"")) -> 0.79034791 | E51: =IF(OR(E36="",E47=""),"",IFERROR(E36/E47,"")) -> 0.84118456 | F51: =IF(OR(F36="",F47=""),"",IFERROR(F36/F47,"")) | G51: =IF(OR(G36="",G47=""),"",IFERROR(G36/G47,"")) | H51: =IF(OR(H36="",H47=""),"",IFERROR(H36/H47,"")) | I51: FORMULA | J51: Ceiling check: compute is ~77-80% of NVDA revenue in the house model; above ~0.85 NSR's pool exceeds what consensus gives NVIDIA
A52: Broadcom AI semiconductor revenue — NSR's OWN datapoint (fiscal years FY26-28, Nov-Oct) | B52: $bn | D52: 58 | E52: 115 | F52: 230 | I52: HARD | J52: NSR p.2: “AI semiconductor revenue of $58bn in FY26, $115bn in FY27 and $230bn in FY28” (= Broadcom guidance). Fiscal Nov-Oct ≈ one month ahead of CY
A53: Implied AVGO custom ASIC (NSR pool × Capstone mix) ÷ NSR's own AVGO AI semis | B53: x | C53: =IF(OR(C37="",C52=""),"",IFERROR(C37/C52,"")) | D53: =IF(OR(D37="",D52=""),"",IFERROR(D37/D52,"")) -> 1.0622069 | E53: =IF(OR(E37="",E52=""),"",IFERROR(E37/E52,"")) -> 1.1125016 | F53: =IF(OR(F37="",F52=""),"",IFERROR(F37/F52,"")) -> 1.3384137 | G53: =IF(OR(G37="",G52=""),"",IFERROR(G37/G52,"")) | H53: =IF(OR(H37="",H52=""),"",IFERROR(H37/H52,"")) | I53: FORMULA | J53: The cleanest XPU check in the note: NSR's pool × our ASIC mix gives MORE Broadcom revenue than NSR's own Broadcom datapoint (which even includes networking) — our ASIC mix is too rich for NSR's pool, or NSR's pool and vendor datapoints disagree
A54: Flag (±25%) | C54: =IF(OR(C37="",C52=""),"",IF(ABS(C37/C52-1)>0.25,"OFF >25%","OK")) | D54: =IF(OR(D37="",D52=""),"",IF(ABS(D37/D52-1)>0.25,"OFF >25%","OK")) -> OK | E54: =IF(OR(E37="",E52=""),"",IF(ABS(E37/E52-1)>0.25,"OFF >25%","OK")) -> OK | F54: =IF(OR(F37="",F52=""),"",IF(ABS(F37/F52-1)>0.25,"OFF >25%","OK")) -> OFF >25% | G54: =IF(OR(G37="",G52=""),"",IF(ABS(G37/G52-1)>0.25,"OFF >25%","OK")) | H54: =IF(OR(H37="",H52=""),"",IF(ABS(H37/H52-1)>0.25,"OFF >25%","OK"))
A55: Broadcom AI semis revenue — Capstone official model (incl. AI networking) | B55: $bn | C55: 24 | D55: 63 | E55: 132 | F55: 251 | I55: EST | J55: house.json AVGO ‘AI semis’ 14/24/63/132/251 (FY24-28, Modelo Avgo pós 2Q26; fiscal Nov-Oct placed in CY columns unadjusted, ~5-8% effect)
A56: Implied AVGO custom ASIC (NSR pool) ÷ Capstone AVGO AI semis incl. networking | B56: x | C56: =IF(OR(C37="",C55=""),"",IFERROR(C37/C55,"")) -> 0.90266824 | D56: =IF(OR(D37="",D55=""),"",IFERROR(D37/D55,"")) -> 0.97790476 | E56: =IF(OR(E37="",E55=""),"",IFERROR(E37/E55,"")) -> 0.9692249 | F56: =IF(OR(F37="",F55=""),"",IFERROR(F37/F55,"")) -> 1.2264349 | G56: =IF(OR(G37="",G55=""),"",IFERROR(G37/G55,"")) | H56: =IF(OR(H37="",H55=""),"",IFERROR(H37/H55,"")) | I56: FORMULA | J56: DIRECTIONAL test: must sit BELOW 1.0 because the denominator adds ~$15-25bn/yr of AI networking silicon. 2028 fails: the AI Model's AVGO XPU line ($284.6bn CY28) already exceeds the official AVGO model's AI semis ($251bn) — an internal house fork, not an NSR issue
A57: Flag (directional: OFF if implied XPU-only > house AI semis incl. networking) | C57: =IF(OR(C37="",C55=""),"",IF(C37>C55,"OFF","OK")) -> OK | D57: =IF(OR(D37="",D55=""),"",IF(D37>D55,"OFF","OK")) -> OK | E57: =IF(OR(E37="",E55=""),"",IF(E37>E55,"OFF","OK")) -> OK | F57: =IF(OR(F37="",F55=""),"",IF(F37>F55,"OFF","OK")) -> OFF | G57: =IF(OR(G37="",G55=""),"",IF(G37>G55,"OFF","OK")) | H57: =IF(OR(H37="",H55=""),"",IF(H37>H55,"OFF","OK"))
A58: AMD total revenue — BBG consensus | B58: $bn | D58: 50.6 | E58: 88.6 | I58: HARD | J58: estimates.json asof 2026-09-18
A59: Implied AMD GPU (NSR pool) ÷ BBG AMD total revenue | B59: x | C59: =IF(OR(C38="",C58=""),"",IFERROR(C38/C58,"")) | D59: =IF(OR(D38="",D58=""),"",IFERROR(D38/D58,"")) -> 0.41727273 | E59: =IF(OR(E38="",E58=""),"",IFERROR(E38/E58,"")) -> 0.44182702 | F59: =IF(OR(F38="",F58=""),"",IFERROR(F38/F58,"")) | G59: =IF(OR(G38="",G58=""),"",IFERROR(G38/G58,"")) | H59: =IF(OR(H38="",H58=""),"",IFERROR(H38/H58,"")) | I59: FORMULA | J59: MI GPUs are ~40-45% of AMD revenue in CY26-27 consensus; a ratio near 0.4-0.5 is consistent
A61: Reading: the share set is our own model's mix, so this sheet re-prices Capstone's vendor split onto NSR's larger pool (NSR ÷ Capstone pool 1.08x 2025, 1.02x 2027, 1.08x 2028; 1.20x 2030 on the stale July base). Two external checks bite: (1) NSR's own Broadcom datapoint ($230bn FY28 incl. networking) is 25% BELOW what NSR's pool × our ASIC mix implies for Broadcom XPUs alone — so either our 24.6% ASIC share in 2028 is too rich for NSR's pool, or NSR's pool is inconsistent with its own vendor marks; (2) on 2030 NVIDIA share the three marks are NSR 60%, our 64% (stale base) and BofA 68%. Do NOT add these vendor figures to the Share_Memory HBM figures: HBM is inside the XPU pool.

Sheet Share_CPU
A1: Server CPUs — vendor market share and implied revenue, 2025-2030 ($bn)
A2: Two NSR pools (total server-CPU market p.5; AI-slice p.4) and three share lenses: (1) Capstone Semis MAP head-node value shares (EST, systems-value basis), (2) Bernstein unit shares (HARD units; unit ≠ value), (3) a street-anchored SILICON value build from reported / printed vendor figures (Intel: BofA's printed 08-12 path; AMD: segment prints + UBS 05-21 on its own TAM; NVIDIA: Bernstein units × $4k chip ASP, with management's systems-basis reading as a scenario). Lens 3 is load-bearing. Skeptic-revised 2026-09-18.
A4: Line | B4: Unit | C4: 2025 | D4: 2026 | E4: 2027 | F4: 2028 | G4: 2029 | H4: 2030 | I4: Tag | J4: Source
A5: A. Pools ($bn) and external TAM marks
A6: NSR total server-CPU market (p.5 ‘CPUs spending’) | B6: $bn | C6: =IF(NSR_Memory!C25="","",NSR_Memory!C25) -> 25 | D6: =IF(NSR_Memory!D25="","",NSR_Memory!D25) -> 49 | E6: =IF(NSR_Memory!E25="","",NSR_Memory!E25) -> 80 | F6: =IF(NSR_Memory!F25="","",NSR_Memory!F25) -> 117 | G6: =IF(NSR_Memory!G25="","",NSR_Memory!G25) -> 159 | H6: =IF(NSR_Memory!H25="","",NSR_Memory!H25) -> 202 | I6: LINK | J6: NSR p.5 (NSR_Memory)
A7: NSR AI-slice CPUs (p.4) | B7: $bn | C7: =IF(NSR_Capex!C6="","",NSR_Capex!C6) -> 6 | D7: =IF(NSR_Capex!D6="","",NSR_Capex!D6) -> 27 | E7: =IF(NSR_Capex!E6="","",NSR_Capex!E6) -> 56 | F7: =IF(NSR_Capex!F6="","",NSR_Capex!F6) -> 90 | G7: =IF(NSR_Capex!G6="","",NSR_Capex!G6) -> 129 | H7: =IF(NSR_Capex!H6="","",NSR_Capex!H6) -> 168 | I7: LINK | J7: NSR p.4 (NSR_Capex)
A8: Capstone AI head-node CPUs — Semis MAP BofA-mix line (uncalibrated) | B8: $bn | C8: =IF(House!E38="","",House!E38) -> 15.2 | D8: =IF(House!F38="","",House!F38) -> 40.2 | E8: =IF(House!G38="","",House!G38) -> 79.2 | F8: =IF(House!H38="","",House!H38) -> 127.2 | G8: =IF(House!I38="","",House!I38) -> 150.1 | H8: =IF(House!J38="","",House!J38) -> 171.1 | I8: LINK | J8: House!sm_cpu (Semis MAP v11 ‘AI DC TAM (BofA mix)’ AI CPUs = BofA ratio × house capex)
A9: Capstone AI head-node CPUs — Semis MAP Build | CPU CALIBRATED line | B9: $bn | C9: 9.3 | D9: 24.6 | E9: 48.4 | F9: 77.8 | G9: 91.8 | H9: 104.7 | I9: EST | J9: AI_Chip_Designers_TAM_v11.xlsx → Build | CPU row 3 (the sheet's own ‘capture-calibrated version’). On this line NSR's AI-slice CPU pool is ~60% ABOVE the house in 2030; on the uncalibrated line above they look aligned — the alignment is a series choice
A10: Capstone total server-CPU (ledger canon) | B10: $bn | C10: =IF(House!E116="","",House!E116) | D10: =IF(House!F116="","",House!F116) -> 55 | E10: =IF(House!G116="","",House!G116) -> 96 | F10: =IF(House!H116="","",House!H116) -> 137 | G10: =IF(House!I116="","",House!I116) | H10: =IF(House!J116="","",House!J116) -> 190 | I10: LINK | J10: House!lg_cpu (assumptions.md server-cpu-tam: ~$55bn CY26 / $96bn CY27 / $137bn CY28 / ~$190bn 2030)
A11: External TAM — BofA (2026-08-12): ~$35bn CY25 level → $210.6bn CY30E | B11: $bn | C11: 35 | H11: 210.6 | I11: HARD | J11: INTC.md rows ~409/553: BofA raised CY30E server-CPU TAM to $210.6bn (from ~$170bn on 07-13); Intel value share 40.4% → 22.0%
A12: External TAM — UBS ‘CPU TAM’ (2026-05-21): $31bn 2025 → $74bn 2027E → $173bn 2030E | B12: $bn | C12: 31 | E12: 74 | H12: 173 | I12: HARD | J12: AMD.md row ~212 / ARM.md: UBS unit shares Intel 60% → 29%, Arm 16% → 42%, AMD 24% → 29% (2025 → 2030); AMD value share 24% → 27% (2027E) → 29% (2030E)
A13: External TAM — Bernstein Rasgon (2026-06-16): $37bn 2025 → $137bn 2030 BASE ($223bn BULL) | B13: $bn | C13: 37 | H13: 137 | I13: HARD | J13: assumptions.md server-cpu-tam
A14: Company target — AMD Advancing AI (2026-07-23): $220bn 2030, AMD share >50% | B14: $bn | H14: 220 | I14: HARD | J14: assumptions.md server-cpu-tam; company event TAM, high bias
A16: B. Lens 1 — Capstone Semis MAP head-node value shares (AI servers only; systems-value basis)
A17: Intel (Xeon head-node) | B17: % | C17: 0.28 | D17: 0.22 | E17: 0.18 | F17: 0.15 | G17: =F17 -> 0.15 | H17: =F17 -> 0.15 | I17: EST | J17: AI_Chip_Designers_TAM_v11.xlsx → Build | CPU rows 7-10 (2026-07-16); CY29-30 held at CY28. Systems-value shares: NVIDIA's 38% carries Grace/Vera at superchip value, which is why lens 1 can exceed the silicon build in block D
A18: AMD (EPYC head-node) | B18: % | C18: 0.3 | D18: 0.26 | E18: 0.24 | F18: 0.22 | G18: =F18 -> 0.22 | H18: =F18 -> 0.22 | I18: EST | J18: same source
A19: NVIDIA (Grace / Vera inside GB200-GB300-VR200 superchips) | B19: % | C19: 0.25 | D19: 0.33 | E19: 0.36 | F19: 0.38 | G19: =F19 -> 0.38 | H19: =F19 -> 0.38 | I19: EST | J19: same source
A20: Captive Arm (Graviton / Axion / Cobalt / Maia-CPU) + others | B20: % | C20: 0.17 | D20: 0.19 | E20: 0.22 | F20: 0.25 | G20: =F20 -> 0.25 | H20: =F20 -> 0.25 | I20: EST | J20: same source
A21: Check: sum of shares | B21: % | C21: =SUM(C17:C20) -> 1 | D21: =SUM(D17:D20) -> 1 | E21: =SUM(E17:E20) -> 1 | F21: =SUM(F17:F20) -> 1 | G21: =SUM(G17:G20) -> 1 | H21: =SUM(H17:H20) -> 1 | I21: FORMULA
A23: C. Lens 2 — Bernstein server-CPU UNITS by vendor (mn units) → unit shares
A24: Intel (excl. Atom) | B24: mn | C24: 18.8 | D24: 21.6 | E24: 24.3 | F24: 26.5 | G24: 31.4 | H24: 38 | I24: HARD | J24: Bernstein · Qingyuan Lin, ‘Global memory interface chips’ model (P:\Felipe Monteiro\Memória\Bernstein on CPU.xlsx → PPT output rows 5-9; server CPU excl. IoT)
A25: AMD | B25: mn | C25: 7.2 | D25: 9.7 | E25: 12.7 | F25: 16.4 | G25: 21.1 | H25: 26.5 | I25: HARD | J25: same source (Bernstein PPT output)
A26: Hygon (China x86) | B26: mn | C26: 1.8 | D26: 2.2 | E26: 3.3 | F26: 5.7 | G26: 8.8 | H26: 11.8 | I26: HARD | J26: same source
A27: Arm — non-NVIDIA (Graviton / Axion / Cobalt / Ampere etc.) | B27: mn | C27: 2.7 | D27: 3.8 | E27: 5.3 | F27: 6.9 | G27: 9.2 | H27: 13 | I27: HARD | J27: same source
A28: Arm — NVIDIA (Grace / Vera) | B28: mn | C28: 1.2 | D28: 2.7 | E28: 6.1 | F28: 6.1 | G28: 6.1 | H28: 5.9 | I28: HARD | J28: same source — note Bernstein has NVIDIA units FLAT 2027-30
A29: Total server CPU units | B29: mn | C29: =SUM(C24:C28) -> 31.7 | D29: =SUM(D24:D28) -> 40 | E29: =SUM(E24:E28) -> 51.7 | F29: =SUM(F24:F28) -> 61.6 | G29: =SUM(G24:G28) -> 76.6 | H29: =SUM(H24:H28) -> 95.2 | I29: FORMULA | J29: Bernstein prints 31.8 / 40.0 / 51.6 mn for 2025-27; JPM proprietary model 26M (2025) → 68M (2028) for comparison
A30: Intel — UNIT share | B30: % | C30: =IF(OR(C24="",C29=""),"",IFERROR(C24/C29,"")) -> 0.59305994 | D30: =IF(OR(D24="",D29=""),"",IFERROR(D24/D29,"")) -> 0.54 | E30: =IF(OR(E24="",E29=""),"",IFERROR(E24/E29,"")) -> 0.47001934 | F30: =IF(OR(F24="",F29=""),"",IFERROR(F24/F29,"")) -> 0.43019481 | G30: =IF(OR(G24="",G29=""),"",IFERROR(G24/G29,"")) -> 0.40992167 | H30: =IF(OR(H24="",H29=""),"",IFERROR(H24/H29,"")) -> 0.39915966 | I30: FORMULA | J30: → units / total units (Bernstein). UBS 2026-05-21 unit shares for reference: Intel 60% → 29%, Arm 16% → 42%, AMD 24% → 29% (2025 → 2030)
A31: AMD — UNIT share | B31: % | C31: =IF(OR(C25="",C29=""),"",IFERROR(C25/C29,"")) -> 0.22712934 | D31: =IF(OR(D25="",D29=""),"",IFERROR(D25/D29,"")) -> 0.2425 | E31: =IF(OR(E25="",E29=""),"",IFERROR(E25/E29,"")) -> 0.24564797 | F31: =IF(OR(F25="",F29=""),"",IFERROR(F25/F29,"")) -> 0.26623377 | G31: =IF(OR(G25="",G29=""),"",IFERROR(G25/G29,"")) -> 0.27545692 | H31: =IF(OR(H25="",H29=""),"",IFERROR(H25/H29,"")) -> 0.27836134 | I31: FORMULA | J31: → units / total units
A32: Hygon — UNIT share | B32: % | C32: =IF(OR(C26="",C29=""),"",IFERROR(C26/C29,"")) -> 0.056782334 | D32: =IF(OR(D26="",D29=""),"",IFERROR(D26/D29,"")) -> 0.055 | E32: =IF(OR(E26="",E29=""),"",IFERROR(E26/E29,"")) -> 0.063829787 | F32: =IF(OR(F26="",F29=""),"",IFERROR(F26/F29,"")) -> 0.092532468 | G32: =IF(OR(G26="",G29=""),"",IFERROR(G26/G29,"")) -> 0.11488251 | H32: =IF(OR(H26="",H29=""),"",IFERROR(H26/H29,"")) -> 0.12394958 | I32: FORMULA | J32: → units / total units
A33: Arm non-NVIDIA — UNIT share | B33: % | C33: =IF(OR(C27="",C29=""),"",IFERROR(C27/C29,"")) -> 0.085173502 | D33: =IF(OR(D27="",D29=""),"",IFERROR(D27/D29,"")) -> 0.095 | E33: =IF(OR(E27="",E29=""),"",IFERROR(E27/E29,"")) -> 0.10251451 | F33: =IF(OR(F27="",F29=""),"",IFERROR(F27/F29,"")) -> 0.11201299 | G33: =IF(OR(G27="",G29=""),"",IFERROR(G27/G29,"")) -> 0.12010444 | H33: =IF(OR(H27="",H29=""),"",IFERROR(H27/H29,"")) -> 0.13655462 | I33: FORMULA | J33: → units / total units
A34: Arm NVIDIA — UNIT share | B34: % | C34: =IF(OR(C28="",C29=""),"",IFERROR(C28/C29,"")) -> 0.03785489 | D34: =IF(OR(D28="",D29=""),"",IFERROR(D28/D29,"")) -> 0.0675 | E34: =IF(OR(E28="",E29=""),"",IFERROR(E28/E29,"")) -> 0.11798839 | F34: =IF(OR(F28="",F29=""),"",IFERROR(F28/F29,"")) -> 0.099025974 | G34: =IF(OR(G28="",G29=""),"",IFERROR(G28/G29,"")) -> 0.079634465 | H34: =IF(OR(H28="",H29=""),"",IFERROR(H28/H29,"")) -> 0.06197479 | I34: FORMULA | J34: → units / total units
A36: D. Lens 3 — street-anchored SILICON value build ($bn of server-CPU revenue by vendor)
A37: Intel server CPU revenue — BofA printed path | B37: $bn | C37: 14.1 | D37: 20.8 | E37: 27.8 | F37: 33.6 | G37: 39.7 | H37: 46.3 | I37: HARD | J37: BofA (2026-08-12, INTC.md ~row 553): $14.1bn CY25 → $20.8bn CY26E → $27.8bn CY27E → $33.6bn CY28E → $46.3bn CY30E (value share 40.4% → 22.0% of a $210.6bn TAM). CY29 = midpoint EST. Cross-check: DCAI prints 1Q26 $5.1bn, 2Q26 $6.26bn (+59% y/y) → CY26 DCAI ≈ $24-25bn incl. ~$2bn custom ASIC
A38: AMD server CPU (EPYC) revenue | B38: $bn | C38: 10 | D38: 16.4 | E38: 22 | F38: 29 | G38: 38 | H38: 50 | I38: PARTIAL | J38: CY26 from segment prints: 2Q26 server CPU $3.63bn, 3Q26 guide $4.53bn (GS model, AMD.md ~row 465) → ≈ $16bn; CY25 ≈ $10bn (35-40% growth). CY30 = UBS 05-21 on ITS OWN TAM: 29% × $173bn ≈ $50bn (skeptic fix — the earlier $75bn crossed UBS's ‘~40% value share’ from a $60bn-TAM vintage onto a $190bn pool). 2027-29 EST path
A39: NVIDIA CPU chip ASP (Grace / Vera) | B39: $k | C39: 4 | D39: 4 | E39: 4 | F39: 4 | G39: 4 | H39: 4 | I39: PARTIAL | J39: Jefferies bottom-up: standalone Vera ‘at a $4k ASP’ (NVDA.md ~row 1211); BofA Core Wars: Vera $4-5k (assumptions.md server-cpu-tam). Cross-check: 1.2mn units × $4k = $4.8bn ≈ Grace TTM revenue ‘>$5bn’ (NVDA mgmt)
A40: NVIDIA CPU revenue — CHIP basis (Bernstein units × ASP) | B40: $bn | C40: =IF(OR(C28="",C39=""),"",C28*C39) -> 4.8 | D40: =IF(OR(D28="",D39=""),"",D28*D39) -> 10.8 | E40: =IF(OR(E28="",E39=""),"",E28*E39) -> 24.4 | F40: =IF(OR(F28="",F39=""),"",F28*F39) -> 24.4 | G40: =IF(OR(G28="",G39=""),"",G28*G39) -> 24.4 | H40: =IF(OR(H28="",H39=""),"",H28*H39) -> 23.6 | I40: FORMULA | J40: → Arm-NVIDIA units × chip ASP. This is the SILICON figure comparable to NSR's CPU pool
A41: NVIDIA CPU — SYSTEMS-basis reading (scenario, not used in the build) | B41: $bn | C41: 5 | D41: 20 | E41: 40 | I41: SCENARIO | J41: NVDA mgmt (Q2 FY27 call, AMD.md ~row 106): Grace TTM revenue ‘>$5bn’; ‘demand for approximately $20 billion in total server CPUs’ (DEMAND SEEN, not a revenue guide); ‘CPU revenue to more than double in fiscal 28’. Reading the doubling off $20bn gives ~$40bn FY28 (Jefferies/relayed ‘$40bn target’, NVDA.md ~row 1075); off the >$5bn Grace base it gives ~$10bn+ (AMD.md ~row 108). UBS Arcuri: the $20bn is systems + DRAM, ~$5bn / ~1mn units of Vera chip at $3-4k (ARM.md). Skeptic: the earlier build carried NVIDIA at ~2x the $4k chip ASP
A42: Captive Arm + Hygon + others — units (Bernstein, mn) | B42: mn | C42: =C27+C26 -> 4.5 | D42: =D27+D26 -> 6 | E42: =E27+E26 -> 8.6 | F42: =F27+F26 -> 12.6 | G42: =G27+G26 -> 18 | H42: =H27+H26 -> 24.8 | I42: FORMULA | J42: → Arm non-NVIDIA + Hygon units
A43: Captive Arm + Hygon — blended value per unit | B43: $k | C43: 1.2 | D43: 1.2 | E43: 1.2 | F43: 1.2 | G43: 1.2 | H43: 1.2 | I43: EST | J43: Cost-based captive silicon (Graviton/Axion) blended with merchant Hygon (likely $2-3k); no disclosed ASP. Sensitivity: ±$0.5k moves this line ±42%, the 2030 anchor sum ±8%
A44: Captive Arm + Hygon + others — implied revenue | B44: $bn | C44: =IF(OR(C42="",C43=""),"",C42*C43) -> 5.4 | D44: =IF(OR(D42="",D43=""),"",D42*D43) -> 7.2 | E44: =IF(OR(E42="",E43=""),"",E42*E43) -> 10.32 | F44: =IF(OR(F42="",F43=""),"",F42*F43) -> 15.12 | G44: =IF(OR(G42="",G43=""),"",G42*G43) -> 21.6 | H44: =IF(OR(H42="",H43=""),"",H42*H43) -> 29.76 | I44: FORMULA | J44: units × value per unit (EST)
A45: Sum of vendor anchors = bottom-up server-CPU SILICON market (chip-basis NVIDIA) | B45: $bn | C45: =C37+C38+C40+C44 -> 34.3 | D45: =D37+D38+D40+D44 -> 55.2 | E45: =E37+E38+E40+E44 -> 84.52 | F45: =F37+F38+F40+F44 -> 102.12 | G45: =G37+G38+G40+G44 -> 123.7 | H45: =H37+H38+H40+H44 -> 149.66 | I45: FORMULA | J45: Compare with block A: BofA ~$35bn CY25 level and Bernstein $37bn corroborate the 2025 sum independently of the NVIDIA basis
A46: Alt sum with the SYSTEMS-basis NVIDIA scenario (2025-27 only) | B46: $bn | C46: =IF(C41="","",C45-C40+C41) -> 34.5 | D46: =IF(D41="","",D45-D40+D41) -> 64.4 | E46: =IF(E41="","",E45-E40+E41) -> 100.12 | F46: =IF(F41="","",F45-F40+F41) | G46: =IF(G41="","",G45-G40+G41) | H46: =IF(H41="","",H45-H40+H41) | I46: FORMULA | J46: → swaps the NVIDIA line; shows how much of the 2026-27 verdict depends on the basis
A47: Intel — VALUE share of the silicon anchor build | B47: % | C47: =IF(OR(C37="",C45=""),"",IFERROR(C37/C45,"")) -> 0.41107872 | D47: =IF(OR(D37="",D45=""),"",IFERROR(D37/D45,"")) -> 0.37681159 | E47: =IF(OR(E37="",E45=""),"",IFERROR(E37/E45,"")) -> 0.32891623 | F47: =IF(OR(F37="",F45=""),"",IFERROR(F37/F45,"")) -> 0.32902468 | G47: =IF(OR(G37="",G45=""),"",IFERROR(G37/G45,"")) -> 0.32093775 | H47: =IF(OR(H37="",H45=""),"",IFERROR(H37/H45,"")) -> 0.3093679 | I47: FORMULA | J47: → vendor $ / sum of anchors (chip basis)
A48: AMD — VALUE share of the silicon anchor build | B48: % | C48: =IF(OR(C38="",C45=""),"",IFERROR(C38/C45,"")) -> 0.29154519 | D48: =IF(OR(D38="",D45=""),"",IFERROR(D38/D45,"")) -> 0.29710145 | E48: =IF(OR(E38="",E45=""),"",IFERROR(E38/E45,"")) -> 0.26029342 | F48: =IF(OR(F38="",F45=""),"",IFERROR(F38/F45,"")) -> 0.28397963 | G48: =IF(OR(G38="",G45=""),"",IFERROR(G38/G45,"")) -> 0.30719483 | H48: =IF(OR(H38="",H45=""),"",IFERROR(H38/H45,"")) -> 0.33409061 | I48: FORMULA | J48: → vendor $ / sum of anchors (chip basis)
A49: NVIDIA — VALUE share of the silicon anchor build | B49: % | C49: =IF(OR(C40="",C45=""),"",IFERROR(C40/C45,"")) -> 0.13994169 | D49: =IF(OR(D40="",D45=""),"",IFERROR(D40/D45,"")) -> 0.19565217 | E49: =IF(OR(E40="",E45=""),"",IFERROR(E40/E45,"")) -> 0.28868907 | F49: =IF(OR(F40="",F45=""),"",IFERROR(F40/F45,"")) -> 0.23893459 | G49: =IF(OR(G40="",G45=""),"",IFERROR(G40/G45,"")) -> 0.19725141 | H49: =IF(OR(H40="",H45=""),"",IFERROR(H40/H45,"")) -> 0.15769077 | I49: FORMULA | J49: → vendor $ / sum of anchors (chip basis)
A50: Captive Arm + Hygon + others — VALUE share of the silicon anchor build | B50: % | C50: =IF(OR(C44="",C45=""),"",IFERROR(C44/C45,"")) -> 0.1574344 | D50: =IF(OR(D44="",D45=""),"",IFERROR(D44/D45,"")) -> 0.13043478 | E50: =IF(OR(E44="",E45=""),"",IFERROR(E44/E45,"")) -> 0.12210128 | F50: =IF(OR(F44="",F45=""),"",IFERROR(F44/F45,"")) -> 0.1480611 | G50: =IF(OR(G44="",G45=""),"",IFERROR(G44/G45,"")) -> 0.17461601 | H50: =IF(OR(H44="",H45=""),"",IFERROR(H44/H45,"")) -> 0.19885073 | I50: FORMULA | J50: → vendor $ / sum of anchors (chip basis)
A52: E. Implied vendor revenue on the NSR pools ($bn)
A53: Intel — NSR TOTAL pool × anchor-build value share | B53: $bn | C53: =IF(OR(C6="",C47=""),"",C6*C47) -> 10.276968 | D53: =IF(OR(D6="",D47=""),"",D6*D47) -> 18.463768 | E53: =IF(OR(E6="",E47=""),"",E6*E47) -> 26.313299 | F53: =IF(OR(F6="",F47=""),"",F6*F47) -> 38.495887 | G53: =IF(OR(G6="",G47=""),"",G6*G47) -> 51.029103 | H53: =IF(OR(H6="",H47=""),"",H6*H47) -> 62.492316 | I53: FORMULA | J53: what each vendor would book if NSR's total CPU pool is right and the silicon anchor mix holds
A54: AMD — NSR TOTAL pool × anchor-build value share | B54: $bn | C54: =IF(OR(C6="",C48=""),"",C6*C48) -> 7.2886297 | D54: =IF(OR(D6="",D48=""),"",D6*D48) -> 14.557971 | E54: =IF(OR(E6="",E48=""),"",E6*E48) -> 20.823474 | F54: =IF(OR(F6="",F48=""),"",F6*F48) -> 33.225617 | G54: =IF(OR(G6="",G48=""),"",G6*G48) -> 48.843977 | H54: =IF(OR(H6="",H48=""),"",H6*H48) -> 67.486302 | I54: FORMULA | J54: what each vendor would book if NSR's total CPU pool is right and the silicon anchor mix holds
A55: NVIDIA — NSR TOTAL pool × anchor-build value share | B55: $bn | C55: =IF(OR(C6="",C49=""),"",C6*C49) -> 3.4985423 | D55: =IF(OR(D6="",D49=""),"",D6*D49) -> 9.5869565 | E55: =IF(OR(E6="",E49=""),"",E6*E49) -> 23.095125 | F55: =IF(OR(F6="",F49=""),"",F6*F49) -> 27.955347 | G55: =IF(OR(G6="",G49=""),"",G6*G49) -> 31.362975 | H55: =IF(OR(H6="",H49=""),"",H6*H49) -> 31.853535 | I55: FORMULA | J55: what each vendor would book if NSR's total CPU pool is right and the silicon anchor mix holds
A56: Captive Arm + Hygon + others — NSR TOTAL pool × anchor-build value share | B56: $bn | C56: =IF(OR(C6="",C50=""),"",C6*C50) -> 3.9358601 | D56: =IF(OR(D6="",D50=""),"",D6*D50) -> 6.3913043 | E56: =IF(OR(E6="",E50=""),"",E6*E50) -> 9.7681022 | F56: =IF(OR(F6="",F50=""),"",F6*F50) -> 17.323149 | G56: =IF(OR(G6="",G50=""),"",G6*G50) -> 27.763945 | H56: =IF(OR(H6="",H50=""),"",H6*H50) -> 40.167847 | I56: FORMULA | J56: what each vendor would book if NSR's total CPU pool is right and the silicon anchor mix holds
A57: Intel — NSR AI-slice pool × Capstone head-node share (lens 1) | B57: $bn | C57: =IF(OR(C7="",C17=""),"",C7*C17) -> 1.68 | D57: =IF(OR(D7="",D17=""),"",D7*D17) -> 5.94 | E57: =IF(OR(E7="",E17=""),"",E7*E17) -> 10.08 | F57: =IF(OR(F7="",F17=""),"",F7*F17) -> 13.5 | G57: =IF(OR(G7="",G17=""),"",G7*G17) -> 19.35 | H57: =IF(OR(H7="",H17=""),"",H7*H17) -> 25.2 | I57: FORMULA | J57: AI head-node only, systems-value basis
A58: AMD — NSR AI-slice pool × Capstone head-node share (lens 1) | B58: $bn | C58: =IF(OR(C7="",C18=""),"",C7*C18) -> 1.8 | D58: =IF(OR(D7="",D18=""),"",D7*D18) -> 7.02 | E58: =IF(OR(E7="",E18=""),"",E7*E18) -> 13.44 | F58: =IF(OR(F7="",F18=""),"",F7*F18) -> 19.8 | G58: =IF(OR(G7="",G18=""),"",G7*G18) -> 28.38 | H58: =IF(OR(H7="",H18=""),"",H7*H18) -> 36.96 | I58: FORMULA | J58: AI head-node only, systems-value basis
A59: NVIDIA — NSR AI-slice pool × Capstone head-node share (lens 1) | B59: $bn | C59: =IF(OR(C7="",C19=""),"",C7*C19) -> 1.5 | D59: =IF(OR(D7="",D19=""),"",D7*D19) -> 8.91 | E59: =IF(OR(E7="",E19=""),"",E7*E19) -> 20.16 | F59: =IF(OR(F7="",F19=""),"",F7*F19) -> 34.2 | G59: =IF(OR(G7="",G19=""),"",G7*G19) -> 49.02 | H59: =IF(OR(H7="",H19=""),"",H7*H19) -> 63.84 | I59: FORMULA | J59: AI head-node only, systems-value basis
A60: Captive Arm + others — NSR AI-slice pool × Capstone head-node share (lens 1) | B60: $bn | C60: =IF(OR(C7="",C20=""),"",C7*C20) -> 1.02 | D60: =IF(OR(D7="",D20=""),"",D7*D20) -> 5.13 | E60: =IF(OR(E7="",E20=""),"",E7*E20) -> 12.32 | F60: =IF(OR(F7="",F20=""),"",F7*F20) -> 22.5 | G60: =IF(OR(G7="",G20=""),"",G7*G20) -> 32.25 | H60: =IF(OR(H7="",H20=""),"",H7*H20) -> 42 | I60: FORMULA | J60: AI head-node only, systems-value basis
A62: F. Guardrails
A63: NSR total CPU pool ÷ silicon anchor sum (chip-basis NVIDIA) | B63: x | C63: =IF(OR(C6="",C45=""),"",IFERROR(C6/C45,"")) -> 0.72886297 | D63: =IF(OR(D6="",D45=""),"",IFERROR(D6/D45,"")) -> 0.88768116 | E63: =IF(OR(E6="",E45=""),"",IFERROR(E6/E45,"")) -> 0.94652153 | F63: =IF(OR(F6="",F45=""),"",IFERROR(F6/F45,"")) -> 1.1457109 | G63: =IF(OR(G6="",G45=""),"",IFERROR(G6/G45,"")) -> 1.2853678 | H63: =IF(OR(H6="",H45=""),"",IFERROR(H6/H45,"")) -> 1.349726 | I63: FORMULA | J63: Below 1.0 = NSR's pool is smaller than what vendors already report; above 1.25 = NSR's pool needs more than the vendor anchors deliver (captive Arm ASP / NVIDIA basis / a 2029-30 AMD path above UBS)
A64: Flag (±25%) | C64: =IF(OR(C6="",C45=""),"",IF(ABS(C6/C45-1)>0.25,"OFF >25%","OK")) -> OFF >25% | D64: =IF(OR(D6="",D45=""),"",IF(ABS(D6/D45-1)>0.25,"OFF >25%","OK")) -> OK | E64: =IF(OR(E6="",E45=""),"",IF(ABS(E6/E45-1)>0.25,"OFF >25%","OK")) -> OK | F64: =IF(OR(F6="",F45=""),"",IF(ABS(F6/F45-1)>0.25,"OFF >25%","OK")) -> OK | G64: =IF(OR(G6="",G45=""),"",IF(ABS(G6/G45-1)>0.25,"OFF >25%","OK")) -> OFF >25% | H64: =IF(OR(H6="",H45=""),"",IF(ABS(H6/H45-1)>0.25,"OFF >25%","OK")) -> OFF >25%
A65: NSR total CPU pool ÷ alt sum (systems-basis NVIDIA scenario) | B65: x | C65: =IF(OR(C6="",C46=""),"",IFERROR(C6/C46,"")) -> 0.72463768 | D65: =IF(OR(D6="",D46=""),"",IFERROR(D6/D46,"")) -> 0.76086957 | E65: =IF(OR(E6="",E46=""),"",IFERROR(E6/E46,"")) -> 0.79904115 | F65: =IF(OR(F6="",F46=""),"",IFERROR(F6/F46,"")) | G65: =IF(OR(G6="",G46=""),"",IFERROR(G6/G46,"")) | H65: =IF(OR(H6="",H46=""),"",IFERROR(H6/H46,"")) | I65: FORMULA | J65: 2026 turns OFF on the systems reading and OK on the chip reading — the 2026 verdict is a basis call; 2025 is OFF on both
A66: Flag (±25%) | C66: =IF(OR(C6="",C46=""),"",IF(ABS(C6/C46-1)>0.25,"OFF >25%","OK")) -> OFF >25% | D66: =IF(OR(D6="",D46=""),"",IF(ABS(D6/D46-1)>0.25,"OFF >25%","OK")) -> OK | E66: =IF(OR(E6="",E46=""),"",IF(ABS(E6/E46-1)>0.25,"OFF >25%","OK")) -> OK | F66: =IF(OR(F6="",F46=""),"",IF(ABS(F6/F46-1)>0.25,"OFF >25%","OK")) | G66: =IF(OR(G6="",G46=""),"",IF(ABS(G6/G46-1)>0.25,"OFF >25%","OK")) | H66: =IF(OR(H6="",H46=""),"",IF(ABS(H6/H46-1)>0.25,"OFF >25%","OK"))
A67: Capstone total CPU pool ÷ silicon anchor sum | B67: x | C67: =IF(OR(C10="",C45=""),"",IFERROR(C10/C45,"")) | D67: =IF(OR(D10="",D45=""),"",IFERROR(D10/D45,"")) -> 0.99637681 | E67: =IF(OR(E10="",E45=""),"",IFERROR(E10/E45,"")) -> 1.1358258 | F67: =IF(OR(F10="",F45=""),"",IFERROR(F10/F45,"")) -> 1.341559 | G67: =IF(OR(G10="",G45=""),"",IFERROR(G10/G45,"")) | H67: =IF(OR(H10="",H45=""),"",IFERROR(H10/H45,"")) -> 1.2695443 | I67: FORMULA | J67: House ledger $55bn / $96bn / $137bn vs anchors
A68: Flag (±25%) | C68: =IF(OR(C10="",C45=""),"",IF(ABS(C10/C45-1)>0.25,"OFF >25%","OK")) | D68: =IF(OR(D10="",D45=""),"",IF(ABS(D10/D45-1)>0.25,"OFF >25%","OK")) -> OK | E68: =IF(OR(E10="",E45=""),"",IF(ABS(E10/E45-1)>0.25,"OFF >25%","OK")) -> OK | F68: =IF(OR(F10="",F45=""),"",IF(ABS(F10/F45-1)>0.25,"OFF >25%","OK")) -> OFF >25% | G68: =IF(OR(G10="",G45=""),"",IF(ABS(G10/G45-1)>0.25,"OFF >25%","OK")) | H68: =IF(OR(H10="",H45=""),"",IF(ABS(H10/H45-1)>0.25,"OFF >25%","OK")) -> OFF >25%
A69: Consistency: lens-1 head-node implied ÷ lens-3 total implied — Intel | B69: x | C69: =IF(OR(C57="",C53=""),"",IFERROR(C57/C53,"")) -> 0.16347234 | D69: =IF(OR(D57="",D53=""),"",IFERROR(D57/D53,"")) -> 0.32171115 | E69: =IF(OR(E57="",E53=""),"",IFERROR(E57/E53,"")) -> 0.38307626 | F69: =IF(OR(F57="",F53=""),"",IFERROR(F57/F53,"")) -> 0.35068681 | G69: =IF(OR(G57="",G53=""),"",IFERROR(G57/G53,"")) -> 0.37919538 | H69: =IF(OR(H57="",H53=""),"",IFERROR(H57/H53,"")) -> 0.40324958 | I69: FORMULA | J69: A subset (AI head-node) cannot exceed the whole market; >1.0 means the Semis MAP systems-value share is inconsistent with the silicon build for that vendor
A70: Flag (directional) | C70: =IF(OR(C57="",C53=""),"",IF(C57>C53,"OFF","OK")) -> OK | D70: =IF(OR(D57="",D53=""),"",IF(D57>D53,"OFF","OK")) -> OK | E70: =IF(OR(E57="",E53=""),"",IF(E57>E53,"OFF","OK")) -> OK | F70: =IF(OR(F57="",F53=""),"",IF(F57>F53,"OFF","OK")) -> OK | G70: =IF(OR(G57="",G53=""),"",IF(G57>G53,"OFF","OK")) -> OK | H70: =IF(OR(H57="",H53=""),"",IF(H57>H53,"OFF","OK")) -> OK
A71: Consistency: lens-1 head-node implied ÷ lens-3 total implied — AMD | B71: x | C71: =IF(OR(C58="",C54=""),"",IFERROR(C58/C54,"")) -> 0.24696 | D71: =IF(OR(D58="",D54=""),"",IFERROR(D58/D54,"")) -> 0.48221005 | E71: =IF(OR(E58="",E54=""),"",IFERROR(E58/E54,"")) -> 0.64542545 | F71: =IF(OR(F58="",F54=""),"",IFERROR(F58/F54,"")) -> 0.59592573 | G71: =IF(OR(G58="",G54=""),"",IFERROR(G58/G54,"")) -> 0.58103376 | H71: =IF(OR(H58="",H54=""),"",IFERROR(H58/H54,"")) -> 0.54766669 | I71: FORMULA | J71: A subset (AI head-node) cannot exceed the whole market; >1.0 means the Semis MAP systems-value share is inconsistent with the silicon build for that vendor
A72: Flag (directional) | C72: =IF(OR(C58="",C54=""),"",IF(C58>C54,"OFF","OK")) -> OK | D72: =IF(OR(D58="",D54=""),"",IF(D58>D54,"OFF","OK")) -> OK | E72: =IF(OR(E58="",E54=""),"",IF(E58>E54,"OFF","OK")) -> OK | F72: =IF(OR(F58="",F54=""),"",IF(F58>F54,"OFF","OK")) -> OK | G72: =IF(OR(G58="",G54=""),"",IF(G58>G54,"OFF","OK")) -> OK | H72: =IF(OR(H58="",H54=""),"",IF(H58>H54,"OFF","OK")) -> OK
A73: Consistency: lens-1 head-node implied ÷ lens-3 total implied — NVIDIA | B73: x | C73: =IF(OR(C59="",C55=""),"",IFERROR(C59/C55,"")) -> 0.42875 | D73: =IF(OR(D59="",D55=""),"",IFERROR(D59/D55,"")) -> 0.92938776 | E73: =IF(OR(E59="",E55=""),"",IFERROR(E59/E55,"")) -> 0.87291148 | F73: =IF(OR(F59="",F55=""),"",IFERROR(F59/F55,"")) -> 1.2233796 | G73: =IF(OR(G59="",G55=""),"",IFERROR(G59/G55,"")) -> 1.5629895 | H73: =IF(OR(H59="",H55=""),"",IFERROR(H59/H55,"")) -> 2.0041732 | I73: FORMULA | J73: A subset (AI head-node) cannot exceed the whole market; >1.0 means the Semis MAP systems-value share is inconsistent with the silicon build for that vendor
A74: Flag (directional) | C74: =IF(OR(C59="",C55=""),"",IF(C59>C55,"OFF","OK")) -> OK | D74: =IF(OR(D59="",D55=""),"",IF(D59>D55,"OFF","OK")) -> OK | E74: =IF(OR(E59="",E55=""),"",IF(E59>E55,"OFF","OK")) -> OK | F74: =IF(OR(F59="",F55=""),"",IF(F59>F55,"OFF","OK")) -> OFF | G74: =IF(OR(G59="",G55=""),"",IF(G59>G55,"OFF","OK")) -> OFF | H74: =IF(OR(H59="",H55=""),"",IF(H59>H55,"OFF","OK")) -> OFF
A75: Consistency: lens-1 head-node implied ÷ lens-3 total implied — Captive Arm + others | B75: x | C75: =IF(OR(C60="",C56=""),"",IFERROR(C60/C56,"")) -> 0.25915556 | D75: =IF(OR(D60="",D56=""),"",IFERROR(D60/D56,"")) -> 0.80265306 | E75: =IF(OR(E60="",E56=""),"",IFERROR(E60/E56,"")) -> 1.2612481 | F75: =IF(OR(F60="",F56=""),"",IFERROR(F60/F56,"")) -> 1.29884 | G75: =IF(OR(G60="",G56=""),"",IFERROR(G60/G56,"")) -> 1.1615784 | H75: =IF(OR(H60="",H56=""),"",IFERROR(H60/H56,"")) -> 1.0456124 | I75: FORMULA | J75: A subset (AI head-node) cannot exceed the whole market; >1.0 means the Semis MAP systems-value share is inconsistent with the silicon build for that vendor
A76: Flag (directional) | C76: =IF(OR(C60="",C56=""),"",IF(C60>C56,"OFF","OK")) -> OK | D76: =IF(OR(D60="",D56=""),"",IF(D60>D56,"OFF","OK")) -> OK | E76: =IF(OR(E60="",E56=""),"",IF(E60>E56,"OFF","OK")) -> OFF | F76: =IF(OR(F60="",F56=""),"",IF(F60>F56,"OFF","OK")) -> OFF | G76: =IF(OR(G60="",G56=""),"",IF(G60>G56,"OFF","OK")) -> OFF | H76: =IF(OR(H60="",H56=""),"",IF(H60>H56,"OFF","OK")) -> OFF
A77: Intel total revenue — BBG consensus | B77: $bn | D77: 60.3 | E77: 72.5 | I77: HARD | J77: estimates.json asof 2026-09-18
A78: Implied Intel (NSR total pool) ÷ BBG Intel total revenue | B78: x | C78: =IF(OR(C53="",C77=""),"",IFERROR(C53/C77,"")) | D78: =IF(OR(D53="",D77=""),"",IFERROR(D53/D77,"")) -> 0.30619848 | E78: =IF(OR(E53="",E77=""),"",IFERROR(E53/E77,"")) -> 0.36294205 | F78: =IF(OR(F53="",F77=""),"",IFERROR(F53/F77,"")) | G78: =IF(OR(G53="",G77=""),"",IFERROR(G53/G77,"")) | H78: =IF(OR(H53="",H77=""),"",IFERROR(H53/H77,"")) | I78: FORMULA | J78: DCAI is ~35-40% of Intel revenue in 2026-27 consensus
A79: AMD total revenue — BBG consensus | B79: $bn | D79: 50.6 | E79: 88.6 | I79: HARD | J79: estimates.json asof 2026-09-18
A80: Implied AMD (NSR total pool) ÷ BBG AMD total revenue | B80: x | C80: =IF(OR(C54="",C79=""),"",IFERROR(C54/C79,"")) | D80: =IF(OR(D54="",D79=""),"",IFERROR(D54/D79,"")) -> 0.28770694 | E80: =IF(OR(E54="",E79=""),"",IFERROR(E54/E79,"")) -> 0.23502792 | F80: =IF(OR(F54="",F79=""),"",IFERROR(F54/F79,"")) | G80: =IF(OR(G54="",G79=""),"",IFERROR(G54/G79,"")) | H80: =IF(OR(H54="",H79=""),"",IFERROR(H54/H79,"")) | I80: FORMULA | J80: Server CPU ≈ 30-35% of AMD revenue in the 2Q26 segment print
A82: Reading (post-skeptic): 2025 is the robust finding — Intel + AMD + NVIDIA chips + captive Arm already add to ~$34bn (BofA's own ‘~$35bn CY25 level’ and Bernstein's $37bn agree) against NSR's $25bn, so NSR's 2025 CPU pool is ~25% light on any basis. 2026 is a basis call: on the silicon reading the anchors give ~$55bn (NSR $49bn, OK); on management's systems reading ~$65bn (OFF). From 2028 the silicon build runs BELOW NSR's pool (2030: ~$150bn vs $202bn) while BofA's $210.6bn and AMD's $220bn sit above it and UBS's $173bn / Bernstein's $137bn below — the 2030 pool is a live debate, the shares are what this sheet can say: on the silicon build Intel ~31%, AMD ~33%, NVIDIA ~16%, captive Arm + Hygon ~20% in 2030; on NSR's own $202bn each vendor scales up ~35%. The Capstone head-node lens (NVIDIA 38%) is a systems-value share and exceeds the silicon build for NVIDIA — flagged in block F, not netted.

Sheet Share_Memory
A1: Memory — vendor market share and implied revenue by pool (HBM / server DRAM / server NAND), 2025-2030 ($bn)
A2: Pools = NSR p.5 lines (HBM inside the XPU; DRAM and NAND as server content) with the Capstone equivalents. HBM shares: Capstone Semis MAP (EST) vs JPM SALES-share path (HARD end-points, interpolated/held EST, plus a slope-continued scenario) vs UBS BIT share (HARD, 2025-27). Server-DRAM shares: total-DRAM bit-supply mix from the Capstone memory bible (PARTIAL proxy). Server-NAND shares: TrendForce 2Q26 enterprise-SSD revenue share (HARD), held flat. NOT ADDITIVE with Share_XPU: HBM dollars sit inside the XPU pool too. Skeptic-revised 2026-09-18.
A4: Line | B4: Unit | C4: 2025 | D4: 2026 | E4: 2027 | F4: 2028 | G4: 2029 | H4: 2030 | I4: Tag | J4: Source
A5: A. Pools ($bn)
A6: HBM — NSR | B6: $bn | C6: =IF(NSR_Memory!C13="","",NSR_Memory!C13) -> 34 | D6: =IF(NSR_Memory!D13="","",NSR_Memory!D13) -> 82 | E6: =IF(NSR_Memory!E13="","",NSR_Memory!E13) -> 189 | F6: =IF(NSR_Memory!F13="","",NSR_Memory!F13) -> 332 | G6: =IF(NSR_Memory!G13="","",NSR_Memory!G13) -> 457 | H6: =IF(NSR_Memory!H13="","",NSR_Memory!H13) -> 560 | I6: LINK | J6: NSR p.5
A7: HBM — Capstone Semis MAP repriced (bits × $/GB) | B7: $bn | C7: =IF(House!E41="","",House!E41) -> 35 | D7: =IF(House!F41="","",House!F41) -> 77.4 | E7: =IF(House!G41="","",House!G41) -> 193.8 | F7: =IF(House!H41="","",House!H41) -> 224 | G7: =IF(House!I41="","",House!I41) -> 255.4 | H7: =IF(House!J41="","",House!J41) -> 283.4 | I7: LINK | J7: House!sm_hbm_rep
A8: HBM — Capstone AI Model HBM Model | B8: $bn | C8: =IF(House!E85="","",House!E85) -> 27 | D8: =IF(House!F85="","",House!F85) -> 63.7 | E8: =IF(House!G85="","",House!G85) -> 127.8 | F8: =IF(House!H85="","",House!H85) -> 281.5 | G8: =IF(House!I85="","",House!I85) | H8: =IF(House!J85="","",House!J85) | I8: LINK | J8: House!am_hbm (CY25-28)
A9: Server DRAM (ex-HBM) — NSR | B9: $bn | C9: =IF(NSR_Memory!C30="","",NSR_Memory!C30) -> 17 | D9: =IF(NSR_Memory!D30="","",NSR_Memory!D30) -> 100 | E9: =IF(NSR_Memory!E30="","",NSR_Memory!E30) -> 211 | F9: =IF(NSR_Memory!F30="","",NSR_Memory!F30) -> 273 | G9: =IF(NSR_Memory!G30="","",NSR_Memory!G30) -> 250 | H9: =IF(NSR_Memory!H30="","",NSR_Memory!H30) -> 241 | I9: LINK | J9: NSR p.5
A10: Fleet DDR5 — Capstone Semis MAP | B10: $bn | C10: =IF(House!E42="","",House!E42) -> 19.5 | D10: =IF(House!F42="","",House!F42) -> 91.3 | E10: =IF(House!G42="","",House!G42) -> 134.4 | F10: =IF(House!H42="","",House!H42) -> 141.8 | G10: =IF(House!I42="","",House!I42) -> 148.2 | H10: =IF(House!J42="","",House!J42) -> 164.9 | I10: LINK | J10: House!sm_ddr
A11: Server NAND — NSR | B11: $bn | C11: =IF(NSR_Memory!C35="","",NSR_Memory!C35) -> 9 | D11: =IF(NSR_Memory!D35="","",NSR_Memory!D35) -> 60 | E11: =IF(NSR_Memory!E35="","",NSR_Memory!E35) -> 127 | F11: =IF(NSR_Memory!F35="","",NSR_Memory!F35) -> 186 | G11: =IF(NSR_Memory!G35="","",NSR_Memory!G35) -> 181 | H11: =IF(NSR_Memory!H35="","",NSR_Memory!H35) -> 182 | I11: LINK | J11: NSR p.5
A12: DC NAND — Capstone Semis MAP | B12: $bn | C12: =IF(House!E43="","",House!E43) -> 22.8 | D12: =IF(House!F43="","",House!F43) -> 119.7 | E12: =IF(House!G43="","",House!G43) -> 182.4 | F12: =IF(House!H43="","",House!H43) -> 204 | G12: =IF(House!I43="","",House!I43) -> 222 | H12: =IF(House!J43="","",House!J43) -> 240 | I12: LINK | J12: House!sm_nand
A14: B. HBM share — three lenses (value unless stated) + slope scenario
A15: SK Hynix — Capstone Semis MAP | B15: % | C15: 0.6 | D15: 0.57 | E15: 0.5 | F15: 0.47 | G15: =F15 -> 0.47 | H15: =F15 -> 0.47 | I15: EST | J15: AI_Chip_Designers_TAM_v11.xlsx → Build | HBM rows 7-9 (2026-07-16). CALIBRATION (corrected): the map is calibrated to the canonical $35bn CY25 HBM TAM (capture 0.621), NOT to SK Hynix's revenue — its implied SK Hynix CY25 is ~$21bn vs an unverified street ~$28bn, an open tension the map flags in its own row 31. CY29-30 held. No ‘others’ plug (CXMT HBM3E not modelled)
A16: Samsung — Capstone Semis MAP | B16: % | C16: 0.17 | D16: 0.18 | E16: 0.25 | F16: 0.28 | G16: =F16 -> 0.28 | H16: =F16 -> 0.28 | I16: EST | J16: same source
A17: Micron — Capstone Semis MAP | B17: % | C17: 0.23 | D17: 0.25 | E17: 0.25 | F17: 0.25 | G17: =F17 -> 0.25 | H17: =F17 -> 0.25 | I17: EST | J17: same source
A18: SK Hynix — JPM sales-share path (2028 held) | B18: % | C18: 0.6 | D18: 0.54 | E18: 0.48 | F18: 0.42 | G18: =F18 -> 0.42 | H18: =F18 -> 0.42 | I18: HARD+EST | J18: JPM · Kwon ‘Global Memory TAM and S&D update’ 2026-08-09/10 (MU.md ~row 615): HBM share BY SALES SK Hynix 60% → 42%, Samsung 20% → 38% (2025 and 2028 printed = HARD), Micron 20/20/21/20 (all four years printed). 2026-27 for SK Hynix/Samsung are straight-line EST (Samsung 2027 back-solved to 31% so the set sums to 100%); CY29-30 HELD at 2028 = EST choice (see slope scenario below)
A19: Samsung — JPM sales-share path (2028 held) | B19: % | C19: 0.2 | D19: 0.26 | E19: 0.31 | F19: 0.38 | G19: =F19 -> 0.38 | H19: =F19 -> 0.38 | I19: HARD+EST | J19: same source
A20: Micron — JPM sales-share path (2028 held) | B20: % | C20: 0.2 | D20: 0.2 | E20: 0.21 | F20: 0.2 | G20: =F20 -> 0.2 | H20: =F20 -> 0.2 | I20: HARD+EST | J20: same source (2025-28 all printed)
A21: SK Hynix — JPM slope CONTINUED (−6pp/yr into 2029-30) | B21: % | G21: 0.36 | H21: 0.3 | I21: SCENARIO | J21: Skeptic: freezing at 2028 stops JPM's −6pp/yr trend exactly at the last printed point; continuing it two more years is an equally defensible reading
A22: Samsung — JPM slope CONTINUED (+6pp/yr into 2029-30) | B22: % | G22: 0.44 | H22: 0.5 | I22: SCENARIO | J22: as above; Micron held at 20%
A23: SK Hynix — UBS (BIT share, not sales share) | B23: % | C23: 0.59 | D23: 0.48 | E23: 0.39 | I23: HARD | J23: UBS Gaudois memory model 2026-07-03 via Memória Capstone dashboard (hbm_ubs = UBS Fig 3 bit supply × Fig 8 share, bn Gb). BIT/volume share: Samsung bins below SK Hynix, so its sales share is lower than its bit share. SKHYNIX.md ‘UBS 2026 HBM share 56/22/22’ is UBS's Dec-2025 overview — an older vintage of the same house, not a conflict
A24: Samsung — UBS (BIT share) | B24: % | C24: 0.2 | D24: 0.3 | E24: 0.41 | I24: HARD | J24: same source. Samsung mgmt: ‘30-40% in 2H26 on HBM4, mid-to-high 30s in 2027’ (hbm-memory theme ~row 915) — a company target, share basis unstated
A25: Micron — UBS (BIT share) | B25: % | C25: 0.21 | D25: 0.21 | E25: 0.2 | I25: HARD | J25: same source; Micron target ‘HBM share = DRAM share’ (~20-25%)
A27: C. Server-DRAM share — total-DRAM bit-supply mix (incl. HBM, all end-markets; server tilt not applied)
A28: Samsung — DRAM bit supply | B28: bn Gb | C28: 120.1 | D28: 146.6 | E28: 173.9 | F28: 213.3 | I28: PARTIAL | J28: Memória Capstone dashboard_data.json seg.sup_dram (bn Gb; sources TrendForce/Bernstein), 2025-28; CY29-30 held (CXMT's bit share is RISING ~1.3pp/yr, so the hold understates CXMT bits and overstates the big three). Wells Fargo (MU.md ~row 702): CXMT ~8% DRAM REVENUE share, ~10% capacity share 1Q26, DDR4/LPDDR4-heavy — bit share overstates CXMT's SERVER relevance
A29: SK Hynix — DRAM bit supply | B29: bn Gb | C29: 93.1 | D29: 117 | E29: 137.3 | F29: 171.1 | I29: PARTIAL | J29: same source (memory bible seg.sup_dram)
A30: Micron — DRAM bit supply | B30: bn Gb | C30: 73.6 | D30: 91 | E30: 107.1 | F30: 135.6 | I30: PARTIAL | J30: same source
A31: CXMT — DRAM bit supply | B31: bn Gb | C31: 22 | D31: 28.4 | E31: 39 | F31: 64 | I31: PARTIAL | J31: same source
A32: Nanya + others — DRAM bit supply | B32: bn Gb | C32: 5.8 | D32: 6.2 | E32: 7 | F32: 9.5 | I32: PARTIAL | J32: same source; residual to the printed total 314.6 / 389.2 / 464.3 / 593.5
A33: Total DRAM bits | B33: bn Gb | C33: =SUM(C28:C32) -> 314.6 | D33: =SUM(D28:D32) -> 389.2 | E33: =SUM(E28:E32) -> 464.3 | F33: =SUM(F28:F32) -> 593.5 | I33: FORMULA
A34: Samsung — DRAM bit share (2029-30 held) | B34: % | C34: =IF(OR(C28="",C33=""),"",C28/C33) -> 0.38175461 | D34: =IF(OR(D28="",D33=""),"",D28/D33) -> 0.37667009 | E34: =IF(OR(E28="",E33=""),"",E28/E33) -> 0.37454232 | F34: =IF(OR(F28="",F33=""),"",F28/F33) -> 0.35939343 | G34: =F34 -> 0.35939343 | H34: =F34 -> 0.35939343 | I34: PARTIAL | J34: bit share as proxy for server-DRAM value share
A35: SK Hynix — DRAM bit share (2029-30 held) | B35: % | C35: =IF(OR(C29="",C33=""),"",C29/C33) -> 0.29593134 | D35: =IF(OR(D29="",D33=""),"",D29/D33) -> 0.30061665 | E35: =IF(OR(E29="",E33=""),"",E29/E33) -> 0.29571398 | F35: =IF(OR(F29="",F33=""),"",F29/F33) -> 0.28828981 | G35: =F35 -> 0.28828981 | H35: =F35 -> 0.28828981 | I35: PARTIAL | J35: bit share as proxy for server-DRAM value share
A36: Micron — DRAM bit share (2029-30 held) | B36: % | C36: =IF(OR(C30="",C33=""),"",C30/C33) -> 0.23394787 | D36: =IF(OR(D30="",D33=""),"",D30/D33) -> 0.23381295 | E36: =IF(OR(E30="",E33=""),"",E30/E33) -> 0.23066983 | F36: =IF(OR(F30="",F33=""),"",F30/F33) -> 0.22847515 | G36: =F36 -> 0.22847515 | H36: =F36 -> 0.22847515 | I36: PARTIAL | J36: bit share as proxy for server-DRAM value share
A37: CXMT — DRAM bit share (2029-30 held) | B37: % | C37: =IF(OR(C31="",C33=""),"",C31/C33) -> 0.06993007 | D37: =IF(OR(D31="",D33=""),"",D31/D33) -> 0.072970195 | E37: =IF(OR(E31="",E33=""),"",E31/E33) -> 0.083997415 | F37: =IF(OR(F31="",F33=""),"",F31/F33) -> 0.10783488 | G37: =F37 -> 0.10783488 | H37: =F37 -> 0.10783488 | I37: PARTIAL | J37: bit share as proxy for server-DRAM value share
A38: Nanya + others — DRAM bit share (2029-30 held) | B38: % | C38: =IF(OR(C32="",C33=""),"",C32/C33) -> 0.018436109 | D38: =IF(OR(D32="",D33=""),"",D32/D33) -> 0.015930113 | E38: =IF(OR(E32="",E33=""),"",E32/E33) -> 0.015076459 | F38: =IF(OR(F32="",F33=""),"",F32/F33) -> 0.01600674 | G38: =F38 -> 0.01600674 | H38: =F38 -> 0.01600674 | I38: PARTIAL | J38: bit share as proxy for server-DRAM value share
A39: CXMT — plausible SERVER-DRAM share (alternative) | B39: % | C39: 0.03 | D39: 0.03 | E39: 0.03 | F39: 0.03 | G39: 0.03 | H39: 0.03 | I39: EST | J39: Skeptic alternative: CXMT is DDR4/LPDDR4-heavy with little server DDR5; ~3% of the server pool would move ~$20bn of 2028 implied revenue from CXMT to the big three
A41: D. Server-NAND share — enterprise-SSD revenue share, TrendForce 2Q26 (single vintage, held flat)
A42: Samsung | B42: % | C42: 0.351 | D42: =C42 -> 0.351 | E42: =C42 -> 0.351 | F42: =C42 -> 0.351 | G42: =C42 -> 0.351 | H42: =C42 -> 0.351 | I42: HARD | J42: TrendForce 2Q26 global enterprise-SSD revenue share via Jefferies (SAMSUNG.md ~row 129) and Yonhap/DealSite (SAMSUNG.md ~row 550): Samsung 35% (~$14.35bn), SK hynix group incl. Solidigm 21% (~$8.63bn; 23.1% in 1Q26), Micron 17% (~$6.98bn; 15.4% in 1Q26), Kioxia 11% (~$4.64bn), SanDisk 7% (~$2.98bn). eSSD REVENUE basis, NOT NAND bits. Applied to every year (EST hold); YMTC/others = residual
A43: SK Hynix + Solidigm | B43: % | C43: 0.211 | D43: =C43 -> 0.211 | E43: =C43 -> 0.211 | F43: =C43 -> 0.211 | G43: =C43 -> 0.211 | H43: =C43 -> 0.211 | I43: HARD | J43: same source
A44: Micron | B44: % | C44: 0.171 | D44: =C44 -> 0.171 | E44: =C44 -> 0.171 | F44: =C44 -> 0.171 | G44: =C44 -> 0.171 | H44: =C44 -> 0.171 | I44: HARD | J44: same source
A45: Kioxia | B45: % | C45: 0.11 | D45: =C45 -> 0.11 | E45: =C45 -> 0.11 | F45: =C45 -> 0.11 | G45: =C45 -> 0.11 | H45: =C45 -> 0.11 | I45: HARD | J45: same source (skeptic fix: was EST 15%)
A46: SanDisk | B46: % | C46: 0.07 | D46: =C46 -> 0.07 | E46: =C46 -> 0.07 | F46: =C46 -> 0.07 | G46: =C46 -> 0.07 | H46: =C46 -> 0.07 | I46: HARD | J46: same source (skeptic fix: was EST 5%)
A47: YMTC + others (residual) | B47: % | C47: =1-SUM(C42:C46) -> 0.087 | D47: =1-SUM(D42:D46) -> 0.087 | E47: =1-SUM(E42:E46) -> 0.087 | F47: =1-SUM(F42:F46) -> 0.087 | G47: =1-SUM(G42:G46) -> 0.087 | H47: =1-SUM(H42:H46) -> 0.087 | I47: FORMULA | J47: residual to 100%; YMTC reportedly passed Micron and SanDisk in TOTAL NAND share (07-23) — not yet in eSSD
A49: E. Implied vendor revenue on the NSR pools ($bn)
A50: HBM — SK Hynix at JPM sales shares (2028 held) | B50: $bn | C50: =IF(OR(C6="",C18=""),"",C6*C18) -> 20.4 | D50: =IF(OR(D6="",D18=""),"",D6*D18) -> 44.28 | E50: =IF(OR(E6="",E18=""),"",E6*E18) -> 90.72 | F50: =IF(OR(F6="",F18=""),"",F6*F18) -> 139.44 | G50: =IF(OR(G6="",G18=""),"",G6*G18) -> 191.94 | H50: =IF(OR(H6="",H18=""),"",H6*H18) -> 235.2 | I50: FORMULA | J50: NSR HBM pool × JPM share
A51: HBM — Samsung at JPM sales shares (2028 held) | B51: $bn | C51: =IF(OR(C6="",C19=""),"",C6*C19) -> 6.8 | D51: =IF(OR(D6="",D19=""),"",D6*D19) -> 21.32 | E51: =IF(OR(E6="",E19=""),"",E6*E19) -> 58.59 | F51: =IF(OR(F6="",F19=""),"",F6*F19) -> 126.16 | G51: =IF(OR(G6="",G19=""),"",G6*G19) -> 173.66 | H51: =IF(OR(H6="",H19=""),"",H6*H19) -> 212.8 | I51: FORMULA | J51: NSR HBM pool × JPM share
A52: HBM — Micron at JPM sales shares (2028 held) | B52: $bn | C52: =IF(OR(C6="",C20=""),"",C6*C20) -> 6.8 | D52: =IF(OR(D6="",D20=""),"",D6*D20) -> 16.4 | E52: =IF(OR(E6="",E20=""),"",E6*E20) -> 39.69 | F52: =IF(OR(F6="",F20=""),"",F6*F20) -> 66.4 | G52: =IF(OR(G6="",G20=""),"",G6*G20) -> 91.4 | H52: =IF(OR(H6="",H20=""),"",H6*H20) -> 112 | I52: FORMULA | J52: NSR HBM pool × JPM share
A53: HBM — SK Hynix at JPM slope CONTINUED (2029-30) | B53: $bn | C53: =IF(OR(C6="",C21=""),"",C6*C21) | D53: =IF(OR(D6="",D21=""),"",D6*D21) | E53: =IF(OR(E6="",E21=""),"",E6*E21) | F53: =IF(OR(F6="",F21=""),"",F6*F21) | G53: =IF(OR(G6="",G21=""),"",G6*G21) -> 164.52 | H53: =IF(OR(H6="",H21=""),"",H6*H21) -> 168 | I53: FORMULA | J53: scenario: $67bn lower than the held case in 2030
A54: HBM — Samsung at JPM slope CONTINUED (2029-30) | B54: $bn | C54: =IF(OR(C6="",C22=""),"",C6*C22) | D54: =IF(OR(D6="",D22=""),"",D6*D22) | E54: =IF(OR(E6="",E22=""),"",E6*E22) | F54: =IF(OR(F6="",F22=""),"",F6*F22) | G54: =IF(OR(G6="",G22=""),"",G6*G22) -> 201.08 | H54: =IF(OR(H6="",H22=""),"",H6*H22) -> 280 | I54: FORMULA | J54: scenario: $67bn higher than the held case in 2030
A55: HBM — SK Hynix at Capstone Semis MAP shares | B55: $bn | C55: =IF(OR(C6="",C15=""),"",C6*C15) -> 20.4 | D55: =IF(OR(D6="",D15=""),"",D6*D15) -> 46.74 | E55: =IF(OR(E6="",E15=""),"",E6*E15) -> 94.5 | F55: =IF(OR(F6="",F15=""),"",F6*F15) -> 156.04 | G55: =IF(OR(G6="",G15=""),"",G6*G15) -> 214.79 | H55: =IF(OR(H6="",H15=""),"",H6*H15) -> 263.2 | I55: FORMULA | J55: NSR HBM pool × house share
A56: HBM — Samsung at Capstone Semis MAP shares | B56: $bn | C56: =IF(OR(C6="",C16=""),"",C6*C16) -> 5.78 | D56: =IF(OR(D6="",D16=""),"",D6*D16) -> 14.76 | E56: =IF(OR(E6="",E16=""),"",E6*E16) -> 47.25 | F56: =IF(OR(F6="",F16=""),"",F6*F16) -> 92.96 | G56: =IF(OR(G6="",G16=""),"",G6*G16) -> 127.96 | H56: =IF(OR(H6="",H16=""),"",H6*H16) -> 156.8 | I56: FORMULA | J56: NSR HBM pool × house share
A57: HBM — Micron at Capstone Semis MAP shares | B57: $bn | C57: =IF(OR(C6="",C17=""),"",C6*C17) -> 7.82 | D57: =IF(OR(D6="",D17=""),"",D6*D17) -> 20.5 | E57: =IF(OR(E6="",E17=""),"",E6*E17) -> 47.25 | F57: =IF(OR(F6="",F17=""),"",F6*F17) -> 83 | G57: =IF(OR(G6="",G17=""),"",G6*G17) -> 114.25 | H57: =IF(OR(H6="",H17=""),"",H6*H17) -> 140 | I57: FORMULA | J57: NSR HBM pool × house share
A58: Server DRAM — Samsung at bit share | B58: $bn | C58: =IF(OR(C9="",C34=""),"",C9*C34) -> 6.4898284 | D58: =IF(OR(D9="",D34=""),"",D9*D34) -> 37.667009 | E58: =IF(OR(E9="",E34=""),"",E9*E34) -> 79.02843 | F58: =IF(OR(F9="",F34=""),"",F9*F34) -> 98.114406 | G58: =IF(OR(G9="",G34=""),"",G9*G34) -> 89.848357 | H58: =IF(OR(H9="",H34=""),"",H9*H34) -> 86.613816 | I58: FORMULA | J58: NSR DRAM pool × bit share
A59: Server DRAM — SK Hynix at bit share | B59: $bn | C59: =IF(OR(C9="",C35=""),"",C9*C35) -> 5.0308328 | D59: =IF(OR(D9="",D35=""),"",D9*D35) -> 30.061665 | E59: =IF(OR(E9="",E35=""),"",E9*E35) -> 62.395649 | F59: =IF(OR(F9="",F35=""),"",F9*F35) -> 78.703117 | G59: =IF(OR(G9="",G35=""),"",G9*G35) -> 72.072452 | H59: =IF(OR(H9="",H35=""),"",H9*H35) -> 69.477843 | I59: FORMULA | J59: NSR DRAM pool × bit share
A60: Server DRAM — Micron at bit share | B60: $bn | C60: =IF(OR(C9="",C36=""),"",C9*C36) -> 3.9771138 | D60: =IF(OR(D9="",D36=""),"",D9*D36) -> 23.381295 | E60: =IF(OR(E9="",E36=""),"",E9*E36) -> 48.671333 | F60: =IF(OR(F9="",F36=""),"",F9*F36) -> 62.373715 | G60: =IF(OR(G9="",G36=""),"",G9*G36) -> 57.118787 | H60: =IF(OR(H9="",H36=""),"",H9*H36) -> 55.062511 | I60: FORMULA | J60: NSR DRAM pool × bit share
A61: Server DRAM — CXMT at bit share | B61: $bn | C61: =IF(OR(C9="",C37=""),"",C9*C37) -> 1.1888112 | D61: =IF(OR(D9="",D37=""),"",D9*D37) -> 7.2970195 | E61: =IF(OR(E9="",E37=""),"",E9*E37) -> 17.723455 | F61: =IF(OR(F9="",F37=""),"",F9*F37) -> 29.438922 | G61: =IF(OR(G9="",G37=""),"",G9*G37) -> 26.958719 | H61: =IF(OR(H9="",H37=""),"",H9*H37) -> 25.988206 | I61: FORMULA | J61: NSR DRAM pool × bit share
A62: Server DRAM — Nanya + others at bit share | B62: $bn | C62: =IF(OR(C9="",C38=""),"",C9*C38) -> 0.31341386 | D62: =IF(OR(D9="",D38=""),"",D9*D38) -> 1.5930113 | E62: =IF(OR(E9="",E38=""),"",E9*E38) -> 3.1811329 | F62: =IF(OR(F9="",F38=""),"",F9*F38) -> 4.3698399 | G62: =IF(OR(G9="",G38=""),"",G9*G38) -> 4.0016849 | H62: =IF(OR(H9="",H38=""),"",H9*H38) -> 3.8576243 | I62: FORMULA | J62: NSR DRAM pool × bit share
A63: Server DRAM — CXMT at ~3% server share (alternative) | B63: $bn | C63: =IF(OR(C9="",C39=""),"",C9*C39) -> 0.51 | D63: =IF(OR(D9="",D39=""),"",D9*D39) -> 3 | E63: =IF(OR(E9="",E39=""),"",E9*E39) -> 6.33 | F63: =IF(OR(F9="",F39=""),"",F9*F39) -> 8.19 | G63: =IF(OR(G9="",G39=""),"",G9*G39) -> 7.5 | H63: =IF(OR(H9="",H39=""),"",H9*H39) -> 7.23 | I63: FORMULA | J63: the bit-share row above minus this row is the amount redistributed to Samsung / SK Hynix / Micron
A64: Server NAND — Samsung at eSSD share | B64: $bn | C64: =IF(OR(C11="",C42=""),"",C11*C42) -> 3.159 | D64: =IF(OR(D11="",D42=""),"",D11*D42) -> 21.06 | E64: =IF(OR(E11="",E42=""),"",E11*E42) -> 44.577 | F64: =IF(OR(F11="",F42=""),"",F11*F42) -> 65.286 | G64: =IF(OR(G11="",G42=""),"",G11*G42) -> 63.531 | H64: =IF(OR(H11="",H42=""),"",H11*H42) -> 63.882 | I64: FORMULA | J64: NSR NAND pool × eSSD share
A65: Server NAND — SK Hynix + Solidigm at eSSD share | B65: $bn | C65: =IF(OR(C11="",C43=""),"",C11*C43) -> 1.899 | D65: =IF(OR(D11="",D43=""),"",D11*D43) -> 12.66 | E65: =IF(OR(E11="",E43=""),"",E11*E43) -> 26.797 | F65: =IF(OR(F11="",F43=""),"",F11*F43) -> 39.246 | G65: =IF(OR(G11="",G43=""),"",G11*G43) -> 38.191 | H65: =IF(OR(H11="",H43=""),"",H11*H43) -> 38.402 | I65: FORMULA | J65: NSR NAND pool × eSSD share
A66: Server NAND — Micron at eSSD share | B66: $bn | C66: =IF(OR(C11="",C44=""),"",C11*C44) -> 1.539 | D66: =IF(OR(D11="",D44=""),"",D11*D44) -> 10.26 | E66: =IF(OR(E11="",E44=""),"",E11*E44) -> 21.717 | F66: =IF(OR(F11="",F44=""),"",F11*F44) -> 31.806 | G66: =IF(OR(G11="",G44=""),"",G11*G44) -> 30.951 | H66: =IF(OR(H11="",H44=""),"",H11*H44) -> 31.122 | I66: FORMULA | J66: NSR NAND pool × eSSD share
A67: Server NAND — Kioxia at eSSD share | B67: $bn | C67: =IF(OR(C11="",C45=""),"",C11*C45) -> 0.99 | D67: =IF(OR(D11="",D45=""),"",D11*D45) -> 6.6 | E67: =IF(OR(E11="",E45=""),"",E11*E45) -> 13.97 | F67: =IF(OR(F11="",F45=""),"",F11*F45) -> 20.46 | G67: =IF(OR(G11="",G45=""),"",G11*G45) -> 19.91 | H67: =IF(OR(H11="",H45=""),"",H11*H45) -> 20.02 | I67: FORMULA | J67: NSR NAND pool × eSSD share
A68: Server NAND — SanDisk at eSSD share | B68: $bn | C68: =IF(OR(C11="",C46=""),"",C11*C46) -> 0.63 | D68: =IF(OR(D11="",D46=""),"",D11*D46) -> 4.2 | E68: =IF(OR(E11="",E46=""),"",E11*E46) -> 8.89 | F68: =IF(OR(F11="",F46=""),"",F11*F46) -> 13.02 | G68: =IF(OR(G11="",G46=""),"",G11*G46) -> 12.67 | H68: =IF(OR(H11="",H46=""),"",H11*H46) -> 12.74 | I68: FORMULA | J68: NSR NAND pool × eSSD share
A69: Server NAND — YMTC + others at eSSD share | B69: $bn | C69: =IF(OR(C11="",C47=""),"",C11*C47) -> 0.783 | D69: =IF(OR(D11="",D47=""),"",D11*D47) -> 5.22 | E69: =IF(OR(E11="",E47=""),"",E11*E47) -> 11.049 | F69: =IF(OR(F11="",F47=""),"",F11*F47) -> 16.182 | G69: =IF(OR(G11="",G47=""),"",G11*G47) -> 15.747 | H69: =IF(OR(H11="",H47=""),"",H11*H47) -> 15.834 | I69: FORMULA | J69: NSR NAND pool × eSSD share
A71: F. Vendor totals on the NSR memory pools (HBM at JPM shares + DRAM + NAND) and guardrails
A72: SK Hynix (+Solidigm) — total server memory revenue implied by NSR | B72: $bn | C72: =IF(C50="","",C50+C59+C65) -> 27.329833 | D72: =IF(D50="","",D50+D59+D65) -> 87.001665 | E72: =IF(E50="","",E50+E59+E65) -> 179.91265 | F72: =IF(F50="","",F50+F59+F65) -> 257.38912 | G72: =IF(G50="","",G50+G59+G65) -> 302.20345 | H72: =IF(H50="","",H50+H59+H65) -> 343.07984 | I72: FORMULA | J72: HBM + server DRAM + server NAND (memory-vendor view; the HBM part is the same dollars as inside Share_XPU)
A73: Samsung — total server memory revenue implied by NSR | B73: $bn | C73: =IF(C51="","",C51+C58+C64) -> 16.448828 | D73: =IF(D51="","",D51+D58+D64) -> 80.047009 | E73: =IF(E51="","",E51+E58+E64) -> 182.19543 | F73: =IF(F51="","",F51+F58+F64) -> 289.56041 | G73: =IF(G51="","",G51+G58+G64) -> 327.03936 | H73: =IF(H51="","",H51+H58+H64) -> 363.29582 | I73: FORMULA | J73: HBM + server DRAM + server NAND (memory-vendor view; the HBM part is the same dollars as inside Share_XPU)
A74: Micron — total server memory revenue implied by NSR | B74: $bn | C74: =IF(C52="","",C52+C60+C66) -> 12.316114 | D74: =IF(D52="","",D52+D60+D66) -> 50.041295 | E74: =IF(E52="","",E52+E60+E66) -> 110.07833 | F74: =IF(F52="","",F52+F60+F66) -> 160.57972 | G74: =IF(G52="","",G52+G60+G66) -> 179.46979 | H74: =IF(H52="","",H52+H60+H66) -> 198.18451 | I74: FORMULA | J74: HBM + server DRAM + server NAND (memory-vendor view; the HBM part is the same dollars as inside Share_XPU)
A75: Kioxia — server NAND only | B75: $bn | C75: =C67 -> 0.99 | D75: =D67 -> 6.6 | E75: =E67 -> 13.97 | F75: =F67 -> 20.46 | G75: =G67 -> 19.91 | H75: =H67 -> 20.02 | I75: FORMULA
A76: CXMT — server DRAM only (bit-share basis) | B76: $bn | C76: =C61 -> 1.1888112 | D76: =D61 -> 7.2970195 | E76: =E61 -> 17.723455 | F76: =F61 -> 29.438922 | G76: =G61 -> 26.958719 | H76: =H61 -> 25.988206 | I76: FORMULA
A77: SK Hynix HBM revenue 2025 — street (unverified) | B77: $bn | C77: 28 | I77: PARTIAL | J77: Semis MAP Build | HBM row 20 — the map itself labels it ‘yellow = verify’ / ‘unverified street ~$28bn’
A78: Micron HBM revenue 2025 — street | B78: $bn | C78: 6 | I78: PARTIAL | J78: Semis MAP Build | HBM row 21 (FY25 ≈ CY25)
A79: Samsung HBM revenue 2025 — reported range midpoint | B79: $bn | C79: 5 | I79: PARTIAL | J79: ~$4.5-6.0bn range for Samsung's 2025 HBM revenue (wiki Samsung/HBM commentary; Samsung's own 2025 HBM share ‘~20%’ per Jefferies/Inspectrum 2025-12-17 in MU.md ~row 338); midpoint used, PARTIAL
A80: Sum of vendor-reported 2025 HBM (SK Hynix + Micron + Samsung) | B80: $bn | C80: =C77+C78+C79 -> 39 | I80: FORMULA | J80: ≈ $39bn vs NSR's $34bn pool (−13%) and the Semis MAP's $35bn (−10%) — the POOL leg of the 2025 gap
A81: Implied SK Hynix HBM 2025 (NSR pool × JPM 60%) ÷ street $28bn | B81: x | C81: =IF(OR(C50="",C77=""),"",IFERROR(C50/C77,"")) -> 0.72857143 | D81: =IF(OR(D50="",D77=""),"",IFERROR(D50/D77,"")) | E81: =IF(OR(E50="",E77=""),"",IFERROR(E50/E77,"")) | F81: =IF(OR(F50="",F77=""),"",IFERROR(F50/F77,"")) | G81: =IF(OR(G50="",G77=""),"",IFERROR(G50/G77,"")) | H81: =IF(OR(H50="",H77=""),"",IFERROR(H50/H77,"")) | I81: FORMULA | J81: Two legs, not one: (a) POOL — vendors reported ~$39bn vs NSR $34bn (~13% light); (b) SHARE — on a $39bn total, SK Hynix's actual 2025 share is ~72%, not JPM's 60%, so JPM's whole path may start ~12pp low. implied = pool × share cannot separate the two
A82: Flag (±25%) — SK Hynix | C82: =IF(OR(C50="",C77=""),"",IF(ABS(C50/C77-1)>0.25,"OFF >25%","OK")) -> OFF >25% | D82: =IF(OR(D50="",D77=""),"",IF(ABS(D50/D77-1)>0.25,"OFF >25%","OK")) | E82: =IF(OR(E50="",E77=""),"",IF(ABS(E50/E77-1)>0.25,"OFF >25%","OK")) | F82: =IF(OR(F50="",F77=""),"",IF(ABS(F50/F77-1)>0.25,"OFF >25%","OK")) | G82: =IF(OR(G50="",G77=""),"",IF(ABS(G50/G77-1)>0.25,"OFF >25%","OK")) | H82: =IF(OR(H50="",H77=""),"",IF(ABS(H50/H77-1)>0.25,"OFF >25%","OK"))
A83: Implied Micron HBM 2025 (NSR pool × JPM 20%) ÷ street $6bn | B83: x | C83: =IF(OR(C52="",C78=""),"",IFERROR(C52/C78,"")) -> 1.1333333 | D83: =IF(OR(D52="",D78=""),"",IFERROR(D52/D78,"")) | E83: =IF(OR(E52="",E78=""),"",IFERROR(E52/E78,"")) | F83: =IF(OR(F52="",F78=""),"",IFERROR(F52/F78,"")) | G83: =IF(OR(G52="",G78=""),"",IFERROR(G52/G78,"")) | H83: =IF(OR(H52="",H78=""),"",IFERROR(H52/H78,"")) | I83: FORMULA | J83: +13%: Micron is NOT short on NSR's pool — only SK Hynix is, which is the share-leg evidence
A84: Flag (±25%) — Micron | C84: =IF(OR(C52="",C78=""),"",IF(ABS(C52/C78-1)>0.25,"OFF >25%","OK")) -> OK | D84: =IF(OR(D52="",D78=""),"",IF(ABS(D52/D78-1)>0.25,"OFF >25%","OK")) | E84: =IF(OR(E52="",E78=""),"",IF(ABS(E52/E78-1)>0.25,"OFF >25%","OK")) | F84: =IF(OR(F52="",F78=""),"",IF(ABS(F52/F78-1)>0.25,"OFF >25%","OK")) | G84: =IF(OR(G52="",G78=""),"",IF(ABS(G52/G78-1)>0.25,"OFF >25%","OK")) | H84: =IF(OR(H52="",H78=""),"",IF(ABS(H52/H78-1)>0.25,"OFF >25%","OK"))
A85: Implied Samsung HBM 2025 (NSR pool × JPM 20%) ÷ reported ~$5bn | B85: x | C85: =IF(OR(C51="",C79=""),"",IFERROR(C51/C79,"")) -> 1.36 | D85: =IF(OR(D51="",D79=""),"",IFERROR(D51/D79,"")) | E85: =IF(OR(E51="",E79=""),"",IFERROR(E51/E79,"")) | F85: =IF(OR(F51="",F79=""),"",IFERROR(F51/F79,"")) | G85: =IF(OR(G51="",G79=""),"",IFERROR(G51/G79,"")) | H85: =IF(OR(H51="",H79=""),"",IFERROR(H51/H79,"")) | I85: FORMULA | J85: +36% on the midpoint (+13% to +50% across the $4.5-6bn range): JPM's 20% Samsung 2025 share looks high against Samsung's own prints
A86: Flag (±25%) — Samsung | C86: =IF(OR(C51="",C79=""),"",IF(ABS(C51/C79-1)>0.25,"OFF >25%","OK")) -> OFF >25% | D86: =IF(OR(D51="",D79=""),"",IF(ABS(D51/D79-1)>0.25,"OFF >25%","OK")) | E86: =IF(OR(E51="",E79=""),"",IF(ABS(E51/E79-1)>0.25,"OFF >25%","OK")) | F86: =IF(OR(F51="",F79=""),"",IF(ABS(F51/F79-1)>0.25,"OFF >25%","OK")) | G86: =IF(OR(G51="",G79=""),"",IF(ABS(G51/G79-1)>0.25,"OFF >25%","OK")) | H86: =IF(OR(H51="",H79=""),"",IF(ABS(H51/H79-1)>0.25,"OFF >25%","OK"))
A87: Micron total revenue — BBG consensus | B87: $bn | D87: 163.4 | E87: 263.3 | I87: HARD | J87: estimates.json asof 2026-09-18 (CY2026 / CY2027)
A88: Implied Micron server memory (NSR) ÷ BBG Micron total revenue | B88: x | C88: =IF(OR(C74="",C87=""),"",IFERROR(C74/C87,"")) | D88: =IF(OR(D74="",D87=""),"",IFERROR(D74/D87,"")) -> 0.30625028 | E88: =IF(OR(E74="",E87=""),"",IFERROR(E74/E87,"")) -> 0.41807191 | F88: =IF(OR(F74="",F87=""),"",IFERROR(F74/F87,"")) | G88: =IF(OR(G74="",G87=""),"",IFERROR(G74/G87,"")) | H88: =IF(OR(H74="",H87=""),"",IFERROR(H74/H87,"")) | I88: FORMULA | J88: Micron says data centre is >50% of revenue; 0.3-0.6 is consistent, >0.8 is not
A89: SK Hynix total revenue — BBG consensus (KRW ÷ 1,380) | B89: $bn | D89: 253.3 | E89: 391.9 | I89: HARD | J89: estimates.json asof 2026-09-18: KRW 349.5tn / 540.8tn; FX 1,380 as in Semis MAP rollup
A90: Implied SK Hynix server memory (NSR) ÷ BBG SK Hynix total revenue | B90: x | C90: =IF(OR(C72="",C89=""),"",IFERROR(C72/C89,"")) | D90: =IF(OR(D72="",D89=""),"",IFERROR(D72/D89,"")) -> 0.34347282 | E90: =IF(OR(E72="",E89=""),"",IFERROR(E72/E89,"")) -> 0.45907795 | F90: =IF(OR(F72="",F89=""),"",IFERROR(F72/F89,"")) | G90: =IF(OR(G72="",G89=""),"",IFERROR(G72/G89,"")) | H90: =IF(OR(H72="",H89=""),"",IFERROR(H72/H89,"")) | I90: FORMULA | J90: HBM + eSSD were ~20% of consensus in the Semis MAP rollup; server DRAM adds the rest — 0.35-0.5 plausible
A91: Samsung Electronics total revenue — BBG consensus (KRW ÷ 1,380) | B91: $bn | D91: 517.4 | E91: 711.8 | I91: HARD | J91: estimates.json asof 2026-09-18: KRW 714.0tn / 982.3tn — WHOLE company (DS memory is ~40-50%)
A92: Implied Samsung server memory (NSR) ÷ BBG Samsung total revenue | B92: x | C92: =IF(OR(C73="",C91=""),"",IFERROR(C73/C91,"")) | D92: =IF(OR(D73="",D91=""),"",IFERROR(D73/D91,"")) -> 0.15471011 | E92: =IF(OR(E73="",E91=""),"",IFERROR(E73/E91,"")) -> 0.25596436 | F92: =IF(OR(F73="",F91=""),"",IFERROR(F73/F91,"")) | G92: =IF(OR(G73="",G91=""),"",IFERROR(G73/G91,"")) | H92: =IF(OR(H73="",H91=""),"",IFERROR(H73/H91,"")) | I92: FORMULA | J92: Ceiling only — Samsung's memory division is roughly half of group revenue
A94: Reading (post-skeptic): on NSR's HBM pool SK Hynix stays the largest vendor through 2028 on the JPM sales-share path held at 2028 (42% vs Samsung 38%); if JPM's −6pp/yr slope simply continues, Samsung passes SK Hynix in 2029 and the 2030 split is 50/30 — a $67bn swing per name, so the 2029-30 HBM ranking is a share CHOICE, not a result. UBS's Samsung-ahead-in-2027 is a BIT share and is not comparable to the sales shares. Micron is 20-25% on every lens. The 2025 guardrail has two legs: vendors reported ~$39bn of HBM vs NSR's $34bn pool (pool ~13% light), and SK Hynix's actual ~72% 2025 share is well above JPM's 60% start point (share leg) — only SK Hynix is short on NSR's pool; Micron and Samsung are not. Server-DRAM shares are a total-DRAM bit proxy (CXMT overstated for servers); server-NAND shares are 2Q26 enterprise-SSD revenue shares held flat.

Sheet NSR_Capex
A1: NSR p.4 — Annual AI infrastructure capex by component, 2025-2030 ($bn)
A2: Source: New Street Research (Ferragu et al.), 18 Sep 2026, p.4 ‘Our updated AI infrastructure capex forecast: $4.1tn overall spending in 2030’. Blue = as printed; black = recomputed; yellow = check.
A4: Component | B4: Unit | C4: 2025 | D4: 2026 | E4: 2027 | F4: 2028 | G4: 2029 | H4: 2030 | I4: CAGR 25-30 (calc) | J4: CAGR printed | K4: NSR comment
A5: XPUs | B5: $bn | C5: 205 | D5: 408 | E5: 782 | F5: 1252 | G5: 1517 | H5: 1702 | I5: =IFERROR((H5/C5)^(1/5)-1,"") -> 0.52700739 | J5: 0.53 | K5: Up ~5pts as a % of technology spend
A6: CPUs | B6: $bn | C6: 6 | D6: 27 | E6: 56 | F6: 90 | G6: 129 | H6: 168 | I6: =IFERROR((H6/C6)^(1/5)-1,"") -> 0.94729436 | J6: 0.93 | K6: Share of spending up 4x off a low base
A7: DRAM & NAND | B7: $bn | C7: 26 | D7: 160 | E7: 338 | F7: 459 | G7: 431 | H7: 423 | I7: =IFERROR((H7/C7)^(1/5)-1,"") -> 0.74692156 | J7: 0.75 | K7: Price normalizing, but share of spending still >2x from 2025 to 2030
A8: Other server content | B8: $bn | C8: 48 | D8: 105 | E8: 192 | F8: 293 | G8: 338 | H8: 373 | I8: =IFERROR((H8/C8)^(1/5)-1,"") -> 0.50693153 | J8: 0.51 | K8: About stable as a % of technology spend
A9: Networking | B9: $bn | C9: 40 | D9: 103 | E9: 211 | F9: 336 | G9: 405 | H9: 465 | I9: =IFERROR((H9/C9)^(1/5)-1,"") -> 0.6333475 | J9: 0.63 | K9: Increasing as a percentage of spending, faster than compute
A10: Other equipment & buildings | B10: $bn | C10: 258 | D10: 328 | E10: 614 | F10: 899 | G10: 986 | H10: 1016 | I10: =IFERROR((H10/C10)^(1/5)-1,"") -> 0.3153908 | J10: 0.32 | K10: Coming down over time as growth slows (frontloaded spending)
A11: Total AI capex (formula = sum of components) | B11: $bn | C11: =SUM(C5:C10) -> 583 | D11: =SUM(D5:D10) -> 1131 | E11: =SUM(E5:E10) -> 2193 | F11: =SUM(F5:F10) -> 3329 | G11: =SUM(G5:G10) -> 3806 | H11: =SUM(H5:H10) -> 4147 | I11: =IFERROR((H11/C11)^(1/5)-1,"") -> 0.48051597 | J11: 0.48 | K11: NSR printed CAGR 48%
A12: Total AI capex — NSR printed | B12: $bn | C12: 584 | D12: 1132 | E12: 2190 | F12: 3330 | G12: 3810 | H12: 4150
A13: Check: formula − printed (rounding) | B13: $bn | C13: =C11-C12 -> -1 | D13: =D11-D12 -> -1 | E13: =E11-E12 -> 3 | F13: =F11-F12 -> -1 | G13: =G11-G12 -> -4 | H13: =H11-H12 -> -3
A15: YoY growth — 2025 as printed by NSR (2024 base not in the table); 2026-30 recomputed
A16: XPUs — y/y | B16: % y/y | C16: 0.66 | D16: =IF(OR(D5="",C5=""),"",IFERROR(D5/C5-1,"")) -> 0.9902439 | E16: =IF(OR(E5="",D5=""),"",IFERROR(E5/D5-1,"")) -> 0.91666667 | F16: =IF(OR(F5="",E5=""),"",IFERROR(F5/E5-1,"")) -> 0.60102302 | G16: =IF(OR(G5="",F5=""),"",IFERROR(G5/F5-1,"")) -> 0.21166134 | H16: =IF(OR(H5="",G5=""),"",IFERROR(H5/G5-1,"")) -> 0.12195122
A17: CPUs — y/y | B17: % y/y | C17: 1.81 | D17: =IF(OR(D6="",C6=""),"",IFERROR(D6/C6-1,"")) -> 3.5 | E17: =IF(OR(E6="",D6=""),"",IFERROR(E6/D6-1,"")) -> 1.0740741 | F17: =IF(OR(F6="",E6=""),"",IFERROR(F6/E6-1,"")) -> 0.60714286 | G17: =IF(OR(G6="",F6=""),"",IFERROR(G6/F6-1,"")) -> 0.43333333 | H17: =IF(OR(H6="",G6=""),"",IFERROR(H6/G6-1,"")) -> 0.30232558
A18: DRAM & NAND — y/y | B18: % y/y | C18: 0.83 | D18: =IF(OR(D7="",C7=""),"",IFERROR(D7/C7-1,"")) -> 5.1538462 | E18: =IF(OR(E7="",D7=""),"",IFERROR(E7/D7-1,"")) -> 1.1125 | F18: =IF(OR(F7="",E7=""),"",IFERROR(F7/E7-1,"")) -> 0.35798817 | G18: =IF(OR(G7="",F7=""),"",IFERROR(G7/F7-1,"")) -> -0.061002179 | H18: =IF(OR(H7="",G7=""),"",IFERROR(H7/G7-1,"")) -> -0.018561485
A19: Other server content — y/y | B19: % y/y | C19: 0.7 | D19: =IF(OR(D8="",C8=""),"",IFERROR(D8/C8-1,"")) -> 1.1875 | E19: =IF(OR(E8="",D8=""),"",IFERROR(E8/D8-1,"")) -> 0.82857143 | F19: =IF(OR(F8="",E8=""),"",IFERROR(F8/E8-1,"")) -> 0.52604167 | G19: =IF(OR(G8="",F8=""),"",IFERROR(G8/F8-1,"")) -> 0.15358362 | H19: =IF(OR(H8="",G8=""),"",IFERROR(H8/G8-1,"")) -> 0.1035503
A20: Networking — y/y | B20: % y/y | C20: 1.52 | D20: =IF(OR(D9="",C9=""),"",IFERROR(D9/C9-1,"")) -> 1.575 | E20: =IF(OR(E9="",D9=""),"",IFERROR(E9/D9-1,"")) -> 1.0485437 | F20: =IF(OR(F9="",E9=""),"",IFERROR(F9/E9-1,"")) -> 0.59241706 | G20: =IF(OR(G9="",F9=""),"",IFERROR(G9/F9-1,"")) -> 0.20535714 | H20: =IF(OR(H9="",G9=""),"",IFERROR(H9/G9-1,"")) -> 0.14814815
A21: Other equipment & buildings — y/y | B21: % y/y | C21: 1.24 | D21: =IF(OR(D10="",C10=""),"",IFERROR(D10/C10-1,"")) -> 0.27131783 | E21: =IF(OR(E10="",D10=""),"",IFERROR(E10/D10-1,"")) -> 0.87195122 | F21: =IF(OR(F10="",E10=""),"",IFERROR(F10/E10-1,"")) -> 0.46416938 | G21: =IF(OR(G10="",F10=""),"",IFERROR(G10/F10-1,"")) -> 0.096774194 | H21: =IF(OR(H10="",G10=""),"",IFERROR(H10/G10-1,"")) -> 0.030425963
A22: Total AI capex — y/y | B22: % y/y | D22: =IF(OR(D11="",C11=""),"",IFERROR(D11/C11-1,"")) -> 0.93996569 | E22: =IF(OR(E11="",D11=""),"",IFERROR(E11/D11-1,"")) -> 0.93899204 | F22: =IF(OR(F11="",E11=""),"",IFERROR(F11/E11-1,"")) -> 0.51801186 | G22: =IF(OR(G11="",F11=""),"",IFERROR(G11/F11-1,"")) -> 0.14328627 | H22: =IF(OR(H11="",G11=""),"",IFERROR(H11/G11-1,"")) -> 0.089595376
A24: Mix — % of total AI capex (recomputed; NSR prints XPU 35/36/36/38/40/41%, other equipment 44/29/28/27/26/24%)
A25: XPUs — % of AI capex | B25: % of total | C25: =IF(OR(C5="",C11=""),"",IFERROR(C5/C11,"")) -> 0.3516295 | D25: =IF(OR(D5="",D11=""),"",IFERROR(D5/D11,"")) -> 0.36074271 | E25: =IF(OR(E5="",E11=""),"",IFERROR(E5/E11,"")) -> 0.35658915 | F25: =IF(OR(F5="",F11=""),"",IFERROR(F5/F11,"")) -> 0.37608892 | G25: =IF(OR(G5="",G11=""),"",IFERROR(G5/G11,"")) -> 0.39858119 | H25: =IF(OR(H5="",H11=""),"",IFERROR(H5/H11,"")) -> 0.41041717
A26: CPUs — % of AI capex | B26: % of total | C26: =IF(OR(C6="",C11=""),"",IFERROR(C6/C11,"")) -> 0.010291595 | D26: =IF(OR(D6="",D11=""),"",IFERROR(D6/D11,"")) -> 0.023872679 | E26: =IF(OR(E6="",E11=""),"",IFERROR(E6/E11,"")) -> 0.025535796 | F26: =IF(OR(F6="",F11=""),"",IFERROR(F6/F11,"")) -> 0.027035146 | G26: =IF(OR(G6="",G11=""),"",IFERROR(G6/G11,"")) -> 0.033893852 | H26: =IF(OR(H6="",H11=""),"",IFERROR(H6/H11,"")) -> 0.040511213
A27: DRAM & NAND — % of AI capex | B27: % of total | C27: =IF(OR(C7="",C11=""),"",IFERROR(C7/C11,"")) -> 0.044596913 | D27: =IF(OR(D7="",D11=""),"",IFERROR(D7/D11,"")) -> 0.14146773 | E27: =IF(OR(E7="",E11=""),"",IFERROR(E7/E11,"")) -> 0.15412677 | F27: =IF(OR(F7="",F11=""),"",IFERROR(F7/F11,"")) -> 0.13787924 | G27: =IF(OR(G7="",G11=""),"",IFERROR(G7/G11,"")) -> 0.11324225 | H27: =IF(OR(H7="",H11=""),"",IFERROR(H7/H11,"")) -> 0.10200145
A28: Other server content — % of AI capex | B28: % of total | C28: =IF(OR(C8="",C11=""),"",IFERROR(C8/C11,"")) -> 0.082332762 | D28: =IF(OR(D8="",D11=""),"",IFERROR(D8/D11,"")) -> 0.092838196 | E28: =IF(OR(E8="",E11=""),"",IFERROR(E8/E11,"")) -> 0.0875513 | F28: =IF(OR(F8="",F11=""),"",IFERROR(F8/F11,"")) -> 0.088014419 | G28: =IF(OR(G8="",G11=""),"",IFERROR(G8/G11,"")) -> 0.088807147 | H28: =IF(OR(H8="",H11=""),"",IFERROR(H8/H11,"")) -> 0.089944538
A29: Networking — % of AI capex | B29: % of total | C29: =IF(OR(C9="",C11=""),"",IFERROR(C9/C11,"")) -> 0.068610635 | D29: =IF(OR(D9="",D11=""),"",IFERROR(D9/D11,"")) -> 0.09106985 | E29: =IF(OR(E9="",E11=""),"",IFERROR(E9/E11,"")) -> 0.09621523 | F29: =IF(OR(F9="",F11=""),"",IFERROR(F9/F11,"")) -> 0.10093121 | G29: =IF(OR(G9="",G11=""),"",IFERROR(G9/G11,"")) -> 0.10641093 | H29: =IF(OR(H9="",H11=""),"",IFERROR(H9/H11,"")) -> 0.11212925
A30: Other equipment & buildings — % of AI capex | B30: % of total | C30: =IF(OR(C10="",C11=""),"",IFERROR(C10/C11,"")) -> 0.44253859 | D30: =IF(OR(D10="",D11=""),"",IFERROR(D10/D11,"")) -> 0.29000884 | E30: =IF(OR(E10="",E11=""),"",IFERROR(E10/E11,"")) -> 0.27998176 | F30: =IF(OR(F10="",F11=""),"",IFERROR(F10/F11,"")) -> 0.27005107 | G30: =IF(OR(G10="",G11=""),"",IFERROR(G10/G11,"")) -> 0.25906463 | H30: =IF(OR(H10="",H11=""),"",IFERROR(H10/H11,"")) -> 0.24499638
A31: Technology spend (= total − other equipment & buildings) | B31: $bn | C31: =C11-C10 -> 325 | D31: =D11-D10 -> 803 | E31: =E11-E10 -> 1579 | F31: =F11-F10 -> 2430 | G31: =G11-G10 -> 2820 | H31: =H11-H10 -> 3131
A32: XPUs — % of technology spend | B32: % of tech | C32: =IF(OR(C5="",C31=""),"",IFERROR(C5/C31,"")) -> 0.63076923 | D32: =IF(OR(D5="",D31=""),"",IFERROR(D5/D31,"")) -> 0.50809465 | E32: =IF(OR(E5="",E31=""),"",IFERROR(E5/E31,"")) -> 0.49525016 | F32: =IF(OR(F5="",F31=""),"",IFERROR(F5/F31,"")) -> 0.51522634 | G32: =IF(OR(G5="",G31=""),"",IFERROR(G5/G31,"")) -> 0.53794326 | H32: =IF(OR(H5="",H31=""),"",IFERROR(H5/H31,"")) -> 0.5435963
A33: DRAM & NAND — % of technology spend | B33: % of tech | C33: =IF(OR(C7="",C31=""),"",IFERROR(C7/C31,"")) -> 0.08 | D33: =IF(OR(D7="",D31=""),"",IFERROR(D7/D31,"")) -> 0.1992528 | E33: =IF(OR(E7="",E31=""),"",IFERROR(E7/E31,"")) -> 0.21405953 | F33: =IF(OR(F7="",F31=""),"",IFERROR(F7/F31,"")) -> 0.18888889 | G33: =IF(OR(G7="",G31=""),"",IFERROR(G7/G31,"")) -> 0.15283688 | H33: =IF(OR(H7="",H31=""),"",IFERROR(H7/H31,"")) -> 0.13510061
A35: Derived — cumulative spend and the non-AI residual
A36: Cumulative AI capex 2026-30 (formula, in 2030 column) | B36: $bn | H36: =SUM(D11:H11) -> 14606
A37: Total DC capex 2026-30 — NSR waterfall (p.6) | B37: $bn | H37: 16500
A38: Implied non-AI DC capex 2026-30 (= total DC − cumulative AI) | B38: $bn | H38: =H37-H36 -> 1894 | K38: p.7 hyperscaler non-AI alone (~$125bn 2025 +13% p.a.) sums to ~$0.9tn over 2026-30; the residual here also holds enterprise/government non-AI.
A40: Forecast history — 2030 AI capex (p.1 / p.3)
A41: Entering 2Q26 earnings season | B41: $bn | H41: 2400
A42: After TSMC / ASML prints | B42: $bn | H42: 3100 | K42: p.1 says $3tn, p.3 says ~$3.1tn
A43: This note (18 Sep 2026) | B43: $bn | H43: =H12 -> 4150
A44: Uplift vs prior | B44: % | H44: =IFERROR(H43/H42-1,"") -> 0.33870968

Sheet NSR_Memory
A1: NSR p.5 — Memory economics within AI infrastructure deployments, 2025-2030 ($bn)
A2: Source: New Street Research (Ferragu et al.), 18 Sep 2026, p.5. Blue = as printed; black = recomputed; green = linked from NSR_Capex; salmon = inconsistency inside the NSR exhibit.
A4: Line | B4: Unit | C4: 2025 | D4: 2026 | E4: 2027 | F4: 2028 | G4: 2029 | H4: 2030 | I4: CAGR 25-30 | J4: Notes
A5: Total server content (formula = XPUs + CPUs + DRAM&NAND + other server content, p.4 lines) | B5: $bn | C5: =NSR_Capex!C5+NSR_Capex!C6+NSR_Capex!C7+NSR_Capex!C8 -> 285 | D5: =NSR_Capex!D5+NSR_Capex!D6+NSR_Capex!D7+NSR_Capex!D8 -> 700 | E5: =NSR_Capex!E5+NSR_Capex!E6+NSR_Capex!E7+NSR_Capex!E8 -> 1368 | F5: =NSR_Capex!F5+NSR_Capex!F6+NSR_Capex!F7+NSR_Capex!F8 -> 2094 | G5: =NSR_Capex!G5+NSR_Capex!G6+NSR_Capex!G7+NSR_Capex!G8 -> 2415 | H5: =NSR_Capex!H5+NSR_Capex!H6+NSR_Capex!H7+NSR_Capex!H8 -> 2666 | J5: Reproduces the printed row within rounding — so p.5 ‘total server content’ = p.4 technology spend ex-networking.
A6: Total server content — NSR printed | B6: $bn | C6: 285 | D6: 701 | E6: 1368 | F6: 2093 | G6: 2415 | H6: 2666
A7: Check: formula − printed | B7: $bn | C7: =C5-C6 -> 0 | D7: =D5-D6 -> -1 | E7: =E5-E6 -> 0 | F7: =F5-F6 -> 1 | G7: =G5-G6 -> 0 | H7: =H5-H6 -> 0
A9: XPUs and HBM
A10: XPUs spending (link p.4) | B10: $bn | C10: =NSR_Capex!C5 -> 205 | D10: =NSR_Capex!D5 -> 408 | E10: =NSR_Capex!E5 -> 782 | F10: =NSR_Capex!F5 -> 1252 | G10: =NSR_Capex!G5 -> 1517 | H10: =NSR_Capex!H5 -> 1702
A11: XPUs — y/y | B11: % y/y | C11: 0.66 | D11: =IF(OR(D10="",C10=""),"",IFERROR(D10/C10-1,"")) -> 0.9902439 | E11: =IF(OR(E10="",D10=""),"",IFERROR(E10/D10-1,"")) -> 0.91666667 | F11: =IF(OR(F10="",E10=""),"",IFERROR(F10/E10-1,"")) -> 0.60102302 | G11: =IF(OR(G10="",F10=""),"",IFERROR(G10/F10-1,"")) -> 0.21166134 | H11: =IF(OR(H10="",G10=""),"",IFERROR(H10/G10-1,"")) -> 0.12195122
A12: XPUs / total server content | B12: % | C12: =IF(OR(C10="",C6=""),"",IFERROR(C10/C6,"")) -> 0.71929825 | D12: =IF(OR(D10="",D6=""),"",IFERROR(D10/D6,"")) -> 0.58202568 | E12: =IF(OR(E10="",E6=""),"",IFERROR(E10/E6,"")) -> 0.57163743 | F12: =IF(OR(F10="",F6=""),"",IFERROR(F10/F6,"")) -> 0.59818442 | G12: =IF(OR(G10="",G6=""),"",IFERROR(G10/G6,"")) -> 0.62815735 | H12: =IF(OR(H10="",H6=""),"",IFERROR(H10/H6,"")) -> 0.6384096
A13: HBM | B13: $bn | C13: 34 | D13: 82 | E13: 189 | F13: 332 | G13: 457 | H13: 560 | I13: =IFERROR((H13/C13)^(1/5)-1,"") -> 0.75122449 | J13: NSR: HBM rises from 15/16% to 33% of XPU spending in 5 years despite pricing normalizing
A14: HBM — y/y | B14: % y/y | C14: 0.93 | D14: =IF(OR(D13="",C13=""),"",IFERROR(D13/C13-1,"")) -> 1.4117647 | E14: =IF(OR(E13="",D13=""),"",IFERROR(E13/D13-1,"")) -> 1.304878 | F14: =IF(OR(F13="",E13=""),"",IFERROR(F13/E13-1,"")) -> 0.75661376 | G14: =IF(OR(G13="",F13=""),"",IFERROR(G13/F13-1,"")) -> 0.37650602 | H14: =IF(OR(H13="",G13=""),"",IFERROR(H13/G13-1,"")) -> 0.22538293
A15: HBM / XPU spending | B15: % | C15: =IF(OR(C13="",C10=""),"",IFERROR(C13/C10,"")) -> 0.16585366 | D15: =IF(OR(D13="",D10=""),"",IFERROR(D13/D10,"")) -> 0.20098039 | E15: =IF(OR(E13="",E10=""),"",IFERROR(E13/E10,"")) -> 0.24168798 | F15: =IF(OR(F13="",F10=""),"",IFERROR(F13/F10,"")) -> 0.26517572 | G15: =IF(OR(G13="",G10=""),"",IFERROR(G13/G10,"")) -> 0.30125247 | H15: =IF(OR(H13="",H10=""),"",IFERROR(H13/H10,"")) -> 0.32902468
A16: HBM COGS growth — NSR printed | B16: % y/y | C16: 0.65 | D16: 0.94 | E16: 0.76 | F16: 0.94 | G16: 0.51 | H16: 0.27
A17: HBM gross margin — NSR printed | B17: % | C17: 0.69 | D17: 0.75 | E17: 0.81 | F17: 0.79 | G17: 0.77 | H17: 0.76
A18: HBM COGS implied (= HBM × (1 − GM)) | B18: $bn | C18: =C13*(1-C17) -> 10.54 | D18: =D13*(1-D17) -> 20.5 | E18: =E13*(1-E17) -> 35.91 | F18: =F13*(1-F17) -> 69.72 | G18: =G13*(1-G17) -> 105.11 | H18: =H13*(1-H17) -> 134.4
A19: HBM COGS growth implied (check vs printed row) | B19: % y/y | D19: =IF(OR(D18="",C18=""),"",IFERROR(D18/C18-1,"")) -> 0.94497154 | E19: =IF(OR(E18="",D18=""),"",IFERROR(E18/D18-1,"")) -> 0.75170732 | F19: =IF(OR(F18="",E18=""),"",IFERROR(F18/E18-1,"")) -> 0.94152047 | G19: =IF(OR(G18="",F18=""),"",IFERROR(G18/F18-1,"")) -> 0.50760184 | H19: =IF(OR(H18="",G18=""),"",IFERROR(H18/G18-1,"")) -> 0.27866045
A20: Other XPU spending (formula = XPU − HBM) | B20: $bn | C20: =C10-C13 -> 171 | D20: =D10-D13 -> 326 | E20: =E10-E13 -> 593 | F20: =F10-F13 -> 920 | G20: =G10-G13 -> 1060 | H20: =H10-H13 -> 1142
A21: Other XPU spending — NSR printed | B21: $bn | C21: 172 | D21: 326 | E21: 593 | F21: 920 | G21: 1060 | H21: 1145
A22: Check: formula − printed | B22: $bn | C22: =C20-C21 -> -1 | D22: =D20-D21 -> 0 | E22: =E20-E21 -> 0 | F22: =F20-F21 -> 0 | G22: =G20-G21 -> 0 | H22: =H20-H21 -> -3
A24: CPUs
A25: CPUs spending (p.5 — TOTAL server-CPU market, not the p.4 AI slice) | B25: $bn | C25: 25 | D25: 49 | E25: 80 | F25: 117 | G25: 159 | H25: 202 | I25: =IFERROR((H25/C25)^(1/5)-1,"") -> 0.51873595 | J25: p.3: ~$200bn CPU market 2030, ~$170bn for AI; p.4 AI-capex CPU line = $168bn 2030
A26: CPUs spending — y/y | B26: % y/y | C26: 0.21 | D26: =IF(OR(D25="",C25=""),"",IFERROR(D25/C25-1,"")) -> 0.96 | E26: =IF(OR(E25="",D25=""),"",IFERROR(E25/D25-1,"")) -> 0.63265306 | F26: =IF(OR(F25="",E25=""),"",IFERROR(F25/E25-1,"")) -> 0.4625 | G26: =IF(OR(G25="",F25=""),"",IFERROR(G25/F25-1,"")) -> 0.35897436 | H26: =IF(OR(H25="",G25=""),"",IFERROR(H25/G25-1,"")) -> 0.27044025
A27: AI share of CPU spending (= p.4 CPUs / p.5 CPUs) | B27: % | C27: =IFERROR(NSR_Capex!C6/C25,"") -> 0.24 | D27: =IFERROR(NSR_Capex!D6/D25,"") -> 0.55102041 | E27: =IFERROR(NSR_Capex!E6/E25,"") -> 0.7 | F27: =IFERROR(NSR_Capex!F6/F25,"") -> 0.76923077 | G27: =IFERROR(NSR_Capex!G6/G25,"") -> 0.81132075 | H27: =IFERROR(NSR_Capex!H6/H25,"") -> 0.83168317
A29: DRAM and NAND
A30: DRAM | B30: $bn | C30: 17 | D30: 100 | E30: 211 | F30: 273 | G30: 250 | H30: 241 | I30: =IFERROR((H30/C30)^(1/5)-1,"") -> 0.69947048 | J30: NSR: DRAM value content tripling 2025-27 (6% → 15% of server content) before prices normalize to just below 10% in 2030
A31: DRAM — y/y | B31: % y/y | C31: 1.05 | D31: =IF(OR(D30="",C30=""),"",IFERROR(D30/C30-1,"")) -> 4.8823529 | E31: =IF(OR(E30="",D30=""),"",IFERROR(E30/D30-1,"")) -> 1.11 | F31: =IF(OR(F30="",E30=""),"",IFERROR(F30/E30-1,"")) -> 0.29383886 | G31: =IF(OR(G30="",F30=""),"",IFERROR(G30/F30-1,"")) -> -0.084249084 | H31: =IF(OR(H30="",G30=""),"",IFERROR(H30/G30-1,"")) -> -0.036
A32: DRAM / total server content | B32: % | C32: =IF(OR(C30="",C6=""),"",IFERROR(C30/C6,"")) -> 0.059649123 | D32: =IF(OR(D30="",D6=""),"",IFERROR(D30/D6,"")) -> 0.14265335 | E32: =IF(OR(E30="",E6=""),"",IFERROR(E30/E6,"")) -> 0.15423977 | F32: =IF(OR(F30="",F6=""),"",IFERROR(F30/F6,"")) -> 0.13043478 | G32: =IF(OR(G30="",G6=""),"",IFERROR(G30/G6,"")) -> 0.10351967 | H32: =IF(OR(H30="",H6=""),"",IFERROR(H30/H6,"")) -> 0.090397599
A33: DRAM COGS growth — NSR printed | B33: % y/y | C33: 0.56 | D33: 0.71 | E33: 1.11 | F33: 0.83 | G33: 0.13 | H33: 0.14
A34: DRAM gross margin — NSR printed | B34: % | C34: 0.58 | D34: 0.88 | E34: 0.88 | F34: 0.83 | G34: 0.79 | H34: 0.75
A35: NAND | B35: $bn | C35: 9 | D35: 60 | E35: 127 | F35: 186 | G35: 181 | H35: 182 | I35: =IFERROR((H35/C35)^(1/5)-1,"") -> 0.82459204 | J35: NSR: NAND follows a pattern similar to DRAM
A36: NAND — y/y | B36: % y/y | C36: 0.53 | D36: =IF(OR(D35="",C35=""),"",IFERROR(D35/C35-1,"")) -> 5.6666667 | E36: =IF(OR(E35="",D35=""),"",IFERROR(E35/D35-1,"")) -> 1.1166667 | F36: =IF(OR(F35="",E35=""),"",IFERROR(F35/E35-1,"")) -> 0.46456693 | G36: =IF(OR(G35="",F35=""),"",IFERROR(G35/F35-1,"")) -> -0.02688172 | H36: =IF(OR(H35="",G35=""),"",IFERROR(H35/G35-1,"")) -> 0.0055248619
A37: NAND / total server content | B37: % | C37: =IF(OR(C35="",C6=""),"",IFERROR(C35/C6,"")) -> 0.031578947 | D37: =IF(OR(D35="",D6=""),"",IFERROR(D35/D6,"")) -> 0.085592011 | E37: =IF(OR(E35="",E6=""),"",IFERROR(E35/E6,"")) -> 0.092836257 | F37: =IF(OR(F35="",F6=""),"",IFERROR(F35/F6,"")) -> 0.088867654 | G37: =IF(OR(G35="",G6=""),"",IFERROR(G35/G6,"")) -> 0.07494824 | H37: =IF(OR(H35="",H6=""),"",IFERROR(H35/H6,"")) -> 0.068267067
A38: NAND COGS growth — NSR printed (identical to DRAM row in the note) | B38: % y/y | C38: 0.56 | D38: 0.71 | E38: 1.11 | F38: 0.83 | G38: 0.13 | H38: 0.14 | J38: NSR prints the SAME COGS-growth row for DRAM and NAND — likely a copy-down in their exhibit.
A39: NAND gross margin — NSR printed | B39: % | C39: 0.25 | D39: 0.8 | E39: 0.8 | F39: 0.75 | G39: 0.71 | H39: 0.67
A41: Other server content (p.5 definition)
A42: Other server content (p.5 row) — NSR printed | B42: $bn | C42: 29 | D42: 181 | E42: 328 | F42: 499 | G42: 626 | H42: 744
A43: Other server content (p.5) — y/y recomputed | B43: % y/y | D43: =IF(OR(D42="",C42=""),"",IFERROR(D42/C42-1,"")) -> 5.2413793 | E43: =IF(OR(E42="",D42=""),"",IFERROR(E42/D42-1,"")) -> 0.8121547 | F43: =IF(OR(F42="",E42=""),"",IFERROR(F42/E42-1,"")) -> 0.52134146 | G43: =IF(OR(G42="",F42=""),"",IFERROR(G42/F42-1,"")) -> 0.25450902 | H43: =IF(OR(H42="",G42=""),"",IFERROR(H42/G42-1,"")) -> 0.1884984
A44: Other server content (p.5) — y/y as printed | B44: % y/y | C44: 2.02 | D44: 1.91 | E44: 1 | F44: 0.59 | G44: 0.16 | H44: 0.1 | J44: Printed +191% for 2026 implies a 2025 base of ~$62bn, not the $29bn printed — internal inconsistency in the NSR exhibit (2025 only).
A46: Reconciliation — how the p.5 lines map onto the p.4 components
A47: DRAM + NAND (p.5) | B47: $bn | C47: =C30+C35 -> 26 | D47: =D30+D35 -> 160 | E47: =E30+E35 -> 338 | F47: =F30+F35 -> 459 | G47: =G30+G35 -> 431 | H47: =H30+H35 -> 423
A48: DRAM & NAND (p.4 line, link) | B48: $bn | C48: =NSR_Capex!C7 -> 26 | D48: =NSR_Capex!D7 -> 160 | E48: =NSR_Capex!E7 -> 338 | F48: =NSR_Capex!F7 -> 459 | G48: =NSR_Capex!G7 -> 431 | H48: =NSR_Capex!H7 -> 423
A49: Check: p.5 − p.4 | B49: $bn | C49: =C47-C48 -> 0 | D49: =D47-D48 -> 0 | E49: =E47-E48 -> 0 | F49: =F47-F48 -> 0 | G49: =G47-G48 -> 0 | H49: =H47-H48 -> 0
A50: p.4 other server content + p.5 CPUs + p.4 CPUs | B50: $bn | C50: =NSR_Capex!C8+C25+NSR_Capex!C6 -> 79 | D50: =NSR_Capex!D8+D25+NSR_Capex!D6 -> 181 | E50: =NSR_Capex!E8+E25+NSR_Capex!E6 -> 328 | F50: =NSR_Capex!F8+F25+NSR_Capex!F6 -> 500 | G50: =NSR_Capex!G8+G25+NSR_Capex!G6 -> 626 | H50: =NSR_Capex!H8+H25+NSR_Capex!H6 -> 743
A51: Check: p.5 other server content − that sum (0 from 2026 → p.5 ‘other’ double-counts the CPU lines; 2025 off by ~$50bn) | B51: $bn | C51: =C42-C50 -> -50 | D51: =D42-D50 -> 0 | E51: =E42-E50 -> 0 | F51: =F42-F50 -> -1 | G51: =G42-G50 -> 0 | H51: =H42-H50 -> 1
A52: TOTAL MEMORY in AI infrastructure (HBM + DRAM + NAND) | B52: $bn | C52: =C13+C30+C35 -> 60 | D52: =D13+D30+D35 -> 242 | E52: =E13+E30+E35 -> 527 | F52: =F13+F30+F35 -> 791 | G52: =G13+G30+G35 -> 888 | H52: =H13+H30+H35 -> 983 | I52: =IFERROR((H52/C52)^(1/5)-1,"") -> 0.74936508
A53: Total memory / total server content | B53: % | C53: =IF(OR(C52="",C6=""),"",IFERROR(C52/C6,"")) -> 0.21052632 | D53: =IF(OR(D52="",D6=""),"",IFERROR(D52/D6,"")) -> 0.34522111 | E53: =IF(OR(E52="",E6=""),"",IFERROR(E52/E6,"")) -> 0.38523392 | F53: =IF(OR(F52="",F6=""),"",IFERROR(F52/F6,"")) -> 0.37792642 | G53: =IF(OR(G52="",G6=""),"",IFERROR(G52/G6,"")) -> 0.36770186 | H53: =IF(OR(H52="",H6=""),"",IFERROR(H52/H6,"")) -> 0.36871718
A54: Total memory / total AI capex (p.4 total) | B54: % | C54: =IFERROR(C52/NSR_Capex!C11,"") -> 0.10291595 | D54: =IFERROR(D52/NSR_Capex!D11,"") -> 0.21396994 | E54: =IFERROR(E52/NSR_Capex!E11,"") -> 0.24031008 | F54: =IFERROR(F52/NSR_Capex!F11,"") -> 0.23760889 | G54: =IFERROR(G52/NSR_Capex!G11,"") -> 0.23331582 | H54: =IFERROR(H52/NSR_Capex!H11,"") -> 0.23703882

Sheet NSR_HyperPL
A1: NSR p.7 — Hyperscalers P&L and cash flow, 2025-2030 (US$bn)
A2: Source: New Street Research (Ferragu et al.), 18 Sep 2026, p.7 ‘We expect hyperscaler FCF to turn negative and recover only in 2030’. Basket not enumerated in the note. Blue = printed; black = recomputed.
A4: Line | B4: Unit | C4: 2025 | D4: 2026 | E4: 2027 | F4: 2028 | G4: 2029 | H4: 2030 | I4: Cum. 2026-30 (calc) | J4: Cum. printed | K4: NSR comment
A5: Core (non-cloud) business
A6: Core revenues | B6: $bn | C6: 1349 | D6: 1550 | E6: 1780 | F6: 2041 | G6: 2337 | H6: 2673 | I6: =SUM(D6:H6) -> 10381 | J6: 10381 | K6: Re-platforming: capital intensity rises, cash-cost efficiency drives revenue growth well above cash-cost growth → fast-expanding EBITDA margin, slowly expanding EBIT margin
A7: Core EBITDA margin — printed | B7: % | C7: 0.36 | D7: 0.39 | E7: 0.42 | F7: 0.45 | G7: 0.48 | H7: 0.52 | J7: 0.46
A8: Core EBIT margin — printed | B8: % | C8: 0.29 | D8: 0.31 | E8: 0.32 | F8: 0.32 | G8: 0.33 | H8: 0.33 | J8: 0.32
A10: Cloud
A11: Cloud — AI revenues | B11: $bn | C11: 55 | D11: 163 | E11: 356 | F11: 651 | G11: 1046 | H11: 1511 | I11: =SUM(D11:H11) -> 3727 | J11: 3726 | K11: >100GW deployed by the end of the decade. ~$13bn revenues / GW
A12: Cloud — Non-AI revenues | B12: $bn | C12: 224 | D12: 253 | E12: 278 | F12: 306 | G12: 336 | H12: 370 | I12: =SUM(D12:H12) -> 1543 | J12: 1543 | K12: Stabilizes at ~10% growth, below historic long-term trend
A13: Cloud revenues (formula = AI + non-AI) | B13: $bn | C13: =C11+C12 -> 279 | D13: =D11+D12 -> 416 | E13: =E11+E12 -> 634 | F13: =F11+F12 -> 957 | G13: =G11+G12 -> 1382 | H13: =H11+H12 -> 1881 | I13: =SUM(D13:H13) -> 5270 | J13: 5269 | K13: printed 279 / 416 / 634 / 957 / 1,382 / 1,881
A14: Cloud revenues — y/y (printed 28/49/52/51/44/36%) | B14: % y/y | C14: 0.28 | D14: =IF(OR(D13="",C13=""),"",IFERROR(D13/C13-1,"")) -> 0.49103943 | E14: =IF(OR(E13="",D13=""),"",IFERROR(E13/D13-1,"")) -> 0.52403846 | F14: =IF(OR(F13="",E13=""),"",IFERROR(F13/E13-1,"")) -> 0.50946372 | G14: =IF(OR(G13="",F13=""),"",IFERROR(G13/F13-1,"")) -> 0.44409613 | H14: =IF(OR(H13="",G13=""),"",IFERROR(H13/G13-1,"")) -> 0.36107091
A15: AI revenues — y/y | B15: % y/y | D15: =IF(OR(D11="",C11=""),"",IFERROR(D11/C11-1,"")) -> 1.9636364 | E15: =IF(OR(E11="",D11=""),"",IFERROR(E11/D11-1,"")) -> 1.1840491 | F15: =IF(OR(F11="",E11=""),"",IFERROR(F11/E11-1,"")) -> 0.82865169 | G15: =IF(OR(G11="",F11=""),"",IFERROR(G11/F11-1,"")) -> 0.60675883 | H15: =IF(OR(H11="",G11=""),"",IFERROR(H11/G11-1,"")) -> 0.44455067
A16: Cloud EBITDA margin — printed | B16: % | C16: 0.57 | D16: 0.62 | E16: 0.68 | F16: 0.72 | G16: 0.76 | H16: 0.78 | J16: 0.74 | K16: Higher capital intensity of AI cloud vs traditional cloud
A17: Cloud EBIT margin — printed | B17: % | C17: 0.39 | D17: 0.37 | E17: 0.35 | F17: 0.33 | G17: 0.32 | H17: 0.32 | J17: 0.33 | K17: EBIT margin declines as lower-margin AI cloud rises in the mix
A19: Group
A20: Group revenues (formula = core + cloud) | B20: $bn | C20: =C6+C13 -> 1628 | D20: =D6+D13 -> 1966 | E20: =E6+E13 -> 2414 | F20: =F6+F13 -> 2998 | G20: =G6+G13 -> 3719 | H20: =H6+H13 -> 4554 | I20: =SUM(D20:H20) -> 15651 | J20: 15650 | K20: printed 1,628 / 1,965 / 2,414 / 2,998 / 3,719 / 4,554
A21: Group revenues — y/y (printed 15/21/23/24/24/22%) | B21: % y/y | C21: 0.15 | D21: =IF(OR(D20="",C20=""),"",IFERROR(D20/C20-1,"")) -> 0.20761671 | E21: =IF(OR(E20="",D20=""),"",IFERROR(E20/D20-1,"")) -> 0.22787386 | F21: =IF(OR(F20="",E20=""),"",IFERROR(F20/E20-1,"")) -> 0.24192212 | G21: =IF(OR(G20="",F20=""),"",IFERROR(G20/F20-1,"")) -> 0.24049366 | H21: =IF(OR(H20="",G20=""),"",IFERROR(H20/G20-1,"")) -> 0.22452272
A22: EBITDA — printed | B22: $bn | C22: 643 | D22: 853 | E22: 1174 | F22: 1613 | G22: 2174 | H22: 2841 | I22: =SUM(D22:H22) -> 8655 | J22: 8654
A23: EBITDA rebuilt from segment margins (core×margin + cloud×margin) | B23: $bn | C23: =C6*C7+C13*C16 -> 644.67 | D23: =D6*D7+D13*D16 -> 862.42 | E23: =E6*E7+E13*E16 -> 1178.72 | F23: =F6*F7+F13*F16 -> 1607.49 | G23: =G6*G7+G13*G16 -> 2172.08 | H23: =H6*H7+H13*H16 -> 2857.14
A24: Check: rebuilt − printed (margin rounding) | B24: $bn | C24: =C23-C22 -> 1.67 | D24: =D23-D22 -> 9.42 | E24: =E23-E22 -> 4.72 | F24: =F23-F22 -> -5.51 | G24: =G23-G22 -> -1.92 | H24: =H23-H22 -> 16.14
A25: EBITDA margin (printed 40/43/49/54/58/62%) | B25: % | C25: =IF(OR(C22="",C20=""),"",IFERROR(C22/C20,"")) -> 0.39496314 | D25: =IF(OR(D22="",D20=""),"",IFERROR(D22/D20,"")) -> 0.43387589 | E25: =IF(OR(E22="",E20=""),"",IFERROR(E22/E20,"")) -> 0.48632974 | F25: =IF(OR(F22="",F20=""),"",IFERROR(F22/F20,"")) -> 0.53802535 | G25: =IF(OR(G22="",G20=""),"",IFERROR(G22/G20,"")) -> 0.58456574 | H25: =IF(OR(H22="",H20=""),"",IFERROR(H22/H20,"")) -> 0.62384717
A26: D&A — printed (negative) | B26: $bn | C26: -142 | D26: -222 | E26: -384 | F26: -634 | G26: -964 | H26: -1350 | I26: =SUM(D26:H26) -> -3554 | J26: -3555
A27: EBIT (formula = EBITDA + D&A) | B27: $bn | C27: =C22+C26 -> 501 | D27: =D22+D26 -> 631 | E27: =E22+E26 -> 790 | F27: =F22+F26 -> 979 | G27: =G22+G26 -> 1210 | H27: =H22+H26 -> 1491 | I27: =SUM(D27:H27) -> 5101 | J27: 5099 | K27: printed 501 / 631 / 789 / 979 / 1,209 / 1,490
A28: EBIT margin (printed 31/32/33/33/33/33%) | B28: % | C28: =IF(OR(C27="",C20=""),"",IFERROR(C27/C20,"")) -> 0.30773956 | D28: =IF(OR(D27="",D20=""),"",IFERROR(D27/D20,"")) -> 0.32095626 | E28: =IF(OR(E27="",E20=""),"",IFERROR(E27/E20,"")) -> 0.32725766 | F28: =IF(OR(F27="",F20=""),"",IFERROR(F27/F20,"")) -> 0.32655103 | G28: =IF(OR(G27="",G20=""),"",IFERROR(G27/G20,"")) -> 0.32535628 | H28: =IF(OR(H27="",H20=""),"",IFERROR(H27/H20,"")) -> 0.32740448
A30: Cash flow
A31: OCF — printed | B31: $bn | C31: 580 | D31: 774 | E31: 1074 | F31: 1489 | G31: 2019 | H31: 2650 | I31: =SUM(D31:H31) -> 8006 | J31: 8005
A32: OCF / EBITDA (cash conversion) | B32: x | C32: =IF(OR(C31="",C22=""),"",IFERROR(C31/C22,"")) -> 0.90202177 | D32: =IF(OR(D31="",D22=""),"",IFERROR(D31/D22,"")) -> 0.9073857 | E32: =IF(OR(E31="",E22=""),"",IFERROR(E31/E22,"")) -> 0.91482112 | F32: =IF(OR(F31="",F22=""),"",IFERROR(F31/F22,"")) -> 0.92312461 | G32: =IF(OR(G31="",G22=""),"",IFERROR(G31/G22,"")) -> 0.92870285 | H32: =IF(OR(H31="",H22=""),"",IFERROR(H31/H22,"")) -> 0.93277015
A33: Group capex — printed | B33: $bn | C33: 415 | D33: 795 | E33: 1384 | F33: 1975 | G33: 2181 | H33: 2387 | I33: =SUM(D33:H33) -> 8722 | J33: 8721 | K33: Mainly AI at ~$40-45bn/GW. Also ~$125bn of non-AI in 2025 growing ~13% p.a.
A34: Group capex — y/y | B34: % y/y | D34: =IF(OR(D33="",C33=""),"",IFERROR(D33/C33-1,"")) -> 0.91566265 | E34: =IF(OR(E33="",D33=""),"",IFERROR(E33/D33-1,"")) -> 0.7408805 | F34: =IF(OR(F33="",E33=""),"",IFERROR(F33/E33-1,"")) -> 0.42702312 | G34: =IF(OR(G33="",F33=""),"",IFERROR(G33/F33-1,"")) -> 0.1043038 | H34: =IF(OR(H33="",G33=""),"",IFERROR(H33/G33-1,"")) -> 0.094452086
A35: Capex / group revenues | B35: % | C35: =IF(OR(C33="",C20=""),"",IFERROR(C33/C20,"")) -> 0.254914 | D35: =IF(OR(D33="",D20=""),"",IFERROR(D33/D20,"")) -> 0.40437436 | E35: =IF(OR(E33="",E20=""),"",IFERROR(E33/E20,"")) -> 0.57332229 | F35: =IF(OR(F33="",F20=""),"",IFERROR(F33/F20,"")) -> 0.65877252 | G35: =IF(OR(G33="",G20=""),"",IFERROR(G33/G20,"")) -> 0.58644797 | H35: =IF(OR(H33="",H20=""),"",IFERROR(H33/H20,"")) -> 0.52415459
A36: FCF (formula = OCF − capex) | B36: $bn | C36: =C31-C33 -> 165 | D36: =D31-D33 -> -21 | E36: =E31-E33 -> -310 | F36: =F31-F33 -> -486 | G36: =G31-G33 -> -162 | H36: =H31-H33 -> 263 | I36: =SUM(D36:H36) -> -716 | J36: -716 | K36: printed 164 / (22) / (310) / (486) / (162) / 263 — negative through 2029, positive 2030; ~$700bn burn through 2029; <$1tn peak financing < 1 year of EBITDA
A37: FCF — printed | B37: $bn | C37: 164 | D37: -22 | E37: -310 | F37: -486 | G37: -162 | H37: 263
A38: Check: formula − printed | B38: $bn | C38: =C36-C37 -> 1 | D38: =D36-D37 -> 1 | E38: =E36-E37 -> 0 | F38: =F36-F37 -> 0 | G38: =G36-G37 -> 0 | H38: =H36-H37 -> 0
A40: Derived from NSR's own stated assumptions (p.7 comments) — AI capex, GW and revenue per GW
A41: Non-AI capex (= $125bn 2025 growing 13% p.a.; inputs on NSR_Datapoints) | B41: $bn | C41: =NSR_Datapoints!$B$31*(1+NSR_Datapoints!$B$32)^(2025-2025) -> 125 | D41: =NSR_Datapoints!$B$31*(1+NSR_Datapoints!$B$32)^(2026-2025) -> 141.25 | E41: =NSR_Datapoints!$B$31*(1+NSR_Datapoints!$B$32)^(2027-2025) -> 159.6125 | F41: =NSR_Datapoints!$B$31*(1+NSR_Datapoints!$B$32)^(2028-2025) -> 180.36212 | G41: =NSR_Datapoints!$B$31*(1+NSR_Datapoints!$B$32)^(2029-2025) -> 203.8092 | H41: =NSR_Datapoints!$B$31*(1+NSR_Datapoints!$B$32)^(2030-2025) -> 230.3044
A42: Implied hyperscaler AI capex (= group capex − non-AI) | B42: $bn | C42: =C33-C41 -> 290 | D42: =D33-D41 -> 653.75 | E42: =E33-E41 -> 1224.3875 | F42: =F33-F41 -> 1794.6379 | G42: =G33-G41 -> 1977.1908 | H42: =H33-H41 -> 2156.6956 | I42: =SUM(D42:H42) -> 7806.6618
A43: Implied GW added per year (= AI capex / $42.5bn per GW midpoint) | B43: GW | C43: =IFERROR(C42/NSR_Datapoints!$B$30,"") -> 6.8235294 | D43: =IFERROR(D42/NSR_Datapoints!$B$30,"") -> 15.382353 | E43: =IFERROR(E42/NSR_Datapoints!$B$30,"") -> 28.809118 | F43: =IFERROR(F42/NSR_Datapoints!$B$30,"") -> 42.226774 | G43: =IFERROR(G42/NSR_Datapoints!$B$30,"") -> 46.522136 | H43: =IFERROR(H42/NSR_Datapoints!$B$30,"") -> 50.745779
A44: Cumulative GW added 2026-30 (in 2030 column) | B44: GW | H44: =SUM(D43:H43) -> 183.68616 | K44: NSR states ‘>100GW deployed by end of decade’ for hyperscalers; $8.7tn of capex at $40-45bn/GW implies ~180-190 GW unless a large part of ‘group capex’ is shell/non-IT on a different $/GW
A45: AI cloud revenue per cumulative GW (memo, 2030 column) | B45: $bn/GW | H45: =IFERROR(H11/H44,"") -> 8.2259872 | K45: vs NSR's own ~$13bn/GW on p.7 — the two statements only reconcile on ~110-120 GW installed, i.e. NSR's $40-45bn/GW must be all-in facility capex

Sheet NSR_Funding
A1: NSR p.6 / p.8 — Funding the buildout: $16.5tn of cumulative datacenter capex 2026-2030 ($tn)
A2: Source: New Street Research (Ferragu et al.), 18 Sep 2026, p.6 waterfall ‘Running the numbers’ and p.8 ‘Neoclouds to finance $3-4tn’. Blue = printed; black = recomputed.
A4: USES — cumulative 2026-30 datacenter capex
A5: Use | B5: $tn (printed) | C5: % of total (calc) | D5: % printed | E5: Note
A6: Hyperscaler capex | B6: 8.5 | C6: =IFERROR(B6/$B$9,"") -> 0.51829268 | E6: p.6 waterfall; p.7 group capex cumulative 2026-30 prints $8.72tn (incl. ~$0.9tn non-AI)
A7: Neocloud (tier-2 & neocloud) capex | B7: 6.5 | C7: =IFERROR(B7/$B$9,"") -> 0.39634146 | E7: p.6 waterfall; p.8 prints ~$6.6tn cumulative group capex for tier-2 & neoclouds
A8: Enterprise & government capex | B8: 1.4 | C8: =IFERROR(B8/$B$9,"") -> 0.085365854 | D8: 0.09 | E8: “will invest in their own infrastructure ($1.4tn, or <10%)”
A9: Total DC capex 2026-30 (formula = sum of uses) | B9: =SUM(B6:B8) -> 16.4 | E9: NSR prints $16.5tn (sum of printed components = 16.4; rounding)
A10: Total DC capex 2026-30 — NSR printed | B10: 16.5
A11: Check: formula − printed | B11: =B9-B10 -> -0.1
A13: SOURCES — how the $16.5tn is covered
A14: Source of funds | B14: $tn (printed) | C14: % of total (calc) | D14: % printed | E14: Note
A15: Enterprise & government own capex | B15: 1.4 | C15: =IFERROR(B15/$B$10,"") -> 0.084848485 | D15: 0.09 | E15: “<10%”
A16: Accumulated hyperscaler OCF — consensus | B16: 6 | C16: =IFERROR(B16/$B$10,"") -> 0.36363636 | D16: 0.36 | E16: “Consensus models $6tn”
A17: NSR adjustments to hyperscaler OCF | B17: 2 | C17: =IFERROR(B17/$B$10,"") -> 0.12121212 | D17: 0.12 | E17: “we expect ~$2tn more, as hyperscalers grow faster (24% ’25-’30 CAGR vs 17% consensus), with higher flow-through incremental OCF margins (77% in 2030 vs consensus 60%)”
A18: Tier-2 & neocloud OCF | B18: 3.3 | C18: =IFERROR(B18/$B$10,"") -> 0.2 | D18: 0.2 | E18: “Tier 2 and Neoclouds growing to $2.3tn of revenue in 2030, generated on 91GW deployed, at 77% AI OCF margin”
A19: Financing required (formula = total DC capex − sources) | B19: =B10-SUM(B15:B18) -> 3.8 | C19: =IFERROR(B19/$B$10,"") -> 0.23030303 | D19: 0.23 | E19: NSR prints ~$3.7tn (~23%) — “Most of it will be carried by Neoclouds, with the support of hyperscalers (guarantees and backstops)”
A20: Financing required — NSR printed | B20: 3.7
A21: Hyperscaler OCF total (consensus + NSR adj.) | B21: =B16+B17 -> 8 | C21: =IFERROR(B21/$B$10,"") -> 0.48484848 | E21: NSR: “Hyperscaler OCF ($8tn, or ~50%)”; p.7 cumulative OCF 2026-30 prints $8.0tn
A23: p.8 — Tier-2 and neocloud financing structure (cumulative 2026-30, $tn)
A24: Line | B24: $tn (printed) | C24: % of neo capex (calc) | E24: Note
A25: Tier-2 & neocloud cumulative group capex 2026-30 | B25: 6.6 | C25: =IFERROR(B25/$B$25,"") -> 1 | E25: denominator
A26: Cumulative operating cash flow 2026-30 | B26: 3.3 | C26: =IFERROR(B26/$B$25,"") -> 0.5 | E26: “Operating cash flow of tier-2 and neoclouds likely to finance 40% of capex” (prints as 50% of 6.6 — NSR's 40% is a rounded statement)
A27: Loans 2026-30 (50% of buildings; 40% of hardware) | B27: 2.6 | C27: =IFERROR(B27/$B$25,"") -> 0.39393939 | E27: “debt 40 to 50%”
A28: Prepayments and equity | B28: 0.7 | C28: =IFERROR(B28/$B$25,"") -> 0.10606061
A29: Check: OCF + loans + prepayments/equity − capex | B29: =SUM(B26:B28)-B25 -> 0
A31: p.8 — Financing requirements vs key-player EBITDA
A32: Line | B32: $tn (printed) | E32: Note
A33: 2027 EBITDA — hyperscalers + Nvidia + Broadcom | B33: 1.8
A34: Total required financing 2026-30 — hyperscalers | B34: 0.7 | E34: Equals the p.7 cumulative FCF 2026-30 of −$716bn
A35: Total required financing 2026-30 — tier-2 & neoclouds | B35: 3.3 | E35: Equals loans 2.6 + prepayments/equity 0.7
A36: Total required financing (formula) | B36: =B34+B35 -> 4 | E36: Gives $4.0tn, vs the $3.7tn on the p.6 waterfall — a $0.3tn internal gap in the note (p.6 nets hyperscaler OCF against total, p.8 counts the hyperscaler shortfall gross)
A37: Debt / EBITDA (formula = required financing / 2027 EBITDA) | B37: =IFERROR(B36/B33,"") -> 2.2222222 | E37: NSR prints ~2.2x; “Industry-wide leverage not to exceed low-single-digit multiple of EBITDA”

Sheet NSR_Datapoints
A1: NSR p.2 — “Multiple datapoints over the earnings season lead us to materially increase our forecast”
A2: Source: New Street Research (Ferragu et al.), 18 Sep 2026, p.2 (datapoints table) and p.3 (forecast bridge). Transcribed verbatim (condensed). The p.3 values feed formulas on the other sheets.
A4: p.2 — supply-chain datapoints
A5: Company | C5: What indicates an acceleration? (NSR wording)
A6: Nvidia | C6: Expects ~70% revenue growth in FY28; unconstrained demand growth is >100% and supply should remain a bottleneck through FY28.
A7: Broadcom | C7: AI semiconductor revenue of $58bn in FY26, $115bn in FY27 and $230bn in FY28. Management sees demand for 30GW across six XPU customers; its financing platform is designed to enable >20GW through 2028.
A8: TSMC | C8: Abandoned its prior mid-to-high 50s% CAGR guide for 2024-29, expecting “stronger and stronger” growth.
A9: ASML | C9: Will increase capacity by 30% in both 2027 and 2028, after 40% in 2026 — implies growth extending strongly in 2028 and 2029 (semicap capacity is a ~1-year leading indicator).
A10: CPU vendors | C10: AMD raised the CPU TAM again to ~$220bn by 2030. Qualcomm and Nvidia are at $200bn.
A11: Hyperscalers | C11: Strong guides lift capex expectations for 2027/28 by 27%/32%. Compute demand continues to exceed available capacity into 2027, with AWS/Azure growth accelerating to 37%/43%. AWS sees “striking” demand for 2028 and $600bn revenue by 2036 (>15% p.a. from 2025).
A12: NSR read | C12: “Across compute, foundry and semicap, the supply chain is now planning capacity through 2030 with increasing confidence that demand will exceed how quickly supply can be added. Demand expectations continue to move higher even as capacity plans are raised, supporting a materially steeper spending trajectory through the end of the decade.”
A14: p.3 — forecast bridge and the marks behind the $4tn (these cells feed formulas on the other sheets)
A15: Mark | B15: Value | C15: NSR wording / basis
A16: 2030 AI capex — entering 2Q26 season | B16: 2400 | C16: $bn. “We entered the 2Q earnings season with a $2.4tn forecast for AI capex in 2030” (p.1).
A17: 2030 AI capex — after TSMC/ASML prints | B17: 3100 | C17: $bn. “before raising it to $3tn following TSMC and ASML’s earnings” (p.1); p.3 gives the prior as “~$3.1tn”.
A18: 2030 AI capex — this note | B18: 4150 | C18: $bn. p.4 total; “>$4tn … >30% above our previous ~$3.1tn estimate” (p.3).
A19: Uplift vs prior (formula) | B19: =IFERROR(B18/B17-1,"") -> 0.33870968 | C19: Recomputed; NSR says >30%.
A20: 2030 XPU spending | B20: 1702 | C20: $bn. “Nvidia at close to 60% of XPU value in 2030, implying ~$1.7tn of total XPU spending” (p.3).
A21: NVDA share of XPU value 2030 | B21: 0.6 | C21: “close to 60%” (p.3) — implied NVDA DC revenue ~$1.0tn 2030; NVDA “points to >$1tn of datacenter revenue run rate by 2028”.
A22: Implied NVDA XPU revenue 2030 (formula) | B22: =B20*B21 -> 1021.2 | C22: $bn = XPU spending × NVDA share.
A23: HBM gross margin 2030 | B23: 0.76 | C23: “we still expect HBM gross margins to normalize to ~76% by 2030” (p.3, p.5).
A24: 2030 CPU market (total) | B24: 200 | C24: $bn. “We increase our 2030 CPU forecast to ~$200bn” (p.3) — industry expectations moved from ~$60bn <1yr ago to $200bn+.
A25: 2030 CPU market (AI applications) | B25: 170 | C25: $bn. “implying close to $170bn for AI applications” (p.3). Note p.4 AI-capex CPU line prints $168bn; p.5 total CPU spending prints $202bn.
A26: Installed AI capacity 2030 | B26: 275 | C26: GW. “We now expect ~275GW of installed AI capacity in 2030, up from ~225GW previously” (p.3). BASIS NOT STATED (facility vs IT-load).
A27: Installed AI capacity 2030 — prior | B27: 225 | C27: GW (p.3).
A28: Hyperscaler deployed GW by end-decade | B28: 100 | C28: GW. “>100GW deployed by the end of the decade. ~$13bn revenues / GW” (p.7, AI cloud line) — a hyperscaler-only subset of the 275GW.
A29: AI cloud revenue per GW | B29: 13 | C29: $bn/GW/yr (p.7).
A30: Hyperscaler AI capex per GW | B30: 42.5 | C30: $bn/GW. “Mainly AI at ~$40-45bn/GW” (p.7); midpoint used here.
A31: Hyperscaler non-AI capex 2025 | B31: 125 | C31: $bn. “~$125bn of non-AI in 2025 growing ~13% p.a.” (p.7).
A32: Non-AI capex growth | B32: 0.13 | C32: p.a. (p.7).
A33: Tier-2 & neocloud revenue 2030 | B33: 2300 | C33: $bn. “growing to $2.3tn of revenue in 2030, generated on 91GW deployed, at 77% AI OCF margin” (p.6).
A34: Tier-2 & neocloud deployed GW 2030 | B34: 91 | C34: GW (p.6).
A35: Implied tier-2/neocloud revenue per GW (formula) | B35: =IFERROR(B33/B34,"") -> 25.274725 | C35: $bn/GW/yr — ~2x the $13bn/GW NSR uses for hyperscaler AI cloud on p.7. Basis fork inside the note; not reconciled by NSR.
A36: Hyperscaler revenue CAGR 2025-30 (NSR vs consensus) | B36: 0.24 | C36: NSR 24% vs consensus 17% (p.6).
A37: Hyperscaler incremental OCF margin 2030 (NSR vs consensus) | B37: 0.77 | C37: NSR 77% vs consensus 60% (p.6).

Sheet House
A1: Capstone house series — what our models say on the same lines (US$bn unless stated)
A2: All values pasted from the named Capstone file/sheet (blue). Vintage column = file save date and base. CY29-30 rows come from July-2026 workbooks built on the July AI Model (CY28 $2,588bn), NOT the current 31-Aug AI Model (CY28 $2,913bn).
A4: Line | B4: Unit | C4: 2023 | D4: 2024 | E4: 2025 | F4: 2026 | G4: 2027 | H4: 2028 | I4: 2029 | J4: 2030 | K4: Source (file → sheet → row) | L4: Vintage / basis
A5: A. AI capex — all players (AI Model ‘Resumo | Total’, $mn → $bn)
A6: Capex Total — all players (hyperscalers + ORCL/CRWV/SpaceX/labs/others) | B6: $bn | C6: 89.7 | D6: 233.9 | E6: 396.3 | F6: 901.6 | G6: 1885.4 | H6: 2913.1 | K6: AI Model.xlsx (Modelos oficiais, saved 2026-08-31) → Resumo | Total → ‘Capex Total’ | L6: 2026-08-31 — CURRENT official model; CY23-28 only
A7: o/w Chips (GPU/XPU incl. HBM inside) = designers’ chip revenue | B7: $bn | C7: 42.4 | D7: 114.8 | E7: 190.2 | F7: 399.9 | G7: 767 | H7: 1157.4 | K7: AI Model.xlsx (Modelos oficiais, saved 2026-08-31) → ‘Capex | Chips’ | L7: 2026-08-31 — CURRENT official model; CY23-28 only
A8: o/w Networking + CPU + server memory/storage | B8: $bn | C8: 12.8 | D8: 34.4 | E8: 65.3 | F8: 178.6 | G8: 435.1 | H8: 715.1 | K8: AI Model.xlsx (Modelos oficiais, saved 2026-08-31) → ‘Capex | Networking + CPU +..’ | L8: 2026-08-31 — CURRENT official model; CY23-28 only
A9: o/w Other (shell, power, land, site) | B9: $bn | C9: 34.5 | D9: 84.6 | E9: 140.8 | F9: 323.1 | G9: 683.3 | H9: 1040.6 | K9: AI Model.xlsx (Modelos oficiais, saved 2026-08-31) → ‘Capex | Other’ | L9: 2026-08-31 — CURRENT official model; CY23-28 only
A10: Check: components − total | B10: $bn | C10: =C7+C8+C9-C6 -> 0 | D10: =D7+D8+D9-D6 -> -0.1 | E10: =E7+E8+E9-E6 -> 0 | F10: =F7+F8+F9-F6 -> 0 | G10: =G7+G8+G9-G6 -> 0 | H10: =H7+H8+H9-H6 -> 0
A11: Capex Total — y/y | B11: % y/y | D11: =IF(OR(D6="",C6=""),"",IFERROR(D6/C6-1,"")) -> 1.6075808 | E11: =IF(OR(E6="",D6=""),"",IFERROR(E6/D6-1,"")) -> 0.69431381 | F11: =IF(OR(F6="",E6=""),"",IFERROR(F6/E6-1,"")) -> 1.2750442 | G11: =IF(OR(G6="",F6=""),"",IFERROR(G6/F6-1,"")) -> 1.0911713 | H11: =IF(OR(H6="",G6=""),"",IFERROR(H6/G6-1,"")) -> 0.54508327 | I11: =IF(OR(I6="",H6=""),"",IFERROR(I6/H6-1,"")) | J11: =IF(OR(J6="",I6=""),"",IFERROR(J6/I6-1,""))
A12: Chips — % of capex | B12: % | C12: =IF(OR(C7="",C6=""),"",IFERROR(C7/C6,"")) -> 0.47268673 | D12: =IF(OR(D7="",D6=""),"",IFERROR(D7/D6,"")) -> 0.49080804 | E12: =IF(OR(E7="",E6=""),"",IFERROR(E7/E6,"")) -> 0.47993944 | F12: =IF(OR(F7="",F6=""),"",IFERROR(F7/F6,"")) -> 0.44354481 | G12: =IF(OR(G7="",G6=""),"",IFERROR(G7/G6,"")) -> 0.40681023 | H12: =IF(OR(H7="",H6=""),"",IFERROR(H7/H6,"")) -> 0.39730871 | I12: =IF(OR(I7="",I6=""),"",IFERROR(I7/I6,"")) | J12: =IF(OR(J7="",J6=""),"",IFERROR(J7/J6,""))
A13: Networking+CPU+memory/storage — % of capex | B13: % | C13: =IF(OR(C8="",C6=""),"",IFERROR(C8/C6,"")) -> 0.14269788 | D13: =IF(OR(D8="",D6=""),"",IFERROR(D8/D6,"")) -> 0.1470714 | E13: =IF(OR(E8="",E6=""),"",IFERROR(E8/E6,"")) -> 0.16477416 | F13: =IF(OR(F8="",F6=""),"",IFERROR(F8/F6,"")) -> 0.19809228 | G13: =IF(OR(G8="",G6=""),"",IFERROR(G8/G6,"")) -> 0.23077331 | H13: =IF(OR(H8="",H6=""),"",IFERROR(H8/H6,"")) -> 0.24547733 | I13: =IF(OR(I8="",I6=""),"",IFERROR(I8/I6,"")) | J13: =IF(OR(J8="",J6=""),"",IFERROR(J8/J6,""))
A14: Other (shell/power/site) — % of capex | B14: % | C14: =IF(OR(C9="",C6=""),"",IFERROR(C9/C6,"")) -> 0.38461538 | D14: =IF(OR(D9="",D6=""),"",IFERROR(D9/D6,"")) -> 0.36169303 | E14: =IF(OR(E9="",E6=""),"",IFERROR(E9/E6,"")) -> 0.3552864 | F14: =IF(OR(F9="",F6=""),"",IFERROR(F9/F6,"")) -> 0.35836291 | G14: =IF(OR(G9="",G6=""),"",IFERROR(G9/G6,"")) -> 0.36241646 | H14: =IF(OR(H9="",H6=""),"",IFERROR(H9/H6,"")) -> 0.35721396 | I14: =IF(OR(I9="",I6=""),"",IFERROR(I9/I6,"")) | J14: =IF(OR(J9="",J6=""),"",IFERROR(J9/J6,""))
A15: Capex Hyperscalers AI — bottom-up (MSFT+AMZN+GOOG+META) | B15: $bn | C15: 93.8 | D15: 178.8 | E15: 336.4 | F15: 681.9 | G15: 1125.5 | H15: 1425.1 | K15: AI Model.xlsx (Modelos oficiais, saved 2026-08-31) → ‘Capex Hyperscalers AI | Bottom-Up’ | L15: 2026-08-31 — CURRENT official model; CY23-28 only
A16: MSFT (AI, bottom-up) | B16: $bn | C16: 22.6 | D16: 50.7 | E16: 95.9 | F16: 170.2 | G16: 272 | H16: 322 | K16: AI Model.xlsx (Modelos oficiais, saved 2026-08-31) | L16: 2026-08-31 — CURRENT official model; CY23-28 only
A17: AMZN / AWS (AI, bottom-up) | B17: $bn | C17: 24.7 | D17: 53 | E17: 96.5 | F17: 175 | G17: 286.3 | H17: 378.7 | K17: AI Model.xlsx (Modelos oficiais, saved 2026-08-31) | L17: 2026-08-31 — CURRENT official model; CY23-28 only
A18: GOOG (AI, bottom-up) | B18: $bn | C18: 19.4 | D18: 37.8 | E18: 74.3 | F18: 195.2 | G18: 361.1 | H18: 463 | K18: AI Model.xlsx (Modelos oficiais, saved 2026-08-31) | L18: 2026-08-31 — CURRENT official model; CY23-28 only
A19: META (AI, bottom-up) | B19: $bn | C19: 27 | D19: 37.3 | E19: 69.7 | F19: 141.4 | G19: 206.1 | H19: 261.5 | K19: AI Model.xlsx (Modelos oficiais, saved 2026-08-31) | L19: 2026-08-31 — CURRENT official model; CY23-28 only
A20: Capex Hyperscalers TOTAL — official company models (AI + non-AI) | B20: $bn | C20: 155.8 | D20: 244.7 | E20: 410.1 | F20: 738.9 | G20: 1097.8 | H20: 1425.1 | K20: AI Model.xlsx (Modelos oficiais, saved 2026-08-31) → ‘Capex Hyperscalers | Modelos Capstone’ (MSFT 117/191/258/322; AMZN 132/214/330/379; GOOG 91/183/310/463; META 70/151/200/261 for CY25-28) | L20: 2026-08-31 — CURRENT official model; CY23-28 only; CY28 AI = total by construction
A21: Capex Other Players — bottom-up (ORCL, CRWV, SpaceX, OpenAI, Anthropic, others) | B21: $bn | C21: -4 | D21: 55.1 | E21: 59.8 | F21: 219.7 | G21: 759.9 | H21: 1488 | K21: AI Model.xlsx (Modelos oficiais, saved 2026-08-31) → ‘Capex Outros Players | Bottom-Up’ (ORCL 31.7/65.3/119.5/198.0; CRWV 26.0/44.3/111.9/198.0; SpaceX 13.7/59.7/260.6/253.8; OpenAI 0/0/56.7/94.9; Anthropic 0/0/97.4/410.3; others -11.5/50.5/113.9/333.0 for CY25-28) | L21: 2026-08-31 — CURRENT official model; CY23-28 only
A22: Other players — % of all-player AI capex | B22: % | C22: =IF(OR(C21="",C6=""),"",IFERROR(C21/C6,"")) -> -0.044593088 | D22: =IF(OR(D21="",D6=""),"",IFERROR(D21/D6,"")) -> 0.23557076 | E22: =IF(OR(E21="",E6=""),"",IFERROR(E21/E6,"")) -> 0.15089579 | F22: =IF(OR(F21="",F6=""),"",IFERROR(F21/F6,"")) -> 0.24367791 | G22: =IF(OR(G21="",G6=""),"",IFERROR(G21/G6,"")) -> 0.40304445 | H22: =IF(OR(H21="",H6=""),"",IFERROR(H21/H6,"")) -> 0.51079606 | I22: =IF(OR(I21="",I6=""),"",IFERROR(I21/I6,"")) | J22: =IF(OR(J21="",J6=""),"",IFERROR(J21/J6,""))
A23: Cumulative all-player capex 2026-28 (in 2028 column) | B23: $bn | H23: =SUM(F6:H6) -> 5700.1
A24: Memo: AI Model ‘Implicito’ CY29-30 cumulative against an $11tn 2024-30 anchor (in 2030 column) | B24: $bn | J24: 4669.8 | K24: AI Model.xlsx (Modelos oficiais, saved 2026-08-31) → Resumo | Total row 8: ‘CAPEX 24-28 Acumulado 6,330 | CAPEX 29-30 Implicito 4,670 | CAPEX 24-30 SA 11,000’ | L24: Scratch cell in the model — implies CY29-30 average ~$2.3tn/yr, BELOW CY28; the cell header reads ‘uma coisa me incomoda: cagr de capacidade’. Not a forecast.
A25: Memo: AI Model scratch CY29E (= CY28 × 1.70) — NOT a modeled year | B25: $bn | I25: 4952.3 | K25: AI Model.xlsx (Modelos oficiais, saved 2026-08-31) → Resumo | Total ‘Capstone Est’ block (row ~282) | L25: placeholder growth 70%; excluded from Comparison
A27: B. Semis MAP v11 — scenario capex path and component TAMs (July-2026 vintage; CY29-30 = extension)
A28: Capstone base capex (= July AI Model Capex Total) — scenario driver | B28: $bn | C28: 85 | D28: 228.5 | E28: 431.7 | F28: 899.6 | G28: 1679.8 | H28: 2588.4 | I28: 3054.3 | J28: 3481.9 | K28: AI_Chip_Designers_TAM_v11.xlsx (Semis MAP, 2026-07-16) → Scenario | Drivers row 3 | L28: 2026-07-16 — on July AI Model base (CY28 2,588); CY29-35 are scenario extensions; extension growth CY29 +18% / CY30 +14%
A29: Alt path: JPM ‘AI Capex 2.0’ | B29: $bn | C29: 85 | D29: 228.5 | E29: 431.7 | F29: 751.2 | G29: 1164.3 | H29: 1513.6 | I29: 1786 | J29: 2036.1 | K29: AI_Chip_Designers_TAM_v11.xlsx (Semis MAP, 2026-07-16) → Scenario | Drivers row 4 | L29: JPM Sur 2026-06-16; CY29+ extended by the map
A30: Alt path: Street five-name consensus | B30: $bn | C30: 85 | D30: 228.5 | E30: 431.7 | F30: 699.4 | G30: 902.2 | H30: 1037.5 | I30: 1224.2 | J30: 1395.6 | K30: AI_Chip_Designers_TAM_v11.xlsx (Semis MAP, 2026-07-16) → Scenario | Drivers row 5 | L30: BBG five-name (MSFT/AMZN/GOOGL/META/ORCL), June-2026 vintage
A31: AI chip revenue — designers (= accelerators, HBM inside) | B31: $bn | C31: 40.5 | D31: 109.5 | E31: 200.2 | F31: 399.9 | G31: 692 | H31: 1051.3 | I31: 1240.6 | J31: 1414.2 | K31: AI_Chip_Designers_TAM_v11.xlsx (Semis MAP, 2026-07-16) → Designers TAM row 2 | L31: 2026-07-16 — on July AI Model base (CY28 2,588); CY29-35 are scenario extensions
A32: NVDA | B32: $bn | C32: 36.6 | D32: 97.1 | E32: 168.8 | F32: 311.8 | G32: 503.6 | H32: 677.9 | I32: 795.3 | J32: 900 | K32: AI_Chip_Designers_TAM_v11.xlsx (Semis MAP, 2026-07-16) → Designers TAM | L32: 2026-07-16 — on July AI Model base (CY28 2,588); CY29-35 are scenario extensions
A33: AMD | B33: $bn | C33: 0.5 | D33: 5.4 | E33: 8 | F33: 20.7 | G33: 38.4 | H33: 51.8 | I33: 60.7 | J33: 68.7 | K33: AI_Chip_Designers_TAM_v11.xlsx (Semis MAP, 2026-07-16) | L33: 2026-07-16 — on July AI Model base (CY28 2,588); CY29-35 are scenario extensions
A34: Custom ASICs (AVGO + MRVL + MediaTek + Alchip) | B34: $bn | C34: 3.4 | D34: 6.9 | E34: 23.4 | F34: 67.4 | G34: 150 | H34: 321.7 | I34: 384.6 | J34: 445.5 | K34: AI_Chip_Designers_TAM_v11.xlsx (Semis MAP, 2026-07-16) | L34: 2026-07-16 — on July AI Model base (CY28 2,588); CY29-35 are scenario extensions
A35: NVDA share of accelerator value | B35: % | C35: =IF(OR(C32="",C31=""),"",IFERROR(C32/C31,"")) -> 0.9037037 | D35: =IF(OR(D32="",D31=""),"",IFERROR(D32/D31,"")) -> 0.88675799 | E35: =IF(OR(E32="",E31=""),"",IFERROR(E32/E31,"")) -> 0.84315684 | F35: =IF(OR(F32="",F31=""),"",IFERROR(F32/F31,"")) -> 0.77969492 | G35: =IF(OR(G32="",G31=""),"",IFERROR(G32/G31,"")) -> 0.72774566 | H35: =IF(OR(H32="",H31=""),"",IFERROR(H32/H31,"")) -> 0.6448207 | I35: =IF(OR(I32="",I31=""),"",IFERROR(I32/I31,"")) -> 0.64106078 | J35: =IF(OR(J32="",J31=""),"",IFERROR(J32/J31,"")) -> 0.63640221
A36: Custom ASIC share of accelerator value | B36: % | C36: =IF(OR(C34="",C31=""),"",IFERROR(C34/C31,"")) -> 0.083950617 | D36: =IF(OR(D34="",D31=""),"",IFERROR(D34/D31,"")) -> 0.063013699 | E36: =IF(OR(E34="",E31=""),"",IFERROR(E34/E31,"")) -> 0.11688312 | F36: =IF(OR(F34="",F31=""),"",IFERROR(F34/F31,"")) -> 0.16854214 | G36: =IF(OR(G34="",G31=""),"",IFERROR(G34/G31,"")) -> 0.21676301 | H36: =IF(OR(H34="",H31=""),"",IFERROR(H34/H31,"")) -> 0.30600209 | I36: =IF(OR(I34="",I31=""),"",IFERROR(I34/I31,"")) -> 0.31001128 | J36: =IF(OR(J34="",J31=""),"",IFERROR(J34/J31,"")) -> 0.31501909
A37: AI DC systems TAM — BofA mix applied to Capstone capex | B37: $bn | C37: 65 | D37: 166.4 | E37: 310.8 | F37: 673.5 | G37: 1201.2 | H37: 1837.5 | I37: 2168.2 | J37: 2471.8 | K37: AI_Chip_Designers_TAM_v11.xlsx (Semis MAP, 2026-07-16) → AI DC TAM (BofA mix) row 5 | L37: 2026-07-16 — on July AI Model base (CY28 2,588); CY29-35 are scenario extensions; systems only (ex-shell/power)
A38: AI CPUs (BofA-mix line; Build | CPU calibrated TAM = 9.3/24.6/48.4/77.8/91.8/104.7 CY25-30) | B38: $bn | C38: 2.8 | D38: 5.7 | E38: 15.2 | F38: 40.2 | G38: 79.2 | H38: 127.2 | I38: 150.1 | J38: 171.1 | K38: AI_Chip_Designers_TAM_v11.xlsx (Semis MAP, 2026-07-16) → AI DC TAM (BofA mix) ‘AI CPUs’; Build | CPU row 3 is the capture-calibrated version | L38: 2026-07-16 — on July AI Model base (CY28 2,588); CY29-35 are scenario extensions; head-node CPUs inside AI servers
A39: HBM — BofA-mix line (uncalibrated; memo inside accelerators) | B39: $bn | C39: 5.6 | D39: 24.8 | E39: 56.4 | F39: 126.1 | G39: 204.7 | H39: 261.6 | I39: 308.7 | J39: 351.9 | K39: AI_Chip_Designers_TAM_v11.xlsx (Semis MAP, 2026-07-16) → AI DC TAM (BofA mix) ‘HBM (memo)’ | L39: 2026-07-16 — on July AI Model base (CY28 2,588); CY29-35 are scenario extensions
A40: HBM — Build | HBM calibrated TAM (capture 0.621 to canonical $35bn CY25) | B40: $bn | C40: 3.5 | D40: 15.4 | E40: 35 | F40: 78.3 | G40: 127 | H40: 162.4 | I40: 191.6 | J40: 218.4 | K40: AI_Chip_Designers_TAM_v11.xlsx (Semis MAP, 2026-07-16) → Build | HBM row 3 | L40: 2026-07-16 — on July AI Model base (CY28 2,588); CY29-35 are scenario extensions; SK Hynix 47% / Samsung 28% / Micron 25% by CY28
A41: HBM — repriced (industry bits 2/4.3/6.25/8/9.6/11.2 EB × $17.5/18/31/28/26.6/25.3 per GB) | B41: $bn | C41: 5.2 | D41: 16.5 | E41: 35 | F41: 77.4 | G41: 193.8 | H41: 224 | I41: 255.4 | J41: 283.4 | K41: AI_Chip_Designers_TAM_v11.xlsx (Semis MAP, 2026-07-16) → Build | Memory (total) row 15 | L41: 2026-07-16 — on July AI Model base (CY28 2,588); CY29-35 are scenario extensions; $31/GB CY27 kept vs wiki $22.75 fork (F14 comment)
A42: Fleet DDR5 (hyperscaler general + DB servers) = bits × realized $/GB | B42: $bn | C42: 12 | D42: 14.8 | E42: 19.5 | F42: 91.3 | G42: 134.4 | H42: 141.8 | I42: 148.2 | J42: 164.9 | K42: AI_Chip_Designers_TAM_v11.xlsx (Semis MAP, 2026-07-16) → Build | Memory (total) row 61 | L42: 2026-07-16 — on July AI Model base (CY28 2,588); CY29-35 are scenario extensions; $/GB 3.2 → 11 → 14 → 13.5 CY25-28
A43: DC NAND total (BofA chain) | B43: $bn | C43: 12 | D43: 16 | E43: 22.8 | F43: 119.7 | G43: 182.4 | H43: 204 | I43: 222 | J43: 240 | K43: AI_Chip_Designers_TAM_v11.xlsx (Semis MAP, 2026-07-16) → Build | Memory (total) row 62 | L43: 2026-07-16 — on July AI Model base (CY28 2,588); CY29-35 are scenario extensions
A44: Nearline HDD (CSP share) | B44: $bn | C44: 10.1 | D44: 11.9 | E44: 16.8 | F44: 24.5 | G44: 40.2 | H44: 64.3 | I44: 75.7 | J44: 87.8 | K44: AI_Chip_Designers_TAM_v11.xlsx (Semis MAP, 2026-07-16) → Build | Memory (total) row 65 | L44: 2026-07-16 — on July AI Model base (CY28 2,588); CY29-35 are scenario extensions
A45: DRAM ex-HBM + NAND (formula = fleet DDR5 + DC NAND) — closest to NSR ‘DRAM & NAND’ | B45: $bn | C45: =C42+C43 -> 24 | D45: =D42+D43 -> 30.8 | E45: =E42+E43 -> 42.3 | F45: =F42+F43 -> 211 | G45: =G42+G43 -> 316.8 | H45: =H42+H43 -> 345.8 | I45: =I42+I43 -> 370.2 | J45: =J42+J43 -> 404.9 | K45: formula on the two rows above | L45: excludes head-node DRAM (26-34) and the memory slice of ‘other’ (10-35); excludes HDD
A46: TOTAL CSP memory bill (mapped + repricing + fleet DDR5/NAND/HDD) | B46: $bn | C46: 17 | D46: 43.2 | E46: 90.4 | F46: 272.4 | G46: 496 | H46: 596.5 | I46: 667 | J46: 737 | K46: AI_Chip_Designers_TAM_v11.xlsx (Semis MAP, 2026-07-16) → Build | Memory (total) row 24 | L46: 2026-07-16 — on July AI Model base (CY28 2,588); CY29-35 are scenario extensions; = 39% / 55% of STREET capex CY26/27
A47: AI Networking (switching + SmartNIC + optical + copper) | B47: $bn | C47: 14.1 | D47: 30.7 | E47: 56.6 | F47: 156.5 | G47: 292.6 | H47: 450.7 | I47: 531.9 | J47: 606.3 | K47: AI_Chip_Designers_TAM_v11.xlsx (Semis MAP, 2026-07-16) → AI DC TAM (BofA mix) ‘AI Networking’ | L47: 2026-07-16 — on July AI Model base (CY28 2,588); CY29-35 are scenario extensions; BofA ratio × house accelerators
A48: o/w Optical | B48: $bn | C48: 4.6 | D48: 12.3 | E48: 25 | F48: 58.8 | G48: 96.1 | H48: 135.3 | I48: 159.6 | J48: 182 | K48: AI_Chip_Designers_TAM_v11.xlsx (Semis MAP, 2026-07-16) | L48: 2026-07-16 — on July AI Model base (CY28 2,588); CY29-35 are scenario extensions
A49: AI Storage | B49: $bn | C49: 4.3 | D49: 11.7 | E49: 22.1 | F49: 44.8 | G49: 79.9 | H49: 123.3 | I49: 145.5 | J49: 165.9 | K49: AI_Chip_Designers_TAM_v11.xlsx (Semis MAP, 2026-07-16) | L49: 2026-07-16 — on July AI Model base (CY28 2,588); CY29-35 are scenario extensions
A50: Implied compute GW added per year (chip $ / $-per-GW capture) | B50: GW | C50: 2.2 | D50: 5.9 | E50: 11.2 | F50: 22.7 | G50: 40 | H50: 62.7 | I50: 72.6 | J50: 81.3 | K50: AI_Chip_Designers_TAM_v11.xlsx (Semis MAP, 2026-07-16) → AI DC TAM (BofA mix) row 28 | L50: 2026-07-16 — on July AI Model base (CY28 2,588); CY29-35 are scenario extensions; CHIP-CONTENT GW (NVDA $19.5-23.5bn/GW, ASIC $11.5bn/GW), gross of retirements
A51: Cumulative compute GW since CY23 (gross, no retirements) | B51: GW | C51: 2.2 | D51: 8.1 | E51: 19.3 | F51: 42.1 | G51: 82.1 | H51: 144.8 | I51: 217.4 | J51: 298.7 | K51: AI_Chip_Designers_TAM_v11.xlsx (Semis MAP, 2026-07-16) → AI DC TAM (BofA mix) row 37 | L51: 2026-07-16 — on July AI Model base (CY28 2,588); CY29-35 are scenario extensions; chip-content basis — NOT facility, NOT IT-load
A53: C. Bottom_Up_Capex_v3 — physical bottom-up (units × ASP; all-buyer; July-2026 vintage)
A54: Capex implied bottom-up (sum of physical lines) | B54: $bn | C54: 166.3 | D54: 314.6 | E54: 528 | F54: 1181.7 | G54: 2015.1 | H54: 2764.5 | I54: 3326.4 | J54: 3924.1 | K54: Bottom_Up_Capex_v3.xlsx (Semis MAP, 2026-07-24) → Resumo | Bottom-up Capex row 10 | L54: 2026-07-24 — physical bottom-up; CY29-30 extension; skeptic-audited PARTIAL; runs 1.2-1.3x the AI Model — the sheet's own note: ‘CY27 $1.9T = bull assumptions stacked’
A55: Accelerators (units × ASP; HBM + LPDDR inside) | B55: $bn | C55: 40.5 | D55: 109.5 | E55: 200.2 | F55: 399.9 | G55: 713.3 | H55: 1017 | I55: 1184.8 | J55: 1344.6 | K55: Bottom_Up_Capex_v3.xlsx (Semis MAP, 2026-07-24) row 3 | L55: 2026-07-24 — physical bottom-up; CY29-30 extension; skeptic-audited PARTIAL
A56: CPUs + general-purpose servers (ex-memory) | B56: $bn | C56: 26.8 | D56: 36.2 | E56: 50.9 | F56: 79 | G56: 120.1 | H56: 176.8 | I56: 212.9 | J56: 263.8 | K56: Bottom_Up_Capex_v3.xlsx (Semis MAP, 2026-07-24) row 4 | L56: 2026-07-24 — physical bottom-up; CY29-30 extension; skeptic-audited PARTIAL; broader than head-node AI CPUs
A57: Memory bought direct (DDR5 + DC NAND + …) | B57: $bn | C57: 28.2 | D57: 38.2 | E57: 75.7 | F57: 301.3 | G57: 495.7 | H57: 628.1 | I57: 751.8 | J57: 892.2 | K57: Bottom_Up_Capex_v3.xlsx (Semis MAP, 2026-07-24) row 5 | L57: 2026-07-24 — physical bottom-up; CY29-30 extension; skeptic-audited PARTIAL
A58: Networking (optical + switching + SmartNIC + copper) | B58: $bn | C58: 18.8 | D58: 36.3 | E58: 55.8 | F58: 101.4 | G58: 158 | H58: 217.1 | I58: 266.5 | J58: 305.8 | K58: Bottom_Up_Capex_v3.xlsx (Semis MAP, 2026-07-24) row 6 | L58: 2026-07-24 — physical bottom-up; CY29-30 extension; skeptic-audited PARTIAL
A59: Infra: P&C equipment + storage | B59: $bn | C59: 24.2 | D59: 33.9 | E59: 44 | F59: 65.5 | G59: 98 | H59: 139 | I59: 165.7 | J59: 190.4 | K59: Bottom_Up_Capex_v3.xlsx (Semis MAP, 2026-07-24) row 7 | L59: 2026-07-24 — physical bottom-up; CY29-30 extension; skeptic-audited PARTIAL
A60: Non-IT: shell + energy + E&C (physical GW × $/GW) | B60: $bn | C60: 27.8 | D60: 60.5 | E60: 101.5 | F60: 234.6 | G60: 430 | H60: 586.5 | I60: 744.7 | J60: 927.2 | K60: Bottom_Up_Capex_v3.xlsx (Semis MAP, 2026-07-24) row 8 | L60: 2026-07-24 — physical bottom-up; CY29-30 extension; skeptic-audited PARTIAL
A61: Memo: memory TOTAL supplier-side (incl. HBM + LPDDR inside accelerators) | B61: $bn | C61: 34.1 | D61: 56.9 | E61: 118.3 | F61: 404.9 | G61: 791.1 | H61: 966 | I61: 1150.3 | J61: 1354.9 | K61: Bottom_Up_Capex_v3.xlsx (Semis MAP, 2026-07-24) row 23 | L61: 2026-07-24 — physical bottom-up; CY29-30 extension; skeptic-audited PARTIAL; = 22% → 39% → 35% of implied capex CY25-27
A62: Facility GW added per year (physical: units × kW × PUE) | B62: GW | C62: 4.3 | D62: 8.1 | E62: 11.3 | F62: 20.8 | G62: 35.6 | H62: 45.3 | I62: 53.8 | J62: 62.6 | K62: Bottom_Up_Capex_v3.xlsx (Semis MAP, 2026-07-24) row 26/40 | L62: 2026-07-24 — physical bottom-up; CY29-30 extension; skeptic-audited PARTIAL; FACILITY basis
A63: Cumulative facility GW since CY23 | B63: GW | C63: 4.3 | D63: 12.3 | E63: 23.6 | F63: 44.4 | G63: 79.9 | H63: 125.3 | I63: 179.1 | J63: 241.7 | K63: Bottom_Up_Capex_v3.xlsx (Semis MAP, 2026-07-24) row 43 | L63: 2026-07-24 — physical bottom-up; CY29-30 extension; skeptic-audited PARTIAL; FACILITY basis; check vs BofA 233 GW CY30 = 1.04x
A64: Effective $/GW of the system (= implied capex / facility GW added) | B64: $bn/GW | C64: 38.9 | D64: 39 | E64: 46.8 | F64: 56.9 | G64: 56.7 | H64: 61 | I64: 61.8 | J64: 62.7 | K64: Bottom_Up_Capex_v3.xlsx (Semis MAP, 2026-07-24) row 29 | L64: 2026-07-24 — physical bottom-up; CY29-30 extension; skeptic-audited PARTIAL
A66: D. AI Model — designers, GW stocks and unit economics (31-Aug-2026)
A67: NVDA chip revenue (AI Model designers) | B67: $bn | C67: 38.5 | D67: 102.5 | E67: 158.8 | F67: 311.8 | G67: 578.6 | H67: 784 | K67: AI Model.xlsx (Modelos oficiais, saved 2026-08-31) → Resumo | Designers ‘Receita’ | L67: 2026-08-31 — CURRENT official model; CY23-28 only
A68: AVGO chip revenue (Google TPU + Meta MTIA + OpenAI) | B68: $bn | C68: 2.9 | D68: 5.5 | E68: 20.1 | F68: 60.4 | G68: 125.5 | H68: 284.6 | K68: AI Model.xlsx (Modelos oficiais, saved 2026-08-31) | L68: 2026-08-31 — CURRENT official model; CY23-28 only
A69: Custom ASICs total (AVGO + MRVL + MSFT + MTK + Alchip) | B69: $bn | C69: 3.4 | D69: 6.9 | E69: 23.4 | F69: 67.4 | G69: 150 | H69: 321.7 | K69: AI Model.xlsx (Modelos oficiais, saved 2026-08-31) → ‘By client | ASICs’ | L69: 2026-08-31 — CURRENT official model; CY23-28 only
A70: NVDA share of chip capex | B70: % | C70: =IF(OR(C67="",C7=""),"",IFERROR(C67/C7,"")) -> 0.90801887 | D70: =IF(OR(D67="",D7=""),"",IFERROR(D67/D7,"")) -> 0.89285714 | E70: =IF(OR(E67="",E7=""),"",IFERROR(E67/E7,"")) -> 0.83491062 | F70: =IF(OR(F67="",F7=""),"",IFERROR(F67/F7,"")) -> 0.77969492 | G70: =IF(OR(G67="",G7=""),"",IFERROR(G67/G7,"")) -> 0.75436767 | H70: =IF(OR(H67="",H7=""),"",IFERROR(H67/H7,"")) -> 0.67738034 | I70: =IF(OR(I67="",I7=""),"",IFERROR(I67/I7,"")) | J70: =IF(OR(J67="",J7=""),"",IFERROR(J67/J7,""))
A71: Accelerator units sold | B71: k units | C71: 5595.3 | D71: 9819.4 | E71: 10126.3 | F71: 15449.2 | G71: 22385 | H71: 23700 | K71: AI Model.xlsx (Modelos oficiais, saved 2026-08-31) → Resumo | Total ‘# Chips’ | L71: 2026-08-31 — CURRENT official model; CY23-28 only; NVDA 5.2M/7.6M/8.7M/5.25M CY25-28
A72: AI GW sold per year (designers) | B72: GW | C72: 3.3 | D72: 7.8 | E72: 12.9 | F72: 27.1 | G72: 50.7 | H72: 69.5 | K72: AI Model.xlsx (Modelos oficiais, saved 2026-08-31) → Resumo | Designers ‘GW de AI vendidos’ (NVDA 8.7/16.6/27.0/30.8; AVGO 2.3/6.7/13.1/20.7 CY25-28) | L72: 2026-08-31 — CURRENT official model; CY23-28 only; chip-content GW shipped
A73: AI GW stock, end of period — PURCHASE basis (cumulative chips bought) | B73: GW | C73: 3.3 | D73: 11.1 | E73: 24.1 | F73: 51.2 | G73: 101.9 | H73: 171.4 | K73: AI Model.xlsx (Modelos oficiais, saved 2026-08-31) → Resumo | Total ‘Estoque GW AI, EOP’ (ótica da compra) | L73: 2026-08-31 — CURRENT official model; CY23-28 only; MSFT 24.5 / AMZN 28.6 / GOOG 34.0 / META 20.6 / ORCL 10.2 / CRWV 9.2 / SpaceX 13 / Anthropic 14 / OpenAI 4.7 / others 12.9 in CY28
A74: AI GW stock, end of period — ONLINE-capacity basis | B74: GW | C74: 0.8 | D74: 5.2 | E74: 14.3 | F74: 30.7 | G74: 63.7 | H74: 119.1 | K74: AI Model.xlsx (Modelos oficiais, saved 2026-08-31) → Resumo | Total ‘Estoque GW AI, EOP’ (ótica da capacidade online) | L74: 2026-08-31 — CURRENT official model; CY23-28 only; lags purchase by ~1 year of deliveries
A75: AI GW stock, average online (drives implied AI revenue) | B75: GW | C75: 0.8 | D75: 3 | E75: 9.8 | F75: 22.5 | G75: 47.2 | H75: 91.4 | K75: AI Model.xlsx (Modelos oficiais, saved 2026-08-31) → ‘Estoque GW AI, AVG’ | L75: 2026-08-31 — CURRENT official model; CY23-28 only
A76: Implied AI revenue (avg online GW × revenue/GW; big-4 + others, incl. internal use) | B76: $bn | C76: 2.8 | D76: 38.7 | E76: 125 | F76: 305.7 | G76: 684.7 | H76: 1183 | K76: AI Model.xlsx (Modelos oficiais, saved 2026-08-31) → Resumo | Total ‘Receita AI Implícita’ | L76: 2026-08-31 — CURRENT official model; CY23-28 only; NOT cloud revenue — includes META internal and ads/copilot value; do not compare to NSR AI cloud
A77: Payback (years) — big-4 blended | B77: yrs | D77: 4.6 | E77: 2.7 | F77: 2.2 | G77: 1.6 | H77: 1.2 | K77: AI Model.xlsx (Modelos oficiais, saved 2026-08-31) → ‘Payback’ | L77: 2026-08-31 — CURRENT official model; CY23-28 only
A78: Capex per GW — NVDA-based build (chip 25.5 + networking/ST 10.3 + other 15.0), CY28E | B78: $bn/GW | H78: 50.8 | K78: AI Model.xlsx (Modelos oficiais, saved 2026-08-31) → Resumo | Economics GW (Ano = CY28E) | L78: 2026-08-31 — CURRENT official model; CY23-28 only; Google 40.1 / Meta 38.8 / OpenAI 33.2 / MSFT 30.3 / Trainium 27.9 $bn/GW
A79: Capex per GW — blended house build cost per GW added | B79: $bn/GW | E79: 30.5 | F79: 34 | G79: 38 | H79: 41.9 | K79: ai-capex-funding.html / ai-capex-sankey.html PGW array (from AI Model economics_1gw, 2026-08-17) | L79: 2026-08-17; blended across designers
A80: Revenue per GW — NVDA-based deployment | B80: $bn/GW/yr | H80: 20 | K80: AI Model.xlsx (Modelos oficiais, saved 2026-08-31) → Economics GW ‘Receita/GW’ (NVDA 20; Google/MTK 14; Meta/OpenAI/MSFT/AMD 10.5; Trainium/Alchip 7) | L80: 2026-08-31 — CURRENT official model; CY23-28 only; MS 1GW block: GB300 $20bn, GB200 $17.5bn, H100 $16bn, TPU $15bn, Trainium $6bn
A81: Revenue per GW — implied blended (= implied AI revenue / avg online GW) | B81: $bn/GW/yr | C81: =IFERROR(C76/C75,"") -> 3.5 | D81: =IFERROR(D76/D75,"") -> 12.9 | E81: =IFERROR(E76/E75,"") -> 12.755102 | F81: =IFERROR(F76/F75,"") -> 13.586667 | G81: =IFERROR(G76/G75,"") -> 14.506356 | H81: =IFERROR(H76/H75,"") -> 12.943107 | K81: formula on the two rows above | L81: blend of designers at model utilisation
A83: E. AI Model — HBM Model (bottom-up: units × GB/chip × $/GB; $17 HBM3E / $26 HBM4 / $29 HBM4E)
A84: HBM shipped | B84: mn GB | C84: 286.5 | D84: 784.4 | E84: 1627.5 | F84: 3547.4 | G84: 5947.6 | H84: 10756.4 | K84: AI Model.xlsx (Modelos oficiais, saved 2026-08-31) → HBM Model Section 2 ‘Total’ (CY cols) | L84: 2026-08-31 — CURRENT official model; CY23-28 only
A85: HBM revenue implied by the accelerator unit plan | B85: $bn | C85: 3.3 | D85: 11.4 | E85: 27 | F85: 63.7 | G85: 127.8 | H85: 281.5 | K85: AI Model.xlsx (Modelos oficiais, saved 2026-08-31) → HBM Model Section 3 ‘Total’ ($mn → $bn) | L85: 2026-08-31 — CURRENT official model; CY23-28 only; CY28 jump = HBM4E 1TB parts (VR300/MI500X) at $29/GB
A86: Implied blended HBM $/GB (formula) | B86: $/GB | C86: =IFERROR(C85*1000/C84,"") -> 11.518325 | D86: =IFERROR(D85*1000/D84,"") -> 14.533401 | E86: =IFERROR(E85*1000/E84,"") -> 16.589862 | F86: =IFERROR(F85*1000/F84,"") -> 17.956813 | G86: =IFERROR(G85*1000/G84,"") -> 21.487659 | H86: =IFERROR(H85*1000/H84,"") -> 26.170466 | K86: formula | L86: static spec-sheet $/GB, no 2027 repricing — hence below the Semis MAP repriced line in CY27
A87: HBM as % of chip capex (AI Model, both bottom-up) | B87: % | C87: =IF(OR(C85="",C7=""),"",IFERROR(C85/C7,"")) -> 0.077830189 | D87: =IF(OR(D85="",D7=""),"",IFERROR(D85/D7,"")) -> 0.099303136 | E87: =IF(OR(E85="",E7=""),"",IFERROR(E85/E7,"")) -> 0.14195584 | F87: =IF(OR(F85="",F7=""),"",IFERROR(F85/F7,"")) -> 0.15928982 | G87: =IF(OR(G85="",G7=""),"",IFERROR(G85/G7,"")) -> 0.16662321 | H87: =IF(OR(H85="",H7=""),"",IFERROR(H85/H7,"")) -> 0.24321756 | I87: =IF(OR(I85="",I7=""),"",IFERROR(I85/I7,"")) | J87: =IF(OR(J85="",J7=""),"",IFERROR(J85/J7,""))
A89: F. Hyperscaler cash — big-4 (MSFT/AMZN/GOOG/META), CALENDAR year, from the AI Model (official company models feed it)
A90: OCF big-4 (CY) | B90: $bn | E90: 514.8 | F90: 687.6 | G90: 923.3 | H90: 1201.9 | K90: AI Model.xlsx (Modelos oficiais, saved 2026-08-31) → Resumo | Total ‘OCF big 4’ (MSFT 160.9/203.4/266.5/341.8; AMZN 139.5/188.7/251.1/330.4; GOOG 124.0/182.2/262.1/347.3; META 90.4/113.3/143.6/182.4) | L90: 2026-08-31 — CURRENT official model; CY23-28 only; GOOG/META house OCF = LL + D&A (ex-SBC, ex-WC), conservative vs GAAP
A91: Capex big-4 (CY, total incl. non-AI) | B91: $bn | E91: 409.7 | F91: 749.9 | G91: 1163 | H91: 1463.3 | K91: AI Model.xlsx (Modelos oficiais, saved 2026-08-31) → ‘Capex big4’ | L91: 2026-08-31 — CURRENT official model; CY23-28 only; MSFT incl. finance leases
A92: FCF big-4 (formula = OCF − capex) | B92: $bn | E92: =E90-E91 -> 105.1 | F92: =F90-F91 -> -62.3 | G92: =G90-G91 -> -239.7 | H92: =H90-H91 -> -261.4 | K92: formula; model prints 105.1 / (62.3) / (239.7) / (261.4) | L92: MSFT 44.2/18.9/17.9/44.2; AMZN 7.7/(25.3)/(79.0)/(96.0); GOOG 32.5/(27.8)/(116.1)/(130.4); META 20.7/(28.1)/(62.5)/(79.1)
A93: Capex / OCF big-4 | B93: x | C93: =IF(OR(C91="",C90=""),"",IFERROR(C91/C90,"")) | D93: =IF(OR(D91="",D90=""),"",IFERROR(D91/D90,"")) | E93: =IF(OR(E91="",E90=""),"",IFERROR(E91/E90,"")) -> 0.79584305 | F93: =IF(OR(F91="",F90=""),"",IFERROR(F91/F90,"")) -> 1.090605 | G93: =IF(OR(G91="",G90=""),"",IFERROR(G91/G90,"")) -> 1.2596123 | H93: =IF(OR(H91="",H90=""),"",IFERROR(H91/H90,"")) -> 1.217489 | I93: =IF(OR(I91="",I90=""),"",IFERROR(I91/I90,"")) | J93: =IF(OR(J91="",J90=""),"",IFERROR(J91/J90,""))
A94: ‘Capex faltante’ = all-player AI capex not covered by big-4 capex (others’ spend) | B94: $bn | E94: -13.4 | F94: 151.6 | G94: 722.4 | H94: 1449.8 | K94: AI Model.xlsx (Modelos oficiais, saved 2026-08-31) → ‘Capex faltante’ | L94: 2026-08-31 — CURRENT official model; CY23-28 only
A95: Cumulative big-4 FCF 2026-28 (in 2028 column) | B95: $bn | H95: =SUM(F92:H92) -> -563.4
A96: OCF 5-name (GOOG+MSFT+META+ORCL+AMZN), FISCAL years, house-on-consensus base | B96: $bn | E96: 577 | F96: 707.5 | G96: 911.9 | K96: ai-capex-funding.html section III (Felipe’s Aug-26 exhibit ‘modelos oficiais sobre base de consenso’) | L96: FY basis (MSFT Jun, ORCL May); FY2025-27 only
A97: Capex 5-name, FISCAL years | B97: $bn | E97: 402.4 | F97: 772.8 | G97: 1180.2 | K97: same exhibit (GOOG 91.4/200.6/360.0; MSFT 88.2/145.3/251.9 incl. leases; META 69.7/150.7/200.0; ORCL 21.2/55.7/91.5; AMZN 131.8/220.6/276.8) | L97: FY basis
A98: OCF − capex, 5-name FY (formula) | B98: $bn | E98: =E96-E97 -> 174.6 | F98: =F96-F97 -> -65.3 | G98: =G96-G97 -> -268.3 | K98: formula
