Workbook

Sheet README
A1: OpenAI revenue → Azure growth — link model (v2)
A2: Capstone buyside research · 2026-10-26 · $bn · MSFT fiscal years end June · revised after an independent skeptic review
A4: THE QUESTION
A5: How much of Azure growth is OpenAI, and how does Azure respond when OpenAI revenue moves?
A7: WHAT IS PINNED (trust)
A8: • FY26 level: Microsoft booked $24.1bn of revenue from OpenAI incl. rev share (10-K related-party note) = ~21-24% of restated FY26 Azure ($101.9bn), depending on how much sits in Azure (80-100%).
A9: • Rev-share mechanics: ~20% of OpenAI revenue, booked gross in Azure, "exists through 2030" (Hood), capped. The reported $38bn cap is consistent with 20% × the 2026-30 plan = $135bn max.
A10: • FY26 rev share ≈ $3.8bn (±20%). The cap binds in 2028-29 in every scenario, so total 2026-30 rev share is a FIXED ~$38bn pie: OpenAI revenue changes its TIMING, not its size.
A12: WHAT IS DIRECTIONAL (ranges on the Dashboard)
A13: • FY26 OpenAI contribution to Azure growth (depends on how FY25 training was booked); FY27-FY28 OpenAI points and Azure growth (depend on the H1-26 exit share, terminal share, training path, ε, Azure-booked share).
A14: • FY29-FY30 are SCENARIO ONLY: the cap cliff rests on one paywalled article; uncapped, FY29 Azure growth is much higher.
A16: THREE CHANNELS
... A35: Microsoft F1Q27 print (late Oct-26): Azure growth vs 44-45% cc guide and any OpenAI disclosure. FY27 10-K (Jul-27): next related-party revenue figure. Any disclosure of the cap size/window or the term of the $250bn commitment.
B37: HARD | C37: PARTIAL | D37: ANCHOR | E37: CALIBRATED | F37: ESTIMATE

Sheet Dashboard
A1: OpenAI revenue → Azure growth — link model (v2, skeptic-revised)
A2: Capstone · 2026-10-26 · MSFT fiscal years (June YE), $bn · blue = control · tags: green HARD, blue PARTIAL, amber ESTIMATE · ranges below are the honest output
B4: Control | C4: Value | D4: Tag | E4: Basis / source
B5: Scenario (1 Bear · 2 Base · 3 Bull) | C5: 2 | D5: ESTIMATE | E5: Base = OpenAI 1Q26 internal-plan growth (S11) re-based to FT 2026 $36bn (S13). Bull = FUNDA run-rates (S17). Bear = placeholder.
B6: Scenario name | C6: =CHOOSE($C$5,"Bear — ESTIMATE decay","Base — OpenAI 1Q26 plan","Bull — FUNDA run-rate path") -> Base — OpenAI 1Q26 plan
B7: OpenAI revenue shock (× on CY2027+ revenue) | C7: 1 | D7: ESTIMATE | E7: Outcome lever.
B8: ε — compute elasticity to revenue (0 = compute fixed at plan $, 1 = fixed $ per revenue $) | C8: 0.5 | D8: ESTIMATE | E8: Near term compute is contracted (ε≈0); long run it is funded by revenue (ε≈1). Midpoint.
B9: Terminal Azure share of OpenAI compute | C9: 0.3333 | D9: PARTIAL | E9: 250/750 cloud commitments (S15); stock share used as flow share — see Inputs note. Alt 38.5% (S16).
B10: FY in which the Azure share reaches the terminal level | C10: 2029 | D10: ESTIMATE | E10: Linear glide from the H1-26 exit share.
B11: Rev-share rate (OpenAI → Microsoft, % of OpenAI revenue) | C11: 0.2 | D11: PARTIAL | E11: ~20% (S9); "percentage stays the same" (S7); 20% × 2026-30 plan = $135bn max (S8).
B12: Rev-share cap, cumulative inside the window ($bn) | C12: 38 | D12: PARTIAL | E12: The Information (S8) only. Microsoft: a cap exists, size not given (S7).
B13: Cap window starts at half-year index (5 = H1-26, 6 = H2-26) | C13: 5 | D13: ESTIMATE | E13: Derived from $135bn = 20% × 2026-30 plan (G7 is that identity, not a test).
B14: Cap window ends (calendar year) | C14: 2030 | D14: PARTIAL | E14: Window per S8. The rev share itself "exists through 2030" is HARD (Hood, S26).
B15: Share of the $24.1bn booked in Azure | C15: 0.9 | D15: ESTIMATE | E15: Rev share lands in Azure (S6); segment of the rest not disclosed (S1). Frontier slice of Cloud $21-26bn incl. Anthropic (S5) → 0.8-1.0.
B16: FY25 Azure share of OpenAI inference + hosting (back-cast) | C16: 1 | D16: PARTIAL | E16: All OpenAI cloud spend on Azure as of Q2-25 (S10).
B17: FY25 share of OpenAI training on Azure booked as Azure REVENUE | C17: 0 | D17: PARTIAL | E17: UBS: training "off-P&L, netted against MSFT's equity stake" (S9). Microsoft AI run-rate check (G5a) fails above ~0.4.
B18: Azure-share drop H2-25 → H1-26 (pts) | C18: 0.1 | D18: ESTIMATE | E18: Unidentified by one annual anchor. 0 = smoothest non-OpenAI profile (G12); ≥0.2 = more AI run-rate headroom (G5b).
... B22: Non-OpenAI Azure growth FY27E | C22: 0.25 | D22: PARTIAL | E22: Proxy: commercial RPO ex-OpenAI +25% (S5). Street-implied ~31% (Model diag.); FY26 back-cast 21-35%.
B23: Non-OpenAI growth fade per year after FY27 (pts) | C23: -0.02 | D23: ESTIMATE
B26: Outputs (live) | C26: FY25 back-cast | D26: FY26 anchor | E26: FY27E | F26: FY28E | G26: FY29E scen. | H26: FY30E scen.
B27: OpenAI revenue ($bn, MSFT FY) | C27: =Model!C46 -> 7.5 | D27: =Model!D46 -> 20.35 | E27: =Model!E46 -> 53.850397 | F27: =Model!F46 -> 101.21212 | G27: =Model!G46 -> 175.45859 | H27: =Model!H46 -> 277.40953
B28: OpenAI-related Azure revenue ($bn) | C28: =Model!C53 -> 6.473628 | D28: =Model!D53 -> 21.69 | E28: =Model!E53 -> 44.33888 | F28: =Model!F53 -> 73.957344 | G28: =Model!G53 -> 75.811579 | H28: =Model!H53 -> 77.237272
B29: of which rev share | C29: =Model!C49 -> 1.352 | D29: =Model!D49 -> 3.81034 | E29: =Model!E49 -> 10.770079 | F29: =Model!F49 -> 20.242424 | G29: =Model!G49 -> 4.5881562 | H29: =Model!H49 -> 0
B30: of which compute | C30: =Model!C52 -> 5.121628 | D30: =Model!D52 -> 17.87966 | E30: =Model!E52 -> 33.568801 | F30: =Model!F52 -> 53.71492 | G30: =Model!G52 -> 71.223423 | H30: =Model!H52 -> 77.237272
B31: Azure share of OpenAI compute (FY average) | C31: =Model!C50 -> 1 | D31: =Model!D50 -> 0.55558503 | E31: =Model!E50 -> 0.45397978 | F31: =Model!F50 -> 0.39363989 | G31: =Model!G50 -> 0.3333 | H31: =Model!H50 -> 0.3333
B32: Azure revenue ($bn) | C32: =Model!C55 -> 72.61 | D32: =Model!D55 -> 101.938 | E32: =Model!E55 -> 144.64888 | F32: =Model!F55 -> 197.33864 | G32: =Model!G55 -> 225.10295 | H32: =Model!H55 -> 254.89401
B33: Azure growth y/y | D33: =Model!D58 -> 0.40391131 | E33: =Model!E58 -> 0.4189888 | F33: =Model!F58 -> 0.36425974 | G33: =Model!G58 -> 0.14069372 | H33: =Model!H58 -> 0.13234413
B34: OpenAI contribution (pts) | D34: =Model!D59 -> 20.956304 | E34: =Model!E59 -> 22.21829 | F34: =Model!F59 -> 20.47611 | G34: =Model!G59 -> 0.93962078 | H34: =Model!H59 -> 0.63335162
B35: rev share (pts) | D35: =Model!D60 -> 3.3856769 | E35: =Model!E60 -> 6.8274239 | F35: =Model!F60 -> 6.5485091 | G35: =Model!G60 -> -7.9326927 | H35: =Model!H60 -> -2.0382479
B36: compute (pts) | D36: =Model!D61 -> 17.570627 | E36: =Model!E61 -> 15.390866 | F36: =Model!F61 -> 13.927601 | G36: =Model!G61 -> 8.8723135 | H36: =Model!H61 -> 2.6715995
B37: Non-OpenAI contribution (pts) | D37: =Model!D62 -> 19.434827 | E37: =Model!E62 -> 19.68059 | F37: =Model!F62 -> 15.949864 | G37: =Model!G62 -> 13.129751 | H37: =Model!H62 -> 12.601061
B38: Non-OpenAI Azure growth | D38: =Model!D57 -> 0.21337167 | E38: =Model!E57 -> 0.25 | F38: =Model!F57 -> 0.23 | G38: =Model!G57 -> 0.21 | H38: =Model!H57 -> 0.19
B39: OpenAI share of Azure growth | D39: =Model!D63 -> 0.51883429 | E39: =Model!E63 -> 0.53028362 | F39: =Model!F63 -> 0.56212937 | G39: =Model!G63 -> 0.066784842 | H39: =Model!H63 -> 0.04785642
B40: OpenAI share of Azure revenue | C40: =Model!C64 -> 0.089156149 | D40: =Model!D64 -> 0.21277639 | E40: =Model!E64 -> 0.30652764 | F40: =Model!F64 -> 0.37477375 | G40: =Model!G64 -> 0.33678625 | H40: =Model!H64 -> 0.30301722
B41: Conversion: OpenAI-related Azure ÷ OpenAI revenue | C41: =Model!C67 -> 0.86315039 | D41: =Model!D67 -> 1.0658477 | E41: =Model!E67 -> 0.82337146 | F41: =Model!F67 -> 0.73071627 | G41: =Model!G67 -> 0.43207675 | H41: =Model!H67 -> 0.27842328
B42: Azure pts per +$10bn OpenAI revenue — durable (compute), demand regime | D42: =Model!D73 -> 5.6008122 | E42: =Model!E73 -> 3.057601 | F42: =Model!F73 -> 1.8344984 | G42: =Model!G73 -> 1.0285042 | H42: =Model!H73 -> 0.61843543
B43: durable, capacity regime (75% backfill) | D43: =Model!D74 -> 1.400203 | E43: =Model!E74 -> 0.76440025 | F43: =Model!F74 -> 0.45862459 | G43: =Model!G74 -> 0.25712604 | H43: =Model!H74 -> 0.15460886
B44: rev-share TIMING (pulled forward, given back when the cap binds) | D44: =Model!D75 -> 2.7544415 | E44: =Model!E75 -> 1.9619769 | F44: =Model!F75 -> 1.3826585 | G44: =Model!G75 -> 0 | H44: =Model!H75 -> 0
B45: Rev-share cap reached by FY-end (1/0) | C45: =Model!C69 -> 0 | D45: =Model!D69 -> 0 | E45: =Model!E69 -> 0 | F45: =Model!F69 -> 0 | G45: =Model!G69 -> 1 | H45: =Model!H69 -> 1
B47: Headline with honest ranges (one-at-a-time assumption envelope, A1-A6)
B48: Metric | C48: Default | D48: Low | E48: High
B49: FY26 OpenAI contribution to Azure growth (pts) | C49: =Model!D59 -> 20.956304 | D49: =MIN(Dashboard!C62:C66) -> 11.499342 | E49: =MAX(Dashboard!C62:C66) -> 20.956304
B50: FY27E OpenAI contribution (pts) | C50: =Model!E59 -> 22.21829 | D50: =MIN(Dashboard!D71:D75,Dashboard!E80:E82,Dashboard!C87:C92,Dashboard!C97:C98,Dashboard!C103:C107) -> 16.231709 | E50: =MAX(Dashboard!D71:D75,Dashboard!E80:E82,Dashboard!C87:C92,Dashboard!C97:C98,Dashboard!C103:C107) -> 26.094989
B51: FY28E OpenAI contribution (pts) | C51: =Model!F59 -> 20.47611 | D51: =MIN(Dashboard!E71:E75,Dashboard!F80:F82,Dashboard!D87:D92,Dashboard!D97:D98,Dashboard!D103:D107) -> 12.487748 | E51: =MAX(Dashboard!E71:E75,Dashboard!F80:F82,Dashboard!D87:D92,Dashboard!D97:D98,Dashboard!D103:D107) -> 25.323404
B52: FY27E Azure growth | C52: =Model!E58 -> 0.4189888 | D52: =MIN(Dashboard!F71:F75,Dashboard!G80:G82,Dashboard!E87:E92,Dashboard!E103:E107) -> 0.35912299 | E52: =MAX(Dashboard!F71:F75,Dashboard!G80:G82,Dashboard!E87:E92,Dashboard!E103:E107) -> 0.45775579
B53: FY28E Azure growth | C53: =Model!F58 -> 0.36425974 | D53: =MIN(Dashboard!F87:F92,Dashboard!E97:E98,Dashboard!F103:F107) -> 0.28693035 | E53: =MAX(Dashboard!F87:F92,Dashboard!E97:E98,Dashboard!F103:F107) -> 0.40962283
B55: Calibrated Azure share H2-25 / H1-26 (exit) | C55: =TEXT(Calibration!$C$13,"0%")&" / "&TEXT(Calibration!$C$12,"0%") -> 61% / 51%
B56: Rev-share cap first binds in (scenario) | C56: =Model!$C$80 -> H2'28
B57: Guardrails | C57: =Guardrails!$C$21 -> 12 pass · 2 watch · 0 fail
B59: A1 · FY25 training booked as Azure revenue (0 = off-P&L per UBS)
B60: Input | C60: FY26 OpenAI pts | D60: FY26 non-OpenAI growth | E60: G5a: AI run-rate left Mar-25 | F60: G12 swing (pts)
C61: =Model!D59 -> 20.956304 | D61: =Model!D57 -> 0.21337167 | E61: =Model!$C$89 -> 0.20755274 | F61: =Model!$C$94 -> 6.3377678
B62: 0 | C62: 20.956304 | D62: 0.21337167 | E62: 0.20755274 | F62: 6.3377678
B63: 0.25 | C63: 18.592063 | D63: 0.24570595 | E63: 0.06692111 | F63: 8.5372389
B64: 0.5 | C64: 16.227823 | D64: 0.27981072 | E64: -0.073710525 | F64: 10.969329
B65: 0.75 | C65: 13.863582 | D65: 0.31583549 | E65: -0.21434216 | F65: 13.664335
B66: 1 | C66: 11.499342 | D66: 0.35394709 | E66: -0.3549738 | F66: 16.657583
B68: A2 · Azure-share drop H2-25 → H1-26 (start of the glide)
B69: Input | C69: H1-26 exit share | D69: FY27 OpenAI pts | E69: FY28 OpenAI pts | F69: FY27 Azure g | G69: G5b: AI run-rate left Mar-26 | H69: G12 swing (pts)
C70: =Calibration!$C$12 -> 0.51431967 | D70: =Model!E59 -> 22.21829 | E70: =Model!F59 -> 20.47611 | F70: =Model!E58 -> 0.4189888 | G70: =Model!$C$90 -> 0.093464602 | H70: =Model!$C$94 -> 6.3377678
B71: 0 | C71: 0.55558503 | D71: 24.213816 | E71: 20.084966 | F71: 0.43894407 | G71: 0.051303016 | H71: 1.6069105
B72: 0.1 | C72: 0.51431967 | D72: 22.21829 | E72: 20.47611 | F72: 0.4189888 | G72: 0.093464602 | H72: 6.3377678
B73: 0.2 | C73: 0.47305431 | D73: 20.222763 | E73: 20.878413 | F73: 0.39903353 | G73: 0.13562619 | H73: 11.068625
B74: 0.3 | C74: 0.43178895 | D74: 18.227236 | E74: 21.292358 | F74: 0.37907826 | G74: 0.17778777 | H74: 15.799483
B75: 0.4 | C75: 0.39052359 | D75: 16.231709 | E75: 21.718459 | F75: 0.35912299 | G75: 0.21994936 | H75: 20.53034
B77: A3 · Share of the $24.1bn booked in Azure
B78: Input | C78: H1-26 exit share | D78: FY26 OpenAI % of Azure | E78: FY27 OpenAI pts | F78: FY28 OpenAI pts | G78: FY27 Azure g
C79: =Calibration!$C$12 -> 0.51431967 | D79: =Model!D64 -> 0.21277639 | E79: =Model!E59 -> 22.21829 | F79: =Model!F59 -> 20.47611 | G79: =Model!E58 -> 0.4189888
B80: 0.8 | C80: 0.43943234 | D80: 0.18913457 | E80: 20.96104 | F80: 20.770874 | G80: 0.41232676
B81: 0.9 | C81: 0.51431967 | D81: 0.21277639 | E81: 22.21829 | F81: 20.47611 | G81: 0.4189888
B82: 1 | C82: 0.58920699 | D82: 0.23641821 | E82: 23.475539 | F82: 20.184101 | G82: 0.42565084
B84: A4 · Terminal Azure share of OpenAI compute
B85: Input | C85: FY27 OpenAI pts | D85: FY28 OpenAI pts | E85: FY27 Azure g | F85: FY28 Azure g | G85: FY29 Azure g | H85: FY30 OpenAI % of Azure
C86: =Model!E59 -> 22.21829 | D86: =Model!F59 -> 20.47611 | E86: =Model!E58 -> 0.4189888 | F86: =Model!F58 -> 0.36425974 | G86: =Model!G58 -> 0.14069372 | H86: =Model!H64 -> 0.30301722
B87: 0.18 | C87: 18.511618 | D87: 13.807776 | E87: 0.38192208 | F87: 0.30185456 | G87: 0.048809379 | H87: 0.1901467
B88: 0.25 | C88: 20.204162 | D88: 16.896519 | E88: 0.39884752 | F88: 0.33076037 | G88: 0.092441184 | H88: 0.24590869
B89: 0.3333 | C89: 22.21829 | D89: 20.47611 | E89: 0.4189888 | F89: 0.36425974 | G89: 0.14069372 | H89: 0.30301722
B90: 0.36 | C90: 22.863874 | D90: 21.602062 | E90: 0.42544464 | F90: 0.37479689 | G90: 0.15538527 | H90: 0.3195349
B91: 0.385 | C91: 23.468354 | D91: 22.647117 | E91: 0.43148944 | F91: 0.38457697 | G91: 0.16882119 | H91: 0.33430658
B92: 0.45 | C92: 25.040002 | D92: 25.323404 | E92: 0.44720593 | F92: 0.40962283 | G92: 0.2023792 | H92: 0.36987188
B94: A5 · Training-compute path (1 = OpenAI plan, 2 = WFS haircut)
B95: Input | C95: FY27 OpenAI pts | D95: FY28 OpenAI pts | E95: FY28 Azure g | F95: FY29 Azure g | G95: Compute 2026-30 $bn | H95: RPO burn by Jun-30
C96: =Model!E59 -> 22.21829 | D96: =Model!F59 -> 20.47611 | E96: =Model!F58 -> 0.36425974 | F96: =Model!G58 -> 0.14069372 | G96: =Model!$C$93 -> 792.92035 | H96: =Model!$C$84 -> 0.87276793
B97: 1 | C97: 22.21829 | D97: 20.47611 | E97: 0.36425974 | F97: 0.14069372 | G97: 792.92035 | H97: 0.87276793
B98: 2 | C98: 19.981725 | D98: 12.487748 | E98: 0.28693035 | F98: 0.08580437 | G98: 593.33399 | H98: 0.64691935
B100: A6 · ε compute elasticity to revenue
B101: Input | C101: FY27 OpenAI pts | D101: FY28 OpenAI pts | E101: FY27 Azure g | F101: FY28 Azure g
C102: =Model!E59 -> 22.21829 | D102: =Model!F59 -> 20.47611 | E102: =Model!E58 -> 0.4189888 | F102: =Model!F58 -> 0.36425974
B103: 0 | C103: 18.673992 | D103: 20.392625 | E103: 0.38354583 | F103: 0.36751085
B104: 0.25 | C104: 20.406433 | D104: 20.434605 | E104: 0.40087023 | F104: 0.36590761
B105: 0.5 | C105: 22.21829 | D105: 20.47611 | E105: 0.4189888 | F105: 0.36425974
B106: 0.75 | C106: 24.113205 | D106: 20.517087 | E106: 0.43793796 | F106: 0.36256764
B107: 1 | C107: 26.094989 | D107: 20.55748 | E107: 0.45775579 | F107: 0.36083179
B109: O1 · OpenAI revenue OUTCOME: shock × on CY27+ revenue
B110: Input | C110: FY27 Azure g | D110: FY28 Azure g | E110: FY29 Azure g | F110: FY30 Azure g | G110: FY27 OpenAI pts | H110: FY28 OpenAI pts | I110: Cap binds
C111: =Model!E58 -> 0.4189888 | D111: =Model!F58 -> 0.36425974 | E111: =Model!G58 -> 0.14069372 | F111: =Model!H58 -> 0.13234413 | G111: =Model!E59 -> 22.21829 | H111: =Model!F59 -> 20.47611 | I111: =Model!$C$80 -> H2'28
B112: 0.6 | C112: 0.36960947 | D112: 0.25790951 | E112: 0.25030046 | F112: 0.081529972 | G112: 17.280357 | H112: 9.266037 | I112: H1'29
B113: 0.8 | C113: 0.39606565 | D113: 0.31273891 | E113: 0.19286889 | F113: 0.10720051 | G113: 19.925975 | H113: 15.062133 | I113: H2'28
B114: 0.9 | C114: 0.40788903 | D114: 0.33885127 | E114: 0.16618823 | F114: 0.11981901 | G114: 21.108313 | H114: 17.809514 | I114: H2'28
B115: 1 | C115: 0.4189888 | D115: 0.36425974 | E115: 0.14069372 | F115: 0.13234413 | G115: 22.21829 | H115: 20.47611 | I115: H2'28
...

Sheet Model
A1: Model — calendar-year → half-year → MSFT fiscal-year engine
A2: All formulas. Half-years are the unit: the rev-share cap is cumulative and MSFT FY = H2 of one calendar year + H1 of the next.
B4: Calendar-year engine ($bn) | C4: 2023 | D4: 2024 | E4: 2025 | F4: 2026 | G4: 2027 | H4: 2028 | I4: 2029 | J4: 2030
B5: Scenario revenue growth (CY27-30) | G5: =CHOOSE(Dashboard!$C$5,Inputs!G57,Inputs!G58,Inputs!G59) -> 1.0598007 | H5: =CHOOSE(Dashboard!$C$5,Inputs!H57,Inputs!H58,Inputs!H59) -> 0.82258065 | I5: =CHOOSE(Dashboard!$C$5,Inputs!I57,Inputs!I58,Inputs!I59) -> 0.65486726 | J5: =CHOOSE(Dashboard!$C$5,Inputs!J57,Inputs!J58,Inputs!J59) -> 0.51069519
B6: OpenAI revenue, scenario (pre-shock) | C6: =Inputs!C50 -> 1 | D6: =SUM(Inputs!C62:F62) -> 4.3 | E6: =SUM(Inputs!G62:J62) -> 12.5 | F6: =Dashboard!$C$21 -> 36 | G6: =F6*(1+G5) -> 74.152824 | H6: =G6*(1+H5) -> 135.1495 | I6: =H6*(1+I5) -> 223.65449 | J6: =I6*(1+J5) -> 337.87375
B7: OpenAI revenue (after shock) | C7: =C6 -> 1 | D7: =D6 -> 4.3 | E7: =E6 -> 12.5 | F7: =F6 -> 36 | G7: =G6*Dashboard!$C$7 -> 74.152824 | H7: =H6*Dashboard!$C$7 -> 135.1495 | I7: =I6*Dashboard!$C$7 -> 223.65449 | J7: =J6*Dashboard!$C$7 -> 337.87375
B8: Revenue growth factor (×) | D8: =D7/C7 -> 4.3 | E8: =E7/D7 -> 2.9069767 | F8: =F7/E7 -> 2.88 | G8: =G7/F7 -> 2.0598007 | H8: =H7/G7 -> 1.8225806 | I8: =I7/H7 -> 1.6548673 | J8: =J7/I7 -> 1.5106952
B9: Plan revenue (1Q26 internal plan) | F9: =Inputs!F52 -> 30.1 | G9: =Inputs!G52 -> 62 | H9: =Inputs!H52 -> 113 | I9: =Inputs!I52 -> 187 | J9: =Inputs!J52 -> 282.5
B10: WFS revenue (scales WFS inference/hosting) | D10: =Inputs!D50 -> 4.3 | E10: =Inputs!E50 -> 12.5 | F10: =Inputs!F50 -> 30.1951 | G10: =Inputs!G50 -> 61.42 | H10: =Inputs!H50 -> 120.1437 | I10: =Inputs!I50 -> 224.9539 | J10: =Inputs!J50 -> 366.8464
B11: Training compute at plan/WFS revenue (selected path) | F11: =CHOOSE(Dashboard!$C$19,Inputs!F53,Inputs!F54) -> 30 | G11: =CHOOSE(Dashboard!$C$19,Inputs!G53,Inputs!G54) -> 60 | H11: =CHOOSE(Dashboard!$C$19,Inputs!H53,Inputs!H54) -> 120 | I11: =CHOOSE(Dashboard!$C$19,Inputs!I53,Inputs!I54) -> 125 | J11: =CHOOSE(Dashboard!$C$19,Inputs!J53,Inputs!J54) -> 98
B12: Inference + hosting at WFS revenue | F12: =Inputs!F55+Inputs!F56 -> 16.9088 | G12: =Inputs!G55+Inputs!G56 -> 30.8225 | H12: =Inputs!H55+Inputs!H56 -> 51.5643 | I12: =Inputs!I55+Inputs!I56 -> 86.2014 | J12: =Inputs!J55+Inputs!J56 -> 131.718
B13: Training compute (scenario) | D13: =SUM(Inputs!C63:F63) -> 4 | E13: =SUM(Inputs!G63:J63) -> 12 | F13: =F11*(F7/F9)^Dashboard!$C$8 -> 32.808718 | G13: =G11*(G7/G9)^Dashboard!$C$8 -> 65.617435 | H13: =H11*(H7/H9)^Dashboard!$C$8 -> 131.23487 | I13: =I11*(I7/I9)^Dashboard!$C$8 -> 136.70299 | J13: =J11*(J7/J9)^Dashboard!$C$8 -> 107.17514
B14: Inference + hosting (scenario) | D14: =SUM(Inputs!C64:F64)+Inputs!D56 -> 2.4339 | E14: =SUM(Inputs!G64:J64)+Inputs!E56 -> 9.5067 | F14: =F12*(F7/F10)^Dashboard!$C$8 -> 18.462725 | G14: =G12*(G7/G10)^Dashboard!$C$8 -> 33.867006 | H14: =H12*(H7/H10)^Dashboard!$C$8 -> 54.689739 | I14: =I12*(I7/I10)^Dashboard!$C$8 -> 85.952074 | J14: =J12*(J7/J10)^Dashboard!$C$8 -> 126.40965
B15: OpenAI total compute spend | D15: =D13+D14 -> 6.4339 | E15: =E13+E14 -> 21.5067 | F15: =F13+F14 -> 51.271443 | G15: =G13+G14 -> 99.484441 | H15: =H13+H14 -> 185.92461 | I15: =I13+I14 -> 222.65506 | J15: =J13+J14 -> 233.58479
B16: Compute growth factor (×) | E16: =E15/D15 -> 3.3427159 | F16: =F15/E15 -> 2.3839754 | G16: =G15/F15 -> 1.940348 | H16: =H15/G15 -> 1.8688813 | I16: =I15/H15 -> 1.1975556 | J16: =J15/I15 -> 1.0490882
B17: Compute intensity k | D17: =D15/D7 -> 1.4962558 | E17: =E15/E7 -> 1.720536 | F17: =F15/F7 -> 1.4242067 | G17: =G15/G7 -> 1.3416137 | H17: =H15/H7 -> 1.3756959 | I17: =I15/I7 -> 0.99553141 | J17: =J15/J7 -> 0.69133749
B20: Half-year engine ($bn) | C20: H1'24 | D20: H2'24 | E20: H1'25 | F20: H2'25 | G20: H1'26 | H20: H2'26 | I20: H1'27 | J20: H2'27 | K20: H1'28 | L20: H2'28 | M20: H1'29 | N20: H2'29 | O20: H1'30 | P20: H2'30
B21: Calendar year | C21: 2024 | D21: 2024 | E21: 2025 | F21: 2025 | G21: 2026 | H21: 2026 | I21: 2027 | J21: 2027 | K21: 2028 | L21: 2028 | M21: 2029 | N21: 2029 | O21: 2030 | P21: 2030
B22: Half (1/2) | C22: 1 | D22: 2 | E22: 1 | F22: 2 | G22: 1 | H22: 2 | I22: 1 | J22: 2 | K22: 1 | L22: 2 | M22: 1 | N22: 2 | O22: 1 | P22: 2
B23: MSFT fiscal year | C23: =IF(C22=1,C21,C21+1) -> 2024 | D23: =IF(D22=1,D21,D21+1) -> 2025 | E23: =IF(E22=1,E21,E21+1) -> 2025 | F23: =IF(F22=1,F21,F21+1) -> 2026 | G23: =IF(G22=1,G21,G21+1) -> 2026 | H23: =IF(H22=1,H21,H21+1) -> 2027 | I23: =IF(I22=1,I21,I21+1) -> 2027 | J23: =IF(J22=1,J21,J21+1) -> 2028 | ... P23: =IF(P22=1,P21,P21+1) -> 2031
B24: Half index | C24: 1 | D24: 2 | E24: 3 | F24: 4 | G24: 5 | H24: 6 | I24: 7 | J24: 8 | K24: 9 | L24: 10 | M24: 11 | N24: 12 | O24: 13 | P24: 14
B25: OpenAI revenue | C25: =Inputs!C62+Inputs!D62 -> 1.55 | D25: =Inputs!E62+Inputs!F62 -> 2.75 | E25: =Inputs!G62+Inputs!H62 -> 4.75 | F25: =Inputs!I62+Inputs!J62 -> 7.75 | G25: =Inputs!K62+Inputs!L62 -> 12.6 | H25: =$F$7-G25 -> 23.4 | I25: =$G$7/(1+SQRT($G$8)) -> 30.450397 | J25: =$G$7-I25 -> 43.702427 | K25: =$H$7/(1+SQRT($H$8)) -> 57.509695 | L25: =$H$7-K25 -> 77.639806 | M25: =$I$7/(1+SQRT($I$8)) -> 97.818788 | N25: =$I$7-M25 -> 125.8357 | O25: =$J$7/(1+SQRT($J$8)) -> 151.57384 | P25: =$J$7-O25 -> 186.29992
B26: of which training compute (memo) | C26: =Inputs!C63+Inputs!D63 -> 1.8 | D26: =Inputs!E63+Inputs!F63 -> 2.2 | E26: =Inputs!G63+Inputs!H63 -> 4.6667 | F26: =Inputs!I63+Inputs!J63 -> 7.3333 | G26: =Inputs!K63+Inputs!L63 -> 12 | H26: =$F$13-G26 -> 20.808718 | I26: =I27*$G$13/$G$15 -> 27.42099 | J26: =J27*$G$13/$G$15 -> 38.196445 | K26: =K27*$H$13/$H$15 -> 55.441898 | L26: =L27*$H$13/$H$15 -> 75.792973 | M26: =M27*$I$13/$I$15 -> 65.272935 | N26: =N27*$I$13/$I$15 -> 71.430056 | O26: =O27*$J$13/$J$15 -> 52.945606 | P26: =P27*$J$13/$J$15 -> 54.229539
B27: OpenAI total compute spend | C27: =C26+Inputs!C64+Inputs!D64+Inputs!D56*C25/Inputs!D50 -> 2.672386 | D27: =D26+Inputs!E64+Inputs!F64+Inputs!D56*D25/Inputs!D50 -> 3.761514 | E27: =E26+Inputs!G64+Inputs!H64+Inputs!E56*E25/Inputs!E50 -> 8.226814 | F27: =F26+Inputs!I64+Inputs!J64+Inputs!E56*F25/Inputs!E50 -> 13.279886 | G27: =G26+Inputs!K64+Inputs!L64+Inputs!F56*G25/Inputs!F50 -> 18.901795 | H27: =$F$15-G27 -> 32.369648 | I27: =$G$15/(1+SQRT($G$16)) -> 41.573735 | J27: =$G$15-I27 -> 57.910706 | K27: =$H$15/(1+SQRT($H$16)) -> 78.546297 | L27: =$H$15-K27 -> 107.37831 | M27: =$I$15/(1+SQRT($I$16)) -> 106.31333 | N27: =$I$15-M27 -> 116.34174 | O27: =$J$15/(1+SQRT($J$16)) -> 115.39325 | P27: =$J$15-O27 -> 118.19154
B28: Compute eligible to be Azure revenue (FY25: ex off-P&L training) | C28: =IF(C23<=2025,C27-(1-Dashboard!$C$17)*C26,C27) -> 0.87238605 | D28: =IF(D23<=2025,D27-(1-Dashboard!$C$17)*D26,D27) -> 1.561514 | E28: =IF(E23<=2025,E27-(1-Dashboard!$C$17)*E26,E27) -> 3.560114 | F28: =IF(F23<=2025,F27-(1-Dashboard!$C$17)*F26,F27) -> 13.279886 | G28: =IF(G23<=2025,G27-(1-Dashboard!$C$17)*G26,G27) -> 18.901795 | H28: =IF(H23<=2025,H27-(1-Dashboard!$C$17)*H26,H27) -> 32.369648 | I28: =IF(I23<=2025,I27-(1-Dashboard!$C$17)*I26,I27) -> 41.573735 | J28: =IF(J23<=2025,J27-(1-Dashboard!$C$17)*J26,J27) -> 57.910706 | ... P28: =IF(P23<=2025,P27-(1-Dashboard!$C$17)*P26,P27) -> 118.19154
B29: Recognised Azure-API revenue (excluded from rev-share base) | C29: =Inputs!C65+Inputs!D65 -> 0.19 | D29: =Inputs!E65+Inputs!F65 -> 0.31 | E29: =Inputs!G65+Inputs!H65 -> 0.43 | F29: =Inputs!I65+Inputs!J65 -> 0.695 | G29: =Inputs!K65+Inputs!L65 -> 0.6033 | H29: 0 | I29: 0 | J29: 0 | K29: 0 | L29: 0 | M29: 0 | N29: 0 | O29: 0 | P29: 0
B30: Rev-share base | C30: =C25-C29 -> 1.36 | D30: =D25-D29 -> 2.44 | E30: =E25-E29 -> 4.32 | F30: =F25-F29 -> 7.055 | G30: =G25-G29 -> 11.9967 | H30: =H25-H29 -> 23.4 | I30: =I25-I29 -> 30.450397 | J30: =J25-J29 -> 43.702427 | ... P30: =P25-P29 -> 186.29992
B31: Rev share, uncapped | C31: =Dashboard!$C$11*C30 -> 0.272 | D31: =Dashboard!$C$11*D30 -> 0.488 | E31: =Dashboard!$C$11*E30 -> 0.864 | F31: =Dashboard!$C$11*F30 -> 1.411 | G31: =Dashboard!$C$11*G30 -> 2.39934 | H31: =Dashboard!$C$11*H30 -> 4.68 | I31: =Dashboard!$C$11*I30 -> 6.0900794 | J31: =Dashboard!$C$11*J30 -> 8.7404854 | ... P31: =Dashboard!$C$11*P30 -> 37.259984
B32: Inside cap window? (1/0) | C32: =IF(AND(C24>=Dashboard!$C$13,C21<=Dashboard!$C$14),1,0) -> 0 | D32: =IF(AND(D24>=Dashboard!$C$13,D21<=Dashboard!$C$14),1,0) -> 0 | E32: =IF(AND(E24>=Dashboard!$C$13,E21<=Dashboard!$C$14),1,0) -> 0 | F32: =IF(AND(F24>=Dashboard!$C$13,F21<=Dashboard!$C$14),1,0) -> 0 | G32: =IF(AND(G24>=Dashboard!$C$13,G21<=Dashboard!$C$14),1,0) -> 1 | H32: =IF(AND(H24>=Dashboard!$C$13,H21<=Dashboard!$C$14),1,0) -> 1 | I32: =IF(AND(I24>=Dashboard!$C$13,I21<=Dashboard!$C$14),1,0) -> 1 | J32: =IF(AND(J24>=Dashboard!$C$13,J21<=Dashboard!$C$14),1,0) -> 1 | ... P32: =IF(AND(P24>=Dashboard!$C$13,P21<=Dashboard!$C$14),1,0) -> 1
B33: Rev share paid to Microsoft | C33: =IF(C32=1,MAX(0,MIN(C31,Dashboard!$C$12-0)),C31) -> 0.272 | D33: =IF(D32=1,MAX(0,MIN(D31,Dashboard!$C$12-C34)),D31) -> 0.488 | E33: =IF(E32=1,MAX(0,MIN(E31,Dashboard!$C$12-D34)),E31) -> 0.864 | F33: =IF(F32=1,MAX(0,MIN(F31,Dashboard!$C$12-E34)),F31) -> 1.411 | G33: =IF(G32=1,MAX(0,MIN(G31,Dashboard!$C$12-F34)),G31) -> 2.39934 | H33: =IF(H32=1,MAX(0,MIN(H31,Dashboard!$C$12-G34)),H31) -> 4.68 | I33: =IF(I32=1,MAX(0,MIN(I31,Dashboard!$C$12-H34)),I31) -> 6.0900794 | J33: =IF(J32=1,MAX(0,MIN(J31,Dashboard!$C$12-I34)),J31) -> 8.7404854 | K33: =IF(K32=1,MAX(0,MIN(K31,Dashboard!$C$12-J34)),K31) -> 11.501939 | ... P33: =IF(P32=1,MAX(0,MIN(P31,Dashboard!$C$12-O34)),P31) -> 0
B34: Cumulative rev share inside window | C34: =0+IF(C32=1,C33,0) -> 0 | D34: =C34+IF(D32=1,D33,0) -> 0 | E34: =D34+IF(E32=1,E33,0) -> 0 | F34: =E34+IF(F32=1,F33,0) -> 0 | G34: =F34+IF(G32=1,G33,0) -> 2.39934 | H34: =G34+IF(H32=1,H33,0) -> 7.07934 | I34: =H34+IF(I32=1,I33,0) -> 13.169419 | J34: =I34+IF(J32=1,J33,0) -> 21.909905 | K34: =J34+IF(K32=1,K33,0) -> 33.411844 | ... P34: =O34+IF(P32=1,P33,0) -> 38
B35: Cap binding this half? (1/0) | C35: =IF(C33<C31-0.000001,1,0) -> 0 | D35: =IF(D33<D31-0.000001,1,0) -> 0 | E35: =IF(E33<E31-0.000001,1,0) -> 0 | F35: =IF(F33<F31-0.000001,1,0) -> 0 | G35: =IF(G33<G31-0.000001,1,0) -> 0 | H35: =IF(H33<H31-0.000001,1,0) -> 0 | I35: =IF(I33<I31-0.000001,1,0) -> 0 | J35: =IF(J33<J31-0.000001,1,0) -> 0 | ... P35: =IF(P33<P31-0.000001,1,0) -> 1
B36: helper: index if binding, else 99 | C36: =IF(C35=1,C24,99) -> 99 | D36: =IF(D35=1,D24,99) -> 99 | E36: =IF(E35=1,E24,99) -> 99 | F36: =IF(F35=1,F24,99) -> 99 | G36: =IF(G35=1,G24,99) -> 99 | H36: =IF(H35=1,H24,99) -> 99 | I36: =IF(I35=1,I24,99) -> 99 | J36: =IF(J35=1,J24,99) -> 99 | ... P36: =IF(P35=1,P24,99) -> 14
B37: Azure share of OpenAI compute | C37: =IF(C23<=2025,Dashboard!$C$16,IF(C23>2030,Dashboard!$C$9,INDEX($C$51:$H$51,C23-2024))) -> 1 | D37: =IF(D23<=2025,Dashboard!$C$16,IF(D23>2030,Dashboard!$C$9,INDEX($C$51:$H$51,D23-2024))) -> 1 | E37: =IF(E23<=2025,Dashboard!$C$16,IF(E23>2030,Dashboard!$C$9,INDEX($C$51:$H$51,E23-2024))) -> 1 | F37: =Calibration!$C$13 -> 0.61431967 | G37: =Calibration!$C$12 -> 0.51431967 | H37: =IF(H23<=2025,Dashboard!$C$16,IF(H23>2030,Dashboard!$C$9,INDEX($C$51:$H$51,H23-2024))) -> 0.45397978 | I37: =IF(I23<=2025,Dashboard!$C$16,IF(I23>2030,Dashboard!$C$9,INDEX($C$51:$H$51,I23-2024))) -> 0.45397978 | J37: =IF(J23<=2025,Dashboard!$C$16,IF(J23>2030,Dashboard!$C$9,INDEX($C$51:$H$51,J23-2024))) -> 0.39363989 | K37: =IF(K23<=2025,Dashboard!$C$16,IF(K23>2030,Dashboard!$C$9,INDEX($C$51:$H$51,K23-2024))) -> 0.39363989 | L37: =IF(L23<=2025,Dashboard!$C$16,IF(L23>2030,Dashboard!$C$9,INDEX($C$51:$H$51,L23-2024))) -> 0.3333 | M37: =IF(M23<=2025,Dashboard!$C$16,IF(M23>2030,Dashboard!$C$9,INDEX($C$51:$H$51,M23-2024))) -> 0.3333 | N37: =IF(N23<=2025,Dashboard!$C$16,IF(N23>2030,Dashboard!$C$9,INDEX($C$51:$H$51,N23-2024))) -> 0.3333 | O37: =IF(O23<=2025,Dashboard!$C$16,IF(O23>2030,Dashboard!$C$9,INDEX($C$51:$H$51,O23-2024))) -> 0.3333 | P37: =IF(P23<=2025,Dashboard!$C$16,IF(P23>2030,Dashboard!$C$9,INDEX($C$51:$H$51,P23-2024))) -> 0.3333
B38: Azure compute revenue from OpenAI | C38: =C37*C28 -> 0.87238605 | D38: =D37*D28 -> 1.561514 | E38: =E37*E28 -> 3.560114 | F38: =F37*F28 -> 8.1580951 | G38: =G37*G28 -> 9.7215649 | H38: =H37*H28 -> 14.695166 | I38: =I37*I28 -> 18.873635 | J38: =J37*J28 -> 22.795964 | ... P38: =P37*P28 -> 39.393241
B39: OpenAI-related Azure revenue (rev share + compute) | C39: =C33+C38 -> 1.144386 | D39: =D33+D38 -> 2.049514 | E39: =E33+E38 -> 4.424114 | F39: =F33+F38 -> 9.5690951 | G39: =G33+G38 -> 12.120905 | H39: =H33+H38 -> 19.375166 | I39: =I33+I38 -> 24.963715 | J39: =J33+J38 -> 31.536449 | ... P39: =P33+P38 -> 39.393241
B40: Azure revenue, restated (HARD; FY25-26 halves) | D40: =Inputs!$C$9+Inputs!$C$10 -> 33.358 | E40: =Inputs!$C$11+Inputs!$C$12 -> 39.252 | F40: =Inputs!$C$13+Inputs!$C$14 -> 46.513 | G40: =Inputs!$C$15+Inputs!$C$16 -> 55.425
B41: Non-OpenAI Azure revenue (halves) | D41: =D40-D39 -> 31.308486 | E41: =E40-E39 -> 34.827886 | F41: =F40-F39 -> 36.943905 | G41: =G40-G39 -> 43.304095
B42: Non-OpenAI Azure y/y (halves) — diagnostic G12 | F42: =F41/D41-1 -> 0.17999653 | G42: =G41/E41-1 -> 0.24337421
B45: Fiscal-year roll-up (MSFT FY, $bn) | C45: 2025 | D45: 2026 | E45: 2027 | F45: 2028 | G45: 2029 | H45: 2030
B46: OpenAI revenue (FY) | C46: =SUMIF($C$23:$P$23,C$45,$C$25:$P$25) -> 7.5 | D46: =SUMIF($C$23:$P$23,D$45,$C$25:$P$25) -> 20.35 | E46: =SUMIF($C$23:$P$23,E$45,$C$25:$P$25) -> 53.850397 | F46: =SUMIF($C$23:$P$23,F$45,$C$25:$P$25) -> 101.21212 | G46: =SUMIF($C$23:$P$23,G$45,$C$25:$P$25) -> 175.45859 | H46: =SUMIF($C$23:$P$23,H$45,$C$25:$P$25) -> 277.40953
B47: OpenAI total compute spend (FY) | C47: =SUMIF($C$23:$P$23,C$45,$C$27:$P$27) -> 11.988328 | D47: =SUMIF($C$23:$P$23,D$45,$C$27:$P$27) -> 32.181681 | E47: =SUMIF($C$23:$P$23,E$45,$C$27:$P$27) -> 73.943383 | F47: =SUMIF($C$23:$P$23,F$45,$C$27:$P$27) -> 136.457 | G47: =SUMIF($C$23:$P$23,G$45,$C$27:$P$27) -> 213.69164 | H47: =SUMIF($C$23:$P$23,H$45,$C$27:$P$27) -> 231.73499
B48: Compute eligible to be Azure revenue | C48: =SUMIF($C$23:$P$23,C$45,$C$28:$P$28) -> 5.121628 | D48: =SUMIF($C$23:$P$23,D$45,$C$28:$P$28) -> 32.181681 | E48: =SUMIF($C$23:$P$23,E$45,$C$28:$P$28) -> 73.943383 | F48: =SUMIF($C$23:$P$23,F$45,$C$28:$P$28) -> 136.457 | G48: =SUMIF($C$23:$P$23,G$45,$C$28:$P$28) -> 213.69164 | H48: =SUMIF($C$23:$P$23,H$45,$C$28:$P$28) -> 231.73499
B49: Rev share paid to Microsoft | C49: =SUMIF($C$23:$P$23,C$45,$C$33:$P$33) -> 1.352 | D49: =SUMIF($C$23:$P$23,D$45,$C$33:$P$33) -> 3.81034 | E49: =SUMIF($C$23:$P$23,E$45,$C$33:$P$33) -> 10.770079 | F49: =SUMIF($C$23:$P$23,F$45,$C$33:$P$33) -> 20.242424 | G49: =SUMIF($C$23:$P$23,G$45,$C$33:$P$33) -> 4.5881562 | H49: =SUMIF($C$23:$P$23,H$45,$C$33:$P$33) -> 0
B50: Azure share of OpenAI compute (effective FY average) | C50: =C52/C48 -> 1 | D50: =D52/D48 -> 0.55558503 | E50: =E52/E48 -> 0.45397978 | F50: =F52/F48 -> 0.39363989 | G50: =G52/G48 -> 0.3333 | H50: =H52/H48 -> 0.3333
B51: Azure share path (FY26 = H1-26 exit; glide to terminal) | C51: =Dashboard!$C$16 -> 1 | D51: =Calibration!$C$12 -> 0.51431967 | E51: =IF(E$45>=Dashboard!$C$10,Dashboard!$C$9,$D$51+(Dashboard!$C$9-$D$51)*(E$45-2026)/(Dashboard!$C$10-2026)) -> 0.45397978 | F51: =IF(F$45>=Dashboard!$C$10,Dashboard!$C$9,$D$51+(Dashboard!$C$9-$D$51)*(F$45-2026)/(Dashboard!$C$10-2026)) -> 0.39363989 | G51: =IF(G$45>=Dashboard!$C$10,Dashboard!$C$9,$D$51+(Dashboard!$C$9-$D$51)*(G$45-2026)/(Dashboard!$C$10-2026)) -> 0.3333 | H51: =IF(H$45>=Dashboard!$C$10,Dashboard!$C$9,$D$51+(Dashboard!$C$9-$D$51)*(H$45-2026)/(Dashboard!$C$10-2026)) -> 0.3333
B52: Azure compute revenue from OpenAI | C52: =SUMIF($C$23:$P$23,C$45,$C$38:$P$38) -> 5.121628 | D52: =SUMIF($C$23:$P$23,D$45,$C$38:$P$38) -> 17.87966 | E52: =SUMIF($C$23:$P$23,E$45,$C$38:$P$38) -> 33.568801 | F52: =SUMIF($C$23:$P$23,F$45,$C$38:$P$38) -> 53.71492 | G52: =SUMIF($C$23:$P$23,G$45,$C$38:$P$38) -> 71.223423 | H52: =SUMIF($C$23:$P$23,H$45,$C$38:$P$38) -> 77.237272
B53: OpenAI-related Azure revenue | C53: =SUMIF($C$23:$P$23,C$45,$C$39:$P$39) -> 6.473628 | D53: =SUMIF($C$23:$P$23,D$45,$C$39:$P$39) -> 21.69 | E53: =SUMIF($C$23:$P$23,E$45,$C$39:$P$39) -> 44.33888 | F53: =SUMIF($C$23:$P$23,F$45,$C$39:$P$39) -> 73.957344 | G53: =SUMIF($C$23:$P$23,G$45,$C$39:$P$39) -> 75.811579 | H53: =SUMIF($C$23:$P$23,H$45,$C$39:$P$39) -> 77.237272
B55: Azure revenue | C55: =Inputs!$C$7 -> 72.61 | D55: =Inputs!$C$8 -> 101.938 | E55: =E56+E53 -> 144.64888 | F55: =F56+F53 -> 197.33864 | G55: =G56+G53 -> 225.10295 | H55: =H56+H53 -> 254.89401
B56: Non-OpenAI Azure revenue | C56: =C55-C53 -> 66.136372 | D56: =D55-D53 -> 80.248 | E56: =D56*(1+E57) -> 100.31 | F56: =E56*(1+F57) -> 123.3813 | G56: =F56*(1+G57) -> 149.29137 | H56: =G56*(1+H57) -> 177.65673
B57: Non-OpenAI Azure growth | D57: =D56/C56-1 -> 0.21337167 | E57: =Dashboard!$C$22+Dashboard!$C$23*(E$45-2027) -> 0.25 | F57: =Dashboard!$C$22+Dashboard!$C$23*(F$45-2027) -> 0.23 | G57: =Dashboard!$C$22+Dashboard!$C$23*(G$45-2027) -> 0.21 | H57: =Dashboard!$C$22+Dashboard!$C$23*(H$45-2027) -> 0.19
B58: Azure growth y/y | D58: =D55/C55-1 -> 0.40391131 | E58: =E55/D55-1 -> 0.4189888 | F58: =F55/E55-1 -> 0.36425974 | G58: =G55/F55-1 -> 0.14069372 | H58: =H55/G55-1 -> 0.13234413
B59: OpenAI contribution to Azure growth (pts) | D59: =(D53-C53)/C55*100 -> 20.956304 | E59: =(E53-D53)/D55*100 -> 22.21829 | F59: =(F53-E53)/E55*100 -> 20.47611 | G59: =(G53-F53)/F55*100 -> 0.93962078 | H59: =(H53-G53)/G55*100 -> 0.63335162
B60: of which rev share (pts) | D60: =(D49-C49)/C55*100 -> 3.3856769 | E60: =(E49-D49)/D55*100 -> 6.8274239 | F60: =(F49-E49)/E55*100 -> 6.5485091 | G60: =(G49-F49)/F55*100 -> -7.9326927 | H60: =(H49-G49)/G55*100 -> -2.0382479
B61: of which compute (pts) | D61: =(D52-C52)/C55*100 -> 17.570627 | E61: =(E52-D52)/D55*100 -> 15.390866 | F61: =(F52-E52)/E55*100 -> 13.927601 | G61: =(G52-F52)/F55*100 -> 8.8723135 | H61: =(H52-G52)/G55*100 -> 2.6715995
B62: Non-OpenAI contribution (pts) | D62: =(D56-C56)/C55*100 -> 19.434827 | E62: =(E56-D56)/D55*100 -> 19.68059 | F62: =(F56-E56)/E55*100 -> 15.949864 | G62: =(G56-F56)/F55*100 -> 13.129751 | H62: =(H56-G56)/G55*100 -> 12.601061
B63: OpenAI share of Azure growth | D63: =IF(D58=0,0,D59/(D58*100)) -> 0.51883429 | E63: =IF(E58=0,0,E59/(E58*100)) -> 0.53028362 | F63: =IF(F58=0,0,F59/(F58*100)) -> 0.56212937 | G63: =IF(G58=0,0,G59/(G58*100)) -> 0.066784842 | H63: =IF(H58=0,0,H59/(H58*100)) -> 0.04785642
B64: OpenAI share of Azure revenue | C64: =C53/C55 -> 0.089156149 | D64: =D53/D55 -> 0.21277639 | E64: =E53/E55 -> 0.30652764 | F64: =F53/F55 -> 0.37477375 | G64: =G53/G55 -> 0.33678625 | H64: =H53/H55 -> 0.30301722
B65: OpenAI COMPUTE share of Azure revenue (FUNDA-comparable) | C65: =C52/C55 -> 0.070536124 | D65: =D52/D55 -> 0.1753974 | E65: =E52/E55 -> 0.23207093 | F65: =F52/F55 -> 0.27219666 | G65: =G52/G55 -> 0.31640377 | H65: =H52/H55 -> 0.30301722
B67: Conversion: OpenAI-related Azure revenue ÷ OpenAI revenue | C67: =C53/C46 -> 0.86315039 | D67: =D53/D46 -> 1.0658477 | E67: =E53/E46 -> 0.82337146 | F67: =F53/F46 -> 0.73071627 | G67: =G53/G46 -> 0.43207675 | H67: =H53/H46 -> 0.27842328
B68: Compute intensity k (FY) | C68: =C47/C46 -> 1.5984437 | D68: =D47/D46 -> 1.5814094 | E68: =E47/E46 -> 1.3731261 | F68: =F47/F46 -> 1.3482279 | G68: =G47/G46 -> 1.2179035 | H68: =H47/H46 -> 0.83535338
B69: Rev-share cap reached by FY-end? (1/0) | C69: =IF(MIN($C$36:$P$36)<=2*(C$45-2024)+1,1,0) -> 0 | D69: =IF(MIN($C$36:$P$36)<=2*(D$45-2024)+1,1,0) -> 0 | E69: =IF(MIN($C$36:$P$36)<=2*(E$45-2024)+1,1,0) -> 0 | F69: =IF(MIN($C$36:$P$36)<=2*(F$45-2024)+1,1,0) -> 0 | G69: =IF(MIN($C$36:$P$36)<=2*(G$45-2024)+1,1,0) -> 1 | H69: =IF(MIN($C$36:$P$36)<=2*(H$45-2024)+1,1,0) -> 1
B70: Durable marginal: Azure $ per +$1 OpenAI revenue (compute only, demand regime) | C70: =C51*C68*Dashboard!$C$8 -> 0.79922186 | D70: =D51*D68*Dashboard!$C$8 -> 0.40667497 | E70: =E51*E68*Dashboard!$C$8 -> 0.31168573 | F70: =F51*F68*Dashboard!$C$8 -> 0.26535813 | G70: =G51*G68*Dashboard!$C$8 -> 0.20296362 | H70: =H51*H68*Dashboard!$C$8 -> 0.13921164
B71: Durable marginal, capacity regime (after backfill) | C71: =C70*(1-Dashboard!$C$20) -> 0.19980547 | D71: =D70*(1-Dashboard!$C$20) -> 0.10166874 | E71: =E70*(1-Dashboard!$C$20) -> 0.077921433 | F71: =F70*(1-Dashboard!$C$20) -> 0.066339533 | G71: =G70*(1-Dashboard!$C$20) -> 0.050740905 | H71: =H70*(1-Dashboard!$C$20) -> 0.03480291
B72: Rev-share timing: $ pulled forward per +$1 (given back once the cap binds) | C72: =Dashboard!$C$11*(1-C69) -> 0.2 | D72: =Dashboard!$C$11*(1-D69) -> 0.2 | E72: =Dashboard!$C$11*(1-E69) -> 0.2 | F72: =Dashboard!$C$11*(1-F69) -> 0.2 | G72: =Dashboard!$C$11*(1-G69) -> 0 | H72: =Dashboard!$C$11*(1-H69) -> 0
B73: Azure pts per +$10bn OpenAI revenue — durable, demand regime | D73: =10*D70/C55*100 -> 5.6008122 | E73: =10*E70/D55*100 -> 3.057601 | F73: =10*F70/E55*100 -> 1.8344984 | G73: =10*G70/F55*100 -> 1.0285042 | H73: =10*H70/G55*100 -> 0.61843543
B74: Azure pts per +$10bn — durable, capacity regime | D74: =10*D71/C55*100 -> 1.400203 | E74: =10*E71/D55*100 -> 0.76440025 | F74: =10*F71/E55*100 -> 0.45862459 | G74: =10*G71/F55*100 -> 0.25712604 | H74: =10*H71/G55*100 -> 0.15460886
B75: Azure pts per +$10bn — rev-share TIMING only | D75: =10*D72/C55*100 -> 2.7544415 | E75: =10*E72/D55*100 -> 1.9619769 | F75: =10*F72/E55*100 -> 1.3826585 | G75: =10*G72/F55*100 -> 0 | H75: =10*H72/G55*100 -> 0
B76: Diagnostic: Street-implied non-OpenAI growth (MS FY27 Azure less this OpenAI path) | E76: =(Inputs!$C$8*(1+Inputs!$C$41)-E53)/D56-1 -> 0.28177141
B79: Single-cell outputs and diagnostics
B80: Rev-share cap first binds in | C80: =IFERROR(INDEX($C$20:$P$20,MIN($C$36:$P$36)),"not reached by 2030") -> H2'28
B81: Cumulative rev share inside the window ($bn) | C81: =$P$34 -> 38
B82: OpenAI share of commercial RPO, Dec-25 ($bn) — STOCK | C82: =Inputs!$C$17*Inputs!$C$18 -> 281.25
B83: Cumulative Azure compute revenue from OpenAI, Jan-26 → Jun-30 ($bn) — cumulative FLOW | C83: =SUM($G$38:$O$38) -> 245.46598
B84: Share of the Dec-25 OpenAI RPO consumed by Jun-30 | C84: =C83/C82 -> 0.87276793
B85: Annualised OpenAI-related Azure revenue, H1-25 (Jan-Jun 25) | C85: =2*$E$39 -> 8.848228
B86: Annualised OpenAI-related Azure revenue, H1-26 (Jan-Jun 26) | C86: =2*$G$39 -> 24.24181
B87: Annualised Azure OpenAI Service gross sales, H1-25 (WFS) | C87: =2*(Inputs!G66+Inputs!H66) -> 4.3
B88: Annualised Azure OpenAI Service gross sales, H1-26 (WFS est.) | C88: =2*(Inputs!K66+Inputs!L66) -> 9.3
B89: AI run-rate left for Copilots & other AI, Mar-25 (% of run-rate) | C89: =(Inputs!$C$47-C85-C87)/Inputs!$C$47 -> 0.20755274
B90: AI run-rate left for Copilots & other AI, Mar-26 (% of run-rate) | C90: =(Inputs!$C$25-C86-C88)/Inputs!$C$25 -> 0.093464602
B91: Annualised OpenAI total compute spend, H1-25 | C91: =2*$E$27 -> 16.453628
B92: Rev share paid in CY26 ($bn) | C92: =$G$33+$H$33 -> 7.07934
B93: OpenAI total compute spend 2026-30, selected scenario ($bn) | C93: =SUM($F$15:$J$15) -> 792.92035
B94: Non-OpenAI y/y swing H2-25 → H1-26 (pts) | C94: =(G42-F42)*100 -> 6.3377678

Sheet Inputs
A1: Inputs — every sourced number, tagged
A2: Values in $bn unless stated. Fill: green HARD · blue PARTIAL · dark blue ANCHOR · amber ESTIMATE. Source IDs → Sources sheet.
A4: ID | B4: Item | C4: Value | D4: Unit | E4: Tag | F4: Source | G4: Note
A5: anchor | B5: FY26 Microsoft revenue from commercial arrangements with OpenAI, incl. revenue-sharing payments (related-party note) | C5: 24.1 | D5: $bn | E5: ANCHOR | F5: S1 | G5: Company-wide (segment not named), Jul-25 to Jun-26. First-ever disclosure (ASC 850). The calibration anchor.
A6: ar | B6: Accounts receivable from OpenAI, 30-Jun-26 | C6: 6 | D6: $bn | E6: HARD | F6: S1 | G6: Memo.
A7: az25 | B7: Azure revenue FY25, restated to the FY27 definition | C7: 72.61 | D7: $bn | E7: HARD | F7: S2
A8: az26 | B8: Azure revenue FY26, restated to the FY27 definition | C8: 101.938 | D8: $bn | E8: HARD | F8: S2 | G8: +40.4% y/y.
A9: az25q1 | B9: Azure F1Q25 (Sep-24 qtr), restated | C9: 16.021 | D9: $bn | E9: HARD | F9: S2
A10: az25q2 | B10: Azure F2Q25 (Dec-24 qtr), restated | C10: 17.337 | D10: $bn | E10: HARD | F10: S2
A11: az25q3 | B11: Azure F3Q25 (Mar-25 qtr), restated | C11: 18.54 | D11: $bn | E11: HARD | F11: S2
A12: az25q4 | B12: Azure F4Q25 (Jun-25 qtr), restated | C12: 20.712 | D12: $bn | E12: HARD | F12: S2
A13: az26q1 | B13: Azure F1Q26 (Sep-25 qtr), restated | C13: 22.384 | D13: $bn | E13: HARD | F13: S2
A14: az26q2 | B14: Azure F2Q26 (Dec-25 qtr), restated | C14: 24.129 | D14: $bn | E14: HARD | F14: S2
A15: az26q3 | B15: Azure F3Q26 (Mar-26 qtr), restated | C15: 26.008 | D15: $bn | E15: HARD | F15: S2
A16: az26q4 | B16: Azure F4Q26 (Jun-26 qtr), restated | C16: 29.417 | D16: $bn | E16: HARD | F16: S2
A17: rpo | B17: Commercial RPO, 31-Dec-25 | C17: 625 | D17: $bn | E17: HARD | F17: S3
A18: rposh | B18: Share of commercial RPO from OpenAI, 31-Dec-25 | C18: 0.45 | D18: % | E18: HARD | F18: S3 | G18: "Approximately 45%" (±~$16bn of rounding). Only quarter with an OpenAI %; F3Q26/F4Q26 give ex-OpenAI growth only.
A19: rpo_x | B19: Commercial RPO growth EXCLUDING OpenAI, F4Q26 | C19: 0.25 | D19: % | E19: HARD | F19: S5 | G19: Proxy used for the FY27 non-OpenAI Azure growth default.
A20: commit | B20: Incremental Azure commitment from OpenAI, Oct-25 | C20: 250 | D20: $bn | E20: HARD | F20: S4 | G20: Term not disclosed.
A21: cloud26 | B21: Microsoft Cloud revenue FY26 (as reported) | C21: 214 | D21: $bn | E21: HARD | F21: S5 | G21: "nearly 90% from customers outside of Frontier model companies".
A22: fr_lo | B22: Frontier-model companies' share of Microsoft Cloud, low end | C22: 0.1 | D22: % | E22: PARTIAL | F22: S5 | G22: Capstone reading of "nearly 90% outside": 10-13%. Includes Anthropic.
A23: fr_hi | B23: Frontier-model companies' share of Microsoft Cloud, high end | C23: 0.13 | D23: % | E23: PARTIAL | F23: S5
A24: ai_dec24 | B24: Microsoft AI business annual revenue run-rate, Dec-24 | C24: 13 | D24: $bn | E24: HARD | F24: S24 | G24: "surpassed $13 billion, up 175%".
A25: ai_rr | B25: Microsoft AI business annual revenue run-rate, Mar-26 | C25: 37 | D25: $bn | E25: HARD | F25: S20 | G25: "surpassed $37 billion ARR, up 123%". Company-wide (Azure AI + Copilots + OpenAI).
A26: ai_g | B26: Growth of that run-rate y/y, Mar-26 | C26: 1.23 | D26: % | E26: HARD | F26: S20 | G26: Implies ~$16.6bn at Mar-25.
A27: ubs_rr | B27: UBS: Azure AI revenue run-rate at Jun-25, "substantially all" OpenAI-tied | C27: 18.6 | D27: $bn | E27: PARTIAL | F27: S9 | G27: Broker estimate; sits near the whole of Microsoft's AI run-rate at the time (see G3).
A28: semi | B28: SemiAnalysis: OpenAI cloud spend, all booked by Azure, as of Q2-25 (">$10B") | C28: 10 | D28: $bn | E28: PARTIAL | F28: S10 | G28: A floor.
A29: info_rs | B29: The Information: Microsoft rev share from OpenAI in 2026 | C29: 6 | D29: $bn | E29: PARTIAL | F29: S8 | G29: "~$6B (vs $4B planned) of $30B" via @wallstengine 2026-05-12.
A30: info_max | B30: The Information: uncapped rev share 2026-30 ("$135B max") | C30: 135 | D30: $bn | E30: PARTIAL | F30: S8 | G30: Cap $38B vs $135B max -> "saves $97B".
A31: ft30 | B31: FT: OpenAI plan revenue, 2030 | C31: 350 | D31: $bn | E31: PARTIAL | F31: S13
A32: ftcum | B32: FT: OpenAI plan revenue "between now and the end of 2030" | C32: 840 | D32: $bn | E32: PARTIAL | F32: S13 | G32: "Now" = Sep-26: window read as Sep-26 to Dec-30.
A33: ftcomp | B33: FT: OpenAI spend "on computing power and infrastructure by the end of 2030" | C33: 856 | D33: $bn | E33: PARTIAL | F33: S13 | G33: Same plan vintage as the revenue ladder. Includes infrastructure, so a ceiling-ish check on compute.
A34: ftsep | B34: FT: OpenAI NET annualised revenue, Sep-26 | C34: 50 | D34: $bn | E34: PARTIAL | F34: S14 | G34: NET basis. Axios ~$70bn is GROSS: never mix.
A35: c_orcl | B35: OpenAI compute agreement: Oracle / Stargate | C35: 300 | D35: $bn | E35: PARTIAL | F35: S15
A36: c_az | B36: OpenAI compute agreement: Microsoft Azure | C36: 250 | D36: $bn | E36: PARTIAL | F36: S15
A37: c_aws | B37: OpenAI compute agreement: AWS | C37: 138 | D37: $bn | E37: PARTIAL | F37: S15 | G37: "over 8 yrs, ramping" — terms differ by contract.
A38: c_gcp | B38: OpenAI compute agreement: Google Cloud | C38: 40 | D38: $bn | E38: PARTIAL | F38: S15
A39: c_crwv | B39: OpenAI compute agreement: CoreWeave | C39: 22 | D39: $bn | E39: PARTIAL | F39: S15
A40: c_nov | B40: Barclays Nov-25: total OpenAI compute obligations | C40: 650 | D40: $bn | E40: PARTIAL | F40: S16 | G40: Alternative denominator.
A41: ms_fy27 | B41: Morgan Stanley: FY27E Azure growth, new definition ($147.2bn) | C41: 0.444 | D41: % | E41: PARTIAL | F41: S25 | G41: Full-year Street comparator (G10).
A42: funda_rev26 | B42: FUNDA: OpenAI revenue, MSFT FY26 | C42: 19.7 | D42: $bn | E42: PARTIAL | F42: S17 | G42: G2.
A43: funda_rr27 | B43: FUNDA: OpenAI annualised revenue run-rate, Jun-27E | C43: 111.8 | D43: $bn | E43: PARTIAL | F43: S17 | G43: Bull scenario CY27.
A44: funda_rr28 | B44: FUNDA: OpenAI annualised revenue run-rate, Jun-28E | C44: 212.9 | D44: $bn | E44: PARTIAL | F44: S17 | G44: Bull scenario CY28.
A45: term_share | B45: Derived: Azure share of OpenAI cloud commitments = Azure ÷ (Oracle + Azure + AWS + GCP + CoreWeave) | C45: =Inputs!$C$36/(Inputs!$C$35+Inputs!$C$36+Inputs!$C$37+Inputs!$C$38+Inputs!$C$39) -> 0.33333333 | E45: PARTIAL | F45: S15 | G45: A share of contract STOCKS used as an annual FLOW share (terms differ). Omits AMD/Broadcom/Cerebras/owned capacity (pushes lower); adding ~$31bn pre-existing Azure RPO pushes to ~36%.
A46: term_alt | B46: Derived (alt): Azure ÷ Barclays Nov-25 total obligations | C46: =Inputs!$C$36/Inputs!$C$40 -> 0.38461538 | E46: PARTIAL | F46: S16
A47: ai_mar25 | B47: Derived: Microsoft AI run-rate at Mar-25 = Mar-26 ÷ (1 + growth) | C47: =Inputs!$C$25/(1+Inputs!$C$26) -> 16.591928 | E47: PARTIAL | F47: S20 | G47: Between the Dec-24 $13bn and Mar-26 $37bn marks.
B49: Calendar-year series ($bn) | C49: 2023 | D49: 2024 | E49: 2025 | F49: 2026 | G49: 2027 | H49: 2028 | I49: 2029 | J49: 2030 | K49: Tag | L49: Source | M49: Note
A50: rev_wfs | B50: OpenAI net (recognised) revenue — WFS model | C50: 1 | D50: 4.3 | E50: 12.5 | F50: 30.1951 | G50: 61.42 | H50: 120.1437 | I50: 224.9539 | J50: 366.8464 | K50: PARTIAL | L50: S11 | M50: WFS tabulation (2023-25) and estimates (2026-30, Jul-26 vintage). Denominator for scaling WFS inference/hosting.
A51: rev_co25 | B51: OpenAI 2025 revenue — company figure | E51: 13.1 | K51: PARTIAL | L51: S12 | M51: Memo: model uses WFS quarters (12.5) to stay consistent with the WFS compute quarters.
A52: plan_rev | B52: OpenAI internal plan revenue, as of 1Q26 | C52: 1 | D52: 4.3 | E52: 12.5 | F52: 30.1 | G52: 62 | H52: 113 | I52: 187 | J52: 282.5 | K52: PARTIAL | L52: S11 | M52: Plan as tabulated by WFS. Sum 2026-30 = $674.6bn; 20% of it = $134.9bn (G7).
A53: train_plan | B53: Training & R&D compute — OpenAI internal plan (WSJ) | C53: 4 | D53: 4 | E53: 12 | F53: 30 | G53: 60 | H53: 120 | I53: 125 | J53: 98 | K53: PARTIAL | L53: S11 | M53: WSJ 2026-04-05 internal projections via WFS. Path 1 (default). LOAD-BEARING for FY28+.
A54: train_wfs | B54: Training & R&D compute — WFS own estimate | F54: 30 | G54: 45 | H54: 58.5 | I54: 58.5 | J54: 58.5 | K54: PARTIAL | L54: S11 | M54: Path 2: WFS haircuts the plan by 25-53% from 2027.
A55: infer | B55: Inference compute (reported) | C55: 0.4661 | D55: 2.0338 | E55: 8.4065 | F55: 14.4019 | G55: 26.0303 | H55: 42.791 | I55: 70.8993 | J55: 108.5981 | K55: PARTIAL | L55: S11 | M55: 2025 $8.4B / 2026E ~$14B per The Information 2026-02-24; 2027-30 WFS (tied to WFS revenue).
A56: host | B56: Hosting & other cost of sales (non-GPU cloud services) | C56: 0.105 | D56: 0.4 | E56: 1.1003 | F56: 2.5069 | G56: 4.7922 | H56: 8.7733 | I56: 15.3021 | J56: 23.1199 | K56: PARTIAL | L56: S11 | M56: 2024 from The Information (Winter-25 projection); rest WFS. Inside the $24.1bn anchor, so inside the share denominator too.
A57: g_bear | B57: Scenario 1 Bear — OpenAI revenue growth y/y | G57: 0.6 | H57: 0.4 | I57: 0.3 | J57: 0.25 | K57: ESTIMATE | L57: — | M57: Capstone placeholder; no source.
A58: g_base | B58: Scenario 2 Base — growth of the 1Q26 internal plan | G58: =G52/F52-1 -> 1.0598007 | H58: =H52/G52-1 -> 0.82258065 | I58: =I52/H52-1 -> 0.65486726 | J58: =J52/I52-1 -> 0.51069519 | K58: PARTIAL | L58: S11, S13 | M58: Plan growth re-based to FT's $36bn 2026 → ~$338bn 2030 vs FT $350bn (G9).
A59: g_bull | B59: Scenario 3 Bull — FUNDA run-rate path, then fade | G59: =Inputs!$C$43/Dashboard!$C$21-1 -> 2.1055556 | H59: =Inputs!$C$44/Inputs!$C$43-1 -> 0.90429338 | I59: 0.45 | J59: 0.35 | K59: PARTIAL | L59: S17 | M59: CY27/CY28 = FUNDA Jun-27E / Jun-28E run-rates (mid-year run-rate ≈ calendar-year revenue); 2029-30 fade ESTIMATE.
B61: WFS quarterly lines ($bn) — basis for the H1-24 … H1-26 half-years | C61: 1Q24 | D61: 2Q24 | E61: 3Q24 | F61: 4Q24 | G61: 1Q25 | H61: 2Q25 | I61: 3Q25 | J61: 4Q25 | K61: 1Q26E | L61: 2Q26E | M61: Source / note
A62: q_rev | B62: OpenAI net revenue | C62: 0.65 | D62: 0.9 | E62: 1.2 | F62: 1.55 | G62: 2.05 | H62: 2.7 | I62: 3.45 | J62: 4.3 | K62: 5.65 | L62: 6.95 | M62: S11 (WFS OpenAI PnL). OpenAI reports no quarters; 1Q26E-2Q26E are WFS estimates.
A63: q_trn | B63: Compute — training & R&D | C63: 0.8667 | D63: 0.9333 | E63: 1 | F63: 1.2 | G63: 2 | H63: 2.6667 | I63: 3.3333 | J63: 4 | K63: 5.3333 | L63: 6.6667 | M63: S11 (WFS OpenAI PnL).
A64: q_inf | B64: Compute — inference (reported) | C64: 0.3003 | D64: 0.4279 | E64: 0.5575 | F64: 0.7482 | G64: 1.3185 | H64: 1.8235 | I64: 2.3556 | J64: 2.9088 | K64: 2.5998 | L64: 3.2559 | M64: S11 (WFS OpenAI PnL).
A65: q_api | B65: Recognised Azure-API revenue (OpenAI's 20% of Azure OpenAI Service) — excluded from the rev-share base | C65: 0.08 | D65: 0.11 | E65: 0.14 | F65: 0.17 | G65: 0.19 | H65: 0.24 | I65: 0.3 | J65: 0.395 | K65: 0.44 | L65: 0.1633 | M65: S11 (WFS OpenAI PnL). Zero after the Apr-26 rework.
A66: q_gapi | B66: Azure OpenAI Service gross sales (channel 3 — Microsoft revenue, not OpenAI's) | C66: 0.4 | D66: 0.55 | E66: 0.7 | F66: 0.85 | G66: 0.95 | H66: 1.2 | I66: 1.5 | J66: 1.975 | K66: 2.2 | L66: 2.45 | M66: S11 (WFS OpenAI PnL). Used only in the AI run-rate checks (G3, G5).

Sheet Calibration
A1: Calibration — back-solve the Azure share from the 10-K anchor
A2: One disclosed level ($24.1bn) identifies ONE constant. The split of FY26 into halves (the drop d) is a separate, unidentified lever.
B4: FY26 Microsoft revenue from OpenAI, incl. rev share (10-K) | C4: =Inputs!$C$5 -> 24.1 | D4: ANCHOR · S1
B5: × share booked in Azure | C5: =Dashboard!$C$15 -> 0.9 | D5: Dashboard control
B6: equals: OpenAI-related Azure revenue FY26 | C6: =C4*C5 -> 21.69
B7: less: rev share FY26 (20% × OpenAI revenue ex recognised Azure-API revenue) | C7: =Model!$D$49 -> 3.81034 | D7: S7/S8/S9 rate · S11 revenue
B8: equals: Azure compute revenue from OpenAI FY26 | C8: =C6-C7 -> 17.87966
B9: OpenAI compute spend H2-25 (WFS, incl. hosting) | C9: =Model!$F$28 -> 13.279886 | D9: S11
B10: OpenAI compute spend H1-26 (WFS estimate, incl. hosting) | C10: =Model!$G$28 -> 18.901795 | D10: S11
B11: Azure-share drop H2-25 → H1-26 (d) | C11: =Dashboard!$C$18 -> 0.1 | D11: Dashboard control
B12: CALIBRATED: Azure share, H1-26 (exit, start of the glide) | C12: =(C8-C11*C9)/(C9+C10) -> 0.51431967 | D12: Solves C8 = s1×C9 + s2×C10 with s1 = s2 + d
B13: CALIBRATED: Azure share, H2-25 | C13: =C12+C11 -> 0.61431967
B14: Effective FY26 average share | C14: =C8/(C9+C10) -> 0.55558503 | D14: Independent of d
B15: Status | C15: =IF(AND(C12>=0,C13<=1),"🟢 PASS — both halves inside 0-100%","🔴 FAIL — anchor, frac or compute basis inconsistent") -> 🟢 PASS — both halves inside 0-100% | D15: Guardrail G1
B17: Conversion FY26: OpenAI-related Azure revenue ÷ OpenAI revenue | C17: =C6/Model!$D$46 -> 1.0658477
B18: Rev share as % of OpenAI-related Azure revenue FY26 | C18: =C7/C6 -> 0.17567266
B19: OpenAI-related revenue as % of restated FY26 Azure | C19: =C6/Inputs!$C$8 -> 0.21277639
B22: Exit share (C12) sensitivity: WFS compute multiplier (columns) × drop d (rows)
C23: 0.8 | D23: 0.9 | E23: 1 | F23: 1.1 | G23: 1.2
B24: 0 | C24: =($C$8-$B24*$C$9*C$23)/(($C$9+$C$10)*C$23) -> 0.69448128 | D24: =($C$8-$B24*$C$9*D$23)/(($C$9+$C$10)*D$23) -> 0.61731669 | E24: =($C$8-$B24*$C$9*E$23)/(($C$9+$C$10)*E$23) -> 0.55558503 | F24: =($C$8-$B24*$C$9*F$23)/(($C$9+$C$10)*F$23) -> 0.5050773 | G24: =($C$8-$B24*$C$9*G$23)/(($C$9+$C$10)*G$23) -> 0.46298752
B25: 0.1 | C25: =($C$8-$B25*$C$9*C$23)/(($C$9+$C$10)*C$23) -> 0.65321592 | D25: =($C$8-$B25*$C$9*D$23)/(($C$9+$C$10)*D$23) -> 0.57605134 | E25: =($C$8-$B25*$C$9*E$23)/(($C$9+$C$10)*E$23) -> 0.51431967 | F25: =($C$8-$B25*$C$9*F$23)/(($C$9+$C$10)*F$23) -> 0.46381194 | G25: =($C$8-$B25*$C$9*G$23)/(($C$9+$C$10)*G$23) -> 0.42172216
B26: 0.2 | C26: =($C$8-$B26*$C$9*C$23)/(($C$9+$C$10)*C$23) -> 0.61195056 | D26: =($C$8-$B26*$C$9*D$23)/(($C$9+$C$10)*D$23) -> 0.53478598 | E26: =($C$8-$B26*$C$9*E$23)/(($C$9+$C$10)*E$23) -> 0.47305431 | F26: =($C$8-$B26*$C$9*F$23)/(($C$9+$C$10)*F$23) -> 0.42254658 | G26: =($C$8-$B26*$C$9*G$23)/(($C$9+$C$10)*G$23) -> 0.3804568
B27: 0.3 | C27: =($C$8-$B27*$C$9*C$23)/(($C$9+$C$10)*C$23) -> 0.57068521 | D27: =($C$8-$B27*$C$9*D$23)/(($C$9+$C$10)*D$23) -> 0.49352062 | E27: =($C$8-$B27*$C$9*E$23)/(($C$9+$C$10)*E$23) -> 0.43178895 | F27: =($C$8-$B27*$C$9*F$23)/(($C$9+$C$10)*F$23) -> 0.38128122 | G27: =($C$8-$B27*$C$9*G$23)/(($C$9+$C$10)*G$23) -> 0.33919145
B29: Read: the FY26 LEVEL of OpenAI-related Azure revenue is pinned by the 10-K (× the Azure-booked share). What is NOT pinned: how it splits between the two halves of FY26, and therefore where the forward glide starts. A ±20% error in the WFS compute halves moves the exit share by roughly ∓8-10pts.

Sheet Guardrails
A1: Guardrails — checks against observables, with honest independence labels
A2: PASS within tolerance · WATCH within 1.6× · FAIL beyond · INFO = cannot realistically fail. NOTHING here tests the share glide, ε, the terminal share or the Azure-booked share: those are shown as ranges on the Dashboard.
A4: # | B4: Check | C4: Type | D4: Model | E4: Anchor | F4: Anchor source | G4: Tolerance | H4: Deviation | I4: Status | J4: Independent of the fit? | K4: Read
A5: G1 | B5: Calibrated Azure shares (H2-25, H1-26) inside 0-100% | C5: derived constant | D5: =Calibration!$C$12 -> 0.51431967 | E5: =Calibration!$C$13 -> 0.61431967 | F5: Calibration | I5: =IF(AND(D5>=0,E5<=1),"🟢 PASS","🔴 FAIL") -> 🟢 PASS | J5: No | K5: Model = H1-26 exit share; Anchor column = H2-25 share.
A6: G2 | B6: FY26 OpenAI revenue (WFS halves) vs FUNDA FY26 | C6: flow vs flow | D6: =Model!$D$46 -> 20.35 | E6: =Inputs!$C$42 -> 19.7 | F6: FUNDA 2026-10-23 (S17) | G6: 0.15 | H6: =D6/E6-1 -> 0.032994924 | I6: =IF(ABS(H6)<=G6,"🟢 PASS",IF(ABS(H6)<=G6*1.6,"🟡 WATCH","🔴 FAIL")) -> 🟢 PASS | J6: Yes — different source | K6: Validates the revenue base for the rev share.
A7: G3 | B7: H1-25 annualised OpenAI-related Azure + Azure OpenAI Service vs UBS Jun-25 Azure-AI run-rate | C7: run-rate vs run-rate | D7: =Model!$C$85+Model!$C$87 -> 13.148228 | E7: =Inputs!$C$27 -> 18.6 | F7: UBS 2025-09-02 (S9) | G7: 0.25 | H7: =D7/E7-1 -> -0.29310602 | I7: =IF(ABS(H7)<=G7,"🟢 PASS",IF(ABS(H7)<=G7*1.6,"🟡 WATCH","🔴 FAIL")) -> 🟡 WATCH | J7: Yes — broker | K7: UBS's $18.6bn sits near the whole of Microsoft's AI run-rate then (~$16.6bn Mar-25, HARD): G5a governs.
A8: G3c | B8: OpenAI total compute run-rate H1-25 ≥ SemiAnalysis ">$10B on Azure" | C8: floor | D8: =Model!$C$91 -> 16.453628 | E8: =Inputs!$C$28 -> 10 | F8: SemiAnalysis 2025-09-03 (S10) | I8: =IF(D8>=E8,"🟢 PASS","🔴 FAIL") -> 🟢 PASS | J8: Yes | K8: Floor only.
A9: G4 | B9: $24.1bn ÷ Microsoft Cloud FY26 inside the frontier-company band (10-13%) | C9: share vs share | D9: =Inputs!$C$5/Inputs!$C$21 -> 0.11261682 | E9: =Inputs!$C$22 -> 0.1 | F9: "nearly 90% outside Frontier model companies" (S5) | I9: =IF(AND(D9>=Inputs!$C$22,D9<=Inputs!$C$23),"🟢 PASS","🔴 FAIL") -> 🟢 PASS | J9: No — same filer, same year | K9: Anchor consistency only.
A10: G5a | B10: Microsoft AI run-rate Mar-25 left for Copilots & other AI after OpenAI-related + Azure OpenAI Service | C10: component vs total | D10: =Model!$C$89 -> 0.20755274 | E10: 0.15 | F10: Microsoft F3Q26 call: $37bn, +123% (S20) | I10: =IF(D10>=E10,"🟢 PASS",IF(D10>=0,"🟡 WATCH","🔴 FAIL")) -> 🟢 PASS | J10: Yes — company AI disclosure, not used in the fit | K10: Tests the FY25 back-cast (training off-P&L lever). Needs ≥15% left for M365/GitHub Copilot etc.
A11: G5b | B11: Same at Mar-26 ($37bn) | C11: component vs total | D11: =Model!$C$90 -> 0.093464602 | E11: 0.15 | F11: S20 | I11: =IF(D11>=E11,"🟢 PASS",IF(D11>=0,"🟡 WATCH","🔴 FAIL")) -> 🟡 WATCH | J11: Yes | K11: Tests the H1-26 exit level (d lever). ~30M+ Copilot seats alone are several $bn.
A12: G6 | B12: Rev share paid in CY26 vs The Information (~$6bn) | C12: flow vs flow | D12: =Model!$C$92 -> 7.07934 | E12: =Inputs!$C$29 -> 6 | F12: The Information 2026-05-11 (S8) | G12: 0.25 | H12: =D12/E12-1 -> 0.17989 | I12: =IF(ABS(H12)<=G12,"🟢 PASS",IF(ABS(H12)<=G12*1.6,"🟡 WATCH","🔴 FAIL")) -> 🟢 PASS | J12: Partly — rate shares a source | K12: Gap = revenue base ($36bn FT plan vs $30bn at the time).
A13: G7 | B13: 20% × 1Q26 plan revenue 2026-30 vs "$135bn max" | C13: identity | D13: =Dashboard!$C$11*SUM(Inputs!F52:J52) -> 134.92 | E13: =Inputs!$C$30 -> 135 | F13: S8 vs S11 | G13: 0.05 | H13: =D13/E13-1 -> -0.00059259259 | I13: =IF(ABS(H13)<=G13,"🟢 PASS",IF(ABS(H13)<=G13*1.6,"🟡 WATCH","🔴 FAIL")) -> 🟢 PASS | J13: No — this identity SETS the window start | K13: Consistency of the reported cap terms with the plan, not a test of the model.
A14: G8 | B14: Cumulative Azure compute revenue Jan-26→Jun-30 ÷ OpenAI RPO Dec-25 ($281bn) | C14: cumulative flow vs stock | D14: =Model!$C$84 -> 0.87276793 | F14: S3 (45% × $625bn) | I14: ="ℹ️ INFO" -> ℹ️ INFO | J14: Yes, but cannot realistically fail | K14: Rev share excluded (sales-based royalty exemption). Jun-26 OpenAI RPO is likely below $281bn (ex-OpenAI RPO growth disclosures).
A15: G9a | B15: Base path 2030 revenue vs FT plan $350bn | C15: flow vs flow | D15: =Dashboard!$C$21*(1+Inputs!G58)*(1+Inputs!H58)*(1+Inputs!I58)*(1+Inputs!J58) -> 337.87375 | E15: =Inputs!$C$31 -> 350 | F15: FT 2026-09-18 (S13) | G15: 0.1 | H15: =D15/E15-1 -> -0.034646417 | I15: =IF(ABS(H15)<=G15,"🟢 PASS",IF(ABS(H15)<=G15*1.6,"🟡 WATCH","🔴 FAIL")) -> 🟢 PASS | J15: Yes | K15: Base computed explicitly whatever scenario is selected.
A16: G9b | B16: Base path revenue Sep-26 → Dec-30 vs FT "$840bn between now and end-2030" | C16: cumulative vs cumulative | D16: =(Dashboard!$C$21-Model!$G$25)*2/3+Dashboard!$C$21*((1+Inputs!G58)+(1+Inputs!G58)*(1+Inputs!H58)+(1+Inputs!G58)*(1+Inputs!H58)*(1+Inputs!I58)+(1+Inputs!G58)*(1+Inputs!H58)*(1+Inputs!I58)*(1+Inputs!J58)) -> 786.43056 | E16: =Inputs!$C$32 -> 840 | F16: FT 2026-09-18 (S13) | G16: 0.1 | H16: =D16/E16-1 -> -0.063773137 | I16: =IF(ABS(H16)<=G16,"🟢 PASS",IF(ABS(H16)<=G16*1.6,"🟡 WATCH","🔴 FAIL")) -> 🟢 PASS | J16: Yes | K16: Sep-Dec 26 ≈ 2/3 of H2-26.
A17: G10 | B17: FY27 Azure growth (model) vs Morgan Stanley FY27E +44.4% (new definition) | C17: rate vs rate | D17: =Model!$E$58 -> 0.4189888 | E17: =Inputs!$C$41 -> 0.444 | F17: MS 2026-10-19 (S25); F1Q27 guide 44-45% cc (S2) | G17: 0.06 | H17: =D17-E17 -> -0.025011202 | I17: =IF(ABS(H17)<=G17,"🟢 PASS",IF(ABS(H17)<=G17*1.6,"🟡 WATCH","🔴 FAIL")) -> 🟢 PASS | J17: Weak — depends on ESTIMATE non-OpenAI growth | K17: Street-implied non-OpenAI growth is in Model diagnostics.
A18: G11 | B18: OpenAI compute 2026-30 (selected scenario) vs FT "$856bn on computing power and infrastructure" | C18: cumulative vs cumulative | D18: =Model!$C$93 -> 792.92035 | E18: =Inputs!$C$33 -> 856 | F18: FT 2026-09-18 (S13) | G18: 0.15 | H18: =D18/E18-1 -> -0.073691177 | I18: =IF(ABS(H18)<=G18,"🟢 PASS",IF(ABS(H18)<=G18*1.6,"🟡 WATCH","🔴 FAIL")) -> 🟢 PASS | J18: Partly — same plan family | K18: FT figure includes infrastructure; WSJ 2026-07-22 says $750bn compute through 2030 (via WFS).
A19: G12 | B19: Non-OpenAI Azure y/y swing H2-25 → H1-26 (pts) | C19: smoothness | D19: =Model!$C$94 -> 6.3377678 | E19: 0 | F19: Restated Azure halves (S2) | G19: 8 | H19: =D19-E19 -> 6.3377678 | I19: =IF(ABS(H19)<=G19,"🟢 PASS",IF(ABS(H19)<=G19*1.6,"🟡 WATCH","🔴 FAIL")) -> 🟢 PASS | J19: Yes — HARD halves | K19: A large swing means the half-year split of the anchor (d) or the FY25 back-cast is off.
B21: Summary (INFO excluded) | C21: =COUNTIF($I$5:$I$19,"*PASS*")&" pass · "&COUNTIF($I$5:$I$19,"*WATCH*")&" watch · "&COUNTIF($I$5:$I$19,"*FAIL*")&" fail" -> 12 pass · 2 watch · 0 fail

Sheet Comparators
A1: Comparators — like-for-like against the sell-side
A2: FUNDA "OpenAI-related Azure revenue" is inference + training compute only (no rev share), so it is compared with this model's COMPUTE line.
A4: Source | B4: Metric (like-for-like) | C4: FY26 | D4: FY27E | E4: FY28E | F4: This model FY26 | G4: FY27E | H4: FY28E
A5: FUNDA 2026-10-23 (S17) | B5: OpenAI COMPUTE revenue in Azure ($bn) | C5: 12.2 | D5: 37 | E5: 66.7 | F5: =Model!D52 -> 17.87966 | G5: =Model!E52 -> 33.568801 | H5: =Model!F52 -> 53.71492
A6: FUNDA 2026-10-23 (S17) | B6: OpenAI revenue, MSFT FY ($bn) | C6: 19.7 | D6: 70.8 | E6: 160.7 | F6: =Model!D46 -> 20.35 | G6: =Model!E46 -> 53.850397 | H6: =Model!F46 -> 101.21212
A7: FUNDA 2026-10-23 (S17) | B7: OpenAI COMPUTE as % of Azure | C7: 0.119 | D7: 0.245 | E7: 0.304 | F7: =Model!D65 -> 0.1753974 | G7: =Model!E65 -> 0.23207093 | H7: =Model!F65 -> 0.27219666
A8: FUNDA 2026-10-23 (S17) | B8: Azure growth y/y | D8: 0.48 | E8: 0.455 | F8: =Model!D58 -> 0.40391131 | G8: =Model!E58 -> 0.4189888 | H8: =Model!F58 -> 0.36425974
A9: FUNDA 2026-10-23 (S17) | B9: OpenAI COMPUTE contribution to Azure growth (pts) | D9: 24.4 | F9: =Model!D61 -> 17.570627 | G9: =Model!E61 -> 15.390866 | H9: =Model!F61 -> 13.927601
A11: 🔭 Variant read | B11: ="FUNDA's FY26 OpenAI compute in Azure is "&TEXT(C5/F5-1,"0%")&" vs this model (pinned to the 10-K). Starting from a smaller base, FUNDA's FY27 compute contribution ("&TEXT(D9,"0.0")&" pts) is HIGHER than this model's ("&TEXT(G9,"0.0")&" pts): FUNDA understates OpenAI's level in Azure and overstates its FY27 growth contribution." -> FUNDA's FY26 OpenAI compute in Azure is -32% vs this model (pinned to the 10-K). Starting from a smaller base, FUNDA's FY27 compute contribution (24 pts) is HIGHER than this model's (15 pts): FUNDA understates OpenAI's level in Azure and overstates its FY27 growth contribution.
A13: Source | B13: Datapoint | F13: How it relates
A14: MS (Weiss), May-2025 (S18) | B14: OpenAI explains 49% of CY25 and 100%+ of CY26 Azure AI growth | F14: Share of Azure AI growth, not total Azure growth: direction agrees, not comparable in level.
A15: UBS (Keirstead), 2025-09-02 (S9) | B15: ~$18.6bn Azure AI run-rate Jun-25; training spend off-P&L, inference + rev share in Azure | F15: G3; training clause → FY25 back-cast lever (default 0).
A16: UBS (Keirstead), 2026-07-26 (S19) | B16: "a strong majority of Microsoft's AI revenues are derived from OpenAI and selling access to OpenAI models/products" | F16: Includes Azure OpenAI Service and Copilots → not a test of OpenAI-as-customer alone; G5 replaces it.
A17: UBS 2026-07-30 (S22) / JPM 2026-08-13 (S23) | B17: $24bn = ~7% of Microsoft revenue, "company-wide, not just Azure"; ~45% of $625bn RPO ≈ $281bn | F17: Hence the Azure-booked share lever (default 90%).
A18: Microsoft F4Q26 call, 2026-07-29 (S5) | B18: Bookings +18% ex-OpenAI vs +10% incl.; RPO +25% ex-OpenAI; all sequential RPO growth from non-frontier customers | F18: OpenAI backlog drawing down; ex-OpenAI RPO +25% = non-OpenAI growth proxy.
A19: Morgan Stanley, 2026-10-19 (S25) | B19: FY27E Azure $147.2bn, +44.4% (new definition) | F19: G10; Street-implied non-OpenAI growth diagnostic.

Sheet Sources
A1: Sources — every datapoint attributed (who · what · date · where on disk)
A2: Paths relative to E:\Wiki Felipe empresas. Journalism and broker relays are PARTIAL; filings and management on calls are HARD.
A4: ID | B4: Source (who · document · date) | C4: Datapoints used | D4: Tag | E4: Location on disk | F4: Role in the model
A5: S1 | B5: Microsoft Form 10-K FY26, related-party note (ASC 850), filed 2026-07-29 | C5: "revenue from commercial arrangements with OpenAI, inclusive of revenue-sharing payments, of $24.1 billion"; A/R $6.0bn; ~25% as-converted interest; $13.0bn funding commitment ($11.6bn funded Sep-25 → $11.9bn Jun-26 per 10-Qs/10-K) | D5: HARD / ANCHOR | E5: MSFT\MSFT_10-K_2026-07-29_0001193125-26-323660.html | F5: Calibration anchor
A6: S2 | B6: Microsoft "FY27 Segments and Investor Metrics" (8-K Ex.99.1), 2026-09-02/03 | C6: Restated Azure FY25 $72,610m / FY26 $101,938m and quarters (p.17); F1Q27 Azure guide 44-45% cc (p.21) | D6: HARD | E6: relatórios bons\20260903_Microsoft_FY27_Segments_and_Investor_Metrics.html (image deck; p017/p021 in _assets); _wiki\MSFT.md 09-03 block | F6: Azure base; G12
A7: S3 | B7: Microsoft F2Q26 earnings call, 2026-01-28 (Amy Hood) | C7: Commercial RPO $625bn; "Approximately 45% of our commercial RPO balance is from OpenAI"; non-OpenAI RPO +28% | D7: HARD | E7: MSFT\transcripts\MSFT_Q2-FY26-earnings_2026-01-28.md | F7: G8
A8: S4 | B8: Microsoft F1Q26 earnings call, 2025-10-29 | C8: "OpenAI has contracted an incremental $250 billion of Azure services" | D8: HARD | E8: MSFT\transcripts\MSFT_Q1-FY26-earnings_2025-10-29.md | F8: Terminal-share numerator
A9: S5 | B9: Microsoft F4Q26 earnings call, 2026-07-29 | C9: Cloud revenue >$214bn, "nearly 90% from customers outside of Frontier model companies"; RPO $678bn, +25% ex-OpenAI; bookings +18% ex-OpenAI | D9: HARD | E9: MSFT\transcripts\MSFT_Q4-FY26-earnings_2026-07-29.md | F9: G4; non-OpenAI growth proxy
A10: S6 | B10: Microsoft IR (Jonathan Nielsen) relayed by UBS · Karl Keirstead, F3Q26 recap call, 2026-04-30 | C10: OpenAI→Microsoft rev share "does land in Azure"; Microsoft→OpenAI rev share was a COGS item, now removed; capacity-constrained so losing some OpenAI spend matters less | D10: PARTIAL (mgmt via broker) | E10: relatórios bons\2026_04_30_msft_ubs_recap_30_par_2026.html | F10: Channel map; backfill
A11: S7 | B11: Microsoft IR investor call, 2026-05-18 (IR speaker unlabelled "Speaker 2" in the machine transcript) | C11: "we continue to get a revenue share from OpenAI, the percentage stays the same. There's a cap"; cap size not disclosed; IP royalty-free through 2032 | D11: HARD (mgmt, machine transcript) | E11: relatórios bons\2026_05_18_msft_ir_call_18_may_26.html | F11: Rate unchanged; cap exists
A12: S8 | B12: The Information · Sri Muppidi & Aaron Holmes, "OpenAI to Save $97 Billion Through 2030 in Latest Microsoft Deal", 2026-05-11, relayed by @wallstengine 2026-05-12 | C12: Cap $38bn vs $135bn max; Microsoft ~$6bn (vs $4bn planned) of OpenAI's ~$30bn 2026 revenue | D12: PARTIAL (journalism; not on disk) | E12: _briefings\by-ticker\MSFT.md lines ~693-722 | F12: Cap size and window; G6; G7
A13: S9 | B13: UBS · Karl Keirstead, OpenAI deep-dive, 2025-09-02 | C13: ~20% rev share; Azure AI run-rate ~$18.6bn Jun-25, substantially all OpenAI-tied; "OpenAI's training supercluster spend is off-P&L (netted against MSFT's equity stake...), while inference compute and the rev-share land in reported Azure" | D13: PARTIAL | E13: _wiki\MSFT.md line 22 (primary not on disk) | F13: Rate; FY25 training lever; G3
A14: S10 | B14: SemiAnalysis, "Amazon's AI Resurgence: AWS & Anthropic's Multi-Gigawatt Trainium Expansion", 2025-09-03 | C14: "As of Q2 2025 (June 2025), all of OpenAI's >$10B cloud spending is booked by Azure" | D14: PARTIAL | E14: relatórios bons\2025_09_03_ENC_Amazons_AI_Resurgence_AWS_Anthropics_Multi-Gigawatt_Trainium_Expansion_email.html | F14: FY25 share; G3c
A15: S11 | B15: Wells Fargo Securities · Ken Gawrelski (w/ Morrissey, Umansky), OpenAI & Anthropic model workbook, 2026-07-31 | C15: OpenAI quarterly revenue/compute/recognised Azure-API/Azure API gross sales 1Q24-2Q26E; 2023-30 annual lines; 1Q26 internal plan; training plan per WSJ 2026-04-05; inference per The Information 2026-02-24; hosting; WSJ 2026-07-22 "$750B compute through 2030" memo | D15: PARTIAL | E15: _inbox\_done\WFS_Distribution_OpenAi and Anthropic Models_073126.xlsx (sheet OpenAI PnL) | F15: Revenue & compute halves; plan; Base
... A30: S26 | B30: Microsoft F3Q26 earnings call, 2026-04-29 (Amy Hood) | C30: "having the revenue share exist through 2030. And the predictability of that is a real positive for us" | D30: HARD | E30: MSFT\transcripts\MSFT_Q3-FY26-earnings_2026-04-29.md | F30: Rev share through 2030
