Workbook

Sheet README
A1: UBS server CPU x DRAM note (26-Oct-2026) — data + DRAM-CPU link
A3: Source | B3: UBS Global Research (Timothy Arcuri, Seth Cho), 'US Semiconductors: $210B Server CPU TAM By C2030; Gated By Memory Supply', 26-Oct-2026. Page refs are to the PDF (39 pp; disclosures from p.28).
A4: Ratings in note | B4: AMD Buy (CBE) US$516.79; ARM Buy US$210.33; INTC Neutral US$86.96 (PT cut $103 -> $100, SOTP); MU Buy US$877.55 — prices 23-Oct-2026 (p.29). UBS: 'we continue to believe MU is the best way to play server CPU demand'.
A5: What the note says | B5: C2030 server-CPU TAM raised ~$175B -> ~$208B (37MM AI CPUs + 30MM traditional = 67MM units, ~77EB DRAM). 'Unconstrained' demand = ~150MM CPUs / $548B / 282EB DRAM, but memory supply caps it; CPU:GPU attach stays ~0.83:1 in C2030.
A6: Colour code | B6: Blue text = number as printed in the note (or a cross-check source) · Black = formula · Green = link to another sheet · Yellow fill = key lever on the link sheet. Tags on the link sheet: HARD (green) printed in a source, PARTIAL/ANCHOR (blue) range sourced or calibration anchor, ESTIMATE (amber) house assumption, DERIVED (white) arithmetic.
A7: Units | B7: EB = exabytes (1 EB = 1e18 bytes = 1,000,000 TB). 1MM CPUs x 1 TB/CPU = 1 EB, so 'EB per MM units' = 'TB per CPU'. 1Gb-equivalent: 1 EB = 8,000 million Gb (8bn Gb).
A8: Sheet map | B8: DRAM_CPU_Link = the relationship model (start here) · Report_Tieouts = internal arithmetic checks of every table (also validates the transcription) · Cross_Check = independent server-DRAM / CPU anchors (Bernstein, UBS memory team, JPM, Mizuho) · Fig* sheets = one per figure, as printed.
A9: Chart data | B9: Figs 9, 12, 17, 18, 20, 21 carry printed data labels -> transcribed. Figs 25-31 (Mercury/UBSe unit + mix history, 1Q19/1Q21-2Q26; Fig 27 1Q08-2Q26) are unlabeled stacked/area charts: values were extracted from the PDF's vector geometry and cross-checked by pixel measurement (+/-0.01MM, +/-0.05pp; labels +/-0.5pp). Fig 27 quarter mapping confirmed by wiki anchors (Intel x86 revenue share 55.4% 2Q26; AMD 41.3% 4Q25, 39.4% 1Q25). Fig 26 shares match Fig 25 units within 0.11pp.
A10: Model basis | B10: DRAM_CPU_Link runs C2030E on UBS's UNROUNDED standalone count: Fig 11's 0.33 attach x 44MM = 14.5MM (printed '~15'), which at 29EB gives 2.0TB/CPU and reproduces the printed $208B TAM, $160B AI-CPU $, $4,378 ASP and 0.83 attach exactly. Reviewed by an independent skeptic pass (transcription verified against 300-dpi renders; calibration claim downgraded to an identity; scenarios added).
A11: Not tabulated | B11: Fig 13/14 (AMD+ARM and INTC+NVDA management quotes — text exhibits), Fig 22 (ex-server desktop/notebook/gaming roadmap Gantt). Fig 23 server roadmap transcribed with approximate quarters read off the Gantt bars.
A12: Transcription | B12: All tables are images in the PDF (no text layer). Read from 300+ dpi renders; every arithmetic identity in the note is re-computed on Report_Tieouts — rows that do not tie are either rounding (|diff| <= rounding of the printed figure) or a flagged inconsistency in the note itself.

Sheet Summary
A1: DRAM <-> server CPU: what the UBS note implies (C2030E unless stated)
A2: Every number below is a live link into DRAM_CPU_Link / Report_Tieouts / Cross_Check — change a yellow lever there and this page moves.
A4: Relationship | B4: Value | C4: Unit | D4: Read-across
A5: 1. DRAM per CPU shipped (UBS C2030E base, Fig 8 implied)
A6: traditional CPU | B6: =DRAM_CPU_Link!D13 -> 0.5 | C6: TB | D6: 0.5TB in every year — Fig 5 / p.6 / Fig 15 say ~1TB by C2030E
A7: AI head-node CPU | B7: =DRAM_CPU_Link!D14 -> 1.5 | C7: TB | D7: 1.0TB today -> 1.5TB (low end of Fig 5)
A8: AI standalone CPU | B8: =DRAM_CPU_Link!D15 -> 1.9972452 | C8: TB | D8: 29EB / 14.5MM; 4x a traditional CPU (low end of Fig 5's 2-3TB)
A9: blended, C2025 | B9: =DRAM_CPU_Link!B16 -> 0.60869565 | C9: TB | D9: on UBS's 23MM base (~0.4-0.47TB on the ~30MM in Fig 25 / Bernstein)
A10: blended, C2030E | B10: =DRAM_CPU_Link!D16 -> 1.1492537 | C10: TB | D10: mix shift alone ~doubles DRAM per new CPU
A11: 2. The identity
A12: DRAM for CPUs C2030E = 30MM x 0.5 + 22MM x 1.5 + 14.5MM x 2.0 | B12: =DRAM_CPU_Link!D22 -> 77 | C12: EB | D12: Equals Fig 7 supply (69EB server + 7EB CXL). UBS sized the base so CPU DRAM = its supply estimate (an identity, not proof that memory set the count)
A13: unconstrained need, 147MM CPUs on UBS's TB/CPU | B13: =DRAM_CPU_Link!F22 -> 238 | C13: EB | D13: printed 282EB is on 169MM CPUs, inconsistent with Fig 4 / the text (147-150MM); at Fig 5 midpoints ~306EB (~4x). Supply covers ~1/4-1/3
A14: 3. Exchange rates at the margin (C2030E)
A15: AI standalone CPUs per +1EB of DRAM | B15: =DRAM_CPU_Link!B45 -> 0.50068966 | C15: MM
A16: CPU TAM per +1EB of DRAM (standalone) | B16: =DRAM_CPU_Link!B46 -> 2.1144124 | C16: $B | D16: vs $3.0B (head-node) / $3.2B (traditional): standalone is the least TAM-dense use of DRAM
A17: 1MM AI CPUs as % of C2030E server DRAM | B17: =DRAM_CPU_Link!B47 -> 0.028945582 | C17: %
A18: -0.1TB de-spec on all AI CPUs -> extra CPU TAM | B18: =DRAM_CPU_Link!B52 -> 7.7218341 | C18: $B
A19: 4. What the ~$208B needs (scenarios, CPU TAM $B)
A20: UBS base | B20: =DRAM_CPU_Link!G112 -> 208.05796 | C20: $B | D20: every class at/below the LOW END of Fig 5, and the HIGHER (99EB) of UBS's two supply bases
A21: supply on Fig 6 vendor-capacity basis (66EB) | B21: =DRAM_CPU_Link!G113 -> 184.79942 | C21: $B
A22: traditional CPUs at Fig 5's ~1TB | B22: =DRAM_CPU_Link!G115 -> 176.34177 | C22: $B
A23: all classes at Fig 5 midpoints | B23: =DRAM_CPU_Link!G120 -> 161.0982 | C23: $B
A24: head nodes at Vera's post-cut 768GB | B24: =DRAM_CPU_Link!G117 -> 242.10846 | C24: $B | D24: de-spec is the upside lever: memory per CPU, not CPU demand, sets the unit count
A25: 5. Dollars and watts
A26: DRAM $ per standalone AI CPU / its $4.2K ASP (at $12K/TB) | B26: =DRAM_CPU_Link!D63 -> 5.6753356 | C26: x | D26: 4.7-5.7x across $10-12K/TB: memory is the bigger dollar pool (UBS: MU is the best way to play CPU demand)
A27: C2030E DRAM bill for CPUs at $10K/TB (Fig 15's implied price) | B27: =DRAM_CPU_Link!C67 -> 770 | C27: $B | D27: $385B at $5K/TB to $1.6T at UBS's 2027E DDR ASP — vs a ~$208B CPU TAM
A28: DRAM per GW of CPU+DIMM power — traditional / AI (Fig 15 spec) | B28: =DRAM_CPU_Link!B78 -> 2.7027027 | C28: EB/GW | D28: 2.70 vs 2.90 on Fig 15's illustrative 1TB/2TB spec; 1.35 vs 2.90 on Fig 8's 0.5TB
A29: CPU-side DRAM per accelerator, C2030E | B29: =DRAM_CPU_Link!D24 -> 1.4090909 | C29: TB/GPU | D29: 1.8-4.9x the GPU's own HBM, depending on generation (Feynman 768GB -> VR200 288GB)
A30: 6. Checks
A31: Report tie-outs | B31: =Report_Tieouts!C97 -> 78 OK / 12 FLAG | D31: FLAGs = inconsistencies inside the note itself (transcription re-read for each)

Sheet DRAM_CPU_Link
A1: DRAM <-> server CPU: the relationship in UBS's 26-Oct-2026 framework (live model)
A2: Identity: DRAM for CPUs (EB) = SUM over CPU types [ units (MM) x DRAM per CPU (TB) ]. Supply-gated: standalone AI CPUs = (DRAM available for CPUs - traditional EB - head-node EB) / TB per standalone CPU. Blue = UBS as printed (linked from Fig sheets in green), yellow = levers you can change.
A4: A. Units and DRAM intensity, as printed (Fig 8 / Fig 10-11)
A5: Line | B5: C2025 | C5: C2027E | D5: C2030E Base | E5: C2030E Unconstr. (as printed) | F5: C2030E Unconstr. (corrected) | G5: Tag | H5: Source / note
A6: Traditional CPUs (MM) | B6: =Fig08_09_DRAM_Demand!B5 -> 20 | C6: =Fig08_09_DRAM_Demand!D5 -> 26 | D6: =Fig08_09_DRAM_Demand!F5 -> 30 | E6: =Fig08_09_DRAM_Demand!H5 -> 30 | F6: =E6 -> 30 | G6: HARD | H6: Fig 8 (p.7); corrected column = Fig 4
A7: AI head-node CPUs (MM) | B7: =Fig08_09_DRAM_Demand!B6 -> 3 | C7: =Fig08_09_DRAM_Demand!D6 -> 11 | D7: =Fig08_09_DRAM_Demand!F6 -> 22 | E7: =Fig08_09_DRAM_Demand!H6 -> 22 | F7: =E7 -> 22 | G7: HARD | H7: Fig 8 (p.7); corrected column = Fig 4
A8: AI standalone CPUs (MM) | B8: =Fig08_09_DRAM_Demand!B7 -> 0 | C8: =Fig08_09_DRAM_Demand!D7 -> 5 | D8: =Fig10_12_TAM!D34*D10 -> 14.52 | E8: =Fig08_09_DRAM_Demand!H7 -> 117 | F8: =Fig04_Unconstrained!D9 -> 95 | G8: HARD | H8: C2030E base = Fig 11 attach 0.33 x 44 = 14.5MM (printed '~15'): the unrounded value reproduces $208B TAM, $160B AI $, $4,378 ASP, 0.83 attach and 29EB at 2.0TB. Unconstrained: Fig 8 prints 117 (equal to Fig 4's total AI CPUs 22+95; mechanism not provable); corrected column uses Fig 4's 95
A9: Total CPUs (MM) | B9: =SUM(B6:B8) -> 23 | C9: =SUM(C6:C8) -> 42 | D9: =SUM(D6:D8) -> 66.52 | E9: =SUM(E6:E8) -> 169 | F9: =SUM(F6:F8) -> 147 | G9: DERIVED | H9: Printed: 23 / 41 / 67 / 169; Fig 4 + text: ~147-150MM unconstrained
A10: Accelerators (MM) | B10: =Fig10_12_TAM!B11 -> 9 | C10: =Fig10_12_TAM!C11 -> 29 | D10: =Fig10_12_TAM!D11 -> 44 | E10: =Fig10_12_TAM!D11 -> 44 | F10: =Fig10_12_TAM!D11 -> 44 | G10: HARD | H10: Fig 10 / Fig 4 (~44MM in C2030, ex-China)
A12: DRAM per CPU (TB) — implied by Fig 8 (EB / MM units)
A13: TB per traditional CPU | B13: =Fig08_09_DRAM_Demand!C12 -> 0.5 | C13: =Fig08_09_DRAM_Demand!E12 -> 0.46153846 | D13: =Fig08_09_DRAM_Demand!G12 -> 0.5 | E13: =Fig08_09_DRAM_Demand!I12 -> 0.5 | F13: =E13 -> 0.5 | G13: HARD | H13: Implied 0.5TB in every year incl. C2030E (also in the unconstrained column) — while Fig 5, the p.6 text and Fig 15/16 all use ~1.0TB by C2030E (see section D/G2)
A14: TB per head-node CPU | B14: =Fig08_09_DRAM_Demand!C13 -> 1 | C14: =Fig08_09_DRAM_Demand!E13 -> 1 | D14: =Fig08_09_DRAM_Demand!G13 -> 1.5 | E14: =Fig08_09_DRAM_Demand!I13 -> 1.5 | F14: =E14 -> 1.5 | G14: HARD | H14: 1.0 / 1.0 / 1.5TB — at the LOW END of Fig 5's ~1-1.5TB (25/27) and ~1.5-2TB (30E) ranges
A15: TB per standalone CPU | B15: =Fig08_09_DRAM_Demand!C14 | C15: =Fig08_09_DRAM_Demand!E14 -> 1.4 | D15: =Fig08_09_DRAM_Demand!G7/D8 -> 1.9972452 | E15: =Fig08_09_DRAM_Demand!I14 -> 2 | F15: =E15 -> 2 | G15: HARD | H15: 1.4 (2027E, below Fig 5's 1.5-2) / 2.0 (C2030E = 29EB / 14.5MM; unconstrained 234/117 = 2.0) — LOW END of Fig 5's ~2-3TB
A16: Blended TB per CPU shipped (all CPUs) | B16: =Fig08_09_DRAM_Demand!C9/Fig08_09_DRAM_Demand!B8 -> 0.60869565 | C16: =Fig08_09_DRAM_Demand!E9/Fig08_09_DRAM_Demand!D8 -> 0.70731707 | D16: =Fig08_09_DRAM_Demand!G9/Fig08_09_DRAM_Demand!F8 -> 1.1492537 | E16: =Fig08_09_DRAM_Demand!I9/Fig08_09_DRAM_Demand!H8 -> 1.6686391 | F16: =F22/F9 -> 1.6190476 | G16: DERIVED | H16: Printed EB / printed units: 0.6 -> 0.7 -> 1.15TB per CPU shipped — mix alone roughly doubles DRAM per new CPU by C2030E (a flow, not the installed fleet)
A17: Blended TB per AI CPU (head-node + standalone) | B17: =IFERROR((B20+B21)/(B7+B8),"") -> 1 | C17: =IFERROR((C20+C21)/(C7+C8),"") -> 1.125 | D17: =IFERROR((D20+D21)/(D7+D8),"") -> 1.6976999 | E17: =IFERROR((E20+E21)/(E7+E8),"") -> 1.9208633 | F17: =IFERROR((F20+F21)/(F7+F8),"") -> 1.9059829 | G17: DERIVED | H17: C2030E base ~1.70TB vs Fig 5's 'Blended AI CPU ~2-2.5TB' — below UBS's own stated range
A18: B. DRAM demand identity (EB = MM x TB) — recomputed
A19: Traditional EB | B19: =IF(B13="",0,B6*B13) -> 10 | C19: =IF(C13="",0,C6*C13) -> 12 | D19: =IF(D13="",0,D6*D13) -> 15 | E19: =IF(E13="",0,E6*E13) -> 15 | F19: =IF(F13="",0,F6*F13) -> 15 | G19: DERIVED
A20: Head-node EB | B20: =IF(B14="",0,B7*B14) -> 3 | C20: =IF(C14="",0,C7*C14) -> 11 | D20: =IF(D14="",0,D7*D14) -> 33 | E20: =IF(E14="",0,E7*E14) -> 33 | F20: =IF(F14="",0,F7*F14) -> 33 | G20: DERIVED
A21: Standalone EB | B21: =IF(B15="",0,B8*B15) -> 0 | C21: =IF(C15="",0,C8*C15) -> 7 | D21: =IF(D15="",0,D8*D15) -> 29 | E21: =IF(E15="",0,E8*E15) -> 234 | F21: =IF(F15="",0,F8*F15) -> 190 | G21: DERIVED
A22: Total DRAM for CPUs (EB) | B22: =SUM(B19:B21) -> 13 | C22: =SUM(C19:C21) -> 30 | D22: =SUM(D19:D21) -> 77 | E22: =SUM(E19:E21) -> 282 | F22: =SUM(F19:F21) -> 238 | G22: DERIVED | H22: Printed: 14 / 29 / 77 / 282 EB. Corrected unconstrained (147MM, Fig 4) = ~238EB on UBS's own TB/CPU = 3.1x base (not 3.5-3.7x); at Fig 5 midpoints the same 147MM need ~306EB (~4x, the figure title)
A23: Printed implied DRAM (EB) | B23: =Fig08_09_DRAM_Demand!C9 -> 14 | C23: =Fig08_09_DRAM_Demand!E9 -> 29 | D23: =Fig08_09_DRAM_Demand!G9 -> 77 | E23: =Fig08_09_DRAM_Demand!I9 -> 282 | G23: HARD | H23: Fig 8
A24: Head-node + standalone DRAM per accelerator (TB/GPU) | B24: =(B20+B21)/B10 -> 0.33333333 | C24: =(C20+C21)/C10 -> 0.62068966 | D24: =(D20+D21)/D10 -> 1.4090909 | E24: =(E20+E21)/E10 -> 6.0681818 | F24: =(F20+F21)/F10 -> 5.0681818 | G24: DERIVED | H24: Conventional DRAM pulled by AI CPUs per accelerator: 0.33 -> 0.62 -> 1.41TB (base). vs HBM per GPU: VR200 288GB / VR300 384-512GB / Feynman 768GB (Cross_Check) -> ~1.8-4.9x depending on GPU generation. The 44MM accelerators include TPU/Trainium
A26: C. Supply gate (Fig 6-7): how many CPUs the DRAM supply can carry
A27: Line | B27: C2025 | C27: C2027E | D27: C2030E Base | E27: C2030E Unconstr. (as printed) | F27: C2030E Unconstr. (corrected) | G27: Tag | H27: Source / note
A28: Server DRAM available (EB) | B28: =Fig06_07_DRAM_Supply!B19 -> 11 | C28: =Fig06_07_DRAM_Supply!C19 -> 27 | D28: =Fig06_07_DRAM_Supply!D19 -> 69 | E28: =Fig06_07_DRAM_Supply!D19 -> 69 | F28: =Fig06_07_DRAM_Supply!D19 -> 69 | G28: HARD | H28: Fig 7: non-HBM total on 'MU share' basis (36/54/99) minus non-server (26/27/30)
A29: Old DDR reuse via CXL (EB) | B29: 0 | C29: =Fig06_07_DRAM_Supply!C20 -> 2 | D29: =Fig06_07_DRAM_Supply!D20 -> 7 | E29: =Fig06_07_DRAM_Supply!D20 -> 7 | F29: =Fig06_07_DRAM_Supply!D20 -> 7 | G29: HARD | H29: Fig 7 (7EB = 10% of 2030 server DRAM vs text's +6-8%)
A30: DRAM available for CPUs (EB) — lever | B30: =Fig06_07_DRAM_Supply!B21 -> 11 | C30: =Fig06_07_DRAM_Supply!C21 -> 29 | D30: =Fig06_07_DRAM_Supply!D21 -> 77 | E30: =Fig06_07_DRAM_Supply!D21 -> 77 | F30: =Fig06_07_DRAM_Supply!D21 -> 77 | G30: HARD | H30: Fig 7 bottom line 11 / 29 / 77 (server + CXL = 11 / 29 / 76 — rounding). Overwrite to test other supply
A31: Coverage: DRAM available / DRAM demanded | B31: =B30/B22 -> 0.84615385 | C31: =C30/C22 -> 0.96666667 | D31: =D30/D22 -> 1 | E31: =E30/E22 -> 0.27304965 | F31: =F30/F22 -> 0.32352941 | G31: DERIVED | H31: C2025 85%: the note's own 2025 numbers disagree (Fig 8 demand 14EB vs Fig 7 supply 11EB; inventory not modelled). C2030E base = 100% by construction; unconstrained ~27% (printed) / ~32% (corrected) covered
A32: Standalone CPUs that fit = (avail - trad EB - head EB) / TB per standalone | C32: =MAX(0,(C30-C19-C20)/C15) -> 4.2857143 | D32: =MAX(0,(D30-D19-D20)/D15) -> 14.52 | E32: =MAX(0,(E30-E19-E20)/E15) -> 14.5 | F32: =MAX(0,(F30-F19-F20)/F15) -> 14.5 | G32: DERIVED | H32: IDENTITY, not a calibration: Fig 8's C2030E column sums to Fig 7's 77EB, so this returns UBS's 14.5MM by construction. It shows UBS sized the base so CPU DRAM = its supply estimate; it cannot show whether memory or demand set the count (the 0.33 standalone attach is unchanged from UBS's pre-memory framework). Use it as the flex tool
A33: Memory-gated total CPUs (MM) | C33: =C6+C7+C32 -> 41.285714 | D33: =D6+D7+D32 -> 66.52 | E33: =E6+E7+E32 -> 66.5 | F33: =F6+F7+F32 -> 66.5 | G33: DERIVED
A34: Memory-gated CPU:GPU attach (AI CPUs / accelerators) | C34: =(C7+C32)/C10 -> 0.5270936 | D34: =(D7+D32)/D10 -> 0.83 | E34: =(E7+E32)/E10 -> 0.82954545 | F34: =(F7+F32)/F10 -> 0.82954545 | G34: DERIVED | H34: UBS: 0.83:1 in C2030 'unchanged from our prior estimate' — practitioners want 3-4:1
A35: ASP traditional ($) | B35: =Fig10_12_TAM!B8 -> 1200 | C35: =Fig10_12_TAM!C8 -> 1348 | D35: =Fig10_12_TAM!D8 -> 1606 | E35: =Fig10_12_TAM!D8 -> 1606 | F35: =Fig10_12_TAM!D8 -> 1606 | G35: HARD | H35: Fig 10
A36: ASP head-node ($) | B36: =Fig10_12_TAM!B32 -> 2430 | C36: =Fig10_12_TAM!C32 -> 3160 | D36: =Fig10_12_TAM!D32 -> 4480 | E36: =Fig10_12_TAM!D32 -> 4480 | F36: =Fig10_12_TAM!D32 -> 4480 | G36: HARD | H36: Fig 11
A37: ASP standalone ($) | B37: 0 | C37: =Fig10_12_TAM!C35 -> 2850 | D37: =Fig10_12_TAM!D35 -> 4223 | E37: =Fig10_12_TAM!D35 -> 4223 | F37: =Fig10_12_TAM!D35 -> 4223 | G37: HARD | H37: Fig 11 (no standalone in 2025)
A38: Memory-gated CPU TAM ($B) | C38: =(C6*C35+C7*C36+C32*C37)/1000 -> 82.022286 | D38: =(D6*D35+D7*D36+D32*D37)/1000 -> 208.05796 | E38: =(E6*E35+E7*E36+E32*E37)/1000 -> 207.9735 | F38: =(F6*F35+F7*F36+F32*F37)/1000 -> 207.9735 | G38: DERIVED | H38: C2030E base reproduces $208.0B on the unrounded 14.5MM; C2027E $82B vs printed $83B (rounded 2027 inputs). Unconstrained columns are capped by the same 77EB
A40: D. Rules of thumb (C2030E base) — the DRAM<->CPU exchange rates
A41: Rule | B41: Value | C41: Unit | G41: Tag | H41: How it is computed / caveat
A42: DRAM per 1MM standalone AI CPUs | B42: =D15 -> 1.9972452 | C42: EB | G42: DERIVED | H42: TB per standalone CPU (1MM x 1TB = 1EB)
A43: DRAM per 1MM head-node CPUs | B43: =D14 -> 1.5 | C43: EB | G43: DERIVED
A44: DRAM per 1MM traditional CPUs | B44: =D13 -> 0.5 | C44: EB | G44: DERIVED
A45: Standalone AI CPUs supported per +1EB of server DRAM | B45: =1/D15 -> 0.50068966 | C45: MM CPUs | G45: DERIVED | H45: Inverse of TB per standalone CPU
A46: CPU TAM unlocked per +1EB of server DRAM | B46: =1/D15*D37/1000 -> 2.1144124 | C46: $B | G46: DERIVED | H46: x standalone ASP $4,223
A47: 1MM AI CPUs as % of C2030E server DRAM | B47: =D15/D28 -> 0.028945582 | C47: % | G47: DERIVED | H47: vs 69EB server DRAM (Fig 7)
A48: 1MM AI CPUs as % of C2030E non-HBM DRAM (MU-share basis) | B48: =D15/Fig06_07_DRAM_Supply!D16 -> 0.020174194 | C48: % | G48: DERIVED | H48: vs 99EB
A49: CPU TAM per EB of DRAM for CPUs (average) | B49: =D38/D30 -> 2.7020514 | C49: $B / EB | G49: DERIVED | H49: $208B / 77EB
A50: Each -0.1TB de-spec on all AI CPUs frees | B50: =0.1*(D7+D8) -> 3.652 | C50: EB | G50: DERIVED | H50: 36.5MM AI CPUs x 0.1TB
A51: ... which supports extra standalone CPUs | B51: =B50/D15 -> 1.8285186 | C51: MM CPUs | G51: DERIVED | H51: freed EB / TB per standalone
A52: ... worth in CPU TAM | B52: =B51*D37/1000 -> 7.7218341 | C52: $B | G52: DERIVED
A53: If traditional CPUs go 0.5 -> 1.0TB (Fig 5 C2030E), standalone CPUs lost | B53: =D6*(1-D13)/D15 -> 7.5103448 | C53: MM CPUs | G53: DERIVED | H53: 30MM x +0.5TB = +15EB crowds out standalone AI CPUs
A54: ... TAM lost | B54: =B53*D37/1000 -> 31.716186 | C54: $B | G54: DERIVED | H54: ~$208B -> ~$176B (near UBS's prior ~$175B only by coincidence — that TAM used a $3.8K ASP and different inputs)
A55: CPU TAM per EB of DRAM — traditional CPUs | B55: =D35/D13/1000 -> 3.212 | C55: $B / EB | G55: DERIVED | H55: ASP / TB per CPU
A56: CPU TAM per EB of DRAM — head-node CPUs | B56: =D36/D14/1000 -> 2.9866667 | C56: $B / EB | G56: DERIVED
A57: CPU TAM per EB of DRAM — standalone AI CPUs | B57: =D37/D15/1000 -> 2.1144124 | C57: $B / EB | G57: DERIVED | H57: Under a binding memory cap the standalone AI CPU is the LEAST TAM-dense use of DRAM — the marginal EB buys the fewest CPU dollars
A59: E. Memory $ attached to each CPU $ (the note gives no C2030 DRAM price — test a range)
A60: Memory price ($ per TB) — lever | B60: =Fig15_18_Power!B16 -> 12000 | G60: HARD | H60: Fig 15 label '$12K/1TB' (= $12/GB) — but Fig 15's own printed memory capex ties at $10K/TB with traditional at 0.5TB (row below)
A61: Traditional CPU: DRAM $ per CPU (C2030E) | B61: =D13*$B$60 -> 6000 | C61: DRAM $ / CPU $ | D61: =B61/D35 -> 3.73599 | G61: DERIVED | H61: TB/CPU x $/TB vs CPU ASP
A62: Head-node CPU: DRAM $ per CPU (C2030E) | B62: =D14*$B$60 -> 18000 | C62: DRAM $ / CPU $ | D62: =B62/D36 -> 4.0178571 | G62: DERIVED | H62: TB/CPU x $/TB vs CPU ASP
A63: Standalone AI CPU: DRAM $ per CPU (C2030E) | B63: =D15*$B$60 -> 23966.942 | C63: DRAM $ / CPU $ | D63: =B63/D37 -> 5.6753356 | G63: DERIVED | H63: TB/CPU x $/TB vs CPU ASP
A64: Fig 15 reconciliation: printed memory capex/GW at $10K/TB and Fig 8's TB (trad 0.5 / AI 2.0) | B64: =Fig15_18_Power!D11*0.5*10000/1000000000 -> 13.513514 | C64: =Fig15_18_Power!E11*2*10000/1000000000 -> 28.985507 | G64: DERIVED | H64: Gives $13.5B / $29.0B exactly as printed -> the Fig 15 '1TB' and '$12K' cells are the inconsistent ones; the capex row agrees with Fig 8
A65: 77EB C2030E DRAM bill at different prices | B65: $/TB | C65: DRAM $B | D65: x CPU TAM | E65: Standalone DRAM $ / ASP | G65: Tag | H65: Price source
A66: 77EB at | B66: 5000 | C66: =$D$22*1000000*B66/1000000000 -> 385 | D66: =C66/$D$38 -> 1.8504459 | E66: =$D$15*B66/$D$37 -> 2.3647232 | G66: ESTIMATE | H66: Illustrative trough-like price ($5/GB)
A67: 77EB at | B67: 10000 | C67: =$D$22*1000000*B67/1000000000 -> 770 | D67: =C67/$D$38 -> 3.7008918 | E67: =$D$15*B67/$D$37 -> 4.7294463 | G67: HARD | H67: Implied by Fig 15's printed memory capex (see reconciliation row)
A68: 77EB at | B68: =B60 -> 12000 | C68: =$D$22*1000000*B68/1000000000 -> 924 | D68: =C68/$D$38 -> 4.4410702 | E68: =$D$15*B68/$D$37 -> 5.6753356 | G68: HARD | H68: Fig 15 label $12K/TB (lever above)
A69: 77EB at | B69: 14280 | C69: =$D$22*1000000*B69/1000000000 -> 1099.56 | D69: =C69/$D$38 -> 5.2848735 | E69: =$D$15*B69/$D$37 -> 6.7536493 | G69: PARTIAL | H69: UBS memory team DDR ASP 2026E $1.785/Gb x 8,000 Gb/TB ('DRAM Model' row 12, client model 3-Jul-26)
A70: 77EB at | B70: 21328 | C70: =$D$22*1000000*B70/1000000000 -> 1642.256 | D70: =C70/$D$38 -> 7.8932621 | E70: =$D$15*B70/$D$37 -> 10.086963 | G70: PARTIAL | H70: UBS memory team DDR ASP 2027E $2.666/Gb x 8,000 (same source) — peak-cycle price, not a 2030 forecast
A71: At any plausible price the DRAM bill for CPUs ($385B-1.6T) is 2-8x the ~$208B CPU TAM — memory is the bigger dollar pool, which is UBS's 'MU is the best way to play server CPU demand'.
A73: F. Per-GW view (Fig 15's illustrative specs): DRAM per GW of CPU+DIMM power
A74: Line | B74: Traditional | C74: AI CPU | G74: Tag | H74: Note
A75: W per CPU incl. DIMMs | B75: =Fig15_18_Power!D10 -> 370 | C75: =Fig15_18_Power!E10 -> 690 | G75: HARD | H75: Fig 15: 250W + 8x15W / 450W + 16x15W
A76: TB per CPU (Fig 15 basis) | B76: =Fig15_18_Power!B7 -> 1 | C76: =Fig15_18_Power!C7 -> 2 | G76: HARD | H76: Fig 15 uses 1TB traditional (vs 0.5TB in Fig 8's C2030E base)
A77: GB per DIMM implied | B77: =B76*1000/Fig15_18_Power!B9 -> 125 | C77: =C76*1000/Fig15_18_Power!C9 -> 125 | G77: DERIVED | H77: 128GB-class RDIMMs
A78: DRAM per GW of CPU power (EB/GW) | B78: =1000/B75*B76 -> 2.7027027 | C78: =1000/C75*C76 -> 2.8985507 | G78: DERIVED | H78: 1GW/W x TB: 2.70 vs 2.90 EB/GW on Fig 15's 1TB/2TB spec — near-invariant there (125GB DIMMs at 15W each); mechanical, holds only on that spec
A79: DRAM per GW on Fig 8's base TB (trad 0.5TB / AI 2.0TB) | B79: =1000/B75*D13 -> 1.3513514 | C79: =1000/C75*D15 -> 2.8945582 | G79: DERIVED | H79: On the basis that drives the TAM, an AI CPU carries ~2.1x the DRAM per watt of a traditional CPU
A80: C2030E CPU GW (Fig 16) | B80: =Fig15_18_Power!D22 -> 11 | C80: =Fig15_18_Power!D26 -> 10 | G80: HARD | H80: Fig 16 (head-node GW 'captured in GW racks')
A81: DRAM implied by GW x EB/GW | B81: =B80*B78 -> 29.72973 | C81: =C80*C78 -> 28.985507 | G81: DERIVED | H81: vs Fig 8 base: traditional 15EB / standalone 29EB — standalone ties, traditional is 2x on the Fig 15 (1TB) basis
A83: G. Sensitivity — C2030E standalone AI CPUs supportable (MM), traditional & head-node held at the levers in section A/B
A84: DRAM available for CPUs (EB) \ TB per standalone CPU | B84: 1 | C84: 1.5 | D84: 2 | E84: 2.5 | F84: 3
A85: 55 | B85: =MIN($F$8,MAX(0,($A85-$D$19-$D$20)/B$84)) -> 7 | C85: =MIN($F$8,MAX(0,($A85-$D$19-$D$20)/C$84)) -> 4.6666667 | D85: =MIN($F$8,MAX(0,($A85-$D$19-$D$20)/D$84)) -> 3.5 | E85: =MIN($F$8,MAX(0,($A85-$D$19-$D$20)/E$84)) -> 2.8 | F85: =MIN($F$8,MAX(0,($A85-$D$19-$D$20)/F$84)) -> 2.3333333
A86: 60 | B86: =MIN($F$8,MAX(0,($A86-$D$19-$D$20)/B$84)) -> 12 | C86: =MIN($F$8,MAX(0,($A86-$D$19-$D$20)/C$84)) -> 8 | D86: =MIN($F$8,MAX(0,($A86-$D$19-$D$20)/D$84)) -> 6 | E86: =MIN($F$8,MAX(0,($A86-$D$19-$D$20)/E$84)) -> 4.8 | F86: =MIN($F$8,MAX(0,($A86-$D$19-$D$20)/F$84)) -> 4
A87: 66 | B87: =MIN($F$8,MAX(0,($A87-$D$19-$D$20)/B$84)) -> 18 | C87: =MIN($F$8,MAX(0,($A87-$D$19-$D$20)/C$84)) -> 12 | D87: =MIN($F$8,MAX(0,($A87-$D$19-$D$20)/D$84)) -> 9 | E87: =MIN($F$8,MAX(0,($A87-$D$19-$D$20)/E$84)) -> 7.2 | F87: =MIN($F$8,MAX(0,($A87-$D$19-$D$20)/F$84)) -> 6
A88: 77 | B88: =MIN($F$8,MAX(0,($A88-$D$19-$D$20)/B$84)) -> 29 | C88: =MIN($F$8,MAX(0,($A88-$D$19-$D$20)/C$84)) -> 19.333333 | D88: =MIN($F$8,MAX(0,($A88-$D$19-$D$20)/D$84)) -> 14.5 | E88: =MIN($F$8,MAX(0,($A88-$D$19-$D$20)/E$84)) -> 11.6 | F88: =MIN($F$8,MAX(0,($A88-$D$19-$D$20)/F$84)) -> 9.6666667
A89: 90 | B89: =MIN($F$8,MAX(0,($A89-$D$19-$D$20)/B$84)) -> 42 | C89: =MIN($F$8,MAX(0,($A89-$D$19-$D$20)/C$84)) -> 28 | D89: =MIN($F$8,MAX(0,($A89-$D$19-$D$20)/D$84)) -> 21 | E89: =MIN($F$8,MAX(0,($A89-$D$19-$D$20)/E$84)) -> 16.8 | F89: =MIN($F$8,MAX(0,($A89-$D$19-$D$20)/F$84)) -> 14
A90: 100 | B90: =MIN($F$8,MAX(0,($A90-$D$19-$D$20)/B$84)) -> 52 | C90: =MIN($F$8,MAX(0,($A90-$D$19-$D$20)/C$84)) -> 34.666667 | D90: =MIN($F$8,MAX(0,($A90-$D$19-$D$20)/D$84)) -> 26 | E90: =MIN($F$8,MAX(0,($A90-$D$19-$D$20)/E$84)) -> 20.8 | F90: =MIN($F$8,MAX(0,($A90-$D$19-$D$20)/F$84)) -> 17.333333
A91: 120 | B91: =MIN($F$8,MAX(0,($A91-$D$19-$D$20)/B$84)) -> 72 | C91: =MIN($F$8,MAX(0,($A91-$D$19-$D$20)/C$84)) -> 48 | D91: =MIN($F$8,MAX(0,($A91-$D$19-$D$20)/D$84)) -> 36 | E91: =MIN($F$8,MAX(0,($A91-$D$19-$D$20)/E$84)) -> 28.8 | F91: =MIN($F$8,MAX(0,($A91-$D$19-$D$20)/F$84)) -> 24
A92: Capped at the corrected unconstrained standalone demand (95MM). 66EB = Fig 7 server DRAM on the vendor-capacity basis (89-30+7); 77EB = UBS base.
A94: Total C2030E CPU TAM ($B) on the same grid
A95: DRAM available for CPUs (EB) \ TB per standalone CPU | B95: 1 | C95: 1.5 | D95: 2 | E95: 2.5 | F95: 3
A96: 55 | B96: =($D$6*$D$35+$D$7*$D$36+B85*$D$37)/1000 -> 176.301 | C96: =($D$6*$D$35+$D$7*$D$36+C85*$D$37)/1000 -> 166.44733 | D96: =($D$6*$D$35+$D$7*$D$36+D85*$D$37)/1000 -> 161.5205 | E96: =($D$6*$D$35+$D$7*$D$36+E85*$D$37)/1000 -> 158.5644 | F96: =($D$6*$D$35+$D$7*$D$36+F85*$D$37)/1000 -> 156.59367
A97: 60 | B97: =($D$6*$D$35+$D$7*$D$36+B86*$D$37)/1000 -> 197.416 | C97: =($D$6*$D$35+$D$7*$D$36+C86*$D$37)/1000 -> 180.524 | D97: =($D$6*$D$35+$D$7*$D$36+D86*$D$37)/1000 -> 172.078 | E97: =($D$6*$D$35+$D$7*$D$36+E86*$D$37)/1000 -> 167.0104 | F97: =($D$6*$D$35+$D$7*$D$36+F86*$D$37)/1000 -> 163.632
A98: 66 | B98: =($D$6*$D$35+$D$7*$D$36+B87*$D$37)/1000 -> 222.754 | C98: =($D$6*$D$35+$D$7*$D$36+C87*$D$37)/1000 -> 197.416 | D98: =($D$6*$D$35+$D$7*$D$36+D87*$D$37)/1000 -> 184.747 | E98: =($D$6*$D$35+$D$7*$D$36+E87*$D$37)/1000 -> 177.1456 | F98: =($D$6*$D$35+$D$7*$D$36+F87*$D$37)/1000 -> 172.078
A99: 77 | B99: =($D$6*$D$35+$D$7*$D$36+B88*$D$37)/1000 -> 269.207 | C99: =($D$6*$D$35+$D$7*$D$36+C88*$D$37)/1000 -> 228.38467 | D99: =($D$6*$D$35+$D$7*$D$36+D88*$D$37)/1000 -> 207.9735 | E99: =($D$6*$D$35+$D$7*$D$36+E88*$D$37)/1000 -> 195.7268 | F99: =($D$6*$D$35+$D$7*$D$36+F88*$D$37)/1000 -> 187.56233
A100: 90 | B100: =($D$6*$D$35+$D$7*$D$36+B89*$D$37)/1000 -> 324.106 | C100: =($D$6*$D$35+$D$7*$D$36+C89*$D$37)/1000 -> 264.984 | D100: =($D$6*$D$35+$D$7*$D$36+D89*$D$37)/1000 -> 235.423 | E100: =($D$6*$D$35+$D$7*$D$36+E89*$D$37)/1000 -> 217.6864 | F100: =($D$6*$D$35+$D$7*$D$36+F89*$D$37)/1000 -> 205.862
A101: 100 | B101: =($D$6*$D$35+$D$7*$D$36+B90*$D$37)/1000 -> 366.336 | C101: =($D$6*$D$35+$D$7*$D$36+C90*$D$37)/1000 -> 293.13733 | D101: =($D$6*$D$35+$D$7*$D$36+D90*$D$37)/1000 -> 256.538 | E101: =($D$6*$D$35+$D$7*$D$36+E90*$D$37)/1000 -> 234.5784 | F101: =($D$6*$D$35+$D$7*$D$36+F90*$D$37)/1000 -> 219.93867
A102: 120 | B102: =($D$6*$D$35+$D$7*$D$36+B91*$D$37)/1000 -> 450.796 | C102: =($D$6*$D$35+$D$7*$D$36+C91*$D$37)/1000 -> 349.444 | D102: =($D$6*$D$35+$D$7*$D$36+D91*$D$37)/1000 -> 298.768 | E102: =($D$6*$D$35+$D$7*$D$36+E91*$D$37)/1000 -> 268.3624 | F102: =($D$6*$D$35+$D$7*$D$36+F91*$D$37)/1000 -> 248.092
A104: C2030E CPU TAM ($B) at 77EB — traditional TB (rows) x head-node TB (cols); standalone TB held at the section-A lever
A105: TB per traditional CPU \ TB per head-node CPU | B105: 1 | C105: 1.5 | D105: 2
A106: 0.5 | B106: =($D$6*$D$35+$D$7*$D$36+MIN($F$8,MAX(0,($D$30-$D$6*$A106-$D$7*B$105)/$D$15))*$D$37)/1000 -> 231.3165 | C106: =($D$6*$D$35+$D$7*$D$36+MIN($F$8,MAX(0,($D$30-$D$6*$A106-$D$7*C$105)/$D$15))*$D$37)/1000 -> 208.05796 | D106: =($D$6*$D$35+$D$7*$D$36+MIN($F$8,MAX(0,($D$30-$D$6*$A106-$D$7*D$105)/$D$15))*$D$37)/1000 -> 184.79942
A107: 0.75 | B107: =($D$6*$D$35+$D$7*$D$36+MIN($F$8,MAX(0,($D$30-$D$6*$A107-$D$7*B$105)/$D$15))*$D$37)/1000 -> 215.4584 | C107: =($D$6*$D$35+$D$7*$D$36+MIN($F$8,MAX(0,($D$30-$D$6*$A107-$D$7*C$105)/$D$15))*$D$37)/1000 -> 192.19987 | D107: =($D$6*$D$35+$D$7*$D$36+MIN($F$8,MAX(0,($D$30-$D$6*$A107-$D$7*D$105)/$D$15))*$D$37)/1000 -> 168.94133
A108: 1 | B108: =($D$6*$D$35+$D$7*$D$36+MIN($F$8,MAX(0,($D$30-$D$6*$A108-$D$7*B$105)/$D$15))*$D$37)/1000 -> 199.60031 | C108: =($D$6*$D$35+$D$7*$D$36+MIN($F$8,MAX(0,($D$30-$D$6*$A108-$D$7*C$105)/$D$15))*$D$37)/1000 -> 176.34177 | D108: =($D$6*$D$35+$D$7*$D$36+MIN($F$8,MAX(0,($D$30-$D$6*$A108-$D$7*D$105)/$D$15))*$D$37)/1000 -> 153.08324
A110: G2. Scenarios — C2030E: the $208B needs every CPU class at the LOW END of UBS's own Fig 5 and the HIGHER (99EB 'MU share') of its two supply bases
...

Sheet Cross_Check
A1: Cross-check: independent anchors for server DRAM and DRAM-per-CPU
A2: Independent of the CPU note: other houses' / other UBS teams' server-DRAM models on P:\Felipe Monteiro\Memória and wiki-logged spec marks. Read the basis column before comparing.
A3: Source: UBS Global Research (Timothy Arcuri, Seth Cho), 'US Semiconductors: $210B Server CPU TAM By C2030; Gated By Memory Supply', 26-Oct-2026
A5: Series | B5: 2023 | C5: 2024 | D5: 2025 | E5: 2026E | F5: 2027E | G5: 2028E | H5: 2030E | I5: Unit | J5: Source / basis
A6: 1. Server DRAM (ex-HBM), EB
A7: UBS CPU note — Fig 7 server DRAM | D7: =Fig06_07_DRAM_Supply!B19 -> 11 | F7: =Fig06_07_DRAM_Supply!C19 -> 27 | H7: =Fig06_07_DRAM_Supply!D19 -> 69 | I7: EB | J7: UBS (Arcuri) 26-Oct-26, Fig 7 (ex-CXL)
A8: UBS CPU note — Fig 8 implied DRAM for CPUs | D8: =Fig08_09_DRAM_Demand!C9 -> 14 | F8: =Fig08_09_DRAM_Demand!E9 -> 29 | H8: =Fig08_09_DRAM_Demand!G9 -> 77 | I8: EB | J8: UBS (Arcuri) 26-Oct-26, Fig 8 (base case, incl. CXL reuse)
A9: Bernstein S&D — server (non-HBM) DRAM demand | B9: 64199.926 | C9: 75305.64 | D9: 96496.206 | E9: 142810.46 | F9: 185467.94 | G9: 223952.54 | I9: M Gb | J9: Bernstein 'S&D' tab row 142, model 'Updated on Jun, 2026' (P:\...\Memória\Bernstein SxD.xlsx)
A10: = EB | B10: =B9/8000 -> 8.0249908 | C10: =C9/8000 -> 9.413205 | D10: =D9/8000 -> 12.062026 | E10: =E9/8000 -> 17.851307 | F10: =F9/8000 -> 23.183493 | G10: =G9/8000 -> 27.994068 | I10: EB | J10: 1 EB = 8,000 M Gb
A11: UBS memory team — server DRAM demand | B11: 59038.759 | C11: 75088.562 | D11: 118057.13 | E11: 179619.94 | F11: 312207.3 | I11: M Gb | J11: UBS Global DRAM NAND model (client file 3-Jul-26; Gaudois/Arcuri memory team), 'DRAM Demand' row 188
A12: = EB | B12: =B11*128/1000000 -> 7.5569612 | C12: =C11*128/1000000 -> 9.6113359 | D12: =D11*128/1000000 -> 15.111312 | E12: =E11*128/1000000 -> 22.991352 | F12: =F11*128/1000000 -> 39.962534 | I12: EB | J12: The UBS model builds its Gb as units x MB x 8/1024, so EB = M Gb x 128/1e6 (= units x content); /8000 would understate by 2.4%. Bernstein/UBS-memory rows are END-DEMAND (unconstrained); the CPU note's Fig 7 is a supply allocation
A14: 2. Server CPU / server units
A15: UBS CPU note — bottom-up CPU units | D15: =Fig10_12_TAM!B22 -> 23 | F15: =Fig10_12_TAM!C22 -> 41 | H15: =Fig10_12_TAM!D22 -> 67 | I15: MM CPUs | J15: UBS Fig 10 (Mercury-based x86+ARM; text: ~23MM CPUs shipped C2025)
A16: Bernstein — server CPUs using DIMM package | B16: 22.81086 | C16: 24.098935 | D16: 30.57085 | E16: 37.281171 | F16: 45.536678 | G16: 55.425041 | I16: MM CPUs | J16: Bernstein China Semis 'Global Memory Interface Chips' model, row 14 (file dated 13-Jul-26 on P:); incl. Hygon + non-NVDA ARM
A17: JPM — server CPU units | D17: 26 | G17: 68 | I17: MM CPUs | J17: JPM proprietary server-CPU model (Hung/Hariharan) 12-Jul-26, via wiki assumptions.md server-cpu-tam; 38% CAGR, agentic 155% CAGR
A18: UBS note Fig 25 (Mercury/UBSe) x86+ARM units — sum of 4 quarters | B18: =SUMPRODUCT((RIGHT(Fig25_CPU_Units_digitized!$A$6:$A$35,2)="23")*Fig25_CPU_Units_digitized!$E$6:$E$35) -> 24.503 | C18: =SUMPRODUCT((RIGHT(Fig25_CPU_Units_digitized!$A$6:$A$35,2)="24")*Fig25_CPU_Units_digitized!$E$6:$E$35) -> 24.204 | D18: =SUMPRODUCT((RIGHT(Fig25_CPU_Units_digitized!$A$6:$A$35,2)="25")*Fig25_CPU_Units_digitized!$E$6:$E$35) -> 29.894 | I18: MM CPUs | J18: Same note, p.18 chart (vector geometry, +/-0.01MM/qtr): 2025 = Intel 18.6 + AMD 7.2 + ARM 4.1 = ~29.9MM — vs the 23MM base of its own TAM table; matches Bernstein's 30.6MM
A19: Bernstein S&D — server SYSTEM units | B19: 12.818458 | C19: 13.074828 | D19: 14.05544 | E19: 16.023201 | F19: 17.785753 | G19: 18.675041 | I19: MM servers | J19: Bernstein S&D row 138 (servers, not CPUs)
A20: UBS memory team — server units | B20: 14.086865 | C20: 16.02536 | D20: 20.078 | E20: 23.8741 | F20: 27.84415 | I20: MM servers | J20: UBS DRAM model 'DRAM Demand' row 24 (Gartner actuals)
A22: 3. DRAM intensity
A23: UBS CPU note — blended TB per CPU | D23: =DRAM_CPU_Link!B16 -> 0.60869565 | F23: =DRAM_CPU_Link!C16 -> 0.70731707 | H23: =DRAM_CPU_Link!D16 -> 1.1492537 | I23: TB/CPU | J23: Fig 8 EB / Fig 8 units
A24: Bernstein — TB per CPU (S&D EB / CPU-model units) | B24: =B10/B16 -> 0.35180572 | C24: =C10/C16 -> 0.39060669 | D24: =D10/D16 -> 0.39455971 | E24: =E10/E16 -> 0.47882904 | F24: =F10/F16 -> 0.50911691 | G24: =G10/G16 -> 0.50507978 | I24: TB/CPU | J24: Two Bernstein files (different teams/dates) combined — basis: all DIMM-socket CPUs incl. China
A25: Bernstein S&D — GB per server system | B25: 626.0496 | C25: 719.94869 | D25: 858.17491 | E25: 1114.0912 | F25: 1303.4867 | G25: 1499.0097 | I25: GB/server | J25: Bernstein S&D row 140
A26: UBS memory team — GB per server | B26: 536.45443 | C26: 599.75788 | D26: 752.63035 | E26: 963.02488 | F26: 1435.2219 | I26: GB/server | J26: UBS DRAM model row 117 (MB/server / 1000)
A27: Bernstein — DIMMs per CPU | B27: 7.8858252 | C27: 8.9237201 | D27: 8.9798091 | E27: 9.5418592 | F27: 10.347981 | G27: 11.664184 | I27: DIMMs/CPU | J27: Bernstein memory-interface model row 45 (12/16-channel mix rising; GP slots 50% / AI 70% occupied)
A28: implied GB per DIMM | B28: =B24*1000/B27 -> 44.612416 | C28: =C24*1000/C27 -> 43.771732 | D28: =D24*1000/D27 -> 43.938541 | E28: =E24*1000/E27 -> 50.181944 | F28: =F24*1000/F27 -> 49.199638 | G28: =G24*1000/G27 -> 43.301768 | I28: GB/DIMM | J28: vs UBS Fig 15: 1TB/8 DIMMs = 125GB (trad), 2TB/16 = 125GB (AI)
A30: 4. Spec-level anchors (per CPU / per GPU)
A31: Anchor | B31: Value | C31: Unit | D31: Source (as logged on the wiki)
A32: NVDA Grace LPDDR per CPU | B32: 0.5 | C32: TB | D32: Mizuho (DELL note) 2026-06-03 — '~500GB Grace' (NVDA.md)
A33: NVDA Vera SOCAMM per CPU — original spec | B33: 1.5 | C33: TB | D33: Mizuho 2026-06-03; DAMNANG 2026-04-25 (independent author) — 1.5TB LPDDR5X
A34: NVDA Vera SOCAMM per CPU — after supply-driven cut | B34: 0.768 | C34: TB | D34: JPM (Harlan Sur) 2026-08-24; JPM memory (Jay Kwon) 2026-08-09 — 'cut 50%, to 768GB per CPU from 1.5TB', 'driven almost exclusively by supply tightness'
A35: Vera CPU-only rack: 256 CPUs ~400TB | B35: 1.5625 | C35: TB/CPU | D35: Mizuho 2026-06-03 (~7.9k CPU-only racks 2026E -> ~3EB DRAM)
A36: HBM per GPU — VR200 (Rubin) | B36: 0.288 | C36: TB | D36: Mizuho (Vijay Rakesh) 2026-08-16 — 288GB HBM4 flat GB300 -> VR200
A37: HBM per GPU — VR300 initial / later | B37: 0.384 | C37: TB | D37: UBS (Gaudois/Arcuri) Memory Semis Monthly 2026-08-07 — 384GB HBM4, then 512GB HBM4E (vs prior 768GB)
A38: HBM per GPU — VR300 HBM4E | B38: 0.512 | C38: TB | D38: UBS 2026-08-07
A39: UBS C2030E head-node DRAM per CPU (this note) | B39: =DRAM_CPU_Link!D14 -> 1.5 | C39: TB | D39: UBS Fig 8 implied (33EB / 22MM)
A40: UBS C2030E CPU-side DRAM per accelerator (this note) | B40: =DRAM_CPU_Link!D24 -> 1.4090909 | C40: TB/GPU | D40: DRAM_CPU_Link section B

Sheet Report_Tieouts
A1: Report tie-outs: every arithmetic identity in the note, recomputed
A2: OK = ties within the stated tolerance (rounding of printed figures). FLAG = does not tie — an inconsistency in the note itself (the transcription was re-read for each FLAG).
A3: Source: UBS Global Research (Timothy Arcuri, Seth Cho), 'US Semiconductors: $210B Server CPU TAM By C2030; Gated By Memory Supply', 26-Oct-2026
A5: # | B5: Figure | C5: Check | D5: Printed | E5: Recomputed | F5: Tolerance | G5: Status | H5: Comment
A6: 1 | B6: Fig 6 | C6: Vendor capacities sum to total (2025) | D6: =Fig06_07_DRAM_Supply!B10 -> 36 | E6: =Fig06_07_DRAM_Supply!B11 -> 36 | F6: 1 | G6: =IF(ABS(E6-D6)<=F6,"OK","FLAG") -> OK | H6: rounding
A7: 2 | B7: Fig 6 | C7: Vendor capacities sum to total (2027E) | D7: =Fig06_07_DRAM_Supply!C10 -> 55 | E7: =Fig06_07_DRAM_Supply!C11 -> 54 | F7: 1 | G7: =IF(ABS(E7-D7)<=F7,"OK","FLAG") -> OK | H7: rounding
A8: 3 | B8: Fig 6 | C8: Vendor capacities sum to total (2030E) | D8: =Fig06_07_DRAM_Supply!D10 -> 89 | E8: =Fig06_07_DRAM_Supply!D11 -> 89 | F8: 1 | G8: =IF(ABS(E8-D8)<=F8,"OK","FLAG") -> OK | H8: rounding
A9: 4 | B9: Fig 7 | C9: Server DRAM = MU-share total - non-server (2025) | D9: =Fig06_07_DRAM_Supply!B19 -> 11 | E9: =Fig06_07_DRAM_Supply!B22 -> 10 | F9: 1 | G9: =IF(ABS(E9-D9)<=F9,"OK","FLAG") -> OK
A10: 5 | B10: Fig 7 | C10: Server DRAM = MU-share total - non-server (2027E) | D10: =Fig06_07_DRAM_Supply!C19 -> 27 | E10: =Fig06_07_DRAM_Supply!C22 -> 27 | F10: 1 | G10: =IF(ABS(E10-D10)<=F10,"OK","FLAG") -> OK
A11: 6 | B11: Fig 7 | C11: Server DRAM = MU-share total - non-server (2030E) | D11: =Fig06_07_DRAM_Supply!D19 -> 69 | E11: =Fig06_07_DRAM_Supply!D22 -> 69 | F11: 1 | G11: =IF(ABS(E11-D11)<=F11,"OK","FLAG") -> OK
A12: 7 | B12: Fig 7 | C12: Server DRAM on Fig 6 vendor-capacity basis (2030E) | D12: =Fig06_07_DRAM_Supply!D19 -> 69 | E12: =Fig06_07_DRAM_Supply!D23 -> 59 | F12: 1 | G12: =IF(ABS(E12-D12)<=F12,"OK","FLAG") -> FLAG | H12: 69EB uses the 99EB 'MU share' total; on the 89EB vendor-sum total it is 59EB (66EB incl. CXL) — a 10EB basis gap inside the note
A13: 8 | B13: Fig 6 vs 7 | C13: Micron capacity (Fig 6) vs MU DRAM ex-HBM (Fig 7), 2030E | D13: =Fig06_07_DRAM_Supply!D8 -> 26 | E13: =Fig06_07_DRAM_Supply!D15 -> 23 | F13: 1 | G13: =IF(ABS(E13-D13)<=F13,"OK","FLAG") -> FLAG | H13: 26EB vs 23EB for the same vendor/year
A14: 9 | B14: Fig 7 | C14: DRAM for CPUs = server + CXL (2027E) | D14: =Fig06_07_DRAM_Supply!C21 -> 29 | E14: =Fig06_07_DRAM_Supply!C19+Fig06_07_DRAM_Supply!C20 -> 29 | F14: 1 | G14: =IF(ABS(E14-D14)<=F14,"OK","FLAG") -> OK
A15: 10 | B15: Fig 7 | C15: DRAM for CPUs = server + CXL (2030E) | D15: =Fig06_07_DRAM_Supply!D21 -> 77 | E15: =Fig06_07_DRAM_Supply!D19+Fig06_07_DRAM_Supply!D20 -> 76 | F15: 1 | G15: =IF(ABS(E15-D15)<=F15,"OK","FLAG") -> OK
A16: 11 | B16: Fig 7 vs text | C16: CXL reuse as % of DRAM for CPUs, 2030E (p.2: 'high-single digits') | D16: =0.08 -> 0.08 | E16: =Fig06_07_DRAM_Supply!D20/Fig06_07_DRAM_Supply!D21 -> 0.090909091 | F16: 0.02 | G16: =IF(ABS(E16-D16)<=F16,"OK","FLAG") -> OK | H16: 7/77 = 9.1% fits 'high-single digits'; META math 25% x 25-33% = 6.25-8.25% of fleet memory (p.7 '+6-8%'); 7/69 = 10% of server DRAM — a note, not an error
A17: 12 | B17: Fig 7 vs 8 | C17: C2025 DRAM for CPUs: Fig 7 vs Fig 8 | D17: =Fig06_07_DRAM_Supply!B21 -> 11 | E17: =Fig08_09_DRAM_Demand!C9 -> 14 | F17: 1 | G17: =IF(ABS(E17-D17)<=F17,"OK","FLAG") -> FLAG | H17: 11EB (supply view) vs 14EB (demand view) for the same year
A18: 13 | B18: Fig 8 | C18: DRAM rows sum to total (2025) | D18: =Fig08_09_DRAM_Demand!C9 -> 14 | E18: =Fig08_09_DRAM_Demand!C10 -> 13 | F18: 1 | G18: =IF(ABS(E18-D18)<=F18,"OK","FLAG") -> OK | H18: rounding
A19: 14 | B19: Fig 8 | C19: DRAM rows sum to total (2027E) | D19: =Fig08_09_DRAM_Demand!E9 -> 29 | E19: =Fig08_09_DRAM_Demand!E10 -> 30 | F19: 1 | G19: =IF(ABS(E19-D19)<=F19,"OK","FLAG") -> OK | H19: rounding
A20: 15 | B20: Fig 8 | C20: DRAM rows sum to total (2030E base) | D20: =Fig08_09_DRAM_Demand!G9 -> 77 | E20: =Fig08_09_DRAM_Demand!G10 -> 77 | F20: 1 | G20: =IF(ABS(E20-D20)<=F20,"OK","FLAG") -> OK | H20: rounding
A21: 16 | B21: Fig 8 | C21: DRAM rows sum to total (2030E unconstr.) | D21: =Fig08_09_DRAM_Demand!I9 -> 282 | E21: =Fig08_09_DRAM_Demand!I10 -> 282 | F21: 1 | G21: =IF(ABS(E21-D21)<=F21,"OK","FLAG") -> OK | H21: rounding
A22: 17 | B22: Fig 8 | C22: CPU rows sum to total (2025) | D22: =Fig08_09_DRAM_Demand!B8 -> 23 | E22: =Fig08_09_DRAM_Demand!B10 -> 23 | F22: 1 | G22: =IF(ABS(E22-D22)<=F22,"OK","FLAG") -> OK
A23: 18 | B23: Fig 8 | C23: CPU rows sum to total (2027E) | D23: =Fig08_09_DRAM_Demand!D8 -> 41 | E23: =Fig08_09_DRAM_Demand!D10 -> 42 | F23: 1 | G23: =IF(ABS(E23-D23)<=F23,"OK","FLAG") -> OK
A24: 19 | B24: Fig 8 | C24: CPU rows sum to total (2030E base) | D24: =Fig08_09_DRAM_Demand!F8 -> 67 | E24: =Fig08_09_DRAM_Demand!F10 -> 67 | F24: 1 | G24: =IF(ABS(E24-D24)<=F24,"OK","FLAG") -> OK
A25: 20 | B25: Fig 8 | C25: CPU rows sum to total (2030E unconstr.) | D25: =Fig08_09_DRAM_Demand!H8 -> 169 | E25: =Fig08_09_DRAM_Demand!H10 -> 169 | F25: 1 | G25: =IF(ABS(E25-D25)<=F25,"OK","FLAG") -> OK
A26: 21 | B26: Fig 8 vs 4 | C26: Unconstrained total CPUs: Fig 8 vs Fig 4 | D26: =Fig08_09_DRAM_Demand!H8 -> 169 | E26: =Fig04_Unconstrained!D16 -> 147 | F26: 2 | G26: =IF(ABS(E26-D26)<=F26,"OK","FLAG") -> FLAG | H26: Fig 8's standalone row carries 117 (= Fig 4's total AI CPUs, 22 head + 95 standalone): 169MM vs 147MM in Fig 4, '~150MM' on p.6, '~120MM AI before ~30MM traditional' on p.1, and Fig 9's $548B. Head nodes appear counted twice (mechanism not provable: 3x44-15 also = 117)
A27: 22 | B27: Fig 8 vs 4 | C27: Unconstrained DRAM: printed vs 147MM on Fig 8's own TB/CPU | D27: =Fig08_09_DRAM_Demand!I9 -> 282 | E27: =DRAM_CPU_Link!F22 -> 238 | F27: 2 | G27: =IF(ABS(E27-D27)<=F27,"OK","FLAG") -> FLAG | H27: 282EB -> ~238EB on UBS's content (3.1x the base, not 3.5-3.7x)
A28: 23 | B28: Fig 8 vs 5 | C28: C2030E traditional TB/CPU: Fig 8 implied vs Fig 5 stated ~1.0TB | D28: =Fig05_DRAM_per_CPU!N5 -> 1 | E28: =Fig08_09_DRAM_Demand!G12 -> 0.5 | F28: 0.1 | G28: =IF(ABS(E28-D28)<=F28,"OK","FLAG") -> FLAG | H28: The 77EB base case holds traditional CPUs at 0.5TB; at Fig 5's ~1.0TB the base case needs +15EB (DRAM_CPU_Link section D)
A29: 24 | B29: Fig 8 vs 5 | C29: C2030E head-node TB/CPU inside Fig 5 range (1.5-2TB, mid) | D29: =Fig05_DRAM_per_CPU!N6 -> 1.75 | E29: =Fig08_09_DRAM_Demand!G13 -> 1.5 | F29: 0.25 | G29: =IF(ABS(E29-D29)<=F29,"OK","FLAG") -> OK | H29: at the low end of the range
A30: 25 | B30: Fig 8 vs 5 | C30: C2030E standalone TB/CPU inside Fig 5 range (2-3TB, mid) | D30: =Fig05_DRAM_per_CPU!N7 -> 2.5 | E30: =Fig08_09_DRAM_Demand!G14 -> 1.9333333 | F30: 0.6 | G30: =IF(ABS(E30-D30)<=F30,"OK","FLAG") -> OK | H30: 29/15 = 1.93 on the rounded print; 29/14.5 = 2.0TB on the unrounded count = LOW END of the 2-3TB range
A31: 26 | B31: Fig 8 vs 5 | C31: C2030E blended AI CPU TB vs Fig 5 'Blended AI CPU ~2-2.5TB' (low end) | D31: =Fig05_DRAM_per_CPU!J8 -> 2 | E31: =DRAM_CPU_Link!D17 -> 1.6976999 | F31: 0.05 | G31: =IF(ABS(E31-D31)<=F31,"OK","FLAG") -> FLAG | H31: 62EB / 36.5MM = 1.70TB — below the low end of UBS's own stated range
A32: 27 | B32: Fig 8 vs 5 | C32: Corrected unconstrained (147MM) DRAM at Fig 5 C2030E midpoints vs title '~4x' | D32: =4*Fig08_09_DRAM_Demand!G9 -> 308 | E32: =Fig08_09_DRAM_Demand!F5*Fig05_DRAM_per_CPU!N5+Fig08_09_DRAM_Demand!F6*Fig05_DRAM_per_CPU!N6+Fig04_Unconstrained!D9*Fig05_DRAM_per_CPU!N7 -> 306 | F32: 20 | G32: =IF(ABS(E32-D32)<=F32,"OK","FLAG") -> OK | H32: 30x1.0 + 22x1.75 + 95x2.5 = ~306EB = 4.0x the 77EB base — the title's '~4x' holds on Fig 5 content even on the 147MM count; 238EB (3.1x) is the fix on Fig 8's own TB/CPU
A33: 28 | B33: Text | C33: Unconstrained DRAM multiple vs base (text: '3.5x') | D33: =3.5 -> 3.5 | E33: =Fig08_09_DRAM_Demand!I9/Fig08_09_DRAM_Demand!G9 -> 3.6623377 | F33: 0.2 | G33: =IF(ABS(E33-D33)<=F33,"OK","FLAG") -> OK | H33: 282/77 = 3.66x
A34: 29 | B34: Fig 4 | C34: Head node + standalone = AI CPUs (2027E) | D34: =Fig04_Unconstrained!C12 -> 30 | E34: =Fig04_Unconstrained!C6+Fig04_Unconstrained!C9 -> 31 | F34: 1 | G34: =IF(ABS(E34-D34)<=F34,"OK","FLAG") -> OK | H34: rounding
A35: 30 | B35: Fig 4 | C35: AI CPU $B = units x ASP (2027E) | D35: =Fig04_Unconstrained!C14 -> 90 | E35: =Fig04_Unconstrained!C12*Fig04_Unconstrained!C13/1000 -> 88.71 | F35: 3 | G35: =IF(ABS(E35-D35)<=F35,"OK","FLAG") -> OK
A36: 31 | B36: Fig 4 | C36: AI ASP = unit-weighted head/standalone ASP (2027E) | D36: =Fig04_Unconstrained!C13 -> 2957 | E36: =(Fig04_Unconstrained!C6*Fig04_Unconstrained!C8+Fig04_Unconstrained!C9*Fig04_Unconstrained!C11)/(Fig04_Unconstrained!C6+Fig04_Unconstrained!C9) -> 2960 | F36: 15 | G36: =IF(ABS(E36-D36)<=F36,"OK","FLAG") -> OK
A37: 32 | B37: Fig 4 | C37: Total TAM = AI $ + traditional $ (2027E) | D37: =Fig04_Unconstrained!C17 -> 125 | E37: =Fig04_Unconstrained!C14+Fig10_12_TAM!C9 -> 125 | F37: 1 | G37: =IF(ABS(E37-D37)<=F37,"OK","FLAG") -> OK
A38: 33 | B38: Fig 4 | C38: Total CPUs = AI + traditional (2027E) | D38: =Fig04_Unconstrained!C16 -> 56 | E38: =Fig04_Unconstrained!C12+Fig10_12_TAM!C7 -> 56 | F38: 1 | G38: =IF(ABS(E38-D38)<=F38,"OK","FLAG") -> OK
A39: 34 | B39: Fig 4 | C39: CPU-to-GPU attach = AI CPUs / accelerators (2027E) | D39: =Fig04_Unconstrained!C15 -> 1.05 | E39: =Fig04_Unconstrained!C12/Fig04_Unconstrained!C5 -> 1.0344828 | F39: 0.03 | G39: =IF(ABS(E39-D39)<=F39,"OK","FLAG") -> OK
A40: 35 | B40: Fig 4 | C40: Head node + standalone = AI CPUs (2030E) | D40: =Fig04_Unconstrained!D12 -> 117 | E40: =Fig04_Unconstrained!D6+Fig04_Unconstrained!D9 -> 117 | F40: 1 | G40: =IF(ABS(E40-D40)<=F40,"OK","FLAG") -> OK | H40: rounding
A41: 36 | B41: Fig 4 | C41: AI CPU $B = units x ASP (2030E) | D41: =Fig04_Unconstrained!D14 -> 500 | E41: =Fig04_Unconstrained!D12*Fig04_Unconstrained!D13/1000 -> 499.707 | F41: 3 | G41: =IF(ABS(E41-D41)<=F41,"OK","FLAG") -> OK
A42: 37 | B42: Fig 4 | C42: AI ASP = unit-weighted head/standalone ASP (2030E) | D42: =Fig04_Unconstrained!D13 -> 4271 | E42: =(Fig04_Unconstrained!D6*Fig04_Unconstrained!D8+Fig04_Unconstrained!D9*Fig04_Unconstrained!D11)/(Fig04_Unconstrained!D6+Fig04_Unconstrained!D9) -> 4271.3248 | F42: 15 | G42: =IF(ABS(E42-D42)<=F42,"OK","FLAG") -> OK
A43: 38 | B43: Fig 4 | C43: Total TAM = AI $ + traditional $ (2030E) | D43: =Fig04_Unconstrained!D17 -> 548 | E43: =Fig04_Unconstrained!D14+Fig10_12_TAM!D9 -> 548 | F43: 1 | G43: =IF(ABS(E43-D43)<=F43,"OK","FLAG") -> OK
A44: 39 | B44: Fig 4 | C44: Total CPUs = AI + traditional (2030E) | D44: =Fig04_Unconstrained!D16 -> 147 | E44: =Fig04_Unconstrained!D12+Fig10_12_TAM!D7 -> 147 | F44: 1 | G44: =IF(ABS(E44-D44)<=F44,"OK","FLAG") -> OK
A45: 40 | B45: Fig 4 | C45: CPU-to-GPU attach = AI CPUs / accelerators (2030E) | D45: =Fig04_Unconstrained!D15 -> 2.66 | E45: =Fig04_Unconstrained!D12/Fig04_Unconstrained!D5 -> 2.6590909 | F45: 0.03 | G45: =IF(ABS(E45-D45)<=F45,"OK","FLAG") -> OK
A46: 41 | B46: Fig 10 | C46: Traditional $B = units x ASP (2025) | D46: =Fig10_12_TAM!B9 -> 24 | E46: =Fig10_12_TAM!B7*Fig10_12_TAM!B8/1000 -> 24 | F46: 0.6 | G46: =IF(ABS(E46-D46)<=F46,"OK","FLAG") -> OK
A47: 42 | B47: Fig 10 | C47: Bottom-up units = traditional + AI (2025) | D47: =Fig10_12_TAM!B22 -> 23 | E47: =Fig10_12_TAM!B7+Fig10_12_TAM!B12 -> 23 | F47: 1 | G47: =IF(ABS(E47-D47)<=F47,"OK","FLAG") -> OK
A48: 43 | B48: Fig 10 | C48: Bottom-up TAM = traditional $ + AI $ (2025) | D48: =Fig10_12_TAM!B23 -> 31 | E48: =Fig10_12_TAM!B9+Fig10_12_TAM!B16 -> 31 | F48: 1 | G48: =IF(ABS(E48-D48)<=F48,"OK","FLAG") -> OK
A49: 44 | B49: Fig 10 | C49: Traditional $B = units x ASP (2027E) | D49: =Fig10_12_TAM!C9 -> 35 | E49: =Fig10_12_TAM!C7*Fig10_12_TAM!C8/1000 -> 35.048 | F49: 0.6 | G49: =IF(ABS(E49-D49)<=F49,"OK","FLAG") -> OK
A50: 45 | B50: Fig 10 | C50: Bottom-up units = traditional + AI (2027E) | D50: =Fig10_12_TAM!C22 -> 41 | E50: =Fig10_12_TAM!C7+Fig10_12_TAM!C12 -> 42 | F50: 1 | G50: =IF(ABS(E50-D50)<=F50,"OK","FLAG") -> OK
A51: 46 | B51: Fig 10 | C51: Bottom-up TAM = traditional $ + AI $ (2027E) | D51: =Fig10_12_TAM!C23 -> 83 | E51: =Fig10_12_TAM!C9+Fig10_12_TAM!C16 -> 83 | F51: 1 | G51: =IF(ABS(E51-D51)<=F51,"OK","FLAG") -> OK
A52: 47 | B52: Fig 10 | C52: Traditional $B = units x ASP (2030E) | D52: =Fig10_12_TAM!D9 -> 48 | E52: =Fig10_12_TAM!D7*Fig10_12_TAM!D8/1000 -> 48.18 | F52: 0.6 | G52: =IF(ABS(E52-D52)<=F52,"OK","FLAG") -> OK
A53: 48 | B53: Fig 10 | C53: Bottom-up units = traditional + AI (2030E) | D53: =Fig10_12_TAM!D22 -> 67 | E53: =Fig10_12_TAM!D7+Fig10_12_TAM!D12 -> 67 | F53: 1 | G53: =IF(ABS(E53-D53)<=F53,"OK","FLAG") -> OK
A54: 49 | B54: Fig 10 | C54: Bottom-up TAM = traditional $ + AI $ (2030E) | D54: =Fig10_12_TAM!D23 -> 208 | E54: =Fig10_12_TAM!D9+Fig10_12_TAM!D16 -> 208 | F54: 1 | G54: =IF(ABS(E54-D54)<=F54,"OK","FLAG") -> OK
A55: 50 | B55: Fig 10 | C55: AI CPU $B = units x ASP (2027E) | D55: =Fig10_12_TAM!C16 -> 48 | E55: =Fig10_12_TAM!C12*Fig10_12_TAM!C15/1000 -> 48.928 | F55: 3 | G55: =IF(ABS(E55-D55)<=F55,"OK","FLAG") -> OK | H55: 16 x $3,058 = $48.9B vs $48B (rounded units)
A56: 51 | B56: Fig 11 | C56: AI ASP = weighted head/standalone (2027E) | D56: =Fig10_12_TAM!C37 -> 3058 | E56: =(Fig10_12_TAM!C30*Fig10_12_TAM!C32+Fig10_12_TAM!C33*Fig10_12_TAM!C35)/(Fig10_12_TAM!C30+Fig10_12_TAM!C33) -> 3063.125 | F56: 15 | G56: =IF(ABS(E56-D56)<=F56,"OK","FLAG") -> OK
A57: 52 | B57: Fig 11 | C57: CPU per GPU attach (2027E) | D57: =Fig10_12_TAM!C39 -> 0.54 | E57: =Fig10_12_TAM!C36/Fig10_12_TAM!C29 -> 0.55172414 | F57: 0.03 | G57: =IF(ABS(E57-D57)<=F57,"OK","FLAG") -> OK
A58: 53 | B58: Fig 10 | C58: AI CPU $B = units x ASP (2030E) | D58: =Fig10_12_TAM!D16 -> 160 | E58: =Fig10_12_TAM!D12*Fig10_12_TAM!D15/1000 -> 161.986 | F58: 3 | G58: =IF(ABS(E58-D58)<=F58,"OK","FLAG") -> OK | H58: 37 x $4,378 = $162B vs $160B printed — the printed 37MM is rounded: standalone is 0.33 x 44 = 14.5MM (row below)
A59: 54 | B59: Fig 11 | C59: AI ASP = weighted head/standalone (2030E) | D59: =Fig10_12_TAM!D37 -> 4378 | E59: =(Fig10_12_TAM!D30*Fig10_12_TAM!D32+Fig10_12_TAM!D33*Fig10_12_TAM!D35)/(Fig10_12_TAM!D30+Fig10_12_TAM!D33) -> 4375.8108 | F59: 15 | G59: =IF(ABS(E59-D59)<=F59,"OK","FLAG") -> OK
A60: 55 | B60: Fig 11 | C60: CPU per GPU attach (2030E) | D60: =Fig10_12_TAM!D39 -> 0.83 | E60: =Fig10_12_TAM!D36/Fig10_12_TAM!D29 -> 0.84090909 | F60: 0.03 | G60: =IF(ABS(E60-D60)<=F60,"OK","FLAG") -> OK
A61: 56 | B61: Fig 10/11 | C61: C2030E AI CPU $B with unrounded standalone (0.33 x 44 = 14.5MM) | D61: =Fig10_12_TAM!D16 -> 160 | E61: =(Fig10_12_TAM!D30*Fig10_12_TAM!D32+Fig10_12_TAM!D34*Fig10_12_TAM!D29*Fig10_12_TAM!D35)/1000 -> 159.87796 | F61: 0.5 | G61: =IF(ABS(E61-D61)<=F61,"OK","FLAG") -> OK | H61: ties: $159.8B
A62: 57 | B62: Fig 10/11 | C62: C2030E bottom-up TAM with unrounded standalone | D62: =Fig10_12_TAM!D23 -> 208 | E62: =DRAM_CPU_Link!D38 -> 208.05796 | F62: 0.5 | G62: =IF(ABS(E62-D62)<=F62,"OK","FLAG") -> OK | H62: ties: $208.0B
A63: 58 | B63: Fig 10 | C63: Traditional units follow the stated 8% CAGR (2027E: 20 x 1.08^2) | D63: =Fig10_12_TAM!C7 -> 26 | E63: =Fig10_12_TAM!B7*1.08^2 -> 23.328 | F63: 1 | G63: =IF(ABS(E63-D63)<=F63,"OK","FLAG") -> FLAG | H63: 26MM printed vs 23.3MM on the stated 8% CAGR (2030E's 30MM does fit 8%: 29.4)
A64: 59 | B64: Fig 10 | C64: Traditional units follow the stated 8% CAGR (2030E) | D64: =Fig10_12_TAM!D7 -> 30 | E64: =Fig10_12_TAM!B7*1.08^5 -> 29.386562 | F64: 1 | G64: =IF(ABS(E64-D64)<=F64,"OK","FLAG") -> OK
A65: 60 | B65: Fig 10 | C65: Traditional ASP follows 1.5 x 4% CAGR (2030E) | D65: =Fig10_12_TAM!D8 -> 1606 | E65: =Fig10_12_TAM!B8*1.06^5 -> 1605.8707 | F65: 2 | G65: =IF(ABS(E65-D65)<=F65,"OK","FLAG") -> OK
A66: 61 | B66: Fig 10 | C66: Top-down AI CPU $ = 80MM x $3,000 | D66: =Fig10_12_TAM!D20 -> 240 | E66: =Fig10_12_TAM!D18*Fig10_12_TAM!D19/1000 -> 240 | F66: 1 | G66: =IF(ABS(E66-D66)<=F66,"OK","FLAG") -> OK
A67: 62 | B67: Fig 12 | C67: Segments (units x ASP) sum to bar total (2025) | D67: =Fig10_12_TAM!B47 -> 31 | E67: =Fig10_12_TAM!B46 -> 31.29 | F67: 3 | G67: =IF(ABS(E67-D67)<=F67,"OK","FLAG") -> OK
A68: 63 | B68: Fig 12 | C68: Segments (units x ASP) sum to bar total (2027E) | D68: =Fig10_12_TAM!C47 -> 83 | E68: =Fig10_12_TAM!C46 -> 84.01 | F68: 3 | G68: =IF(ABS(E68-D68)<=F68,"OK","FLAG") -> OK
A69: 64 | B69: Fig 12 | C69: Segments (units x ASP) sum to bar total (2030E) | D69: =Fig10_12_TAM!D47 -> 208 | E69: =Fig10_12_TAM!D46 -> 209.905 | F69: 3 | G69: =IF(ABS(E69-D69)<=F69,"OK","FLAG") -> OK
A70: 65 | B70: Fig 15 | C70: Total W per traditional CPU (250 + 8 x 15) | D70: =Fig15_18_Power!B10 -> 370 | E70: =Fig15_18_Power!D10 -> 370 | F70: 0.5 | G70: =IF(ABS(E70-D70)<=F70,"OK","FLAG") -> OK
A71: 66 | B71: Fig 15 | C71: Total W per AI CPU (450 + 16 x 15) | D71: =Fig15_18_Power!C10 -> 690 | E71: =Fig15_18_Power!E10 -> 690 | F71: 0.5 | G71: =IF(ABS(E71-D71)<=F71,"OK","FLAG") -> OK
A72: 67 | B72: Fig 15 | C72: Traditional CPUs per GW | D72: =Fig15_18_Power!B11 -> 2702703 | E72: =Fig15_18_Power!D11 -> 2702702.7 | F72: 2 | G72: =IF(ABS(E72-D72)<=F72,"OK","FLAG") -> OK
A73: 68 | B73: Fig 15 | C73: AI CPUs per GW | D73: =Fig15_18_Power!C11 -> 1449275 | E73: =Fig15_18_Power!E11 -> 1449275.4 | F73: 2 | G73: =IF(ABS(E73-D73)<=F73,"OK","FLAG") -> OK
A74: 69 | B74: Fig 15 | C74: CPU capex per GW, traditional ($B) | D74: =Fig15_18_Power!B14 -> 4.1 | E74: =Fig15_18_Power!D14 -> 4.0540541 | F74: 0.06 | G74: =IF(ABS(E74-D74)<=F74,"OK","FLAG") -> OK
A75: 70 | B75: Fig 15 | C75: CPU capex per GW, AI ($B) | D75: =Fig15_18_Power!C14 -> 5.1 | E75: =Fig15_18_Power!E14 -> 5.0724638 | F75: 0.06 | G75: =IF(ABS(E75-D75)<=F75,"OK","FLAG") -> OK
A76: 71 | B76: Fig 15 | C76: Memory capex per GW at the printed $12K/TB x 1TB, traditional ($B) | D76: =Fig15_18_Power!B15 -> 13.5 | E76: =Fig15_18_Power!D15 -> 32.432432 | F76: 0.1 | G76: =IF(ABS(E76-D76)<=F76,"OK","FLAG") -> FLAG | H76: printed 13.5 vs 32.4 on the table's own '$12K/1TB' and '1TB' cells
A77: 72 | B77: Fig 15 | C77: Memory capex per GW at the printed $12K/TB x 2TB, AI ($B) | D77: =Fig15_18_Power!C15 -> 29 | E77: =Fig15_18_Power!E15 -> 34.782609 | F77: 0.1 | G77: =IF(ABS(E77-D77)<=F77,"OK","FLAG") -> FLAG | H77: printed 29.0 vs 34.8
A78: 73 | B78: Fig 15 | C78: Memory capex per GW at $10K/TB x 0.5TB (Fig 8's traditional TB) | D78: =Fig15_18_Power!B15 -> 13.5 | E78: =Fig15_18_Power!D11*0.5*10000/1000000000 -> 13.513514 | F78: 0.06 | G78: =IF(ABS(E78-D78)<=F78,"OK","FLAG") -> OK | H78: ties exactly -> the capex row was built at $10K/TB on Fig 8's 0.5TB; the '1TB' and '$12K' cells are the inconsistent ones
A79: 74 | B79: Fig 15 | C79: Memory capex per GW at $10K/TB x 2TB, AI | D79: =Fig15_18_Power!C15 -> 29 | E79: =Fig15_18_Power!E11*2*10000/1000000000 -> 28.985507 | F79: 0.06 | G79: =IF(ABS(E79-D79)<=F79,"OK","FLAG") -> OK | H79: ties exactly
A80: 75 | B80: Fig 16 | C80: Traditional GW = units x 370W (2025) | D80: =Fig15_18_Power!B22 -> 8 | E80: =Fig15_18_Power!B28 -> 7.4 | F80: 0.6 | G80: =IF(ABS(E80-D80)<=F80,"OK","FLAG") -> OK
A81: 76 | B81: Fig 16 | C81: Standalone GW = units x 690W (2025) | D81: =Fig15_18_Power!B26 -> 0 | E81: =Fig15_18_Power!B29 -> 0 | F81: 0.6 | G81: =IF(ABS(E81-D81)<=F81,"OK","FLAG") -> OK
A82: 77 | B82: Fig 17/18 | C82: Fig 18 = Fig 17 x PUE 1.12 (2025) | D82: =Fig15_18_Power!B35 -> 21 | E82: =Fig15_18_Power!B33*1.12 -> 21.28 | F82: 1 | G82: =IF(ABS(E82-D82)<=F82,"OK","FLAG") -> OK
A83: 78 | B83: Fig 16 | C83: Traditional GW = units x 370W (2027E) | D83: =Fig15_18_Power!C22 -> 10 | E83: =Fig15_18_Power!C28 -> 9.62 | F83: 0.6 | G83: =IF(ABS(E83-D83)<=F83,"OK","FLAG") -> OK
A84: 79 | B84: Fig 16 | C84: Standalone GW = units x 690W (2027E) | D84: =Fig15_18_Power!C26 -> 4 | E84: =Fig15_18_Power!C29 -> 3.45 | F84: 0.6 | G84: =IF(ABS(E84-D84)<=F84,"OK","FLAG") -> OK
A85: 80 | B85: Fig 17/18 | C85: Fig 18 = Fig 17 x PUE 1.12 (2027E) | D85: =Fig15_18_Power!C35 -> 70 | E85: =Fig15_18_Power!C33*1.12 -> 69.44 | F85: 1 | G85: =IF(ABS(E85-D85)<=F85,"OK","FLAG") -> OK
A86: 81 | B86: Fig 16 | C86: Traditional GW = units x 370W (2030E) | D86: =Fig15_18_Power!D22 -> 11 | E86: =Fig15_18_Power!D28 -> 11.1 | F86: 0.6 | G86: =IF(ABS(E86-D86)<=F86,"OK","FLAG") -> OK
A87: 82 | B87: Fig 16 | C87: Standalone GW = units x 690W (2030E) | D87: =Fig15_18_Power!D26 -> 10 | E87: =Fig15_18_Power!D29 -> 10.35 | F87: 0.6 | G87: =IF(ABS(E87-D87)<=F87,"OK","FLAG") -> OK
A88: 83 | B88: Fig 17/18 | C88: Fig 18 = Fig 17 x PUE 1.12 (2030E) | D88: =Fig15_18_Power!D35 -> 141 | E88: =Fig15_18_Power!D33*1.12 -> 141.12 | F88: 1 | G88: =IF(ABS(E88-D88)<=F88,"OK","FLAG") -> OK
A89: 84 | B89: Fig 19 | C89: AMD + INTC + ARM = total | D89: =Fig19_21_Share!B12 -> 208 | E89: =Fig19_21_Share!B6+Fig19_21_Share!B7+Fig19_21_Share!B8 -> 208 | F89: 1 | G89: =IF(ABS(E89-D89)<=F89,"OK","FLAG") -> OK
A90: 85 | B90: Fig 19 | C90: ARM sub-rows sum to ARM | D90: =Fig19_21_Share!B8 -> 102 | E90: =SUM(Fig19_21_Share!B9:B11) -> 103 | F90: 1 | G90: =IF(ABS(E90-D90)<=F90,"OK","FLAG") -> OK | H90: rounding
A91: 86 | B91: Fig 19 vs 10 | C91: C2030E revenue split total = Fig 10 bottom-up TAM | D91: =Fig19_21_Share!B12 -> 208 | E91: =Fig10_12_TAM!D23 -> 208 | F91: 1 | G91: =IF(ABS(E91-D91)<=F91,"OK","FLAG") -> OK
A92: 87 | B92: Fig 10 vs 25 | C92: C2025 server CPU units: Fig 10 bottom-up vs Fig 25 Mercury chart (sum of 4 quarters) | D92: =Fig10_12_TAM!B22 -> 23 | E92: =SUMPRODUCT((RIGHT(Fig25_CPU_Units_digitized!$A$6:$A$35,2)="25")*Fig25_CPU_Units_digitized!$E$6:$E$35) -> 29.894 | F92: 2 | G92: =IF(ABS(E92-D92)<=F92,"OK","FLAG") -> FLAG | H92: 23MM in the TAM table vs ~29.9MM x86+ARM units in the note's own Mercury chart (Bernstein: 30.6MM). The C2025 base — and the 8% CAGR off it — looks ~7MM low
A93: 88 | B93: Fig 1 | C93: Blended CPU:GPU: printed 4:1 vs printed 421 cores / 128 cores per CPU | D93: =Fig01_Workloads!F9 -> 4 | E93: =Fig01_Workloads!H10/128 -> 3.2890625 | F93: 0.5 | G93: =IF(ABS(E93-D93)<=F93,"OK","FLAG") -> FLAG | H93: In every row cores:GPU = 128 x CPU:GPU, so the printed 421 implies 3.29:1 whatever the weights. The table's '4:1' is the outlier; the text's '~3:1' and 'we use 3:1' agree with 421
A94: 89 | B94: Fig 3 | C94: Muse CPUs used, base case | D94: =Fig02_03_Muse!B40 -> 2382 | E94: =Fig02_03_Muse!D40 -> 2380.9524 | F94: 2 | G94: =IF(ABS(E94-D94)<=F94,"OK","FLAG") -> OK | H94: 2,382 printed vs 2,381
A95: 90 | B95: Fig 3 | C95: Muse CPUs used, high engagement | D95: =Fig02_03_Muse!C40 -> 4012 | E95: =Fig02_03_Muse!E40 -> 4013.3779 | F95: 2 | G95: =IF(ABS(E95-D95)<=F95,"OK","FLAG") -> OK | H95: 4,012 printed vs 4,013
A97: Count | C97: =COUNTIF(G6:G95,"OK")&" OK / "&COUNTIF(G6:G95,"FLAG")&" FLAG" -> 78 OK / 12 FLAG

Sheet Fig01_Workloads
A1: Figure 1: CPU requirements vary by different workloads (p.3)
A2: UBS layering of Dell white paper 'Characterizing CPU Demand for Agentic AI: Three Agentic Workloads on the Dell PowerEdge R7725' (14-Sep-26); R7725 = 2x AMD Turin 64-core CPUs
A3: Source: UBS Global Research (Timothy Arcuri, Seth Cho), 'US Semiconductors: $210B Server CPU TAM By C2030; Gated By Memory Supply', 26-Oct-2026 — Fig 1
A5: Workload tested | B5: What the agent does | C5: Workload CPU requirements | D5: CPU quota per agent (cores) | E5: Sustained agents on 2x AMD 64-core Turin | F5: Measured CPU:GPU demand (x:1) | G5: % of consumer agentic workload (UBSe) | H5: Measured CPU cores:GPU (x:1) | I5: Check: cores/GPU = CPU:GPU x 128 cores
A6: Workload 1: pypi-server | B6: Writes a Python package and serves it from a local package index | C6: Light CPU: mostly model/code generation with short tool calls | D6: 1 | E6: 512 | F6: 1 | G6: 0.65 | H6: 128 | I6: =F6*128 -> 128
A7: Workload 2: sqlite-with-gcov | B7: Compiles SQLite with code-coverage instrumentation and fixes build errors | C7: Bursty CPU: compiler runs substantially between model reasoning turns | D7: 1 | E7: 238 | F7: 7 | G7: 0.3 | H7: 896 | I7: =F7*128 -> 896
A8: Workload 3: mcmc-sampling-stan | B8: Writes a statistical model, compiles it, then runs computationally heavy sampling | C8: Heavy CPU/HPC: sustained multi-core numerical computation | D8: 4 | E8: 60 | F8: 18 | G8: 0.05 | H8: 2304 | I8: =F8*128 -> 2304 | J8: printed '<5%' — 5% used as upper bound
A9: Blended CPU ratio (printed) | E9: CPU:GPU | F9: 4 | G9: printed 4:1
E10: CPU cores:GPU | H10: 421
A11: Recompute: mix-weighted (workload 3 at 5%) | F11: =SUMPRODUCT(F6:F8,G6:G8) -> 3.65 | H11: =SUMPRODUCT(H6:H8,G6:G8) -> 467.2
A12: Recompute: workload 3 weight that reproduces 421:1 | F12: =F6*G6+F7*G7+F8*G12 -> 3.2890625 | G12: =(H10-H6*G6-H7*G7)/H8 -> 0.029947917 | H12: =H6*G6+H7*G7+H8*G12 -> 421
A13: Each row has cores:GPU = 128 x CPU:GPU (2 x 64-core Turin), so the printed blended 421 cores:GPU implies 421/128 = 3.29:1 whatever the weights (a ~3% weight on workload 3 reproduces it). The table's '4:1' is the outlier; the text's '~3:1' / 'we use 3:1' agree with 421.
A15: Note text (p.3-4): layering this over Dell -> ~3:1 CPU:GPU on the current CPU generation, ~400 cores:1 GPU; core counts double every ~3-4 yrs (~500 cores/CPU by decade-end) but accelerator perf rises too -> UBS uses 3:1 in its demand estimate. Prior framework: ~0.33 standalone + ~0.5 head-node = ~0.85 CPUs/GPU.

Sheet Fig02_03_Muse
A1: Figures 2-3: META Muse CPU sizing (p.4-5)
A2: Muse ~2.5MM DAUs weeks after release; UBS: Muse is a demand signal, not a needle mover (~1MM units even at 1B users with 5-10% provisioning vs ~23MM CPUs shipped C2025)
A3: Source: UBS Global Research (Timothy Arcuri, Seth Cho), 'US Semiconductors: $210B Server CPU TAM By C2030; Gated By Memory Supply', 26-Oct-2026 — Figs 2, 3
A5: Figure 2: META Muse Sensitivity Table
A6: Scenario input | B6: Base Case | C6: High Engagement | D6: Notes (as printed)
A7: Daily Active Users (DAU) | B7: 3000000 | C7: 3000000 | D7: UBSe (printed '3MM')
A8: Peak Concurrent Sandboxes (% of DAU) | B8: 0.25 | C8: 0.5 | D8: UBSe
A9: vCPUs per Sandbox | B9: 2 | C9: 2 | D9: META
A10: Oversubscription | B10: 4 | C10: 1 | D10: Conservative vs. Firecracker/DeepSeek
A11: Cores per CPU | B11: 126 | C11: 126 | D11: AMD EPYC 9D25 (126 cores/252 threads)
A12: Math | B12: Base (recomputed) | C12: High (recomputed) | D12: Printed base | E12: Printed high | F12: Math (as printed)
A13: Concurrent Sandboxes | B13: =B7*B8 -> 750000 | C13: =C7*C8 -> 1500000 | D13: 1MM | E13: 2MM | F13: DAU x Concurrency
A14: vCPUs Demanded | B14: =B13*B9 -> 1500000 | C14: =C13*C9 -> 3000000 | D14: 2MM | E14: 3MM | F14: Sandboxes x vCPUs per Sandbox
A15: Cores Needed | B15: =B14/B10 -> 375000 | C15: =C14/C10 -> 3000000 | D15: 375K | E15: 3MM | F15: vCPUs / Oversubscription
A16: CPU Units (EPYC chips) | B16: =B15/B11 -> 2976.1905 | C16: =C15/C11 -> 23809.524 | D16: 2.98K | E16: 23.81K | F16: Cores needed / Cores per CPU
A17: Printed 'Concurrent Sandboxes 1MM / vCPUs 2MM' are rounded from 0.75MM / 1.5MM; the cores and CPU-unit lines use the unrounded values.
A19: # of CPU units — concurrency x oversubscription (printed)
A20: Concurrency | B20: 1x | C20: 2x | D20: 4x | E20: 8x | F20: Check 1x (recomputed) | G20: Max |printed - recomputed| in row
A21: 0.1 | B21: 4762 | C21: 2381 | D21: 1190 | E21: 595 | F21: =$B$7*A21*$B$9/1/$B$11 -> 4761.9048 | G21: =MAX(ABS(B21-$B$7*A21*$B$9/1/$B$11),ABS(C21-$B$7*A21*$B$9/2/$B$11),ABS(D21-$B$7*A21*$B$9/4/$B$11),ABS(E21-$B$7*A21*$B$9/8/$B$11)) -> 0.47619048
A22: 0.25 | B22: 11905 | C22: 5952 | D22: 2976 | E22: 1488 | F22: =$B$7*A22*$B$9/1/$B$11 -> 11904.762 | G22: =MAX(ABS(B22-$B$7*A22*$B$9/1/$B$11),ABS(C22-$B$7*A22*$B$9/2/$B$11),ABS(D22-$B$7*A22*$B$9/4/$B$11),ABS(E22-$B$7*A22*$B$9/8/$B$11)) -> 0.38095238
A23: 0.5 | B23: 23810 | C23: 11905 | D23: 5952 | E23: 2976 | F23: =$B$7*A23*$B$9/1/$B$11 -> 23809.524 | G23: =MAX(ABS(B23-$B$7*A23*$B$9/1/$B$11),ABS(C23-$B$7*A23*$B$9/2/$B$11),ABS(D23-$B$7*A23*$B$9/4/$B$11),ABS(E23-$B$7*A23*$B$9/8/$B$11)) -> 0.47619048
A24: 1 | B24: 47619 | C24: 23810 | D24: 11905 | E24: 5952 | F24: =$B$7*A24*$B$9/1/$B$11 -> 47619.048 | G24: =MAX(ABS(B24-$B$7*A24*$B$9/1/$B$11),ABS(C24-$B$7*A24*$B$9/2/$B$11),ABS(D24-$B$7*A24*$B$9/4/$B$11),ABS(E24-$B$7*A24*$B$9/8/$B$11)) -> 0.47619048
A26: Figure 3: Assuming 5-10% Target Utilization (thread-based sizing)
A27: Line | B27: Base Case | C27: High Engagement | D27: Base recomputed | E27: High recomputed | F27: Notes (as printed)
A28: Daily Active Users (DAUs) | B28: 3000000 | C28: 3000000 | F28: Unique users who open Muse on a given day
A29: (x) vCPUs per Sandbox | B29: 2 | C29: 2 | F29: Virtual CPUs allocated to each user's virtual machine (VM)
A30: Total Capacity Needed (Threads) | B30: 6000000 | C30: 6000000 | D30: =B28*B29 -> 6000000 | E30: =C28*C29 -> 6000000 | F30: Hardware needed if every DAU ran at once on dedicated hardware at one thread per vCPU
A31: (x) Peak Concurrent Sandboxes (% of DAUs) | B31: 0.2 | C31: 0.3 | F31: UBSe share of DAU with a live sandbox (a running VM, whether active or idle) during peak hours
A32: Concurrent sandboxes | B32: 600000 | C32: 900000 | D32: =B28*B31 -> 600000 | E32: =C28*C31 -> 900000 | F32: # of VMs alive at peak
A33: (/) Target Utilization | B33: 0.7 | C33: 0.65 | F33: UBSe how fully the provisioned capacity runs at peak, remainder = headroom
A34: Sandboxes Provisioned | B34: 857143 | C34: 1384615 | D34: =B32/B33 -> 857142.86 | E34: =C32/C33 -> 1384615.4 | F34: Sandbox slots built, including headroom
A35: vCPUs Provisioned | B35: 1714286 | C35: 2769231 | D35: =D34*B29 -> 1714285.7 | E35: =E34*C29 -> 2769230.8 | F35: vCPUs across all provisioned slots
A36: (/) Oversubscription | B36: 3 | C36: 3 | F36: UBSe vCPUs sharing one physical hardware thread (benchmarked vs DeepSeek and AWS)
A37: Threads Provisioned | B37: 571429 | C37: 923077 | D37: =D35/B36 -> 571428.57 | E37: =E35/C36 -> 923076.92 | F37: Physical hardware threads needed after sharing
A38: Hardware Deployed (% of total capacity) | B38: 0.1 | C38: 0.15 | D38: =D37/D30 -> 0.095238095 | E38: =E37/E30 -> 0.15384615 | F38: UBSe: heavily oversubscribed cloud workloads deploy 5-10% of dedicated-equivalent hardware in base case
A39: (/) Usable Threads per CPU | B39: 240 | C39: 230 | F39: Hardware threads available for sandboxes after host OS and hypervisor take their share
A40: # of CPUs being used | B40: 2382 | C40: 4012 | D40: =D37/B39 -> 2380.9524 | E40: =E37/C39 -> 4013.3779 | F40: # of CPUs required
A41: Printed 2,382 / 4,012 vs recomputed 2,381 / 4,013 (rounding in the note). Text: ~2,382 CPUs for 3MM DAUs base, ~4,012 high; deployed hardware = 10-15% of dedicated capacity.

Sheet Fig04_Unconstrained
A1: Figure 4: Unconstrained Estimates Suggest a $500B+ CPU TAM by C2030 (p.6)
A2: Source: UBS Global Research (Timothy Arcuri, Seth Cho), 'US Semiconductors: $210B Server CPU TAM By C2030; Gated By Memory Supply', 26-Oct-2026 — Fig 4 (UBS estimates)
A4: Unconstrained Demand Ests | B4: 2025 | C4: 2027E | D4: 2030E | E4: Comment
A5: Accelerators (NVDA, AMD, TPU, Trn), MM | B5: 9 | C5: 29 | D5: 44 | E5: Assumes units stay the same but TDP/performance increases; printed '~44'
A6: Head node CPU, MM | B6: 3 | C6: 11 | D6: 22 | E6: UBSe based announced systems; printed '~22'
A7: Head Node CPU-to-GPU attach rate | B7: 0.29 | C7: 0.36 | D7: 0.5
A8: Head Node ASP ($) | B8: 2430 | C8: 3160 | D8: 4480 | E8: Higher ASP given higher portion of NVDA CPUs
A9: Standalone (outside of rack), MM | B9: 0 | C9: 20 | D9: 95 | E9: Additional CPU units outside of rack; printed '~20' / '~95'
A10: Standalone CPU-to-GPU attach rate | C10: 0.69 | D10: 2.16 | E10: 3CPU:1GPU target ratio ex-head nodes and 50% of trad CPUs for tool calls
A11: Standalone CPU ASP ($) | C11: 2850 | D11: 4223 | E11: Assumes higher share of x86 even over time for multithread
A12: AI CPU Market (Bottom-up Ests), MM | B12: 3 | C12: 30 | D12: 117
A13: AI CPU ASP ($) | B13: 2430 | C13: 2957 | D13: 4271 | E13: Higher core counts and clock speeds increasing ASPs (row printed 'AI CPU ASP, K' but values are $)
A14: AI CPU Market (Bottom-up Ests), $B | B14: 7 | C14: 90 | D14: 500
A15: CPU-to-GPU Attach | B15: 0.29 | C15: 1.05 | D15: 2.66
A16: Implied Total CPUs (AI + Traditional), MM | B16: 23 | C16: 56 | D16: 147
A17: Implied Total CPU TAM, $B | B17: 31 | C17: 125 | D17: 548
A18: Implied DRAM Memory, EB | E18: Row printed blank in Fig 4 — the DRAM figure (282EB) is in Fig 8

Sheet Fig05_DRAM_per_CPU
A1: Figure 5: Memory Demand For Agentic Workloads is 3-4x Higher vs Traditional CPUs (p.6)
A2: Source: UBS Global Research (Timothy Arcuri, Seth Cho), 'US Semiconductors: $210B Server CPU TAM By C2030; Gated By Memory Supply', 26-Oct-2026 — Fig 5 (UBS Research)
A4: DRAM / CPU (TB) — as printed | B4: C2025/26 | C4: C2026/27 | D4: C2030E | E4: Growth | F4: low 25/26 | G4: high 25/26 | H4: low 26/27 | I4: high 26/27 | J4: low 30E | K4: high 30E | L4: mid 25/26 | M4: mid 26/27 | N4: mid 30E
A5: Traditional CPU | B5: ~0.25-0.5TB | C5: ~0.5-0.75TB | D5: ~1.0TB | E5: ~1.5-2x | F5: 0.25 | G5: 0.5 | H5: 0.5 | I5: 0.75 | J5: 1 | K5: 1 | L5: =AVERAGE(F5,G5) -> 0.375 | M5: =AVERAGE(H5,I5) -> 0.625 | N5: =AVERAGE(J5,K5) -> 1
A6: AI head-node CPU | B6: ~1-1.5TB | C6: ~1-1.5TB | D6: ~1.5-2TB | E6: ~1.5x | F6: 1 | G6: 1.5 | H6: 1 | I6: 1.5 | J6: 1.5 | K6: 2 | L6: =AVERAGE(F6,G6) -> 1.25 | M6: =AVERAGE(H6,I6) -> 1.25 | N6: =AVERAGE(J6,K6) -> 1.75
A7: AI standalone / agentic CPU | B7: ~1.5-2TB | C7: ~1.5-2TB | D7: ~2-3TB | E7: ~1.5x | F7: 1.5 | G7: 2 | H7: 1.5 | I7: 2 | J7: 2 | K7: 3 | L7: =AVERAGE(F7,G7) -> 1.75 | M7: =AVERAGE(H7,I7) -> 1.75 | N7: =AVERAGE(J7,K7) -> 2.5
A8: Blended AI CPU | B8: ~1.5TB | C8: ~1.5TB | D8: ~2-2.5TB | E8: ~1.5x | F8: 1.5 | G8: 1.5 | H8: 1.5 | I8: 1.5 | J8: 2 | K8: 2.5 | L8: =AVERAGE(F8,G8) -> 1.5 | M8: =AVERAGE(H8,I8) -> 1.5 | N8: =AVERAGE(J8,K8) -> 2.25
A10: Text (p.6): traditional ~0.5TB today -> ~1TB by end of decade; AI head-node already >1.5TB -> ~2TB; AI standalone may reach ~3TB over the next few generations. Low/high/mid columns are the printed ranges split into numbers for the link sheet.

Sheet Fig06_07_DRAM_Supply
A1: Figures 6-7: UBSe DRAM capacity by vendor and ex-HBM DRAM available for CPUs (p.6-7)
A2: Source: UBS Global Research (Timothy Arcuri, Seth Cho), 'US Semiconductors: $210B Server CPU TAM By C2030; Gated By Memory Supply', 26-Oct-2026 — Figs 6, 7 (UBS Research)
A4: Figure 6: UBSe DRAM Capacity by Vendor (EB)
A5: EB | B5: C2025 | C5: C2027E | D5: C2030E | E5: Note
A6: Samsung | B6: 14 | C6: 19 | D6: 31
A7: SK Hynix | B7: 10 | C7: 16 | D7: 22
A8: Micron | B8: 9 | C8: 13 | D8: 26
A9: CXMT | B9: 3 | C9: 6 | D9: 10
A10: Total | B10: 36 | C10: 55 | D10: 89 | E10: printed total
A11: Sum of vendors (recomputed) | B11: =SUM(B6:B9) -> 36 | C11: =SUM(C6:C9) -> 54 | D11: =SUM(D6:D9) -> 89
A13: Figure 7: Our Current Base Case Memory Model Suggests 77EB for Server DRAM in C2030
A14: ex-HBM DRAM Market (EB) | B14: C2025 | C14: C2027E | D14: C2030E | E14: Note
A15: MU DRAM ex-HBM | B15: 9 | C15: 13 | D15: 23
A16: Total Mkt (MU share, UBS Ests) | B16: 36 | C16: 54 | D16: 99 | E16: MU ex-HBM / assumed MU share
A17: Total non-HBM DRAM Mkt | B17: 36 | C17: 55 | D17: 89 | E17: equals Fig 6 total
A18: Non-Server DRAM | B18: 26 | C18: 27 | D18: 30
A19: Server DRAM Memory | B19: 11 | C19: 27 | D19: 69
A20: Old DDR Reuse via CXL (UBS Ests) | C20: 2 | D20: 7
A21: Total DRAM Memory for CPUs, EB | B21: 11 | C21: 29 | D21: 77
A22: Server DRAM = MU-share total - non-server (recomputed) | B22: =B16-B18 -> 10 | C22: =C16-C18 -> 27 | D22: =D16-D18 -> 69
A23: Server DRAM = vendor total - non-server (recomputed) | B23: =B17-B18 -> 10 | C23: =C17-C18 -> 28 | D23: =D17-D18 -> 59
A24: Implied MU share of non-HBM DRAM (MU / MU-share total) | B24: =B15/B16 -> 0.25 | C24: =C15/C16 -> 0.24074074 | D24: =D15/D16 -> 0.23232323
A25: CXL reuse as % of server DRAM | C25: =C20/C19 -> 0.074074074 | D25: =D20/D19 -> 0.10144928
A27: Text (p.7): META at AI Infra Summit showed a 1TB server using a 3:1 mix of DDR5 RDIMMs and CXL-attached DDR4; usable in 25-33% of 4 META CPU-workload fleets -> UBS: +6-8% memory capacity via reuse of older RDIMMs (experts: high-single-digit %).

Sheet Fig08_09_DRAM_Demand
A1: Figure 8: The 3:1 CPU:GPU Attach Ratio Results in DRAM Demand ~4x Above UBS Estimates (p.7)
A2: Source: UBS Global Research (Timothy Arcuri, Seth Cho), 'US Semiconductors: $210B Server CPU TAM By C2030; Gated By Memory Supply', 26-Oct-2026 — Figs 8, 9 (UBS estimates)
A4: DRAM / CPU | B4: C2025 CPU, MM | C4: C2025 DRAM, EB | D4: C2027E CPU, MM | E4: C2027E DRAM, EB | F4: C2030E Base CPU, MM | G4: C2030E Base DRAM, EB | H4: C2030E Unconstr. CPU, MM | I4: C2030E Unconstr. DRAM, EB
A5: Traditional CPU | B5: 20 | C5: 10 | D5: 26 | E5: 12 | F5: 30 | G5: 15 | H5: 30 | I5: 15
A6: AI head-node CPU | B6: 3 | C6: 3 | D6: 11 | E6: 11 | F6: 22 | G6: 33 | H6: 22 | I6: 33
A7: AI standalone / agentic CPU | B7: 0 | C7: 0 | D7: 5 | E7: 7 | F7: 15 | G7: 29 | H7: 117 | I7: 234
A8: Total CPU, MM | B8: 23 | D8: 41 | F8: 67 | H8: 169
A9: Implied DRAM, EB | C9: 14 | E9: 29 | G9: 77 | I9: 282
A10: Sum of rows (recomputed) | B10: =SUM(B5:B7) -> 23 | C10: =SUM(C5:C7) -> 13 | D10: =SUM(D5:D7) -> 42 | E10: =SUM(E5:E7) -> 30 | F10: =SUM(F5:F7) -> 67 | G10: =SUM(G5:G7) -> 77 | H10: =SUM(H5:H7) -> 169 | I10: =SUM(I5:I7) -> 282
A11: Implied TB per CPU (DRAM EB / CPU MM)
A12: Traditional CPU | C12: =IF(B5=0,"",C5/B5) -> 0.5 | E12: =IF(D5=0,"",E5/D5) -> 0.46153846 | G12: =IF(F5=0,"",G5/F5) -> 0.5 | I12: =IF(H5=0,"",I5/H5) -> 0.5
A13: AI head-node CPU | C13: =IF(B6=0,"",C6/B6) -> 1 | E13: =IF(D6=0,"",E6/D6) -> 1 | G13: =IF(F6=0,"",G6/F6) -> 1.5 | I13: =IF(H6=0,"",I6/H6) -> 1.5
A14: AI standalone / agentic CPU | C14: =IF(B7=0,"",C7/B7) | E14: =IF(D7=0,"",E7/D7) -> 1.4 | G14: =IF(F7=0,"",G7/F7) -> 1.9333333 | I14: =IF(H7=0,"",I7/H7) -> 2
A15: Blended (total EB / total CPUs) | C15: =C9/B8 -> 0.60869565 | E15: =E9/D8 -> 0.70731707 | G15: =G9/F8 -> 1.1492537 | I15: =I9/H8 -> 1.6686391
A17: Note: the Unconstrained column puts 117MM in the standalone row — 117MM is Fig 4's TOTAL AI CPU count (22 head-node + 95 standalone), giving 169MM CPUs vs Fig 4's 147MM and the text's '~150MM' (3 x 44 - 15 also equals 117, so the mechanism is not provable). On UBS's own TB/CPU, 147MM CPUs need ~238EB — see Report_Tieouts / DRAM_CPU_Link.
A19: Figure 9: Bottom Up TAM Difference (data labels as printed; legend says 'MM units' but values match the $B TAMs of Figs 4/10)
A20: Series | B20: 2025 | C20: 2027E | D20: 2030E | E20: Note
A21: UBS CPU TAM ($B; legend printed 'MM units') | B21: 31 | C21: 83 | D21: 208 | E21: equals Fig 10 bottom-up TAM
A22: Demand CPU TAM ($B; legend printed 'MM units') | B22: 31 | C22: 125 | D22: 548 | E22: equals Fig 4 unconstrained TAM

Sheet Fig10_12_TAM
A1: Figures 10-12: Updated ~$210B C2030 CPU TAM framework (p.8)
A2: Source: UBS Global Research (Timothy Arcuri, Seth Cho), 'US Semiconductors: $210B Server CPU TAM By C2030; Gated By Memory Supply', 26-Oct-2026 — Figs 10, 11, 12 (UBS estimates; Fig 12 also Mercury Research)
A4: Figure 10: Our Estimates Suggest a ~$210B TAM by C2030
A5: Estimate | B5: 2025 | C5: 2027E | D5: 2030E | E5: Comment
A6: Traditional CPU Market
A7: Traditional CPU Market, MM | B7: 20 | C7: 26 | D7: 30 | E7: Grows from 2025 at 8% CAGR like C2005-2020
A8: Traditional CPU ASP ($) | B8: 1200 | C8: 1348 | D8: 1606 | E8: Grows from 2025 at 1.5x 4% CAGR like C2005-2020 (row printed 'ASP, K' but values are $)
A9: Traditional Market, $B | B9: 24 | C9: 35 | D9: 48 | E9: Implied by units and ASPs
A10: AI CPU (Bottom-Up)
A11: AI Accelerator Units (Bottom-Up), MM | B11: 9 | C11: 29 | D11: 44 | E11: Largest programs (NVDA, AMD, TPU, Trn), ex-China
A12: AI CPU Market (Bottom-Up Ests), MM | B12: 3 | C12: 16 | D12: 37
A13: Head Node | B13: 3 | C13: 11 | D13: 22 | E13: UBSe based announced systems; printed '~22'
A14: Standalone | B14: 0 | C14: 5 | D14: 15 | E14: Additional CPU units outside of rack
A15: AI CPU ASP ($) | B15: 2430 | C15: 3058 | D15: 4378 | E15: Higher core count and clock speed increasing ASPs
A16: AI CPU Market (Bottom-up Ests), $B | B16: 7 | C16: 48 | D16: 160
A17: AI CPU (Top-Down)
A18: AI CPU Market (Top-Down Ests), MM | D18: 80 | E18: TAM based on 3-4T AI Spend, and 1-to-1 CPU/GPU attach
A19: AI CPU ASP ($) top-down | D19: 3000 | E19: UBS ASP ests
A20: AI CPU Market, $B top-down | D20: 240 | E20: Implied by units and ASPs
A21: Total Market
A22: Bottom-up Units, MM | B22: 23 | C22: 41 | D22: 67 | E22: Traditional CPU + AI CPU Bottom-up Ests
A23: Bottom-up TAM, $B | B23: 31 | C23: 83 | D23: 208
A24: Top-Down CPU Market, MM | D24: 110 | E24: Traditional CPU + AI CPU Top-Down Ests
A25: Top-Down CPU Market, $B | D25: 288
A27: Figure 11: AI CPU Bottom-Up TAM Estimate
A28: AI CPU Bottom-Up TAM Estimate | B28: 2025 | C28: 2027E | D28: 2030E | E28: Comment
A29: Accelerators (NVDA, AMD, TPU, Trn) | B29: 9 | C29: 29 | D29: 44 | E29: Assumes units stay the same but TDP/performance increases
A30: Head Node CPUs, MM | B30: 3 | C30: 11 | D30: 22 | E30: UBSe based announced systems
A31: Head Node CPU per GPU attach rate | B31: 0.29 | C31: 0.36 | D31: 0.5
A32: Head Node ASP ($) | B32: 2430 | C32: 3160 | D32: 4480 | E32: Higher ASP given higher portion of NVDA CPUs
A33: Standalone (outside of rack), MM | B33: 0 | C33: 5 | D33: 15 | E33: Additional CPU units outside of rack; printed '~15'
A34: Standalone CPU per GPU attach rate | C34: 0.18 | D34: 0.33
A35: Standalone CPU ASP ($) | C35: 2850 | D35: 4223 | E35: Assumes higher share of x86 even over time for multithread
A36: AI CPU Market (Bottom-up Ests), MM | B36: 3 | C36: 16 | D36: 37
A37: AI CPU ASP ($) | B37: 2430 | C37: 3058 | D37: 4378 | E37: Higher core count and clock speed increasing ASPs
A38: AI CPU Market (Bottom-up Ests), $B | B38: 7 | C38: 48 | D38: 160
A39: CPU per GPU attach | B39: 0.29 | C39: 0.54 | D39: 0.83
A41: Figure 12: CPU Market To Reach ~$210B By C2030E ($B; stacked bar — totals printed, segments = Fig 10/11 units x ASP)
A42: Segment ($B) | B42: 2025 | C42: 2027E | D42: 2030E | E42: Basis
A43: Traditional servers | B43: =B9 -> 24 | C43: =C9 -> 35 | D43: =D9 -> 48 | E43: Fig 10 traditional $B
A44: AI Head Node | B44: =B30*B32/1000 -> 7.29 | C44: =C30*C32/1000 -> 34.76 | D44: =D30*D32/1000 -> 98.56 | E44: Fig 11 units x ASP
A45: AI Standalone | B45: =IF(B35="",0,B33*B35/1000) -> 0 | C45: =IF(C35="",0,C33*C35/1000) -> 14.25 | D45: =IF(D35="",0,D33*D35/1000) -> 63.345 | E45: Fig 11 units x ASP
A46: Sum of segments | B46: =SUM(B43:B45) -> 31.29 | C46: =SUM(C43:C45) -> 84.01 | D46: =SUM(D43:D45) -> 209.905
A47: Printed bar total | B47: 31 | C47: 83 | D47: 208
A49: Text (p.8): ASP ~$4.4K (vs prior $3.8K/CPU); $4-5K/CPU possible in outer years if ASP/core holds and core counts double (vs $2-2.5K in C2025). AMD sizes the TAM at $220B, NVDA at $200B (no year).

Sheet Fig15_18_Power
A1: Figures 15-18: CPUs per GW and CPU power / compute capacity deployed (p.11-12)
A2: Source: UBS Global Research (Timothy Arcuri, Seth Cho), 'US Semiconductors: $210B Server CPU TAM By C2030; Gated By Memory Supply', 26-Oct-2026 — Figs 15-18 (UBS Research)
A4: Figure 15: ~2.7MM traditional CPUs per GW, only ~1.4MM AI CPUs
A5: CPUs per GW | B5: Traditional CPU | C5: AI CPU | D5: Trad recomputed | E5: AI recomputed | F5: Note
A6: CPU TDP (W) | B6: 250 | C6: 450
A7: Approx DRAM / CPU (TB) | B7: 1 | C7: 2
A8: DRAM/DIMM (W) | B8: 15 | C8: 15
A9: # of DIMMs populated | B9: 8 | C9: 16
A10: Total TDP per CPU (W) | B10: 370 | C10: 690 | D10: =B6+B8*B9 -> 370 | E10: =C6+C8*C9 -> 690
A11: # of CPUs per GW | B11: 2702703 | C11: 1449275 | D11: =1000000000/D10 -> 2702702.7 | E11: =1000000000/E10 -> 1449275.4
A12: CPU ASP ($) | B12: 1500 | C12: 3500
A13: CPU+DIMMs Capex per GW, $B | B13: 17.6 | C13: 34.1 | D13: =D14+D15 -> 36.486486 | E13: =E14+E15 -> 39.855072 | F13: Text: CPU+memory capex/GW ~$34B (AI) vs ~$18B (traditional), memory the vast majority of the increase.
A14: CPU Capex ($B/GW) | B14: 4.1 | C14: 5.1 | D14: =D11*B12/1000000000 -> 4.0540541 | E14: =E11*C12/1000000000 -> 5.0724638
A15: Memory Capex ($B/GW; printed '$12K/1TB') | B15: 13.5 | C15: 29 | D15: =D11*B7*B16/1000000000 -> 32.432432 | E15: =E11*C7*C16/1000000000 -> 34.782609 | F15: Printed memory capex does NOT tie to the table's own 1TB x $12K/TB (recomputed cols: $32.4B / $34.8B). It ties EXACTLY at $10K/TB with traditional at 0.5TB (Fig 8's basis) and AI at 2TB: $5.0K / $20.0K of memory per CPU.
A16: Memory price assumption ($ per TB, printed '$12K/1TB') | B16: 12000 | C16: 12000
A18: Figure 16: ~21GW of power required for new CPUs in C2030
A19: CPU Power, GW | B19: 2025 | C19: 2027E | D19: 2030E | E19: Note
A20: Traditional CPUs, MM | B20: 20 | C20: 26 | D20: 30
A21: W per CPU + DIMMs (trad) | B21: 370 | C21: 370 | D21: 370
A22: Traditional Implied GW | B22: 8 | C22: 10 | D22: 11
A23: AI Head node Implied GW | E23: printed 'captured in GW racks'
A24: AI Standalone CPUs, MM | B24: 0 | C24: 5 | D24: 15
A25: W per CPU + DIMMs (AI) | B25: 690 | C25: 690 | D25: 690
A26: AI Standalone Implied GW | B26: 0 | C26: 4 | D26: 10
A27: Total CPUs, Implied GW | B27: 8 | C27: 13 | D27: 21
A28: Trad GW recomputed | B28: =B20*B21/1000 -> 7.4 | C28: =C20*C21/1000 -> 9.62 | D28: =D20*D21/1000 -> 11.1
A29: Standalone GW recomputed | B29: =B24*B25/1000 -> 0 | C29: =C24*C25/1000 -> 3.45 | D29: =D24*D25/1000 -> 10.35
A31: Figures 17-18: GW of annual compute / data-center capacity deployed (stacked bars; totals printed, CPU slice = Fig 16)
A32: GW | B32: 2025 | C32: 2027E | D32: 2030E | E32: Note
A33: Fig 17 annual compute capacity deployed (GPU+ASIC+CPU), GW | B33: 19 | C33: 62 | D33: 126 | E33: printed totals
A34: of which CPU (Fig 16), GW | B34: 8 | C34: 13 | D34: 21 | E34: Fig 16 total CPUs implied GW
A35: Fig 18 annual DC capacity deployed at PUE 1.12, GW | B35: 21 | C35: 70 | D35: 141 | E35: printed totals
A36: Fig 17 x 1.12 (recomputed) | B36: =B33*1.12 -> 21.28 | C36: =C33*1.12 -> 69.44 | D36: =D33*1.12 -> 141.12
A37: CPU share of compute GW | B37: =B34/B33 -> 0.42105263 | C37: =C34/C33 -> 0.20967742 | D37: =D34/D33 -> 0.16666667
A39: GPU/ASIC split of Figs 17-18 is unlabeled in the chart (2030E roughly GPU ~60GW / ASIC ~45GW / CPU ~21GW by eye) — not tabulated. Text: CPU-driven infrastructure ~20% of 2030 annual compute capacity deployed; Fig 18 assumes PUE 1.12.

Sheet Fig19_21_Share
A1: Figures 19-21: C2030E server-CPU revenue split and unit shares (p.13-14)
A2: Source: UBS Global Research (Timothy Arcuri, Seth Cho), 'US Semiconductors: $210B Server CPU TAM By C2030; Gated By Memory Supply', 26-Oct-2026 — Figs 19, 20, 21 (UBS estimates / UBS Research)
A4: Figure 19: UBSe Server CPU Market Breakdown C2030E
A5: (Revenues $B) | B5: C2030E | C5: % (printed) | D5: % (recomputed)
A6: AMD Server | B6: 62 | C6: 0.3 | D6: =B6/B12 -> 0.29807692
A7: INTC Server | B7: 44 | C7: 0.21 | D7: =B7/B12 -> 0.21153846
A8: ARM Server | B8: 102 | C8: 0.49 | D8: =B8/B12 -> 0.49038462
A9: of which ARM AGI | B9: 15 | C9: 0.07 | D9: =B9/B12 -> 0.072115385
A10: of which NVDA | B10: 53 | C10: 0.25 | D10: =B10/B12 -> 0.25480769
A11: of which Other | B11: 35 | C11: 0.17 | D11: =B11/B12 -> 0.16826923
A12: Total Server CPU | B12: 208 | C12: 1 | D12: =B12/B12 -> 1
A13: Sum AMD+INTC+ARM | B13: =B6+B7+B8 -> 208
A14: Sum ARM sub-rows | B14: =SUM(B9:B11) -> 103
A16: Figures 20-21: unit shares (pie labels)
A17: Unit share | B17: C2025 traditional CPU (Fig 20) | C17: UBSe C2030 total CPU (Fig 21) | D17: C2030 revenue share (Fig 19) | E17: Implied C2030 ASP ($) = rev / (share x 67MM)
A18: INTC | B18: 0.6 | C18: 0.28 | D18: =D7 -> 0.21153846 | E18: =B7*1000/(C18*Fig10_12_TAM!D22) -> 2345.4158
A19: AMD | B19: 0.24 | C19: 0.34 | D19: =D6 -> 0.29807692 | E19: =B6*1000/(C19*Fig10_12_TAM!D22) -> 2721.6857
A20: ARM | B20: 0.16 | C20: 0.38 | D20: =D8 -> 0.49038462 | E20: =B8*1000/(C20*Fig10_12_TAM!D22) -> 4006.2844
A22: Implied ASP column uses Fig 10's 67MM C2030 units: ARM-based revenue includes NVDA Grace/Vera and ARM AGI chips (full-chip $), not royalties. Text: AMD/INTC monetize ~$3-4K per CPU vs ARM IP economics ~$100+/CPU.

Sheet Fig23_Server_Roadmap
A1: Figure 23: Server CPU Roadmap (p.16) — approximate timing read off the Gantt bars
A2: Source: UBS Global Research (Timothy Arcuri, Seth Cho), 'US Semiconductors: $210B Server CPU TAM By C2030; Gated By Memory Supply', 26-Oct-2026 — Fig 23 (Company reports, UBS research)
A4: Vendor | B4: Generation / platform | C4: Microarchitecture | D4: Product family | E4: Process | F4: Bar start (approx) | G4: Bar end (approx)
A5: AMD | B5: 1st Gen | C5: Zen | D5: Naples | E5: 14nm | F5: 2017 | G5: 2019 Q2
A6: AMD | B6: 2nd Gen | C6: Zen2 | D6: General Purpose, Rome | E6: 7nm, 14nm | F6: 2019 Q3 | G6: 2021 Q1
A7: AMD | B7: 3rd Gen | C7: Zen3, 3D V-Cache | D7: General Purpose, Milan; Technical, Milan-X | E7: 7nm | F7: 2021 Q1 | G7: 2022 Q3
A8: AMD | B8: 4th Gen | C8: Zen4/4C, 3D V-Cache | D8: General Purpose, Genoa; Cloud Native - Bergamo; Technical - Genoa-X; Telco - Siena | E8: 5nm | F8: 2022 Q4 | G8: 2024 Q3
A9: AMD | B9: 5th Gen | C9: Zen5/5c | D9: Turin | E9: TSMC 3nm | F9: 2024 Q4 | G9: 2026 Q2
A10: AMD | B10: 6th Gen | C10: Zen6/6c | D10: Venice (26) and Verano (27) | E10: TSMC 2nm | F10: 2026 Q3 | G10: 2028 Q2
A11: AMD | B11: 7th Gen | C11: Zen 7/7c | D11: Florence | E11: Next Gen Process Node | F11: 2028 Q3 | G11: 2029+
A12: INTC | B12: 1st Gen (Purley) | C12: - | D12: Skylake-SP | E12: 14nm+ | F12: 2017 | G12: 2019 Q1
A13: INTC | B13: 1st Gen (Purley) | C13: - | D13: Cascade Lake-SP | E13: 14nm++ | F13: 2019 Q2 | G13: 2020 Q1
A14: INTC | B14: 2nd Gen (Purley) | C14: - | D14: Cooper Lake; Cascade Lake R | E14: 14nm++ | F14: 2020 | G14: 2020
A15: INTC | B15: 3rd Gen (Whitley) | C15: - | D15: Ice Lake-SP | E15: 10nm+ | F15: 2021 | G15: 2022
... A41: GOOG | B41: Gen 3 | C41: Neoverse V4/N4 | D41: Axion Gen 3 | E41: 2nm* | F41: 2027 Q4 | G41: 2029+
A43: '*' as printed in the note (unconfirmed / expected). Start/end quarters are read from bar edges and are approximate (+/- 1 quarter).

Sheet Fig24_CPU_Specs
A1: Figure 24: CPU Specs (p.17)
A2: Source: UBS Global Research (Timothy Arcuri, Seth Cho), 'US Semiconductors: $210B Server CPU TAM By C2030; Gated By Memory Supply', 26-Oct-2026 — Fig 24 (Company reports, UBS research)
A4: Spec | B4: AMD Venice | C4: INTC Clearwater Forest | D4: INTC Diamond Rapids | E4: NVDA Vera | F4: ARM AGI | G4: AWS Graviton5 | H4: MSFT Cobalt 200 | I4: QCOM Dragonfly C1000 | J4: Google Axion N4A
A5: Process | B5: TSMC N2 | C5: Compute 18A; Base INTC 3; I/O INTC 7 | D5: Cores 18A-P; Base INTC 3-T; Fabric hubs INTC 3 | E5: - | F5: TSMC N3P | G5: TSMC 3nm | H5: TSMC 3nm | I5: - | J5: TSMC 3nm
A6: Package | B6: 8 CCDs + 2 I/O dies | C6: 12 compute + 3 bases + 2 I/O tiles | D6: 16 core chiplets on 4 base tiles + 2 fabric hubs | E6: Monolithic compute die + separate memory controller and I/O dies | F6: 2 chiplets | G6: 4 chiplets | H6: 2 chiplets | I6: Multi-chiplet | J6: -
A7: Base / nominal clock | B7: 2.55 GHz (9996) | C7: 2.2 GHz (6990E+, 450W) | D7: - | E7: - | F7: 3.2 GHz (128/136C); 3.5 GHz (64C); 2.8 GHz typical | G7: - | H7: - | I7: - | J7: -
A8: Max boost | B8: 5.0 GHz (F-SKUs); 5.15 GHz (Venice-X) | C8: 3.2 GHz (2.8 all-core) | D8: - | E8: - | F8: 3.5 GHz (128/136C); 3.7 GHz (64C) | G8: - | H8: - | I8: - | J8: -
A9: TDP | B9: Up to 600W | C9: 300-450W | D9: Up to 650W | E9: 250-450W | F9: 300W | G9: - | H9: - | I9: - | J9: -
A10: Core design | B10: Zen 6 / Zen 6c | C10: Darkmont E-core | D10: Panther Cove | E10: Custom Olympus | F10: Neoverse V3 | G10: Neoverse V3 | H10: Neoverse V3 | I10: Custom Oryon | J10: Neoverse V3
A11: Max cores | B11: 256 Zen 6c; 128 Gen 6 | C11: 288 | D11: 256 | E11: 88 | F11: 136 | G11: 192 | H11: 132 | I11: 250+ | J11: -
A12: Max threads | B12: 512 | C12: 288 | D12: - | E12: 176 | F12: - | G12: - | H12: - | I12: - | J12: -
A13: Multithreading | B13: SMT 2 threads/core | C13: None | D13: - | E13: Spatial multithreading 2 threads/core | F13: - | G13: - | H13: - | I13: - | J13: -
A14: Core-count options | B14: SP7: 64-256; SP8: 8-128 | C14: 144 / 192 / 264 / 288 | D14: - | E14: Single 88-core SKU | F14: 64 / 128 / 136 | G14: - | H14: - | I14: - | J14: -
A15: Compute dies x core | B15: 8 x 32 Zen 6c | C15: 12 x 24 | D15: 16 x up to 16 | E15: 1 x 88 | F15: 2 x 70 physical | G15: 4 chiplets | H15: 2 x 66 active | I15: Multi-chiplet | J15: -
... A21: Other links | B21: - | C21: 6 UPI 2.0 links | D21: UPI 3 (on flexible lanes) | E21: NVLink-C2C (1,800 GB/s) | F21: 2 socket SMP; AMBA CHI extension links | G21: - | H21: - | I21: - | J21: -
A23: Memory capacity per CPU is NOT given in Fig 24 (only type/bandwidth). Vera capacity context lives on Cross_Check (1.5TB SOCAMM spec -> 768GB per JPM 24-Aug-26).

Sheet Fig25_CPU_Units_digitized
A1: Figure 25: Intel, AMD and ARM Server CPU Units (p.18) — DIGITIZED
A2: Chart values extracted from the PDF's vector geometry (charts are vector forms; axis fit residual <=0.003MM / <=0.04pp), cross-checked by a 600-dpi pixel measurement (max diff 0.01MM / 0.22pp); printed segment labels used where present (+/-0.5pp rounding) — see Fig28_31_Provenance. Not printed numbers.
A3: Source: UBS Global Research (Timothy Arcuri, Seth Cho), 'US Semiconductors: $210B Server CPU TAM By C2030; Gated By Memory Supply', 26-Oct-2026
A5: quarter | B5: intel_mm | C5: amd_mm | D5: arm_mm | E5: total_mm
A6: 1Q19 | B6: 6.724 | C6: 0.197 | D6: 0.036 | E6: 6.957
A7: 2Q19 | B7: 6.557 | C7: 0.233 | D7: 0.03 | E7: 6.82
A8: 3Q19 | B8: 7.771 | C8: 0.347 | D8: 0.042 | E8: 8.16
A9: 4Q19 | B9: 8.931 | C9: 0.425 | D9: 0.048 | E9: 9.404
A10: 1Q20 | B10: 8.507 | C10: 0.461 | D10: 0.054 | E10: 9.022
A11: 2Q20 | B11: 8.435 | C11: 0.521 | D11: 0.054 | E11: 9.01
A12: 3Q20 | B12: 8.082 | C12: 0.574 | D12: 0.06 | E12: 8.716
A13: 4Q20 | B13: 8.142 | C13: 0.622 | D13: 0.066 | E13: 8.83
A14: 1Q21 | B14: 7.406 | C14: 0.724 | D14: 0.054 | E14: 8.184
A15: 2Q21 | B15: 8.315 | C15: 0.873 | D15: 0.066 | E15: 9.255
A16: 3Q21 | B16: 8.77 | C16: 0.999 | D16: 0.072 | E16: 9.841
A17: 4Q21 | B17: 9.5 | C17: 1.142 | D17: 0.09 | E17: 10.733
... A35: 2Q26 | B35: 4.959 | C35: 2.615 | D35: 1.621 | E35: 9.195

Sheet Fig26_Unit_Share_digitized
A1: Figure 26: Server CPU Unit Share (p.18) — DIGITIZED
A2: Chart values extracted from the PDF's vector geometry (charts are vector forms; axis fit residual <=0.003MM / <=0.04pp), cross-checked by a 600-dpi pixel measurement (max diff 0.01MM / 0.22pp); printed segment labels used where present (+/-0.5pp rounding) — see Fig28_31_Provenance. Not printed numbers.
A3: Source: UBS Global Research (Timothy Arcuri, Seth Cho), 'US Semiconductors: $210B Server CPU TAM By C2030; Gated By Memory Supply', 26-Oct-2026
A5: quarter | B5: intel_pct | C5: amd_pct | D5: arm_pct
A6: 1Q19 | B6: 96.65 | C6: 2.85 | D6: 0.5
A7: 2Q19 | B7: 96.14 | C7: 3.36 | D7: 0.5
A8: 3Q19 | B8: 95.19 | C8: 4.31 | D8: 0.5
A9: 4Q19 | B9: 94.96 | C9: 4.54 | D9: 0.5
A10: 1Q20 | B10: 94.32 | C10: 5.09 | D10: 0.59
A11: 2Q20 | B11: 93.64 | C11: 5.77 | D11: 0.59
A12: 3Q20 | B12: 92.73 | C12: 6.59 | D12: 0.68
A13: 4Q20 | B13: 92.23 | C13: 7.09 | D13: 0.68
A14: 1Q21 | B14: 90.46 | C14: 8.86 | D14: 0.68
A15: 2Q21 | B15: 89.87 | C15: 9.45 | D15: 0.68
A16: 3Q21 | B16: 89.14 | C16: 10.09 | D16: 0.77
A17: 4Q21 | B17: 88.55 | C17: 10.63 | D17: 0.81
... A35: 2Q26 | B35: 53.92 | C35: 28.45 | D35: 17.63

Sheet Fig27_x86_RevShare_digitized
A1: Figure 27: Intel vs AMD x86 Server CPU Revenue Share (p.18) — DIGITIZED
A2: Chart values extracted from the PDF's vector geometry (charts are vector forms; axis fit residual <=0.003MM / <=0.04pp), cross-checked by a 600-dpi pixel measurement (max diff 0.01MM / 0.22pp); printed segment labels used where present (+/-0.5pp rounding) — see Fig28_31_Provenance. Not printed numbers.
A3: Source: UBS Global Research (Timothy Arcuri, Seth Cho), 'US Semiconductors: $210B Server CPU TAM By C2030; Gated By Memory Supply', 26-Oct-2026
A5: quarter | B5: point_index | C5: intel_pct | D5: amd_pct | E5: sum_pct
A6: 1Q08 | B6: 0 | C6: 90.98 | D6: 9.02 | E6: 100
A7: 2Q08 | B7: 1 | C7: 91.02 | D7: 8.98 | E7: 100
A8: 3Q08 | B8: 2 | C8: 89 | D8: 11 | E8: 100
A9: 4Q08 | B9: 3 | C9: 89.13 | D9: 10.87 | E9: 100
A10: 1Q09 | B10: 4 | C10: 88.95 | D10: 11.05 | E10: 100
A11: 2Q09 | B11: 5 | C11: 91.2 | D11: 8.8 | E11: 100
A12: 3Q09 | B12: 6 | C12: 91.79 | D12: 8.21 | E12: 100
A13: 4Q09 | B13: 7 | C13: 92.51 | D13: 7.49 | E13: 100
A14: 1Q10 | B14: 8 | C14: 92.01 | D14: 7.99 | E14: 100
A15: 2Q10 | B15: 9 | C15: 93.14 | D15: 6.86 | E15: 100
A16: 3Q10 | B16: 10 | C16: 93.36 | D16: 6.64 | E16: 100
A17: 4Q10 | B17: 11 | C17: 94.44 | D17: 5.56 | E17: 100
... A79: 2Q26 | B79: 73 | C79: 55.43 | D79: 44.57 | E79: 100

Sheet Fig28_INTC_Product_Mix
A1: Figure 28: INTC Server Units Decomposition (p.18)
A2: Chart values extracted from the PDF's vector geometry (charts are vector forms; axis fit residual <=0.003MM / <=0.04pp), cross-checked by a 600-dpi pixel measurement (max diff 0.01MM / 0.22pp); printed segment labels used where present (+/-0.5pp rounding) — see Fig28_31_Provenance. Not printed numbers.
A3: Source: UBS Global Research (Timothy Arcuri, Seth Cho), 'US Semiconductors: $210B Server CPU TAM By C2030; Gated By Memory Supply', 26-Oct-2026
A5: quarter | B5: granite_rapids_pct | C5: sierra_forest_pct | D5: emerald_rapids_pct | E5: sapphire_rapids_pct | F5: ice_lake_pct | G5: cascade_lake_pct | H5: others_pct | I5: unplotted_residual_pct | J5: row_sum_pct
A6: 1Q21 | B6: 0 | C6: 0 | D6: 0 | E6: 0 | F6: 2 | G6: 76 | H6: 22 | I6: 0 | J6: 100
A7: 2Q21 | B7: 0 | C7: 0 | D7: 0 | E7: 0 | F7: 7 | G7: 75 | H7: 18 | I7: 0 | J7: 100
A8: 3Q21 | B8: 0 | C8: 0 | D8: 0 | E8: 0 | F8: 12 | G8: 72 | H8: 17 | I8: 0 | J8: 101
A9: 4Q21 | B9: 0 | C9: 0 | D9: 0 | E9: 0 | F9: 18 | G9: 70 | H9: 13 | I9: 0 | J9: 101
A10: 1Q22 | B10: 0 | C10: 0 | D10: 0 | E10: 0.1 | F10: 28 | G10: 63 | H10: 9 | I10: 0 | J10: 100.1
A11: 2Q22 | B11: 0 | C11: 0 | D11: 0 | E11: 1 | F11: 33 | G11: 58 | H11: 8 | I11: 0 | J11: 100
A12: 3Q22 | B12: 0 | C12: 0 | D12: 0 | E12: 1 | F12: 37 | G12: 55 | H12: 7 | I12: 0 | J12: 100
A13: 4Q22 | B13: 0 | C13: 0 | D13: 0 | E13: 2.5 | F13: 42 | G13: 50 | H13: 6 | I13: 0 | J13: 100.5
A14: 1Q23 | B14: 0 | C14: 0 | D14: 0 | E14: 5 | F14: 45 | G14: 45 | H14: 5 | I14: 0 | J14: 100
A15: 2Q23 | B15: 0 | C15: 0 | D15: 0 | E15: 13 | F15: 45 | G15: 40 | H15: 3 | I15: 0 | J15: 101
A16: 3Q23 | B16: 0 | C16: 0 | D16: 1 | E16: 27 | F16: 39 | G16: 33 | H16: 0 | I16: 0 | J16: 100
A17: 4Q23 | B17: 0 | C17: 0 | D17: 4 | E17: 41 | F17: 31 | G17: 24 | H17: 0 | I17: 0 | J17: 100
... A27: 2Q26 | B27: 26 | C27: 12 | D27: 42 | E27: 12 | F27: 3 | G27: 0 | H27: 2.4 | I27: 2.6 | J27: 100

Sheet Fig29_AMD_Product_Mix
A1: Figure 29: AMD Server Units Decomposition (p.18)
A2: Chart values extracted from the PDF's vector geometry (charts are vector forms; axis fit residual <=0.003MM / <=0.04pp), cross-checked by a 600-dpi pixel measurement (max diff 0.01MM / 0.22pp); printed segment labels used where present (+/-0.5pp rounding) — see Fig28_31_Provenance. Not printed numbers.
A3: Source: UBS Global Research (Timothy Arcuri, Seth Cho), 'US Semiconductors: $210B Server CPU TAM By C2030; Gated By Memory Supply', 26-Oct-2026
A5: quarter | B5: venice_pct | C5: turin_pct | D5: bergamo_pct | E5: siena_pct | F5: genoa_pct | G5: milan_pct | H5: others_pct | I5: unplotted_residual_pct | J5: row_sum_pct
A6: 1Q21 | B6: 0 | C6: 0 | D6: 0 | E6: 0 | F6: 0 | G6: 14 | H6: 14 | I6: 72 | J6: 100
A7: 2Q21 | B7: 0 | C7: 0 | D7: 0 | E7: 0 | F7: 0 | G7: 26 | H7: 11 | I7: 63 | J7: 100
A8: 3Q21 | B8: 0 | C8: 0 | D8: 0 | E8: 0 | F8: 0 | G8: 47 | H8: 8 | I8: 45 | J8: 100
A9: 4Q21 | B9: 0 | C9: 0 | D9: 0 | E9: 0 | F9: 0 | G9: 54 | H9: 8 | I9: 38 | J9: 100
A10: 1Q22 | B10: 0 | C10: 0 | D10: 0 | E10: 0 | F10: 0.1 | G10: 62 | H10: 7 | I10: 30.9 | J10: 100
A11: 2Q22 | B11: 0 | C11: 0 | D11: 0 | E11: 0 | F11: 0.1 | G11: 67 | H11: 6 | I11: 26.9 | J11: 100
A12: 3Q22 | B12: 0 | C12: 0 | D12: 0 | E12: 0 | F12: 1.9 | G12: 75 | H12: 6 | I12: 17.1 | J12: 100
A13: 4Q22 | B13: 0 | C13: 0 | D13: 0 | E13: 0 | F13: 6 | G13: 75 | H13: 5 | I13: 14 | J13: 100
A14: 1Q23 | B14: 0 | C14: 0 | D14: 0.1 | E14: 0 | F14: 12 | G14: 73 | H14: 5 | I14: 9.9 | J14: 100
A15: 2Q23 | B15: 0 | C15: 0 | D15: 2 | E15: 0.2 | F15: 19 | G15: 67 | H15: 4 | I15: 7.8 | J15: 100
A16: 3Q23 | B16: 0 | C16: 0 | D16: 23 | E16: 0.5 | F16: 29 | G16: 38 | H16: 4 | I16: 5.5 | J16: 100
A17: 4Q23 | B17: 0 | C17: 0 | D17: 22 | E17: 1 | F17: 47 | G17: 21 | H17: 3 | I17: 6 | J17: 100
... A27: 2Q26 | B27: 6 | C27: 45 | D27: 9 | E27: 1.6 | F27: 33 | G27: 3 | H27: 1.2 | I27: 1.1 | J27: 99.9

Sheet Fig30_INTC_Node_Mix
A1: Figure 30: INTC Server Units by Node (p.19)
A2: Chart values extracted from the PDF's vector geometry (charts are vector forms; axis fit residual <=0.003MM / <=0.04pp), cross-checked by a 600-dpi pixel measurement (max diff 0.01MM / 0.22pp); printed segment labels used where present (+/-0.5pp rounding) — see Fig28_31_Provenance. Not printed numbers.
A3: Source: UBS Global Research (Timothy Arcuri, Seth Cho), 'US Semiconductors: $210B Server CPU TAM By C2030; Gated By Memory Supply', 26-Oct-2026
A5: quarter | B5: intel_14_pct | C5: intel_10_pct | D5: intel_7_pct | E5: intel_3_pct | F5: unknown_other_pct | G5: unplotted_residual_pct | H5: row_sum_pct
A6: 1Q21 | B6: 76 | C6: 2 | D6: 0 | E6: 0 | F6: 22 | G6: 0 | H6: 100
A7: 2Q21 | B7: 75 | C7: 7 | D7: 0 | E7: 0 | F7: 18 | G7: 0 | H7: 100
A8: 3Q21 | B8: 72 | C8: 12 | D8: 0 | E8: 0 | F8: 17 | G8: 0 | H8: 101
A9: 4Q21 | B9: 70 | C9: 18 | D9: 0 | E9: 0 | F9: 13 | G9: 0 | H9: 101
A10: 1Q22 | B10: 63 | C10: 28 | D10: 0.1 | E10: 0 | F10: 9 | G10: 0 | H10: 100.1
A11: 2Q22 | B11: 58 | C11: 33 | D11: 1 | E11: 0 | F11: 8 | G11: 0 | H11: 100
A12: 3Q22 | B12: 55 | C12: 37 | D12: 1 | E12: 0 | F12: 7 | G12: 0 | H12: 100
A13: 4Q22 | B13: 50 | C13: 42 | D13: 3 | E13: 0 | F13: 6 | G13: 0 | H13: 101
A14: 1Q23 | B14: 45 | C14: 45 | D14: 5 | E14: 0 | F14: 5 | G14: 0 | H14: 100
A15: 2Q23 | B15: 40 | C15: 45 | D15: 13 | E15: 0 | F15: 3 | G15: 0 | H15: 101
A16: 3Q23 | B16: 33 | C16: 39 | D16: 28 | E16: 0 | F16: 0 | G16: 0 | H16: 100
A17: 4Q23 | B17: 24 | C17: 31 | D17: 45 | E17: 0 | F17: 0 | G17: 0 | H17: 100
... A27: 2Q26 | B27: 0 | C27: 3 | D27: 54 | E27: 41 | F27: 2 | G27: 0 | H27: 100

Sheet Fig31_AMD_Node_Mix
A1: Figure 31: AMD Server Units by Node (p.19)
A2: Chart values extracted from the PDF's vector geometry (charts are vector forms; axis fit residual <=0.003MM / <=0.04pp), cross-checked by a 600-dpi pixel measurement (max diff 0.01MM / 0.22pp); printed segment labels used where present (+/-0.5pp rounding) — see Fig28_31_Provenance. Not printed numbers.
A3: Source: UBS Global Research (Timothy Arcuri, Seth Cho), 'US Semiconductors: $210B Server CPU TAM By C2030; Gated By Memory Supply', 26-Oct-2026
A5: quarter | B5: 7nm_pct | C5: 5nm_pct | D5: 3_4nm_pct | E5: 2nm_pct | F5: unknown_other_pct | G5: unplotted_residual_pct | H5: row_sum_pct
A6: 1Q21 | B6: 86 | C6: 0 | D6: 0 | E6: 0 | F6: 14 | G6: 0 | H6: 100
A7: 2Q21 | B7: 89 | C7: 0 | D7: 0 | E7: 0 | F7: 11 | G7: 0 | H7: 100
A8: 3Q21 | B8: 92 | C8: 0 | D8: 0 | E8: 0 | F8: 8 | G8: 0 | H8: 100
A9: 4Q21 | B9: 92 | C9: 0 | D9: 0 | E9: 0 | F9: 8 | G9: 0 | H9: 100
A10: 1Q22 | B10: 93 | C10: 0.1 | D10: 0 | E10: 0 | F10: 7 | G10: 0 | H10: 100.1
A11: 2Q22 | B11: 94 | C11: 0.1 | D11: 0 | E11: 0 | F11: 6 | G11: 0 | H11: 100.1
A12: 3Q22 | B12: 92 | C12: 2 | D12: 0 | E12: 0 | F12: 6 | G12: 0 | H12: 100
A13: 4Q22 | B13: 89 | C13: 6 | D13: 0 | E13: 0 | F13: 5 | G13: 0 | H13: 100
A14: 1Q23 | B14: 83 | C14: 12 | D14: 0 | E14: 0 | F14: 5 | G14: 0 | H14: 100
A15: 2Q23 | B15: 75 | C15: 21 | D15: 0 | E15: 0 | F15: 4 | G15: 0 | H15: 100
A16: 3Q23 | B16: 44 | C16: 52 | D16: 0 | E16: 0 | F16: 4 | G16: 0 | H16: 100
A17: 4Q23 | B17: 26 | C17: 70 | D17: 0 | E17: 0 | F17: 3 | G17: 0 | H17: 99
... A27: 2Q26 | B27: 5 | C27: 43 | D27: 45 | E27: 6 | F27: 1.3 | G27: 0 | H27: 100.3

Sheet Fig32_AMD_Model
A1: Figure 32: AMD - Summary Model (p.21)
A2: Transcribed from the image table as printed (UBS estimates; Company data, FactSet). Percentages stored as fractions.
A3: Source: UBS Global Research (Timothy Arcuri, Seth Cho), 'US Semiconductors: $210B Server CPU TAM By C2030; Gated By Memory Supply', 26-Oct-2026
A5: Advanced Micro Devices (AMD) - Key Metrics (in $MM except EPS and Units) | B5: C2023A | C5: C2024A | D5: C2025A | E5: CQ1A | F5: CQ2A | G5: CQ3E | H5: CQ4E | I5: C2026E | J5: CQ1E | K5: CQ2E | L5: CQ3E | M5: CQ4E | N5: C2027E | O5: CQ1E | P5: CQ2E | Q5: CQ3E | R5: CQ4E | S5: C2028E | T5: C2029E | U5: C2030E
A6: Revenue | B6: 22680 | C6: 25785 | D6: 34639 | E6: 10253 | F6: 11536 | G6: 13180 | H6: 17122 | I6: 52092 | J6: 19063 | K6: 20930 | L6: 25508 | M6: 32421 | N6: 97922 | O6: 32538 | P6: 33841 | Q6: 35995 | R6: 37618 | S6: 139993 | T6: 176924 | U6: 221588
A7: Y/Y Growth | B7: -0.04 | C7: 0.14 | D7: 0.34 | E7: 0.38 | F7: 0.5 | G7: 0.43 | H7: 0.67 | I7: 0.5 | J7: 0.86 | K7: 0.81 | L7: 0.94 | M7: 0.89 | N7: 0.88 | O7: 0.71 | P7: 0.62 | Q7: 0.41 | R7: 0.16 | S7: 0.43 | T7: 0.26 | U7: 0.25
A8: Gross Profit (Non-GAAP) | B8: 11436 | C8: 13759 | D8: 18165 | E8: 5685 | F8: 6488 | G8: 7386 | H8: 9476 | I8: 29035 | J8: 10492 | K8: 11499 | L8: 14066 | M8: 17958 | N8: 54016 | O8: 18105 | P8: 18897 | Q8: 20208 | R8: 21213 | S8: 78424 | T8: 101143 | U8: 129261
A9: Gross Margin | B9: 0.504 | C9: 0.534 | D9: 0.524 | E9: 0.554 | F9: 0.562 | G9: 0.56 | H9: 0.553 | I9: 0.557 | J9: 0.55 | K9: 0.549 | L9: 0.551 | M9: 0.554 | N9: 0.552 | O9: 0.556 | P9: 0.558 | Q9: 0.561 | R9: 0.564 | S9: 0.56 | T9: 0.572 | U9: 0.583
A10: Ex-Semi-Custom GM (UBSe) | B10: 0.57 | C10: 0.55 | D10: 0.54 | E10: 0.56 | F10: 0.57 | G10: 0.57 | H10: 0.56 | I10: 0.56 | J10: 0.55 | K10: 0.55 | L10: 0.55 | M10: 0.56 | N10: 0.55 | O10: 0.56 | P10: 0.56 | Q10: 0.57 | R10: 0.57 | S10: 0.56 | T10: 0.58 | U10: 0.59
A11: R&D (GAAP) | B11: 5872 | C11: 6456 | D11: 8091 | E11: 2397 | F11: 2528 | G11: 2638 | H11: 2818 | I11: 10381 | J11: 3118 | K11: 3368 | L11: 3608 | M11: 3848 | N11: 13942 | O11: 3968 | P11: 4038 | Q11: 4108 | R11: 4178 | S11: 16292 | T11: 17712 | U11: 19512
A12: SG&A (GAAP) | B12: 2352 | C12: 2783 | D12: 4144 | E12: 1253 | F12: 1401 | G12: 1491 | H12: 1591 | I12: 5736 | J12: 1661 | K12: 1731 | L12: 1781 | M12: 1831 | N12: 7004 | O12: 1806 | P12: 1856 | Q12: 1931 | R12: 2001 | S12: 7594 | T12: 8184 | U12: 8754
A13: Other & Non-GAAP Adjustment (GAAP) | B13: 1835 | C13: 1586 | D13: 1223 | E13: 290 | F13: 284 | G13: 284 | H13: 284 | I13: 1142 | J13: 284 | K13: 284 | L13: 284 | M13: 284 | N13: 1136 | O13: 284 | P13: 284 | Q13: 284 | R13: 284 | S13: 1136 | T13: 1136 | U13: 1136
A14: Total Opex (Non-GAAP) | B14: 6616 | C14: 7669 | D14: 10397 | E14: 3145 | F14: 3394 | G14: 3634 | H14: 3914 | I14: 14087 | J14: 4284 | K14: 4604 | L14: 4894 | M14: 5184 | N14: 18966 | O14: 5279 | P14: 5399 | Q14: 5544 | R14: 5684 | S14: 21906 | T14: 23916 | U14: 26286
A15: Y/Y Growth | B15: 0.1 | C15: 0.16 | D15: 0.36 | E15: 0.42 | F15: 0.4 | G15: 0.32 | H15: 0.3 | I15: 0.35 | J15: 0.36 | K15: 0.36 | L15: 0.35 | M15: 0.32 | N15: 0.35 | O15: 0.23 | P15: 0.17 | Q15: 0.13 | R15: 0.1 | S15: 0.16 | T15: 0.09 | U15: 0.1
A16: Operating Income (Non-GAAP) | B16: 4854 | C16: 6138 | D16: 7768 | E16: 2540 | F16: 3094 | G16: 3752 | H16: 5562 | I16: 14948 | J16: 6208 | K16: 6895 | L16: 9172 | M16: 12774 | N16: 35050 | O16: 12826 | P16: 13498 | Q16: 14664 | R16: 15529 | S16: 56518 | T16: 77227 | U16: 102975
A17: Operating Margin | B17: 0.214 | C17: 0.238 | D17: 0.224 | E17: 0.248 | F17: 0.268 | G17: 0.285 | H17: 0.325 | I17: 0.287 | J17: 0.326 | K17: 0.329 | L17: 0.36 | M17: 0.394 | N17: 0.358 | O17: 0.394 | P17: 0.399 | Q17: 0.407 | R17: 0.413 | S17: 0.404 | T17: 0.436 | U17: 0.465
A18: Non-GAAP EPS | B18: 2.65 | C18: 3.31 | D18: 4.17 | E18: 1.37 | F18: 1.66 | G18: 2 | H18: 2.87 | I18: 7.91 | J18: 3.17 | K18: 3.5 | L18: 4.59 | M18: 6.23 | N18: 17.58 | O18: 6.19 | P18: 6.46 | Q18: 6.97 | R18: 7.3 | S18: 26.94 | T18: 35.57 | U18: 45.18
A19: Free Cash Flow
A20: CFFO | B20: 1667 | C20: 3041 | D20: 7709 | E20: 2955 | F20: 2366 | G20: 4145 | H20: 4329 | I20: 13796 | J20: 5815 | K20: 6149 | L20: 7185 | M20: 9622 | N20: 28771 | O20: 12585 | P20: 12292 | Q20: 13057 | R20: 13979 | S20: 51913 | T20: 68439 | U20: 91002
A21: Capex | B21: 546 | C21: 636 | D21: 974 | E21: 389 | F21: 808 | G21: 958 | H21: 1158 | I21: 3313 | J21: 900 | K21: 900 | L21: 900 | M21: 900 | N21: 3600 | O21: 900 | P21: 900 | Q21: 900 | R21: 900 | S21: 3600 | T21: 3600 | U21: 3600
A22: FCF | B22: 1121 | C22: 2405 | D22: 6735 | E22: 2566 | F22: 1558 | G22: 3187 | H22: 3171 | I22: 10483 | J22: 4915 | K22: 5249 | L22: 6285 | M22: 8722 | N22: 25171 | O22: 11685 | P22: 11392 | Q22: 12157 | R22: 13079 | S22: 48313 | T22: 64839 | U22: 87402
A23: % revenue | B23: 0.05 | C23: 0.09 | D23: 0.19 | E23: 0.25 | F23: 0.14 | G23: 0.24 | H23: 0.19 | I23: 0.2 | J23: 0.26 | K23: 0.25 | L23: 0.25 | M23: 0.27 | N23: 0.26 | O23: 0.36 | P23: 0.34 | Q23: 0.34 | R23: 0.35 | S23: 0.35 | T23: 0.37 | U23: 0.39
A24: Segment Revenues
A25: Data Center | B25: 6496 | C25: 12579 | D25: 16635 | E25: 5775 | F25: 6718 | G25: 8394 | H25: 12467 | I25: 33355 | J25: 14419 | K25: 16400 | L25: 20747 | M25: 27432 | N25: 78999 | O25: 27556 | P25: 28897 | Q25: 30359 | R25: 31716 | S25: 118528 | T25: 153270 | U25: 196924
A26: Data Center GPU Revenue | B26: 555 | C26: 5025 | D26: 6754 | E26: 2430 | F26: 2750 | G26: 3550 | H26: 6400 | I26: 15130 | J26: 7600 | K26: 8500 | L26: 11250 | M26: 15900 | N26: 43250 | O26: 15900 | P26: 17000 | Q26: 18100 | R26: 19200 | S26: 70200 | T26: 97800 | U26: 131400
A27: Server CPU Revenue | B27: 5433 | C27: 6794 | D27: 8827 | E27: 3065 | F27: 3684 | G27: 4539 | H27: 5705 | I27: 16993 | J27: 6457 | K27: 7537 | L27: 9133 | M27: 11167 | N27: 34295 | O27: 11261 | P27: 11468 | Q27: 11793 | R27: 12010 | S27: 46531 | T27: 52961 | U27: 61987
A28: Server ASP ($) | B28: 1140 | C28: 1351 | D28: 1347 | E28: 1535 | F28: 1591 | G28: 1647 | H28: 1725 | I28: 1638 | J28: 1775 | K28: 1850 | L28: 1975 | M28: 2100 | N28: 1943 | O28: 2107 | P28: 2114 | Q28: 2121 | R28: 2128 | S28: 2118 | T28: 2254 | U28: 2420
A29: Server Units (K) | B29: 4768 | C29: 5028 | D29: 6554 | E29: 1997 | F29: 2316 | G29: 2756 | H29: 3307 | I29: 10375 | J29: 3638 | K29: 4074 | L29: 4624 | M29: 5318 | N29: 17654 | O29: 5344 | P29: 5425 | Q29: 5560 | R29: 5644 | S29: 21973 | T29: 23493 | U29: 25616
A30: Server TAM (K units) | B30: 23307 | C30: 22432 | D30: 26046 | E30: 6506 | F30: 6640 | G30: 6727 | H30: 6939 | I30: 26812 | J30: 6683 | K30: 6823 | L30: 6913 | M30: 7126 | N30: 27545
A31: AMD Share | B31: 0.2 | C31: 0.22
A32: XLNX FPGAs | B32: 252 | C32: 318 | D32: 385 | E32: 89 | F32: 93 | G32: 98 | H32: 102 | I32: 382 | J32: 97 | K32: 92 | L32: 88 | M32: 83 | N32: 361 | O32: 86 | P32: 88 | Q32: 91 | R32: 94 | S32: 359 | T32: 405 | U32: 455
A33: Pensando | B33: 254 | C33: 441 | D33: 669 | E33: 191 | F33: 191 | G33: 208 | H33: 260 | I33: 850 | J33: 265 | K33: 271 | L33: 276 | M33: 282 | N33: 1094 | O33: 310 | P33: 341 | Q33: 375 | R33: 412 | S33: 1437 | T33: 2104 | U33: 3081
A34: Data Center Operating Margin | B34: 0.2 | C34: 0.28 | D34: 0.22 | E34: 0.28 | F34: 0.31 | G34: 0.31 | H34: 0.35 | I34: 0.32 | J34: 0.36 | K34: 0.36 | L34: 0.36 | M34: 0.36 | N34: 0.36 | O34: 0.37 | P34: 0.37 | Q34: 0.37 | R34: 0.37 | S34: 0.37 | T34: 0.38 | U34: 0.38
A35: Data Center Operating Profit Y/Y Drop-through | E35: 0.32 | F35: 0.65 | G35: 0.38 | H35: 0.37 | J35: 0.42 | K35: 0.39 | L35: 0.39 | M35: 0.37 | O35: 0.38 | P35: 0.38 | Q35: 0.39 | R35: 0.43
A36: Client | B36: 4651 | C36: 7054 | D36: 10640 | E36: 2885 | F36: 3062 | G36: 2997 | H36: 2957 | I36: 11901 | J36: 2900 | K36: 2847 | L36: 2987 | M36: 3147 | N36: 11881 | O36: 2943 | P36: 2969 | Q36: 3466 | R36: 3605 | S36: 12983 | T36: 14080 | U36: 14290
A37: PC Revenue | B37: 4386 | C37: 6718 | D37: 10154 | E37: 2751 | F37: 2914 | G37: 2952 | H37: 2938 | I37: 11555 | J37: 2876 | K37: 2822 | L37: 2947 | M37: 3130 | N37: 11775 | O37: 2921 | P37: 2947 | Q37: 3431 | R37: 3589 | S37: 12888 | T37: 13995 | U37: 14205
A38: Desktop Revenue | B38: 1386 | C38: 1863 | D38: 3196 | E38: 798 | F38: 829 | G38: 862 | H38: 827 | I38: 3317 | J38: 820 | K38: 807 | L38: 851 | M38: 909 | N38: 3387 | O38: 889 | P38: 884 | Q38: 1038 | R38: 1101 | S38: 3912 | T38: 4389 | U38: 4617
A39: AMD DT ASP ($) | B39: 174 | C39: 188 | D39: 266 | E39: 270 | F39: 275 | G39: 275 | H39: 272 | I39: 273 | J39: 278 | K39: 282 | L39: 286 | M39: 288 | N39: 284 | O39: 286 | P39: 286 | Q39: 311 | R39: 311 | S39: 299 | T39: 309 | U39: 307
A40: AMD DT Units (K) | B40: 7950 | C40: 9931 | D40: 12029 | E40: 2956 | F40: 3015 | G40: 3135 | H40: 3041 | I40: 12147 | J40: 2950 | K40: 2862 | L40: 2976 | M40: 3155 | N40: 11942 | O40: 3107 | P40: 3092 | Q40: 3339 | R40: 3539 | S40: 13078 | T40: 14202 | U40: 15038
A41: DT TAM (K units) | B41: 67010 | C41: 69021 | D41: 75737 | E41: 17683 | F41: 17652 | G41: 19987 | H41: 21236 | I41: 76558 | J41: 17685 | K41: 17667 | L41: 20019 | M41: 21277 | N41: 76647 | O41: 18215 | P41: 18197 | Q41: 20619 | R41: 21915 | S41: 78947 | T41: 81315 | U41: 83754
A42: AMD Share | B42: 0.12 | C42: 0.14 | D42: 0.16 | E42: 0.17 | F42: 0.17 | G42: 0.16 | H42: 0.14 | I42: 0.16 | J42: 0.17 | K42: 0.16 | L42: 0.15 | M42: 0.15 | N42: 0.16 | O42: 0.17 | P42: 0.17 | Q42: 0.16 | R42: 0.16 | S42: 0.17 | T42: 0.17 | U42: 0.18
A43: Mobile Revenue | B43: 3001 | C43: 4854 | D43: 6958 | E43: 1953 | F43: 2085 | G43: 2090 | H43: 2111 | I43: 8239 | J43: 2056 | K43: 2015 | L43: 2096 | M43: 2221 | N43: 8388 | O43: 2032 | P43: 2062 | Q43: 2393 | R43: 2488 | S43: 8975 | T43: 9606 | U43: 9588
A44: AMD Mobile ASP ($) | B44: 98 | C44: 115 | D44: 157 | E44: 173 | F44: 173 | G44: 170 | H44: 170 | I44: 172 | J44: 180 | K44: 180 | L44: 180 | M44: 180 | N44: 180 | O44: 178 | P44: 178 | Q44: 193 | R44: 193 | S44: 186 | T44: 193 | U44: 193
A45: AMD Mobile Units (K) | B45: 30609 | C45: 42212 | D45: 44314 | E45: 11264 | F45: 12052 | G45: 12293 | H45: 12416 | I45: 48026 | J45: 11423 | K45: 11195 | L45: 11642 | M45: 12341 | N45: 46601 | O45: 11415 | P45: 11587 | Q45: 12398 | R45: 12893 | S45: 48293 | T45: 49774 | U45: 49681
A46: Mobile TAM (K units) | B46: 160289 | C46: 186556 | D46: 180960 | E46: 41006 | F46: 42182 | G46: 43053 | H46: 43653 | I46: 169894 | J46: 41751 | K46: 42715 | L46: 43538 | M46: 43951 | N46: 171955 | O46: 43004 | P46: 43996 | Q46: 44844 | R46: 45270 | S46: 177114 | T46: 182427 | U46: 187900
A47: AMD Share | B47: 0.19 | C47: 0.23 | D47: 0.24 | E47: 0.27 | F47: 0.29 | G47: 0.29 | H47: 0.28 | I47: 0.28 | J47: 0.27 | K47: 0.26 | L47: 0.27 | M47: 0.28 | N47: 0.27 | O47: 0.27 | P47: 0.26 | Q47: 0.28 | R47: 0.28 | S47: 0.27 | T47: 0.27 | U47: 0.26
... A49: Client Operating Margin | B49: -0.01 | C49: 0.13 | D49: 0.23 | E49: 0.16 | F49: 0.15 | G49: 0.19 | H49: 0.2 | I49: 0.18 | J49: 0.18 | K49: 0.19 | L49: 0.2 | M49: 0.21 | N49: 0.2 | O49: 0.19 | P49: 0.19 | Q49: 0.2 | R49: 0.2 | S49: 0.2 | T49: 0.2 | U49: 0.2
A50: Client Operating Profit Y/Y Drop-through | E50: 0.03 | F50: -0.3 | G50: -0.57 | H50: 0.05 | J50: 3.51 | K50: -0.35 | L50: -2.79 | M50: 0.37 | O50: 0.86 | P50: 0.19 | Q50: 0.2 | R50: 0.13
A51: Gaming | B51: 6212 | C51: 2595 | D51: 3910 | E51: 720 | F51: 779 | G51: 640 | H51: 514 | I51: 2653 | J51: 583 | K51: 511 | L51: 568 | M51: 623 | N51: 2285 | O51: 795 | P51: 720 | Q51: 839 | R51: 927 | S51: 3281 | T51: 3725 | U51: 3795
A52: PC GPU Gaming Revenue | B52: 858 | C52: 707 | D52: 1618 | E52: 440 | F52: 388 | G52: 369 | H52: 313 | I52: 1510 | J52: 282 | K52: 310 | L52: 217 | M52: 272 | N52: 1081 | O52: 244 | P52: 269 | Q52: 188 | R52: 226 | S52: 927 | T52: 771 | U52: 641
A53: Semi-Custom Revenue | B53: 5354 | C53: 1888 | D53: 2292 | E53: 280 | F53: 391 | G53: 271 | H53: 201 | I53: 1143 | J53: 301 | K53: 201 | L53: 351 | M53: 351 | N53: 1204 | O53: 551 | P53: 451 | Q53: 651 | R53: 701 | S53: 2354 | T53: 2954 | U53: 3154
A54: Gaming Operating Margin | B54: 0.16 | C54: 0.11 | D54: 0.12 | E54: 0.11 | F54: 0.15 | G54: 0.15 | H54: 0.17 | I54: 0.14 | J54: 0.16 | K54: 0.15 | L54: 0.14 | M54: 0.15 | N54: 0.15 | O54: 0.16 | P54: 0.14 | Q54: 0.13 | R54: 0.14 | S54: 0.14 | T54: 0.16 | U54: 0.16
A55: Embedded | B55: 5321 | C55: 3557 | D55: 3454 | E55: 873 | F55: 977 | G55: 1149 | H55: 1184 | I55: 4183 | J55: 1160 | K55: 1172 | L55: 1207 | M55: 1219 | N55: 4757 | O55: 1243 | P55: 1256 | Q55: 1331 | R55: 1371 | S55: 5200 | T55: 5849 | U55: 6579
A56: Embedded Operating Margin | B56: 0.49 | C56: 0.4 | D56: 0.36 | E56: 0.39 | F56: 0.4 | G56: 0.42 | H56: 0.44 | I56: 0.41 | J56: 0.35 | K56: 0.32 | L56: 0.85 | M56: 1.76 | N56: 0.83 | O56: 1.56 | P56: 1.71 | Q56: 1.98 | R56: 2.15 | S56: 1.86 | T56: 2.67 | U56: 3.75
A57: Q/Q Revenue Growth
A58: Data Center | E58: 0.07 | F58: 0.16 | G58: 0.25 | H58: 0.49 | J58: 0.16 | K58: 0.14 | L58: 0.27 | M58: 0.32 | O58: 0 | P58: 0.05 | Q58: 0.05 | R58: 0.04
A59: Client | E59: -0.07 | F59: 0.06 | G59: -0.02 | H59: -0.01 | J59: -0.02 | K59: -0.02 | L59: 0.05 | M59: 0.05 | O59: -0.06 | P59: 0.01 | Q59: 0.17 | R59: 0.04
A60: Gaming | E60: -0.15 | F60: 0.08 | G60: -0.18 | H60: -0.2 | J60: 0.13 | K60: -0.12 | L60: 0.11 | M60: 0.1 | O60: 0.28 | P60: -0.09 | Q60: 0.17 | R60: 0.1
A61: Embedded | E61: -0.08 | F61: 0.12 | G61: 0.18 | H61: 0.03 | J61: -0.02 | K61: 0.01 | L61: 0.03 | M61: 0.01 | O61: 0.02 | P61: 0.01 | Q61: 0.06 | R61: 0.03
A62: Y/Y Revenue Growth
A63: Data Center | C63: 0.94 | D63: 0.32 | E63: 0.57 | F63: 1.07 | G63: 0.93 | H63: 1.32 | I63: 1.01 | J63: 1.5 | K63: 1.44 | L63: 1.47 | M63: 1.2 | N63: 1.37 | O63: 0.91 | P63: 0.76 | Q63: 0.46 | R63: 0.16 | S63: 0.5 | T63: 0.29 | U63: 0.28
A64: Client | C64: 0.52 | D64: 0.51 | E64: 0.26 | F64: 0.23 | G64: 0.09 | H64: -0.05 | I64: 0.12 | J64: 0.01 | K64: -0.07 | L64: 0 | M64: 0.06 | N64: 0 | O64: 0.01 | P64: 0.04 | Q64: 0.16 | R64: 0.15 | S64: 0.09 | T64: 0.08 | U64: 0.01
A65: Gaming | C65: -0.58 | D65: 0.51 | E65: 0.11 | F65: -0.31 | G65: -0.51 | H65: -0.39 | I65: -0.32 | J65: -0.19 | K65: -0.34 | L65: -0.11 | M65: 0.21 | N65: -0.14 | O65: 0.36 | P65: 0.41 | Q65: 0.48 | R65: 0.49 | S65: 0.44 | T65: 0.14 | U65: 0.02
A66: Embedded | C66: -0.33 | D66: -0.03 | E66: 0.06 | F66: 0.19 | G66: 0.34 | H66: 0.25 | I66: 0.21 | J66: 0.33 | K66: 0.2 | L66: 0.05 | M66: 0.03 | N66: 0.14 | O66: 0.07 | P66: 0.07 | Q66: 0.1 | R66: 0.12 | S66: 0.09 | T66: 0.12 | U66: 0.12

Sheet Fig33_INTC_Model
A1: Figure 33: INTC - Summary Model (p.22)
A2: Transcribed from the image table as printed (UBS estimates; Company data, FactSet). Percentages stored as fractions.
A3: Source: UBS Global Research (Timothy Arcuri, Seth Cho), 'US Semiconductors: $210B Server CPU TAM By C2030; Gated By Memory Supply', 26-Oct-2026
A5: Intel (INTC) - Key Metrics (in $MM except EPS and units) | B5: C2024A | C5: C2025A | D5: CQ1A | E5: CQ2A | F5: CQ3E | G5: CQ4E | H5: C2026E | I5: CQ1E | J5: CQ2E | K5: CQ3E | L5: CQ4E | M5: C2027E | N5: CQ1E | O5: CQ2E | P5: CQ3E | Q5: CQ4E | R5: C2028E | S5: C2029E | T5: C2030E
A6: Revenue (Non GAAP) | B6: 53101 | C6: 52853 | D6: 13577 | E6: 16128 | F6: 16974 | G6: 17769 | H6: 64448 | I6: 17886 | J6: 18134 | K6: 19202 | L6: 19970 | M6: 75192 | N6: 19978 | O6: 21156 | P6: 22673 | Q6: 23482 | R6: 87288 | S6: 107256 | T6: 132058
A7: Y/Y Growth | B7: -0.02 | C7: 0 | D7: 0.07 | E7: 0.25 | F7: 0.24 | G7: 0.3 | H7: 0.22 | I7: 0.32 | J7: 0.12 | K7: 0.13 | L7: 0.12 | M7: 0.17 | N7: 0.12 | O7: 0.17 | P7: 0.18 | Q7: 0.18 | R7: 0.16 | S7: 0.23 | T7: 0.23
A8: Gross Profit (Non -GAAP) | B8: 19099 | C8: 19410 | D8: 5570 | E8: 6737 | F8: 7180 | G8: 7552 | H8: 27039 | I8: 7566 | J8: 7798 | K8: 8449 | L8: 8897 | M8: 32709 | N8: 8780 | O8: 9361 | P8: 10101 | Q8: 10543 | R8: 38786 | S8: 48792 | T8: 62686
A9: Gross Margin | B9: 0.36 | C9: 0.367 | D9: 0.41 | E9: 0.418 | F9: 0.423 | G9: 0.425 | H9: 0.42 | I9: 0.423 | J9: 0.43 | K9: 0.44 | L9: 0.446 | M9: 0.435 | N9: 0.44 | O9: 0.443 | P9: 0.446 | Q9: 0.449 | R9: 0.444 | S9: 0.455 | T9: 0.475
A10: R&D (Non-GAAP) | B10: 16546 | C10: 13774 | D10: 3375 | E10: 3368 | F10: 3775 | G10: 3860 | H10: 14378 | I10: 3840 | J10: 3820 | K10: 3870 | L10: 3930 | M10: 15460 | N10: 4050 | O10: 4170 | P10: 4290 | Q10: 4410 | R10: 16920 | S10: 20140 | T10: 23050
A11: MG&A (Non-GAAP) | B11: 5507 | C11: 4624 | D11: 1038 | E11: 1175 | F11: 1250 | G11: 1280 | H11: 4743 | I11: 1200 | J11: 1250 | K11: 1320 | L11: 1380 | M11: 5150 | N11: 1310 | O11: 1430 | P11: 1530 | Q11: 1560 | R11: 5830 | S11: 6240 | T11: 6890
A12: Other | B12: -2700 | C12: -1904 | D12: -511 | E12: -576 | H12: -1087
A13: Total Opex (Non-GAAP) | B13: 19353 | C13: 16494 | D13: 3902 | E13: 3967 | F13: 4475 | G13: 4564 | H13: 16908 | I13: 4503 | J13: 4526 | K13: 4614 | L13: 4711 | M13: 18354 | N13: 4761 | O13: 4965 | P13: 5140 | Q13: 5266 | R13: 20131 | S13: 23162 | T13: 25978
A14: Y/Y Growth | B14: 0.02 | C14: -0.15 | D14: -0.09 | E14: -0.08 | F14: 0.14 | G14: 0.15 | H14: 0.03 | I14: 0.15 | J14: 0.14 | K14: 0.03 | L14: 0.03 | M14: 0.09 | N14: 0.06 | O14: 0.1 | P14: 0.11 | Q14: 0.12 | R14: 0.1 | S14: 0.15 | T14: 0.12
A15: Operating Income (Non-GAAP) | B15: -254 | C15: 2916 | D15: 1668 | E15: 2770 | F15: 2705 | G15: 2988 | H15: 10131 | I15: 3062 | J15: 3272 | K15: 3835 | L15: 4186 | M15: 14355 | N15: 4020 | O15: 4396 | P15: 4961 | Q15: 5278 | R15: 18655 | S15: 25630 | T15: 36708
A16: Operating Margin | B16: -0.005 | C16: 0.055 | D16: 0.123 | E16: 0.172 | F16: 0.159 | G16: 0.168 | H16: 0.157 | I16: 0.171 | J16: 0.18 | K16: 0.2 | L16: 0.21 | M16: 0.191 | N16: 0.201 | O16: 0.208 | P16: 0.219 | Q16: 0.225 | R16: 0.214 | S16: 0.239 | T16: 0.278
A17: Non-GAAP EPS | B17: -0.13 | C17: 0.42 | D17: 0.29 | E17: 0.43 | F17: 0.39 | G17: 0.45 | H17: 1.57 | I17: 0.46 | J17: 0.5 | K17: 0.59 | L17: 0.64 | M17: 2.2 | N17: 0.64 | O17: 0.69 | P17: 0.78 | Q17: 0.83 | R17: 2.94 | S17: 3.96 | T17: 5.42
A18: Free Cash Flow
A19: CFFO | B19: 8288 | C19: 9697 | D19: 1096 | E19: 7006 | F19: 6561 | G19: 4747 | H19: 19410 | I19: 3903 | J19: 6388 | K19: 7502 | L19: 7448 | M19: 25241 | N19: 6945 | O19: 8754 | P19: 9748 | Q19: 9549 | R19: 34996 | S19: 47299 | T19: 58197
A20: Less: Gross Capex | B20: 25122 | C20: 17672 | D20: 5136 | E20: 2479 | F20: 6000 | G20: 6600 | H20: 20215 | I20: 7500 | J20: 7000 | K20: 7000 | L20: 7000 | M20: 28500 | N20: 10000 | O20: 10000 | P20: 10000 | Q20: 10000 | R20: 40000 | S20: 40000 | T20: 30000
A21: Add: Contribution from Partners | B21: 14650 | C21: 6685 | D21: 1607 | E21: 2642 | F21: 1900 | G21: 2000 | H21: 8149 | I21: 1200 | J21: 700 | K21: 200 | L21: 200 | M21: 2300 | N21: 200 | O21: 200 | P21: 200 | Q21: 200 | R21: 800 | S21: 800 | T21: 800
A22: Net Capex | B22: 10472 | C22: 10987 | D22: 3529 | E22: -163 | F22: 4100 | G22: 4600 | H22: 12066 | I22: 6300 | J22: 6300 | K22: 6800 | L22: 6800 | M22: 26200 | N22: 9800 | O22: 9800 | P22: 9800 | Q22: 9800 | R22: 39200 | S22: 39200 | T22: 29200
A23: FCF | B23: -2228 | C23: -1612 | D23: -2433 | E23: 7169 | F23: 2461 | G23: 147 | H23: 7344 | I23: -2397 | J23: 88 | K23: 702 | L23: 648 | M23: -959 | N23: -2855 | O23: -1046 | P23: -52 | Q23: -251 | R23: -4204 | S23: 8099 | T23: 28997
A24: % of revenue | B24: -0.04 | C24: -0.03 | D24: -0.18 | E24: 0.44 | F24: 0.15 | G24: 0.01 | H24: 0.11 | I24: -0.13 | J24: 0 | K24: 0.04 | L24: 0.03 | M24: -0.01 | N24: -0.14 | O24: -0.05 | P24: 0 | Q24: -0.01 | R24: -0.05 | S24: 0.08 | T24: 0.22
A25: Y/Y Growth | D25: -0.34 | E25: -7.83 | F25: 1.75 | G25: -0.93 | I25: -0.01 | J25: -0.99 | K25: -0.71 | L25: 3.42 | N25: 0.19 | O25: -12.89 | P25: -1.07 | Q25: -1.39
A26: Product Revenue
A27: Intel Products | B27: 49471 | C27: 49147 | D27: 12779 | E27: 15139 | F27: 15932 | G27: 16654 | H27: 60504 | I27: 16634 | J27: 16916 | K27: 17884 | L27: 18609 | M27: 70042 | N27: 18219 | O27: 19177 | P27: 20374 | Q27: 20739 | R27: 78508 | S27: 86779 | T27: 93871
A28: Q/Q | D28: -0.01 | E28: 0.18 | F28: 0.05 | G28: 0.05 | I28: 0 | J28: 0.02 | K28: 0.06 | L28: 0.04 | N28: -0.02 | O28: 0.05 | P28: 0.06 | Q28: 0.02
A29: Y/Y | B29: 0.04 | C29: -0.01 | D29: 0.09 | E29: 0.28 | F29: 0.26 | G29: 0.29 | H29: 0.23 | I29: 0.3 | J29: 0.12 | K29: 0.12 | L29: 0.12 | M29: 0.16 | N29: 0.1 | O29: 0.13 | P29: 0.14 | Q29: 0.11 | R29: 0.12 | S29: 0.11 | T29: 0.08
A30: Operating Income | B30: 13008 | C30: 12739
A31: Operating Margin | B31: 0.26 | C31: 0.26
A32: CCPG | B32: 33346 | C32: 32228 | D32: 7727 | E32: 8877 | F32: 8895 | G32: 8756 | H32: 34255 | I32: 8098 | J32: 7801 | K32: 8148 | L32: 8143 | M32: 32190 | N32: 7624 | O32: 8014 | P32: 8384 | Q32: 8158 | R32: 32181 | S32: 33196 | T32: 34783
A33: Q/Q | D33: -0.06 | E33: 0.15 | F33: 0 | G33: -0.02 | I33: -0.08 | J33: -0.04 | K33: 0.04 | L33: 0 | N33: -0.06 | O33: 0.05 | P33: 0.05 | Q33: -0.03
A34: Y/Y | C34: -0.03 | D34: 0.01 | E34: 0.13 | F34: 0.04 | G34: 0.07 | H34: 0.06 | I34: 0.05 | J34: -0.12 | K34: -0.08 | L34: -0.07 | M34: -0.06 | N34: -0.06 | O34: 0.03 | P34: 0.03 | Q34: 0 | R34: 0 | S34: 0.03 | T34: 0.05
A35: Operating Income | B35: 11594 | C35: 9317 | D35: 2516 | E35: 2343
A36: Operating Margin | B36: 0.35 | C36: 0.29 | D36: 0.33 | E36: 0.26
A37: Desktop Revenue | B37: 9650 | C37: 8966 | D37: 2141 | E37: 2310 | F37: 2159 | G37: 2029 | H37: 8639 | I37: 1844 | J37: 1741 | K37: 1758 | L37: 1671 | M37: 7014 | N37: 1503 | O37: 1503 | P37: 1549 | Q37: 1626 | R37: 6182 | S37: 6078 | T37: 5977
A38: Q/Q | D38: -0.07 | E38: 0.08 | F38: -0.07 | G38: -0.06 | I38: -0.09 | J38: -0.06 | K38: 0.01 | L38: -0.05 | N38: -0.1 | P38: 0.03 | Q38: 0.05
A39: Y/Y | B39: -0.05 | C39: -0.07 | D39: 0.01 | E39: 0.07 | F39: -0.1 | G39: -0.12 | H39: -0.04 | I39: -0.14 | J39: -0.25 | K39: -0.19 | L39: -0.18 | M39: -0.19 | N39: -0.18 | O39: -0.14 | P39: -0.12 | Q39: -0.03 | R39: -0.12 | S39: -0.02 | T39: -0.02
A40: Desktop Units ('000s) | B40: 58316 | C40: 52506 | D40: 10886 | E40: 11267 | F40: 10478 | G40: 9849 | H40: 42479 | I40: 8864 | J40: 8244 | K40: 8244 | L40: 7832 | M40: 33184 | N40: 7048 | O40: 7048 | P40: 7260 | Q40: 7623 | R40: 28980 | S40: 27785 | T40: 26257
A41: Desktop ASP | B41: 165 | C41: 171 | D41: 197 | E41: 205 | F41: 206 | G41: 206 | H41: 203 | I41: 208 | J41: 211 | K41: 213 | L41: 213 | M41: 211 | N41: 213 | O41: 213 | P41: 213 | Q41: 213 | R41: 213 | S41: 219 | T41: 228
A42: Notebook Revenue | B42: 19091 | C42: 18657 | D42: 4449 | E42: 5381 | F42: 5537 | G42: 5648 | H42: 21015 | I42: 5196 | J42: 5013 | K42: 5290 | L42: 5340 | M42: 20840 | N42: 5011 | O42: 5412 | P42: 5683 | Q42: 5344 | R42: 21450 | S42: 22345 | T42: 23798
A43: Q/Q | D43: -0.08 | E43: 0.21 | F43: 0.03 | G43: 0.02 | I43: -0.08 | J43: -0.04 | K43: 0.06 | L43: 0.01 | N43: -0.06 | O43: 0.08 | P43: 0.05 | Q43: -0.06
A44: Y/Y | B44: 0.12 | C44: -0.02 | D44: 0.01 | E44: 0.21 | F44: 0.12 | G44: 0.17 | H44: 0.13 | I44: 0.17 | J44: -0.07 | K44: -0.04 | L44: -0.05 | M44: -0.01 | N44: -0.04 | O44: 0.08 | P44: 0.07 | Q44: 0 | R44: 0.03 | S44: 0.04 | T44: 0.06
A45: Notebook Units ('000s) | B45: 150490 | C45: 148178 | D45: 30748 | E45: 33207 | F45: 32543 | G45: 32543 | H45: 129041 | I45: 29940 | J45: 28742 | K45: 30179 | L45: 31085 | M45: 119946 | N45: 28598 | O45: 30886 | P45: 32430 | Q45: 30808 | R45: 122722 | S45: 125598 | T45: 128541
A46: Notebook ASP | B46: 127 | C46: 126 | D46: 145 | E46: 162 | F46: 170 | G46: 174 | H46: 163 | I46: 174 | J46: 174 | K46: 175 | L46: 172 | M46: 174 | N46: 175 | O46: 175 | P46: 175 | Q46: 173 | R46: 175 | S46: 178 | T46: 185
A47: Other | B47: 1549 | C47: 1365 | D47: 353 | E47: 355 | F47: 357 | G47: 359 | H47: 1424 | I47: 364 | J47: 369 | K47: 374 | L47: 379 | M47: 1485 | N47: 384 | O47: 390 | P47: 396 | Q47: 402 | R47: 1572 | S47: 1666 | T47: 1766
A48: NEX in CCG | B48: 3056 | C48: 3239 | D48: 784 | E48: 831 | F48: 848 | G48: 848 | H48: 3310 | I48: 848 | J48: 848 | K48: 890 | L48: 917 | M48: 3503 | N48: 899 | O48: 890 | P48: 934 | Q48: 962 | R48: 3685 | S48: 3866 | T48: 4057
A49: DCAI | B49: 16125 | C49: 16919 | D49: 5052 | E49: 6262 | F49: 7037 | G49: 7898 | H49: 26357 | I49: 8536 | J49: 9115 | K49: 9736 | L49: 10466 | M49: 37853 | N49: 10595 | O49: 11163 | P49: 11989 | Q49: 12580 | R49: 46328 | S49: 53583 | T49: 59088
A50: Q/Q | D50: 0.07 | E50: 0.24 | F50: 0.12 | G50: 0.12 | I50: 0.08 | J50: 0.07 | K50: 0.07 | L50: 0.07 | N50: 0.01 | O50: 0.05 | P50: 0.07 | Q50: 0.05
A51: Y/Y | C51: 0.05 | D51: 0.22 | E51: 0.59 | F51: 0.71 | G51: 0.67 | H51: 0.56 | I51: 0.69 | J51: 0.46 | K51: 0.38 | L51: 0.33 | M51: 0.44 | N51: 0.24 | O51: 0.22 | P51: 0.23 | Q51: 0.2 | R51: 0.22 | S51: 0.16 | T51: 0.1
A52: Operating Income | B52: 1414 | C52: 3422 | D52: 1542 | E52: 2956
A53: Operating Margin | B53: 0.09 | C53: 0.2 | D53: 0.31 | E53: 0.47
A54: Edge (ex-NEX in DCAI, incl Custom until D | B54: 3308 | C54: 3250 | D54: 766 | E54: 687 | F54: 694 | G54: 701 | H54: 2849 | I54: 687 | J54: 701 | K54: 743 | L54: 773 | M54: 2904 | N54: 757 | O54: 750 | P54: 787 | Q54: 811 | R54: 3105 | S54: 3258 | T54: 3418
A55: Custom ASIC | D55: 370 | E55: 500 | F55: 650 | G55: 800 | H55: 2320 | I55: 1000 | J55: 1150 | K55: 1288 | L55: 1443 | M55: 4881 | N55: 1587 | O55: 1745 | P55: 1920 | Q55: 2112 | R55: 7364 | S55: 9558 | T55: 11062
A56: Server Revenues | B56: 12817 | C56: 13419 | D56: 3916 | E56: 5075 | F56: 5693 | G56: 6397 | H56: 21080 | I56: 6784 | J56: 7197 | K56: 7635 | L56: 8177 | M56: 29793 | N56: 8173 | O56: 8587 | P56: 9196 | Q56: 9568 | R56: 35523 | S56: 40359 | T56: 44112
A57: Server Units ('000s) | B57: 15315 | C57: 16709 | D57: 4354 | E57: 4397 | F57: 4661 | G57: 4941 | H57: 18353 | I57: 5039 | J57: 5191 | K57: 5346 | L57: 5560 | M57: 21137 | N57: 5393 | O57: 5501 | P57: 5721 | Q57: 5779 | R57: 22395 | S57: 22682 | T57: 22975
A58: Server ASP | B58: 824 | C58: 791 | D58: 887 | E58: 1142 | F58: 1221 | G58: 1295 | H58: 1143 | I58: 1334 | J58: 1374 | K58: 1415 | L58: 1457 | M58: 1396 | N58: 1501 | O58: 1546 | P58: 1592 | Q58: 1640 | R58: 1571 | S58: 1761 | T58: 1898
A59: Accelerators | B59: 200 | C59: 200 | D59: 53 | E59: 55 | H59: 108 | I59: 64 | J59: 67 | K59: 71 | L59: 74 | M59: 276 | N59: 78 | O59: 82 | P59: 86 | Q59: 90 | R59: 335 | S59: 408 | T59: 495
A60: Intel Foundry | B60: 17317 | C60: 17826 | D60: 5421 | E60: 5765 | F60: 6365 | G60: 7037 | H60: 24588 | I60: 6945 | J60: 7060 | K60: 7422 | L60: 7598 | M60: 29025 | N60: 7600 | O60: 8190 | P60: 8861 | Q60: 9301 | R60: 33950 | S60: 45310 | T60: 62637
A61: Q/Q | D61: 0.2 | E61: 0.06 | F61: 0.1 | G61: 0.11 | I61: -0.01 | J61: 0.02 | K61: 0.05 | L61: 0.02 | N61: 0 | O61: 0.08 | P61: 0.08 | Q61: 0.05
A62: Y/Y | B62: -0.08 | C62: 0.03 | D62: 0.16 | E62: 0.31 | F62: 0.5 | G62: 0.56 | H62: 0.38 | I62: 0.28 | J62: 0.22 | K62: 0.17 | L62: 0.08 | M62: 0.18 | N62: 0.09 | O62: 0.16 | P62: 0.19 | Q62: 0.22 | R62: 0.17 | S62: 0.33 | T62: 0.38
A63: Internal Foundry Revenue | B63: 17288 | C63: 17683 | D63: 5251 | E63: 5477 | F63: 6025 | G63: 6627 | H63: 23380 | I63: 6495 | J63: 6560 | K63: 6822 | L63: 6958 | M63: 26835 | N63: 6750 | O63: 7020 | P63: 7371 | Q63: 7371 | R63: 28510 | S63: 28510 | T63: 28510
A64: External Foundry Revenue | B64: 29 | C64: 143 | D64: 170 | E64: 288 | F64: 340 | G64: 410 | H64: 1208 | I64: 450 | J64: 500 | K64: 600 | L64: 640 | M64: 2190 | N64: 850 | O64: 1170 | P64: 1490 | Q64: 1930 | R64: 5440 | S64: 16800 | T64: 34127
A65: Operating Income | B65: -13291 | C65: -10318 | D65: -2320 | E65: -2320
A66: Operating Margin | B66: -0.77 | C66: -0.58 | D66: -0.43 | E66: -0.4
A67: All Other | B67: 3601 | C67: 3563 | D67: 628 | E67: 701 | F67: 702 | G67: 705 | H67: 2736 | I67: 802 | J67: 717 | K67: 719 | L67: 722 | M67: 2960 | N67: 909 | O67: 808 | P67: 810 | Q67: 813 | R67: 3340 | S67: 3677 | T67: 4061
A68: Q/Q | D68: 0.09 | E68: 0.12 | F68: 0 | G68: 0 | I68: 0.14 | J68: -0.11 | K68: 0 | L68: 0 | N68: 0.26 | O68: -0.11 | P68: 0 | Q68: 0
A69: Y/Y | C69: -0.01 | D69: -0.33 | E69: -0.33 | F69: -0.29 | G69: 0.23 | H69: -0.23 | I69: 0.28 | J69: 0.02 | K69: 0.02 | L69: 0.02 | M69: 0.08 | N69: 0.13 | O69: 0.13 | P69: 0.13 | Q69: 0.13 | R69: 0.13 | S69: 0.1 | T69: 0.1
A70: Operating Income | B70: -57 | C70: 264 | D70: 103 | E70: -139
A71: Operating Margin | B71: -0.02 | C71: 0.07 | D71: 0.16 | E71: -0.2

Sheet Fig34_ARM_Model
A1: Figure 34: ARM - Summary Model (p.23)
A2: Transcribed from the image table as printed (UBS estimates; Company data, FactSet). Percentages stored as fractions.
A3: Source: UBS Global Research (Timothy Arcuri, Seth Cho), 'US Semiconductors: $210B Server CPU TAM By C2030; Gated By Memory Supply', 26-Oct-2026
A5: Arm Holdings Plc. (ARM) - Key Metrics (in $MM except EPS and units) | B5: C2022A | C5: C2023A | D5: C2024A | E5: C2025A | F5: FQ4:26A CQ1A | G5: FQ1A CQ2A | H5: FQ2E CQ3E | I5: FQ3E CQ4E | J5: C2026E | K5: FQ4:27E CQ1E | L5: FQ1E CQ2E | M5: FQ2E CQ3E | N5: FQ3E CQ4E | O5: C2027E | P5: FQ4:28E CQ1E | Q5: FQ1E CQ2E | R5: FQ2E CQ3E | S5: FQ3E CQ4E | T5: C2028E | U5: C2029E | V5: C2030E | W5: F2023A | X5: F2024A | Y5: F2025A | Z5: F2026E | AA5: F2027E
A6: Revenue | B6: 2703 | C6: 2938 | D6: 3694 | E6: 4671 | F6: 1490 | G6: 1289 | H6: 1379 | I6: 1552 | J6: 5711 | K6: 1923 | L6: 1710 | M6: 1855 | N6: 2162 | O6: 7650 | P6: 2505 | Q6: 2554 | R6: 2692 | S6: 2893 | T6: 10644 | U6: 14648 | V6: 24698 | W6: 2679 | X6: 3233 | Y6: 4007 | Z6: 4920 | AA6: 6143
A7: Y/Y Growth | C7: 0.087 | D7: 0.257 | E7: 0.264 | F7: 0.201 | G7: 0.224 | H7: 0.215 | I7: 0.25 | J7: 0.223 | K7: 0.29 | L7: 0.326 | M7: 0.345 | N7: 0.393 | O7: 0.34 | P7: 0.303 | Q7: 0.494 | R7: 0.451 | S7: 0.338 | T7: 0.391 | U7: 0.376 | V7: 0.686 | W7: -0.009 | X7: 0.207 | Y7: 0.239 | Z7: 0.228 | AA7: 0.249
A8: Gross Profit (Non-GAAP) | B8: 2592 | C8: 2837 | D8: 3607 | E8: 4588 | F8: 1465 | G8: 1264 | H8: 1354 | I8: 1527 | J8: 5611 | K8: 1818 | L8: 1628 | M8: 1730 | N8: 1951 | O8: 7126 | P8: 2212 | Q8: 2223 | R8: 2358 | S8: 2501 | T8: 9294 | U8: 12070 | V8: 17305 | W8: 2580 | X8: 3131 | Y8: 3926 | Z8: 4832 | AA8: 5964
A9: Gross Margin | B9: 0.959 | C9: 0.966 | D9: 0.976 | E9: 0.982 | F9: 0.983 | G9: 0.981 | H9: 0.982 | I9: 0.984 | J9: 0.982 | K9: 0.946 | L9: 0.952 | M9: 0.932 | N9: 0.902 | O9: 0.932 | P9: 0.883 | Q9: 0.87 | R9: 0.876 | S9: 0.864 | T9: 0.873 | U9: 0.824 | V9: 0.701 | W9: 0.963 | X9: 0.968 | Y9: 0.98 | Z9: 0.982 | AA9: 0.971
A10: Opex (Non-GAAP) | B10: 1839 | C10: 1821 | D10: 1994 | E10: 2549 | F10: 734 | G10: 733 | H10: 780 | I10: 822 | J10: 3069 | K10: 866 | L10: 900 | M10: 931 | N10: 966 | O10: 3662 | P10: 999 | Q10: 1038 | R10: 1077 | S10: 1117 | T10: 4232 | U10: 4909 | V10: 5564 | W10: 1797 | X10: 1723 | Y10: 2049 | Z10: 2717 | AA10: 3202
A11: Y/Y Growth | D11: 0.095 | E11: 0.278 | F11: 0.297 | G11: 0.184 | H11: 0.204 | I11: 0.148 | J11: 0.204 | K11: 0.18 | L11: 0.227 | M11: 0.193 | N11: 0.174 | O11: 0.193 | P11: 0.154 | Q11: 0.154 | R11: 0.157 | S11: 0.157 | T11: 0.155 | U11: 0.16 | V11: 0.133 | W11: -0.029 | X11: -0.041 | Y11: 0.189 | Z11: 0.326 | AA11: 0.178
A12: Operating Income (Non-GAAP) | B12: 753 | C12: 1016 | D12: 1613 | E12: 2039 | F12: 731 | G12: 531 | H12: 574 | I12: 705 | J12: 2541 | K12: 952 | L12: 728 | M12: 799 | N12: 986 | O12: 3464 | P12: 1213 | Q12: 1185 | R12: 1281 | S12: 1384 | T12: 5062 | U12: 7161 | V12: 11741 | W12: 783 | X12: 1408 | Y12: 1877 | Z12: 2115 | AA12: 2762
A13: Operating Margin | B13: 0.279 | C13: 0.346 | D13: 0.437 | E13: 0.437 | F13: 0.491 | G13: 0.412 | H13: 0.416 | I13: 0.454 | J13: 0.445 | K13: 0.495 | L13: 0.426 | M13: 0.431 | N13: 0.456 | O13: 0.453 | P13: 0.484 | Q13: 0.464 | R13: 0.476 | S13: 0.478 | T13: 0.476 | U13: 0.489 | V13: 0.475 | W13: 0.292 | X13: 0.436 | Y13: 0.468 | Z13: 0.43 | AA13: 0.45
A14: Non-GAAP EPS | B14: 0.62 | C14: 0.94 | D14: 1.45 | E14: 1.72 | F14: 0.6 | G14: 0.45 | H14: 0.48 | I14: 0.58 | J14: 2.1 | K14: 0.78 | L14: 0.6 | M14: 0.66 | N14: 0.81 | O14: 2.85 | P14: 0.99 | Q14: 0.97 | R14: 1.05 | S14: 1.13 | T14: 4.14 | U14: 5.8 | V14: 9.31 | W14: 0.64 | X14: 1.28 | Y14: 1.64 | Z14: 1.77 | AA14: 2.28
A15: Free Cash Flow
A16: CFFO | B16: 256 | C16: 906 | D16: 806 | E16: 1522 | F16: 260 | G16: 902 | H16: 510 | I16: 536 | J16: 2208 | K16: 538 | L16: 1013 | M16: 686 | N16: 684 | O16: 2921 | P16: 859 | Q16: 1156 | R16: 1159 | S16: 1200 | T16: 4374 | U16: 5644 | V16: 8910 | W16: 739 | X16: 1090 | Y16: 397 | Z16: 1524 | AA16: 2486
A17: Capex and intangibles | B17: -104 | C17: -182 | D17: -233 | E17: -629 | F17: -108 | G17: -237 | H17: -177 | I17: -200 | J17: -722 | K17: -247 | L17: -203 | M17: -220 | N17: -256 | O17: -926 | P17: -297 | Q17: -277 | R17: -292 | S17: -314 | T17: -1180 | U17: -1474 | V17: -2239 | W17: -133 | X17: -183 | Y17: -298 | Z17: -642 | AA17: -861
A18: FCF | B18: 152 | C18: 724 | D18: 573 | E18: 893 | F18: 152 | G18: 665 | H18: 332 | I18: 337 | J18: 1486 | K18: 291 | L18: 810 | M18: 466 | N18: 427 | O18: 1995 | P18: 562 | Q18: 879 | R18: 867 | S18: 886 | T18: 3194 | U18: 4170 | V18: 6671 | W18: 606 | X18: 907 | Y18: 99 | Z18: 882 | AA18: 1625
A19: % of revenue | B19: -0.06 | C19: -0.246 | D19: -0.155 | E19: -0.191 | F19: -0.102 | G19: -0.516 | H19: -0.241 | I19: -0.217 | J19: -0.26 | K19: -0.151 | L19: -0.474 | M19: -0.251 | N19: -0.198 | O19: -0.261 | P19: -0.224 | Q19: -0.344 | R19: -0.322 | S19: -0.306 | T19: -0.3 | U19: -0.285 | V19: -0.27 | W19: 0.226 | X19: 0.281 | Y19: 0.025 | Z19: 0.179 | AA19: 0.265
A20: Y/Y Growth | C20: 3.763 | D20: -0.209 | E20: 0.558 | F20: -0.067 | G20: 3.433 | H20: -0.191 | I20: 0.993 | J20: 0.664 | K20: 0.915 | L20: 0.219 | M20: 0.403 | N20: 0.269 | O20: 0.342 | P20: 0.93 | Q20: 0.085 | R20: 0.859 | S20: 1.072 | T20: 0.601 | U20: 0.306 | V20: 0.6 | W20: 0.751 | X20: 0.497 | Y20: -0.891 | Z20: 7.909 | AA20: 0.843
A21: Revenue Reporting
A22: Royalty revenue | B22: 1725 | C22: 1662 | D22: 2075 | E22: 2549 | F22: 671 | G22: 715 | H22: 708 | I22: 807 | J22: 2901 | K22: 831 | L22: 856 | M22: 899 | N22: 975 | O22: 3561 | P22: 1019 | Q22: 1029 | R22: 1112 | S22: 1201 | T22: 4361 | U22: 5332 | V22: 6377 | W22: 1675 | X22: 1802 | Y22: 2168 | Z22: 2613 | AA22: 3061
A23: % of revenue | B23: 0.64 | C23: 0.566 | D23: 0.562 | E23: 0.546 | F23: 0.45 | G23: 0.555 | H23: 0.513 | I23: 0.52 | J23: 0.508 | K23: 0.432 | L23: 0.501 | M23: 0.485 | N23: 0.451 | O23: 0.466 | P23: 0.407 | Q23: 0.403 | R23: 0.413 | S23: 0.415 | T23: 0.41 | U23: 0.364 | V23: 0.258 | W23: 0.625 | X23: 0.557 | Y23: 0.541 | Z23: 0.531 | AA23: 0.498
A24: Y/Y growth | C24: -0.037 | D24: 0.248 | E24: 0.228 | F24: 0.105 | G24: 0.222 | H24: 0.142 | I24: 0.095 | J24: 0.138 | K24: 0.239 | L24: 0.197 | M24: 0.27 | N24: 0.209 | O24: 0.228 | P24: 0.226 | Q24: 0.202 | R24: 0.237 | S24: 0.231 | T24: 0.224 | U24: 0.223 | V24: 0.196 | W24: 0.072 | X24: 0.076 | Y24: 0.203 | Z24: 0.205 | AA24: 0.171
A25: Q/Q growth | F25: -0.09 | G25: 0.066 | H25: -0.01 | I25: 0.14 | K25: 0.03 | L25: 0.03 | M25: 0.05 | N25: 0.085 | P25: 0.045 | Q25: 0.01 | R25: 0.08 | S25: 0.08
A26: of which ARM v7 | D26: 0.9 | E26: 0.25 | W26: 0.43 | X26: 0.36 | Y26: 0.286 | Z26: 0.25
A27: of which ARM v8 | D27: 1.35 | E27: 0.44 | W27: 0.49 | X27: 0.465 | Y27: 0.447 | Z27: 0.15
A28: of which ARM v9 | C28: 0.25 | D28: 0.95 | E28: 0.31 | W28: 0.08 | X28: 0.175 | Y28: 0.267 | Z28: 0.6
A29: License and other revenue | B29: 978 | C29: 1276 | D29: 1619 | E29: 2122 | F29: 819 | G29: 574 | H29: 672 | I29: 745 | J29: 2810 | K29: 991 | L29: 754 | M29: 776 | N29: 807 | O29: 3328 | P29: 936 | Q29: 908 | R29: 890 | S29: 899 | T29: 3634 | U29: 3659 | V29: 3693 | W29: 1004 | X29: 1431 | Y29: 1839 | Z29: 2307 | AA29: 2982
A30: % of Total revenue | B30: 0.36 | C30: 0.434 | D30: 0.438 | E30: 0.454 | F30: 0.55 | G30: 0.445 | H30: 0.487 | I30: 0.48 | J30: 0.492 | K30: 0.516 | L30: 0.441 | M30: 0.418 | N30: 0.373 | O30: 0.435 | P30: 0.374 | Q30: 0.356 | R30: 0.331 | S30: 0.311 | T30: 0.341 | U30: 0.25 | V30: 0.15 | W30: 0.375 | X30: 0.443 | Y30: 0.459 | Z30: 0.469 | AA30: 0.485
A31: Y/Y growth | C31: 0.305 | D31: 0.269 | E31: 0.311 | F31: 0.292 | G31: 0.226 | H31: 0.304 | I31: 0.476 | J31: 0.324 | K31: 0.211 | L31: 0.313 | M31: 0.156 | N31: 0.083 | O31: 0.184 | P31: -0.056 | Q31: 0.205 | R31: 0.147 | S31: 0.114 | T31: 0.092 | U31: 0.007 | V31: 0.009 | W31: -0.12 | X31: 0.425 | Y31: 0.285 | Z31: 0.254 | AA31: 0.293
A32: Q/Q growth | F32: 0.622 | G32: -0.299 | H32: 0.17 | I32: 0.11 | K32: 0.33 | L32: -0.24 | M32: 0.03 | N32: 0.04 | P32: 0.16 | Q32: -0.03 | R32: -0.02 | S32: 0.01
A33: Annualized Contract Value (ACV) | B33: 4171 | C33: 4346 | D33: 4898 | E33: 6113 | W33: 1030 | X33: 1182 | Y33: 1365
A34: % Y/Y | C34: 0.042 | D34: 0.127 | E34: 0.248 | X34: 0.148 | Y34: 0.155
A35: % Q/Q
A36: Remaining Performance Obligation (RPO) | B36: 6993 | C36: 8177 | D36: 9362 | E36: 8852 | W36: 1712 | X36: 2484 | Y36: 2226
A37: % Y/Y | C37: 0.169 | D37: 0.145 | E37: -0.054 | W37: -0.022 | X37: 0.451 | Y37: -0.104
A38: % Q/Q
A39: implied orders | B39: 408 | C39: 1528 | D39: 1162 | E39: 1043 | F39: 518 | G39: 935 | H39: 1020 | I39: 1132 | J39: 3604 | K39: 1505 | L39: 1151 | M39: 1186 | N39: 1233 | O39: 5076 | P39: 1431 | Q39: 1397 | R39: 1369 | S39: 1383 | T39: 5580 | U39: 5655 | V39: 5746 | W39: 530 | X39: 1823 | Y39: 1163 | Z39: 1143 | AA39: 4592
A40: book-to-bill | B40: 2.4 | C40: 0.8 | D40: 1.4 | E40: 2 | F40: 0.9 | G40: 1.1 | H40: 1 | I40: 1 | J40: 0.8 | K40: 1 | L40: 1 | M40: 1 | N40: 1 | O40: 0.7 | P40: 1 | Q40: 1 | R40: 1 | S40: 1 | T40: 0.7 | U40: 0.6 | V40: 0.6 | W40: 0.9 | X40: 1.7 | Y40: 0.8 | Z40: 0.9 | AA40: 1

Sheet Fig35_INTC_New_vs_Old
A1: Figure 35: INTC - New vs Old Estimates (p.24)
A2: Transcribed from the image table as printed (UBS estimates; Company data, FactSet). Percentages stored as fractions.
A3: Source: UBS Global Research (Timothy Arcuri, Seth Cho), 'US Semiconductors: $210B Server CPU TAM By C2030; Gated By Memory Supply', 26-Oct-2026
B5: C2026E New | C5: C2026E Old | D5: C2026E Change | E5: C2027E New | F5: C2027E Old | G5: C2027E Change | H5: C2028E New | I5: C2028E Old | J5: C2028E Change
A6: Revenue ($MM) | B6: 64448 | C6: 64448 | E6: 75192 | F6: 75192 | H6: 87382 | I6: 87382
A7: Y/Y Growth | B7: 0.219 | C7: 0.219 | E7: 0.167 | F7: 0.167 | H7: 0.162 | I7: 0.162
A8: Gross Margin | B8: 0.42 | C8: 0.42 | E8: 0.435 | F8: 0.435 | H8: 0.444 | I8: 0.444
A9: Operating Margin | B9: 0.157 | C9: 0.156 | D9: 0.002 | E9: 0.191 | F9: 0.191 | H9: 0.214 | I9: 0.214
A10: Non-GAAP EPS | B10: 1.57 | C10: 1.55 | D10: 0.011 | E10: 2.2 | F10: 2.19 | G10: 0 | H10: 2.94 | I10: 2.94 | J10: 0
A11: FCF | B11: 7344 | C11: 7244 | D11: 0.014 | E11: -959 | F11: -962 | G11: -0.003 | H11: -4077 | I11: -4080 | J11: -0.001
A12: Gross Capex | B12: 20215 | C12: 20215 | E12: 28500 | F12: 28500 | H12: 40000 | I12: 40000
A13: Segment Revenues ($MM)
A14: Intel Products | B14: 60504 | C14: 60504 | E14: 70042 | F14: 70042 | H14: 78602 | I14: 78602
A15: Y/Y Growth | B15: 0.231 | C15: 0.231 | E15: 0.158 | F15: 0.158 | H15: 0.122 | I15: 0.122
A16: Client Computing (CCPG) | B16: 34255 | C16: 34255 | E16: 32190 | F16: 32190 | H16: 32181 | I16: 32181
A17: Y/Y Growth | B17: 0.063 | C17: 0.063 | E17: -0.06 | F17: -0.06 | H17: 0 | I17: 0
A18: Datacenter and AI (DCAI) | B18: 26357 | C18: 26357 | E18: 37853 | F18: 37853 | H18: 46421 | I18: 46421
A19: Y/Y Growth | B19: 0.558 | C19: 0.558 | E19: 0.436 | F19: 0.436 | H19: 0.226 | I19: 0.226
A20: Intel Foundry | B20: 24588 | C20: 24588 | E20: 29025 | F20: 29025 | H20: 33950 | I20: 33950
A21: Y/Y Growth | B21: 0.379 | C21: 0.379 | E21: 0.18 | F21: 0.18 | H21: 0.17 | I21: 0.17
A22: of which external revenue | B22: 1208 | C22: 1208 | E22: 2190 | F22: 2190 | H22: 5440 | I22: 5440
A23: All Other | B23: 2736 | C23: 2736 | E23: 2960 | F23: 2960 | H23: 3340 | I23: 3340
A24: Y/Y Growth | B24: -0.232 | C24: -0.232 | E24: 0.082 | F24: 0.082 | H24: 0.128 | I24: 0.128
A25: Intersegment Eliminations | B25: -23380 | C25: -23380 | E25: -26835 | F25: -26835 | H25: -28510 | I25: -28510

Sheet Fig36_UBSe_vs_Street
A1: Figure 36: UBSe vs. Street (p.25)
A2: Transcribed from the image table as printed (UBS estimates; Company data, FactSet). Percentages stored as fractions.
A3: Source: UBS Global Research (Timothy Arcuri, Seth Cho), 'US Semiconductors: $210B Server CPU TAM By C2030; Gated By Memory Supply', 26-Oct-2026
B5: Actual 2025 | C5: Actual 2026/1F | D5: Actual 2026/2F | E5: Estimate 2026/3F | F5: Estimate 2026/4F | G5: Estimate 2026 | H5: Estimate 2027/1F | I5: Estimate 2027/2F | J5: Estimate 2027/3F | K5: Estimate 2027/4F | L5: Estimate 2027 | M5: Estimate 2028/1F | N5: Estimate 2028/2F | O5: Estimate 2028/3F | P5: Estimate 2028/4F | Q5: Estimate 2028
A6: Revenues ($MM)
A7: UBS New | B7: 52853 | C7: 13577 | D7: 16128 | E7: 16974 | F7: 17769 | G7: 64448 | H7: 17886 | I7: 18134 | J7: 19202 | K7: 19970 | L7: 75192 | M7: 19978 | N7: 21156 | O7: 22673 | P7: 23482 | Q7: 87288
A8: UBS Old | E8: 16974 | F8: 17769 | G8: 64448 | H8: 17886 | I8: 18134 | J8: 19202 | K8: 19970 | L8: 75192 | M8: 19899 | N8: 21155 | O8: 22757 | P8: 23571 | Q8: 87382
A9: Consensus | E9: 16518 | F9: 17119 | G9: 63341 | H9: 16928 | I9: 17858 | J9: 18799 | K9: 19584 | L9: 73169 | M9: 19507 | N9: 20357 | O9: 21513 | P9: 22612 | Q9: 83990
A10: Delta | E10: 0.028 | F10: 0.038 | G10: 0.017 | H10: 0.057 | I10: 0.015 | J10: 0.021 | K10: 0.02 | L10: 0.028 | M10: 0.024 | N10: 0.039 | O10: 0.054 | P10: 0.038 | Q10: 0.039
A11: Non-GAAP EPS
A12: UBS New | B12: 0.42 | C12: 0.29 | D12: 0.43 | E12: 0.39 | F12: 0.45 | G12: 1.57 | H12: 0.46 | I12: 0.5 | J12: 0.59 | K12: 0.64 | L12: 2.2 | M12: 0.64 | N12: 0.69 | O12: 0.78 | P12: 0.83 | Q12: 2.94
A13: UBS Old | E13: 0.39 | F13: 0.45 | G13: 1.57 | H13: 0.46 | I13: 0.5 | J13: 0.59 | K13: 0.64 | L13: 2.2 | M13: 0.63 | N13: 0.69 | O13: 0.79 | P13: 0.83 | Q13: 2.94
A14: Consensus | E14: 0.4 | F14: 0.44 | G14: 1.56 | H14: 0.41 | I14: 0.49 | J14: 0.58 | K14: 0.65 | L14: 2.13 | M14: 0.67 | N14: 0.75 | O14: 0.85 | P14: 0.94 | Q14: 3.22
A15: Delta | E15: -0.035 | F15: 0.024 | G15: 0.008 | H15: 0.137 | I15: 0.018 | J15: 0.008 | K15: -0.016 | L15: 0.028 | M15: -0.054 | N15: -0.075 | O15: -0.083 | P15: -0.123 | Q15: -0.087

Sheet Fig37_INTC_SOTP_New
A1: Figure 37: Intel SOTP Valuation (New) (p.26)
A2: Transcribed from the image table as printed (UBS estimates; Company data, FactSet). Percentages stored as fractions.
A3: Source: UBS Global Research (Timothy Arcuri, Seth Cho), 'US Semiconductors: $210B Server CPU TAM By C2030; Gated By Memory Supply', 26-Oct-2026
B5: Total $MM | C5: Per Share | D5: Comments
A6: Intel Products
A7: Revenue | B7: 70042
A8: Normalized EBIT margin | B8: 0.25
A9: Normalized EBIT | B9: 17511
A10: Peer EV/EBIT | B10: 27
A11: Products SoTP Value | B11: 465783 | C11: 86
A12: Intel Foundry
A13: Intel Capacity (k-wsm) | B13: 364
A14: Peer Value per k-wsm | B14: 160
A15: Gross Foundry Value | B15: 58393 | C15: 11
A16: Noncontrolling Interest | B16: -14200 | C16: -3 | D16: Brookfield only, at historical cost
A17: Net Foundry SoTP Value | B17: 44193 | C17: 8
A18: Other
A19: Market Cap | B19: 14310 | D19: Based on valuation and market cap.
A20: Intel Stake | B20: 0.61
A21: Other SoTP Value | B21: 8736 | C21: 2
A22: TOTAL
A23: SoTP Enterprise Value | B23: 518712 | C23: 95
A24: Net Debt | B24: 27184 | C24: 5
A25: SoTP Equity Value | B25: 545896 | C25: 100

Sheet Fig38_INTC_SOTP_Old
A1: Figure 38: Intel SOTP Valuation (Old) (p.26)
A2: Transcribed from the image table as printed (UBS estimates; Company data, FactSet). Percentages stored as fractions.
A3: Source: UBS Global Research (Timothy Arcuri, Seth Cho), 'US Semiconductors: $210B Server CPU TAM By C2030; Gated By Memory Supply', 26-Oct-2026
B5: Total $MM | C5: Per Share | D5: Comments
A6: Intel Products
A7: Revenue | B7: 70042
A8: Normalized EBIT margin | B8: 0.25
A9: Normalized EBIT | B9: 17511
A10: Peer EV/EBIT | B10: 27
A11: Products SoTP Value | B11: 476289 | C11: 88
A12: Intel Foundry
A13: Intel Capacity (k-wsm) | B13: 364
A14: Peer Value per k-wsm | B14: 166
A15: Gross Foundry Value | B15: 60445 | C15: 11
A16: Noncontrolling Interest | B16: -14200 | C16: -3 | D16: Brookfield only, at historical cost
A17: Net Foundry SoTP Value | B17: 46245 | C17: 9
A18: Other
A19: Market Cap | B19: 14888 | D19: Based on valuation and market cap.
A20: Intel Stake | B20: 0.62
A21: Other SoTP Value | B21: 9198 | C21: 2
A22: TOTAL
A23: SoTP Enterprise Value | B23: 531732 | C23: 98
A24: Net Debt | B24: 27184 | C24: 5
A25: SoTP Equity Value | B25: 558916 | C25: 103

Sheet Fig39_INTC_Foundry_Comps
A1: Figure 39: Intel Foundry Comps (p.26)
A2: Transcribed from the image table as printed (UBS estimates; Company data, FactSet). Percentages stored as fractions.
A3: Source: UBS Global Research (Timothy Arcuri, Seth Cho), 'US Semiconductors: $210B Server CPU TAM By C2030; Gated By Memory Supply', 26-Oct-2026
A5: Ticker | B5: Company Name | C5: Capacity | D5: EV | E5: EV/k-wsm
A6: 2330-TW | B6: TSMC | C6: 1642 | D6: 1802505 | E6: 604
A7: 005930-KR | B7: Samsung Foundry | C7: 1685 | D7: 969422 | E7: 178
A8: 2303-TW | B8: UMC | C8: 440 | D8: 45618 | E8: 104
A9: 981-HK | B9: SMIC | C9: 507 | D9: 65426 | E9: 129
A10: GFS-US | B10: GlobalFoundries | C10: 292 | D10: 23736 | E10: 81
A11: 1347-HK | B11: Hua Hong | C11: 247 | D11: 18747 | E11: 76
A12: 688249-CN | B12: Vanguard (200mm) | C12: 146 | D12: 8752 | E12: 60
A13: 6770-TW | B13: PSMC (200mm) | C13: 163 | D13: 8379 | E13: 51
B14: Simple Average | C14: 640 | D14: 367823 | E14: 160
B15: Median | C15: 366 | D15: 34677 | E15: 92

Sheet Fig28_31_Provenance
A1: Figs 28-31: provenance of each digitized cell
A2: label = printed segment label (+/-0.5pp) · measured = vector segment height (+/-0.05pp) · measured_x_S = height rescaled by the bar's plotted sum S (Fig 29 bars are drawn scaled to 100% although the plotted series sum to only 28-99%; the unplotted residual is almost certainly Rome/Zen 2 — Fig 31's 7nm = Milan + residual within 1pp) · not_drawn = segment absent
A3: Source: UBS Global Research (Timothy Arcuri, Seth Cho), 'US Semiconductors: $210B Server CPU TAM By C2030; Gated By Memory Supply', 26-Oct-2026
A5: Fig 28 INTC product mix
A6: quarter | B6: granite_rapids_src | C6: sierra_forest_src | D6: emerald_rapids_src | E6: sapphire_rapids_src | F6: ice_lake_src | G6: cascade_lake_src | H6: others_src | I6: unplotted_residual_src
A7: 1Q21 | B7: not_drawn | C7: not_drawn | D7: not_drawn | E7: not_drawn | F7: measured | G7: label | H7: label | I7: n/a
A8: 2Q21 | B8: not_drawn | C8: not_drawn | D8: not_drawn | E8: not_drawn | F8: label | G8: label | H8: label | I8: n/a
A9: 3Q21 | B9: not_drawn | C9: not_drawn | D9: not_drawn | E9: not_drawn | F9: label | G9: label | H9: label | I9: n/a
A10: 4Q21 | B10: not_drawn | C10: not_drawn | D10: not_drawn | E10: not_drawn | F10: label | G10: label | H10: label | I10: n/a
A11: 1Q22 | B11: not_drawn | C11: not_drawn | D11: not_drawn | E11: measured | F11: label | G11: label | H11: label | I11: n/a
A12: 2Q22 | B12: not_drawn | C12: not_drawn | D12: not_drawn | E12: measured | F12: label | G12: label | H12: label | I12: n/a
A13: 3Q22 | B13: not_drawn | C13: not_drawn | D13: not_drawn | E13: measured | F13: label | G13: label | H13: label | I13: n/a
A14: 4Q22 | B14: not_drawn | C14: not_drawn | D14: not_drawn | E14: measured | F14: label | G14: label | H14: label | I14: n/a
A15: 1Q23 | B15: not_drawn | C15: not_drawn | D15: not_drawn | E15: measured | F15: label | G15: label | H15: label | I15: n/a
A16: 2Q23 | B16: not_drawn | C16: not_drawn | D16: not_drawn | E16: label | F16: label | G16: label | H16: label | I16: n/a
A17: 3Q23 | B17: not_drawn | C17: not_drawn | D17: measured | E17: label | F17: label | G17: label | H17: not_drawn | I17: n/a
... A28: 2Q26 | B28: label | C28: label | D28: label | E28: label | F28: label | G28: not_drawn | H28: measured_x_S | I28: 100-S
A30: Fig 29 AMD product mix
A31: quarter | B31: venice_src | C31: turin_src | D31: bergamo_src | E31: siena_src | F31: genoa_src | G31: milan_src | H31: others_src | I31: unplotted_residual_src
A32: 1Q21 | B32: not_drawn | C32: not_drawn | D32: not_drawn | E32: not_drawn | F32: not_drawn | G32: label | H32: label | I32: 100-S
A33: 2Q21 | B33: not_drawn | C33: not_drawn | D33: not_drawn | E33: not_drawn | F33: not_drawn | G33: label | H33: label | I33: 100-S
A34: 3Q21 | B34: not_drawn | C34: not_drawn | D34: not_drawn | E34: not_drawn | F34: not_drawn | G34: label | H34: label | I34: 100-S
A35: 4Q21 | B35: not_drawn | C35: not_drawn | D35: not_drawn | E35: not_drawn | F35: not_drawn | G35: label | H35: label | I35: 100-S
A36: 1Q22 | B36: not_drawn | C36: not_drawn | D36: not_drawn | E36: not_drawn | F36: measured_x_S | G36: label | H36: label | I36: 100-S
A37: 2Q22 | B37: not_drawn | C37: not_drawn | D37: not_drawn | E37: not_drawn | F37: measured_x_S | G37: label | H37: label | I37: 100-S
A38: 3Q22 | B38: not_drawn | C38: not_drawn | D38: not_drawn | E38: not_drawn | F38: measured_x_S | G38: label | H38: label | I38: 100-S
A39: 4Q22 | B39: not_drawn | C39: not_drawn | D39: not_drawn | E39: not_drawn | F39: label | G39: label | H39: label | I39: 100-S
A40: 1Q23 | B40: not_drawn | C40: not_drawn | D40: measured_x_S | E40: not_drawn | F40: label | G40: label | H40: label | I40: 100-S
A41: 2Q23 | B41: not_drawn | C41: not_drawn | D41: measured_x_S | E41: measured_x_S | F41: label | G41: label | H41: label | I41: 100-S
A42: 3Q23 | B42: not_drawn | C42: not_drawn | D42: label | E42: measured_x_S | F42: label | G42: label | H42: label | I42: 100-S
... A53: 2Q26 | B53: label | C53: label | D53: label | E53: measured_x_S | F53: label | G53: label | H53: measured_x_S | I53: 100-S
A55: Fig 30 INTC node mix
A56: quarter | B56: intel_14_src | C56: intel_10_src | D56: intel_7_src | E56: intel_3_src | F56: unknown_other_src | G56: unplotted_residual_src
A57: 1Q21 | B57: label | C57: measured | D57: not_drawn | E57: not_drawn | F57: label | G57: n/a
A58: 2Q21 | B58: label | C58: label | D58: not_drawn | E58: not_drawn | F58: label | G58: n/a
A59: 3Q21 | B59: label | C59: label | D59: not_drawn | E59: not_drawn | F59: label | G59: n/a
A60: 4Q21 | B60: label | C60: label | D60: not_drawn | E60: not_drawn | F60: label | G60: n/a
A61: 1Q22 | B61: label | C61: label | D61: measured | E61: not_drawn | F61: label | G61: n/a
A62: 2Q22 | B62: label | C62: label | D62: measured | E62: not_drawn | F62: label | G62: n/a
A63: 3Q22 | B63: label | C63: label | D63: measured | E63: not_drawn | F63: label | G63: n/a
A64: 4Q22 | B64: label | C64: label | D64: label | E64: not_drawn | F64: label | G64: n/a
A65: 1Q23 | B65: label | C65: label | D65: label | E65: not_drawn | F65: label | G65: n/a
A66: 2Q23 | B66: label | C66: label | D66: label | E66: not_drawn | F66: label | G66: n/a
A67: 3Q23 | B67: label | C67: label | D67: label | E67: not_drawn | F67: not_drawn | G67: n/a
... A78: 2Q26 | B78: not_drawn | C78: label | D78: label | E78: label | F78: label | G78: n/a
A80: Fig 31 AMD node mix
A81: quarter | B81: 7nm_src | C81: 5nm_src | D81: 3_4nm_src | E81: 2nm_src | F81: unknown_other_src | G81: unplotted_residual_src
A82: 1Q21 | B82: label | C82: not_drawn | D82: not_drawn | E82: not_drawn | F82: label | G82: n/a
A83: 2Q21 | B83: label | C83: not_drawn | D83: not_drawn | E83: not_drawn | F83: label | G83: n/a
A84: 3Q21 | B84: label | C84: not_drawn | D84: not_drawn | E84: not_drawn | F84: label | G84: n/a
A85: 4Q21 | B85: label | C85: not_drawn | D85: not_drawn | E85: not_drawn | F85: label | G85: n/a
A86: 1Q22 | B86: label | C86: measured | D86: not_drawn | E86: not_drawn | F86: label | G86: n/a
A87: 2Q22 | B87: label | C87: measured | D87: not_drawn | E87: not_drawn | F87: label | G87: n/a
A88: 3Q22 | B88: label | C88: label | D88: not_drawn | E88: not_drawn | F88: label | G88: n/a
A89: 4Q22 | B89: label | C89: label | D89: not_drawn | E89: not_drawn | F89: label | G89: n/a
A90: 1Q23 | B90: label | C90: label | D90: not_drawn | E90: not_drawn | F90: label | G90: n/a
A91: 2Q23 | B91: label | C91: label | D91: not_drawn | E91: not_drawn | F91: label | G91: n/a
A92: 3Q23 | B92: label | C92: label | D92: not_drawn | E92: not_drawn | F92: label | G92: n/a
... A103: 2Q26 | B103: label | C103: label | D103: label | E103: label | F103: measured | G103: n/a
