Workbook

Sheet RESUMO
A1: MEMÓRIA — RESUMO CAPSTONE · DRAM ex-HBM · HBM · NAND | G1: gerado 2026-07-09
A2: Cenário ASP 27E/28E → | C2: House | D2: dropdown muda ASPs 27E/28E e o P&L (banda F). Fontes: coluna I + comentários nas células. Números em bn Gb salvo indicação.
A3: linha | B3: unid. | C3: CY23 | D3: CY24 | E3: CY25 | F3: CY26E | G3: CY27E | H3: CY28E | I3: fonte
A4: A · O CICLO EM 6 LINHAS
A5: Receita DRAM (indústria) | B5: $bn | C5: 56.177077 | D5: 92.395742 | E5: 150.894 | F5: 691.595 | G5: 1248.138 | H5: =ROUND(528.5/8*INDEX(_dados!$D$2:$D$4,MATCH($C$2,_dados!$A$2:$A$4,0))*8,0)+258.7 | I5: UBS 03-jul-26 · 28E engine+build
A6: Receita NAND (indústria) | B6: $bn | C6: ··· | D6: ··· | E6: 65.317 | F6: 300.248 | G6: 515.12 | H6: — | I6: UBS 03-jul-26
A7: Suficiência DRAM (S/D−1) | B7: % | C7: -0.0036 | D7: -0.0233 | E7: -0.0235 | F7: -0.0813 | G7: -0.012 | H7: ≈0 eng. | I7: UBS · engine 28E
A8: ASP DRAM blended | B8: $/Gb | C8: 0.25756 | D8: 0.36345 | E8: 0.47978252 | F8: 1.7786382 | G8: =INDEX(_dados!$B$2:$B$4,MATCH($C$2,_dados!$A$2:$A$4,0)) | H8: =INDEX(_dados!$D$2:$D$4,MATCH($C$2,_dados!$A$2:$A$4,0)) | I8: UBS · 27/28E = cenário
A9: Marcação a mercado (spot vs modelo) | B9: DDR5 spot 22.47 (jul) vs contract 12.25 (jun) — meses e bases distintos, spot ~80% acima · RDIMM 64GB 20.47 (jun) · NAND 512Gb 0.384 contract / 0.322 spot — série e unidades = aba de preços da bíblia (TrendForce); direção valida o 26E | I9: bíblia px (TrendForce/spot)
A10: Demanda HBM | B10: bn Gb | C10: 2.2 | D10: 5.6 | E10: 13.4 | F10: 28.4 | G10: 45.6 | H10: 80 | I10: build Capstone 40+ SKUs
A11: WFE total | B11: $bn | C11: 95.76 | D11: 100.34 | E11: 109.62 | F11: 158.4 | G11: 214.9 | H11: 260 | I11: UBS · ledger wfe-tam
A12: B · DEMANDA POR APLICAÇÃO (bn Gb)
A13: DRAM ex-HBM — Servidor DDR | B13: bn Gb | C13: 56.355 | D13: 65.224 | E13: 100.602 | F13: 146.482 | G13: 253.56 | H13: — | I13: UBS Fig.30-39
A14: Mobile | B14: bn Gb | C14: 62.954287 | D14: 74.63466 | E14: 86.263485 | F14: 85.74261 | G14: 92.148047 | H14: — | I14: UBS
A15: PC | B15: bn Gb | C15: 21.91033 | D15: 23.090512 | E15: 27.75809 | F15: 26.489642 | G15: 27.806007 | H15: — | I15: UBS
A16: Graphics + consumer + outros | B16: bn Gb | C16: 79.778585 | D16: 87.121582 | E16: 98.086844 | F16: 108.48115 | G16: 111.01416 | H16: — | I16: UBS (agregado)
A17: DRAM ex-HBM — total | B17: bn Gb | C17: 220.9982 | D17: 250.07075 | E17: 312.71042 | F17: 367.19541 | G17: 484.52821 | H17: 528.5 | I17: UBS · 28E engine
A18: HBM — NVIDIA | B18: bn Gb | C18: 1.65312 | D18: 3.870488 | E18: 9.43032 | F18: 17.18208 | G18: 17.6832 | H18: 30.2464 | I18: build (SKUs)
A19: Google TPU + AMD + AWS + outros | B19: bn Gb | C19: 0.56227828 | D19: 1.7138122 | E19: 3.9760883 | F19: 11.196975 | G19: 27.9392 | H19: 49.7632 | I19: build (agregado)
A20: HBM — total | B20: bn Gb | C20: 2.2 | D20: 5.6 | E20: 13.4 | F20: 28.4 | G20: 45.6 | H20: 80 | I20: build
A21: NAND — Mobile | B21: bn GB | C21: 215.36718 | D21: 245.34244 | E21: 286.5909 | F21: 292.58646 | G21: 316.88347 | H21: — | I21: UBS
A22: eSSD (servidores) | B22: bn GB | C22: 142.33054 | D22: 177.36585 | E22: 257.32064 | F22: 402.12783 | G22: 591.19527 | H22: — | I22: UBS
A23: SSD client + storage + outros | B23: bn GB | C23: 307.23106 | D23: 317.98989 | E23: 345.98534 | F23: 392.45069 | G23: 471.40198 | H23: — | I23: UBS (agregado)
A24: Embedded + cartões + tablet | B24: bn GB | C24: 149.92963 | D24: 175.80578 | E24: 190.72433 | F24: 209.29109 | G24: 215.7509 | H24: — | I24: UBS (agregado)
A25: NAND — total | B25: bn GB | C25: 814.85841 | D25: 916.50396 | E25: 1080.6212 | F25: 1296.4561 | G25: 1595.2316 | H25: — | I25: UBS
A26: B2 · SMARTPHONE — DESTRUIÇÃO DE DEMANDA (células amarelas: edite p/ sensibilizar)
A27: Units smartphone (base UBS — já com corte) | B27: M | C27: 1152 | D27: 1217 | E27: 1249 | F27: 1124 | G27: 1146 | H27: 1160 | I27: UBS via engine Capstone (handset)
A28: DRAM GB/unidade (base UBS — conteúdo desacelera) | B28: GB | C28: 6.8 | D28: 7.7 | E28: 8.1 | F28: 8.9 | G28: 9.4 | H28: 10.2 | I28: UBS
A29: Units contrafactual (sem aperto de preço) | B29: M | C29: 1152 | D29: 1217 | E29: 1249 | F29: 1249 | G29: 1249 | H29: 1249 | I29: EST: flat @ 1.249M pós-25
A30: GB/unidade contrafactual (tendência +10,5%/ano) | B30: GB | C30: 6.8 | D30: 7.7 | E30: 8.1 | F30: 9 | G30: 9.9 | H30: 10.9 | I30: EST: CAGR 22-25 real mantido
A31: Demanda DRAM destruída (contrafactual − base) | B31: bn Gb | C31: =(C29*C30-C27*C28)*8/1000 | D31: =(D29*D30-D27*D28)*8/1000 | E31: =(E29*E30-E27*E28)*8/1000 | F31: =(F29*F30-F27*F28)*8/1000 | G31: =(G29*G30-G27*G28)*8/1000 | H31: =(H29*H30-H27*H28)*8/1000 | I31: fórmula (viva)
A32: Suficiência DRAM sem a destruição (contrafactual) | B32: % | C32: — | D32: — | E32: — | F32: =-0.0813-F31/386.7 | G32: =-0.012-G31/520.1 | H32: — | I32: aprox.: suff − destruição ÷ demanda
A33: leitura | B33: a elasticidade já trabalhou: sem o corte de units+conteúdo o déficit 27E seria ~3× maior (−3,7% vs −1,2%). NAND análogo (238→253 GB/unit) não modelado aqui. | I33: Capstone
A34: C · OFERTA POR EMPRESA (bn Gb produção)
A35: DRAM — Samsung | B35: bn Gb | C35: 96.098088 | D35: 109.60591 | E35: 120.25075 | F35: 146.50516 | G35: 173.74904 | H35: — | I35: UBS
A36: DRAM — SK Hynix | B36: bn Gb | C36: 63.921644 | D36: 74.848909 | E36: 93.014352 | F36: 116.90085 | G36: 137.40942 | H36: — | I36: UBS
A37: DRAM — Micron | B37: bn Gb | C37: 47.452596 | D37: 60.413008 | E37: 73.604791 | F37: 90.902261 | G37: 107.16543 | H37: — | I37: UBS
A38: DRAM — CXMT | B38: bn Gb | C38: 2.0880205 | D38: 11.046041 | E38: 22.161558 | F38: 28.320604 | G38: 38.765855 | H38: — | I38: UBS
A39: Nanya + outros | B39: bn Gb | C39: 3.7808058 | D39: 3.8135743 | E39: 5.4731144 | F39: 6.2055794 | G39: 6.7246891 | H39: — | I39: UBS (agregado)
A40: DRAM — total oferta | B40: bn Gb | C40: 213.34115 | D40: 259.72744 | E40: 314.50457 | F40: 388.83446 | G40: 463.81444 | H40: — | I40: UBS
A41: share 27E | B41: Samsung 37% · SK Hynix 30% · Micron 23% · CXMT 8% | I41: calc
A42: HBM — SK Hynix | B42: bn Gb | C42: — | D42: — | E42: 12.7 | F42: 17.5 | G42: 23 | H42: — | I42: UBS Fig 3 × Fig 8 (03-jul)
A43: HBM — Samsung | B43: bn Gb | C43: — | D43: — | E43: 4.3 | F43: 11 | G43: 24.2 | H43: — | I43: UBS Fig 3 × Fig 8 (03-jul)
A44: HBM — Micron | B44: bn Gb | C44: — | D44: — | E44: 4.5 | F44: 7.7 | G44: 11.8 | H44: — | I44: UBS Fig 3 × Fig 8 (03-jul)
A45: HBM — total oferta (UBS) | B45: bn Gb | C45: — | D45: — | E45: 21.5 | F45: 36.5 | G45: 59.1 | H45: — | I45: UBS Fig 3
A46: share HBM (Fig 8) | B46: Hynix 59% → 48% → 39% · Samsung 20% → 30% → 41% (ultrapassa em 27E) · Micron 21% → 21% → 20% — capacidade k wpm 26E: Samsung 689 UBS / 740 TF · SK 609/610 · MU 317/365 | I46: UBS Fig 8 · TrendForce
A47: NAND — Samsung | B47: bn GB | C47: 254.18423 | D47: 296.67057 | E47: 305.67012 | F47: 347.88733 | G47: 405.81332 | H47: — | I47: UBS
A48: NAND — Kioxia | B48: bn GB | C48: 105.82073 | D48: 130.47588 | E48: 148.05621 | F48: 173.85672 | G48: 211.10658 | H48: — | I48: UBS
A49: NAND — SanDisk | B49: bn GB | C49: 100.91351 | D49: 101.29813 | E49: 119.22048 | F49: 139.43212 | G49: 162.97394 | H49: — | I49: UBS
A50: NAND — SK Hynix | B50: bn GB | C50: 148.50345 | D50: 143.57221 | E50: 160.56267 | F50: 192.381 | G50: 233.6754 | H50: — | I50: UBS
A51: NAND — Micron | B51: bn GB | C51: 90.029576 | D51: 106.60904 | E51: 133.88101 | F51: 161.21828 | G51: 188.92001 | H51: — | I51: UBS
A52: NAND — YMTC | B52: bn GB | C52: 41.826803 | D52: 75.74132 | E52: 119.13198 | F52: 148.33805 | G52: 197.47627 | H52: — | I52: UBS
A53: NAND — total oferta | B53: bn GB | C53: 748.3583 | D53: 862.08715 | E53: 994.88246 | F53: 1172.1135 | G53: 1409.6055 | H53: — | I53: UBS
A54: D · SUFICIÊNCIA (S/D − 1) — a síntese
A55: DRAM blended | B55: % | C55: -0.0036 | D55: -0.0233 | E55: -0.0235 | F55: -0.0813 | G55: -0.012 | H55: ≈0 eng. | I55: UBS · engine
A56: DDR ex-HBM | B56: % | C56: — | D56: — | E56: -0.0433 | F56: -0.0156 | G56: -0.1461 | H56: -0.0032 | I56: engine house
A57: DRAM blended — HOUSE (units Capstone, inv-adj) | B57: % | C57: — | D57: — | E57: -0.0131 | F57: -0.0881 | G57: 0.0262 | H57: — | I57: bíblia Memory S&D (modelo)
A58: NAND (S/D−1) | B58: % | C58: — | D58: — | E58: -0.0101 | F58: -0.0935 | G58: -0.0066 | H58: — | I58: UBS Fig.41
A59: HBM | B59: sold out CY26 incl. HBM4 (Micron Q1 FY26) · 27E oferta revisada 60→50 bn Gb-equiv por alocação, não demanda · oferta UBS por vendor na banda C | I59: assumptions ledger
A60: E · CAPACIDADE, CANIBALIZAÇÃO HBM E CAPEX
A61: Wafers DDR | B61: k wpm | C61: — | D61: — | E61: 1535 | F61: 1498 | G61: 1486 | H61: 1785.5 | I61: engine (Fig.9 UBS)
A62: Wafers HBM | B62: k wpm | C62: — | D62: — | E62: 390 | F62: 500 | G62: 690 | H62: 694.5 | I62: SemiAnalysis · engine
A63: Penalidade de wafer HBM (bits DDR ÷ bits HBM por wafer) | B63: × | C63: — | D63: — | E63: 3.5 | F63: 3.2 | G63: 3.2 | H63: 3.1 | I63: engine
A64: Bits líquidos perdidos p/ HBM (% da demanda) | B64: % | C64: — | D64: — | E64: 0.1646 | F64: 0.2042 | G64: 0.2415 | H64: 0.2323 | I64: engine
A65: Capex memória | B65: $bn | C65: — | D65: — | E65: 75 | F65: 85 | G65: 120 | H65: 140 | I65: UBS · bridge
A66: Conta do capex (26E→27E) | B66: greenfield/net-add 17→32 · conversão HBM+packaging 20→30 · node/manutenção 48→58 $bn | I66: bíblia (ponte)
A67: F · P&L 27E POR EMPRESA → P/E (muda com o cenário ASP)
A68: vendor → | C68: Micron | D68: SK Hynix | E68: Samsung* | F68: Kioxia | G68: SanDisk | I68: BBG 02-jul · bíblia SxD
A69: Receita memória 27E (bits × ASP cenário) | B69: $bn | C69: =(_dados!B7*INDEX(_dados!$B$2:$B$4,MATCH($C$2,_dados!$A$2:$A$4,0))+_dados!C7*INDEX(_dados!$C$2:$C$4,MATCH($C$2,_dados!$A$2:$A$4,0)))/1000 | D69: =(_dados!B8*INDEX(_dados!$B$2:$B$4,MATCH($C$2,_dados!$A$2:$A$4,0))+_dados!C8*INDEX(_dados!$C$2:$C$4,MATCH($C$2,_dados!$A$2:$A$4,0)))/1000 | E69: =(_dados!B9*INDEX(_dados!$B$2:$B$4,MATCH($C$2,_dados!$A$2:$A$4,0))+_dados!C9*INDEX(_dados!$C$2:$C$4,MATCH($C$2,_dados!$A$2:$A$4,0)))/1000 | F69: =(_dados!B10*INDEX(_dados!$B$2:$B$4,MATCH($C$2,_dados!$A$2:$A$4,0))+_dados!C10*INDEX(_dados!$C$2:$C$4,MATCH($C$2,_dados!$A$2:$A$4,0)))/1000 | G69: =(_dados!B11*INDEX(_dados!$B$2:$B$4,MATCH($C$2,_dados!$A$2:$A$4,0))+_dados!C11*INDEX(_dados!$C$2:$C$4,MATCH($C$2,_dados!$A$2:$A$4,0)))/1000 | I69: fórmula = dashboard P&L
A70: EPS 27E house (modelo) | B70: local | C70: =((_dados!B7*INDEX(_dados!$B$2:$B$4,MATCH($C$2,_dados!$A$2:$A$4,0))+_dados!C7*INDEX(_dados!$C$2:$C$4,MATCH($C$2,_dados!$A$2:$A$4,0)))*_dados!D7-_dados!E7)*(1-_dados!F7)*_dados!G7/_dados!H7 | D70: =((_dados!B8*INDEX(_dados!$B$2:$B$4,MATCH($C$2,_dados!$A$2:$A$4,0))+_dados!C8*INDEX(_dados!$C$2:$C$4,MATCH($C$2,_dados!$A$2:$A$4,0)))*_dados!D8-_dados!E8)*(1-_dados!F8)*_dados!G8/_dados!H8 | E70: =((_dados!B9*INDEX(_dados!$B$2:$B$4,MATCH($C$2,_dados!$A$2:$A$4,0))+_dados!C9*INDEX(_dados!$C$2:$C$4,MATCH($C$2,_dados!$A$2:$A$4,0)))*_dados!D9-_dados!E9)*(1-_dados!F9)*_dados!G9/_dados!H9 | F70: =((_dados!B10*INDEX(_dados!$B$2:$B$4,MATCH($C$2,_dados!$A$2:$A$4,0))+_dados!C10*INDEX(_dados!$C$2:$C$4,MATCH($C$2,_dados!$A$2:$A$4,0)))*_dados!D10-_dados!E10)*(1-_dados!F10)*_dados!G10/_dados!H10 | G70: =((_dados!B11*INDEX(_dados!$B$2:$B$4,MATCH($C$2,_dados!$A$2:$A$4,0))+_dados!C11*INDEX(_dados!$C$2:$C$4,MATCH($C$2,_dados!$A$2:$A$4,0)))*_dados!D11-_dados!E11)*(1-_dados!F11)*_dados!G11/_dados!H11 | I70: gm×rev−opex, ×(1−tax)×fx÷ações
A71: P/E house @ px atual | B71: × | C71: =_dados!I7/C70 | D71: =_dados!I8/D70 | E71: =_dados!I9/E70 | F71: =_dados!I10/F70 | G71: =_dados!I11/G70 | I71: px BBG ÷ EPS modelo
A72: P/E consenso 27E (BBG) | B72: × | C72: =_dados!I7/_dados!J7 | D72: =_dados!I8/_dados!J8 | E72: =_dados!I9/_dados!J9 | F72: =_dados!I10/_dados!J10 | G72: =_dados!I11/_dados!J11
A73: Δ EPS house vs consenso (o edge) | B73: % | C73: =C70/_dados!J7-1 | D73: =D70/_dados!J8-1 | E73: =E70/_dados!J9-1 | F73: =F70/_dados!J10-1 | G73: =G70/_dados!J11-1 | I73: modelo ÷ BBG − 1
A74: *Samsung | B74: consenso = empresa inteira (foundry/mobile/display) — P/E consenso não é 1:1 com o P&L memória-only. EPS local: MU/SNDK $, SK/Samsung ₩, Kioxia ¥.
A75: G · BUILDS — CROSS-CHECKS BOTTOM-UP
A76: CPUs de servidor | B76: M | C76: 22.6 | D76: 24 | E76: 32.2 | F76: 40.6 | G76: 52.8 | H76: 61.2 | I76: Bernstein/Mercury (recal.)
A77: DRAM convencional por CPU | B77: GB | C77: 314 | D77: 340 | E77: 393 | F77: 475 | G77: 590 | H77: 683 | I77: modelo (conv ÷ CPUs)
A78: DIMMs por CPU | B78: un. | C78: 7.9 | D78: 8.9 | E78: 9 | F78: 9.5 | G78: 10.3 | H78: 11.7 | I78: Bernstein (canais×slots×ocup.)
A79: GB por DIMM implícito | B79: GB | C79: 39 | D79: 38 | E79: 46 | F79: 54 | G79: 66 | H79: 65 | I79: modelo ÷ DIMMs Bernstein
A80: HBM $/GB blended (build) | B80: $/GB | C80: 10.5 | D80: 14.6 | E80: 16.7 | F80: 17.9 | G80: 21.3 | H80: 25.9 | I80: build (rev ÷ bits × 8)
A81: HBM $/GB por geração | B81: preço build: HBM3E $17 · HBM4 $26 · HBM4E $29 — mix bits: 26E 3E 84% / 4 13% → 27E 3E 51% / 4 46% → 28E 3E 14% / 4 45% / 4E 41% | I81: build (por gen) · debate Redburn vs JPM
A82: Smartphone GB/unidade | B82: GB | C82: — | D82: — | E82: 8.1 | F82: 8.9 | G82: 9.4 | H82: — | I82: UBS Fig. (BOM 12→40%)
A83: H · DEBATES VIVOS, CATALISADORES E CONVENÇÕES
A84: Virada 2028 | B84: house: déficit fecha ≈0 (wafers HBM flatten ~695k, adds vão p/ DDR) vs Bernstein +5% surplus — os 109,6 bn Gb de HBM deles em 28E exigiriam ~1,1M wafers e matariam o próprio surplus | I84: engine · Bernstein SxD
A85: Alocação 26 | B85: general-server DDR ultrapassou HBM como prioridade #1 de alocação (Redburn/TrendForce) — e ainda assim HBM sobe: $17-18 → $30-32/GB 27E (Redburn) vs blended +30% (JPM/Micron) | I85: assumptions ledger
A86: China | B86: CXMT: 4% da oferta DRAM 25 → 12% 27E (UBS) + IPO a caminho; YMTC 41→? bn GB NAND — o wildcard de oferta pós-28 | I86: UBS · ledger
A87: Conteúdo | B87: MRDIMM 12% do mix 28E (Bernstein) + 12/16-canais → DIMMs/CPU 9→11,7 — upside de conteúdo independente de units | I87: Bernstein
A88: Catalisadores | B88: SK Hynix results 10-jul-26 (amanhã) · Micron FQ4 set-26 · TrendForce/UBS monthly (Fig.9 wafer adds) · Samsung prelim 2Q | I88: catalysts.md
A89: CONVENÇÕES | B89: Gb vs GB: ÷8 · wafer HBM ≈ 1/3 dos bits de um wafer DDR (penalidade 3,1-3,5×) · servidores UBS (20,1M em 25) ≠ Gartner (12,5M) — bases distintas · GW facility ≠ GW IT-load (fora deste arquivo) | I89: regras da wiki

Sheet _dados
A1: cenário | B1: DDR 27E $/Gb | C1: NAND 27E $/GB | D1: DDR 28E $/Gb | E1: NAND 28E $/GB
A2: House | B2: 2.375 | C2: 0.33 | D2: 1.625 | E2: 0.28
A3: UBS base | B3: 2.67 | C3: 0.365 | D3: 2.25 | E3: 0.37
A4: Soft landing | B4: 1.6875 | C4: 0.28 | D4: 1.25 | E4: 0.28
A6: vendor | B6: dram MGb | C6: nand MGB | D6: gm | E6: opex $M | F6: tax | G6: fx | H6: shares M | I6: px | J6: eps27 cons
A7: MU | B7: 107165.43 | C7: 188920.01 | D7: 0.86 | E7: 3500 | F7: 0.15 | G7: 1 | H7: 1120 | I7: 878.84 | J7: 187.56
A8: SKHYNIX | B8: 137409.42 | C8: 233675.4 | D8: 0.84 | E8: 4000 | F8: 0.15 | G8: 1380 | H8: 728 | I8: 1272000 | J8: 488486.58
A9: SAMSUNG | B9: 173749.04 | C9: 405813.32 | D9: 0.84 | E9: 3000 | F9: 0.15 | G9: 1380 | H9: 5969 | I9: 215500 | J9: 74718.08
A10: KIOXIA | B10: 0 | C10: 211106.58 | D10: 0.84 | E10: 3000 | F10: 0.15 | G10: 150 | H10: 540 | I10: 13375 | J10: 4797.53
A11: SNDK | B11: 0 | C11: 162973.94 | D11: 0.84 | E11: 3000 | F11: 0.15 | G11: 1 | H11: 145 | I11: 1299.3 | J11: 241.9
